Workbook
Name answers_needed: Control!$J$15:$J$30
Name Status: Control!$H$24:$H$44
Name waiting_words: Control!$K$24:$K$44
Name worse_at: '_live'!$C$5
Name better_at: '_live'!$C$6
Name confidence: '_live'!$C$7
Name significance_bar: '_live'!$C$8
Name judged_band: '_live'!$C$9
Name materiality_kind: '_live'!$C$10
Name materiality_share: '_live'!$C$11
Name materiality_gco: '_live'!$C$12
Name profit_kind: '_live'!$C$13
Name profit_line: '_live'!$C$14
Name in_use_words: '_live'!$C$17
Name line_keys: '_live'!$G$20:$G$30
Name line_values: '_live'!$C$20:$C$30
Name book_gco: '_live'!$C$15
Name pk_kind: '_pockets'!$A$4:$A$1048576
Name pk_measure: '_pockets'!$E$4:$E$1048576
Name pk_dollars: '_pockets'!$Z$4:$Z$1048576
Name pk_flag: '_pockets'!$Y$4:$Y$1048576
Name pk_material: '_pockets'!$AA$4:$AA$1048576
Name pk_worse: '_pockets'!$AI$4:$AI$1048576
Name pk_mat: '_pockets'!$AJ$4:$AJ$1048576
Name pk_border: '_pockets'!$AM$4:$AM$1048576
Name pk_wborder: '_pockets'!$AN$4:$AN$1048576

Sheet Start here
B1: PocketBook | C1: Scouting book.csv · 12,000 loans · 19 columns · last Run 2026-09-30 04:36
B3: How this tab works
B4: Where things stand | C4: What is left before Run, counted live from Control and Columns as you fill them in.
B5: What the last Run found | C5: Each group of the tested column on the holdout, against the reference group. Significant? follows the confidence on Control; the rest is as of the last Run.
B6: The tabs | C6: Red tabs you fill in; black tabs hold results; grey tabs are the record.
B8: WHERE THINGS STAND
B9: Answers needed before Run | D9: Odd values to answer | F9: Changes waiting for a Run
B10: =IFERROR(SUM(answers_needed),0)+IF(Control!$C$33="",1,0)+IF(Columns!$C$3="Yes",0,1) | D10: =COUNTIFS(Columns!$S$13:$S$32,"?*",Columns!$H$13:$H$32,"") | F10: =IFERROR(COUNTIF(Status,"↻ Waiting for a Run"),0)
B11: Control and Columns | D11: Columns · Treat as | F11: Control · Status
B13: =IFERROR(IF(COUNTIF(Status,"↻ Waiting for a Run")=0,"","↻ "&COUNTIF(Status,"↻ Waiting for a Run")&IF(COUNTIF(Status,"↻ Waiting for a Run")=1," change is"," changes are")&" waiting for a Run. "&LEFT(INDEX(waiting_words,1)&INDEX(waiting_words,2)&INDEX(waiting_words,3)&INDEX(waiting_words,4)&INDEX(waiting_words,5)&INDEX(waiting_words,6)&INDEX(waiting_words,7)&INDEX(waiting_words,8)&INDEX(waiting_words,9)&INDEX(waiting_words,10)&INDEX(waiting_words,11)&INDEX(waiting_words,12)&INDEX(waiting_words,13)&INDEX(waiting_words,14)&INDEX(waiting_words,15)&INDEX(waiting_words,16)&INDEX(waiting_words,17)&INDEX(waiting_words,18)&INDEX(waiting_words,19)&INDEX(waiting_words,20)&INDEX(waiting_words,21),LEN(INDEX(waiting_words,1)&INDEX(waiting_words,2)&INDEX(waiting_words,3)&INDEX(waiting_words,4)&INDEX(waiting_words,5)&INDEX(waiting_words,6)&INDEX(waiting_words,7)&INDEX(waiting_words,8)&INDEX(waiting_words,9)&INDEX(waiting_words,10)&INDEX(waiting_words,11)&INDEX(waiting_words,12)&INDEX(waiting_words,13)&INDEX(waiting_words,14)&INDEX(waiting_words,15)&INDEX(waiting_words,16)&INDEX(waiting_words,17)&INDEX(waiting_words,18)&INDEX(waiting_words,19)&INDEX(waiting_words,20)&INDEX(waiting_words,21))-2)&". The result tabs still show the last Run. Save, close, and press Run in the launcher."),"")
B15: WHAT THE LAST RUN FOUND
B16: Groups worse than their reference, on the holdout | D16: Candidates with a group worse | F16: Loans tested | H16: Follows the pre-spec
B17: =IFERROR(COUNTIFS('_found'!$A:$A,"group",'_found'!$F:$F,">1",'_found'!$G:$G,"<"&significance_bar)&" of 3","") | D17: =IFERROR(((COUNTIFS('_found'!$A:$A,"group",'_found'!$J:$J,"UTIL",'_found'!$F:$F,">1",'_found'!$G:$G,"<"&significance_bar)>0)+(COUNTIFS('_found'!$A:$A,"group",'_found'!$J:$J,"income_to_sales",'_found'!$F:$F,">1",'_found'!$G:$G,"<"&significance_bar)>0))&" of 2","") | F17: 8,394 found · 3,605 held back | H17: Written now: by this Run's scouting
B19: Candidate: group | C19: Loans | D19: Bad rate | E19: × its reference's odds, FICO and CHANNEL held fixed | F19: p-value | G19: Significant? | H19: Share of bad loans
B20: ='_found'!$J$9&": "&'_found'!$B$9&" (reference)" | C20: ='_found'!$C$9 | D20: =IF('_found'!$E$9="","",'_found'!$E$9) | E20: =IF('_found'!$F$9="","none",'_found'!$F$9) | F20: =IF('_found'!$G$9="","",'_found'!$G$9) | H20: ='_found'!$H$9
B21: ='_found'!$J$10&": "&'_found'!$B$10 | C21: ='_found'!$C$10 | D21: =IF('_found'!$E$10="","",'_found'!$E$10) | E21: =IF('_found'!$F$10="","none",'_found'!$F$10) | F21: =IF('_found'!$G$10="","",'_found'!$G$10) | G21: =IF(AND(ISNUMBER('_found'!$G$10),'_found'!$G$10<significance_bar),IF('_found'!$F$10>1,"Yes, worse","Yes, better"),"No") | H21: ='_found'!$H$10
B22: ='_found'!$J$11&": "&'_found'!$B$11 | C22: ='_found'!$C$11 | D22: =IF('_found'!$E$11="","",'_found'!$E$11) | E22: =IF('_found'!$F$11="","none",'_found'!$F$11) | F22: =IF('_found'!$G$11="","",'_found'!$G$11) | G22: =IF(AND(ISNUMBER('_found'!$G$11),'_found'!$G$11<significance_bar),IF('_found'!$F$11>1,"Yes, worse","Yes, better"),"No") | H22: ='_found'!$H$11
B23: ='_found'!$J$12&": "&'_found'!$B$12&" (reference)" | C23: ='_found'!$C$12 | D23: =IF('_found'!$E$12="","",'_found'!$E$12) | E23: =IF('_found'!$F$12="","none",'_found'!$F$12) | F23: =IF('_found'!$G$12="","",'_found'!$G$12) | H23: ='_found'!$H$12
B24: ='_found'!$J$13&": "&'_found'!$B$13 | C24: ='_found'!$C$13 | D24: =IF('_found'!$E$13="","",'_found'!$E$13) | E24: =IF('_found'!$F$13="","none",'_found'!$F$13) | F24: =IF('_found'!$G$13="","",'_found'!$G$13) | G24: =IF(AND(ISNUMBER('_found'!$G$13),'_found'!$G$13<significance_bar),IF('_found'!$F$13>1,"Yes, worse","Yes, better"),"No") | H24: ='_found'!$H$13
B25: Found beside confirmed, with and without the columns held fixed, and how it's worked out: the New variables tab.
B28: THE TABS
B29: You answer | D29: Results | G29: Record
B30: Control: the professional calls | D30: Scouting: the candidates ranked, on development loans | G30: Record: what ran, the tie-outs, every Run
B31: Columns: meanings, odd values, memory | D31: New variables: the shortlist, confirmed
B32: Look: each number column's shape

Sheet Control
B1: Control | C1: The professional calls. The top block changes results now; the second waits for a Run.
B3: How this tab works
B4: Changes now | C4: The result tabs read these answers with formulas. Change one and every reading, dollar figure, colour and verdict follows at once. The order of rows stays as the last Run left it.
B5: Needs a Run | C5: These decide which pockets exist and which test each one gets, so they take effect when you press Run again. Status says when an answer differs from what the last Run used.
B6: Your answer | C6: Pick from the list, or type a number under Or your own: a number there wins. A shaded answer still needs one. Comes to shows what the answer amounts to now.
B7: Worked out | C7: Worse at has a value worked out from this extract, from the groups being confirmed, shown beside the setting. It is never picked for you.
B8: Chosen in the launcher | C8: What you're running and how the pockets are cut. Change them in the launcher's Choose tests, then press Next. They are shown here so a reviewer sees them.
B9: Materiality levels | C9: Material? on New variables compares each group's excess with the level you pick, live. The panel of levels counts pockets, so it is hidden on this run, which builds none.
B11: Changes now | C11: Needs a Run | F11: Still needs an answer | G11: legend
B13: Changes now · the result tabs follow as you change these | G13: block|now | M13: What each materiality level keeps
B14: Setting | C14: Your answer | D14: Or your own | E14: Comes to | F14: Last Run used | I14: Worked out from the loans | M14: Level | N14: Dollars | O14: Pockets | P14: Of excess
B15: How much worse than its comparison a pocket must be | C15: 1.25 times | E15: =IF(NOT(TRUE),"",IF(AND($D$15<>"",$D$15<>"n/a"),$D$15,IF($C$15="","",IF(ISNA(IFERROR(MATCH($G$15&"|"&$C$15,_options!$A:$A,0),MATCH($G$15&"|"&IFERROR(VALUE($C$15),$C$15),_options!$H:$H,0))),"not an option",IFERROR(TEXT(worse_at,"0.00")&"×",IF(ISNUMBER(IFERROR(INDEX(_options!$D:$D,IFERROR(MATCH($G$15&"|"&$C$15,_options!$A:$A,0),MATCH($G$15&"|"&IFERROR(VALUE($C$15),$C$15),_options!$H:$H,0))),"")),TEXT(IFERROR(INDEX(_options!$D:$D,IFERROR(MATCH($G$15&"|"&$C$15,_options!$A:$A,0),MATCH($G$15&"|"&IFERROR(VALUE($C$15),$C$15),_options!$H:$H,0))),""),"0.00")&"×",IF(ISNUMBER($K$15),TEXT($K$15,"0.00")&"×",""))))))) | F15: 1.25 times | G15: worse_at | I15: suggested: 1.43x, from this extract at the last Run | J15: =IF(AND(TRUE,$C15="",OR($D15="",$D15="n/a")),1,0) | K15: 1.43 | M15: =IFERROR("0.5%"&IF(AND(materiality_kind="share",ABS(materiality_share-0.005)<1E-9)," ◂",""),"0.5%") | N15: =IFERROR((0.005*book_gco),"") | O15: =IFERROR(COUNTIFS(pk_kind,"grids",pk_measure,"gco_rate",pk_dollars,">="&(0.005*book_gco),pk_dollars,">0"),"") | P15: =IFERROR(IF(SUMIFS(pk_dollars,pk_kind,"grids",pk_measure,"gco_rate",pk_dollars,">0")=0,0,SUMIFS(pk_dollars,pk_kind,"grids",pk_measure,"gco_rate",pk_dollars,">="&(0.005*book_gco),pk_dollars,">0")/SUMIFS(pk_dollars,pk_kind,"grids",pk_measure,"gco_rate",pk_dollars,">0")),"")
B16: How much better than its comparison a pocket must be | C16: 0.8 times | E16: =IF(NOT($C$33="Where the book bleeds"),"",IF(AND($D$16<>"",$D$16<>"n/a"),$D$16,IF($C$16="","",IF(ISNA(IFERROR(MATCH($G$16&"|"&$C$16,_options!$A:$A,0),MATCH($G$16&"|"&IFERROR(VALUE($C$16),$C$16),_options!$H:$H,0))),"not an option",IFERROR(TEXT(better_at,"0.00")&"×",IF(ISNUMBER(IFERROR(INDEX(_options!$D:$D,IFERROR(MATCH($G$16&"|"&$C$16,_options!$A:$A,0),MATCH($G$16&"|"&IFERROR(VALUE($C$16),$C$16),_options!$H:$H,0))),"")),TEXT(IFERROR(INDEX(_options!$D:$D,IFERROR(MATCH($G$16&"|"&$C$16,_options!$A:$A,0),MATCH($G$16&"|"&IFERROR(VALUE($C$16),$C$16),_options!$H:$H,0))),""),"0.00")&"×",IF(ISNUMBER($K$16),TEXT($K$16,"0.00")&"×",""))))))) | G16: better_at | J16: =IF(AND($C$33="Where the book bleeds",$C16="",OR($D16="",$D16="n/a")),1,0) | M16: =IFERROR("1%"&IF(AND(materiality_kind="share",ABS(materiality_share-0.01)<1E-9)," ◂",""),"1%") | N16: =IFERROR((0.01*book_gco),"") | O16: =IFERROR(COUNTIFS(pk_kind,"grids",pk_measure,"gco_rate",pk_dollars,">="&(0.01*book_gco),pk_dollars,">0"),"") | P16: =IFERROR(IF(SUMIFS(pk_dollars,pk_kind,"grids",pk_measure,"gco_rate",pk_dollars,">0")=0,0,SUMIFS(pk_dollars,pk_kind,"grids",pk_measure,"gco_rate",pk_dollars,">="&(0.01*book_gco),pk_dollars,">0")/SUMIFS(pk_dollars,pk_kind,"grids",pk_measure,"gco_rate",pk_dollars,">0")),"")
B17: How far profit must move before it counts as more or less | C17: Each pocket's own test (suggested) | E17: =IF(NOT($C$33="Where the book bleeds"),"",IF(AND($D$17<>"",$D$17<>"n/a"),$D$17,IF($C$17="","",IF(ISNA(IFERROR(MATCH($G$17&"|"&$C$17,_options!$A:$A,0),MATCH($G$17&"|"&IFERROR(VALUE($C$17),$C$17),_options!$H:$H,0))),"not an option","")))) | G17: revenue_line | J17: =IF(AND($C$33="Where the book bleeds",$C17="",OR($D17="",$D17="n/a")),1,0) | M17: =IFERROR("2%"&IF(AND(materiality_kind="share",ABS(materiality_share-0.02)<1E-9)," ◂",""),"2%") | N17: =IFERROR((0.02*book_gco),"") | O17: =IFERROR(COUNTIFS(pk_kind,"grids",pk_measure,"gco_rate",pk_dollars,">="&(0.02*book_gco),pk_dollars,">0"),"") | P17: =IFERROR(IF(SUMIFS(pk_dollars,pk_kind,"grids",pk_measure,"gco_rate",pk_dollars,">0")=0,0,SUMIFS(pk_dollars,pk_kind,"grids",pk_measure,"gco_rate",pk_dollars,">="&(0.02*book_gco),pk_dollars,">0")/SUMIFS(pk_dollars,pk_kind,"grids",pk_measure,"gco_rate",pk_dollars,">0")),"")
B18: How sure a difference must be before it counts | C18: 95% | E18: =IF(NOT(TRUE),"",IF(AND($D$18<>"",$D$18<>"n/a"),$D$18,IF($C$18="","",IF(ISNA(IFERROR(MATCH($G$18&"|"&$C$18,_options!$A:$A,0),MATCH($G$18&"|"&IFERROR(VALUE($C$18),$C$18),_options!$H:$H,0))),"not an option","")))) | F18: 95% sure | G18: confidence | J18: =IF(AND(TRUE,$C18="",OR($D18="",$D18="n/a")),1,0) | M18: =IFERROR("5%"&IF(AND(materiality_kind="share",ABS(materiality_share-0.05)<1E-9)," ◂",""),"5%") | N18: =IFERROR((0.05*book_gco),"") | O18: =IFERROR(COUNTIFS(pk_kind,"grids",pk_measure,"gco_rate",pk_dollars,">="&(0.05*book_gco),pk_dollars,">0"),"") | P18: =IFERROR(IF(SUMIFS(pk_dollars,pk_kind,"grids",pk_measure,"gco_rate",pk_dollars,">0")=0,0,SUMIFS(pk_dollars,pk_kind,"grids",pk_measure,"gco_rate",pk_dollars,">="&(0.05*book_gco),pk_dollars,">0")/SUMIFS(pk_dollars,pk_kind,"grids",pk_measure,"gco_rate",pk_dollars,">0")),"")
B19: Smallest excess loss worth reporting | C19: 1% of the book's total losses | E19: =IF(NOT(TRUE),"",IF(AND($D$19<>"",$D$19<>"n/a"),$D$19,IF($C$19="","",IF(ISNA(IFERROR(MATCH($G$19&"|"&$C$19,_options!$A:$A,0),MATCH($G$19&"|"&IFERROR(VALUE($C$19),$C$19),_options!$H:$H,0))),"not an option",IFERROR(IF(materiality_kind="none","No floor",IF(materiality_gco>0,"$"&TEXT(materiality_gco,"#,##0"),IFERROR(INDEX(_options!$G:$G,IFERROR(MATCH($G$19&"|"&$C$19,_options!$A:$A,0),MATCH($G$19&"|"&IFERROR(VALUE($C$19),$C$19),_options!$H:$H,0))),"not an option"))),""))))) | F19: 1% of the book's total losses | G19: materiality | J19: =IF(AND(TRUE,$C19="",OR($D19="",$D19="n/a")),1,0) | M19: =IFERROR("10%"&IF(AND(materiality_kind="share",ABS(materiality_share-0.1)<1E-9)," ◂",""),"10%") | N19: =IFERROR((0.1*book_gco),"") | O19: =IFERROR(COUNTIFS(pk_kind,"grids",pk_measure,"gco_rate",pk_dollars,">="&(0.1*book_gco),pk_dollars,">0"),"") | P19: =IFERROR(IF(SUMIFS(pk_dollars,pk_kind,"grids",pk_measure,"gco_rate",pk_dollars,">0")=0,0,SUMIFS(pk_dollars,pk_kind,"grids",pk_measure,"gco_rate",pk_dollars,">="&(0.1*book_gco),pk_dollars,">0")/SUMIFS(pk_dollars,pk_kind,"grids",pk_measure,"gco_rate",pk_dollars,">0")),"")
B20: What a pocket is judged against | C20: The rest of its band | D20: n/a | E20: =IF(NOT($C$33="Where the book bleeds"),"",IF(AND($D$20<>"",$D$20<>"n/a"),$D$20,IF($C$20="","",IF(ISNA(IFERROR(MATCH($G$20&"|"&$C$20,_options!$A:$A,0),MATCH($G$20&"|"&IFERROR(VALUE($C$20),$C$20),_options!$H:$H,0))),"not an option","")))) | G20: compare_to | J20: =IF(AND($C$33="Where the book bleeds",$C20="",OR($D20="",$D20="n/a")),1,0) | M20: Charge-offs, every grid, against what each pocket is judged against.
M21: A profit shortfall is held to the same dollar line.
B22: ↻ Needs a Run · takes effect when you press Run again | G22: block|run
B23: Setting | C23: Your answer ↻ | D23: Or your own | F23: Last Run used | H23: Status | I23: Worked out from the loans
B24: Fewest loans in a pocket for the usual test (smaller ones get the exact test) | C24: 30 | G24: min_loans | H24: =IF(OR(NOT($C$33="Where the book bleeds"),AND($C$33="Where the book bleeds",$C24="",OR($D24="",$D24="n/a"))),"",IFERROR(IF(IF(AND($D$24<>"",$D$24<>"n/a"),$D$24,$C$24)&""=INDEX(_used!$B:$B,MATCH($G$24,_used!$A:$A,0))&"","Same as last Run","↻ Waiting for a Run"),"")) | J24: =IF(AND($C$33="Where the book bleeds",$C24="",OR($D24="",$D24="n/a")),1,0) | K24: =IF($H24="↻ Waiting for a Run",$B24&": "&INDEX(_used!$C:$C,MATCH($G$24,_used!$A:$A,0))&" → "&IF(AND($D$24<>"",$D$24<>"n/a"),$D$24,$C$24)&" (Control C24); ","")
B25: Fewest loans with a loss before a loss rate is tested | C25: 10 | G25: min_events | H25: =IF(OR(NOT($C$33="Where the book bleeds"),AND($C$33="Where the book bleeds",$C25="",OR($D25="",$D25="n/a"))),"",IFERROR(IF(IF(AND($D$25<>"",$D$25<>"n/a"),$D$25,$C$25)&""=INDEX(_used!$B:$B,MATCH($G$25,_used!$A:$A,0))&"","Same as last Run","↻ Waiting for a Run"),"")) | J25: =IF(AND($C$33="Where the book bleeds",$C25="",OR($D25="",$D25="n/a")),1,0) | K25: =IF($H25="↻ Waiting for a Run",$B25&": "&INDEX(_used!$C:$C,MATCH($G$25,_used!$A:$A,0))&" → "&IF(AND($D$25<>"",$D$25<>"n/a"),$D$25,$C$25)&" (Control C25); ","")
B26: How many bands a number column is cut into | C26: 5 bands (recommended) | F26: 5 bands | G26: band_count | H26: =IF(OR(NOT(TRUE),AND(TRUE,$C26="",OR($D26="",$D26="n/a"))),"",IFERROR(IF(IF(AND($D$26<>"",$D$26<>"n/a"),$D$26,$C$26)&""=INDEX(_used!$B:$B,MATCH($G$26,_used!$A:$A,0))&"","Same as last Run","↻ Waiting for a Run"),"")) | J26: =IF(AND(TRUE,$C26="",OR($D26="",$D26="n/a")),1,0) | K26: =IF($H26="↻ Waiting for a Run",$B26&": "&INDEX(_used!$C:$C,MATCH($G$26,_used!$A:$A,0))&" → "&IF(AND($D$26<>"",$D$26<>"n/a"),$D$26,$C$26)&" (Control C26); ","")
B27: Where the band edges fall | C27: Each band holds about the same number of loans (recommended) | D27: n/a | F27: Each band holds about the same number of loans | G27: band_cut | H27: =IF(OR(NOT(TRUE),AND(TRUE,$C27="",OR($D27="",$D27="n/a"))),"",IFERROR(IF(IF(AND($D$27<>"",$D$27<>"n/a"),$D$27,$C$27)&""=INDEX(_used!$B:$B,MATCH($G$27,_used!$A:$A,0))&"","Same as last Run","↻ Waiting for a Run"),"")) | J27: =IF(AND(TRUE,$C27="",OR($D27="",$D27="n/a")),1,0) | K27: =IF($H27="↻ Waiting for a Run",$B27&": "&INDEX(_used!$C:$C,MATCH($G$27,_used!$A:$A,0))&" → "&IF(AND($D$27<>"",$D$27<>"n/a"),$D$27,$C$27)&" (Control C27); ","")
B28: How often a real gap should be caught | C28: 80% of the time (recommended) | G28: power | H28: =IF(OR(NOT($C$33="Where the book bleeds"),AND($C$33="Where the book bleeds",$C28="",OR($D28="",$D28="n/a"))),"",IFERROR(IF(IF(AND($D$28<>"",$D$28<>"n/a"),$D$28,$C$28)&""=INDEX(_used!$B:$B,MATCH($G$28,_used!$A:$A,0))&"","Same as last Run","↻ Waiting for a Run"),"")) | J28: =IF(AND($C$33="Where the book bleeds",$C28="",OR($D28="",$D28="n/a")),1,0) | K28: =IF($H28="↻ Waiting for a Run",$B28&": "&INDEX(_used!$C:$C,MATCH($G$28,_used!$A:$A,0))&" → "&IF(AND($D$28<>"",$D$28<>"n/a"),$D$28,$C$28)&" (Control C28); ","")
B29: Allowing for testing many pockets at once | C29: Hold down the share of false finds (Benjamini-Hochberg) (recommended) | D29: n/a | F29: Hold down the share of false finds (Benjamini-Hochberg) | G29: many_tests | H29: =IF(OR(NOT(TRUE),AND(TRUE,$C29="",OR($D29="",$D29="n/a"))),"",IFERROR(IF(IF(AND($D$29<>"",$D$29<>"n/a"),$D$29,$C$29)&""=INDEX(_used!$B:$B,MATCH($G$29,_used!$A:$A,0))&"","Same as last Run","↻ Waiting for a Run"),"")) | J29: =IF(AND(TRUE,$C29="",OR($D29="",$D29="n/a")),1,0) | K29: =IF($H29="↻ Waiting for a Run",$B29&": "&INDEX(_used!$C:$C,MATCH($G$29,_used!$A:$A,0))&" → "&IF(AND($D$29<>"",$D$29<>"n/a"),$D$29,$C$29)&" (Control C29); ","")
B30: Loans made before this date find the candidates; the rest are held back | C30: The month start nearest 70% of the loans (suggested) | F30: 2024-11-01 (worked out from this book) | G30: cutoff | H30: =IF(OR(NOT(AND($C$33="Finding and testing a new variable",$C$34="Scout first")),AND(AND($C$33="Finding and testing a new variable",$C$34="Scout first"),$C30="",OR($D30="",$D30="n/a"))),"",IFERROR(IF(IF(AND($D$30<>"",$D$30<>"n/a"),$D$30,$C$30)&""=INDEX(_used!$B:$B,MATCH($G$30,_used!$A:$A,0))&"","Same as last Run","↻ Waiting for a Run"),"")) | I30: suggested: 2024-11-01 (8,395 loans before, 3,605 after) | J30: =IF(AND(AND($C$33="Finding and testing a new variable",$C$34="Scout first"),$C30="",OR($D30="",$D30="n/a")),1,0) | K30: =IF($H30="↻ Waiting for a Run",$B30&": "&INDEX(_used!$C:$C,MATCH($G$30,_used!$A:$A,0))&" → "&IF(AND($D$30<>"",$D$30<>"n/a"),$D$30,$C$30)&" (Control C30); ","")
B32: Chosen in the launcher · read-only here | D32: To change these, go back to Choose tests in the launcher and press Next. | G32: launcher|head
B33: What are you running? | C33: Finding and testing a new variable | G33: run_kind | H33: =IFERROR(IF(IF(AND($D$33<>"",$D$33<>"n/a"),$D$33,$C$33)&""=INDEX(_used!$B:$B,MATCH($G$33,_used!$A:$A,0))&"","Same as last Run","↻ Waiting for a Run"),"") | K33: =IF($H33="↻ Waiting for a Run",$B33&": "&IF(INDEX(_used!$B:$B,MATCH($G$33,_used!$A:$A,0))&""="","none",INDEX(_used!$B:$B,MATCH($G$33,_used!$A:$A,0)))&" → "&IF(IF(AND($D$33<>"",$D$33<>"n/a"),$D$33,$C$33)&""="","none",IF(AND($D$33<>"",$D$33<>"n/a"),$D$33,$C$33))&" (launcher); ","")
B34: Scout first, or test from a pre-spec already written? | C34: Scout first | G34: new_variable_step | H34: =IF($H$33="↻ Waiting for a Run","",IFERROR(IF(IF(AND($D$34<>"",$D$34<>"n/a"),$D$34,$C$34)&""=INDEX(_used!$B:$B,MATCH($G$34,_used!$A:$A,0))&"","Same as last Run","↻ Waiting for a Run"),"")) | K34: =IF($H34="↻ Waiting for a Run",$B34&": "&IF(INDEX(_used!$B:$B,MATCH($G$34,_used!$A:$A,0))&""="","none",INDEX(_used!$B:$B,MATCH($G$34,_used!$A:$A,0)))&" → "&IF(IF(AND($D$34<>"",$D$34<>"n/a"),$D$34,$C$34)&""="","none",IF(AND($D$34<>"",$D$34<>"n/a"),$D$34,$C$34))&" (launcher); ","")
B35: Cut into bands | C35: FICO | G35: launcher|bands | H35: =IF($H$33="↻ Waiting for a Run","",IFERROR(IF(IF(AND($D$35<>"",$D$35<>"n/a"),$D$35,$C$35)&""=INDEX(_used!$B:$B,MATCH($G$35,_used!$A:$A,0))&"","Same as last Run","↻ Waiting for a Run"),"")) | K35: =IF($H35="↻ Waiting for a Run",$B35&": "&IF(INDEX(_used!$B:$B,MATCH($G$35,_used!$A:$A,0))&""="","none",INDEX(_used!$B:$B,MATCH($G$35,_used!$A:$A,0)))&" → "&IF(IF(AND($D$35<>"",$D$35<>"n/a"),$D$35,$C$35)&""="","none",IF(AND($D$35<>"",$D$35<>"n/a"),$D$35,$C$35))&" (launcher); ","")
B36: Segment by | C36: CHANNEL | G36: launcher|segments | H36: =IF($H$33="↻ Waiting for a Run","",IFERROR(IF(IF(AND($D$36<>"",$D$36<>"n/a"),$D$36,$C$36)&""=INDEX(_used!$B:$B,MATCH($G$36,_used!$A:$A,0))&"","Same as last Run","↻ Waiting for a Run"),"")) | K36: =IF($H36="↻ Waiting for a Run",$B36&": "&IF(INDEX(_used!$B:$B,MATCH($G$36,_used!$A:$A,0))&""="","none",INDEX(_used!$B:$B,MATCH($G$36,_used!$A:$A,0)))&" → "&IF(IF(AND($D$36<>"",$D$36<>"n/a"),$D$36,$C$36)&""="","none",IF(AND($D$36<>"",$D$36<>"n/a"),$D$36,$C$36))&" (launcher); ","")
B37: Split every pocket by | G37: launcher|split | H37: =IF($H$33="↻ Waiting for a Run","",IFERROR(IF(IF(AND($D$37<>"",$D$37<>"n/a"),$D$37,$C$37)&""=INDEX(_used!$B:$B,MATCH($G$37,_used!$A:$A,0))&"","Same as last Run","↻ Waiting for a Run"),"")) | K37: =IF($H37="↻ Waiting for a Run",$B37&": "&IF(INDEX(_used!$B:$B,MATCH($G$37,_used!$A:$A,0))&""="","none",INDEX(_used!$B:$B,MATCH($G$37,_used!$A:$A,0)))&" → "&IF(IF(AND($D$37<>"",$D$37<>"n/a"),$D$37,$C$37)&""="","none",IF(AND($D$37<>"",$D$37<>"n/a"),$D$37,$C$37))&" (launcher); ","")
B38: Filter the Grids by | G38: launcher|filter | H38: =IF($H$33="↻ Waiting for a Run","",IFERROR(IF(IF(AND($D$38<>"",$D$38<>"n/a"),$D$38,$C$38)&""=INDEX(_used!$B:$B,MATCH($G$38,_used!$A:$A,0))&"","Same as last Run","↻ Waiting for a Run"),"")) | K38: =IF($H38="↻ Waiting for a Run",$B38&": "&IF(INDEX(_used!$B:$B,MATCH($G$38,_used!$A:$A,0))&""="","none",INDEX(_used!$B:$B,MATCH($G$38,_used!$A:$A,0)))&" → "&IF(IF(AND($D$38<>"",$D$38<>"n/a"),$D$38,$C$38)&""="","none",IF(AND($D$38<>"",$D$38<>"n/a"),$D$38,$C$38))&" (launcher); ","")
B39: Tested against | C39: BAD_FLAG | G39: launcher|outcome | H39: =IF($H$33="↻ Waiting for a Run","",IFERROR(IF(IF(AND($D$39<>"",$D$39<>"n/a"),$D$39,$C$39)&""=INDEX(_used!$B:$B,MATCH($G$39,_used!$A:$A,0))&"","Same as last Run","↻ Waiting for a Run"),"")) | K39: =IF($H39="↻ Waiting for a Run",$B39&": "&IF(INDEX(_used!$B:$B,MATCH($G$39,_used!$A:$A,0))&""="","none",INDEX(_used!$B:$B,MATCH($G$39,_used!$A:$A,0)))&" → "&IF(IF(AND($D$39<>"",$D$39<>"n/a"),$D$39,$C$39)&""="","none",IF(AND($D$39<>"",$D$39<>"n/a"),$D$39,$C$39))&" (launcher); ","")
B40: Inputs tested | C40: UTIL, TENURE, F1, F2, F3, F4, REGION | G40: launcher|test | H40: =IF($H$33="↻ Waiting for a Run","",IFERROR(IF(IF(AND($D$40<>"",$D$40<>"n/a"),$D$40,$C$40)&""=INDEX(_used!$B:$B,MATCH($G$40,_used!$A:$A,0))&"","Same as last Run","↻ Waiting for a Run"),"")) | K40: =IF($H40="↻ Waiting for a Run",$B40&": "&IF(INDEX(_used!$B:$B,MATCH($G$40,_used!$A:$A,0))&""="","none",INDEX(_used!$B:$B,MATCH($G$40,_used!$A:$A,0)))&" → "&IF(IF(AND($D$40<>"",$D$40<>"n/a"),$D$40,$C$40)&""="","none",IF(AND($D$40<>"",$D$40<>"n/a"),$D$40,$C$40))&" (launcher); ","")
B41: Held fixed | C41: FICO, CHANNEL | G41: launcher|hold | H41: =IF($H$33="↻ Waiting for a Run","",IFERROR(IF(IF(AND($D$41<>"",$D$41<>"n/a"),$D$41,$C$41)&""=INDEX(_used!$B:$B,MATCH($G$41,_used!$A:$A,0))&"","Same as last Run","↻ Waiting for a Run"),"")) | K41: =IF($H41="↻ Waiting for a Run",$B41&": "&IF(INDEX(_used!$B:$B,MATCH($G$41,_used!$A:$A,0))&""="","none",INDEX(_used!$B:$B,MATCH($G$41,_used!$A:$A,0)))&" → "&IF(IF(AND($D$41<>"",$D$41<>"n/a"),$D$41,$C$41)&""="","none",IF(AND($D$41<>"",$D$41<>"n/a"),$D$41,$C$41))&" (launcher); ","")
B42: Saved shortlist (pre-spec file) | G42: prespec | H42: =IF($H$33="↻ Waiting for a Run","",IFERROR(IF(IF(AND($D$42<>"",$D$42<>"n/a"),$D$42,$C$42)&""=INDEX(_used!$B:$B,MATCH($G$42,_used!$A:$A,0))&"","Same as last Run","↻ Waiting for a Run"),"")) | K42: =IF($H42="↻ Waiting for a Run",$B42&": "&IF(INDEX(_used!$B:$B,MATCH($G$42,_used!$A:$A,0))&""="","none",INDEX(_used!$B:$B,MATCH($G$42,_used!$A:$A,0)))&" → "&IF(IF(AND($D$42<>"",$D$42<>"n/a"),$D$42,$C$42)&""="","none",IF(AND($D$42<>"",$D$42<>"n/a"),$D$42,$C$42))&" (launcher); ","")
B43: Number columns: this many values or fewer is a category; more is cut into bands | C43: 12 values | G43: few_values | H43: =IF($H$33="↻ Waiting for a Run","",IFERROR(IF(IF(AND($D$43<>"",$D$43<>"n/a"),$D$43,$C$43)&""=INDEX(_used!$B:$B,MATCH($G$43,_used!$A:$A,0))&"","Same as last Run","↻ Waiting for a Run"),"")) | K43: =IF($H43="↻ Waiting for a Run",$B43&": "&IF(INDEX(_used!$B:$B,MATCH($G$43,_used!$A:$A,0))&""="","none",INDEX(_used!$B:$B,MATCH($G$43,_used!$A:$A,0)))&" → "&IF(IF(AND($D$43<>"",$D$43<>"n/a"),$D$43,$C$43)&""="","none",IF(AND($D$43<>"",$D$43<>"n/a"),$D$43,$C$43))&" (launcher); ","")
B44: Text columns: more values than this is too many to cut by (text is never cut into bands) | C44: 50 values | G44: many_values | H44: =IF($H$33="↻ Waiting for a Run","",IFERROR(IF(IF(AND($D$44<>"",$D$44<>"n/a"),$D$44,$C$44)&""=INDEX(_used!$B:$B,MATCH($G$44,_used!$A:$A,0))&"","Same as last Run","↻ Waiting for a Run"),"")) | K44: =IF($H44="↻ Waiting for a Run",$B44&": "&IF(INDEX(_used!$B:$B,MATCH($G$44,_used!$A:$A,0))&""="","none",INDEX(_used!$B:$B,MATCH($G$44,_used!$A:$A,0)))&" → "&IF(IF(AND($D$44<>"",$D$44<>"n/a"),$D$44,$C$44)&""="","none",IF(AND($D$44<>"",$D$44<>"n/a"),$D$44,$C$44))&" (launcher); ","")

Sheet Columns
B1: Columns | C1: What each column means, what looks odd in it, and what PocketBook remembers about it.
B3: Checked every column? | C3: Yes | D3: Run won't start until this is Yes.
B5: How this tab works
B6: What it is | C6: Set up guesses each column's meaning from its name and values; the reason is beside it. Fix any that's wrong. Confirmed meanings are remembered for the next extract.
B7: Odd values | C7: Values that may be codes rather than real numbers: one value far more often than any other, or negatives in a column that's mostly positive. Missing is treated as blank and counted.
B8: Treat as | C8: Answer Real or Missing. One left blank is used as recorded.
B9: Band edges | C9: Blank means Control's setting. Type edges as 620; 680; 740, or every 20. Look shows what each would cut, live.
B10: Remembered | C10: Set Forget? to Yes to drop what was learned about a column at the next Run. It then waits here for you to confirm it again. Answers marked ↻ take effect at the next Run.
B12: Column | C12: Samples | D12: What it is ↻ | E12: Why we think so | F12: Blank | G12: Odd values | H12: Treat as ↻ | I12: Band edges ↻ | J12: Remembered | K12: Forget? ↻ | L12: Check first | M12: Yes means ↻ | N12: Show per pocket ↻ | O12: Period ↻ | P12: In your words
B13: LOAN_NBR | C13: L0000000, L0000001, L0000002 | D13: Loan number (key) | E13: name contains 'loan'; a different value on every row | F13: 0 | J13: Yes · 1 Run | K13: No | Q13: key
B14: FICO | C14: -9999, 713, 716 | D14: FICO score | E14: name contains 'fico'; 98% of values between 300 and 850 | F14: 8.3333333e-05 | G14: -9999 on 240 loans | H14: Missing | J14: Yes · 1 Run | K14: No | Q14: fico | S14: FICO|repeated_value|-9999.0
B15: CHANNEL | C15: Online, Broker, Branch | D15: Category | E15: 3 different values | F15: 0 | J15: Yes · 1 Run | K15: No | L15: suggested as Category from its shape alone (3 different values). If it's something more specific, say so and it will be remembered. | Q15: category
B16: ORIG_BAL | C16: 7655.75, 27999.47, 39684.43 | D16: Booked amount | E16: name contains 'bal'; positive on every loan | F16: 8.3333333e-05 | J16: Yes · 1 Run | K16: No | Q16: booked
B17: BAD_FLAG | C17: 0, 2, 1 | D17: Outcome (yes/no) | E17: name contains 'bad'; 0 and 1 (7.9% are 1) | F17: 0 | J17: Yes · 1 Run | K17: No | L17: 1 value is neither 0 nor 1. They're left out of the outcome rates and counted; if they mean something, fix the extract. | Q17: outcome
B18: GCO_AMT | C18: 0.0, #N/A, 27620.62 | D18: GCO dollars | E18: name contains 'gco'; zero on 92% of loans, never negative | F18: 0 | J18: Yes · 1 Run | K18: No | L18: 1 value isn't a number among 11,999 that are. They're left out of any rate using this column and counted. | Q18: gco
B19: RANR_AMT | C19: 3017.35, 3928.24, 5816.98 | D19: RANR dollars | E19: name contains 'ranr'; numbers | F19: 0 | G19: Negative on 919 loans | J19: Yes · 1 Run | K19: No | Q19: ranr | S19: RANR_AMT|negatives|
B20: ASSET_CLASS | C20: 1, 2, 4 | D20: Category | E20: 4 different values | F20: 0 | J20: Yes · 1 Run | K20: No | L20: suggested as Category from its shape alone (4 different values). If it's something more specific, say so and it will be remembered. | Q20: category
B21: REV_DEBT | C21: 15868.86, 12884.7, 8920.97 | D21: Amount or number | E21: numbers with 11,826 values | F21: 0 | J21: Yes · 1 Run | K21: No | L21: suggested as Amount or number from its shape alone (numbers with 11,826 values). If it's something more specific, say so and it will be remembered. | Q21: amount
B22: ORIG_DATE | C22: 2021-11-18, 2024-06-24, 2023-07-12 | D22: Origination date | E22: name contains 'orig'; dates | F22: 0 | J22: Yes · 1 Run | K22: No | Q22: origination_date
B23: SALES | C23: 84264, 296409, 94519 | D23: Amount or number | E23: numbers with 11,786 values | F23: 0.001 | J23: Yes · 1 Run | K23: No | L23: suggested as Amount or number from its shape alone (numbers with 11,786 values). If it's something more specific, say so and it will be remembered. | Q23: amount
B24: INCOME | C24: 161848, 79129, 109898 | D24: Amount or number | E24: numbers with 11,797 values | F24: 0 | J24: Yes · 1 Run | K24: No | L24: suggested as Amount or number from its shape alone (numbers with 11,797 values). If it's something more specific, say so and it will be remembered. | Q24: amount
B25: UTIL | C25: 0.1748, 0.3661, 0.0656 | D25: Amount or number | E25: numbers with 7,529 values | F25: 0 | J25: Yes · 1 Run | K25: No | L25: suggested as Amount or number from its shape alone (numbers with 7,529 values). If it's something more specific, say so and it will be remembered. | Q25: amount
B26: TENURE | C26: 2.3, 5.0, 0.1 | D26: Amount or number | E26: numbers with 358 values | F26: 0 | J26: Yes · 1 Run | K26: No | L26: suggested as Amount or number from its shape alone (numbers with 358 values). If it's something more specific, say so and it will be remembered. | Q26: amount
B27: F1 | C27: 47.42, 56.7, 36.36 | D27: Amount or number | E27: numbers with 5,153 values | F27: 0 | G27: Negative on 8 loans | J27: Yes · 1 Run | K27: No | L27: suggested as Amount or number from its shape alone (numbers with 5,153 values). If it's something more specific, say so and it will be remembered. | Q27: amount | S27: F1|negatives|
B28: F2 | C28: 42.63, 52.93, 27.12 | D28: Amount or number | E28: numbers with 4,924 values | F28: 0 | G28: Negative on 10 loans | J28: Yes · 1 Run | K28: No | L28: suggested as Amount or number from its shape alone (numbers with 4,924 values). If it's something more specific, say so and it will be remembered. | Q28: amount | S28: F2|negatives|
B29: F3 | C29: 9.644, 9.893, 8.869 | D29: Amount or number | E29: numbers with 3,914 values | F29: 0 | J29: Yes · 1 Run | K29: No | L29: suggested as Amount or number from its shape alone (numbers with 3,914 values). If it's something more specific, say so and it will be remembered. | Q29: amount
B30: F4 | C30: 15.6, 42.7, 46.4 | D30: Amount or number | E30: numbers with 1,001 values | F30: 0 | J30: Yes · 1 Run | K30: No | L30: suggested as Amount or number from its shape alone (numbers with 1,001 values). If it's something more specific, say so and it will be remembered. | Q30: amount
B31: REGION | C31: North, West, South | D31: Category | E31: 5 different values | F31: 0 | J31: Yes · 1 Run | K31: No | L31: suggested as Category from its shape alone (5 different values). If it's something more specific, say so and it will be remembered. | Q31: category
B32: income_to_sales | C32: 1.921, 0.267, 1.163 | D32: Amount or number | E32: made under Add a column: INCOME ÷ SALES | F32: 0.002 | J32: Yes · 1 Run | K32: No | L32: New since the last check. | Q32: amount | R32: INCOME ÷ SALES
S33: table|end
B35: Add a column: one divided by another | S35: derived|head
B36: Shows here and on Look, and in Choose tests, once you press Set up again. Blank where the bottom is zero or blank. | S36: derived|note
B37: New column name ↻ | C37: Top (divided) | D37: Bottom (divided by) | E37: What it makes | S37: derived|cols
B38: income_to_sales | C38: INCOME | D38: SALES | E38: =IF(COUNTA(B38:D38)=0,"",IF(COUNTA(B38:D38)<3,"Needs a name, a top and a bottom.",B38&" = "&C38&" ÷ "&D38&" on each loan.")) | S38: derived|1
E39: =IF(COUNTA(B39:D39)=0,"",IF(COUNTA(B39:D39)<3,"Needs a name, a top and a bottom.",B39&" = "&C39&" ÷ "&D39&" on each loan.")) | S39: derived|2
E40: =IF(COUNTA(B40:D40)=0,"",IF(COUNTA(B40:D40)<3,"Needs a name, a top and a bottom.",B40&" = "&C40&" ÷ "&D40&" on each loan.")) | S40: derived|3

Sheet Look
B1: Look | C1: Each number column before you choose its band edges.
B3: How this tab works
B4: The bars | C4: How many loans fall in each step between From and To. Pick 10, 20 or 50 bars and change the range; the chart follows. The grey bar at each end holds the loans outside the range.
B5: The red bar | C5: A value that looks like a code, such as a score of -9999, gets a red bar of its own left of the chart, so it doesn't flatten the rest. Columns asks whether it means missing.
B6: The lines | C6: Red dashed: the band edges typed on Columns. They follow that tab as you type, so you can try edges here before the next Run; blank edges are cut at the Run, so no lines show. Grey: the 10th, 25th, 50th, 75th and 90th percentile, P10 to P90. A tenth of the loans on the chart lie below P10, half below P50 (the median). Worked out as Excel's PERCENTILE.INC does.
B7: How it counts | C7: Set up counts each column once, in 200 equal slices around its 1st to 99th percentile. A range you type is counted to the nearest slice.
B8: The dots | C8: The split column against each band column: a random 2,000 loans, the same every time. If the dots slope, the two move together, and part of a gap on Split may belong to the band column.
B10: FICO | H10: =IF('_look'!$F$20="","FICO · no edges on Columns yet","FICO · edges now "&'_look'!$F$20)
B11: Loans | C11: 12000
B12: Blank | C12: 1 | D12: 8.3333333e-05
B13: Not a number | C13: 0 | D13: 0
B14: Likely a code | C14: none found
B15: Smallest | C15: 496
B16: Median | C16: 699
B17: Mean | C17: 699.73127
B18: Largest | C18: 921
B19: Answered missing, left out | C19: 240 | D19: 0.02
B20: Bars | C20: 20
B21: From | C21: 550
B22: To | C22: 850
B24: 10th percentile (P10) | C24: 629
B25: 25th percentile (P25) | C25: 663
B26: 50th percentile (P50), the median | C26: 699
B27: 75th percentile (P75) | C27: 736
B28: 90th percentile (P90) | C28: 771
B30: ORIG_BAL | H30: =IF('_look'!$S$20="","ORIG_BAL · no edges on Columns yet","ORIG_BAL · edges now "&'_look'!$S$20)
B31: Loans | C31: 12000
B32: Blank | C32: 1 | D32: 8.3333333e-05
B33: Not a number | C33: 0 | D33: 0
B34: Likely a code | C34: none found
B35: Smallest | C35: 5005.32
B36: Median | C36: 32134.41
B37: Mean | C37: 32375.786
B38: Largest | C38: 59998.91
B40: Bars | C40: 20
B41: From | C41: 0
B42: To | C42: 60000
B44: 10th percentile (P10) | C44: 10280.21
B45: 25th percentile (P25) | C45: 18492.645
B46: 50th percentile (P50), the median | C46: 32134.41
B47: 75th percentile (P75) | C47: 46390.825
B48: 90th percentile (P90) | C48: 54473.9
B50: REV_DEBT | H50: =IF('_look'!$AF$20="","REV_DEBT · no edges on Columns yet","REV_DEBT · edges now "&'_look'!$AF$20)
B51: Loans | C51: 12000
B52: Blank | C52: 0 | D52: 0
B53: Not a number | C53: 0 | D53: 0
B54: Likely a code | C54: none found
B55: Smallest | C55: 0
B56: Median | C56: 11419.78
B57: Mean | C57: 12069.907
B58: Largest | C58: 48521.79
B60: Bars | C60: 20
B61: From | C61: 0
B62: To | C62: 30000
B64: 10th percentile (P10) | C64: 4350.677
B65: 25th percentile (P25) | C65: 7447.23
B66: 50th percentile (P50), the median | C66: 11419.78
B67: 75th percentile (P75) | C67: 15884.17
B68: 90th percentile (P90) | C68: 20625.653
B70: SALES | H70: =IF('_look'!$AS$20="","SALES · no edges on Columns yet","SALES · edges now "&'_look'!$AS$20)
B71: Loans | C71: 12000
B72: Blank | C72: 12 | D72: 0.001
B73: Not a number | C73: 0 | D73: 0
B74: Likely a code | C74: none found
B75: Smallest | C75: 0
B76: Median | C76: 250287
B77: Mean | C77: 282306.73
B78: Largest | C78: 2222343
B80: Bars | C80: 20
B81: From | C81: 0
B82: To | C82: 800000
B84: 10th percentile (P10) | C84: 132027.3
B85: 25th percentile (P25) | C85: 179052.25
B86: 50th percentile (P50), the median | C86: 250287
B87: 75th percentile (P75) | C87: 347989
B88: 90th percentile (P90) | C88: 471015.5
B90: INCOME | H90: =IF('_look'!$BF$20="","INCOME · no edges on Columns yet","INCOME · edges now "&'_look'!$BF$20)
B91: Loans | C91: 12000
B92: Blank | C92: 0 | D92: 0
B93: Not a number | C93: 0 | D93: 0
B94: Likely a code | C94: none found
B95: Smallest | C95: 3830
B96: Median | C96: 126028
B97: Mean | C97: 197973.47
B98: Largest | C98: 4683491
B100: Bars | C100: 20
B101: From | C101: 0
B102: To | C102: 1400000
B104: 10th percentile (P10) | C104: 38394.5
B105: 25th percentile (P25) | C105: 66585.75
B106: 50th percentile (P50), the median | C106: 126028
B107: 75th percentile (P75) | C107: 235048.25
B108: 90th percentile (P90) | C108: 429233.6
B110: UTIL | H110: =IF('_look'!$BS$20="","UTIL · no edges on Columns yet","UTIL · edges now "&'_look'!$BS$20)
B111: Loans | C111: 12000
B112: Blank | C112: 0 | D112: 0
B113: Not a number | C113: 0 | D113: 0
B114: Likely a code | C114: none found
B115: Smallest | C115: 0
B116: Median | C116: 0.6073
...

Sheet Scouting
B1: Scouting | C1: Which of the 8 candidates does the book lean on, and where does each one bend? On the development loans only.
B3: How this tab works
B4: What it is | C4: Scouting: which of the 8 candidates the book leans on, and where each one bends. It nominates; it never confirms (statistics.md B7). The confirmation is the New variables tab, on loans scouting never read.
B5: Found on | C5: 8,394 development loans made 2021-06-30 to 2024-10-31, 673 of them bad: every loan made before the cutoff on Control, 2024-11-01. The 3,605 loans made on or after it are held back. Only their dates were read to rank the candidates and cut their bins; their outcomes and every other value were read only once the pre-spec was written, to check the tree on them (the New variables tab). Left out: 1 with no readable outcome.
B6: Candidates | C6: The columns ticked Test it in the launcher, and every new column made on Columns (one column divided by another), each fed in as a column in its own right. A category is given one number per value, in the order of its values.
B7: The forest | C7: A random forest: 200 trees, each leaf at least 40 loans, seed 7, grown by scikit-learn 1.9.1. Each tree splits the loans wherever a cut best separates bad from good, and the forest averages their votes. It writes no formula and assumes no shape. The same extract gives the same forest; another version of scikit-learn may not.
B8: Importance | C8: How far the forest's AUC drops when the column is shuffled, on loans it did not train on. AUC is the chance a random bad loan scores above a random good one; 0.5 is a coin flip. The development loans are cut into 3 runs by date; each run is scored by a forest grown on the other two, with 5 shuffles of each column, and the drops are averaged. The forest's own AUC is 0.628. It is a ranking: no direction, no size and no range, and it leans towards columns with many distinct values.
B9: With and without | C9: Importance is from a forest given the candidates alone. The next column is from a forest given FICO and CHANNEL as well (AUC 0.692): a candidate that drops there was mostly telling you FICO and CHANNEL. Their own importance is under the table.
B10: Noise floor | C10: 0.0085: the largest importance any candidate reached in the same forests grown on the development loans with their outcomes shuffled among them, so that no column could matter (24 tries). It is what a column scores by chance.
B11: Proposed? | C11: Yes for a number column whose importance is above the noise floor, with the held-fixed columns in the forest or without them, and whose shape bends somewhere to cut. A category is ranked and not proposed: the pre-spec cuts a number at its bins.
B12: Suggested bins | C12: From the shape: the forest's bad rate with the column set to one value for every loan (partial dependence, on 1,000 development loans drawn by seed), over the column's own percentiles, from a forest grown on every development loan with FICO and CHANNEL in it. A cut goes where the curve steps by at least 25% of its average, largest step first, each group holding at least 2% of the loans, at most 6 groups. Inside each step the edge sits where the forest itself split the column most, rounded to two figures. The shapes are under the table.
B13: Reference | C13: The group holding the development loans' median value: the ordinary case, which every other group is compared with.
B14: Correlated with | C14: Candidates, and held-fixed number columns, whose values rise and fall together with this one: a rank correlation (Spearman's) of 0.7 or more either way, on the development loans with both. Importance splits between such columns, and the shape of one can borrow the other's.
B15: The pre-spec | C15: PocketBook writes the pre-spec from the proposed candidates beside the workbook, when there is none, and the confirmation reads it. One that is there already is confirmed as it stands: an edit is yours to make, and Record logs it. The file is under the table.
B16: As of | C16: The last Run, 2026-09-30 04:36. Nothing here follows Control until the next Run.
B18: Outcome | D18: Candidates · proposed | F18: Held fixed | G18: Noise floor | H18: Development loans
B19: BAD_FLAG | D19: 8 · 2 proposed | F19: FICO · CHANNEL | G19: 0.0084764578 | H19: 8,394 · 673 bad
B21: Worked out at the last Run, 2026-09-30 04:36, on the development loans. Ranked by the larger of the two importances.
B23: Candidate | C23: Rank | D23: Importance | E23: FICO and CHANNEL held fixed | F23: Suggested bins | G23: Reference | H23: Correlated with | I23: Proposed? | J23: Why
B24: UTIL | C24: 1 | D24: 0.077301 | E24: 0.04644 | F24: 0.0 - 0.8; 0.9 - 1.2 | G24: 0.0 - 0.8 | I24: Yes | J24: clears the noise floor
B25: income_to_sales | C25: 2 | D25: 0.036077 | E25: 0.031561 | F25: 0.02 - 0.09; 0.10 - 1.99; 2.00 - 8.30 | G25: 0.10 - 1.99 | I25: Yes | J25: clears the noise floor
B26: F4 | C26: 3 | D26: 0.005662 | E26: 0.004672 | I26: No | J26: below the noise floor
B27: F2 | C27: 4 | D27: 0.003198 | E27: -0.002621 | H27: F1 (+0.97) | I27: No | J27: below the noise floor
B28: F1 | C28: 5 | D28: 0.002109 | E28: 0.00105 | H28: F2 (+0.97) | I28: No | J28: below the noise floor
B29: TENURE | C29: 6 | D29: 0.000605 | E29: 0.002076 | I29: No | J29: below the noise floor
B30: F3 | C30: 7 | D30: -0.001772 | E30: 0.000193 | I30: No | J30: below the noise floor
B31: REGION | C31: 8 | D31: -0.001832 | E31: -0.000929 | F31: Each value | I31: No | J31: a category
B33: Held fixed, for comparison: their own importance with the candidates
B34: Column | D34: Importance
B35: FICO | D35: 0.080336
B36: CHANNEL | D36: 0.005494
B38: The pre-spec
B39: Written by this Run: Scouting book - pre-spec.yaml, beside the workbook, fingerprint 374284797598, before any held-back loan was tested. Edit it if you like; Record logs every change.
B41: # Written by PocketBook's scouting on 2026-09-30, from 8,394 development loans made 2021-06-30 to 2024-10-31.
B42: # The 3,605 loans held back (made 2024-11-01 to 2026-03-30) were not read. Edit it if you like: Record logs every change.
B43: prespec: 1
B44: written: 2026-09-30
B45: outcome: BAD_FLAG
B46: inputs:
B47: - column: UTIL
B48: bins: [0.9]
B49: reference: 0 # 0.0 - 0.8, the group holding the median
B50: - column: income_to_sales
... B58: UTIL: the forest's bad rate as UTIL moves (cut at 0.9)
B59: UTIL | D59: Bad rate
B60: 0.011879 | D60: 0.06385443
B61: 0.021086 | D61: 0.064349997
B62: 0.0321 | D62: 0.064923367
B63: 0.0545 | D63: 0.064325629
B64: 0.083295 | D64: 0.06312739
B65: 0.11423 | D65: 0.062312231
B66: 0.1802 | D66: 0.064473844
B67: 0.24132 | D67: 0.067114284
B68: 0.3023 | D68: 0.066288758
B69: 0.36677 | D69: 0.065787278
B70: 0.48352 | D70: 0.064205107
B71: 0.6068 | D71: 0.065396136
... B82: 1.188114 | D82: 0.1185751
B84: income_to_sales: the forest's bad rate as income_to_sales moves (cut at 0.1, 2)
B85: income_to_sales | D85: Bad rate
B86: 0.073873775 | D86: 0.098198202
B87: 0.092908323 | D87: 0.096065435
B88: 0.10908831 | D88: 0.084493559
B89: 0.13047906 | D89: 0.077670756
B90: 0.15495005 | D90: 0.075319211
B91: 0.17682879 | D91: 0.074995083
B92: 0.21790781 | D92: 0.070275459
B93: 0.25695465 | D93: 0.070231739
B94: 0.2961053 | D94: 0.069998745
B95: 0.3338033 | D95: 0.069575198
B96: 0.41775547 | D96: 0.071609987
B97: 0.51146012 | D97: 0.073689352
... B108: 3.4363751 | D108: 0.17109795

Sheet New variables
B1: New variables | C1: Does each of the 2 candidates still tell good loans from bad on loans it was never found on, and once FICO and CHANNEL are held fixed?
B3: How this tab works
B4: The tree, unseen | C4: The random forest from the Scouting tab, grown on every loan made before the cutoff (2024-11-01), scores the loans made on or after it, which it never saw. AUC is the chance a random bad loan scores above a random good one: 0.5 is a coin flip, 1 is perfect. Built is the forest's AUC on the development loans, each scored by a forest grown on the others (the Scouting tab); unseen is on the held-back loans. Unseen well under built means the tree learnt those years, not the book. Said twice: from the candidates alone, and with FICO and CHANNEL in the forest too.
B5: All together | C5: One logistic regression on the held-back loans with every candidate's groups in it at once, each against its own reference, and one constant for each pocket FICO and CHANNEL make, so the pockets are held fixed as they are below. Each odds ratio is then net of every other candidate. Adds is a likelihood ratio test of taking the candidate out, all its groups at once: its test statistic, on as many degrees of freedom as it has groups less one, and its p-value, after the allowance for testing the shortlist at once. Adds? is Yes when that p-value is under the bar. Moves with names candidates whose values rise and fall together (a rank correlation of 0.7 or more, on the development loans): what one adds, the other may already say. The loans are the held-back ones with a value of every candidate, in pockets where some went bad and some didn't.
B6: The candidates | C6: 2 inputs on the shortlist scouting wrote, each in its own groups, the pre-spec's: UTIL in 2 groups (0.0 - 0.8, 0.9 - 1.2); income_to_sales in 3 groups (0.02 - 0.09, 0.10 - 1.99, 2.00 - 8.30).
B7: Compared with | C7: Each candidate's own reference group, the pre-spec's: UTIL against 0.0 - 0.8; income_to_sales against 0.10 - 1.99. Every other group of a candidate is compared with its reference.
B8: Found, then confirmed | C8: Loans made 2021-06-30 to 2024-10-31: UTIL 8,394 loans, 673 bad; income_to_sales 8,379 loans, 672 bad; found on: where the groups were chosen. Loans made 2024-11-01 to 2026-03-30: UTIL 3,605 loans, 280 bad; income_to_sales 3,596 loans, 278 bad; held back: the test that counts. Left out of UTIL's test: 1 with no readable outcome. Left out of income_to_sales's test: 24 with no readable value of the column tested; 1 with no readable outcome. Record counts every loan. The comparison is made once on each; only the held-back result counts.
B9: Gap | C9: The odds ratio against its reference group. Odds are bad loans divided by good ones, and an odds ratio is a group's odds divided by its reference group's: 2.00× means twice the odds of going bad. While few loans go bad it is close to how many times as often they do. Worked out by conditional logistic regression, which compares the groups inside each pocket and takes each pocket's own count of bad loans as given, instead of estimating a rate for every pocket, which biases the answer when pockets are thin.
B10: p-value | C10: ="The chance of a gap at least this big if the group were no different from its reference group, after the allowance for testing many at once (below). Below "&TEXT(significance_bar,"0%")&" is significant, at "&TEXT(confidence,"0%")&" sure. Two-sided: a gap either way counts."
B11: Many at once | C11: Benjamini-Hochberg, as Control's "Allowing for testing many pockets at once" says: across the 2 candidates' 3 groups, each against its reference, on each set of loans. The New variables table shows the p-value after it, and Holds up? and Still holds? read that one; the tests in full keep each raw p-value.
B12: Holds up? | C12: Yes when the held-back loans show the gap on the same side of 1 as the found loans did, and significant. Only the held-back result counts: the found one is where the idea came from.
B13: FICO and CHANNEL held fixed | C13: The held-back comparison made again with every loan compared only with loans in its own pocket, cut by FICO and CHANNEL at the band edges on Record. A difference in the FICO and CHANNEL mix then can't pass for a difference in the candidate. Still holds? says whether the gap stays; if it goes, the candidate was mostly telling you FICO and CHANNEL. Every pocket counts, however small: fewest loans and fewest losses decide only whether one pocket can be read on its own, and a pocket where no loan, or every loan, went bad says nothing and adds nothing.
B14: Material? | C14: Excess is a group's charge-offs on the held-back loans above its share of them (its share of the held-back loans), times the whole book's charge-offs over the held-back loans', so it sits on the same scale as Control's materiality line. Material? is Yes when it reaches the line.
B15: In words | C15: The two verdicts read together: holds up, and not just FICO and CHANNEL; holds up, but it was mostly FICO and CHANNEL; holds up only with them held fixed; or didn't hold up on held-back loans.
B16: The tests in full | C16: Under the chart, one block per candidate. Does each candidate matter at all: the general test (the Mantel-Haenszel test for its groups: a standard way to add pockets up without mixing their loans), read against a chi-square on one fewer degree of freedom than its groups; the trend test, which gives the groups the scores 1 to their number and asks whether the bad rate climbs or falls steadily with them, on 1 degree of freedom; and the regression's block test (a likelihood ratio test, on one fewer degree of freedom than its groups), whether the groups together add anything. A difference with no trend is a U or a hump, which a straight-line test would call nothing. Then each group's odds ratio with its range and its raw p-value, before any allowance, and how much of the held-back loans' losses sit in each group (on the holdout only, and on the book as a whole, not pocket by pocket: the lift, the group's bad rate over the holdout's, is the finding, never the share of all losses).
B17: The range | C17: ="Where the true odds ratio sits, "&TEXT(confidence,"0%")&" sure: the log odds ratio plus and minus the multiple of its standard error that the confidence level sets. It is each group's own, before the allowance. As a check, each odds ratio held fixed was worked out a second way, pair by pair with Mantel-Hae"&"nszel: the largest gap between the two is 3.3%."
B18: Written by scouting | C18: This Run found the candidates on its development loans (the Scouting tab), wrote the pre-spec Scouting book - pre-spec.yaml from them, and then confirmed it on the loans held back. Found is those development loans, where the groups were chosen. Record names the file.
B19: Choices made here that no ruling settles yet | C19: The trend test scores each candidate's groups 1, 2, 3 and on, evenly spaced, rather than by where their numbers sit. Conditional logistic regression is used in every pocket, whatever its size: the unconditional fit the scope allows for pockets over a few thousand loans isn't used, as the conditional one is exact and quick at any size. A loan with no readable value in a column the pockets are cut by sits in a pocket of its own, as on the grids. A group with no bad loan, or only bad loans, in the pockets that say something has no odds ratio; the others are fitted as if its loans weren't there, which is where the regression heads anyway. Excess is scaled to the whole book by its losses over the held-back loans' losses. The allowance treats each set of loans as one family, every candidate's groups together, as a grid's pockets are one family per rate. All together gives each pocket its own constant rather than conditioning the pockets out, and refuses when they average under 5 bad loans each (statistics.md B10).
B20: As of | C20: The numbers are the last Run's, 2026-09-30 04:36. Holds up?, Still holds?, Material?, In words, every range and the chart's worse line follow Control.
B22: WHAT WAS TESTED | C22: Outcome | F22: Candidates · live | I22: Held fixed | L22: Material at · live | N22: Loans
B23: from the shortlist scouting wrote | C23: BAD_FLAG | F23: =IFERROR("2 · "&((COUNTIFS($B$45:$B$47,"UTIL",$H$45:$H$47,"Yes")>0)+(COUNTIFS($B$45:$B$47,"income_to_sales",$H$45:$H$47,"Yes")>0))&" hold up","2") | I23: FICO · CHANNEL | L23: =IFERROR(IF(materiality_kind="none","No floor",IF(INDEX(line_values,MATCH("gco_rate",line_keys,0))="","No line",IF(FALSE,TEXT(INDEX(line_values,MATCH("gco_rate",line_keys,0)),"#,##0.0")&" bad loans","$"&TEXT(INDEX(line_values,MATCH("gco_rate",line_keys,0)),"#,##0")))),"") | N23: up to 8,394 found · 3,605 held back
B25: The numbers are from the last Run, 2026-09-30 04:36. The verdicts, the materiality line and the chart's worse line follow Control.
B26: =IFERROR(IF(COUNTIF(Status,"↻ Waiting for a Run")=0,"","↻ "&COUNTIF(Status,"↻ Waiting for a Run")&IF(COUNTIF(Status,"↻ Waiting for a Run")=1," Control change waits for a Run."," Control changes wait for a Run.")),"")
B28: The tree on loans it never saw
B29: What it found | C29: Built on loans made 2021-06-30 to 2024-10-31: AUC 0.63. On loans made 2024-11-01 to 2026-03-30, unseen: 0.60. With FICO and CHANNEL in the forest too: 0.69 built, 0.68 unseen.
B31: All 2 candidates together, on the held-back loans
B32: Candidate | C32: Compared | F32: Loans | G32: Bad rate | H32: Odds ratio, together | I32: ="Range ("&TEXT(confidence,"0%")&" sure)" | J32: p-value | K32: Adds: statistic | L32: Adds: p, allowed | M32: Adds? | N32: Moves with
B33: UTIL | C33: 0.9 - 1.2 vs 0.0 - 0.8 | F33: 950 | G33: 0.12947368 | H33: 2.350393 | I33: =TEXT(EXP(0.8545825580989187-NORMSINV(1-(1-confidence)/2)*0.1304815733270686),"0.00")&"x to "&TEXT(EXP(0.8545825580989187+NORMSINV(1-(1-confidence)/2)*0.1304815733270686),"0.00")&"x" | J33: 5.7749319e-11 | K33: 41.12 on 1 | L33: 2.8564427e-10 | M33: =IF(NOT(ISNUMBER($L33)),"",IF(AND(ISNUMBER($L33),$L33<significance_bar),"Yes","No"))
B34: income_to_sales | C34: 0.02 - 0.09 vs 0.10 - 1.99 | F34: 79 | G34: 0.12658228 | H34: 2.0019998 | I34: =TEXT(EXP(0.6941465746534167-NORMSINV(1-(1-confidence)/2)*0.3604044238537812),"0.00")&"x to "&TEXT(EXP(0.6941465746534167+NORMSINV(1-(1-confidence)/2)*0.3604044238537812),"0.00")&"x" | J34: 0.054101722 | K34: 17.36 on 2 | L34: 0.0001701513 | M34: =IF(NOT(ISNUMBER($L34)),"",IF(AND(ISNUMBER($L34),$L34<significance_bar),"Yes","No"))
C35: 2.00 - 8.30 vs 0.10 - 1.99 | F35: 156 | G35: 0.17307692 | H35: 2.6191744 | I35: =TEXT(EXP(0.9628591693192158-NORMSINV(1-(1-confidence)/2)*0.23259688567310022),"0.00")&"x to "&TEXT(EXP(0.9628591693192158+NORMSINV(1-(1-confidence)/2)*0.23259688567310022),"0.00")&"x" | J35: 3.4790474e-05
B37: What it found | C37: =IF($Z$37="","No candidate adds anything significant once the others are in. ","Adds something the others don't: "&MID($Z$37,3,2000)&". ")&IF($Z$38="","","Adds nothing significant once the others are in: "&MID($Z$38,3,2000)&".") | Z37: =IF(AND(ISNUMBER($L33),$L33<significance_bar),"; UTIL","")&IF(AND(ISNUMBER($L34),$L34<significance_bar),"; income_to_sales","")
Z38: =IF(AND(ISNUMBER($L33),NOT(AND(ISNUMBER($L33),$L33<significance_bar))),"; UTIL","")&IF(AND(ISNUMBER($L34),NOT(AND(ISNUMBER($L34),$L34<significance_bar))),"; income_to_sales","")
C39: Held-back loans left out of the candidates together: 9 with no readable value of income_to_sales.
B41: Each candidate on its own
D43: Found | F43: Confirmed on the held-back loans | I43: Confirmed, FICO and CHANNEL held fixed
B44: Candidate | C44: Compared | D44: Gap | E44: p, allowed | F44: Gap | G44: p, allowed | H44: Holds up? | I44: Gap | J44: p, allowed | K44: Still holds? | L44: Excess $ | M44: Material? | N44: In words
B45: UTIL | C45: 0.9 - 1.2 vs 0.0 - 0.8 | D45: 2.2838987 | E45: 2.5676259e-23 | F45: 2.3657698 | G45: 3.4643114e-11 | H45: =IF(NOT(ISNUMBER($F45)),"",IF(AND(AND(ISNUMBER($G45),$G45<significance_bar),IF(ISNUMBER($D45),($D45>1)=($F45>1),$F45>1)),"Yes","No")) | I45: 2.3216725 | J45: 2.0368526e-10 | K45: =IF(NOT(ISNUMBER($I45)),"",IF(AND(AND(ISNUMBER($J45),$J45<significance_bar),IF(ISNUMBER($D45),($D45>1)=($I45>1),$I45>1)),"Yes","No")) | L45: 3158801.6 | M45: =IFERROR(IF(NOT(ISNUMBER($L45)),"",IF(IF(materiality_kind="none",0,INDEX(line_values,MATCH("gco_rate",line_keys,0)))="","",IF(AND($L45>0,$L45>=IF(materiality_kind="none",0,INDEX(line_values,MATCH("gco_rate",line_keys,0)))),"Yes","No"))),"") | N45: =IF($H45="","",IF($H45="Yes",IF($K45="Yes","Holds up, and not just FICO and CHANNEL","Holds up, but it was mostly FICO and CHANNEL"),IF($K45="Yes","Holds up only with FICO and CHANNEL held fixed","Didn't hold up on held-back loans"))) | X45: =worse_at
B46: income_to_sales | C46: 0.02 - 0.09 vs 0.10 - 1.99 | D46: 2.4076344 | E46: 8.5494733e-06 | F46: 1.8758362 | G46: 0.068119581 | H46: =IF(NOT(ISNUMBER($F46)),"",IF(AND(AND(ISNUMBER($G46),$G46<significance_bar),IF(ISNUMBER($D46),($D46>1)=($F46>1),$F46>1)),"Yes","No")) | I46: 1.9614321 | J46: 0.057280505 | K46: =IF(NOT(ISNUMBER($I46)),"",IF(AND(AND(ISNUMBER($J46),$J46<significance_bar),IF(ISNUMBER($D46),($D46>1)=($I46>1),$I46>1)),"Yes","No")) | L46: 206433.48 | M46: =IFERROR(IF(NOT(ISNUMBER($L46)),"",IF(IF(materiality_kind="none",0,INDEX(line_values,MATCH("gco_rate",line_keys,0)))="","",IF(AND($L46>0,$L46>=IF(materiality_kind="none",0,INDEX(line_values,MATCH("gco_rate",line_keys,0)))),"Yes","No"))),"") | N46: =IF($H46="","",IF($H46="Yes",IF($K46="Yes","Holds up, and not just FICO and CHANNEL","Holds up, but it was mostly FICO and CHANNEL"),IF($K46="Yes","Holds up only with FICO and CHANNEL held fixed","Didn't hold up on held-back loans"))) | X46: =worse_at
B47: income_to_sales | C47: 2.00 - 8.30 vs 0.10 - 1.99 | D47: 3.380068 | E47: 3.0386401e-21 | F47: 2.7085621 | G47: 1.0646986e-05 | H47: =IF(NOT(ISNUMBER($F47)),"",IF(AND(AND(ISNUMBER($G47),$G47<significance_bar),IF(ISNUMBER($D47),($D47>1)=($F47>1),$F47>1)),"Yes","No")) | I47: 2.6386293 | J47: 3.0495414e-05 | K47: =IF(NOT(ISNUMBER($I47)),"",IF(AND(AND(ISNUMBER($J47),$J47<significance_bar),IF(ISNUMBER($D47),($D47>1)=($I47>1),$I47>1)),"Yes","No")) | L47: 693606.27 | M47: =IFERROR(IF(NOT(ISNUMBER($L47)),"",IF(IF(materiality_kind="none",0,INDEX(line_values,MATCH("gco_rate",line_keys,0)))="","",IF(AND($L47>0,$L47>=IF(materiality_kind="none",0,INDEX(line_values,MATCH("gco_rate",line_keys,0)))),"Yes","No"))),"") | N47: =IF($H47="","",IF($H47="Yes",IF($K47="Yes","Holds up, and not just FICO and CHANNEL","Holds up, but it was mostly FICO and CHANNEL"),IF($K47="Yes","Holds up only with FICO and CHANNEL held fixed","Didn't hold up on held-back loans"))) | X47: =worse_at
B81: The tests in full: UTIL
B83: Does UTIL matter?
B84: Test | F84: Statistic | G84: Degrees of freedom | H84: p-value | I84: Reading
B85: Found, nothing held fixed: loans made 2021-06-30 to 2024-10-31
B86: Any difference across the groups (general) | F86: 105.67835 | G86: 1 | H86: 8.6729741e-25 | I86: =IF(H86="","",IF(AND(ISNUMBER(H86),H86<significance_bar),"significant","not significant"))
B87: A steady climb or fall (trend) | F87: 105.67835 | G87: 1 | H87: 8.6729741e-25 | I87: =IF(H87="","",IF(AND(ISNUMBER(H87),H87<significance_bar),"significant","not significant"))
B88: Any difference, from the regression (block test) | F88: 96.39805 | G88: 1 | H88: 9.3959667e-23 | I88: =IF(H88="","",IF(AND(ISNUMBER(H88),H88<significance_bar),"significant","not significant"))
B89: What it found | C89: =IF(AND(AND(ISNUMBER(H86),H86<significance_bar),AND(ISNUMBER(H87),H87<significance_bar)),"On development, with nothing held fixed, the bad rate differs across the groups, and rises steadily as UTIL rises.",IF(AND(ISNUMBER(H86),H86<significance_bar),"On development, with nothing held fixed, the bad rate differs across the groups, but not in one direction: higher in some groups, lower in others.",IF(AND(ISNUMBER(H87),H87<significance_bar),"On development, with nothing held fixed, the groups taken all at once do not differ significantly, but the bad rate rises steadily as UTIL rises (the trend test).","On development, with nothing held fixed, no difference across the groups shows at "&TEXT(confidence,"0%")&" sure. That is not proof there is none.")))
B91: Found, FICO and CHANNEL held fixed: loans made 2021-06-30 to 2024-10-31
B92: Any difference across the groups (general) | F92: 93.811484 | G92: 1 | H92: 3.4705231e-22 | I92: =IF(H92="","",IF(AND(ISNUMBER(H92),H92<significance_bar),"significant","not significant"))
B93: A steady climb or fall (trend) | F93: 93.811484 | G93: 1 | H93: 3.4705231e-22 | I93: =IF(H93="","",IF(AND(ISNUMBER(H93),H93<significance_bar),"significant","not significant"))
B94: Any difference, from the regression (block test) | F94: 86.562083 | G94: 1 | H94: 1.3541874e-20 | I94: =IF(H94="","",IF(AND(ISNUMBER(H94),H94<significance_bar),"significant","not significant"))
B95: What it found | C95: =IF(AND(AND(ISNUMBER(H92),H92<significance_bar),AND(ISNUMBER(H93),H93<significance_bar)),"On development, the bad rate differs across the groups, and rises steadily as UTIL rises.",IF(AND(ISNUMBER(H92),H92<significance_bar),"On development, the bad rate differs across the groups, but not in one direction: higher in some groups, lower in others.",IF(AND(ISNUMBER(H93),H93<significance_bar),"On development, the groups taken all at once do not differ significantly, but the bad rate rises steadily as UTIL rises (the trend test).","On development, no difference across the groups shows at "&TEXT(confidence,"0%")&" sure. That is not proof there is none.")))
B97: Confirmed on the held-back loans, nothing held fixed: loans made 2024-11-01 to 2026-03-30
B98: Any difference across the groups (general) | F98: 48.308955 | G98: 1 | H98: 3.6408577e-12 | I98: =IF(H98="","",IF(AND(ISNUMBER(H98),H98<significance_bar),"significant","not significant"))
B99: A steady climb or fall (trend) | F99: 48.308955 | G99: 1 | H99: 3.6408577e-12 | I99: =IF(H99="","",IF(AND(ISNUMBER(H99),H99<significance_bar),"significant","not significant"))
B100: Any difference, from the regression (block test) | F100: 43.877469 | G100: 1 | H100: 3.4959006e-11 | I100: =IF(H100="","",IF(AND(ISNUMBER(H100),H100<significance_bar),"significant","not significant"))
B101: What it found | C101: =IF(AND(AND(ISNUMBER(H98),H98<significance_bar),AND(ISNUMBER(H99),H99<significance_bar)),"On the holdout, with nothing held fixed, the bad rate differs across the groups, and rises steadily as UTIL rises.",IF(AND(ISNUMBER(H98),H98<significance_bar),"On the holdout, with nothing held fixed, the bad rate differs across the groups, but not in one direction: higher in some groups, lower in others.",IF(AND(ISNUMBER(H99),H99<significance_bar),"On the holdout, with nothing held fixed, the groups taken all at once do not differ significantly, but the bad rate rises steadily as UTIL rises (the trend test).","On the holdout, with nothing held fixed, no difference across the groups shows at "&TEXT(confidence,"0%")&" sure. That is not proof there is none.")))
B103: Confirmed on the held-back loans, FICO and CHANNEL held fixed: loans made 2024-11-01 to 2026-03-30
B104: Any difference across the groups (general) | F104: 44.444214 | G104: 1 | H104: 2.6170935e-11 | I104: =IF(H104="","",IF(AND(ISNUMBER(H104),H104<significance_bar),"significant","not significant"))
B105: A steady climb or fall (trend) | F105: 44.444214 | G105: 1 | H105: 2.6170935e-11 | I105: =IF(H105="","",IF(AND(ISNUMBER(H105),H105<significance_bar),"significant","not significant"))
B106: Any difference, from the regression (block test) | F106: 40.761071 | G106: 1 | H106: 1.7202604e-10 | I106: =IF(H106="","",IF(AND(ISNUMBER(H106),H106<significance_bar),"significant","not significant"))
B107: What it found | C107: =IF(AND(AND(ISNUMBER(H104),H104<significance_bar),AND(ISNUMBER(H105),H105<significance_bar)),"On the holdout, the bad rate differs across the groups, and rises steadily as UTIL rises.",IF(AND(ISNUMBER(H104),H104<significance_bar),"On the holdout, the bad rate differs across the groups, but not in one direction: higher in some groups, lower in others.",IF(AND(ISNUMBER(H105),H105<significance_bar),"On the holdout, the groups taken all at once do not differ significantly, but the bad rate rises steadily as UTIL rises (the trend test).","On the holdout, no difference across the groups shows at "&TEXT(confidence,"0%")&" sure. That is not proof there is none.")))
B109: How much more often does each group go bad than 0.0 - 0.8?
B110: Group of UTIL | F110: Loans | G110: Bad loans | H110: Bad rate | I110: Odds ratio | J110: p-value | K110: ="Range ("&TEXT(confidence,"0%")&" sure)" | L110: Odds ratio, FICO and CHANNEL held fixed | M110: p-value | N110: ="Range ("&TEXT(confidence,"0%")&" sure)"
B111: Found: loans made 2021-06-30 to 2024-10-31
B112: 0.0 - 0.8 (reference) | F112: 6172 | G112: 382 | H112: 0.061892417 | I112: 1.00 | L112: 1.00
B113: 0.9 - 1.2 | F113: 2222 | G113: 291 | H113: 0.1309631 | I113: 2.2838987 | J113: 8.5587529e-24 | K113: =TEXT(EXP(0.8258839461764884-NORMSINV(1-(1-confidence)/2)*0.08212051049485869),"0.00")&"x to "&TEXT(EXP(0.8258839461764884+NORMSINV(1-(1-confidence)/2)*0.08212051049485869),"0.00")&"x" | L113: 2.2137598 | M113: 1.999218e-21 | N113: =TEXT(EXP(0.7946923170483604-NORMSINV(1-(1-confidence)/2)*0.0836072409330936),"0.00")&"x to "&TEXT(EXP(0.7946923170483604+NORMSINV(1-(1-confidence)/2)*0.0836072409330936),"0.00")&"x"
B114: What it found | C114: =IF($Z$114="","On development, with nothing held fixed, no group differs from 0.0 - 0.8 at "&TEXT(confidence,"0%")&" sure.","On development, with nothing held fixed, "&MID($Z$114,3,2000)&".") | Z114: =IF(AND(ISNUMBER(J113),J113<significance_bar),IF(I113>=1,"; 0.9 - 1.2 goes bad "&TEXT(I113,"0.00")&" times as often as 0.0 - 0.8","; 0.9 - 1.2 goes bad less often than 0.0 - 0.8, "&TEXT(I113,"0.00")&" times as often")&" ("&TEXT(EXP(0.8258839461764884-NORMSINV(1-(1-confidence)/2)*0.08212051049485869),"0.00")&"x to "&TEXT(EXP(0.8258839461764884+NORMSINV(1-(1-confidence)/2)*0.08212051049485869),"0.00")&"x)","")
B115: What it found | C115: =IF($Z$115="","On development, no group differs from 0.0 - 0.8 at "&TEXT(confidence,"0%")&" sure, with the pockets held fixed.","On development, "&MID($Z$115,3,2000)&", with the pockets held fixed.") | Z115: =IF(AND(ISNUMBER(M113),M113<significance_bar),IF(L113>=1,"; 0.9 - 1.2 goes bad "&TEXT(L113,"0.00")&" times as often as 0.0 - 0.8","; 0.9 - 1.2 goes bad less often than 0.0 - 0.8, "&TEXT(L113,"0.00")&" times as often")&" ("&TEXT(EXP(0.7946923170483604-NORMSINV(1-(1-confidence)/2)*0.0836072409330936),"0.00")&"x to "&TEXT(EXP(0.7946923170483604+NORMSINV(1-(1-confidence)/2)*0.0836072409330936),"0.00")&"x)","")
B117: Group of UTIL | F117: Loans | G117: Bad loans | H117: Bad rate | I117: Odds ratio | J117: p-value | K117: ="Range ("&TEXT(confidence,"0%")&" sure)" | L117: Odds ratio, FICO and CHANNEL held fixed | M117: p-value | N117: ="Range ("&TEXT(confidence,"0%")&" sure)"
B118: Confirmed on the held-back loans: loans made 2024-11-01 to 2026-03-30
B119: 0.0 - 0.8 (reference) | F119: 2655 | G119: 157 | H119: 0.05913371 | I119: 1.00 | L119: 1.00
B120: 0.9 - 1.2 | F120: 950 | G120: 123 | H120: 0.12947368 | I120: 2.3657698 | J120: 1.1547705e-11 | K120: =TEXT(EXP(0.8611034712384326-NORMSINV(1-(1-confidence)/2)*0.12689860556110097),"0.00")&"x to "&TEXT(EXP(0.8611034712384326+NORMSINV(1-(1-confidence)/2)*0.12689860556110097),"0.00")&"x" | L120: 2.3216725 | M120: 6.7895087e-11 | N120: =TEXT(EXP(0.842287821703663-NORMSINV(1-(1-confidence)/2)*0.12908161116541814),"0.00")&"x to "&TEXT(EXP(0.842287821703663+NORMSINV(1-(1-confidence)/2)*0.12908161116541814),"0.00")&"x"
B121: What it found | C121: =IF($Z$121="","On the holdout, with nothing held fixed, no group differs from 0.0 - 0.8 at "&TEXT(confidence,"0%")&" sure.","On the holdout, with nothing held fixed, "&MID($Z$121,3,2000)&".") | Z121: =IF(AND(ISNUMBER(J120),J120<significance_bar),IF(I120>=1,"; 0.9 - 1.2 goes bad "&TEXT(I120,"0.00")&" times as often as 0.0 - 0.8","; 0.9 - 1.2 goes bad less often than 0.0 - 0.8, "&TEXT(I120,"0.00")&" times as often")&" ("&TEXT(EXP(0.8611034712384326-NORMSINV(1-(1-confidence)/2)*0.12689860556110097),"0.00")&"x to "&TEXT(EXP(0.8611034712384326+NORMSINV(1-(1-confidence)/2)*0.12689860556110097),"0.00")&"x)","")
B122: What it found | C122: =IF($Z$122="","On the holdout, no group differs from 0.0 - 0.8 at "&TEXT(confidence,"0%")&" sure, with the pockets held fixed.","On the holdout, "&MID($Z$122,3,2000)&", with the pockets held fixed.") | Z122: =IF(AND(ISNUMBER(M120),M120<significance_bar),IF(L120>=1,"; 0.9 - 1.2 goes bad "&TEXT(L120,"0.00")&" times as often as 0.0 - 0.8","; 0.9 - 1.2 goes bad less often than 0.0 - 0.8, "&TEXT(L120,"0.00")&" times as often")&" ("&TEXT(EXP(0.842287821703663-NORMSINV(1-(1-confidence)/2)*0.12908161116541814),"0.00")&"x to "&TEXT(EXP(0.842287821703663+NORMSINV(1-(1-confidence)/2)*0.12908161116541814),"0.00")&"x)","")
B124: How much of the held-back loans' losses sit in each group?
B125: Group of UTIL | F125: Loans | G125: Share of loans | H125: Bad loans | I125: Share of bad loans | J125: GCO | K125: Share of GCO | L125: Bad rate | M125: Times the holdout's bad rate
B126: 0.0 - 0.8 (reference) | F126: 2655 | G126: 0.73647712 | H126: 157 | I126: 0.56071429 | J126: 2708259.4 | K126: 0.54852722 | L126: 0.05913371 | M126: 0.76134652
B127: 0.9 - 1.2 | F127: 950 | G127: 0.26352288 | H127: 123 | I127: 0.43928571 | J127: 2229069.7 | K127: 0.45147278 | L127: 0.12947368 | M127: 1.6669737
B128: All held-back loans in the test | F128: 3605 | G128: 1 | H128: 280 | I128: 1 | J128: 4937329.2 | K128: 1 | L128: 0.077669903 | M128: 1
B130: What it found | C130: =IF($Z$130="","On the holdout, no group goes bad significantly more often than 0.0 - 0.8, so none is singled out; every group is in the table.","On the holdout, "&MID($Z$130,3,2000)&".") | Z130: =IF(AND(AND(ISNUMBER(6.78950872713059e-11),6.78950872713059e-11<significance_bar),2.321672478130649>1),"; 0.9 - 1.2 holds "&TEXT(G127,"0.0%")&" of the loans, "&TEXT(I127,"0.0%")&" of the bad loans and "&TEXT(K127,"0.0%")&" of the GCO, at "&TEXT(M127,"0.00")&" times the holdout's bad rate","")
B132: The tests in full: income_to_sales
B134: Does income_to_sales matter?
B135: Test | F135: Statistic | G135: Degrees of freedom | H135: p-value | I135: Reading
B136: Found, nothing held fixed: loans made 2021-06-30 to 2024-10-31
B137: Any difference across the groups (general) | F137: 115.01454 | G137: 2 | H137: 1.0590314e-25 | I137: =IF(H137="","",IF(AND(ISNUMBER(H137),H137<significance_bar),"significant","not significant"))
B138: A steady climb or fall (trend) | F138: 30.832958 | G138: 1 | H138: 2.8122091e-08 | I138: =IF(H138="","",IF(AND(ISNUMBER(H138),H138<significance_bar),"significant","not significant"))
B139: Any difference, from the regression (block test) | F139: 86.964906 | G139: 2 | H139: 1.3056012e-19 | I139: =IF(H139="","",IF(AND(ISNUMBER(H139),H139<significance_bar),"significant","not significant"))
B140: What it found | C140: =IF(AND(AND(ISNUMBER(H137),H137<significance_bar),AND(ISNUMBER(H138),H138<significance_bar)),"On development, with nothing held fixed, the bad rate differs across the groups, and rises steadily as income_to_sales rises.",IF(AND(ISNUMBER(H137),H137<significance_bar),"On development, with nothing held fixed, the bad rate differs across the groups, but not in one direction: higher in some groups, lower in others.",IF(AND(ISNUMBER(H138),H138<significance_bar),"On development, with nothing held fixed, the groups taken all at once do not differ significantly, but the bad rate rises steadily as income_to_sales rises (the trend test).","On development, with nothing held fixed, no difference across the groups shows at "&TEXT(confidence,"0%")&" sure. That is not proof there is none.")))
B142: Found, FICO and CHANNEL held fixed: loans made 2021-06-30 to 2024-10-31
B143: Any difference across the groups (general) | F143: 112.04727 | G143: 2 | H143: 4.6692208e-25 | I143: =IF(H143="","",IF(AND(ISNUMBER(H143),H143<significance_bar),"significant","not significant"))
B144: A steady climb or fall (trend) | F144: 30.288644 | G144: 1 | H144: 3.7229915e-08 | I144: =IF(H144="","",IF(AND(ISNUMBER(H144),H144<significance_bar),"significant","not significant"))
B145: Any difference, from the regression (block test) | F145: 86.200341 | G145: 2 | H145: 1.9135231e-19 | I145: =IF(H145="","",IF(AND(ISNUMBER(H145),H145<significance_bar),"significant","not significant"))
B146: What it found | C146: =IF(AND(AND(ISNUMBER(H143),H143<significance_bar),AND(ISNUMBER(H144),H144<significance_bar)),"On development, the bad rate differs across the groups, and rises steadily as income_to_sales rises.",IF(AND(ISNUMBER(H143),H143<significance_bar),"On development, the bad rate differs across the groups, but not in one direction: higher in some groups, lower in others.",IF(AND(ISNUMBER(H144),H144<significance_bar),"On development, the groups taken all at once do not differ significantly, but the bad rate rises steadily as income_to_sales rises (the trend test).","On development, no difference across the groups shows at "&TEXT(confidence,"0%")&" sure. That is not proof there is none.")))
B148: Confirmed on the held-back loans, nothing held fixed: loans made 2024-11-01 to 2026-03-30
B149: Any difference across the groups (general) | F149: 24.219717 | G149: 2 | H149: 5.5049747e-06 | I149: =IF(H149="","",IF(AND(ISNUMBER(H149),H149<significance_bar),"significant","not significant"))
B150: A steady climb or fall (trend) | F150: 7.329893 | G150: 1 | H150: 0.0067817095 | I150: =IF(H150="","",IF(AND(ISNUMBER(H150),H150<significance_bar),"significant","not significant"))
B151: Any difference, from the regression (block test) | F151: 19.042833 | G151: 2 | H151: 7.3265793e-05 | I151: =IF(H151="","",IF(AND(ISNUMBER(H151),H151<significance_bar),"significant","not significant"))
B152: What it found | C152: =IF(AND(AND(ISNUMBER(H149),H149<significance_bar),AND(ISNUMBER(H150),H150<significance_bar)),"On the holdout, with nothing held fixed, the bad rate differs across the groups, and rises steadily as income_to_sales rises.",IF(AND(ISNUMBER(H149),H149<significance_bar),"On the holdout, with nothing held fixed, the bad rate differs across the groups, but not in one direction: higher in some groups, lower in others.",IF(AND(ISNUMBER(H150),H150<significance_bar),"On the holdout, with nothing held fixed, the groups taken all at once do not differ significantly, but the bad rate rises steadily as income_to_sales rises (the trend test).","On the holdout, with nothing held fixed, no difference across the groups shows at "&TEXT(confidence,"0%")&" sure. That is not proof there is none.")))
B154: Confirmed on the held-back loans, FICO and CHANNEL held fixed: loans made 2024-11-01 to 2026-03-30
...

Sheet Record
B1: Record | C1: What ran, whether it adds up, what was left out, and every Run. For the reviewer.
B3: How this tab works
B4: What it holds | C4: What the last Run was, whether it adds up, which tests it used, what it left out, and every Run and refusal. Nothing here is a result: the result tabs hold those.
B5: Settings | C5: Each Control setting: the answer in use now, and what the last Run used. A setting changed since the Run is shaded; the result tabs follow a Changes-now setting at once, and a Needs-a-Run one at the next Run.
B6: Every Run | C6: Newest first. Each entry is what that Run used, and a refusal says what it was waiting for.
B8: This Run | E8: Settings | K8: pair|this|settings
B9: Item | C9: Detail | E9: Setting | F9: In use now | G9: Last Run used
B10: Extract | C10: Scouting book.csv | E10: Loans made before this date find the candidates; the rest are held back | F10: =IF(AND(Control!$D$30<>"",Control!$D$30<>"n/a"),Control!$D$30,IFERROR(INDEX(_options!$G:$G,MATCH(Control!$G$30&"|"&Control!$C$30,_options!$A:$A,0)),Control!$C$30&"")) | G10: 2024-11-01 (worked out from this book) | K10: row|this|settings | L10: =IF(Control!$H$30="↻ Waiting for a Run",1,0)
B11: Loans run | C11: 12,000 | E11: How many bands a number column is cut into | F11: =IF(AND(Control!$D$26<>"",Control!$D$26<>"n/a"),Control!$D$26,IFERROR(INDEX(_options!$G:$G,MATCH(Control!$G$26&"|"&Control!$C$26,_options!$A:$A,0)),Control!$C$26&"")) | G11: 5 bands | K11: row|this|settings | L11: =IF(Control!$H$26="↻ Waiting for a Run",1,0)
B12: What was run | C12: Finding and testing a new variable: scout first | E12: Where the band edges fall | F12: =IF(AND(Control!$D$27<>"",Control!$D$27<>"n/a"),Control!$D$27,IFERROR(INDEX(_options!$G:$G,MATCH(Control!$G$27&"|"&Control!$C$27,_options!$A:$A,0)),Control!$C$27&"")) | G12: Each band holds about the same number of loans | K12: row|this|settings | L12: =IF(Control!$H$27="↻ Waiting for a Run",1,0)
B13: Record of this run | C13: Scouting book - PocketBook - what ran.yaml, beside this workbook: every setting the run used, kept for the file. | E13: Smallest excess loss worth reporting | F13: ='_live'!$E$10 | G13: 1.0% of the book's GCO, $168,066 | K13: row|this|settings | L13: =IF('_live'!$E$10<>'_live'!$F$10,1,0)
C14: It is replaced by the next Run. | E14: How much worse than its comparison a pocket must be | F14: ='_live'!$E$5 | G14: worse at 1.25x | K14: row|this|settings | L14: =IF('_live'!$E$5<>'_live'!$F$5,1,0) | M14: sp
B15: Origination dates | C15: 2021-06-30 to 2026-03-30 (12,000 loans; 0 without a readable date) | E15: How sure a difference must be before it counts | F15: ='_live'!$E$7 | G15: 95% sure | K15: row|this|settings | L15: =IF('_live'!$E$7<>'_live'!$F$7,1,0)
B16: New column: income_to_sales | C16: INCOME ÷ SALES on each loan. Made on 11,976; blank on 24 (12 where SALES is zero; 12 where SALES blank). | E16: Allowing for testing many pockets at once | F16: =IF(AND(Control!$D$29<>"",Control!$D$29<>"n/a"),Control!$D$29,IFERROR(INDEX(_options!$G:$G,MATCH(Control!$G$29&"|"&Control!$C$29,_options!$A:$A,0)),Control!$C$29&"")) | G16: Hold down the share of false finds (Benjamini-Hochberg) | K16: row|this|settings | L16: =IF(Control!$H$29="↻ Waiting for a Run",1,0)
B17: Band edges used: FICO | C17: 654; 686; 713; 746 (5 bands) | K17: row|this|settings
B18: Scouting | C18: 8 candidates on 8,394 development loans made 2021-06-30 to 2024-10-31; 2 proposed: UTIL, income_to_sales. See | K18: row|this|settings
C19: the Scouting tab. | K19: row|this|settings | M19: sp
B20: Scouting held back | C20: 3,605 loans made 2024-11-01 to 2026-03-30: none of their outcomes or values was read by scouting. | K20: row|this|settings
B21: Scouting's pre-spec | C21: Written by this Run: Scouting book - pre-spec.yaml, beside the workbook, fingerprint 374284797598, before any | K21: row|this|settings
C22: held-back loan was tested. Edit it if you like; Record logs every change. | K22: row|this|settings | M22: sp
B23: Scouting out of time | C23: Built on loans made 2021-06-30 to 2024-10-31: AUC 0.63. On loans made 2024-11-01 to 2026-03-30, unseen: 0.60. | K23: row|this|settings
C24: With FICO and CHANNEL in the forest too: 0.69 built, 0.68 unseen. | K24: row|this|settings | M24: sp
B25: Pre-spec | C25: /tmp/credit3/Scout files/Scouting book - pre-spec.yaml | K25: row|this|settings
B26: Pre-spec commit | C26: not in a git repository, so not committed: a pre-spec only counts once it is committed | K26: row|this|settings
B27: Pre-spec fingerprint | C27: 374284797598: the first 12 characters of the file's SHA-256, so any change to it shows | K27: row|this|settings
B28: What the pre-spec says | C28: written: 2026-09-30 | K28: row|this|settings
C29: outcome: BAD_FLAG | K29: row|this|settings | M29: nl
C30: inputs: 2 | K30: row|this|settings | M30: nl
C31: 1. column: UTIL | K31: row|this|settings | M31: nl
C32: 1. bins: 0.9 (groups: 0.0 - 0.8; 0.9 - 1.2) | K32: row|this|settings | M32: nl
C33: 1. reference: 0.0 - 0.8 | K33: row|this|settings | M33: nl
C34: 2. column: income_to_sales | K34: row|this|settings | M34: nl
C35: 2. bins: 0.1, 2 (groups: 0.02 - 0.09; 0.10 - 1.99; 2.00 - 8.30) | K35: row|this|settings | M35: nl
C36: 2. reference: 0.10 - 1.99 | K36: row|this|settings | M36: nl
C37: strata: FICO, CHANNEL | K37: row|this|settings | M37: nl
C38: confidence: 0.95 | K38: row|this|settings | M38: nl
C39: holdout: 2024-11-01 to 2026-03-30 | K39: row|this|settings | M39: nl
C40: development: 2021-06-30 to 2024-10-31 | K40: row|this|settings | M40: nl
B41: Warning | C41: This run doesn't count as the pre-specified one until the pre-spec is committed, unchanged. | K41: row|this|settings
B42: Differs from the pre-spec | C42: nowhere: this run used what it says | K42: row|this|settings
B43: Holdout | C43: 3,605 of this extract's loans were made in the holdout (2024-11-01 to 2026-03-30), the first on 2024-11-01 and | K43: row|this|settings
C44: the last on 2026-03-30. This run touched the holdout. | K44: row|this|settings | M44: sp
B45: Confirmatory test | C45: UTIL: Development 2021-06-30 to 2024-10-31: 8,394 loans, 673 bad; holdout 2024-11-01 to 2026-03-30: 3,605 loans, | K45: row|this|settings
C46: 280 bad. See the New variables tab. Left out of this test only (the loan counts on Record include them): 1 with | K46: row|this|settings | M46: sp
C47: no readable outcome. | K47: row|this|settings | M47: sp
B48: Confirmatory test | C48: income_to_sales: Development 2021-06-30 to 2024-10-31: 8,379 loans, 672 bad; holdout 2024-11-01 to 2026-03-30: | K48: row|this|settings
C49: 3,596 loans, 278 bad. See the New variables tab. Left out of this test only (the loan counts on Record include | K49: row|this|settings | M49: sp
C50: them): 24 with no readable value of the column tested; 1 with no readable outcome. | K50: row|this|settings | M50: sp
B51: Runs that touched the holdout | C51: 1 on Record's Every Run, this one included | K51: row|this|settings
B52: This pre-spec's held-back runs | C52: In order: this run (374284797598). | K52: row|this|settings
B54: Does it add up | E54: Tests used | K54: pair|adds|tests
B55: Check | C55: Result | E55: Where | F55: Test
B56: Bleed tabs | C56: None: testing a new variable runs only the confirmatory test. Any left by an earlier Run were taken off. | E56: Borderline now: Bad dollars | F56: =COUNTIFS('_pockets'!$A$4:$A$1048576,"grids",'_pockets'!$E$4:$E$1048576,"outcome_booked",'_pockets'!$AM$4:$AM$1048576,"?*")&" of 0 pockets on the grids have a borderline verdict ("&COUNTIFS('_pockets'!$A$4:$A$1048576,"grids",'_pockets'!$E$4:$E$1048576,"outcome_booked",'_pockets'!$AN$4:$AN$1048576,"?*")&" on Worse?)." | K56: row|adds|tests
E57: Borderline now: Charge-offs | F57: =COUNTIFS('_pockets'!$A$4:$A$1048576,"grids",'_pockets'!$E$4:$E$1048576,"gco_rate",'_pockets'!$AM$4:$AM$1048576,"?*")&" of 0 pockets on the grids have a borderline verdict ("&COUNTIFS('_pockets'!$A$4:$A$1048576,"grids",'_pockets'!$E$4:$E$1048576,"gco_rate",'_pockets'!$AN$4:$AN$1048576,"?*")&" on Worse?)." | K57: row|adds|tests
E58: Borderline now: Kept after losses | F58: =COUNTIFS('_pockets'!$A$4:$A$1048576,"grids",'_pockets'!$E$4:$E$1048576,"ranr_rate",'_pockets'!$AM$4:$AM$1048576,"?*")&" of 0 pockets on the grids have a borderline verdict ("&COUNTIFS('_pockets'!$A$4:$A$1048576,"grids",'_pockets'!$E$4:$E$1048576,"ranr_rate",'_pockets'!$AN$4:$AN$1048576,"?*")&" on Worse?)." | K58: row|adds|tests
E59: Borderline now: Earned before losses | F59: =COUNTIFS('_pockets'!$A$4:$A$1048576,"grids",'_pockets'!$E$4:$E$1048576,"contribution_rate",'_pockets'!$AM$4:$AM$1048576,"?*")&" of 0 pockets on the grids have a borderline verdict ("&COUNTIFS('_pockets'!$A$4:$A$1048576,"grids",'_pockets'!$E$4:$E$1048576,"contribution_rate",'_pockets'!$AN$4:$AN$1048576,"?*")&" on Worse?)." | K59: row|adds|tests
E60: p-value | F60: ="The chance of a gap at least this big if there were no real difference, after the allowance for many tests. Below "&TEXT(significance_bar,"0%")&" is significant, at "&TEXT(confidence,"0%")&" sure. Two-sided: a gap either way counts." | K60: row|adds|tests
E61: Borderline | F61: ="A verdict is borderline when the p-value that decides it came from shuffling and sits within 2 of its own standard errors of the "&TEXT(significance_bar,"0%")&" bar, either side, so another run of the shuffles could read it the other way. The standard error is the square root of p (1 - p) / shuffles, times what the allowance for many tests multiplied the p-value by. The tabs add ""borderline (p 0.048)"" to th"&"e verdict; its colour, order and counts stay the verdict's. The z test and the exact test give the same p-value on every run, so they are never borderline." | K61: row|adds|tests
E62: Standard error | F62: ="How far a rate worked out from this many loans typically lands from its true value. A gap of "&TEXT(NORMSINV(1-(1-confidence)/2),"0.00")&" standard errors is the "&TEXT(confidence,"0%")&" line." | K62: row|adds|tests
E63: Contribution before losses | F63: RANR + GCO, per booked dollar. This assumes RANR has gross charge-offs taken out. If RANR nets | K63: row|adds|tests
F64: recoveries instead, contribution is overstated by the recoveries. | K64: row|adds|tests | N64: sp
E65: Profit counts as more or less | F65: ='_live'!$E$13&IF(profit_kind="test",": only a gap that is significant at "&TEXT(confidence,"0%"),"")&" (none was chosen, so each pocket's own test)" | K65: row|adds|tests
E66: How profit reads | F66: As the gap: how many points of booked dollars a pocket is short of or ahead of its band, and the dollars | K66: row|adds|tests
F67: that comes to. A gap its own test doesn't call significant gives the gap and says not significant. The | K67: row|adds|tests | N67: sp
F68: examples are as of the last Run. | K68: row|adds|tests | N68: sp
E69: Tests: scouting | F69: A random forest (scikit-learn 1.9.1, 200 trees, leaves of at least 40, seed 7) ranking by permutation | K69: row|adds|tests
F70: importance, cross-fitted in 3 runs by date, against a noise floor from shuffled outcomes; bins from | K70: row|adds|tests | N70: sp
F71: partial dependence and the forest's own splits; once the pre-spec was written, the forests' AUC on the | K71: row|adds|tests | N71: sp
F72: held-back loans (statistics.md B11). | K72: row|adds|tests | N72: sp
E73: Tests on New variables | F73: Each group against the reference: conditional logistic regression, its odds ratio, range and p-value, | K73: row|adds|tests
F74: and its block test (a likelihood ratio test on one fewer degree of freedom than the groups); whether the | K74: row|adds|tests | N74: sp
F75: column matters at all: the Mantel-Haenszel test for the groups and its trend test. Each on the loans the | K75: row|adds|tests | N75: sp
F76: groups were found on and on the held-back loans, with and without the columns held fixed. | K76: row|adds|tests | N76: sp
E77: Tests: the allowance for many at once | F77: Benjamini-Hochberg, as Control's "Allowing for testing many pockets at once" says: across the 2 | K77: row|adds|tests
F78: candidates' 3 groups, each against its reference, on each set of loans. The New variables table shows | K78: row|adds|tests | N78: sp
F79: the p-value after it, and Holds up? and Still holds? read that one; the tests in full keep each raw | K79: row|adds|tests | N79: sp
F80: p-value. | K80: row|adds|tests | N80: sp
E81: Tests: all together | F81: One logistic regression on the held-back loans with every candidate's groups at once and one constant | K81: row|adds|tests
F82: per pocket (the pockets as control dummies); per candidate, a likelihood ratio test of taking it out, | K82: row|adds|tests | N82: sp
F83: with the allowance above across the shortlist (statistics.md B10). | K83: row|adds|tests | N83: sp
B85: Left out | E85: Every Run, newest first | K85: pair|left|runs
B86: Where | C86: What and how many | E86: When | F86: What happened
B87: Left out of Bad loans | C87: 1 x BAD_FLAG flag not 0 or 1 | E87: 2026-09-30 04:36 | F87: Ran on 12,000 loans from Scouting book.csv. What was run: Finding and testing a new variable: scout | K87: row|left|runs
B88: Left out of Bad dollars | C88: 1 x ORIG_BAL blank; 1 x BAD_FLAG flag not 0 or 1 | F88: first. | K88: row|left|runs | N88: sp
B89: Left out of Charge-offs | C89: 1 x GCO_AMT not a number; 1 x ORIG_BAL blank | F89: Scouting on 8,394 development loans made 2021-06-30 to 2024-10-31 (the 3,605 held back not read): 2 of 8 | K89: row|left|runs
B90: Left out of Kept after losses | C90: 1 x ORIG_BAL blank | F90: candidates proposed (UTIL, income_to_sales). Wrote the pre-spec Scouting book - pre-spec.yaml on | K90: row|left|runs | N90: sp
B91: Left out of Earned before losses | C91: 1 x GCO_AMT not a number; 1 x ORIG_BAL blank | F91: 2026-09-30: fingerprint 374284797598. | K91: row|left|runs | N91: sp
B92: Warning | C92: open data question: "RANR_AMT": negative values in a column that is mostly positive (919 rows). Used as recorded | F92: Follows pre-spec Scouting book - pre-spec.yaml (not committed). | K92: row|left|runs
C93: until answered Real or Missing under Treat as on Columns | F93: Touched the holdout: 3,605 loans made 2024-11-01 to 2026-03-30. | K93: row|left|runs | M93: sp
B94: Warning | C94: open data question: "F1": negative values in a column that is mostly positive (8 rows). Used as recorded until | F94: Pre-spec Scouting book - pre-spec.yaml written: fingerprint 374284797598, dated 2026-09-30 in the file; | K94: row|left|runs
C95: answered Real or Missing under Treat as on Columns | F95: first read by this run. | K95: row|left|runs | M95: sp | N95: sp
B96: Warning | C96: open data question: "F2": negative values in a column that is mostly positive (10 rows). Used as recorded until | F96: Touched the holdout: the tree's out-of-time check scored 3,605 loans made 2024-11-01 to 2026-03-30, | K96: row|left|runs
C97: answered Real or Missing under Treat as on Columns | F97: after the pre-spec was written. Built on loans made 2021-06-30 to 2024-10-31: AUC 0.63. On loans made | K97: row|left|runs | M97: sp | N97: sp
F98: 2024-11-01 to 2026-03-30, unseen: 0.60. With FICO and CHANNEL in the forest too: 0.69 built, 0.68 | K98: row|left|runs | N98: sp
F99: unseen. | K99: row|left|runs | N99: sp
F100: Warning: open data question: "RANR_AMT": negative values in a column that is mostly positive (919 rows). | K100: row|left|runs
F101: Used as recorded until answered Real or Missing under Treat as on Columns | K101: row|left|runs | N101: sp
F102: Warning: open data question: "F1": negative values in a column that is mostly positive (8 rows). Used as | K102: row|left|runs
F103: recorded until answered Real or Missing under Treat as on Columns | K103: row|left|runs | N103: sp
F104: Warning: open data question: "F2": negative values in a column that is mostly positive (10 rows). Used | K104: row|left|runs
...

Sheet _options
A1: lookup | B1: setting | C1: option | D1: value | E1: what it means | F1: your own value accepts | G1: plain | H1: lookup by value | J1: number columns
A2: run_kind|Where the book bleeds | B2: run_kind | C2: Where the book bleeds | E2: The grids, the split and the three-way: which pockets lose more than their share. Needs the loan number, booked amount, outcome, GCO and RANR. No date. | G2: Where the book bleeds | J2: FICO
A3: run_kind|Finding and testing a new variable | B3: run_kind | C3: Finding and testing a new variable | E3: Whether a new column, like income over sales, tells good loans from bad on loans kept back. Needs the loan number, the outcome and a column marked Origination date. | G3: Finding and testing a new variable | J3: ORIG_BAL
A4: new_variable_step|Scout first | B4: new_variable_step | C4: Scout first | E4: The main path: the tree ranks the ticked columns on loans before the cutoff, to write the pre-spec and confirm it on the loans held back. Needs scikit-learn. | G4: Scout first | J4: BAD_FLAG
A5: new_variable_step|Test from a pre-spec | B5: new_variable_step | C5: Test from a pre-spec | E5: Or test a shortlist saved earlier, once, on the loans it kept back. The launcher names the pre-spec file. | G5: Test from a pre-spec | J5: GCO_AMT
A6: cutoff|The month start nearest 70% of the loans (suggested) | B6: cutoff | C6: The month start nearest 70% of the loans (suggested) | E6: Worked out from this extract's dates: the first of the month by which about 70% of the loans had been made. The tree is built on the loans before it. | F6: a date, such as 2024-01-01 | G6: The month start nearest 70% of the loans (suggested) | J6: RANR_AMT
A7: cutoff|The month start nearest 80% of the loans | B7: cutoff | C7: The month start nearest 80% of the loans | E7: The same at 80%: more loans to find on, fewer held back to confirm on. | F7: a date, such as 2024-01-01 | G7: The month start nearest 80% of the loans | J7: ASSET_CLASS
A8: few_values|12 values (recommended) | B8: few_values | C8: 12 values (recommended) | D8: 12 | E8: Term (36, 48, 60) or a grade from 1 to 10 is read as categories, not cut into bands. | F8: whole number of values | G8: 12 values | H8: few_values|12 | J8: REV_DEBT
A9: few_values|6 values | B9: few_values | C9: 6 values | D9: 6 | E9: Only very short lists are categories; more columns are cut into bands. | F9: whole number of values | G9: 6 values | H9: few_values|6 | J9: SALES
A10: few_values|24 values | B10: few_values | C10: 24 values | D10: 24 | E10: Longer lists stay categories, such as a month or a 1-20 score. | F10: whole number of values | G10: 24 values | H10: few_values|24 | J10: INCOME
A11: many_values|50 values (recommended) | B11: many_values | C11: 50 values (recommended) | D11: 50 | E11: State (50 or so) is still a dimension; a city or a dealer name is raised as a question instead. | F11: whole number of values | G11: 50 values | H11: many_values|50 | J11: UTIL
A12: many_values|25 values | B12: many_values | C12: 25 values | D12: 25 | E12: Keeps grids small. Longer lists are raised as questions. | F12: whole number of values | G12: 25 values | H12: many_values|25 | J12: TENURE
A13: many_values|100 values | B13: many_values | C13: 100 values | D13: 100 | E13: Allows long lists as dimensions; many of their pockets will be tiny. | F13: whole number of values | G13: 100 values | H13: many_values|100 | J13: F1
A14: band_count|5 bands (recommended) | B14: band_count | C14: 5 bands (recommended) | D14: 5 | E14: Fine enough to see a trend, with each band holding a fifth of the loans. | F14: whole number of bands | G14: 5 bands | H14: band_count|5 | J14: F2
A15: band_count|3 bands | B15: band_count | C15: 3 bands | D15: 3 | E15: Low, middle, high. Big pockets; a problem at the edge may be diluted. | F15: whole number of bands | G15: 3 bands | H15: band_count|3 | J15: F3
A16: band_count|10 bands | B16: band_count | C16: 10 bands | D16: 10 | E16: Shows where a rate turns, but each band is a tenth of the book. | F16: whole number of bands | G16: 10 bands | H16: band_count|10 | J16: F4
A17: band_count|20 bands | B17: band_count | C17: 20 bands | D17: 20 | E17: Narrow bands, each a twentieth of the book. Needs a big book, or most pockets will be too small to test. | F17: whole number of bands | G17: 20 bands | H17: band_count|20
A18: band_cut|Each band holds about the same number of loans (recommended) | B18: band_cut | C18: Each band holds about the same number of loans (recommended) | E18: Every band can be tested equally well. Edges land on uneven numbers. | G18: Each band holds about the same number of loans
A19: band_cut|The same, snapped to round numbers | B19: band_cut | C19: The same, snapped to round numbers | E19: Edges on round numbers, easier to quote. Bands hold uneven counts. | G19: The same, snapped to round numbers
A20: min_loans|Enough for 5 expected losses (suggested) | B20: min_loans | C20: Enough for 5 expected losses (suggested) | E20: Worked out from this book: the loans a pocket needs to expect 5 with the outcome at the book's rate, the textbook floor for the usual test. | F20: whole number of loans | G20: Enough for 5 expected losses (suggested)
A21: min_loans|30 loans | B21: min_loans | C21: 30 loans | D21: 30 | E21: The old workbook's value. Smaller pockets get the exact test, which needs no minimum. | F21: whole number of loans | G21: 30 loans | H21: min_loans|30
A22: min_loans|100 loans | B22: min_loans | C22: 100 loans | D22: 100 | E22: Pockets under 100 loans get the exact test. | F22: whole number of loans | G22: 100 loans | H22: min_loans|100
A23: min_loans|300 loans | B23: min_loans | C23: 300 loans | D23: 300 | E23: Pockets under 300 loans get the exact test. | F23: whole number of loans | G23: 300 loans | H23: min_loans|300
A24: min_events|5 losses | B24: min_events | C24: 5 losses | D24: 5 | E24: The least the test can work with. Ranges will be wide. | F24: whole number of loans | G24: 5 losses | H24: min_events|5
A25: min_events|10 losses | B25: min_events | C25: 10 losses | D25: 10 | E25: A loss rate rests on how many loans lost money, not how many a pocket holds. Ten is a common floor. | F25: whole number of loans | G25: 10 losses | H25: min_events|10
A26: min_events|20 losses | B26: min_events | C26: 20 losses | D26: 20 | E26: Ranges narrow enough to rank pockets against each other. | F26: whole number of loans | G26: 20 losses | H26: min_events|20
A27: materiality|0.5% of the book's total losses | B27: materiality | C27: 0.5% of the book's total losses | E27: Catches small pockets as well as big ones. Excess is counted against whatever a pocket is judged against, below. | F27: a dollar amount of GCO | G27: 0.5% of the book's total losses
A28: materiality|1% of the book's total losses | B28: materiality | C28: 1% of the book's total losses | E28: Scales with the book, so the same setting works on any population. Excess is counted against whatever a pocket is judged against, below. | F28: a dollar amount of GCO | G28: 1% of the book's total losses
A29: materiality|2% of the book's total losses | B29: materiality | C29: 2% of the book's total losses | E29: Keeps pockets whose excess is over 2% of the book's losses. Excess is counted against whatever a pocket is judged against, below. | F29: a dollar amount of GCO | G29: 2% of the book's total losses
A30: materiality|5% of the book's total losses | B30: materiality | C30: 5% of the book's total losses | E30: Only pockets that move the total. Excess is counted against whatever a pocket is judged against, below. | F30: a dollar amount of GCO | G30: 5% of the book's total losses
A31: materiality|10% of the book's total losses | B31: materiality | C31: 10% of the book's total losses | E31: Only the few pockets that carry the book. Excess is counted against whatever a pocket is judged against, below. | F31: a dollar amount of GCO | G31: 10% of the book's total losses
A32: materiality|No floor | B32: materiality | C32: No floor | E32: Every pocket that tests worse is listed, however small. For spotting patterns rather than dollars. | F32: a dollar amount of GCO | G32: No floor
A33: compare_to|The rest of its band | B33: compare_to | C33: The rest of its band | E33: A pocket against the other segments in the same band. Both comparisons are printed; this one decides the flag. | G33: The rest of its band
A34: compare_to|The rest of the book | B34: compare_to | C34: The rest of the book | E34: The simplest story: does this pocket stand out overall? Both comparisons are printed; this one decides the flag. | G34: The rest of the book
A35: worse_at|The smallest significant gap in a typical pocket (suggested) | B35: worse_at | C35: The smallest significant gap in a typical pocket (suggested) | E35: From this book: the smallest gap a typical pocket can call significant, 1.96 standard errors at 95% (how far a pocket's rate typically lands from its true value). | F35: a multiple above 1, such as 1.4 | G35: The smallest significant gap in a typical pocket (suggested)
A36: worse_at|1.25 times | B36: worse_at | C36: 1.25 times | D36: 1.25 | E36: The old workbook's value. Moderate gaps; more pockets flagged. | F36: a multiple above 1, such as 1.4 | G36: 1.25 times | H36: worse_at|1.25
A37: worse_at|1.5 times | B37: worse_at | C37: 1.5 times | D37: 1.5 | E37: Half as bad again. | F37: a multiple above 1, such as 1.4 | G37: 1.5 times | H37: worse_at|1.5
A38: worse_at|2 times | B38: worse_at | C38: 2 times | D38: 2 | E38: Only pockets at double the rate or more. Few, and obvious. | F38: a multiple above 1, such as 1.4 | G38: 2 times | H38: worse_at|2
A39: better_at|The smallest significant gap in a typical pocket (suggested) | B39: better_at | C39: The smallest significant gap in a typical pocket (suggested) | E39: The same as above, the other way: one over the smallest gap a pocket of typical size can call significant. | F39: a multiple below 1, such as 0.7 | G39: The smallest significant gap in a typical pocket (suggested)
A40: better_at|0.8 times | B40: better_at | C40: 0.8 times | D40: 0.8 | E40: The old workbook's value. | F40: a multiple below 1, such as 0.7 | G40: 0.8 times | H40: better_at|0.8
A41: better_at|0.67 times | B41: better_at | C41: 0.67 times | D41: 0.67 | E41: A third better or more. | F41: a multiple below 1, such as 0.7 | G41: 0.67 times | H41: better_at|0.67
A42: better_at|0.5 times | B42: better_at | C42: 0.5 times | D42: 0.5 | E42: Half the rate or less. Few, and obvious. | F42: a multiple below 1, such as 0.7 | G42: 0.5 times | H42: better_at|0.5
A43: revenue_line|Each pocket's own test (suggested) | B43: revenue_line | C43: Each pocket's own test (suggested) | E43: Profit counts as keeping more or less only when the pocket's own test calls the gap significant. A small pocket needs a bigger gap. | F43: a number of points, such as 0.3 | G43: Each pocket's own test (suggested)
A44: revenue_line|0.25 points either way | B44: revenue_line | C44: 0.25 points either way | D44: 0.25 | E44: A point is 1% of booked dollars. A gap of a quarter point or more counts, and one that isn't significant says so. | F44: a number of points, such as 0.3 | G44: 0.25 points either way | H44: revenue_line|0.25
A45: revenue_line|0.5 points either way | B45: revenue_line | C45: 0.5 points either way | D45: 0.5 | E45: Only gaps of half a point of booked dollars or more count. | F45: a number of points, such as 0.3 | G45: 0.5 points either way | H45: revenue_line|0.5
A46: revenue_line|A gap as big as the materiality line | B46: revenue_line | C46: A gap as big as the materiality line | E46: Profit counts as keeping less when the pocket's shortfall against its comparison reaches the dollar line above, and as more when its surplus does. | F46: a number of points, such as 0.3 | G46: A gap as big as the materiality line
A47: confidence|90% sure | B47: confidence | C47: 90% sure | D47: 0.9 | E47: Finds more. About 1 in 10 pockets with no real difference will still pass. | F47: a share, such as 0.95 for 95% | G47: 90% sure | H47: confidence|0.9
A48: confidence|95% sure | B48: confidence | C48: 95% sure | D48: 0.95 | E48: The usual standard. About 1 pocket in 20 with no real difference will still pass. | F48: a share, such as 0.95 for 95% | G48: 95% sure | H48: confidence|0.95
A49: confidence|99% sure | B49: confidence | C49: 99% sure | D49: 0.99 | E49: Strict. About 1 in 100, and smaller real gaps will be missed. | F49: a share, such as 0.95 for 95% | G49: 99% sure | H49: confidence|0.99
A50: power|80% of the time (recommended) | B50: power | C50: 80% of the time (recommended) | D50: 0.8 | E50: The usual standard. Used only to say how big a gap each pocket's size could show; it never flags anything. | F50: a share, such as 0.8 for 80% | G50: 80% of the time | H50: power|0.8
A51: power|90% of the time | B51: power | C51: 90% of the time | D51: 0.9 | E51: Each pocket can vouch for larger gaps only. | F51: a share, such as 0.8 for 80% | G51: 90% of the time | H51: power|0.9
A52: power|50% of the time | B52: power | C52: 50% of the time | D52: 0.5 | E52: A coin toss. The smallest gap a pocket could possibly show. | F52: a share, such as 0.8 for 80% | G52: 50% of the time | H52: power|0.5
A53: many_tests|No allowance | B53: many_tests | C53: No allowance | E53: Each pocket is tested alone. Scan 200 pockets at 95% and about 10 will read significant with no real difference behind them. | G53: No allowance
A54: many_tests|Hold down the share of false finds (Benjamini-Hochberg) (recommended) | B54: many_tests | C54: Hold down the share of false finds (Benjamini-Hochberg) (recommended) | E54: Of the pockets that read significant, about 5% at 95% are expected to have no real difference behind them. Suits scanning for leads. | G54: Hold down the share of false finds (Benjamini-Hochberg)
A55: many_tests|Hold down the chance of any false find (Bonferroni) | B55: many_tests | C55: Hold down the chance of any false find (Bonferroni) | E55: The chance of even one pocket reading significant with no real difference is held to 5% at 95%. Very strict; suits a short list going to the LOB. | G55: Hold down the chance of any false find (Bonferroni)

Sheet _meanings
A1: Loan number (key) | B1: key | C1: loan or application number
A2: Booked amount | B2: booked | C2: booked or loan amount, which weights the reporting-level rates
A3: Outcome (yes/no) | B3: outcome | C3: the yes/no outcome: charged off, ever delinquent, decided by the system
A4: GCO dollars | B4: gco | C4: gross charge-off dollars
A5: RANR dollars | B5: ranr | C5: RANR dollars
A6: Origination date | B6: origination_date | C6: when the loan was made
A7: FICO score | B7: fico | C7: a FICO score
A8: Other score | B8: score | C8: a score not on the FICO scale (a custom or bank score)
A9: DTI-style ratio | B9: dti | C9: a debt-to-income style ratio
A10: LTV-style ratio | B10: ltv | C10: a loan-to-value style ratio
A11: Rate or APR | B11: rate | C11: interest rate or APR
A12: Term | B12: term | C12: loan term in months
... A19: Not sure yet | B19: unknown | C19: not known yet, so not cut by until you say what it is

Sheet _look
A1: columns | B1: FICO | C1: ORIG_BAL | D1: REV_DEBT | E1: SALES | F1: INCOME | G1: UTIL | H1: TENURE | I1: F1 | J1: F2 | K1: F3 | L1: F4 | M1: income_to_sales
A2: 250 | B2: slice from | C2: middle | D2: loans | G2: bar from | H2: bar loans | I2: chart label | J2: chart loans | K2: edge x | L2: edge y | M2: edge | N2: bar label | O2: slice from | P2: middle | Q2: loans | T2: bar from | U2: bar loans | V2: chart label | W2: chart loans | X2: edge x | Y2: edge y | Z2: edge | AA2: bar label | AB2: slice from | AC2: middle | AD2: loans | AG2: bar from | AH2: bar loans | AI2: chart label | AJ2: chart loans | AK2: edge x | AL2: edge y | AM2: edge | AN2: bar label | AO2: slice from | AP2: middle | AQ2: loans | AT2: bar from | AU2: bar loans | AV2: chart label | AW2: chart loans | AX2: edge x | AY2: edge y | AZ2: edge | BA2: bar label | BB2: slice from | BC2: middle | BD2: loans | BG2: bar from | BH2: bar loans | BI2: chart label | BJ2: chart loans | BK2: edge x | BL2: edge y | BM2: edge | BN2: bar label | BO2: slice from | BP2: middle | BQ2: loans | BT2: bar from | BU2: bar loans | BV2: chart label | BW2: chart loans | BX2: edge x | BY2: edge y | BZ2: edge | CA2: bar label | CB2: slice from | CC2: middle | CD2: loans | CG2: bar from | CH2: bar loans | CI2: chart label | CJ2: chart loans | CK2: edge x | CL2: edge y | CM2: edge | CN2: bar label | CO2: slice from | CP2: middle | CQ2: loans | CT2: bar from | CU2: bar loans | CV2: chart label | CW2: chart loans | CX2: edge x | CY2: edge y | CZ2: edge | DA2: bar label | DB2: slice from | DC2: middle | DD2: loans | DG2: bar from | DH2: bar loans | DI2: chart label | DJ2: chart loans | DK2: edge x | DL2: edge y | DM2: edge | DN2: bar label | DO2: slice from | DP2: middle | DQ2: loans | DT2: bar from | DU2: bar loans | DV2: chart label | DW2: chart loans | DX2: edge x | DY2: edge y | DZ2: edge | EA2: bar label | EB2: slice from | EC2: middle | ED2: loans | EG2: bar from | EH2: bar loans | EI2: chart label | EJ2: chart loans | EK2: edge x | EL2: edge y | EM2: edge | EN2: bar label | EO2: slice from | EP2: middle | EQ2: loans | ET2: bar from | EU2: bar loans | EV2: chart label | EW2: chart loans | EX2: edge x | EY2: edge y | EZ2: edge | FA2: bar label
A3: | | B3: FICO | O3: ORIG_BAL | AB3: REV_DEBT | AO3: SALES | BB3: INCOME | BO3: UTIL | CB3: TENURE | CO3: F1 | DB3: F2 | DO3: F3 | EB3: F4 | EO3: income_to_sales
A4: FICO:None:None:[-9999.0] | B4: 550 | C4: 550.75 | D4: 5 | E4: column | F4: FICO | G4: =IF(1<=$F$13,$F$14+(1-1)*$F$16,"") | H4: =IF(1>$F$13,"",SUMIFS($D$4:$D$203,$C$4:$C$203,">="&$G$4,$C$4:$C$203,IF(1=$F$13,"<=","<")&($G$4+$F$16))) | I4: ="" | J4: =IF(AND(1>=11-$F$17,1<=9),$F$18,0) | K4: =IFERROR(IF(AND($M$4>=$F$14,$M$4<=$F$15),10+0.5+100*($M$4-$F$14)/($F$15-$F$14),NA()),NA()) | L4: =IF(ISNA($K$4),NA(),0) | M4: =IFERROR(IF(LEFT(LOWER(TRIM($F$20)),5)="every",IF(((INT($F$11/VALUE(TRIM(MID(TRIM($F$20),6,99))))*VALUE(TRIM(MID(TRIM($F$20),6,99)))+VALUE(TRIM(MID(TRIM($F$20),6,99))))+0*VALUE(TRIM(MID(TRIM($F$20),6,99))))<=$F$12,((INT($F$11/VALUE(TRIM(MID(TRIM($F$20),6,99))))*VALUE(TRIM(MID(TRIM($F$20),6,99)))+VALUE(TRIM(MID(TRIM($F$20),6,99))))+0*VALUE(TRIM(MID(TRIM($F$20),6,99)))),NA()),VALUE(TRIM(MID(SUBSTITUTE(SUBSTITUTE(SUBSTITUTE(TRIM($F$20),",",";")," ",""),";",REPT(" ",99)),1,99)))),NA()) | N4: =IF($G$4="","",IFERROR(IF(ABS($G$4)>=1000000,ROUND($G$4/1000000,MAX(0,1-INT(LOG10($F$27/1000000))))&"M",IF(ABS($G$4)>=1000,ROUND($G$4/1000,MAX(0,1-INT(LOG10($F$27/1000))))&"k",TEXT($G$4,"#,##0"))),TEXT($G$4,"#,##0"))) | O4: 0 | P4: 150 | Q4: 0 | R4: column | S4: ORIG_BAL | T4: =IF(1<=$S$13,$S$14+(1-1)*$S$16,"") | U4: =IF(1>$S$13,"",SUMIFS($Q$4:$Q$203,$P$4:$P$203,">="&$T$4,$P$4:$P$203,IF(1=$S$13,"<=","<")&($T$4+$S$16))) | V4: ="" | W4: =IF(AND(1>=11-$S$17,1<=9),$S$18,0) | X4: =IFERROR(IF(AND($Z$4>=$S$14,$Z$4<=$S$15),10+0.5+100*($Z$4-$S$14)/($S$15-$S$14),NA()),NA()) | Y4: =IF(ISNA($X$4),NA(),0) | Z4: =IFERROR(IF(LEFT(LOWER(TRIM($S$20)),5)="every",IF(((INT($S$11/VALUE(TRIM(MID(TRIM($S$20),6,99))))*VALUE(TRIM(MID(TRIM($S$20),6,99)))+VALUE(TRIM(MID(TRIM($S$20),6,99))))+0*VALUE(TRIM(MID(TRIM($S$20),6,99))))<=$S$12,((INT($S$11/VALUE(TRIM(MID(TRIM($S$20),6,99))))*VALUE(TRIM(MID(TRIM($S$20),6,99)))+VALUE(TRIM(MID(TRIM($S$20),6,99))))+0*VALUE(TRIM(MID(TRIM($S$20),6,99)))),NA()),VALUE(TRIM(MID(SUBSTITUTE(SUBSTITUTE(SUBSTITUTE(TRIM($S$20),",",";")," ",""),";",REPT(" ",99)),1,99)))),NA()) | AA4: =IF($T$4="","",IFERROR(IF(ABS($T$4)>=1000000,ROUND($T$4/1000000,MAX(0,1-INT(LOG10($S$27/1000000))))&"M",IF(ABS($T$4)>=1000,ROUND($T$4/1000,MAX(0,1-INT(LOG10($S$27/1000))))&"k",TEXT($T$4,"#,##0"))),TEXT($T$4,"#,##0"))) | AB4: 0 | AC4: 75 | AD4: 161 | AE4: column | AF4: REV_DEBT | AG4: =IF(1<=$AF$13,$AF$14+(1-1)*$AF$16,"") | AH4: =IF(1>$AF$13,"",SUMIFS($AD$4:$AD$203,$AC$4:$AC$203,">="&$AG$4,$AC$4:$AC$203,IF(1=$AF$13,"<=","<")&($AG$4+$AF$16))) | AI4: ="" | AJ4: =IF(AND(1>=11-$AF$17,1<=9),$AF$18,0) | AK4: =IFERROR(IF(AND($AM$4>=$AF$14,$AM$4<=$AF$15),10+0.5+100*($AM$4-$AF$14)/($AF$15-$AF$14),NA()),NA()) | AL4: =IF(ISNA($AK$4),NA(),0) | AM4: =IFERROR(IF(LEFT(LOWER(TRIM($AF$20)),5)="every",IF(((INT($AF$11/VALUE(TRIM(MID(TRIM($AF$20),6,99))))*VALUE(TRIM(MID(TRIM($AF$20),6,99)))+VALUE(TRIM(MID(TRIM($AF$20),6,99))))+0*VALUE(TRIM(MID(TRIM($AF$20),6,99))))<=$AF$12,((INT($AF$11/VALUE(TRIM(MID(TRIM($AF$20),6,99))))*VALUE(TRIM(MID(TRIM($AF$20),6,99)))+VALUE(TRIM(MID(TRIM($AF$20),6,99))))+0*VALUE(TRIM(MID(TRIM($AF$20),6,99)))),NA()),VALUE(TRIM(MID(SUBSTITUTE(SUBSTITUTE(SUBSTITUTE(TRIM($AF$20),",",";")," ",""),";",REPT(" ",99)),1,99)))),NA()) | AN4: =IF($AG$4="","",IFERROR(IF(ABS($AG$4)>=1000000,ROUND($AG$4/1000000,MAX(0,1-INT(LOG10($AF$27/1000000))))&"M",IF(ABS($AG$4)>=1000,ROUND($AG$4/1000,MAX(0,1-INT(LOG10($AF$27/1000))))&"k",TEXT($AG$4,"#,##0"))),TEXT($AG$4,"#,##0"))) | AO4: 0 | AP4: 2000 | AQ4: 12 | AR4: column | AS4: SALES | AT4: =IF(1<=$AS$13,$AS$14+(1-1)*$AS$16,"") | AU4: =IF(1>$AS$13,"",SUMIFS($AQ$4:$AQ$203,$AP$4:$AP$203,">="&$AT$4,$AP$4:$AP$203,IF(1=$AS$13,"<=","<")&($AT$4+$AS$16))) | AV4: ="" | AW4: =IF(AND(1>=11-$AS$17,1<=9),$AS$18,0) | AX4: =IFERROR(IF(AND($AZ$4>=$AS$14,$AZ$4<=$AS$15),10+0.5+100*($AZ$4-$AS$14)/($AS$15-$AS$14),NA()),NA()) | AY4: =IF(ISNA($AX$4),NA(),0) | AZ4: =IFERROR(IF(LEFT(LOWER(TRIM($AS$20)),5)="every",IF(((INT($AS$11/VALUE(TRIM(MID(TRIM($AS$20),6,99))))*VALUE(TRIM(MID(TRIM($AS$20),6,99)))+VALUE(TRIM(MID(TRIM($AS$20),6,99))))+0*VALUE(TRIM(MID(TRIM($AS$20),6,99))))<=$AS$12,((INT($AS$11/VALUE(TRIM(MID(TRIM($AS$20),6,99))))*VALUE(TRIM(MID(TRIM($AS$20),6,99)))+VALUE(TRIM(MID(TRIM($AS$20),6,99))))+0*VALUE(TRIM(MID(TRIM($AS$20),6,99)))),NA()),VALUE(TRIM(MID(SUBSTITUTE(SUBSTITUTE(SUBSTITUTE(TRIM($AS$20),",",";")," ",""),";",REPT(" ",99)),1,99)))),NA()) | BA4: =IF($AT$4="","",IFERROR(IF(ABS($AT$4)>=1000000,ROUND($AT$4/1000000,MAX(0,1-INT(LOG10($AS$27/1000000))))&"M",IF(ABS($AT$4)>=1000,ROUND($AT$4/1000,MAX(0,1-INT(LOG10($AS$27/1000))))&"k",TEXT($AT$4,"#,##0"))),TEXT($AT$4,"#,##0"))) | BB4: 0 | BC4: 3500 | BD4: 15 | BE4: column | BF4: INCOME | BG4: =IF(1<=$BF$13,$BF$14+(1-1)*$BF$16,"") | BH4: =IF(1>$BF$13,"",SUMIFS($BD$4:$BD$203,$BC$4:$BC$203,">="&$BG$4,$BC$4:$BC$203,IF(1=$BF$13,"<=","<")&($BG$4+$BF$16))) | BI4: ="" | BJ4: =IF(AND(1>=11-$BF$17,1<=9),$BF$18,0) | BK4: =IFERROR(IF(AND($BM$4>=$BF$14,$BM$4<=$BF$15),10+0.5+100*($BM$4-$BF$14)/($BF$15-$BF$14),NA()),NA()) | BL4: =IF(ISNA($BK$4),NA(),0) | BM4: =IFERROR(IF(LEFT(LOWER(TRIM($BF$20)),5)="every",IF(((INT($BF$11/VALUE(TRIM(MID(TRIM($BF$20),6,99))))*VALUE(TRIM(MID(TRIM($BF$20),6,99)))+VALUE(TRIM(MID(TRIM($BF$20),6,99))))+0*VALUE(TRIM(MID(TRIM($BF$20),6,99))))<=$BF$12,((INT($BF$11/VALUE(TRIM(MID(TRIM($BF$20),6,99))))*VALUE(TRIM(MID(TRIM($BF$20),6,99)))+VALUE(TRIM(MID(TRIM($BF$20),6,99))))+0*VALUE(TRIM(MID(TRIM($BF$20),6,99)))),NA()),VALUE(TRIM(MID(SUBSTITUTE(SUBSTITUTE(SUBSTITUTE(TRIM($BF$20),",",";")," ",""),";",REPT(" ",99)),1,99)))),NA()) | BN4: =IF($BG$4="","",IFERROR(IF(ABS($BG$4)>=1000000,ROUND($BG$4/1000000,MAX(0,1-INT(LOG10($BF$27/1000000))))&"M",IF(ABS($BG$4)>=1000,ROUND($BG$4/1000,MAX(0,1-INT(LOG10($BF$27/1000))))&"k",TEXT($BG$4,"#,##0"))),TEXT($BG$4,"#,##0"))) | BO4: 0 | BP4: 0.003 | BQ4: 72 | BR4: column | BS4: UTIL | BT4: =IF(1<=$BS$13,$BS$14+(1-1)*$BS$16,"") | BU4: =IF(1>$BS$13,"",SUMIFS($BQ$4:$BQ$203,$BP$4:$BP$203,">="&$BT$4,$BP$4:$BP$203,IF(1=$BS$13,"<=","<")&($BT$4+$BS$16))) | BV4: ="" | BW4: =IF(AND(1>=11-$BS$17,1<=9),$BS$18,0) | BX4: =IFERROR(IF(AND($BZ$4>=$BS$14,$BZ$4<=$BS$15),10+0.5+100*($BZ$4-$BS$14)/($BS$15-$BS$14),NA()),NA()) | BY4: =IF(ISNA($BX$4),NA(),0) | BZ4: =IFERROR(IF(LEFT(LOWER(TRIM($BS$20)),5)="every",IF(((INT($BS$11/VALUE(TRIM(MID(TRIM($BS$20),6,99))))*VALUE(TRIM(MID(TRIM($BS$20),6,99)))+VALUE(TRIM(MID(TRIM($BS$20),6,99))))+0*VALUE(TRIM(MID(TRIM($BS$20),6,99))))<=$BS$12,((INT($BS$11/VALUE(TRIM(MID(TRIM($BS$20),6,99))))*VALUE(TRIM(MID(TRIM($BS$20),6,99)))+VALUE(TRIM(MID(TRIM($BS$20),6,99))))+0*VALUE(TRIM(MID(TRIM($BS$20),6,99)))),NA()),VALUE(TRIM(MID(SUBSTITUTE(SUBSTITUTE(SUBSTITUTE(TRIM($BS$20),",",";")," ",""),";",REPT(" ",99)),1,99)))),NA()) | CA4: =IF($BT$4="","",IFERROR(IF(ABS($BT$4)>=1000000,ROUND($BT$4/1000000,MAX(0,1-INT(LOG10($BS$27/1000000))))&"M",IF(ABS($BT$4)>=1000,ROUND($BT$4/1000,MAX(0,1-INT(LOG10($BS$27/1000))))&"k",TEXT($BT$4,"0.00"))),TEXT($BT$4,"0.00"))) | CB4: 0 | CC4: 0.075 | CD4: 290 | CE4: column | CF4: TENURE | CG4: =IF(1<=$CF$13,$CF$14+(1-1)*$CF$16,"") | CH4: =IF(1>$CF$13,"",SUMIFS($CD$4:$CD$203,$CC$4:$CC$203,">="&$CG$4,$CC$4:$CC$203,IF(1=$CF$13,"<=","<")&($CG$4+$CF$16))) | CI4: ="" | CJ4: =IF(AND(1>=11-$CF$17,1<=9),$CF$18,0) | CK4: =IFERROR(IF(AND($CM$4>=$CF$14,$CM$4<=$CF$15),10+0.5+100*($CM$4-$CF$14)/($CF$15-$CF$14),NA()),NA()) | CL4: =IF(ISNA($CK$4),NA(),0) | CM4: =IFERROR(IF(LEFT(LOWER(TRIM($CF$20)),5)="every",IF(((INT($CF$11/VALUE(TRIM(MID(TRIM($CF$20),6,99))))*VALUE(TRIM(MID(TRIM($CF$20),6,99)))+VALUE(TRIM(MID(TRIM($CF$20),6,99))))+0*VALUE(TRIM(MID(TRIM($CF$20),6,99))))<=$CF$12,((INT($CF$11/VALUE(TRIM(MID(TRIM($CF$20),6,99))))*VALUE(TRIM(MID(TRIM($CF$20),6,99)))+VALUE(TRIM(MID(TRIM($CF$20),6,99))))+0*VALUE(TRIM(MID(TRIM($CF$20),6,99)))),NA()),VALUE(TRIM(MID(SUBSTITUTE(SUBSTITUTE(SUBSTITUTE(TRIM($CF$20),",",";")," ",""),";",REPT(" ",99)),1,99)))),NA()) | CN4: =IF($CG$4="","",IFERROR(IF(ABS($CG$4)>=1000000,ROUND($CG$4/1000000,MAX(0,1-INT(LOG10($CF$27/1000000))))&"M",IF(ABS($CG$4)>=1000,ROUND($CG$4/1000,MAX(0,1-INT(LOG10($CF$27/1000))))&"k",TEXT($CG$4,"#,##0.0"))),TEXT($CG$4,"#,##0.0"))) | CO4: 10 | CP4: 10.2 | CQ4: 5 | CR4: column | CS4: F1 | CT4: =IF(1<=$CS$13,$CS$14+(1-1)*$CS$16,"") | CU4: =IF(1>$CS$13,"",SUMIFS($CQ$4:$CQ$203,$CP$4:$CP$203,">="&$CT$4,$CP$4:$CP$203,IF(1=$CS$13,"<=","<")&($CT$4+$CS$16))) | CV4: ="" | CW4: =IF(AND(1>=11-$CS$17,1<=9),$CS$18,0) | CX4: =IFERROR(IF(AND($CZ$4>=$CS$14,$CZ$4<=$CS$15),10+0.5+100*($CZ$4-$CS$14)/($CS$15-$CS$14),NA()),NA()) | CY4: =IF(ISNA($CX$4),NA(),0) | CZ4: =IFERROR(IF(LEFT(LOWER(TRIM($CS$20)),5)="every",IF(((INT($CS$11/VALUE(TRIM(MID(TRIM($CS$20),6,99))))*VALUE(TRIM(MID(TRIM($CS$20),6,99)))+VALUE(TRIM(MID(TRIM($CS$20),6,99))))+0*VALUE(TRIM(MID(TRIM($CS$20),6,99))))<=$CS$12,((INT($CS$11/VALUE(TRIM(MID(TRIM($CS$20),6,99))))*VALUE(TRIM(MID(TRIM($CS$20),6,99)))+VALUE(TRIM(MID(TRIM($CS$20),6,99))))+0*VALUE(TRIM(MID(TRIM($CS$20),6,99)))),NA()),VALUE(TRIM(MID(SUBSTITUTE(SUBSTITUTE(SUBSTITUTE(TRIM($CS$20),",",";")," ",""),";",REPT(" ",99)),1,99)))),NA()) | DA4: =IF($CT$4="","",IFERROR(IF(ABS($CT$4)>=1000000,ROUND($CT$4/1000000,MAX(0,1-INT(LOG10($CS$27/1000000))))&"M",IF(ABS($CT$4)>=1000,ROUND($CT$4/1000,MAX(0,1-INT(LOG10($CS$27/1000))))&"k",TEXT($CT$4,"#,##0"))),TEXT($CT$4,"#,##0"))) | DB4: 10 | DC4: 10.175 | DD4: 6 | DE4: column | DF4: F2 | DG4: =IF(1<=$DF$13,$DF$14+(1-1)*$DF$16,"") | DH4: =IF(1>$DF$13,"",SUMIFS($DD$4:$DD$203,$DC$4:$DC$203,">="&$DG$4,$DC$4:$DC$203,IF(1=$DF$13,"<=","<")&($DG$4+$DF$16))) | DI4: ="" | DJ4: =IF(AND(1>=11-$DF$17,1<=9),$DF$18,0) | DK4: =IFERROR(IF(AND($DM$4>=$DF$14,$DM$4<=$DF$15),10+0.5+100*($DM$4-$DF$14)/($DF$15-$DF$14),NA()),NA()) | DL4: =IF(ISNA($DK$4),NA(),0) | DM4: =IFERROR(IF(LEFT(LOWER(TRIM($DF$20)),5)="every",IF(((INT($DF$11/VALUE(TRIM(MID(TRIM($DF$20),6,99))))*VALUE(TRIM(MID(TRIM($DF$20),6,99)))+VALUE(TRIM(MID(TRIM($DF$20),6,99))))+0*VALUE(TRIM(MID(TRIM($DF$20),6,99))))<=$DF$12,((INT($DF$11/VALUE(TRIM(MID(TRIM($DF$20),6,99))))*VALUE(TRIM(MID(TRIM($DF$20),6,99)))+VALUE(TRIM(MID(TRIM($DF$20),6,99))))+0*VALUE(TRIM(MID(TRIM($DF$20),6,99)))),NA()),VALUE(TRIM(MID(SUBSTITUTE(SUBSTITUTE(SUBSTITUTE(TRIM($DF$20),",",";")," ",""),";",REPT(" ",99)),1,99)))),NA()) | DN4: =IF($DG$4="","",IFERROR(IF(ABS($DG$4)>=1000000,ROUND($DG$4/1000000,MAX(0,1-INT(LOG10($DF$27/1000000))))&"M",IF(ABS($DG$4)>=1000,ROUND($DG$4/1000,MAX(0,1-INT(LOG10($DF$27/1000))))&"k",TEXT($DG$4,"#,##0.0"))),TEXT($DG$4,"#,##0.0"))) | DO4: 7.5 | DP4: 7.5125 | DQ4: 4 | DR4: column | DS4: F3 | DT4: =IF(1<=$DS$13,$DS$14+(1-1)*$DS$16,"") | DU4: =IF(1>$DS$13,"",SUMIFS($DQ$4:$DQ$203,$DP$4:$DP$203,">="&$DT$4,$DP$4:$DP$203,IF(1=$DS$13,"<=","<")&($DT$4+$DS$16))) | DV4: ="" | DW4: =IF(AND(1>=11-$DS$17,1<=9),$DS$18,0) | DX4: =IFERROR(IF(AND($DZ$4>=$DS$14,$DZ$4<=$DS$15),10+0.5+100*($DZ$4-$DS$14)/($DS$15-$DS$14),NA()),NA()) | DY4: =IF(ISNA($DX$4),NA(),0) | DZ4: =IFERROR(IF(LEFT(LOWER(TRIM($DS$20)),5)="every",IF(((INT($DS$11/VALUE(TRIM(MID(TRIM($DS$20),6,99))))*VALUE(TRIM(MID(TRIM($DS$20),6,99)))+VALUE(TRIM(MID(TRIM($DS$20),6,99))))+0*VALUE(TRIM(MID(TRIM($DS$20),6,99))))<=$DS$12,((INT($DS$11/VALUE(TRIM(MID(TRIM($DS$20),6,99))))*VALUE(TRIM(MID(TRIM($DS$20),6,99)))+VALUE(TRIM(MID(TRIM($DS$20),6,99))))+0*VALUE(TRIM(MID(TRIM($DS$20),6,99)))),NA()),VALUE(TRIM(MID(SUBSTITUTE(SUBSTITUTE(SUBSTITUTE(TRIM($DS$20),",",";")," ",""),";",REPT(" ",99)),1,99)))),NA()) | EA4: =IF($DT$4="","",IFERROR(IF(ABS($DT$4)>=1000000,ROUND($DT$4/1000000,MAX(0,1-INT(LOG10($DS$27/1000000))))&"M",IF(ABS($DT$4)>=1000,ROUND($DT$4/1000,MAX(0,1-INT(LOG10($DS$27/1000))))&"k",TEXT($DT$4,"#,##0.0"))),TEXT($DT$4,"#,##0.0"))) | EB4: 0 | EC4: 0.25 | ED4: 45 | EE4: column | EF4: F4 | EG4: =IF(1<=$EF$13,$EF$14+(1-1)*$EF$16,"") | EH4: =IF(1>$EF$13,"",SUMIFS($ED$4:$ED$203,$EC$4:$EC$203,">="&$EG$4,$EC$4:$EC$203,IF(1=$EF$13,"<=","<")&($EG$4+$EF$16))) | EI4: ="" | EJ4: =IF(AND(1>=11-$EF$17,1<=9),$EF$18,0) | EK4: =IFERROR(IF(AND($EM$4>=$EF$14,$EM$4<=$EF$15),10+0.5+100*($EM$4-$EF$14)/($EF$15-$EF$14),NA()),NA()) | EL4: =IF(ISNA($EK$4),NA(),0) | EM4: =IFERROR(IF(LEFT(LOWER(TRIM($EF$20)),5)="every",IF(((INT($EF$11/VALUE(TRIM(MID(TRIM($EF$20),6,99))))*VALUE(TRIM(MID(TRIM($EF$20),6,99)))+VALUE(TRIM(MID(TRIM($EF$20),6,99))))+0*VALUE(TRIM(MID(TRIM($EF$20),6,99))))<=$EF$12,((INT($EF$11/VALUE(TRIM(MID(TRIM($EF$20),6,99))))*VALUE(TRIM(MID(TRIM($EF$20),6,99)))+VALUE(TRIM(MID(TRIM($EF$20),6,99))))+0*VALUE(TRIM(MID(TRIM($EF$20),6,99)))),NA()),VALUE(TRIM(MID(SUBSTITUTE(SUBSTITUTE(SUBSTITUTE(TRIM($EF$20),",",";")," ",""),";",REPT(" ",99)),1,99)))),NA()) | EN4: =IF($EG$4="","",IFERROR(IF(ABS($EG$4)>=1000000,ROUND($EG$4/1000000,MAX(0,1-INT(LOG10($EF$27/1000000))))&"M",IF(ABS($EG$4)>=1000,ROUND($EG$4/1000,MAX(0,1-INT(LOG10($EF$27/1000))))&"k",TEXT($EG$4,"#,##0"))),TEXT($EG$4,"#,##0"))) | EO4: 0 | EP4: 0.00875 | EQ4: 0 | ER4: column | ES4: income_to_sales | ET4: =IF(1<=$ES$13,$ES$14+(1-1)*$ES$16,"") | EU4: =IF(1>$ES$13,"",SUMIFS($EQ$4:$EQ$203,$EP$4:$EP$203,">="&$ET$4,$EP$4:$EP$203,IF(1=$ES$13,"<=","<")&($ET$4+$ES$16))) | EV4: ="" | EW4: =IF(AND(1>=11-$ES$17,1<=9),$ES$18,0) | EX4: =IFERROR(IF(AND($EZ$4>=$ES$14,$EZ$4<=$ES$15),10+0.5+100*($EZ$4-$ES$14)/($ES$15-$ES$14),NA()),NA()) | EY4: =IF(ISNA($EX$4),NA(),0) | EZ4: =IFERROR(IF(LEFT(LOWER(TRIM($ES$20)),5)="every",IF(((INT($ES$11/VALUE(TRIM(MID(TRIM($ES$20),6,99))))*VALUE(TRIM(MID(TRIM($ES$20),6,99)))+VALUE(TRIM(MID(TRIM($ES$20),6,99))))+0*VALUE(TRIM(MID(TRIM($ES$20),6,99))))<=$ES$12,((INT($ES$11/VALUE(TRIM(MID(TRIM($ES$20),6,99))))*VALUE(TRIM(MID(TRIM($ES$20),6,99)))+VALUE(TRIM(MID(TRIM($ES$20),6,99))))+0*VALUE(TRIM(MID(TRIM($ES$20),6,99)))),NA()),VALUE(TRIM(MID(SUBSTITUTE(SUBSTITUTE(SUBSTITUTE(TRIM($ES$20),",",";")," ",""),";",REPT(" ",99)),1,99)))),NA()) | FA4: =IF($ET$4="","",IFERROR(IF(ABS($ET$4)>=1000000,ROUND($ET$4/1000000,MAX(0,1-INT(LOG10($ES$27/1000000))))&"M",IF(ABS($ET$4)>=1000,ROUND($ET$4/1000,MAX(0,1-INT(LOG10($ES$27/1000))))&"k",TEXT($ET$4,"0.00"))),TEXT($ET$4,"0.00")))
B5: 551.5 | C5: 552.25 | D5: 0 | E5: slices from | F5: 550 | G5: =IF(2<=$F$13,$F$14+(2-1)*$F$16,"") | H5: =IF(2>$F$13,"",SUMIFS($D$4:$D$203,$C$4:$C$203,">="&$G$5,$C$4:$C$203,IF(2=$F$13,"<=","<")&($G$5+$F$16))) | I5: ="" | J5: =IF(AND(2>=11-$F$17,2<=9),$F$18,0) | K5: =IFERROR(IF(AND($M$4>=$F$14,$M$4<=$F$15),10+0.5+100*($M$4-$F$14)/($F$15-$F$14),NA()),NA()) | L5: =IF(ISNA($K$5),NA(),MAX($J$4:$J$123)) | M5: =IFERROR(IF(LEFT(LOWER(TRIM($F$20)),5)="every",IF(((INT($F$11/VALUE(TRIM(MID(TRIM($F$20),6,99))))*VALUE(TRIM(MID(TRIM($F$20),6,99)))+VALUE(TRIM(MID(TRIM($F$20),6,99))))+1*VALUE(TRIM(MID(TRIM($F$20),6,99))))<=$F$12,((INT($F$11/VALUE(TRIM(MID(TRIM($F$20),6,99))))*VALUE(TRIM(MID(TRIM($F$20),6,99)))+VALUE(TRIM(MID(TRIM($F$20),6,99))))+1*VALUE(TRIM(MID(TRIM($F$20),6,99)))),NA()),VALUE(TRIM(MID(SUBSTITUTE(SUBSTITUTE(SUBSTITUTE(TRIM($F$20),",",";")," ",""),";",REPT(" ",99)),100,99)))),NA()) | N5: =IF($G$5="","",IFERROR(IF(ABS($G$5)>=1000000,ROUND($G$5/1000000,MAX(0,1-INT(LOG10($F$27/1000000))))&"M",IF(ABS($G$5)>=1000,ROUND($G$5/1000,MAX(0,1-INT(LOG10($F$27/1000))))&"k",TEXT($G$5,"#,##0"))),TEXT($G$5,"#,##0"))) | O5: 300 | P5: 450 | Q5: 0 | R5: slices from | S5: 0 | T5: =IF(2<=$S$13,$S$14+(2-1)*$S$16,"") | U5: =IF(2>$S$13,"",SUMIFS($Q$4:$Q$203,$P$4:$P$203,">="&$T$5,$P$4:$P$203,IF(2=$S$13,"<=","<")&($T$5+$S$16))) | V5: ="" | W5: =IF(AND(2>=11-$S$17,2<=9),$S$18,0) | X5: =IFERROR(IF(AND($Z$4>=$S$14,$Z$4<=$S$15),10+0.5+100*($Z$4-$S$14)/($S$15-$S$14),NA()),NA()) | Y5: =IF(ISNA($X$5),NA(),MAX($W$4:$W$123)) | Z5: =IFERROR(IF(LEFT(LOWER(TRIM($S$20)),5)="every",IF(((INT($S$11/VALUE(TRIM(MID(TRIM($S$20),6,99))))*VALUE(TRIM(MID(TRIM($S$20),6,99)))+VALUE(TRIM(MID(TRIM($S$20),6,99))))+1*VALUE(TRIM(MID(TRIM($S$20),6,99))))<=$S$12,((INT($S$11/VALUE(TRIM(MID(TRIM($S$20),6,99))))*VALUE(TRIM(MID(TRIM($S$20),6,99)))+VALUE(TRIM(MID(TRIM($S$20),6,99))))+1*VALUE(TRIM(MID(TRIM($S$20),6,99)))),NA()),VALUE(TRIM(MID(SUBSTITUTE(SUBSTITUTE(SUBSTITUTE(TRIM($S$20),",",";")," ",""),";",REPT(" ",99)),100,99)))),NA()) | AA5: =IF($T$5="","",IFERROR(IF(ABS($T$5)>=1000000,ROUND($T$5/1000000,MAX(0,1-INT(LOG10($S$27/1000000))))&"M",IF(ABS($T$5)>=1000,ROUND($T$5/1000,MAX(0,1-INT(LOG10($S$27/1000))))&"k",TEXT($T$5,"#,##0"))),TEXT($T$5,"#,##0"))) | AB5: 150 | AC5: 225 | AD5: 17 | AE5: slices from | AF5: 0 | AG5: =IF(2<=$AF$13,$AF$14+(2-1)*$AF$16,"") | AH5: =IF(2>$AF$13,"",SUMIFS($AD$4:$AD$203,$AC$4:$AC$203,">="&$AG$5,$AC$4:$AC$203,IF(2=$AF$13,"<=","<")&($AG$5+$AF$16))) | AI5: ="" | AJ5: =IF(AND(2>=11-$AF$17,2<=9),$AF$18,0) | AK5: =IFERROR(IF(AND($AM$4>=$AF$14,$AM$4<=$AF$15),10+0.5+100*($AM$4-$AF$14)/($AF$15-$AF$14),NA()),NA()) | AL5: =IF(ISNA($AK$5),NA(),MAX($AJ$4:$AJ$123)) | AM5: =IFERROR(IF(LEFT(LOWER(TRIM($AF$20)),5)="every",IF(((INT($AF$11/VALUE(TRIM(MID(TRIM($AF$20),6,99))))*VALUE(TRIM(MID(TRIM($AF$20),6,99)))+VALUE(TRIM(MID(TRIM($AF$20),6,99))))+1*VALUE(TRIM(MID(TRIM($AF$20),6,99))))<=$AF$12,((INT($AF$11/VALUE(TRIM(MID(TRIM($AF$20),6,99))))*VALUE(TRIM(MID(TRIM($AF$20),6,99)))+VALUE(TRIM(MID(TRIM($AF$20),6,99))))+1*VALUE(TRIM(MID(TRIM($AF$20),6,99)))),NA()),VALUE(TRIM(MID(SUBSTITUTE(SUBSTITUTE(SUBSTITUTE(TRIM($AF$20),",",";")," ",""),";",REPT(" ",99)),100,99)))),NA()) | AN5: =IF($AG$5="","",IFERROR(IF(ABS($AG$5)>=1000000,ROUND($AG$5/1000000,MAX(0,1-INT(LOG10($AF$27/1000000))))&"M",IF(ABS($AG$5)>=1000,ROUND($AG$5/1000,MAX(0,1-INT(LOG10($AF$27/1000))))&"k",TEXT($AG$5,"#,##0"))),TEXT($AG$5,"#,##0"))) | AO5: 4000 | AP5: 6000 | AQ5: 0 | AR5: slices from | AS5: 0 | AT5: =IF(2<=$AS$13,$AS$14+(2-1)*$AS$16,"") | AU5: =IF(2>$AS$13,"",SUMIFS($AQ$4:$AQ$203,$AP$4:$AP$203,">="&$AT$5,$AP$4:$AP$203,IF(2=$AS$13,"<=","<")&($AT$5+$AS$16))) | AV5: ="" | AW5: =IF(AND(2>=11-$AS$17,2<=9),$AS$18,0) | AX5: =IFERROR(IF(AND($AZ$4>=$AS$14,$AZ$4<=$AS$15),10+0.5+100*($AZ$4-$AS$14)/($AS$15-$AS$14),NA()),NA()) | AY5: =IF(ISNA($AX$5),NA(),MAX($AW$4:$AW$123)) | AZ5: =IFERROR(IF(LEFT(LOWER(TRIM($AS$20)),5)="every",IF(((INT($AS$11/VALUE(TRIM(MID(TRIM($AS$20),6,99))))*VALUE(TRIM(MID(TRIM($AS$20),6,99)))+VALUE(TRIM(MID(TRIM($AS$20),6,99))))+1*VALUE(TRIM(MID(TRIM($AS$20),6,99))))<=$AS$12,((INT($AS$11/VALUE(TRIM(MID(TRIM($AS$20),6,99))))*VALUE(TRIM(MID(TRIM($AS$20),6,99)))+VALUE(TRIM(MID(TRIM($AS$20),6,99))))+1*VALUE(TRIM(MID(TRIM($AS$20),6,99)))),NA()),VALUE(TRIM(MID(SUBSTITUTE(SUBSTITUTE(SUBSTITUTE(TRIM($AS$20),",",";")," ",""),";",REPT(" ",99)),100,99)))),NA()) | BA5: =IF($AT$5="","",IFERROR(IF(ABS($AT$5)>=1000000,ROUND($AT$5/1000000,MAX(0,1-INT(LOG10($AS$27/1000000))))&"M",IF(ABS($AT$5)>=1000,ROUND($AT$5/1000,MAX(0,1-INT(LOG10($AS$27/1000))))&"k",TEXT($AT$5,"#,##0"))),TEXT($AT$5,"#,##0"))) | BB5: 7000 | BC5: 10500 | BD5: 95 | BE5: slices from | BF5: 0 | BG5: =IF(2<=$BF$13,$BF$14+(2-1)*$BF$16,"") | BH5: =IF(2>$BF$13,"",SUMIFS($BD$4:$BD$203,$BC$4:$BC$203,">="&$BG$5,$BC$4:$BC$203,IF(2=$BF$13,"<=","<")&($BG$5+$BF$16))) | BI5: ="" | BJ5: =IF(AND(2>=11-$BF$17,2<=9),$BF$18,0) | BK5: =IFERROR(IF(AND($BM$4>=$BF$14,$BM$4<=$BF$15),10+0.5+100*($BM$4-$BF$14)/($BF$15-$BF$14),NA()),NA()) | BL5: =IF(ISNA($BK$5),NA(),MAX($BJ$4:$BJ$123)) | BM5: =IFERROR(IF(LEFT(LOWER(TRIM($BF$20)),5)="every",IF(((INT($BF$11/VALUE(TRIM(MID(TRIM($BF$20),6,99))))*VALUE(TRIM(MID(TRIM($BF$20),6,99)))+VALUE(TRIM(MID(TRIM($BF$20),6,99))))+1*VALUE(TRIM(MID(TRIM($BF$20),6,99))))<=$BF$12,((INT($BF$11/VALUE(TRIM(MID(TRIM($BF$20),6,99))))*VALUE(TRIM(MID(TRIM($BF$20),6,99)))+VALUE(TRIM(MID(TRIM($BF$20),6,99))))+1*VALUE(TRIM(MID(TRIM($BF$20),6,99)))),NA()),VALUE(TRIM(MID(SUBSTITUTE(SUBSTITUTE(SUBSTITUTE(TRIM($BF$20),",",";")," ",""),";",REPT(" ",99)),100,99)))),NA()) | BN5: =IF($BG$5="","",IFERROR(IF(ABS($BG$5)>=1000000,ROUND($BG$5/1000000,MAX(0,1-INT(LOG10($BF$27/1000000))))&"M",IF(ABS($BG$5)>=1000,ROUND($BG$5/1000,MAX(0,1-INT(LOG10($BF$27/1000))))&"k",TEXT($BG$5,"#,##0"))),TEXT($BG$5,"#,##0"))) | BO5: 0.006 | BP5: 0.009 | BQ5: 56 | BR5: slices from | BS5: 0 | BT5: =IF(2<=$BS$13,$BS$14+(2-1)*$BS$16,"") | BU5: =IF(2>$BS$13,"",SUMIFS($BQ$4:$BQ$203,$BP$4:$BP$203,">="&$BT$5,$BP$4:$BP$203,IF(2=$BS$13,"<=","<")&($BT$5+$BS$16))) | BV5: ="" | BW5: =IF(AND(2>=11-$BS$17,2<=9),$BS$18,0) | BX5: =IFERROR(IF(AND($BZ$4>=$BS$14,$BZ$4<=$BS$15),10+0.5+100*($BZ$4-$BS$14)/($BS$15-$BS$14),NA()),NA()) | BY5: =IF(ISNA($BX$5),NA(),MAX($BW$4:$BW$123)) | BZ5: =IFERROR(IF(LEFT(LOWER(TRIM($BS$20)),5)="every",IF(((INT($BS$11/VALUE(TRIM(MID(TRIM($BS$20),6,99))))*VALUE(TRIM(MID(TRIM($BS$20),6,99)))+VALUE(TRIM(MID(TRIM($BS$20),6,99))))+1*VALUE(TRIM(MID(TRIM($BS$20),6,99))))<=$BS$12,((INT($BS$11/VALUE(TRIM(MID(TRIM($BS$20),6,99))))*VALUE(TRIM(MID(TRIM($BS$20),6,99)))+VALUE(TRIM(MID(TRIM($BS$20),6,99))))+1*VALUE(TRIM(MID(TRIM($BS$20),6,99)))),NA()),VALUE(TRIM(MID(SUBSTITUTE(SUBSTITUTE(SUBSTITUTE(TRIM($BS$20),",",";")," ",""),";",REPT(" ",99)),100,99)))),NA()) | CA5: =IF($BT$5="","",IFERROR(IF(ABS($BT$5)>=1000000,ROUND($BT$5/1000000,MAX(0,1-INT(LOG10($BS$27/1000000))))&"M",IF(ABS($BT$5)>=1000,ROUND($BT$5/1000,MAX(0,1-INT(LOG10($BS$27/1000))))&"k",TEXT($BT$5,"0.00"))),TEXT($BT$5,"0.00"))) | CB5: 0.15 | CC5: 0.225 | CD5: 210 | CE5: slices from | CF5: 0 | CG5: =IF(2<=$CF$13,$CF$14+(2-1)*$CF$16,"") | CH5: =IF(2>$CF$13,"",SUMIFS($CD$4:$CD$203,$CC$4:$CC$203,">="&$CG$5,$CC$4:$CC$203,IF(2=$CF$13,"<=","<")&($CG$5+$CF$16))) | CI5: ="" | CJ5: =IF(AND(2>=11-$CF$17,2<=9),$CF$18,0) | CK5: =IFERROR(IF(AND($CM$4>=$CF$14,$CM$4<=$CF$15),10+0.5+100*($CM$4-$CF$14)/($CF$15-$CF$14),NA()),NA()) | CL5: =IF(ISNA($CK$5),NA(),MAX($CJ$4:$CJ$123)) | CM5: =IFERROR(IF(LEFT(LOWER(TRIM($CF$20)),5)="every",IF(((INT($CF$11/VALUE(TRIM(MID(TRIM($CF$20),6,99))))*VALUE(TRIM(MID(TRIM($CF$20),6,99)))+VALUE(TRIM(MID(TRIM($CF$20),6,99))))+1*VALUE(TRIM(MID(TRIM($CF$20),6,99))))<=$CF$12,((INT($CF$11/VALUE(TRIM(MID(TRIM($CF$20),6,99))))*VALUE(TRIM(MID(TRIM($CF$20),6,99)))+VALUE(TRIM(MID(TRIM($CF$20),6,99))))+1*VALUE(TRIM(MID(TRIM($CF$20),6,99)))),NA()),VALUE(TRIM(MID(SUBSTITUTE(SUBSTITUTE(SUBSTITUTE(TRIM($CF$20),",",";")," ",""),";",REPT(" ",99)),100,99)))),NA()) | CN5: =IF($CG$5="","",IFERROR(IF(ABS($CG$5)>=1000000,ROUND($CG$5/1000000,MAX(0,1-INT(LOG10($CF$27/1000000))))&"M",IF(ABS($CG$5)>=1000,ROUND($CG$5/1000,MAX(0,1-INT(LOG10($CF$27/1000))))&"k",TEXT($CG$5,"#,##0.0"))),TEXT($CG$5,"#,##0.0"))) | CO5: 10.4 | CP5: 10.6 | CQ5: 1 | CR5: slices from | CS5: 10 | CT5: =IF(2<=$CS$13,$CS$14+(2-1)*$CS$16,"") | CU5: =IF(2>$CS$13,"",SUMIFS($CQ$4:$CQ$203,$CP$4:$CP$203,">="&$CT$5,$CP$4:$CP$203,IF(2=$CS$13,"<=","<")&($CT$5+$CS$16))) | CV5: ="" | CW5: =IF(AND(2>=11-$CS$17,2<=9),$CS$18,0) | CX5: =IFERROR(IF(AND($CZ$4>=$CS$14,$CZ$4<=$CS$15),10+0.5+100*($CZ$4-$CS$14)/($CS$15-$CS$14),NA()),NA()) | CY5: =IF(ISNA($CX$5),NA(),MAX($CW$4:$CW$123)) | CZ5: =IFERROR(IF(LEFT(LOWER(TRIM($CS$20)),5)="every",IF(((INT($CS$11/VALUE(TRIM(MID(TRIM($CS$20),6,99))))*VALUE(TRIM(MID(TRIM($CS$20),6,99)))+VALUE(TRIM(MID(TRIM($CS$20),6,99))))+1*VALUE(TRIM(MID(TRIM($CS$20),6,99))))<=$CS$12,((INT($CS$11/VALUE(TRIM(MID(TRIM($CS$20),6,99))))*VALUE(TRIM(MID(TRIM($CS$20),6,99)))+VALUE(TRIM(MID(TRIM($CS$20),6,99))))+1*VALUE(TRIM(MID(TRIM($CS$20),6,99)))),NA()),VALUE(TRIM(MID(SUBSTITUTE(SUBSTITUTE(SUBSTITUTE(TRIM($CS$20),",",";")," ",""),";",REPT(" ",99)),100,99)))),NA()) | DA5: =IF($CT$5="","",IFERROR(IF(ABS($CT$5)>=1000000,ROUND($CT$5/1000000,MAX(0,1-INT(LOG10($CS$27/1000000))))&"M",IF(ABS($CT$5)>=1000,ROUND($CT$5/1000,MAX(0,1-INT(LOG10($CS$27/1000))))&"k",TEXT($CT$5,"#,##0"))),TEXT($CT$5,"#,##0"))) | DB5: 10.35 | DC5: 10.525 | DD5: 5 | DE5: slices from | DF5: 10 | DG5: =IF(2<=$DF$13,$DF$14+(2-1)*$DF$16,"") | DH5: =IF(2>$DF$13,"",SUMIFS($DD$4:$DD$203,$DC$4:$DC$203,">="&$DG$5,$DC$4:$DC$203,IF(2=$DF$13,"<=","<")&($DG$5+$DF$16))) | DI5: ="" | DJ5: =IF(AND(2>=11-$DF$17,2<=9),$DF$18,0) | DK5: =IFERROR(IF(AND($DM$4>=$DF$14,$DM$4<=$DF$15),10+0.5+100*($DM$4-$DF$14)/($DF$15-$DF$14),NA()),NA()) | DL5: =IF(ISNA($DK$5),NA(),MAX($DJ$4:$DJ$123)) | DM5: =IFERROR(IF(LEFT(LOWER(TRIM($DF$20)),5)="every",IF(((INT($DF$11/VALUE(TRIM(MID(TRIM($DF$20),6,99))))*VALUE(TRIM(MID(TRIM($DF$20),6,99)))+VALUE(TRIM(MID(TRIM($DF$20),6,99))))+1*VALUE(TRIM(MID(TRIM($DF$20),6,99))))<=$DF$12,((INT($DF$11/VALUE(TRIM(MID(TRIM($DF$20),6,99))))*VALUE(TRIM(MID(TRIM($DF$20),6,99)))+VALUE(TRIM(MID(TRIM($DF$20),6,99))))+1*VALUE(TRIM(MID(TRIM($DF$20),6,99)))),NA()),VALUE(TRIM(MID(SUBSTITUTE(SUBSTITUTE(SUBSTITUTE(TRIM($DF$20),",",";")," ",""),";",REPT(" ",99)),100,99)))),NA()) | DN5: =IF($DG$5="","",IFERROR(IF(ABS($DG$5)>=1000000,ROUND($DG$5/1000000,MAX(0,1-INT(LOG10($DF$27/1000000))))&"M",IF(ABS($DG$5)>=1000,ROUND($DG$5/1000,MAX(0,1-INT(LOG10($DF$27/1000))))&"k",TEXT($DG$5,"#,##0.0"))),TEXT($DG$5,"#,##0.0"))) | DO5: 7.525 | DP5: 7.5375 | DQ5: 4 | DR5: slices from | DS5: 7.5 | DT5: =IF(2<=$DS$13,$DS$14+(2-1)*$DS$16,"") | DU5: =IF(2>$DS$13,"",SUMIFS($DQ$4:$DQ$203,$DP$4:$DP$203,">="&$DT$5,$DP$4:$DP$203,IF(2=$DS$13,"<=","<")&($DT$5+$DS$16))) | DV5: ="" | DW5: =IF(AND(2>=11-$DS$17,2<=9),$DS$18,0) | DX5: =IFERROR(IF(AND($DZ$4>=$DS$14,$DZ$4<=$DS$15),10+0.5+100*($DZ$4-$DS$14)/($DS$15-$DS$14),NA()),NA()) | DY5: =IF(ISNA($DX$5),NA(),MAX($DW$4:$DW$123)) | DZ5: =IFERROR(IF(LEFT(LOWER(TRIM($DS$20)),5)="every",IF(((INT($DS$11/VALUE(TRIM(MID(TRIM($DS$20),6,99))))*VALUE(TRIM(MID(TRIM($DS$20),6,99)))+VALUE(TRIM(MID(TRIM($DS$20),6,99))))+1*VALUE(TRIM(MID(TRIM($DS$20),6,99))))<=$DS$12,((INT($DS$11/VALUE(TRIM(MID(TRIM($DS$20),6,99))))*VALUE(TRIM(MID(TRIM($DS$20),6,99)))+VALUE(TRIM(MID(TRIM($DS$20),6,99))))+1*VALUE(TRIM(MID(TRIM($DS$20),6,99)))),NA()),VALUE(TRIM(MID(SUBSTITUTE(SUBSTITUTE(SUBSTITUTE(TRIM($DS$20),",",";")," ",""),";",REPT(" ",99)),100,99)))),NA()) | EA5: =IF($DT$5="","",IFERROR(IF(ABS($DT$5)>=1000000,ROUND($DT$5/1000000,MAX(0,1-INT(LOG10($DS$27/1000000))))&"M",IF(ABS($DT$5)>=1000,ROUND($DT$5/1000,MAX(0,1-INT(LOG10($DS$27/1000))))&"k",TEXT($DT$5,"#,##0.0"))),TEXT($DT$5,"#,##0.0"))) | EB5: 0.5 | EC5: 0.75 | ED5: 61 | EE5: slices from | EF5: 0 | EG5: =IF(2<=$EF$13,$EF$14+(2-1)*$EF$16,"") | EH5: =IF(2>$EF$13,"",SUMIFS($ED$4:$ED$203,$EC$4:$EC$203,">="&$EG$5,$EC$4:$EC$203,IF(2=$EF$13,"<=","<")&($EG$5+$EF$16))) | EI5: ="" | EJ5: =IF(AND(2>=11-$EF$17,2<=9),$EF$18,0) | EK5: =IFERROR(IF(AND($EM$4>=$EF$14,$EM$4<=$EF$15),10+0.5+100*($EM$4-$EF$14)/($EF$15-$EF$14),NA()),NA()) | EL5: =IF(ISNA($EK$5),NA(),MAX($EJ$4:$EJ$123)) | EM5: =IFERROR(IF(LEFT(LOWER(TRIM($EF$20)),5)="every",IF(((INT($EF$11/VALUE(TRIM(MID(TRIM($EF$20),6,99))))*VALUE(TRIM(MID(TRIM($EF$20),6,99)))+VALUE(TRIM(MID(TRIM($EF$20),6,99))))+1*VALUE(TRIM(MID(TRIM($EF$20),6,99))))<=$EF$12,((INT($EF$11/VALUE(TRIM(MID(TRIM($EF$20),6,99))))*VALUE(TRIM(MID(TRIM($EF$20),6,99)))+VALUE(TRIM(MID(TRIM($EF$20),6,99))))+1*VALUE(TRIM(MID(TRIM($EF$20),6,99)))),NA()),VALUE(TRIM(MID(SUBSTITUTE(SUBSTITUTE(SUBSTITUTE(TRIM($EF$20),",",";")," ",""),";",REPT(" ",99)),100,99)))),NA()) | EN5: =IF($EG$5="","",IFERROR(IF(ABS($EG$5)>=1000000,ROUND($EG$5/1000000,MAX(0,1-INT(LOG10($EF$27/1000000))))&"M",IF(ABS($EG$5)>=1000,ROUND($EG$5/1000,MAX(0,1-INT(LOG10($EF$27/1000))))&"k",TEXT($EG$5,"#,##0"))),TEXT($EG$5,"#,##0"))) | EO5: 0.0175 | EP5: 0.02625 | EQ5: 5 | ER5: slices from | ES5: 0 | ET5: =IF(2<=$ES$13,$ES$14+(2-1)*$ES$16,"") | EU5: =IF(2>$ES$13,"",SUMIFS($EQ$4:$EQ$203,$EP$4:$EP$203,">="&$ET$5,$EP$4:$EP$203,IF(2=$ES$13,"<=","<")&($ET$5+$ES$16))) | EV5: ="" | EW5: =IF(AND(2>=11-$ES$17,2<=9),$ES$18,0) | EX5: =IFERROR(IF(AND($EZ$4>=$ES$14,$EZ$4<=$ES$15),10+0.5+100*($EZ$4-$ES$14)/($ES$15-$ES$14),NA()),NA()) | EY5: =IF(ISNA($EX$5),NA(),MAX($EW$4:$EW$123)) | EZ5: =IFERROR(IF(LEFT(LOWER(TRIM($ES$20)),5)="every",IF(((INT($ES$11/VALUE(TRIM(MID(TRIM($ES$20),6,99))))*VALUE(TRIM(MID(TRIM($ES$20),6,99)))+VALUE(TRIM(MID(TRIM($ES$20),6,99))))+1*VALUE(TRIM(MID(TRIM($ES$20),6,99))))<=$ES$12,((INT($ES$11/VALUE(TRIM(MID(TRIM($ES$20),6,99))))*VALUE(TRIM(MID(TRIM($ES$20),6,99)))+VALUE(TRIM(MID(TRIM($ES$20),6,99))))+1*VALUE(TRIM(MID(TRIM($ES$20),6,99)))),NA()),VALUE(TRIM(MID(SUBSTITUTE(SUBSTITUTE(SUBSTITUTE(TRIM($ES$20),",",";")," ",""),";",REPT(" ",99)),100,99)))),NA()) | FA5: =IF($ET$5="","",IFERROR(IF(ABS($ET$5)>=1000000,ROUND($ET$5/1000000,MAX(0,1-INT(LOG10($ES$27/1000000))))&"M",IF(ABS($ET$5)>=1000,ROUND($ET$5/1000,MAX(0,1-INT(LOG10($ES$27/1000))))&"k",TEXT($ET$5,"0.00"))),TEXT($ET$5,"0.00")))
B6: 553 | C6: 553.75 | D6: 7 | E6: slices to | F6: 850 | G6: =IF(3<=$F$13,$F$14+(3-1)*$F$16,"") | H6: =IF(3>$F$13,"",SUMIFS($D$4:$D$203,$C$4:$C$203,">="&$G$6,$C$4:$C$203,IF(3=$F$13,"<=","<")&($G$6+$F$16))) | I6: ="" | J6: =IF(AND(3>=11-$F$17,3<=9),$F$18,0) | K6: =IFERROR(IF(AND($M$5>=$F$14,$M$5<=$F$15),10+0.5+100*($M$5-$F$14)/($F$15-$F$14),NA()),NA()) | L6: =IF(ISNA($K$6),NA(),0) | M6: =IFERROR(IF(LEFT(LOWER(TRIM($F$20)),5)="every",IF(((INT($F$11/VALUE(TRIM(MID(TRIM($F$20),6,99))))*VALUE(TRIM(MID(TRIM($F$20),6,99)))+VALUE(TRIM(MID(TRIM($F$20),6,99))))+2*VALUE(TRIM(MID(TRIM($F$20),6,99))))<=$F$12,((INT($F$11/VALUE(TRIM(MID(TRIM($F$20),6,99))))*VALUE(TRIM(MID(TRIM($F$20),6,99)))+VALUE(TRIM(MID(TRIM($F$20),6,99))))+2*VALUE(TRIM(MID(TRIM($F$20),6,99)))),NA()),VALUE(TRIM(MID(SUBSTITUTE(SUBSTITUTE(SUBSTITUTE(TRIM($F$20),",",";")," ",""),";",REPT(" ",99)),199,99)))),NA()) | N6: =IF($G$6="","",IFERROR(IF(ABS($G$6)>=1000000,ROUND($G$6/1000000,MAX(0,1-INT(LOG10($F$27/1000000))))&"M",IF(ABS($G$6)>=1000,ROUND($G$6/1000,MAX(0,1-INT(LOG10($F$27/1000))))&"k",TEXT($G$6,"#,##0"))),TEXT($G$6,"#,##0"))) | O6: 600 | P6: 750 | Q6: 0 | R6: slices to | S6: 60000 | T6: =IF(3<=$S$13,$S$14+(3-1)*$S$16,"") | U6: =IF(3>$S$13,"",SUMIFS($Q$4:$Q$203,$P$4:$P$203,">="&$T$6,$P$4:$P$203,IF(3=$S$13,"<=","<")&($T$6+$S$16))) | V6: ="" | W6: =IF(AND(3>=11-$S$17,3<=9),$S$18,0) | X6: =IFERROR(IF(AND($Z$5>=$S$14,$Z$5<=$S$15),10+0.5+100*($Z$5-$S$14)/($S$15-$S$14),NA()),NA()) | Y6: =IF(ISNA($X$6),NA(),0) | Z6: =IFERROR(IF(LEFT(LOWER(TRIM($S$20)),5)="every",IF(((INT($S$11/VALUE(TRIM(MID(TRIM($S$20),6,99))))*VALUE(TRIM(MID(TRIM($S$20),6,99)))+VALUE(TRIM(MID(TRIM($S$20),6,99))))+2*VALUE(TRIM(MID(TRIM($S$20),6,99))))<=$S$12,((INT($S$11/VALUE(TRIM(MID(TRIM($S$20),6,99))))*VALUE(TRIM(MID(TRIM($S$20),6,99)))+VALUE(TRIM(MID(TRIM($S$20),6,99))))+2*VALUE(TRIM(MID(TRIM($S$20),6,99)))),NA()),VALUE(TRIM(MID(SUBSTITUTE(SUBSTITUTE(SUBSTITUTE(TRIM($S$20),",",";")," ",""),";",REPT(" ",99)),199,99)))),NA()) | AA6: =IF($T$6="","",IFERROR(IF(ABS($T$6)>=1000000,ROUND($T$6/1000000,MAX(0,1-INT(LOG10($S$27/1000000))))&"M",IF(ABS($T$6)>=1000,ROUND($T$6/1000,MAX(0,1-INT(LOG10($S$27/1000))))&"k",TEXT($T$6,"#,##0"))),TEXT($T$6,"#,##0"))) | AB6: 300 | AC6: 375 | AD6: 12 | AE6: slices to | AF6: 30000 | AG6: =IF(3<=$AF$13,$AF$14+(3-1)*$AF$16,"") | AH6: =IF(3>$AF$13,"",SUMIFS($AD$4:$AD$203,$AC$4:$AC$203,">="&$AG$6,$AC$4:$AC$203,IF(3=$AF$13,"<=","<")&($AG$6+$AF$16))) | AI6: ="" | AJ6: =IF(AND(3>=11-$AF$17,3<=9),$AF$18,0) | AK6: =IFERROR(IF(AND($AM$5>=$AF$14,$AM$5<=$AF$15),10+0.5+100*($AM$5-$AF$14)/($AF$15-$AF$14),NA()),NA()) | AL6: =IF(ISNA($AK$6),NA(),0) | AM6: =IFERROR(IF(LEFT(LOWER(TRIM($AF$20)),5)="every",IF(((INT($AF$11/VALUE(TRIM(MID(TRIM($AF$20),6,99))))*VALUE(TRIM(MID(TRIM($AF$20),6,99)))+VALUE(TRIM(MID(TRIM($AF$20),6,99))))+2*VALUE(TRIM(MID(TRIM($AF$20),6,99))))<=$AF$12,((INT($AF$11/VALUE(TRIM(MID(TRIM($AF$20),6,99))))*VALUE(TRIM(MID(TRIM($AF$20),6,99)))+VALUE(TRIM(MID(TRIM($AF$20),6,99))))+2*VALUE(TRIM(MID(TRIM($AF$20),6,99)))),NA()),VALUE(TRIM(MID(SUBSTITUTE(SUBSTITUTE(SUBSTITUTE(TRIM($AF$20),",",";")," ",""),";",REPT(" ",99)),199,99)))),NA()) | AN6: =IF($AG$6="","",IFERROR(IF(ABS($AG$6)>=1000000,ROUND($AG$6/1000000,MAX(0,1-INT(LOG10($AF$27/1000000))))&"M",IF(ABS($AG$6)>=1000,ROUND($AG$6/1000,MAX(0,1-INT(LOG10($AF$27/1000))))&"k",TEXT($AG$6,"#,##0"))),TEXT($AG$6,"#,##0"))) | AO6: 8000 | AP6: 10000 | AQ6: 0 | AR6: slices to | AS6: 800000 | AT6: =IF(3<=$AS$13,$AS$14+(3-1)*$AS$16,"") | AU6: =IF(3>$AS$13,"",SUMIFS($AQ$4:$AQ$203,$AP$4:$AP$203,">="&$AT$6,$AP$4:$AP$203,IF(3=$AS$13,"<=","<")&($AT$6+$AS$16))) | AV6: ="" | AW6: =IF(AND(3>=11-$AS$17,3<=9),$AS$18,0) | AX6: =IFERROR(IF(AND($AZ$5>=$AS$14,$AZ$5<=$AS$15),10+0.5+100*($AZ$5-$AS$14)/($AS$15-$AS$14),NA()),NA()) | AY6: =IF(ISNA($AX$6),NA(),0) | AZ6: =IFERROR(IF(LEFT(LOWER(TRIM($AS$20)),5)="every",IF(((INT($AS$11/VALUE(TRIM(MID(TRIM($AS$20),6,99))))*VALUE(TRIM(MID(TRIM($AS$20),6,99)))+VALUE(TRIM(MID(TRIM($AS$20),6,99))))+2*VALUE(TRIM(MID(TRIM($AS$20),6,99))))<=$AS$12,((INT($AS$11/VALUE(TRIM(MID(TRIM($AS$20),6,99))))*VALUE(TRIM(MID(TRIM($AS$20),6,99)))+VALUE(TRIM(MID(TRIM($AS$20),6,99))))+2*VALUE(TRIM(MID(TRIM($AS$20),6,99)))),NA()),VALUE(TRIM(MID(SUBSTITUTE(SUBSTITUTE(SUBSTITUTE(TRIM($AS$20),",",";")," ",""),";",REPT(" ",99)),199,99)))),NA()) | BA6: =IF($AT$6="","",IFERROR(IF(ABS($AT$6)>=1000000,ROUND($AT$6/1000000,MAX(0,1-INT(LOG10($AS$27/1000000))))&"M",IF(ABS($AT$6)>=1000,ROUND($AT$6/1000,MAX(0,1-INT(LOG10($AS$27/1000))))&"k",TEXT($AT$6,"#,##0"))),TEXT($AT$6,"#,##0"))) | BB6: 14000 | BC6: 17500 | BD6: 221 | BE6: slices to | BF6: 1400000 | BG6: =IF(3<=$BF$13,$BF$14+(3-1)*$BF$16,"") | BH6: =IF(3>$BF$13,"",SUMIFS($BD$4:$BD$203,$BC$4:$BC$203,">="&$BG$6,$BC$4:$BC$203,IF(3=$BF$13,"<=","<")&($BG$6+$BF$16))) | BI6: ="" | BJ6: =IF(AND(3>=11-$BF$17,3<=9),$BF$18,0) | BK6: =IFERROR(IF(AND($BM$5>=$BF$14,$BM$5<=$BF$15),10+0.5+100*($BM$5-$BF$14)/($BF$15-$BF$14),NA()),NA()) | BL6: =IF(ISNA($BK$6),NA(),0) | BM6: =IFERROR(IF(LEFT(LOWER(TRIM($BF$20)),5)="every",IF(((INT($BF$11/VALUE(TRIM(MID(TRIM($BF$20),6,99))))*VALUE(TRIM(MID(TRIM($BF$20),6,99)))+VALUE(TRIM(MID(TRIM($BF$20),6,99))))+2*VALUE(TRIM(MID(TRIM($BF$20),6,99))))<=$BF$12,((INT($BF$11/VALUE(TRIM(MID(TRIM($BF$20),6,99))))*VALUE(TRIM(MID(TRIM($BF$20),6,99)))+VALUE(TRIM(MID(TRIM($BF$20),6,99))))+2*VALUE(TRIM(MID(TRIM($BF$20),6,99)))),NA()),VALUE(TRIM(MID(SUBSTITUTE(SUBSTITUTE(SUBSTITUTE(TRIM($BF$20),",",";")," ",""),";",REPT(" ",99)),199,99)))),NA()) | BN6: =IF($BG$6="","",IFERROR(IF(ABS($BG$6)>=1000000,ROUND($BG$6/1000000,MAX(0,1-INT(LOG10($BF$27/1000000))))&"M",IF(ABS($BG$6)>=1000,ROUND($BG$6/1000,MAX(0,1-INT(LOG10($BF$27/1000))))&"k",TEXT($BG$6,"#,##0"))),TEXT($BG$6,"#,##0"))) | BO6: 0.012 | BP6: 0.015 | BQ6: 74 | BR6: slices to | BS6: 1.2 | BT6: =IF(3<=$BS$13,$BS$14+(3-1)*$BS$16,"") | BU6: =IF(3>$BS$13,"",SUMIFS($BQ$4:$BQ$203,$BP$4:$BP$203,">="&$BT$6,$BP$4:$BP$203,IF(3=$BS$13,"<=","<")&($BT$6+$BS$16))) | BV6: ="" | BW6: =IF(AND(3>=11-$BS$17,3<=9),$BS$18,0) | BX6: =IFERROR(IF(AND($BZ$5>=$BS$14,$BZ$5<=$BS$15),10+0.5+100*($BZ$5-$BS$14)/($BS$15-$BS$14),NA()),NA()) | BY6: =IF(ISNA($BX$6),NA(),0) | BZ6: =IFERROR(IF(LEFT(LOWER(TRIM($BS$20)),5)="every",IF(((INT($BS$11/VALUE(TRIM(MID(TRIM($BS$20),6,99))))*VALUE(TRIM(MID(TRIM($BS$20),6,99)))+VALUE(TRIM(MID(TRIM($BS$20),6,99))))+2*VALUE(TRIM(MID(TRIM($BS$20),6,99))))<=$BS$12,((INT($BS$11/VALUE(TRIM(MID(TRIM($BS$20),6,99))))*VALUE(TRIM(MID(TRIM($BS$20),6,99)))+VALUE(TRIM(MID(TRIM($BS$20),6,99))))+2*VALUE(TRIM(MID(TRIM($BS$20),6,99)))),NA()),VALUE(TRIM(MID(SUBSTITUTE(SUBSTITUTE(SUBSTITUTE(TRIM($BS$20),",",";")," ",""),";",REPT(" ",99)),199,99)))),NA()) | CA6: =IF($BT$6="","",IFERROR(IF(ABS($BT$6)>=1000000,ROUND($BT$6/1000000,MAX(0,1-INT(LOG10($BS$27/1000000))))&"M",IF(ABS($BT$6)>=1000,ROUND($BT$6/1000,MAX(0,1-INT(LOG10($BS$27/1000))))&"k",TEXT($BT$6,"0.00"))),TEXT($BT$6,"0.00"))) | CB6: 0.3 | CC6: 0.375 | CD6: 358 | CE6: slices to | CF6: 30 | CG6: =IF(3<=$CF$13,$CF$14+(3-1)*$CF$16,"") | CH6: =IF(3>$CF$13,"",SUMIFS($CD$4:$CD$203,$CC$4:$CC$203,">="&$CG$6,$CC$4:$CC$203,IF(3=$CF$13,"<=","<")&($CG$6+$CF$16))) | CI6: ="" | CJ6: =IF(AND(3>=11-$CF$17,3<=9),$CF$18,0) | CK6: =IFERROR(IF(AND($CM$5>=$CF$14,$CM$5<=$CF$15),10+0.5+100*($CM$5-$CF$14)/($CF$15-$CF$14),NA()),NA()) | CL6: =IF(ISNA($CK$6),NA(),0) | CM6: =IFERROR(IF(LEFT(LOWER(TRIM($CF$20)),5)="every",IF(((INT($CF$11/VALUE(TRIM(MID(TRIM($CF$20),6,99))))*VALUE(TRIM(MID(TRIM($CF$20),6,99)))+VALUE(TRIM(MID(TRIM($CF$20),6,99))))+2*VALUE(TRIM(MID(TRIM($CF$20),6,99))))<=$CF$12,((INT($CF$11/VALUE(TRIM(MID(TRIM($CF$20),6,99))))*VALUE(TRIM(MID(TRIM($CF$20),6,99)))+VALUE(TRIM(MID(TRIM($CF$20),6,99))))+2*VALUE(TRIM(MID(TRIM($CF$20),6,99)))),NA()),VALUE(TRIM(MID(SUBSTITUTE(SUBSTITUTE(SUBSTITUTE(TRIM($CF$20),",",";")," ",""),";",REPT(" ",99)),199,99)))),NA()) | CN6: =IF($CG$6="","",IFERROR(IF(ABS($CG$6)>=1000000,ROUND($CG$6/1000000,MAX(0,1-INT(LOG10($CF$27/1000000))))&"M",IF(ABS($CG$6)>=1000,ROUND($CG$6/1000,MAX(0,1-INT(LOG10($CF$27/1000))))&"k",TEXT($CG$6,"#,##0.0"))),TEXT($CG$6,"#,##0.0"))) | CO6: 10.8 | CP6: 11 | CQ6: 6 | CR6: slices to | CS6: 90 | CT6: =IF(3<=$CS$13,$CS$14+(3-1)*$CS$16,"") | CU6: =IF(3>$CS$13,"",SUMIFS($CQ$4:$CQ$203,$CP$4:$CP$203,">="&$CT$6,$CP$4:$CP$203,IF(3=$CS$13,"<=","<")&($CT$6+$CS$16))) | CV6: ="" | CW6: =IF(AND(3>=11-$CS$17,3<=9),$CS$18,0) | CX6: =IFERROR(IF(AND($CZ$5>=$CS$14,$CZ$5<=$CS$15),10+0.5+100*($CZ$5-$CS$14)/($CS$15-$CS$14),NA()),NA()) | CY6: =IF(ISNA($CX$6),NA(),0) | CZ6: =IFERROR(IF(LEFT(LOWER(TRIM($CS$20)),5)="every",IF(((INT($CS$11/VALUE(TRIM(MID(TRIM($CS$20),6,99))))*VALUE(TRIM(MID(TRIM($CS$20),6,99)))+VALUE(TRIM(MID(TRIM($CS$20),6,99))))+2*VALUE(TRIM(MID(TRIM($CS$20),6,99))))<=$CS$12,((INT($CS$11/VALUE(TRIM(MID(TRIM($CS$20),6,99))))*VALUE(TRIM(MID(TRIM($CS$20),6,99)))+VALUE(TRIM(MID(TRIM($CS$20),6,99))))+2*VALUE(TRIM(MID(TRIM($CS$20),6,99)))),NA()),VALUE(TRIM(MID(SUBSTITUTE(SUBSTITUTE(SUBSTITUTE(TRIM($CS$20),",",";")," ",""),";",REPT(" ",99)),199,99)))),NA()) | DA6: =IF($CT$6="","",IFERROR(IF(ABS($CT$6)>=1000000,ROUND($CT$6/1000000,MAX(0,1-INT(LOG10($CS$27/1000000))))&"M",IF(ABS($CT$6)>=1000,ROUND($CT$6/1000,MAX(0,1-INT(LOG10($CS$27/1000))))&"k",TEXT($CT$6,"#,##0"))),TEXT($CT$6,"#,##0"))) | DB6: 10.7 | DC6: 10.875 | DD6: 7 | DE6: slices to | DF6: 80 | DG6: =IF(3<=$DF$13,$DF$14+(3-1)*$DF$16,"") | DH6: =IF(3>$DF$13,"",SUMIFS($DD$4:$DD$203,$DC$4:$DC$203,">="&$DG$6,$DC$4:$DC$203,IF(3=$DF$13,"<=","<")&($DG$6+$DF$16))) | DI6: ="" | DJ6: =IF(AND(3>=11-$DF$17,3<=9),$DF$18,0) | DK6: =IFERROR(IF(AND($DM$5>=$DF$14,$DM$5<=$DF$15),10+0.5+100*($DM$5-$DF$14)/($DF$15-$DF$14),NA()),NA()) | DL6: =IF(ISNA($DK$6),NA(),0) | DM6: =IFERROR(IF(LEFT(LOWER(TRIM($DF$20)),5)="every",IF(((INT($DF$11/VALUE(TRIM(MID(TRIM($DF$20),6,99))))*VALUE(TRIM(MID(TRIM($DF$20),6,99)))+VALUE(TRIM(MID(TRIM($DF$20),6,99))))+2*VALUE(TRIM(MID(TRIM($DF$20),6,99))))<=$DF$12,((INT($DF$11/VALUE(TRIM(MID(TRIM($DF$20),6,99))))*VALUE(TRIM(MID(TRIM($DF$20),6,99)))+VALUE(TRIM(MID(TRIM($DF$20),6,99))))+2*VALUE(TRIM(MID(TRIM($DF$20),6,99)))),NA()),VALUE(TRIM(MID(SUBSTITUTE(SUBSTITUTE(SUBSTITUTE(TRIM($DF$20),",",";")," ",""),";",REPT(" ",99)),199,99)))),NA()) | DN6: =IF($DG$6="","",IFERROR(IF(ABS($DG$6)>=1000000,ROUND($DG$6/1000000,MAX(0,1-INT(LOG10($DF$27/1000000))))&"M",IF(ABS($DG$6)>=1000,ROUND($DG$6/1000,MAX(0,1-INT(LOG10($DF$27/1000))))&"k",TEXT($DG$6,"#,##0.0"))),TEXT($DG$6,"#,##0.0"))) | DO6: 7.55 | DP6: 7.5625 | DQ6: 7 | DR6: slices to | DS6: 12.5 | DT6: =IF(3<=$DS$13,$DS$14+(3-1)*$DS$16,"") | DU6: =IF(3>$DS$13,"",SUMIFS($DQ$4:$DQ$203,$DP$4:$DP$203,">="&$DT$6,$DP$4:$DP$203,IF(3=$DS$13,"<=","<")&($DT$6+$DS$16))) | DV6: ="" | DW6: =IF(AND(3>=11-$DS$17,3<=9),$DS$18,0) | DX6: =IFERROR(IF(AND($DZ$5>=$DS$14,$DZ$5<=$DS$15),10+0.5+100*($DZ$5-$DS$14)/($DS$15-$DS$14),NA()),NA()) | DY6: =IF(ISNA($DX$6),NA(),0) | DZ6: =IFERROR(IF(LEFT(LOWER(TRIM($DS$20)),5)="every",IF(((INT($DS$11/VALUE(TRIM(MID(TRIM($DS$20),6,99))))*VALUE(TRIM(MID(TRIM($DS$20),6,99)))+VALUE(TRIM(MID(TRIM($DS$20),6,99))))+2*VALUE(TRIM(MID(TRIM($DS$20),6,99))))<=$DS$12,((INT($DS$11/VALUE(TRIM(MID(TRIM($DS$20),6,99))))*VALUE(TRIM(MID(TRIM($DS$20),6,99)))+VALUE(TRIM(MID(TRIM($DS$20),6,99))))+2*VALUE(TRIM(MID(TRIM($DS$20),6,99)))),NA()),VALUE(TRIM(MID(SUBSTITUTE(SUBSTITUTE(SUBSTITUTE(TRIM($DS$20),",",";")," ",""),";",REPT(" ",99)),199,99)))),NA()) | EA6: =IF($DT$6="","",IFERROR(IF(ABS($DT$6)>=1000000,ROUND($DT$6/1000000,MAX(0,1-INT(LOG10($DS$27/1000000))))&"M",IF(ABS($DT$6)>=1000,ROUND($DT$6/1000,MAX(0,1-INT(LOG10($DS$27/1000))))&"k",TEXT($DT$6,"#,##0.0"))),TEXT($DT$6,"#,##0.0"))) | EB6: 1 | EC6: 1.25 | ED6: 70 | EE6: slices to | EF6: 100 | EG6: =IF(3<=$EF$13,$EF$14+(3-1)*$EF$16,"") | EH6: =IF(3>$EF$13,"",SUMIFS($ED$4:$ED$203,$EC$4:$EC$203,">="&$EG$6,$EC$4:$EC$203,IF(3=$EF$13,"<=","<")&($EG$6+$EF$16))) | EI6: ="" | EJ6: =IF(AND(3>=11-$EF$17,3<=9),$EF$18,0) | EK6: =IFERROR(IF(AND($EM$5>=$EF$14,$EM$5<=$EF$15),10+0.5+100*($EM$5-$EF$14)/($EF$15-$EF$14),NA()),NA()) | EL6: =IF(ISNA($EK$6),NA(),0) | EM6: =IFERROR(IF(LEFT(LOWER(TRIM($EF$20)),5)="every",IF(((INT($EF$11/VALUE(TRIM(MID(TRIM($EF$20),6,99))))*VALUE(TRIM(MID(TRIM($EF$20),6,99)))+VALUE(TRIM(MID(TRIM($EF$20),6,99))))+2*VALUE(TRIM(MID(TRIM($EF$20),6,99))))<=$EF$12,((INT($EF$11/VALUE(TRIM(MID(TRIM($EF$20),6,99))))*VALUE(TRIM(MID(TRIM($EF$20),6,99)))+VALUE(TRIM(MID(TRIM($EF$20),6,99))))+2*VALUE(TRIM(MID(TRIM($EF$20),6,99)))),NA()),VALUE(TRIM(MID(SUBSTITUTE(SUBSTITUTE(SUBSTITUTE(TRIM($EF$20),",",";")," ",""),";",REPT(" ",99)),199,99)))),NA()) | EN6: =IF($EG$6="","",IFERROR(IF(ABS($EG$6)>=1000000,ROUND($EG$6/1000000,MAX(0,1-INT(LOG10($EF$27/1000000))))&"M",IF(ABS($EG$6)>=1000,ROUND($EG$6/1000,MAX(0,1-INT(LOG10($EF$27/1000))))&"k",TEXT($EG$6,"#,##0"))),TEXT($EG$6,"#,##0"))) | EO6: 0.035 | EP6: 0.04375 | EQ6: 25 | ER6: slices to | ES6: 3.5 | ET6: =IF(3<=$ES$13,$ES$14+(3-1)*$ES$16,"") | EU6: =IF(3>$ES$13,"",SUMIFS($EQ$4:$EQ$203,$EP$4:$EP$203,">="&$ET$6,$EP$4:$EP$203,IF(3=$ES$13,"<=","<")&($ET$6+$ES$16))) | EV6: ="" | EW6: =IF(AND(3>=11-$ES$17,3<=9),$ES$18,0) | EX6: =IFERROR(IF(AND($EZ$5>=$ES$14,$EZ$5<=$ES$15),10+0.5+100*($EZ$5-$ES$14)/($ES$15-$ES$14),NA()),NA()) | EY6: =IF(ISNA($EX$6),NA(),0) | EZ6: =IFERROR(IF(LEFT(LOWER(TRIM($ES$20)),5)="every",IF(((INT($ES$11/VALUE(TRIM(MID(TRIM($ES$20),6,99))))*VALUE(TRIM(MID(TRIM($ES$20),6,99)))+VALUE(TRIM(MID(TRIM($ES$20),6,99))))+2*VALUE(TRIM(MID(TRIM($ES$20),6,99))))<=$ES$12,((INT($ES$11/VALUE(TRIM(MID(TRIM($ES$20),6,99))))*VALUE(TRIM(MID(TRIM($ES$20),6,99)))+VALUE(TRIM(MID(TRIM($ES$20),6,99))))+2*VALUE(TRIM(MID(TRIM($ES$20),6,99)))),NA()),VALUE(TRIM(MID(SUBSTITUTE(SUBSTITUTE(SUBSTITUTE(TRIM($ES$20),",",";")," ",""),";",REPT(" ",99)),199,99)))),NA()) | FA6: =IF($ET$6="","",IFERROR(IF(ABS($ET$6)>=1000000,ROUND($ET$6/1000000,MAX(0,1-INT(LOG10($ES$27/1000000))))&"M",IF(ABS($ET$6)>=1000,ROUND($ET$6/1000,MAX(0,1-INT(LOG10($ES$27/1000))))&"k",TEXT($ET$6,"0.00"))),TEXT($ET$6,"0.00")))
B7: 554.5 | C7: 555.25 | D7: 1 | E7: loans below the slices | F7: 26 | G7: =IF(4<=$F$13,$F$14+(4-1)*$F$16,"") | H7: =IF(4>$F$13,"",SUMIFS($D$4:$D$203,$C$4:$C$203,">="&$G$7,$C$4:$C$203,IF(4=$F$13,"<=","<")&($G$7+$F$16))) | I7: ="" | J7: =IF(AND(4>=11-$F$17,4<=9),$F$18,0) | K7: =IFERROR(IF(AND($M$5>=$F$14,$M$5<=$F$15),10+0.5+100*($M$5-$F$14)/($F$15-$F$14),NA()),NA()) | L7: =IF(ISNA($K$7),NA(),MAX($J$4:$J$123)) | M7: =IFERROR(IF(LEFT(LOWER(TRIM($F$20)),5)="every",IF(((INT($F$11/VALUE(TRIM(MID(TRIM($F$20),6,99))))*VALUE(TRIM(MID(TRIM($F$20),6,99)))+VALUE(TRIM(MID(TRIM($F$20),6,99))))+3*VALUE(TRIM(MID(TRIM($F$20),6,99))))<=$F$12,((INT($F$11/VALUE(TRIM(MID(TRIM($F$20),6,99))))*VALUE(TRIM(MID(TRIM($F$20),6,99)))+VALUE(TRIM(MID(TRIM($F$20),6,99))))+3*VALUE(TRIM(MID(TRIM($F$20),6,99)))),NA()),VALUE(TRIM(MID(SUBSTITUTE(SUBSTITUTE(SUBSTITUTE(TRIM($F$20),",",";")," ",""),";",REPT(" ",99)),298,99)))),NA()) | N7: =IF($G$7="","",IFERROR(IF(ABS($G$7)>=1000000,ROUND($G$7/1000000,MAX(0,1-INT(LOG10($F$27/1000000))))&"M",IF(ABS($G$7)>=1000,ROUND($G$7/1000,MAX(0,1-INT(LOG10($F$27/1000))))&"k",TEXT($G$7,"#,##0"))),TEXT($G$7,"#,##0"))) | O7: 900 | P7: 1050 | Q7: 0 | R7: loans below the slices | S7: 0 | T7: =IF(4<=$S$13,$S$14+(4-1)*$S$16,"") | U7: =IF(4>$S$13,"",SUMIFS($Q$4:$Q$203,$P$4:$P$203,">="&$T$7,$P$4:$P$203,IF(4=$S$13,"<=","<")&($T$7+$S$16))) | V7: ="" | W7: =IF(AND(4>=11-$S$17,4<=9),$S$18,0) | X7: =IFERROR(IF(AND($Z$5>=$S$14,$Z$5<=$S$15),10+0.5+100*($Z$5-$S$14)/($S$15-$S$14),NA()),NA()) | Y7: =IF(ISNA($X$7),NA(),MAX($W$4:$W$123)) | Z7: =IFERROR(IF(LEFT(LOWER(TRIM($S$20)),5)="every",IF(((INT($S$11/VALUE(TRIM(MID(TRIM($S$20),6,99))))*VALUE(TRIM(MID(TRIM($S$20),6,99)))+VALUE(TRIM(MID(TRIM($S$20),6,99))))+3*VALUE(TRIM(MID(TRIM($S$20),6,99))))<=$S$12,((INT($S$11/VALUE(TRIM(MID(TRIM($S$20),6,99))))*VALUE(TRIM(MID(TRIM($S$20),6,99)))+VALUE(TRIM(MID(TRIM($S$20),6,99))))+3*VALUE(TRIM(MID(TRIM($S$20),6,99)))),NA()),VALUE(TRIM(MID(SUBSTITUTE(SUBSTITUTE(SUBSTITUTE(TRIM($S$20),",",";")," ",""),";",REPT(" ",99)),298,99)))),NA()) | AA7: =IF($T$7="","",IFERROR(IF(ABS($T$7)>=1000000,ROUND($T$7/1000000,MAX(0,1-INT(LOG10($S$27/1000000))))&"M",IF(ABS($T$7)>=1000,ROUND($T$7/1000,MAX(0,1-INT(LOG10($S$27/1000))))&"k",TEXT($T$7,"#,##0"))),TEXT($T$7,"#,##0"))) | AB7: 450 | AC7: 525 | AD7: 25 | AE7: loans below the slices | AF7: 0 | AG7: =IF(4<=$AF$13,$AF$14+(4-1)*$AF$16,"") | AH7: =IF(4>$AF$13,"",SUMIFS($AD$4:$AD$203,$AC$4:$AC$203,">="&$AG$7,$AC$4:$AC$203,IF(4=$AF$13,"<=","<")&($AG$7+$AF$16))) | AI7: ="" | AJ7: =IF(AND(4>=11-$AF$17,4<=9),$AF$18,0) | AK7: =IFERROR(IF(AND($AM$5>=$AF$14,$AM$5<=$AF$15),10+0.5+100*($AM$5-$AF$14)/($AF$15-$AF$14),NA()),NA()) | AL7: =IF(ISNA($AK$7),NA(),MAX($AJ$4:$AJ$123)) | AM7: =IFERROR(IF(LEFT(LOWER(TRIM($AF$20)),5)="every",IF(((INT($AF$11/VALUE(TRIM(MID(TRIM($AF$20),6,99))))*VALUE(TRIM(MID(TRIM($AF$20),6,99)))+VALUE(TRIM(MID(TRIM($AF$20),6,99))))+3*VALUE(TRIM(MID(TRIM($AF$20),6,99))))<=$AF$12,((INT($AF$11/VALUE(TRIM(MID(TRIM($AF$20),6,99))))*VALUE(TRIM(MID(TRIM($AF$20),6,99)))+VALUE(TRIM(MID(TRIM($AF$20),6,99))))+3*VALUE(TRIM(MID(TRIM($AF$20),6,99)))),NA()),VALUE(TRIM(MID(SUBSTITUTE(SUBSTITUTE(SUBSTITUTE(TRIM($AF$20),",",";")," ",""),";",REPT(" ",99)),298,99)))),NA()) | AN7: =IF($AG$7="","",IFERROR(IF(ABS($AG$7)>=1000000,ROUND($AG$7/1000000,MAX(0,1-INT(LOG10($AF$27/1000000))))&"M",IF(ABS($AG$7)>=1000,ROUND($AG$7/1000,MAX(0,1-INT(LOG10($AF$27/1000))))&"k",TEXT($AG$7,"#,##0"))),TEXT($AG$7,"#,##0"))) | AO7: 12000 | AP7: 14000 | AQ7: 0 | AR7: loans below the slices | AS7: 0 | AT7: =IF(4<=$AS$13,$AS$14+(4-1)*$AS$16,"") | AU7: =IF(4>$AS$13,"",SUMIFS($AQ$4:$AQ$203,$AP$4:$AP$203,">="&$AT$7,$AP$4:$AP$203,IF(4=$AS$13,"<=","<")&($AT$7+$AS$16))) | AV7: ="" | AW7: =IF(AND(4>=11-$AS$17,4<=9),$AS$18,0) | AX7: =IFERROR(IF(AND($AZ$5>=$AS$14,$AZ$5<=$AS$15),10+0.5+100*($AZ$5-$AS$14)/($AS$15-$AS$14),NA()),NA()) | AY7: =IF(ISNA($AX$7),NA(),MAX($AW$4:$AW$123)) | AZ7: =IFERROR(IF(LEFT(LOWER(TRIM($AS$20)),5)="every",IF(((INT($AS$11/VALUE(TRIM(MID(TRIM($AS$20),6,99))))*VALUE(TRIM(MID(TRIM($AS$20),6,99)))+VALUE(TRIM(MID(TRIM($AS$20),6,99))))+3*VALUE(TRIM(MID(TRIM($AS$20),6,99))))<=$AS$12,((INT($AS$11/VALUE(TRIM(MID(TRIM($AS$20),6,99))))*VALUE(TRIM(MID(TRIM($AS$20),6,99)))+VALUE(TRIM(MID(TRIM($AS$20),6,99))))+3*VALUE(TRIM(MID(TRIM($AS$20),6,99)))),NA()),VALUE(TRIM(MID(SUBSTITUTE(SUBSTITUTE(SUBSTITUTE(TRIM($AS$20),",",";")," ",""),";",REPT(" ",99)),298,99)))),NA()) | BA7: =IF($AT$7="","",IFERROR(IF(ABS($AT$7)>=1000000,ROUND($AT$7/1000000,MAX(0,1-INT(LOG10($AS$27/1000000))))&"M",IF(ABS($AT$7)>=1000,ROUND($AT$7/1000,MAX(0,1-INT(LOG10($AS$27/1000))))&"k",TEXT($AT$7,"#,##0"))),TEXT($AT$7,"#,##0"))) | BB7: 21000 | BC7: 24500 | BD7: 323 | BE7: loans below the slices | BF7: 0 | BG7: =IF(4<=$BF$13,$BF$14+(4-1)*$BF$16,"") | BH7: =IF(4>$BF$13,"",SUMIFS($BD$4:$BD$203,$BC$4:$BC$203,">="&$BG$7,$BC$4:$BC$203,IF(4=$BF$13,"<=","<")&($BG$7+$BF$16))) | BI7: ="" | BJ7: =IF(AND(4>=11-$BF$17,4<=9),$BF$18,0) | BK7: =IFERROR(IF(AND($BM$5>=$BF$14,$BM$5<=$BF$15),10+0.5+100*($BM$5-$BF$14)/($BF$15-$BF$14),NA()),NA()) | BL7: =IF(ISNA($BK$7),NA(),MAX($BJ$4:$BJ$123)) | BM7: =IFERROR(IF(LEFT(LOWER(TRIM($BF$20)),5)="every",IF(((INT($BF$11/VALUE(TRIM(MID(TRIM($BF$20),6,99))))*VALUE(TRIM(MID(TRIM($BF$20),6,99)))+VALUE(TRIM(MID(TRIM($BF$20),6,99))))+3*VALUE(TRIM(MID(TRIM($BF$20),6,99))))<=$BF$12,((INT($BF$11/VALUE(TRIM(MID(TRIM($BF$20),6,99))))*VALUE(TRIM(MID(TRIM($BF$20),6,99)))+VALUE(TRIM(MID(TRIM($BF$20),6,99))))+3*VALUE(TRIM(MID(TRIM($BF$20),6,99)))),NA()),VALUE(TRIM(MID(SUBSTITUTE(SUBSTITUTE(SUBSTITUTE(TRIM($BF$20),",",";")," ",""),";",REPT(" ",99)),298,99)))),NA()) | BN7: =IF($BG$7="","",IFERROR(IF(ABS($BG$7)>=1000000,ROUND($BG$7/1000000,MAX(0,1-INT(LOG10($BF$27/1000000))))&"M",IF(ABS($BG$7)>=1000,ROUND($BG$7/1000,MAX(0,1-INT(LOG10($BF$27/1000))))&"k",TEXT($BG$7,"#,##0"))),TEXT($BG$7,"#,##0"))) | BO7: 0.018 | BP7: 0.021 | BQ7: 73 | BR7: loans below the slices | BS7: 0 | BT7: =IF(4<=$BS$13,$BS$14+(4-1)*$BS$16,"") | BU7: =IF(4>$BS$13,"",SUMIFS($BQ$4:$BQ$203,$BP$4:$BP$203,">="&$BT$7,$BP$4:$BP$203,IF(4=$BS$13,"<=","<")&($BT$7+$BS$16))) | BV7: ="" | BW7: =IF(AND(4>=11-$BS$17,4<=9),$BS$18,0) | BX7: =IFERROR(IF(AND($BZ$5>=$BS$14,$BZ$5<=$BS$15),10+0.5+100*($BZ$5-$BS$14)/($BS$15-$BS$14),NA()),NA()) | BY7: =IF(ISNA($BX$7),NA(),MAX($BW$4:$BW$123)) | BZ7: =IFERROR(IF(LEFT(LOWER(TRIM($BS$20)),5)="every",IF(((INT($BS$11/VALUE(TRIM(MID(TRIM($BS$20),6,99))))*VALUE(TRIM(MID(TRIM($BS$20),6,99)))+VALUE(TRIM(MID(TRIM($BS$20),6,99))))+3*VALUE(TRIM(MID(TRIM($BS$20),6,99))))<=$BS$12,((INT($BS$11/VALUE(TRIM(MID(TRIM($BS$20),6,99))))*VALUE(TRIM(MID(TRIM($BS$20),6,99)))+VALUE(TRIM(MID(TRIM($BS$20),6,99))))+3*VALUE(TRIM(MID(TRIM($BS$20),6,99)))),NA()),VALUE(TRIM(MID(SUBSTITUTE(SUBSTITUTE(SUBSTITUTE(TRIM($BS$20),",",";")," ",""),";",REPT(" ",99)),298,99)))),NA()) | CA7: =IF($BT$7="","",IFERROR(IF(ABS($BT$7)>=1000000,ROUND($BT$7/1000000,MAX(0,1-INT(LOG10($BS$27/1000000))))&"M",IF(ABS($BT$7)>=1000,ROUND($BT$7/1000,MAX(0,1-INT(LOG10($BS$27/1000))))&"k",TEXT($BT$7,"0.00"))),TEXT($BT$7,"0.00"))) | CB7: 0.45 | CC7: 0.525 | CD7: 174 | CE7: loans below the slices | CF7: 0 | CG7: =IF(4<=$CF$13,$CF$14+(4-1)*$CF$16,"") | CH7: =IF(4>$CF$13,"",SUMIFS($CD$4:$CD$203,$CC$4:$CC$203,">="&$CG$7,$CC$4:$CC$203,IF(4=$CF$13,"<=","<")&($CG$7+$CF$16))) | CI7: ="" | CJ7: =IF(AND(4>=11-$CF$17,4<=9),$CF$18,0) | CK7: =IFERROR(IF(AND($CM$5>=$CF$14,$CM$5<=$CF$15),10+0.5+100*($CM$5-$CF$14)/($CF$15-$CF$14),NA()),NA()) | CL7: =IF(ISNA($CK$7),NA(),MAX($CJ$4:$CJ$123)) | CM7: =IFERROR(IF(LEFT(LOWER(TRIM($CF$20)),5)="every",IF(((INT($CF$11/VALUE(TRIM(MID(TRIM($CF$20),6,99))))*VALUE(TRIM(MID(TRIM($CF$20),6,99)))+VALUE(TRIM(MID(TRIM($CF$20),6,99))))+3*VALUE(TRIM(MID(TRIM($CF$20),6,99))))<=$CF$12,((INT($CF$11/VALUE(TRIM(MID(TRIM($CF$20),6,99))))*VALUE(TRIM(MID(TRIM($CF$20),6,99)))+VALUE(TRIM(MID(TRIM($CF$20),6,99))))+3*VALUE(TRIM(MID(TRIM($CF$20),6,99)))),NA()),VALUE(TRIM(MID(SUBSTITUTE(SUBSTITUTE(SUBSTITUTE(TRIM($CF$20),",",";")," ",""),";",REPT(" ",99)),298,99)))),NA()) | CN7: =IF($CG$7="","",IFERROR(IF(ABS($CG$7)>=1000000,ROUND($CG$7/1000000,MAX(0,1-INT(LOG10($CF$27/1000000))))&"M",IF(ABS($CG$7)>=1000,ROUND($CG$7/1000,MAX(0,1-INT(LOG10($CF$27/1000))))&"k",TEXT($CG$7,"#,##0.0"))),TEXT($CG$7,"#,##0.0"))) | CO7: 11.2 | CP7: 11.4 | CQ7: 9 | CR7: loans below the slices | CS7: 45 | CT7: =IF(4<=$CS$13,$CS$14+(4-1)*$CS$16,"") | CU7: =IF(4>$CS$13,"",SUMIFS($CQ$4:$CQ$203,$CP$4:$CP$203,">="&$CT$7,$CP$4:$CP$203,IF(4=$CS$13,"<=","<")&($CT$7+$CS$16))) | CV7: ="" | CW7: =IF(AND(4>=11-$CS$17,4<=9),$CS$18,0) | CX7: =IFERROR(IF(AND($CZ$5>=$CS$14,$CZ$5<=$CS$15),10+0.5+100*($CZ$5-$CS$14)/($CS$15-$CS$14),NA()),NA()) | CY7: =IF(ISNA($CX$7),NA(),MAX($CW$4:$CW$123)) | CZ7: =IFERROR(IF(LEFT(LOWER(TRIM($CS$20)),5)="every",IF(((INT($CS$11/VALUE(TRIM(MID(TRIM($CS$20),6,99))))*VALUE(TRIM(MID(TRIM($CS$20),6,99)))+VALUE(TRIM(MID(TRIM($CS$20),6,99))))+3*VALUE(TRIM(MID(TRIM($CS$20),6,99))))<=$CS$12,((INT($CS$11/VALUE(TRIM(MID(TRIM($CS$20),6,99))))*VALUE(TRIM(MID(TRIM($CS$20),6,99)))+VALUE(TRIM(MID(TRIM($CS$20),6,99))))+3*VALUE(TRIM(MID(TRIM($CS$20),6,99)))),NA()),VALUE(TRIM(MID(SUBSTITUTE(SUBSTITUTE(SUBSTITUTE(TRIM($CS$20),",",";")," ",""),";",REPT(" ",99)),298,99)))),NA()) | DA7: =IF($CT$7="","",IFERROR(IF(ABS($CT$7)>=1000000,ROUND($CT$7/1000000,MAX(0,1-INT(LOG10($CS$27/1000000))))&"M",IF(ABS($CT$7)>=1000,ROUND($CT$7/1000,MAX(0,1-INT(LOG10($CS$27/1000))))&"k",TEXT($CT$7,"#,##0"))),TEXT($CT$7,"#,##0"))) | DB7: 11.05 | DC7: 11.225 | DD7: 7 | DE7: loans below the slices | DF7: 69 | DG7: =IF(4<=$DF$13,$DF$14+(4-1)*$DF$16,"") | DH7: =IF(4>$DF$13,"",SUMIFS($DD$4:$DD$203,$DC$4:$DC$203,">="&$DG$7,$DC$4:$DC$203,IF(4=$DF$13,"<=","<")&($DG$7+$DF$16))) | DI7: ="" | DJ7: =IF(AND(4>=11-$DF$17,4<=9),$DF$18,0) | DK7: =IFERROR(IF(AND($DM$5>=$DF$14,$DM$5<=$DF$15),10+0.5+100*($DM$5-$DF$14)/($DF$15-$DF$14),NA()),NA()) | DL7: =IF(ISNA($DK$7),NA(),MAX($DJ$4:$DJ$123)) | DM7: =IFERROR(IF(LEFT(LOWER(TRIM($DF$20)),5)="every",IF(((INT($DF$11/VALUE(TRIM(MID(TRIM($DF$20),6,99))))*VALUE(TRIM(MID(TRIM($DF$20),6,99)))+VALUE(TRIM(MID(TRIM($DF$20),6,99))))+3*VALUE(TRIM(MID(TRIM($DF$20),6,99))))<=$DF$12,((INT($DF$11/VALUE(TRIM(MID(TRIM($DF$20),6,99))))*VALUE(TRIM(MID(TRIM($DF$20),6,99)))+VALUE(TRIM(MID(TRIM($DF$20),6,99))))+3*VALUE(TRIM(MID(TRIM($DF$20),6,99)))),NA()),VALUE(TRIM(MID(SUBSTITUTE(SUBSTITUTE(SUBSTITUTE(TRIM($DF$20),",",";")," ",""),";",REPT(" ",99)),298,99)))),NA()) | DN7: =IF($DG$7="","",IFERROR(IF(ABS($DG$7)>=1000000,ROUND($DG$7/1000000,MAX(0,1-INT(LOG10($DF$27/1000000))))&"M",IF(ABS($DG$7)>=1000,ROUND($DG$7/1000,MAX(0,1-INT(LOG10($DF$27/1000))))&"k",TEXT($DG$7,"#,##0.0"))),TEXT($DG$7,"#,##0.0"))) | DO7: 7.575 | DP7: 7.5875 | DQ7: 5 | DR7: loans below the slices | DS7: 73 | DT7: =IF(4<=$DS$13,$DS$14+(4-1)*$DS$16,"") | DU7: =IF(4>$DS$13,"",SUMIFS($DQ$4:$DQ$203,$DP$4:$DP$203,">="&$DT$7,$DP$4:$DP$203,IF(4=$DS$13,"<=","<")&($DT$7+$DS$16))) | DV7: ="" | DW7: =IF(AND(4>=11-$DS$17,4<=9),$DS$18,0) | DX7: =IFERROR(IF(AND($DZ$5>=$DS$14,$DZ$5<=$DS$15),10+0.5+100*($DZ$5-$DS$14)/($DS$15-$DS$14),NA()),NA()) | DY7: =IF(ISNA($DX$7),NA(),MAX($DW$4:$DW$123)) | DZ7: =IFERROR(IF(LEFT(LOWER(TRIM($DS$20)),5)="every",IF(((INT($DS$11/VALUE(TRIM(MID(TRIM($DS$20),6,99))))*VALUE(TRIM(MID(TRIM($DS$20),6,99)))+VALUE(TRIM(MID(TRIM($DS$20),6,99))))+3*VALUE(TRIM(MID(TRIM($DS$20),6,99))))<=$DS$12,((INT($DS$11/VALUE(TRIM(MID(TRIM($DS$20),6,99))))*VALUE(TRIM(MID(TRIM($DS$20),6,99)))+VALUE(TRIM(MID(TRIM($DS$20),6,99))))+3*VALUE(TRIM(MID(TRIM($DS$20),6,99)))),NA()),VALUE(TRIM(MID(SUBSTITUTE(SUBSTITUTE(SUBSTITUTE(TRIM($DS$20),",",";")," ",""),";",REPT(" ",99)),298,99)))),NA()) | EA7: =IF($DT$7="","",IFERROR(IF(ABS($DT$7)>=1000000,ROUND($DT$7/1000000,MAX(0,1-INT(LOG10($DS$27/1000000))))&"M",IF(ABS($DT$7)>=1000,ROUND($DT$7/1000,MAX(0,1-INT(LOG10($DS$27/1000))))&"k",TEXT($DT$7,"#,##0.0"))),TEXT($DT$7,"#,##0.0"))) | EB7: 1.5 | EC7: 1.75 | ED7: 64 | EE7: loans below the slices | EF7: 0 | EG7: =IF(4<=$EF$13,$EF$14+(4-1)*$EF$16,"") | EH7: =IF(4>$EF$13,"",SUMIFS($ED$4:$ED$203,$EC$4:$EC$203,">="&$EG$7,$EC$4:$EC$203,IF(4=$EF$13,"<=","<")&($EG$7+$EF$16))) | EI7: ="" | EJ7: =IF(AND(4>=11-$EF$17,4<=9),$EF$18,0) | EK7: =IFERROR(IF(AND($EM$5>=$EF$14,$EM$5<=$EF$15),10+0.5+100*($EM$5-$EF$14)/($EF$15-$EF$14),NA()),NA()) | EL7: =IF(ISNA($EK$7),NA(),MAX($EJ$4:$EJ$123)) | EM7: =IFERROR(IF(LEFT(LOWER(TRIM($EF$20)),5)="every",IF(((INT($EF$11/VALUE(TRIM(MID(TRIM($EF$20),6,99))))*VALUE(TRIM(MID(TRIM($EF$20),6,99)))+VALUE(TRIM(MID(TRIM($EF$20),6,99))))+3*VALUE(TRIM(MID(TRIM($EF$20),6,99))))<=$EF$12,((INT($EF$11/VALUE(TRIM(MID(TRIM($EF$20),6,99))))*VALUE(TRIM(MID(TRIM($EF$20),6,99)))+VALUE(TRIM(MID(TRIM($EF$20),6,99))))+3*VALUE(TRIM(MID(TRIM($EF$20),6,99)))),NA()),VALUE(TRIM(MID(SUBSTITUTE(SUBSTITUTE(SUBSTITUTE(TRIM($EF$20),",",";")," ",""),";",REPT(" ",99)),298,99)))),NA()) | EN7: =IF($EG$7="","",IFERROR(IF(ABS($EG$7)>=1000000,ROUND($EG$7/1000000,MAX(0,1-INT(LOG10($EF$27/1000000))))&"M",IF(ABS($EG$7)>=1000,ROUND($EG$7/1000,MAX(0,1-INT(LOG10($EF$27/1000))))&"k",TEXT($EG$7,"#,##0"))),TEXT($EG$7,"#,##0"))) | EO7: 0.0525 | EP7: 0.06125 | EQ7: 51 | ER7: loans below the slices | ES7: 0 | ET7: =IF(4<=$ES$13,$ES$14+(4-1)*$ES$16,"") | EU7: =IF(4>$ES$13,"",SUMIFS($EQ$4:$EQ$203,$EP$4:$EP$203,">="&$ET$7,$EP$4:$EP$203,IF(4=$ES$13,"<=","<")&($ET$7+$ES$16))) | EV7: ="" | EW7: =IF(AND(4>=11-$ES$17,4<=9),$ES$18,0) | EX7: =IFERROR(IF(AND($EZ$5>=$ES$14,$EZ$5<=$ES$15),10+0.5+100*($EZ$5-$ES$14)/($ES$15-$ES$14),NA()),NA()) | EY7: =IF(ISNA($EX$7),NA(),MAX($EW$4:$EW$123)) | EZ7: =IFERROR(IF(LEFT(LOWER(TRIM($ES$20)),5)="every",IF(((INT($ES$11/VALUE(TRIM(MID(TRIM($ES$20),6,99))))*VALUE(TRIM(MID(TRIM($ES$20),6,99)))+VALUE(TRIM(MID(TRIM($ES$20),6,99))))+3*VALUE(TRIM(MID(TRIM($ES$20),6,99))))<=$ES$12,((INT($ES$11/VALUE(TRIM(MID(TRIM($ES$20),6,99))))*VALUE(TRIM(MID(TRIM($ES$20),6,99)))+VALUE(TRIM(MID(TRIM($ES$20),6,99))))+3*VALUE(TRIM(MID(TRIM($ES$20),6,99)))),NA()),VALUE(TRIM(MID(SUBSTITUTE(SUBSTITUTE(SUBSTITUTE(TRIM($ES$20),",",";")," ",""),";",REPT(" ",99)),298,99)))),NA()) | FA7: =IF($ET$7="","",IFERROR(IF(ABS($ET$7)>=1000000,ROUND($ET$7/1000000,MAX(0,1-INT(LOG10($ES$27/1000000))))&"M",IF(ABS($ET$7)>=1000,ROUND($ET$7/1000,MAX(0,1-INT(LOG10($ES$27/1000))))&"k",TEXT($ET$7,"0.00"))),TEXT($ET$7,"0.00")))
B8: 556 | C8: 556.75 | D8: 5 | E8: loans above the slices | F8: 44 | G8: =IF(5<=$F$13,$F$14+(5-1)*$F$16,"") | H8: =IF(5>$F$13,"",SUMIFS($D$4:$D$203,$C$4:$C$203,">="&$G$8,$C$4:$C$203,IF(5=$F$13,"<=","<")&($G$8+$F$16))) | I8: ="" | J8: =IF(AND(5>=11-$F$17,5<=9),$F$18,0) | K8: =IFERROR(IF(AND($M$6>=$F$14,$M$6<=$F$15),10+0.5+100*($M$6-$F$14)/($F$15-$F$14),NA()),NA()) | L8: =IF(ISNA($K$8),NA(),0) | M8: =IFERROR(IF(LEFT(LOWER(TRIM($F$20)),5)="every",IF(((INT($F$11/VALUE(TRIM(MID(TRIM($F$20),6,99))))*VALUE(TRIM(MID(TRIM($F$20),6,99)))+VALUE(TRIM(MID(TRIM($F$20),6,99))))+4*VALUE(TRIM(MID(TRIM($F$20),6,99))))<=$F$12,((INT($F$11/VALUE(TRIM(MID(TRIM($F$20),6,99))))*VALUE(TRIM(MID(TRIM($F$20),6,99)))+VALUE(TRIM(MID(TRIM($F$20),6,99))))+4*VALUE(TRIM(MID(TRIM($F$20),6,99)))),NA()),VALUE(TRIM(MID(SUBSTITUTE(SUBSTITUTE(SUBSTITUTE(TRIM($F$20),",",";")," ",""),";",REPT(" ",99)),397,99)))),NA()) | N8: =IF($G$8="","",IFERROR(IF(ABS($G$8)>=1000000,ROUND($G$8/1000000,MAX(0,1-INT(LOG10($F$27/1000000))))&"M",IF(ABS($G$8)>=1000,ROUND($G$8/1000,MAX(0,1-INT(LOG10($F$27/1000))))&"k",TEXT($G$8,"#,##0"))),TEXT($G$8,"#,##0"))) | O8: 1200 | P8: 1350 | Q8: 0 | R8: loans above the slices | S8: 0 | T8: =IF(5<=$S$13,$S$14+(5-1)*$S$16,"") | U8: =IF(5>$S$13,"",SUMIFS($Q$4:$Q$203,$P$4:$P$203,">="&$T$8,$P$4:$P$203,IF(5=$S$13,"<=","<")&($T$8+$S$16))) | V8: ="" | W8: =IF(AND(5>=11-$S$17,5<=9),$S$18,0) | X8: =IFERROR(IF(AND($Z$6>=$S$14,$Z$6<=$S$15),10+0.5+100*($Z$6-$S$14)/($S$15-$S$14),NA()),NA()) | Y8: =IF(ISNA($X$8),NA(),0) | Z8: =IFERROR(IF(LEFT(LOWER(TRIM($S$20)),5)="every",IF(((INT($S$11/VALUE(TRIM(MID(TRIM($S$20),6,99))))*VALUE(TRIM(MID(TRIM($S$20),6,99)))+VALUE(TRIM(MID(TRIM($S$20),6,99))))+4*VALUE(TRIM(MID(TRIM($S$20),6,99))))<=$S$12,((INT($S$11/VALUE(TRIM(MID(TRIM($S$20),6,99))))*VALUE(TRIM(MID(TRIM($S$20),6,99)))+VALUE(TRIM(MID(TRIM($S$20),6,99))))+4*VALUE(TRIM(MID(TRIM($S$20),6,99)))),NA()),VALUE(TRIM(MID(SUBSTITUTE(SUBSTITUTE(SUBSTITUTE(TRIM($S$20),",",";")," ",""),";",REPT(" ",99)),397,99)))),NA()) | AA8: =IF($T$8="","",IFERROR(IF(ABS($T$8)>=1000000,ROUND($T$8/1000000,MAX(0,1-INT(LOG10($S$27/1000000))))&"M",IF(ABS($T$8)>=1000,ROUND($T$8/1000,MAX(0,1-INT(LOG10($S$27/1000))))&"k",TEXT($T$8,"#,##0"))),TEXT($T$8,"#,##0"))) | AB8: 600 | AC8: 675 | AD8: 22 | AE8: loans above the slices | AF8: 105 | AG8: =IF(5<=$AF$13,$AF$14+(5-1)*$AF$16,"") | AH8: =IF(5>$AF$13,"",SUMIFS($AD$4:$AD$203,$AC$4:$AC$203,">="&$AG$8,$AC$4:$AC$203,IF(5=$AF$13,"<=","<")&($AG$8+$AF$16))) | AI8: ="" | AJ8: =IF(AND(5>=11-$AF$17,5<=9),$AF$18,0) | AK8: =IFERROR(IF(AND($AM$6>=$AF$14,$AM$6<=$AF$15),10+0.5+100*($AM$6-$AF$14)/($AF$15-$AF$14),NA()),NA()) | AL8: =IF(ISNA($AK$8),NA(),0) | AM8: =IFERROR(IF(LEFT(LOWER(TRIM($AF$20)),5)="every",IF(((INT($AF$11/VALUE(TRIM(MID(TRIM($AF$20),6,99))))*VALUE(TRIM(MID(TRIM($AF$20),6,99)))+VALUE(TRIM(MID(TRIM($AF$20),6,99))))+4*VALUE(TRIM(MID(TRIM($AF$20),6,99))))<=$AF$12,((INT($AF$11/VALUE(TRIM(MID(TRIM($AF$20),6,99))))*VALUE(TRIM(MID(TRIM($AF$20),6,99)))+VALUE(TRIM(MID(TRIM($AF$20),6,99))))+4*VALUE(TRIM(MID(TRIM($AF$20),6,99)))),NA()),VALUE(TRIM(MID(SUBSTITUTE(SUBSTITUTE(SUBSTITUTE(TRIM($AF$20),",",";")," ",""),";",REPT(" ",99)),397,99)))),NA()) | AN8: =IF($AG$8="","",IFERROR(IF(ABS($AG$8)>=1000000,ROUND($AG$8/1000000,MAX(0,1-INT(LOG10($AF$27/1000000))))&"M",IF(ABS($AG$8)>=1000,ROUND($AG$8/1000,MAX(0,1-INT(LOG10($AF$27/1000))))&"k",TEXT($AG$8,"#,##0"))),TEXT($AG$8,"#,##0"))) | AO8: 16000 | AP8: 18000 | AQ8: 0 | AR8: loans above the slices | AS8: 113 | AT8: =IF(5<=$AS$13,$AS$14+(5-1)*$AS$16,"") | AU8: =IF(5>$AS$13,"",SUMIFS($AQ$4:$AQ$203,$AP$4:$AP$203,">="&$AT$8,$AP$4:$AP$203,IF(5=$AS$13,"<=","<")&($AT$8+$AS$16))) | AV8: ="" | AW8: =IF(AND(5>=11-$AS$17,5<=9),$AS$18,0) | AX8: =IFERROR(IF(AND($AZ$6>=$AS$14,$AZ$6<=$AS$15),10+0.5+100*($AZ$6-$AS$14)/($AS$15-$AS$14),NA()),NA()) | AY8: =IF(ISNA($AX$8),NA(),0) | AZ8: =IFERROR(IF(LEFT(LOWER(TRIM($AS$20)),5)="every",IF(((INT($AS$11/VALUE(TRIM(MID(TRIM($AS$20),6,99))))*VALUE(TRIM(MID(TRIM($AS$20),6,99)))+VALUE(TRIM(MID(TRIM($AS$20),6,99))))+4*VALUE(TRIM(MID(TRIM($AS$20),6,99))))<=$AS$12,((INT($AS$11/VALUE(TRIM(MID(TRIM($AS$20),6,99))))*VALUE(TRIM(MID(TRIM($AS$20),6,99)))+VALUE(TRIM(MID(TRIM($AS$20),6,99))))+4*VALUE(TRIM(MID(TRIM($AS$20),6,99)))),NA()),VALUE(TRIM(MID(SUBSTITUTE(SUBSTITUTE(SUBSTITUTE(TRIM($AS$20),",",";")," ",""),";",REPT(" ",99)),397,99)))),NA()) | BA8: =IF($AT$8="","",IFERROR(IF(ABS($AT$8)>=1000000,ROUND($AT$8/1000000,MAX(0,1-INT(LOG10($AS$27/1000000))))&"M",IF(ABS($AT$8)>=1000,ROUND($AT$8/1000,MAX(0,1-INT(LOG10($AS$27/1000))))&"k",TEXT($AT$8,"#,##0"))),TEXT($AT$8,"#,##0"))) | BB8: 28000 | BC8: 31500 | BD8: 358 | BE8: loans above the slices | BF8: 67 | BG8: =IF(5<=$BF$13,$BF$14+(5-1)*$BF$16,"") | BH8: =IF(5>$BF$13,"",SUMIFS($BD$4:$BD$203,$BC$4:$BC$203,">="&$BG$8,$BC$4:$BC$203,IF(5=$BF$13,"<=","<")&($BG$8+$BF$16))) | BI8: ="" | BJ8: =IF(AND(5>=11-$BF$17,5<=9),$BF$18,0) | BK8: =IFERROR(IF(AND($BM$6>=$BF$14,$BM$6<=$BF$15),10+0.5+100*($BM$6-$BF$14)/($BF$15-$BF$14),NA()),NA()) | BL8: =IF(ISNA($BK$8),NA(),0) | BM8: =IFERROR(IF(LEFT(LOWER(TRIM($BF$20)),5)="every",IF(((INT($BF$11/VALUE(TRIM(MID(TRIM($BF$20),6,99))))*VALUE(TRIM(MID(TRIM($BF$20),6,99)))+VALUE(TRIM(MID(TRIM($BF$20),6,99))))+4*VALUE(TRIM(MID(TRIM($BF$20),6,99))))<=$BF$12,((INT($BF$11/VALUE(TRIM(MID(TRIM($BF$20),6,99))))*VALUE(TRIM(MID(TRIM($BF$20),6,99)))+VALUE(TRIM(MID(TRIM($BF$20),6,99))))+4*VALUE(TRIM(MID(TRIM($BF$20),6,99)))),NA()),VALUE(TRIM(MID(SUBSTITUTE(SUBSTITUTE(SUBSTITUTE(TRIM($BF$20),",",";")," ",""),";",REPT(" ",99)),397,99)))),NA()) | BN8: =IF($BG$8="","",IFERROR(IF(ABS($BG$8)>=1000000,ROUND($BG$8/1000000,MAX(0,1-INT(LOG10($BF$27/1000000))))&"M",IF(ABS($BG$8)>=1000,ROUND($BG$8/1000,MAX(0,1-INT(LOG10($BF$27/1000))))&"k",TEXT($BG$8,"#,##0"))),TEXT($BG$8,"#,##0"))) | BO8: 0.024 | BP8: 0.027 | BQ8: 57 | BR8: loans above the slices | BS8: 0 | BT8: =IF(5<=$BS$13,$BS$14+(5-1)*$BS$16,"") | BU8: =IF(5>$BS$13,"",SUMIFS($BQ$4:$BQ$203,$BP$4:$BP$203,">="&$BT$8,$BP$4:$BP$203,IF(5=$BS$13,"<=","<")&($BT$8+$BS$16))) | BV8: ="" | BW8: =IF(AND(5>=11-$BS$17,5<=9),$BS$18,0) | BX8: =IFERROR(IF(AND($BZ$6>=$BS$14,$BZ$6<=$BS$15),10+0.5+100*($BZ$6-$BS$14)/($BS$15-$BS$14),NA()),NA()) | BY8: =IF(ISNA($BX$8),NA(),0) | BZ8: =IFERROR(IF(LEFT(LOWER(TRIM($BS$20)),5)="every",IF(((INT($BS$11/VALUE(TRIM(MID(TRIM($BS$20),6,99))))*VALUE(TRIM(MID(TRIM($BS$20),6,99)))+VALUE(TRIM(MID(TRIM($BS$20),6,99))))+4*VALUE(TRIM(MID(TRIM($BS$20),6,99))))<=$BS$12,((INT($BS$11/VALUE(TRIM(MID(TRIM($BS$20),6,99))))*VALUE(TRIM(MID(TRIM($BS$20),6,99)))+VALUE(TRIM(MID(TRIM($BS$20),6,99))))+4*VALUE(TRIM(MID(TRIM($BS$20),6,99)))),NA()),VALUE(TRIM(MID(SUBSTITUTE(SUBSTITUTE(SUBSTITUTE(TRIM($BS$20),",",";")," ",""),";",REPT(" ",99)),397,99)))),NA()) | CA8: =IF($BT$8="","",IFERROR(IF(ABS($BT$8)>=1000000,ROUND($BT$8/1000000,MAX(0,1-INT(LOG10($BS$27/1000000))))&"M",IF(ABS($BT$8)>=1000,ROUND($BT$8/1000,MAX(0,1-INT(LOG10($BS$27/1000))))&"k",TEXT($BT$8,"0.00"))),TEXT($BT$8,"0.00"))) | CB8: 0.6 | CC8: 0.675 | CD8: 357 | CE8: loans above the slices | CF8: 82 | CG8: =IF(5<=$CF$13,$CF$14+(5-1)*$CF$16,"") | CH8: =IF(5>$CF$13,"",SUMIFS($CD$4:$CD$203,$CC$4:$CC$203,">="&$CG$8,$CC$4:$CC$203,IF(5=$CF$13,"<=","<")&($CG$8+$CF$16))) | CI8: ="" | CJ8: =IF(AND(5>=11-$CF$17,5<=9),$CF$18,0) | CK8: =IFERROR(IF(AND($CM$6>=$CF$14,$CM$6<=$CF$15),10+0.5+100*($CM$6-$CF$14)/($CF$15-$CF$14),NA()),NA()) | CL8: =IF(ISNA($CK$8),NA(),0) | CM8: =IFERROR(IF(LEFT(LOWER(TRIM($CF$20)),5)="every",IF(((INT($CF$11/VALUE(TRIM(MID(TRIM($CF$20),6,99))))*VALUE(TRIM(MID(TRIM($CF$20),6,99)))+VALUE(TRIM(MID(TRIM($CF$20),6,99))))+4*VALUE(TRIM(MID(TRIM($CF$20),6,99))))<=$CF$12,((INT($CF$11/VALUE(TRIM(MID(TRIM($CF$20),6,99))))*VALUE(TRIM(MID(TRIM($CF$20),6,99)))+VALUE(TRIM(MID(TRIM($CF$20),6,99))))+4*VALUE(TRIM(MID(TRIM($CF$20),6,99)))),NA()),VALUE(TRIM(MID(SUBSTITUTE(SUBSTITUTE(SUBSTITUTE(TRIM($CF$20),",",";")," ",""),";",REPT(" ",99)),397,99)))),NA()) | CN8: =IF($CG$8="","",IFERROR(IF(ABS($CG$8)>=1000000,ROUND($CG$8/1000000,MAX(0,1-INT(LOG10($CF$27/1000000))))&"M",IF(ABS($CG$8)>=1000,ROUND($CG$8/1000,MAX(0,1-INT(LOG10($CF$27/1000))))&"k",TEXT($CG$8,"#,##0.0"))),TEXT($CG$8,"#,##0.0"))) | CO8: 11.6 | CP8: 11.8 | CQ8: 10 | CR8: loans above the slices | CS8: 45 | CT8: =IF(5<=$CS$13,$CS$14+(5-1)*$CS$16,"") | CU8: =IF(5>$CS$13,"",SUMIFS($CQ$4:$CQ$203,$CP$4:$CP$203,">="&$CT$8,$CP$4:$CP$203,IF(5=$CS$13,"<=","<")&($CT$8+$CS$16))) | CV8: ="" | CW8: =IF(AND(5>=11-$CS$17,5<=9),$CS$18,0) | CX8: =IFERROR(IF(AND($CZ$6>=$CS$14,$CZ$6<=$CS$15),10+0.5+100*($CZ$6-$CS$14)/($CS$15-$CS$14),NA()),NA()) | CY8: =IF(ISNA($CX$8),NA(),0) | CZ8: =IFERROR(IF(LEFT(LOWER(TRIM($CS$20)),5)="every",IF(((INT($CS$11/VALUE(TRIM(MID(TRIM($CS$20),6,99))))*VALUE(TRIM(MID(TRIM($CS$20),6,99)))+VALUE(TRIM(MID(TRIM($CS$20),6,99))))+4*VALUE(TRIM(MID(TRIM($CS$20),6,99))))<=$CS$12,((INT($CS$11/VALUE(TRIM(MID(TRIM($CS$20),6,99))))*VALUE(TRIM(MID(TRIM($CS$20),6,99)))+VALUE(TRIM(MID(TRIM($CS$20),6,99))))+4*VALUE(TRIM(MID(TRIM($CS$20),6,99)))),NA()),VALUE(TRIM(MID(SUBSTITUTE(SUBSTITUTE(SUBSTITUTE(TRIM($CS$20),",",";")," ",""),";",REPT(" ",99)),397,99)))),NA()) | DA8: =IF($CT$8="","",IFERROR(IF(ABS($CT$8)>=1000000,ROUND($CT$8/1000000,MAX(0,1-INT(LOG10($CS$27/1000000))))&"M",IF(ABS($CT$8)>=1000,ROUND($CT$8/1000,MAX(0,1-INT(LOG10($CS$27/1000))))&"k",TEXT($CT$8,"#,##0"))),TEXT($CT$8,"#,##0"))) | DB8: 11.4 | DC8: 11.575 | DD8: 7 | DE8: loans above the slices | DF8: 63 | DG8: =IF(5<=$DF$13,$DF$14+(5-1)*$DF$16,"") | DH8: =IF(5>$DF$13,"",SUMIFS($DD$4:$DD$203,$DC$4:$DC$203,">="&$DG$8,$DC$4:$DC$203,IF(5=$DF$13,"<=","<")&($DG$8+$DF$16))) | DI8: ="" | DJ8: =IF(AND(5>=11-$DF$17,5<=9),$DF$18,0) | DK8: =IFERROR(IF(AND($DM$6>=$DF$14,$DM$6<=$DF$15),10+0.5+100*($DM$6-$DF$14)/($DF$15-$DF$14),NA()),NA()) | DL8: =IF(ISNA($DK$8),NA(),0) | DM8: =IFERROR(IF(LEFT(LOWER(TRIM($DF$20)),5)="every",IF(((INT($DF$11/VALUE(TRIM(MID(TRIM($DF$20),6,99))))*VALUE(TRIM(MID(TRIM($DF$20),6,99)))+VALUE(TRIM(MID(TRIM($DF$20),6,99))))+4*VALUE(TRIM(MID(TRIM($DF$20),6,99))))<=$DF$12,((INT($DF$11/VALUE(TRIM(MID(TRIM($DF$20),6,99))))*VALUE(TRIM(MID(TRIM($DF$20),6,99)))+VALUE(TRIM(MID(TRIM($DF$20),6,99))))+4*VALUE(TRIM(MID(TRIM($DF$20),6,99)))),NA()),VALUE(TRIM(MID(SUBSTITUTE(SUBSTITUTE(SUBSTITUTE(TRIM($DF$20),",",";")," ",""),";",REPT(" ",99)),397,99)))),NA()) | DN8: =IF($DG$8="","",IFERROR(IF(ABS($DG$8)>=1000000,ROUND($DG$8/1000000,MAX(0,1-INT(LOG10($DF$27/1000000))))&"M",IF(ABS($DG$8)>=1000,ROUND($DG$8/1000,MAX(0,1-INT(LOG10($DF$27/1000))))&"k",TEXT($DG$8,"#,##0.0"))),TEXT($DG$8,"#,##0.0"))) | DO8: 7.6 | DP8: 7.6125 | DQ8: 2 | DR8: loans above the slices | DS8: 77 | DT8: =IF(5<=$DS$13,$DS$14+(5-1)*$DS$16,"") | DU8: =IF(5>$DS$13,"",SUMIFS($DQ$4:$DQ$203,$DP$4:$DP$203,">="&$DT$8,$DP$4:$DP$203,IF(5=$DS$13,"<=","<")&($DT$8+$DS$16))) | DV8: ="" | DW8: =IF(AND(5>=11-$DS$17,5<=9),$DS$18,0) | DX8: =IFERROR(IF(AND($DZ$6>=$DS$14,$DZ$6<=$DS$15),10+0.5+100*($DZ$6-$DS$14)/($DS$15-$DS$14),NA()),NA()) | DY8: =IF(ISNA($DX$8),NA(),0) | DZ8: =IFERROR(IF(LEFT(LOWER(TRIM($DS$20)),5)="every",IF(((INT($DS$11/VALUE(TRIM(MID(TRIM($DS$20),6,99))))*VALUE(TRIM(MID(TRIM($DS$20),6,99)))+VALUE(TRIM(MID(TRIM($DS$20),6,99))))+4*VALUE(TRIM(MID(TRIM($DS$20),6,99))))<=$DS$12,((INT($DS$11/VALUE(TRIM(MID(TRIM($DS$20),6,99))))*VALUE(TRIM(MID(TRIM($DS$20),6,99)))+VALUE(TRIM(MID(TRIM($DS$20),6,99))))+4*VALUE(TRIM(MID(TRIM($DS$20),6,99)))),NA()),VALUE(TRIM(MID(SUBSTITUTE(SUBSTITUTE(SUBSTITUTE(TRIM($DS$20),",",";")," ",""),";",REPT(" ",99)),397,99)))),NA()) | EA8: =IF($DT$8="","",IFERROR(IF(ABS($DT$8)>=1000000,ROUND($DT$8/1000000,MAX(0,1-INT(LOG10($DS$27/1000000))))&"M",IF(ABS($DT$8)>=1000,ROUND($DT$8/1000,MAX(0,1-INT(LOG10($DS$27/1000))))&"k",TEXT($DT$8,"#,##0.0"))),TEXT($DT$8,"#,##0.0"))) | EB8: 2 | EC8: 2.25 | ED8: 71 | EE8: loans above the slices | EF8: 0 | EG8: =IF(5<=$EF$13,$EF$14+(5-1)*$EF$16,"") | EH8: =IF(5>$EF$13,"",SUMIFS($ED$4:$ED$203,$EC$4:$EC$203,">="&$EG$8,$EC$4:$EC$203,IF(5=$EF$13,"<=","<")&($EG$8+$EF$16))) | EI8: ="" | EJ8: =IF(AND(5>=11-$EF$17,5<=9),$EF$18,0) | EK8: =IFERROR(IF(AND($EM$6>=$EF$14,$EM$6<=$EF$15),10+0.5+100*($EM$6-$EF$14)/($EF$15-$EF$14),NA()),NA()) | EL8: =IF(ISNA($EK$8),NA(),0) | EM8: =IFERROR(IF(LEFT(LOWER(TRIM($EF$20)),5)="every",IF(((INT($EF$11/VALUE(TRIM(MID(TRIM($EF$20),6,99))))*VALUE(TRIM(MID(TRIM($EF$20),6,99)))+VALUE(TRIM(MID(TRIM($EF$20),6,99))))+4*VALUE(TRIM(MID(TRIM($EF$20),6,99))))<=$EF$12,((INT($EF$11/VALUE(TRIM(MID(TRIM($EF$20),6,99))))*VALUE(TRIM(MID(TRIM($EF$20),6,99)))+VALUE(TRIM(MID(TRIM($EF$20),6,99))))+4*VALUE(TRIM(MID(TRIM($EF$20),6,99)))),NA()),VALUE(TRIM(MID(SUBSTITUTE(SUBSTITUTE(SUBSTITUTE(TRIM($EF$20),",",";")," ",""),";",REPT(" ",99)),397,99)))),NA()) | EN8: =IF($EG$8="","",IFERROR(IF(ABS($EG$8)>=1000000,ROUND($EG$8/1000000,MAX(0,1-INT(LOG10($EF$27/1000000))))&"M",IF(ABS($EG$8)>=1000,ROUND($EG$8/1000,MAX(0,1-INT(LOG10($EF$27/1000))))&"k",TEXT($EG$8,"#,##0"))),TEXT($EG$8,"#,##0"))) | EO8: 0.07 | EP8: 0.07875 | EQ8: 102 | ER8: loans above the slices | ES8: 108 | ET8: =IF(5<=$ES$13,$ES$14+(5-1)*$ES$16,"") | EU8: =IF(5>$ES$13,"",SUMIFS($EQ$4:$EQ$203,$EP$4:$EP$203,">="&$ET$8,$EP$4:$EP$203,IF(5=$ES$13,"<=","<")&($ET$8+$ES$16))) | EV8: ="" | EW8: =IF(AND(5>=11-$ES$17,5<=9),$ES$18,0) | EX8: =IFERROR(IF(AND($EZ$6>=$ES$14,$EZ$6<=$ES$15),10+0.5+100*($EZ$6-$ES$14)/($ES$15-$ES$14),NA()),NA()) | EY8: =IF(ISNA($EX$8),NA(),0) | EZ8: =IFERROR(IF(LEFT(LOWER(TRIM($ES$20)),5)="every",IF(((INT($ES$11/VALUE(TRIM(MID(TRIM($ES$20),6,99))))*VALUE(TRIM(MID(TRIM($ES$20),6,99)))+VALUE(TRIM(MID(TRIM($ES$20),6,99))))+4*VALUE(TRIM(MID(TRIM($ES$20),6,99))))<=$ES$12,((INT($ES$11/VALUE(TRIM(MID(TRIM($ES$20),6,99))))*VALUE(TRIM(MID(TRIM($ES$20),6,99)))+VALUE(TRIM(MID(TRIM($ES$20),6,99))))+4*VALUE(TRIM(MID(TRIM($ES$20),6,99)))),NA()),VALUE(TRIM(MID(SUBSTITUTE(SUBSTITUTE(SUBSTITUTE(TRIM($ES$20),",",";")," ",""),";",REPT(" ",99)),397,99)))),NA()) | FA8: =IF($ET$8="","",IFERROR(IF(ABS($ET$8)>=1000000,ROUND($ET$8/1000000,MAX(0,1-INT(LOG10($ES$27/1000000))))&"M",IF(ABS($ET$8)>=1000,ROUND($ET$8/1000,MAX(0,1-INT(LOG10($ES$27/1000))))&"k",TEXT($ET$8,"0.00"))),TEXT($ET$8,"0.00")))
B9: 557.5 | C9: 558.25 | D9: 5 | E9: likely code | G9: =IF(6<=$F$13,$F$14+(6-1)*$F$16,"") | H9: =IF(6>$F$13,"",SUMIFS($D$4:$D$203,$C$4:$C$203,">="&$G$9,$C$4:$C$203,IF(6=$F$13,"<=","<")&($G$9+$F$16))) | I9: ="" | J9: =IF(AND(6>=11-$F$17,6<=9),$F$18,0) | K9: =IFERROR(IF(AND($M$6>=$F$14,$M$6<=$F$15),10+0.5+100*($M$6-$F$14)/($F$15-$F$14),NA()),NA()) | L9: =IF(ISNA($K$9),NA(),MAX($J$4:$J$123)) | M9: =IFERROR(IF(LEFT(LOWER(TRIM($F$20)),5)="every",IF(((INT($F$11/VALUE(TRIM(MID(TRIM($F$20),6,99))))*VALUE(TRIM(MID(TRIM($F$20),6,99)))+VALUE(TRIM(MID(TRIM($F$20),6,99))))+5*VALUE(TRIM(MID(TRIM($F$20),6,99))))<=$F$12,((INT($F$11/VALUE(TRIM(MID(TRIM($F$20),6,99))))*VALUE(TRIM(MID(TRIM($F$20),6,99)))+VALUE(TRIM(MID(TRIM($F$20),6,99))))+5*VALUE(TRIM(MID(TRIM($F$20),6,99)))),NA()),VALUE(TRIM(MID(SUBSTITUTE(SUBSTITUTE(SUBSTITUTE(TRIM($F$20),",",";")," ",""),";",REPT(" ",99)),496,99)))),NA()) | N9: =IF($G$9="","",IFERROR(IF(ABS($G$9)>=1000000,ROUND($G$9/1000000,MAX(0,1-INT(LOG10($F$27/1000000))))&"M",IF(ABS($G$9)>=1000,ROUND($G$9/1000,MAX(0,1-INT(LOG10($F$27/1000))))&"k",TEXT($G$9,"#,##0"))),TEXT($G$9,"#,##0"))) | O9: 1500 | P9: 1650 | Q9: 0 | R9: likely code | T9: =IF(6<=$S$13,$S$14+(6-1)*$S$16,"") | U9: =IF(6>$S$13,"",SUMIFS($Q$4:$Q$203,$P$4:$P$203,">="&$T$9,$P$4:$P$203,IF(6=$S$13,"<=","<")&($T$9+$S$16))) | V9: ="" | W9: =IF(AND(6>=11-$S$17,6<=9),$S$18,0) | X9: =IFERROR(IF(AND($Z$6>=$S$14,$Z$6<=$S$15),10+0.5+100*($Z$6-$S$14)/($S$15-$S$14),NA()),NA()) | Y9: =IF(ISNA($X$9),NA(),MAX($W$4:$W$123)) | Z9: =IFERROR(IF(LEFT(LOWER(TRIM($S$20)),5)="every",IF(((INT($S$11/VALUE(TRIM(MID(TRIM($S$20),6,99))))*VALUE(TRIM(MID(TRIM($S$20),6,99)))+VALUE(TRIM(MID(TRIM($S$20),6,99))))+5*VALUE(TRIM(MID(TRIM($S$20),6,99))))<=$S$12,((INT($S$11/VALUE(TRIM(MID(TRIM($S$20),6,99))))*VALUE(TRIM(MID(TRIM($S$20),6,99)))+VALUE(TRIM(MID(TRIM($S$20),6,99))))+5*VALUE(TRIM(MID(TRIM($S$20),6,99)))),NA()),VALUE(TRIM(MID(SUBSTITUTE(SUBSTITUTE(SUBSTITUTE(TRIM($S$20),",",";")," ",""),";",REPT(" ",99)),496,99)))),NA()) | AA9: =IF($T$9="","",IFERROR(IF(ABS($T$9)>=1000000,ROUND($T$9/1000000,MAX(0,1-INT(LOG10($S$27/1000000))))&"M",IF(ABS($T$9)>=1000,ROUND($T$9/1000,MAX(0,1-INT(LOG10($S$27/1000))))&"k",TEXT($T$9,"#,##0"))),TEXT($T$9,"#,##0"))) | AB9: 750 | AC9: 825 | AD9: 17 | AE9: likely code | AG9: =IF(6<=$AF$13,$AF$14+(6-1)*$AF$16,"") | AH9: =IF(6>$AF$13,"",SUMIFS($AD$4:$AD$203,$AC$4:$AC$203,">="&$AG$9,$AC$4:$AC$203,IF(6=$AF$13,"<=","<")&($AG$9+$AF$16))) | AI9: ="" | AJ9: =IF(AND(6>=11-$AF$17,6<=9),$AF$18,0) | AK9: =IFERROR(IF(AND($AM$6>=$AF$14,$AM$6<=$AF$15),10+0.5+100*($AM$6-$AF$14)/($AF$15-$AF$14),NA()),NA()) | AL9: =IF(ISNA($AK$9),NA(),MAX($AJ$4:$AJ$123)) | AM9: =IFERROR(IF(LEFT(LOWER(TRIM($AF$20)),5)="every",IF(((INT($AF$11/VALUE(TRIM(MID(TRIM($AF$20),6,99))))*VALUE(TRIM(MID(TRIM($AF$20),6,99)))+VALUE(TRIM(MID(TRIM($AF$20),6,99))))+5*VALUE(TRIM(MID(TRIM($AF$20),6,99))))<=$AF$12,((INT($AF$11/VALUE(TRIM(MID(TRIM($AF$20),6,99))))*VALUE(TRIM(MID(TRIM($AF$20),6,99)))+VALUE(TRIM(MID(TRIM($AF$20),6,99))))+5*VALUE(TRIM(MID(TRIM($AF$20),6,99)))),NA()),VALUE(TRIM(MID(SUBSTITUTE(SUBSTITUTE(SUBSTITUTE(TRIM($AF$20),",",";")," ",""),";",REPT(" ",99)),496,99)))),NA()) | AN9: =IF($AG$9="","",IFERROR(IF(ABS($AG$9)>=1000000,ROUND($AG$9/1000000,MAX(0,1-INT(LOG10($AF$27/1000000))))&"M",IF(ABS($AG$9)>=1000,ROUND($AG$9/1000,MAX(0,1-INT(LOG10($AF$27/1000))))&"k",TEXT($AG$9,"#,##0"))),TEXT($AG$9,"#,##0"))) | AO9: 20000 | AP9: 22000 | AQ9: 0 | AR9: likely code | AT9: =IF(6<=$AS$13,$AS$14+(6-1)*$AS$16,"") | AU9: =IF(6>$AS$13,"",SUMIFS($AQ$4:$AQ$203,$AP$4:$AP$203,">="&$AT$9,$AP$4:$AP$203,IF(6=$AS$13,"<=","<")&($AT$9+$AS$16))) | AV9: ="" | AW9: =IF(AND(6>=11-$AS$17,6<=9),$AS$18,0) | AX9: =IFERROR(IF(AND($AZ$6>=$AS$14,$AZ$6<=$AS$15),10+0.5+100*($AZ$6-$AS$14)/($AS$15-$AS$14),NA()),NA()) | AY9: =IF(ISNA($AX$9),NA(),MAX($AW$4:$AW$123)) | AZ9: =IFERROR(IF(LEFT(LOWER(TRIM($AS$20)),5)="every",IF(((INT($AS$11/VALUE(TRIM(MID(TRIM($AS$20),6,99))))*VALUE(TRIM(MID(TRIM($AS$20),6,99)))+VALUE(TRIM(MID(TRIM($AS$20),6,99))))+5*VALUE(TRIM(MID(TRIM($AS$20),6,99))))<=$AS$12,((INT($AS$11/VALUE(TRIM(MID(TRIM($AS$20),6,99))))*VALUE(TRIM(MID(TRIM($AS$20),6,99)))+VALUE(TRIM(MID(TRIM($AS$20),6,99))))+5*VALUE(TRIM(MID(TRIM($AS$20),6,99)))),NA()),VALUE(TRIM(MID(SUBSTITUTE(SUBSTITUTE(SUBSTITUTE(TRIM($AS$20),",",";")," ",""),";",REPT(" ",99)),496,99)))),NA()) | BA9: =IF($AT$9="","",IFERROR(IF(ABS($AT$9)>=1000000,ROUND($AT$9/1000000,MAX(0,1-INT(LOG10($AS$27/1000000))))&"M",IF(ABS($AT$9)>=1000,ROUND($AT$9/1000,MAX(0,1-INT(LOG10($AS$27/1000))))&"k",TEXT($AT$9,"#,##0"))),TEXT($AT$9,"#,##0"))) | BB9: 35000 | BC9: 38500 | BD9: 414 | BE9: likely code | BG9: =IF(6<=$BF$13,$BF$14+(6-1)*$BF$16,"") | BH9: =IF(6>$BF$13,"",SUMIFS($BD$4:$BD$203,$BC$4:$BC$203,">="&$BG$9,$BC$4:$BC$203,IF(6=$BF$13,"<=","<")&($BG$9+$BF$16))) | BI9: ="" | BJ9: =IF(AND(6>=11-$BF$17,6<=9),$BF$18,0) | BK9: =IFERROR(IF(AND($BM$6>=$BF$14,$BM$6<=$BF$15),10+0.5+100*($BM$6-$BF$14)/($BF$15-$BF$14),NA()),NA()) | BL9: =IF(ISNA($BK$9),NA(),MAX($BJ$4:$BJ$123)) | BM9: =IFERROR(IF(LEFT(LOWER(TRIM($BF$20)),5)="every",IF(((INT($BF$11/VALUE(TRIM(MID(TRIM($BF$20),6,99))))*VALUE(TRIM(MID(TRIM($BF$20),6,99)))+VALUE(TRIM(MID(TRIM($BF$20),6,99))))+5*VALUE(TRIM(MID(TRIM($BF$20),6,99))))<=$BF$12,((INT($BF$11/VALUE(TRIM(MID(TRIM($BF$20),6,99))))*VALUE(TRIM(MID(TRIM($BF$20),6,99)))+VALUE(TRIM(MID(TRIM($BF$20),6,99))))+5*VALUE(TRIM(MID(TRIM($BF$20),6,99)))),NA()),VALUE(TRIM(MID(SUBSTITUTE(SUBSTITUTE(SUBSTITUTE(TRIM($BF$20),",",";")," ",""),";",REPT(" ",99)),496,99)))),NA()) | BN9: =IF($BG$9="","",IFERROR(IF(ABS($BG$9)>=1000000,ROUND($BG$9/1000000,MAX(0,1-INT(LOG10($BF$27/1000000))))&"M",IF(ABS($BG$9)>=1000,ROUND($BG$9/1000,MAX(0,1-INT(LOG10($BF$27/1000))))&"k",TEXT($BG$9,"#,##0"))),TEXT($BG$9,"#,##0"))) | BO9: 0.03 | BP9: 0.033 | BQ9: 50 | BR9: likely code | BT9: =IF(6<=$BS$13,$BS$14+(6-1)*$BS$16,"") | BU9: =IF(6>$BS$13,"",SUMIFS($BQ$4:$BQ$203,$BP$4:$BP$203,">="&$BT$9,$BP$4:$BP$203,IF(6=$BS$13,"<=","<")&($BT$9+$BS$16))) | BV9: ="" | BW9: =IF(AND(6>=11-$BS$17,6<=9),$BS$18,0) | BX9: =IFERROR(IF(AND($BZ$6>=$BS$14,$BZ$6<=$BS$15),10+0.5+100*($BZ$6-$BS$14)/($BS$15-$BS$14),NA()),NA()) | BY9: =IF(ISNA($BX$9),NA(),MAX($BW$4:$BW$123)) | BZ9: =IFERROR(IF(LEFT(LOWER(TRIM($BS$20)),5)="every",IF(((INT($BS$11/VALUE(TRIM(MID(TRIM($BS$20),6,99))))*VALUE(TRIM(MID(TRIM($BS$20),6,99)))+VALUE(TRIM(MID(TRIM($BS$20),6,99))))+5*VALUE(TRIM(MID(TRIM($BS$20),6,99))))<=$BS$12,((INT($BS$11/VALUE(TRIM(MID(TRIM($BS$20),6,99))))*VALUE(TRIM(MID(TRIM($BS$20),6,99)))+VALUE(TRIM(MID(TRIM($BS$20),6,99))))+5*VALUE(TRIM(MID(TRIM($BS$20),6,99)))),NA()),VALUE(TRIM(MID(SUBSTITUTE(SUBSTITUTE(SUBSTITUTE(TRIM($BS$20),",",";")," ",""),";",REPT(" ",99)),496,99)))),NA()) | CA9: =IF($BT$9="","",IFERROR(IF(ABS($BT$9)>=1000000,ROUND($BT$9/1000000,MAX(0,1-INT(LOG10($BS$27/1000000))))&"M",IF(ABS($BT$9)>=1000,ROUND($BT$9/1000,MAX(0,1-INT(LOG10($BS$27/1000))))&"k",TEXT($BT$9,"0.00"))),TEXT($BT$9,"0.00"))) | CB9: 0.75 | CC9: 0.825 | CD9: 183 | CE9: likely code | CG9: =IF(6<=$CF$13,$CF$14+(6-1)*$CF$16,"") | CH9: =IF(6>$CF$13,"",SUMIFS($CD$4:$CD$203,$CC$4:$CC$203,">="&$CG$9,$CC$4:$CC$203,IF(6=$CF$13,"<=","<")&($CG$9+$CF$16))) | CI9: ="" | CJ9: =IF(AND(6>=11-$CF$17,6<=9),$CF$18,0) | CK9: =IFERROR(IF(AND($CM$6>=$CF$14,$CM$6<=$CF$15),10+0.5+100*($CM$6-$CF$14)/($CF$15-$CF$14),NA()),NA()) | CL9: =IF(ISNA($CK$9),NA(),MAX($CJ$4:$CJ$123)) | CM9: =IFERROR(IF(LEFT(LOWER(TRIM($CF$20)),5)="every",IF(((INT($CF$11/VALUE(TRIM(MID(TRIM($CF$20),6,99))))*VALUE(TRIM(MID(TRIM($CF$20),6,99)))+VALUE(TRIM(MID(TRIM($CF$20),6,99))))+5*VALUE(TRIM(MID(TRIM($CF$20),6,99))))<=$CF$12,((INT($CF$11/VALUE(TRIM(MID(TRIM($CF$20),6,99))))*VALUE(TRIM(MID(TRIM($CF$20),6,99)))+VALUE(TRIM(MID(TRIM($CF$20),6,99))))+5*VALUE(TRIM(MID(TRIM($CF$20),6,99)))),NA()),VALUE(TRIM(MID(SUBSTITUTE(SUBSTITUTE(SUBSTITUTE(TRIM($CF$20),",",";")," ",""),";",REPT(" ",99)),496,99)))),NA()) | CN9: =IF($CG$9="","",IFERROR(IF(ABS($CG$9)>=1000000,ROUND($CG$9/1000000,MAX(0,1-INT(LOG10($CF$27/1000000))))&"M",IF(ABS($CG$9)>=1000,ROUND($CG$9/1000,MAX(0,1-INT(LOG10($CF$27/1000))))&"k",TEXT($CG$9,"#,##0.0"))),TEXT($CG$9,"#,##0.0"))) | CO9: 12 | CP9: 12.2 | CQ9: 5 | CR9: likely code | CT9: =IF(6<=$CS$13,$CS$14+(6-1)*$CS$16,"") | CU9: =IF(6>$CS$13,"",SUMIFS($CQ$4:$CQ$203,$CP$4:$CP$203,">="&$CT$9,$CP$4:$CP$203,IF(6=$CS$13,"<=","<")&($CT$9+$CS$16))) | CV9: ="" | CW9: =IF(AND(6>=11-$CS$17,6<=9),$CS$18,0) | CX9: =IFERROR(IF(AND($CZ$6>=$CS$14,$CZ$6<=$CS$15),10+0.5+100*($CZ$6-$CS$14)/($CS$15-$CS$14),NA()),NA()) | CY9: =IF(ISNA($CX$9),NA(),MAX($CW$4:$CW$123)) | CZ9: =IFERROR(IF(LEFT(LOWER(TRIM($CS$20)),5)="every",IF(((INT($CS$11/VALUE(TRIM(MID(TRIM($CS$20),6,99))))*VALUE(TRIM(MID(TRIM($CS$20),6,99)))+VALUE(TRIM(MID(TRIM($CS$20),6,99))))+5*VALUE(TRIM(MID(TRIM($CS$20),6,99))))<=$CS$12,((INT($CS$11/VALUE(TRIM(MID(TRIM($CS$20),6,99))))*VALUE(TRIM(MID(TRIM($CS$20),6,99)))+VALUE(TRIM(MID(TRIM($CS$20),6,99))))+5*VALUE(TRIM(MID(TRIM($CS$20),6,99)))),NA()),VALUE(TRIM(MID(SUBSTITUTE(SUBSTITUTE(SUBSTITUTE(TRIM($CS$20),",",";")," ",""),";",REPT(" ",99)),496,99)))),NA()) | DA9: =IF($CT$9="","",IFERROR(IF(ABS($CT$9)>=1000000,ROUND($CT$9/1000000,MAX(0,1-INT(LOG10($CS$27/1000000))))&"M",IF(ABS($CT$9)>=1000,ROUND($CT$9/1000,MAX(0,1-INT(LOG10($CS$27/1000))))&"k",TEXT($CT$9,"#,##0"))),TEXT($CT$9,"#,##0"))) | DB9: 11.75 | DC9: 11.925 | DD9: 11 | DE9: likely code | DG9: =IF(6<=$DF$13,$DF$14+(6-1)*$DF$16,"") | DH9: =IF(6>$DF$13,"",SUMIFS($DD$4:$DD$203,$DC$4:$DC$203,">="&$DG$9,$DC$4:$DC$203,IF(6=$DF$13,"<=","<")&($DG$9+$DF$16))) | DI9: ="" | DJ9: =IF(AND(6>=11-$DF$17,6<=9),$DF$18,0) | DK9: =IFERROR(IF(AND($DM$6>=$DF$14,$DM$6<=$DF$15),10+0.5+100*($DM$6-$DF$14)/($DF$15-$DF$14),NA()),NA()) | DL9: =IF(ISNA($DK$9),NA(),MAX($DJ$4:$DJ$123)) | DM9: =IFERROR(IF(LEFT(LOWER(TRIM($DF$20)),5)="every",IF(((INT($DF$11/VALUE(TRIM(MID(TRIM($DF$20),6,99))))*VALUE(TRIM(MID(TRIM($DF$20),6,99)))+VALUE(TRIM(MID(TRIM($DF$20),6,99))))+5*VALUE(TRIM(MID(TRIM($DF$20),6,99))))<=$DF$12,((INT($DF$11/VALUE(TRIM(MID(TRIM($DF$20),6,99))))*VALUE(TRIM(MID(TRIM($DF$20),6,99)))+VALUE(TRIM(MID(TRIM($DF$20),6,99))))+5*VALUE(TRIM(MID(TRIM($DF$20),6,99)))),NA()),VALUE(TRIM(MID(SUBSTITUTE(SUBSTITUTE(SUBSTITUTE(TRIM($DF$20),",",";")," ",""),";",REPT(" ",99)),496,99)))),NA()) | DN9: =IF($DG$9="","",IFERROR(IF(ABS($DG$9)>=1000000,ROUND($DG$9/1000000,MAX(0,1-INT(LOG10($DF$27/1000000))))&"M",IF(ABS($DG$9)>=1000,ROUND($DG$9/1000,MAX(0,1-INT(LOG10($DF$27/1000))))&"k",TEXT($DG$9,"#,##0.0"))),TEXT($DG$9,"#,##0.0"))) | DO9: 7.625 | DP9: 7.6375 | DQ9: 8 | DR9: likely code | DT9: =IF(6<=$DS$13,$DS$14+(6-1)*$DS$16,"") | DU9: =IF(6>$DS$13,"",SUMIFS($DQ$4:$DQ$203,$DP$4:$DP$203,">="&$DT$9,$DP$4:$DP$203,IF(6=$DS$13,"<=","<")&($DT$9+$DS$16))) | DV9: ="" | DW9: =IF(AND(6>=11-$DS$17,6<=9),$DS$18,0) | DX9: =IFERROR(IF(AND($DZ$6>=$DS$14,$DZ$6<=$DS$15),10+0.5+100*($DZ$6-$DS$14)/($DS$15-$DS$14),NA()),NA()) | DY9: =IF(ISNA($DX$9),NA(),MAX($DW$4:$DW$123)) | DZ9: =IFERROR(IF(LEFT(LOWER(TRIM($DS$20)),5)="every",IF(((INT($DS$11/VALUE(TRIM(MID(TRIM($DS$20),6,99))))*VALUE(TRIM(MID(TRIM($DS$20),6,99)))+VALUE(TRIM(MID(TRIM($DS$20),6,99))))+5*VALUE(TRIM(MID(TRIM($DS$20),6,99))))<=$DS$12,((INT($DS$11/VALUE(TRIM(MID(TRIM($DS$20),6,99))))*VALUE(TRIM(MID(TRIM($DS$20),6,99)))+VALUE(TRIM(MID(TRIM($DS$20),6,99))))+5*VALUE(TRIM(MID(TRIM($DS$20),6,99)))),NA()),VALUE(TRIM(MID(SUBSTITUTE(SUBSTITUTE(SUBSTITUTE(TRIM($DS$20),",",";")," ",""),";",REPT(" ",99)),496,99)))),NA()) | EA9: =IF($DT$9="","",IFERROR(IF(ABS($DT$9)>=1000000,ROUND($DT$9/1000000,MAX(0,1-INT(LOG10($DS$27/1000000))))&"M",IF(ABS($DT$9)>=1000,ROUND($DT$9/1000,MAX(0,1-INT(LOG10($DS$27/1000))))&"k",TEXT($DT$9,"#,##0.0"))),TEXT($DT$9,"#,##0.0"))) | EB9: 2.5 | EC9: 2.75 | ED9: 55 | EE9: likely code | EG9: =IF(6<=$EF$13,$EF$14+(6-1)*$EF$16,"") | EH9: =IF(6>$EF$13,"",SUMIFS($ED$4:$ED$203,$EC$4:$EC$203,">="&$EG$9,$EC$4:$EC$203,IF(6=$EF$13,"<=","<")&($EG$9+$EF$16))) | EI9: ="" | EJ9: =IF(AND(6>=11-$EF$17,6<=9),$EF$18,0) | EK9: =IFERROR(IF(AND($EM$6>=$EF$14,$EM$6<=$EF$15),10+0.5+100*($EM$6-$EF$14)/($EF$15-$EF$14),NA()),NA()) | EL9: =IF(ISNA($EK$9),NA(),MAX($EJ$4:$EJ$123)) | EM9: =IFERROR(IF(LEFT(LOWER(TRIM($EF$20)),5)="every",IF(((INT($EF$11/VALUE(TRIM(MID(TRIM($EF$20),6,99))))*VALUE(TRIM(MID(TRIM($EF$20),6,99)))+VALUE(TRIM(MID(TRIM($EF$20),6,99))))+5*VALUE(TRIM(MID(TRIM($EF$20),6,99))))<=$EF$12,((INT($EF$11/VALUE(TRIM(MID(TRIM($EF$20),6,99))))*VALUE(TRIM(MID(TRIM($EF$20),6,99)))+VALUE(TRIM(MID(TRIM($EF$20),6,99))))+5*VALUE(TRIM(MID(TRIM($EF$20),6,99)))),NA()),VALUE(TRIM(MID(SUBSTITUTE(SUBSTITUTE(SUBSTITUTE(TRIM($EF$20),",",";")," ",""),";",REPT(" ",99)),496,99)))),NA()) | EN9: =IF($EG$9="","",IFERROR(IF(ABS($EG$9)>=1000000,ROUND($EG$9/1000000,MAX(0,1-INT(LOG10($EF$27/1000000))))&"M",IF(ABS($EG$9)>=1000,ROUND($EG$9/1000,MAX(0,1-INT(LOG10($EF$27/1000))))&"k",TEXT($EG$9,"#,##0"))),TEXT($EG$9,"#,##0"))) | EO9: 0.0875 | EP9: 0.09625 | EQ9: 152 | ER9: likely code | ET9: =IF(6<=$ES$13,$ES$14+(6-1)*$ES$16,"") | EU9: =IF(6>$ES$13,"",SUMIFS($EQ$4:$EQ$203,$EP$4:$EP$203,">="&$ET$9,$EP$4:$EP$203,IF(6=$ES$13,"<=","<")&($ET$9+$ES$16))) | EV9: ="" | EW9: =IF(AND(6>=11-$ES$17,6<=9),$ES$18,0) | EX9: =IFERROR(IF(AND($EZ$6>=$ES$14,$EZ$6<=$ES$15),10+0.5+100*($EZ$6-$ES$14)/($ES$15-$ES$14),NA()),NA()) | EY9: =IF(ISNA($EX$9),NA(),MAX($EW$4:$EW$123)) | EZ9: =IFERROR(IF(LEFT(LOWER(TRIM($ES$20)),5)="every",IF(((INT($ES$11/VALUE(TRIM(MID(TRIM($ES$20),6,99))))*VALUE(TRIM(MID(TRIM($ES$20),6,99)))+VALUE(TRIM(MID(TRIM($ES$20),6,99))))+5*VALUE(TRIM(MID(TRIM($ES$20),6,99))))<=$ES$12,((INT($ES$11/VALUE(TRIM(MID(TRIM($ES$20),6,99))))*VALUE(TRIM(MID(TRIM($ES$20),6,99)))+VALUE(TRIM(MID(TRIM($ES$20),6,99))))+5*VALUE(TRIM(MID(TRIM($ES$20),6,99)))),NA()),VALUE(TRIM(MID(SUBSTITUTE(SUBSTITUTE(SUBSTITUTE(TRIM($ES$20),",",";")," ",""),";",REPT(" ",99)),496,99)))),NA()) | FA9: =IF($ET$9="","",IFERROR(IF(ABS($ET$9)>=1000000,ROUND($ET$9/1000000,MAX(0,1-INT(LOG10($ES$27/1000000))))&"M",IF(ABS($ET$9)>=1000,ROUND($ET$9/1000,MAX(0,1-INT(LOG10($ES$27/1000))))&"k",TEXT($ET$9,"0.00"))),TEXT($ET$9,"0.00")))
