Workbook

Sheet Home
B1: Credit Risk Review — Line Sheet System
B2: Independent review per the 2020 Interagency Guidance on Credit Risk Review Systems: rely on LOB information only after critically evaluating it; every conclusion traces to a source.
B4: How the system works
B5: 1. Ingest | C5: Run the engine on source documents: regulatory PDFs, internal policy, credit memos (python -m engine extract-thresholds / extract-cam).
B6: 2. Stage | C6: Extracted rows land on Staging_TypeA / Staging_TypeB with the verbatim source span, page/section, and a confidence flag. Nothing is live yet.
B7: 3. Confirm | C7: A reviewer marks each staged row Confirmed or Rejected. Low-confidence and Coverage Gap rows are highlighted for resolution.
B8: 4. Promote | C8: python -m engine promote copies ONLY Confirmed rows to the Crosswalk (thresholds) and Assertions (credit-memo facts) sheets.
B9: 5. Review | C9: Line sheets re-derive each asserted value independently, compare to the in-force threshold for the review date and agency, and record Yes / No / N/A / Obs answers.
B10: 6. Report | C10: Database and dashboards roll up exceptions (No only), observations (Obs only), rates (N/A excluded), grades, and concentrations.
B12: Answer convention (identical on every form)
B13: Yes | C13: Clean pass. Note optional.
B14: No | C14: Exception / finding. Drives the exception rollup and aging. Rationale note required.
B15: N/A | C15: Not applicable. Excluded from numerator AND denominator of every rate.
B16: Obs | C16: Pass with a note on record. Note required. Never counted as an exception; surfaces only in the Observations view for thematic patterns.
B18: Color conventions
B19: Blue | C19: Hardcoded inputs you can change
B20: Black | C20: Formulas and calculations
B21: Green | C21: Links pulling from other sheets (Crosswalk, Settings)
B22: Yellow fill | C22: Key assumptions needing attention
B24: Navigation
B25: Settings | C25: As-of date, primary agency, capital inputs
B26: LS_CI | C26: C&I / Commercial line sheet (reference template)
B27: LS_CRE | C27: Commercial Real Estate line sheet
B28: LS_LL | C28: Leveraged Lending line sheet
B29: LS_ABL | C29: Asset-Based Lending line sheet
B30: LS_ARG | C30: ARG / Workout line sheet
B31: LS_COMP | C31: General Compliance line sheet
B32: LS_IA | C32: Internal Audit test sheet - generic template for audit shops
B33: Database | C33: One row per credit per review
B34: Responses | C34: One row per question per credit
B35: Dash_Portfolio | C35: Portfolio overview & grade migration
B36: Dash_Exceptions | C36: Exceptions (No answers only), severity, aging
... B43: Staging_TypeB | C43: Extracted credit-memo assertions awaiting confirmation

Sheet Settings
B1: Settings & Bank Inputs
B3: Review controls
B4: Review As-Of Date | C4: 46183 | D4: Drives crosswalk Active/Rescinded status and exception aging.
B5: Primary Supervisory Agency | C5: OCC | D5: Agency whose thresholds the dashboards cite. Forms use this plus internal policy.
B7: Capital & concentration inputs
B8: Total Risk-Based Capital ($000) | C8: 185000 | D8: Source: Call Report Schedule RC-R, 3/31/2026 filing.
B9: Construction, Land & Development Loans ($000) | C9: 142000 | D9: Source: internal MIS concentration report, 5/31/2026.
B10: Total Non-Owner-Occupied CRE Loans ($000) | C10: 612000 | D10: Source: internal MIS concentration report, 5/31/2026.
B11: Non-OO CRE Balance 36 Months Ago ($000) | C11: 425000 | D11: Source: internal MIS concentration report, 5/31/2023.

Sheet Lists
A1: Answers | B1: Status | C1: Agencies | D1: Grade | E1: Category | F1: PropType | G1: Severity | H1: ReviewType | J1: Grade | K1: Category | L1: Regulatory Definition
A2: Yes | B2: In Progress | C2: OCC | D2: 1 | E2: Pass | F2: Office | G2: High | H2: Periodic | J2: 1 | K2: Pass | L2: Substantially risk-free; strongest financial condition.
A3: No | B3: Complete | C3: FRB | D3: 2 | E3: Pass | F3: Multifamily | G3: Medium | H3: Targeted | J3: 2 | K3: Pass | L3: Strong financial condition; ample debt-service capacity.
A4: N/A | C4: FDIC | D4: 3 | E4: Pass | F4: Retail | G4: Low | H4: Continuous | J4: 3 | K4: Pass | L4: Satisfactory; adequate capacity with identifiable secondary support.
A5: Obs | C5: CFPB | D5: 4 | E5: Pass | F5: Industrial | J5: 4 | K5: Pass | L5: Acceptable with attention; tighter margins or higher leverage.
C6: Internal | D6: 5 | E6: Special Mention | F6: Hospitality | J6: 5 | K6: Special Mention | L6: Potential weaknesses deserving close attention; if uncorrected may weaken prospects.
D7: 6 | E7: Substandard | F7: Other | J7: 6 | K7: Substandard | L7: Well-defined weakness; distinct possibility of loss if not corrected.
D8: 7 | E8: Doubtful | J8: 7 | K8: Doubtful | L8: Collection in full highly questionable and improbable.
D9: 8 | E9: Loss | J9: 8 | K9: Loss | L9: Considered uncollectible; charge-off warranted.

Sheet Questions
A1: QID | B1: Seg | C1: Section (2020 CRR criteria) | D1: Question | E1: Severity
A2: CI-Q01 | B2: CI | C2: Credit Quality & Risk-Grade Accuracy | D2: LOB-assigned risk grade is supported by current financial analysis. | E2: High
A3: CI-Q02 | B3: CI | C3: Credit Quality & Risk-Grade Accuracy | D3: Grade reflects all material credit weaknesses identified in the file. | E3: High
A4: CI-Q03 | B4: CI | C4: Credit Quality & Risk-Grade Accuracy | D4: Grade was reviewed/affirmed within policy frequency requirements. | E4: Medium
A5: CI-Q04 | B5: CI | C5: Underwriting Soundness | D5: Underwriting at origination conformed to policy standards in effect. | E5: High
A6: CI-Q05 | B6: CI | C6: Underwriting Soundness | D6: Financial statements meet policy quality/recency requirements (audit level, age). | E6: Medium
A7: CI-Q06 | B7: CI | C7: Underwriting Soundness | D7: Analysis critically evaluates borrower-provided information rather than restating it. | E7: High
A8: CI-Q07 | B8: CI | C8: Repayment Sources & Projections | D8: Primary repayment source is clearly identified and quantitatively supported. | E8: High
A9: CI-Q08 | B9: CI | C9: Repayment Sources & Projections | D9: Secondary repayment source is identified and realizable. | E9: Medium
A10: CI-Q09 | B10: CI | C10: Repayment Sources & Projections | D10: Projection assumptions are reasonable versus historical performance and market data. | E10: High
A11: CI-Q10 | B11: CI | C11: Guarantor / Sponsor Creditworthiness | D11: Guarantor/sponsor financial condition is current, analyzed, and supports reliance. | E11: Medium
A12: CI-Q11 | B12: CI | C12: Guarantor / Sponsor Creditworthiness | D12: Guaranty enforceability documented (signed, unconditional unless approved otherwise). | E12: Medium
... A179: COMP-Q26 | B179: COMP | C179: Consumer-Adjacent Touchpoints | D179: Fair-lending / HMDA data points captured where the credit is reportable. | E179: Medium

Sheet LS_CI
B1: C&I / Commercial — Credit Risk Review Line Sheet
B2: Independent challenge function: re-derive, confirm, or dispute each asserted value. Answers: Yes / No / N/A / Obs (Obs requires a note; N/A is excluded from all rates).
B4: A. Credit Identification
B5: Credit ID | C5: CI-2026001 | E5: Review Date | F5: 45883 | H5: LOB Assigned Grade | I5: 2
B6: Borrower | C6: Meridian Fabrication Holdings, LLC | E6: Financials As-Of | F6: 45808 | H6: CRR Concluded Grade | I6: 2
B7: Commitment ($000) | C7: 25000 | E7: Reviewer | F7: A. Chen | H7: Regulatory Category | I7: =IF($I$6="","",VLOOKUP($I$6,Lists!$D$2:$E$9,2,0)) -> Pass
B8: Review Type | C8: Periodic | E8: Subtype / Property Type | H8: Grade Concurrence | I8: =IF(OR($I$5="",$I$6=""),"",IF($I$5=$I$6,"Concur","Grade Change")) -> Concur
B10: B. Financial Inputs — CRR Independent Spread
B11: Input | C11: Value | D11: Source / Note
B12: Revenue ($000) | C12: 96400
B13: EBITDA ($000) | C13: 17100
B14: Interest Expense ($000) | C14: 3400
B15: CPLTD ($000) | C15: 4980 | D15: Current portion of long-term debt
B16: Cash Taxes ($000) | C16: 2400
B17: Maintenance Capex ($000) | C17: 1800
B18: Distributions ($000) | C18: 1000
B19: Total Debt ($000) | C19: 65000
B20: Senior Debt ($000) | C20: 49590
B21: Current Assets ($000) | C21: 31200
B22: Current Liabilities ($000) | C22: 18350
B23: Accounts Receivable ($000) | C23: 14800
B24: Inventory ($000) | C24: 9650
B25: Accounts Payable ($000) | C25: 7900
B26: COGS ($000) | C26: 66500
B27: Tangible Net Worth ($000) | C27: 28900
B28: Guarantor Cash Flow ($000) | C28: 1200 | D28: Personal CF available for debt service
B29: Guarantor Debt Service ($000) | C29: 600
B31: C. Ratio Engine — Independent vs. Asserted
A32: ID | B32: Ratio | C32: CRR Independent | D32: Per CAM (Asserted) | E32: Variance | F32: Alignment | G32: Threshold (In Force) | H32: Vs Threshold | J32: Note
A33: CI-R1 | B33: Total Debt / EBITDA | C33: =IF($C$13<=0,"n/m",$C$19/$C$13) -> 3.8011696 | D33: 3.8 | E33: =IF(OR(ISTEXT(C33),C33="",D33=""),"",C33-D33) -> 0.0011695906 | F33: =IF(E33="","",IF(ABS(E33)<=0.05*MAX(ABS(D33),0.0001),"Aligned","Variance")) -> Aligned | G33: =IF(SUMPRODUCT(MAX((Crosswalk!$O$2:$O$300="Total Debt / EBITDA|"&PrimaryAgency)*(Crosswalk!$H$2:$H$300<>"")*(Crosswalk!$H$2:$H$300<=$F$5)*((Crosswalk!$I$2:$I$300="")+(Crosswalk!$I$2:$I$300>$F$5))*Crosswalk!$C$2:$C$300))=0,"",SUMPRODUCT(MAX((Crosswalk!$O$2:$O$300="Total Debt / EBITDA|"&PrimaryAgency)*(Crosswalk!$H$2:$H$300<>"")*(Crosswalk!$H$2:$H$300<=$F$5)*((Crosswalk!$I$2:$I$300="")+(Crosswalk!$I$2:$I$300>$F$5))*Crosswalk!$C$2:$C$300))) -> 6 | H33: =IF(OR(G33="",ISTEXT(C33),C33=""),"n/a",IF(C33>G33,"Exception","Pass")) -> Pass
A34: CI-R2 | B34: Senior Debt / EBITDA | C34: =IF($C$13<=0,"n/m",$C$20/$C$13) -> 2.9 | D34: 2.9 | E34: =IF(OR(ISTEXT(C34),C34="",D34=""),"",C34-D34) -> 0 | F34: =IF(E34="","",IF(ABS(E34)<=0.05*MAX(ABS(D34),0.0001),"Aligned","Variance")) -> Aligned | G34: =IF(SUMPRODUCT(MAX((Crosswalk!$O$2:$O$300="Senior Debt / EBITDA|"&PrimaryAgency)*(Crosswalk!$H$2:$H$300<>"")*(Crosswalk!$H$2:$H$300<=$F$5)*((Crosswalk!$I$2:$I$300="")+(Crosswalk!$I$2:$I$300>$F$5))*Crosswalk!$C$2:$C$300))=0,"",SUMPRODUCT(MAX((Crosswalk!$O$2:$O$300="Senior Debt / EBITDA|"&PrimaryAgency)*(Crosswalk!$H$2:$H$300<>"")*(Crosswalk!$H$2:$H$300<=$F$5)*((Crosswalk!$I$2:$I$300="")+(Crosswalk!$I$2:$I$300>$F$5))*Crosswalk!$C$2:$C$300))) -> 3 | H34: =IF(OR(G34="",ISTEXT(C34),C34=""),"n/a",IF(C34>G34,"Exception","Pass")) -> Pass
A35: CI-R3 | B35: DSCR | C35: =IF(($C$14+$C$15)=0,"n/m",($C$13-$C$16-$C$17-$C$18)/($C$14+$C$15)) -> 1.4200477 | D35: 1.42 | E35: =IF(OR(ISTEXT(C35),C35="",D35=""),"",C35-D35) -> 4.7732697e-05 | F35: =IF(E35="","",IF(ABS(E35)<=0.05*MAX(ABS(D35),0.0001),"Aligned","Variance")) -> Aligned | G35: =IF(SUMPRODUCT(MAX((Crosswalk!$O$2:$O$300="Minimum DSCR|"&"Internal")*(Crosswalk!$H$2:$H$300<>"")*(Crosswalk!$H$2:$H$300<=$F$5)*((Crosswalk!$I$2:$I$300="")+(Crosswalk!$I$2:$I$300>$F$5))*Crosswalk!$C$2:$C$300))=0,"",SUMPRODUCT(MAX((Crosswalk!$O$2:$O$300="Minimum DSCR|"&"Internal")*(Crosswalk!$H$2:$H$300<>"")*(Crosswalk!$H$2:$H$300<=$F$5)*((Crosswalk!$I$2:$I$300="")+(Crosswalk!$I$2:$I$300>$F$5))*Crosswalk!$C$2:$C$300))) -> 1.25 | H35: =IF(OR(G35="",ISTEXT(C35),C35=""),"n/a",IF(C35<G35,"Exception","Pass")) -> Pass
A36: CI-R4 | B36: Fixed-Charge Coverage | C36: =IF(($C$14+$C$15)=0,"n/m",($C$13-$C$16-$C$18)/($C$14+$C$15)) -> 1.6348449 | D36: 1.25 | E36: =IF(OR(ISTEXT(C36),C36="",D36=""),"",C36-D36) -> 0.38484487 | F36: =IF(E36="","",IF(ABS(E36)<=0.05*MAX(ABS(D36),0.0001),"Aligned","Variance")) -> Variance | H36: n/a
A37: CI-R5 | B37: Interest Coverage | C37: =IF($C$14=0,"n/m",$C$13/$C$14) -> 5.0294118 | D37: 3.6 | E37: =IF(OR(ISTEXT(C37),C37="",D37=""),"",C37-D37) -> 1.4294118 | F37: =IF(E37="","",IF(ABS(E37)<=0.05*MAX(ABS(D37),0.0001),"Aligned","Variance")) -> Variance | H37: n/a
A38: CI-R6 | B38: Current Ratio | C38: =IF($C$22=0,"n/m",$C$21/$C$22) -> 1.7002725 | D38: 1.7 | E38: =IF(OR(ISTEXT(C38),C38="",D38=""),"",C38-D38) -> 0.00027247956 | F38: =IF(E38="","",IF(ABS(E38)<=0.05*MAX(ABS(D38),0.0001),"Aligned","Variance")) -> Aligned | H38: n/a
A39: CI-R7 | B39: Working Capital Cycle (days) | C39: =IF(OR($C$12=0,$C$26=0),"n/m",365*$C$23/$C$12+365*$C$24/$C$26-365*$C$25/$C$26) -> 65.642608 | E39: =IF(OR(ISTEXT(C39),C39="",D39=""),"",C39-D39) | F39: =IF(E39="","",IF(ABS(E39)<=0.05*MAX(ABS(D39),0.0001),"Aligned","Variance")) | H39: n/a
A40: CI-R8 | B40: Debt / Tangible Net Worth | C40: =IF($C$27<=0,"n/m",$C$19/$C$27) -> 2.2491349 | E40: =IF(OR(ISTEXT(C40),C40="",D40=""),"",C40-D40) | F40: =IF(E40="","",IF(ABS(E40)<=0.05*MAX(ABS(D40),0.0001),"Aligned","Variance")) | H40: n/a
A41: CI-R9 | B41: Global DSCR (incl. guarantor) | C41: =IF(($C$14+$C$15+$C$29)=0,"n/m",($C$13-$C$16-$C$17-$C$18+$C$28)/($C$14+$C$15+$C$29)) -> 1.4587973 | D41: 1.55 | E41: =IF(OR(ISTEXT(C41),C41="",D41=""),"",C41-D41) -> -0.091202673 | F41: =IF(E41="","",IF(ABS(E41)<=0.05*MAX(ABS(D41),0.0001),"Aligned","Variance")) -> Variance | H41: n/a
B43: D. Credit Quality & Risk-Grade Accuracy
A44: ID | B44: Review Question | C44: Severity | D44: Answer | E44: Reviewer Note / Finding Rationale | J44: Check
A45: CI-Q01 | B45: LOB-assigned risk grade is supported by current financial analysis. | C45: High | D45: Yes | J45: =IF(AND(D45="Obs",E45=""),"Note required",IF(AND(D45="No",E45=""),"Rationale required",""))
A46: CI-Q02 | B46: Grade reflects all material credit weaknesses identified in the file. | C46: High | D46: Yes | J46: =IF(AND(D46="Obs",E46=""),"Note required",IF(AND(D46="No",E46=""),"Rationale required",""))
A47: CI-Q03 | B47: Grade was reviewed/affirmed within policy frequency requirements. | C47: Medium | D47: N/A | J47: =IF(AND(D47="Obs",E47=""),"Note required",IF(AND(D47="No",E47=""),"Rationale required",""))
B48: E. Underwriting Soundness
A49: ID | B49: Review Question | C49: Severity | D49: Answer | E49: Reviewer Note / Finding Rationale | J49: Check
A50: CI-Q04 | B50: Underwriting at origination conformed to policy standards in effect. | C50: High | D50: Yes | J50: =IF(AND(D50="Obs",E50=""),"Note required",IF(AND(D50="No",E50=""),"Rationale required",""))
A51: CI-Q05 | B51: Financial statements meet policy quality/recency requirements (audit level, age). | C51: Medium | D51: Yes | J51: =IF(AND(D51="Obs",E51=""),"Note required",IF(AND(D51="No",E51=""),"Rationale required",""))
A52: CI-Q06 | B52: Analysis critically evaluates borrower-provided information rather than restating it. | C52: High | D52: Yes | J52: =IF(AND(D52="Obs",E52=""),"Note required",IF(AND(D52="No",E52=""),"Rationale required",""))
B53: F. Repayment Sources & Projections
A54: ID | B54: Review Question | C54: Severity | D54: Answer | E54: Reviewer Note / Finding Rationale | J54: Check
A55: CI-Q07 | B55: Primary repayment source is clearly identified and quantitatively supported. | C55: High | D55: Yes | J55: =IF(AND(D55="Obs",E55=""),"Note required",IF(AND(D55="No",E55=""),"Rationale required",""))
A56: CI-Q08 | B56: Secondary repayment source is identified and realizable. | C56: Medium | D56: Yes | J56: =IF(AND(D56="Obs",E56=""),"Note required",IF(AND(D56="No",E56=""),"Rationale required",""))
A57: CI-Q09 | B57: Projection assumptions are reasonable versus historical performance and market data. | C57: High | D57: No | E57: UCC continuation lapsed; lien perfection not verified at review date. | J57: =IF(AND(D57="Obs",E57=""),"Note required",IF(AND(D57="No",E57=""),"Rationale required",""))
B58: G. Guarantor / Sponsor Creditworthiness
A59: ID | B59: Review Question | C59: Severity | D59: Answer | E59: Reviewer Note / Finding Rationale | J59: Check
A60: CI-Q10 | B60: Guarantor/sponsor financial condition is current, analyzed, and supports reliance. | C60: Medium | D60: N/A | J60: =IF(AND(D60="Obs",E60=""),"Note required",IF(AND(D60="No",E60=""),"Rationale required",""))
A61: CI-Q11 | B61: Guaranty enforceability documented (signed, unconditional unless approved otherwise). | C61: Medium | D61: Yes | J61: =IF(AND(D61="Obs",E61=""),"Note required",IF(AND(D61="No",E61=""),"Rationale required",""))
B62: H. Credit & Collateral Documentation / Lien Perfection
A63: ID | B63: Review Question | C63: Severity | D63: Answer | E63: Reviewer Note / Finding Rationale | J63: Check
A64: CI-Q12 | B64: All required credit documents are present, current, and properly executed. | C64: High | D64: Yes | J64: =IF(AND(D64="Obs",E64=""),"Note required",IF(AND(D64="No",E64=""),"Rationale required",""))
A65: CI-Q13 | B65: Lien positions are perfected and verified (searches, filings, titles). | C65: High | D65: Yes | J65: =IF(AND(D65="Obs",E65=""),"Note required",IF(AND(D65="No",E65=""),"Rationale required",""))
A66: CI-Q14 | B66: Insurance requirements are met and the bank is loss payee where required. | C66: Low | D66: No | E66: UCC continuation lapsed; lien perfection not verified at review date. | J66: =IF(AND(D66="Obs",E66=""),"Note required",IF(AND(D66="No",E66=""),"Rationale required",""))
B67: I. Approval Authority
A68: ID | B68: Review Question | C68: Severity | D68: Answer | E68: Reviewer Note / Finding Rationale | J68: Check
A69: CI-Q15 | B69: Credit was approved within delegated authority of the approving officer(s). | C69: High | D69: Yes | J69: =IF(AND(D69="Obs",E69=""),"Note required",IF(AND(D69="No",E69=""),"Rationale required",""))
A70: CI-Q16 | B70: Policy exceptions at approval were identified, justified, and approved at proper level. | C70: Medium | D70: Yes | J70: =IF(AND(D70="Obs",E70=""),"Note required",IF(AND(D70="No",E70=""),"Rationale required",""))
B71: J. Covenant Adherence
A72: ID | B72: Review Question | C72: Severity | D72: Answer | E72: Reviewer Note / Finding Rationale | J72: Check
A73: CI-Q17 | B73: Covenant compliance is tested at required frequency with evidence retained. | C73: Medium | D73: Yes | J73: =IF(AND(D73="Obs",E73=""),"Note required",IF(AND(D73="No",E73=""),"Rationale required",""))
A74: CI-Q18 | B74: Covenant breaches (if any) were identified, reported, and waived/cured per policy. | C74: High | D74: Yes | J74: =IF(AND(D74="Obs",E74=""),"Note required",IF(AND(D74="No",E74=""),"Rationale required",""))
B75: K. Policy Compliance
A76: ID | B76: Review Question | C76: Severity | D76: Answer | E76: Reviewer Note / Finding Rationale | J76: Check
A77: CI-Q19 | B77: Credit complies with internal lending policy limits (hold limits, tenor, pricing floors). | C77: Medium | D77: Yes | J77: =IF(AND(D77="Obs",E77=""),"Note required",IF(AND(D77="No",E77=""),"Rationale required",""))
A78: CI-Q20 | B78: Required periodic monitoring (annual review, site visits) is current. | C78: Medium | D78: N/A | J78: =IF(AND(D78="Obs",E78=""),"Note required",IF(AND(D78="No",E78=""),"Rationale required",""))
B79: L. Five Cs of Credit
A80: ID | B80: Review Question | C80: Severity | D80: Answer | E80: Reviewer Note / Finding Rationale | J80: Check
A81: CI-Q21 | B81: Character: management track record, credit history, and integrity assessed. | C81: Medium | D81: Yes | J81: =IF(AND(D81="Obs",E81=""),"Note required",IF(AND(D81="No",E81=""),"Rationale required",""))
A82: CI-Q22 | B82: Capacity: cash-flow capacity analysis covers debt service under stress. | C82: High | D82: Yes | J82: =IF(AND(D82="Obs",E82=""),"Note required",IF(AND(D82="No",E82=""),"Rationale required",""))
A83: CI-Q23 | B83: Capital: borrower equity/tangible net worth is adequate for the risk. | C83: Medium | D83: Yes | J83: =IF(AND(D83="Obs",E83=""),"Note required",IF(AND(D83="No",E83=""),"Rationale required",""))
A84: CI-Q24 | B84: Collateral: valuation basis is current and discounts are appropriate. | C84: Medium | D84: Yes | J84: =IF(AND(D84="Obs",E84=""),"Note required",IF(AND(D84="No",E84=""),"Rationale required",""))
A85: CI-Q25 | B85: Conditions: industry, market, and macro conditions are evaluated. | C85: Low | D85: N/A | J85: =IF(AND(D85="Obs",E85=""),"Note required",IF(AND(D85="No",E85=""),"Rationale required",""))
B86: M. Global Cash Flow
A87: ID | B87: Review Question | C87: Severity | D87: Answer | E87: Reviewer Note / Finding Rationale | J87: Check
A88: CI-Q26 | B88: Global cash flow combines business and guarantor sources with consistent treatment of taxes/living expenses. | C88: High | D88: Yes | J88: =IF(AND(D88="Obs",E88=""),"Note required",IF(AND(D88="No",E88=""),"Rationale required",""))
A89: CI-Q27 | B89: Inter-company / related-entity flows are identified and not double-counted. | C89: Medium | D89: Yes | J89: =IF(AND(D89="Obs",E89=""),"Note required",IF(AND(D89="No",E89=""),"Rationale required",""))
B91: Review Summary
B92: Questions (total) | C92: =27 -> 27
B93: Answered (Yes / No / N/A / Obs) | C93: =COUNTIF(D45:D89,"Yes")+COUNTIF(D45:D89,"No")+COUNTIF(D45:D89,"N/A")+COUNTIF(D45:D89,"Obs") -> 27
B94: Completion % | C94: =IF(C92=0,"",C93/C92) -> 1
B95: Applicable (excl. N/A) | C95: =C93-COUNTIF(D45:D89,"N/A") -> 23
B96: Exceptions (No) | C96: =COUNTIF(D45:D89,"No") -> 2
B97: Observations (Obs) | C97: =COUNTIF(D45:D89,"Obs") -> 0
B98: Exception Rate (No / Applicable) | C98: =IF(C95=0,"",C96/C95) -> 0.086956522
B99: Note Checks Outstanding | C99: =COUNTIF(J45:J89,"*required*") -> 0
B101: CRR Conclusion / Grade Rationale:

Sheet LS_CRE
B1: Commercial Real Estate — Credit Risk Review Line Sheet
B2: Independent challenge function: re-derive, confirm, or dispute each asserted value. Answers: Yes / No / N/A / Obs (Obs requires a note; N/A is excluded from all rates).
B4: A. Credit Identification
B5: Credit ID | C5: CRE-2026001 | E5: Review Date | F5: 45883 | H5: LOB Assigned Grade | I5: 4
B6: Borrower | C6: Lakeview Office Partners LP | E6: Financials As-Of | F6: 45808 | H6: CRR Concluded Grade | I6: 4
B7: Commitment ($000) | C7: 32500 | E7: Reviewer | F7: A. Chen | H7: Regulatory Category | I7: =IF($I$6="","",VLOOKUP($I$6,Lists!$D$2:$E$9,2,0)) -> Pass
B8: Review Type | C8: Periodic | E8: Subtype / Property Type | F8: Office | H8: Grade Concurrence | I8: =IF(OR($I$5="",$I$6=""),"",IF($I$5=$I$6,"Concur","Grade Change")) -> Concur
B10: B. Financial Inputs — CRR Independent Spread
B11: Input | C11: Value | D11: Source / Note
B12: Net Operating Income ($000) | C12: 4150 | D12: In-place, trailing 12 months
B13: Annual Debt Service ($000) | C13: 3120
B14: Loan Commitment ($000) | C14: 42000
B15: Appraised Value ($000) | C15: 58500
B16: Current Occupancy (%) | C16: 0.88
B17: Leases Rolling 24 Mo (%) | C17: 0.31
B18: In-Place Cap Rate (%) | C18: 0.071
B19: Stressed Cap Rate (%) | C19: 0.085 | D19: Key assumption
B21: C. Ratio Engine — Independent vs. Asserted
A22: ID | B22: Ratio | C22: CRR Independent | D22: Per CAM (Asserted) | E22: Variance | F22: Alignment | G22: Threshold (In Force) | H22: Vs Threshold | J22: Note
A23: CRE-R1 | B23: DSCR | C23: =IF($C$13=0,"n/m",$C$12/$C$13) -> 1.3301282 | D23: 1.33 | E23: =IF(OR(ISTEXT(C23),C23="",D23=""),"",C23-D23) -> 0.00012820513 | F23: =IF(E23="","",IF(ABS(E23)<=0.05*MAX(ABS(D23),0.0001),"Aligned","Variance")) -> Aligned | G23: =IF(SUMPRODUCT(MAX((Crosswalk!$O$2:$O$300="Minimum DSCR|"&"Internal")*(Crosswalk!$H$2:$H$300<>"")*(Crosswalk!$H$2:$H$300<=$F$5)*((Crosswalk!$I$2:$I$300="")+(Crosswalk!$I$2:$I$300>$F$5))*Crosswalk!$C$2:$C$300))=0,"",SUMPRODUCT(MAX((Crosswalk!$O$2:$O$300="Minimum DSCR|"&"Internal")*(Crosswalk!$H$2:$H$300<>"")*(Crosswalk!$H$2:$H$300<=$F$5)*((Crosswalk!$I$2:$I$300="")+(Crosswalk!$I$2:$I$300>$F$5))*Crosswalk!$C$2:$C$300))) -> 1.25 | H23: =IF(OR(G23="",ISTEXT(C23),C23=""),"n/a",IF(C23<G23,"Exception","Pass")) -> Pass
A24: CRE-R2 | B24: LTV | C24: =IF($C$15=0,"n/m",$C$14/$C$15) -> 0.71794872 | D24: 0.718 | E24: =IF(OR(ISTEXT(C24),C24="",D24=""),"",C24-D24) -> -5.1282051e-05 | F24: =IF(E24="","",IF(ABS(E24)<=0.05*MAX(ABS(D24),0.0001),"Aligned","Variance")) -> Aligned | G24: =IF(SUMPRODUCT(MAX((Crosswalk!$O$2:$O$300="Maximum LTV|"&"Internal")*(Crosswalk!$H$2:$H$300<>"")*(Crosswalk!$H$2:$H$300<=$F$5)*((Crosswalk!$I$2:$I$300="")+(Crosswalk!$I$2:$I$300>$F$5))*Crosswalk!$C$2:$C$300))=0,"",SUMPRODUCT(MAX((Crosswalk!$O$2:$O$300="Maximum LTV|"&"Internal")*(Crosswalk!$H$2:$H$300<>"")*(Crosswalk!$H$2:$H$300<=$F$5)*((Crosswalk!$I$2:$I$300="")+(Crosswalk!$I$2:$I$300>$F$5))*Crosswalk!$C$2:$C$300))/100) -> 0.75 | H24: =IF(OR(G24="",ISTEXT(C24),C24=""),"n/a",IF(C24>G24,"Exception","Pass")) -> Pass
A25: CRE-R3 | B25: Debt Yield | C25: =IF($C$14=0,"n/m",$C$12/$C$14) -> 0.098809524 | D25: 0.099 | E25: =IF(OR(ISTEXT(C25),C25="",D25=""),"",C25-D25) -> -0.00019047619 | F25: =IF(E25="","",IF(ABS(E25)<=0.05*MAX(ABS(D25),0.0001),"Aligned","Variance")) -> Aligned | H25: n/a
A26: CRE-R4 | B26: Stressed Value ($000) | C26: =IF($C$19=0,"n/m",$C$12/$C$19) -> 48823.529 | E26: =IF(OR(ISTEXT(C26),C26="",D26=""),"",C26-D26) | F26: =IF(E26="","",IF(ABS(E26)<=0.05*MAX(ABS(D26),0.0001),"Aligned","Variance")) | H26: n/a
A27: CRE-R5 | B27: Stressed LTV | C27: =IF(OR($C$19=0,$C$12=0),"n/m",$C$14/($C$12/$C$19)) -> 0.86024096 | E27: =IF(OR(ISTEXT(C27),C27="",D27=""),"",C27-D27) | F27: =IF(E27="","",IF(ABS(E27)<=0.05*MAX(ABS(D27),0.0001),"Aligned","Variance")) | H27: n/a
B29: D. Credit Quality & Risk-Grade Accuracy
A30: ID | B30: Review Question | C30: Severity | D30: Answer | E30: Reviewer Note / Finding Rationale | J30: Check
A31: CRE-Q01 | B31: LOB-assigned risk grade is supported by current financial analysis. | C31: High | D31: Yes | J31: =IF(AND(D31="Obs",E31=""),"Note required",IF(AND(D31="No",E31=""),"Rationale required",""))
A32: CRE-Q02 | B32: Grade reflects all material credit weaknesses identified in the file. | C32: High | D32: Yes | J32: =IF(AND(D32="Obs",E32=""),"Note required",IF(AND(D32="No",E32=""),"Rationale required",""))
A33: CRE-Q03 | B33: Grade was reviewed/affirmed within policy frequency requirements. | C33: Medium | D33: Yes | J33: =IF(AND(D33="Obs",E33=""),"Note required",IF(AND(D33="No",E33=""),"Rationale required",""))
B34: E. Underwriting Soundness
A35: ID | B35: Review Question | C35: Severity | D35: Answer | E35: Reviewer Note / Finding Rationale | J35: Check
A36: CRE-Q04 | B36: Underwriting at origination conformed to policy standards in effect. | C36: High | D36: Yes | J36: =IF(AND(D36="Obs",E36=""),"Note required",IF(AND(D36="No",E36=""),"Rationale required",""))
A37: CRE-Q05 | B37: Financial statements meet policy quality/recency requirements (audit level, age). | C37: Medium | D37: Yes | J37: =IF(AND(D37="Obs",E37=""),"Note required",IF(AND(D37="No",E37=""),"Rationale required",""))
A38: CRE-Q06 | B38: Analysis critically evaluates borrower-provided information rather than restating it. | C38: High | D38: Yes | J38: =IF(AND(D38="Obs",E38=""),"Note required",IF(AND(D38="No",E38=""),"Rationale required",""))
B39: F. Repayment Sources & Projections
A40: ID | B40: Review Question | C40: Severity | D40: Answer | E40: Reviewer Note / Finding Rationale | J40: Check
A41: CRE-Q07 | B41: Primary repayment source is clearly identified and quantitatively supported. | C41: High | D41: Yes | J41: =IF(AND(D41="Obs",E41=""),"Note required",IF(AND(D41="No",E41=""),"Rationale required",""))
A42: CRE-Q08 | B42: Secondary repayment source is identified and realizable. | C42: Medium | D42: Yes | J42: =IF(AND(D42="Obs",E42=""),"Note required",IF(AND(D42="No",E42=""),"Rationale required",""))
A43: CRE-Q09 | B43: Projection assumptions are reasonable versus historical performance and market data. | C43: High | D43: N/A | J43: =IF(AND(D43="Obs",E43=""),"Note required",IF(AND(D43="No",E43=""),"Rationale required",""))
B44: G. Guarantor / Sponsor Creditworthiness
A45: ID | B45: Review Question | C45: Severity | D45: Answer | E45: Reviewer Note / Finding Rationale | J45: Check
A46: CRE-Q10 | B46: Guarantor/sponsor financial condition is current, analyzed, and supports reliance. | C46: Medium | D46: Obs | E46: Spread mislabels FY2024 column as FY2025; values correct. | J46: =IF(AND(D46="Obs",E46=""),"Note required",IF(AND(D46="No",E46=""),"Rationale required",""))
A47: CRE-Q11 | B47: Guaranty enforceability documented (signed, unconditional unless approved otherwise). | C47: Medium | D47: N/A | J47: =IF(AND(D47="Obs",E47=""),"Note required",IF(AND(D47="No",E47=""),"Rationale required",""))
B48: H. Credit & Collateral Documentation / Lien Perfection
A49: ID | B49: Review Question | C49: Severity | D49: Answer | E49: Reviewer Note / Finding Rationale | J49: Check
A50: CRE-Q12 | B50: All required credit documents are present, current, and properly executed. | C50: High | D50: Yes | J50: =IF(AND(D50="Obs",E50=""),"Note required",IF(AND(D50="No",E50=""),"Rationale required",""))
A51: CRE-Q13 | B51: Lien positions are perfected and verified (searches, filings, titles). | C51: High | D51: Yes | J51: =IF(AND(D51="Obs",E51=""),"Note required",IF(AND(D51="No",E51=""),"Rationale required",""))
A52: CRE-Q14 | B52: Insurance requirements are met and the bank is loss payee where required. | C52: Low | D52: Yes | J52: =IF(AND(D52="Obs",E52=""),"Note required",IF(AND(D52="No",E52=""),"Rationale required",""))
B53: I. Approval Authority
A54: ID | B54: Review Question | C54: Severity | D54: Answer | E54: Reviewer Note / Finding Rationale | J54: Check
A55: CRE-Q15 | B55: Credit was approved within delegated authority of the approving officer(s). | C55: High | D55: Yes | J55: =IF(AND(D55="Obs",E55=""),"Note required",IF(AND(D55="No",E55=""),"Rationale required",""))
A56: CRE-Q16 | B56: Policy exceptions at approval were identified, justified, and approved at proper level. | C56: Medium | D56: No | E56: Financial statements stale beyond policy window; no waiver in file. | J56: =IF(AND(D56="Obs",E56=""),"Note required",IF(AND(D56="No",E56=""),"Rationale required",""))
B57: J. Covenant Adherence
A58: ID | B58: Review Question | C58: Severity | D58: Answer | E58: Reviewer Note / Finding Rationale | J58: Check
A59: CRE-Q17 | B59: Covenant compliance is tested at required frequency with evidence retained. | C59: Medium | D59: N/A | J59: =IF(AND(D59="Obs",E59=""),"Note required",IF(AND(D59="No",E59=""),"Rationale required",""))
A60: CRE-Q18 | B60: Covenant breaches (if any) were identified, reported, and waived/cured per policy. | C60: High | D60: Yes | J60: =IF(AND(D60="Obs",E60=""),"Note required",IF(AND(D60="No",E60=""),"Rationale required",""))
B61: K. Policy Compliance
A62: ID | B62: Review Question | C62: Severity | D62: Answer | E62: Reviewer Note / Finding Rationale | J62: Check
A63: CRE-Q19 | B63: Credit complies with internal lending policy limits (hold limits, tenor, pricing floors). | C63: Medium | D63: Yes | J63: =IF(AND(D63="Obs",E63=""),"Note required",IF(AND(D63="No",E63=""),"Rationale required",""))
A64: CRE-Q20 | B64: Required periodic monitoring (annual review, site visits) is current. | C64: Medium | D64: Yes | J64: =IF(AND(D64="Obs",E64=""),"Note required",IF(AND(D64="No",E64=""),"Rationale required",""))
B65: L. Property & Market (subform: Office / Multifamily / Retail)
A66: ID | B66: Review Question | C66: Severity | D66: Answer | E66: Reviewer Note / Finding Rationale | J66: Check
A67: CRE-Q21 | B67: Property-type risk factors (office obsolescence, MF supply, retail anchor risk) addressed for the subject type. | C67: Medium | D67: Yes | J67: =IF(AND(D67="Obs",E67=""),"Note required",IF(AND(D67="No",E67=""),"Rationale required",""))
A68: CRE-Q22 | B68: Occupancy and lease rollover within 24 months are analyzed against market. | C68: High | D68: Yes | J68: =IF(AND(D68="Obs",E68=""),"Note required",IF(AND(D68="No",E68=""),"Rationale required",""))
A69: CRE-Q23 | B69: Cap-rate sensitivity / stressed-value analysis is documented. | C69: Medium | D69: Yes | J69: =IF(AND(D69="Obs",E69=""),"Note required",IF(AND(D69="No",E69=""),"Rationale required",""))
B70: M. Appraisal & Evaluation (FIRREA / USPAP)
A71: ID | B71: Review Question | C71: Severity | D71: Answer | E71: Reviewer Note / Finding Rationale | J71: Check
A72: CRE-Q24 | B72: Valuation product type (appraisal vs. evaluation) meets the regulatory threshold for this transaction size. | C72: High | D72: Yes | J72: =IF(AND(D72="Obs",E72=""),"Note required",IF(AND(D72="No",E72=""),"Rationale required",""))
A73: CRE-Q25 | B73: Appraiser was engaged independently of the credit function. | C73: High | D73: Yes | J73: =IF(AND(D73="Obs",E73=""),"Note required",IF(AND(D73="No",E73=""),"Rationale required",""))
A74: CRE-Q26 | B74: Appraisal is valid/recent for this action or revalidation is documented. | C74: Medium | D74: Yes | J74: =IF(AND(D74="Obs",E74=""),"Note required",IF(AND(D74="No",E74=""),"Rationale required",""))
A75: CRE-Q27 | B75: Appraisal review evidence is in file and issues were resolved. | C75: Medium | D75: Yes | J75: =IF(AND(D75="Obs",E75=""),"Note required",IF(AND(D75="No",E75=""),"Rationale required",""))
B77: Review Summary
B78: Questions (total) | C78: =27 -> 27
B79: Answered (Yes / No / N/A / Obs) | C79: =COUNTIF(D31:D75,"Yes")+COUNTIF(D31:D75,"No")+COUNTIF(D31:D75,"N/A")+COUNTIF(D31:D75,"Obs") -> 27
B80: Completion % | C80: =IF(C78=0,"",C79/C78) -> 1
B81: Applicable (excl. N/A) | C81: =C79-COUNTIF(D31:D75,"N/A") -> 24
B82: Exceptions (No) | C82: =COUNTIF(D31:D75,"No") -> 1
B83: Observations (Obs) | C83: =COUNTIF(D31:D75,"Obs") -> 1
B84: Exception Rate (No / Applicable) | C84: =IF(C81=0,"",C82/C81) -> 0.041666667
B85: Note Checks Outstanding | C85: =COUNTIF(J31:J75,"*required*") -> 0
B87: CRR Conclusion / Grade Rationale:

Sheet LS_LL
B1: Leveraged Lending — Credit Risk Review Line Sheet
B2: Independent challenge function: re-derive, confirm, or dispute each asserted value. Answers: Yes / No / N/A / Obs (Obs requires a note; N/A is excluded from all rates).
B4: A. Credit Identification
B5: Credit ID | C5: LL-2026001 | E5: Review Date | F5: 45883 | H5: LOB Assigned Grade | I5: 4
B6: Borrower | C6: Apex Packaging Buyout Co. | E6: Financials As-Of | F6: 45808 | H6: CRR Concluded Grade | I6: 4
B7: Commitment ($000) | C7: 27500 | E7: Reviewer | F7: A. Chen | H7: Regulatory Category | I7: =IF($I$6="","",VLOOKUP($I$6,Lists!$D$2:$E$9,2,0)) -> Pass
B8: Review Type | C8: Periodic | E8: Subtype / Property Type | H8: Grade Concurrence | I8: =IF(OR($I$5="",$I$6=""),"",IF($I$5=$I$6,"Concur","Grade Change")) -> Concur
B10: B. Financial Inputs — CRR Independent Spread
B11: Input | C11: Value | D11: Source / Note
B12: Reported EBITDA ($000) | C12: 22400
B13: EBITDA Add-Backs ($000) | C13: 4300 | D13: Key assumption - scrutinize
B14: Total Debt ($000) | C14: 152000
B15: Senior Debt ($000) | C15: 98000
B16: Base-Case Annual FCF ($000) | C16: 11500 | D16: Free cash flow available for debt repayment
B17: Enterprise Value ($000) | C17: 240000
B18: Interest Expense ($000) | C18: 13900
B20: C. Ratio Engine — Independent vs. Asserted
A21: ID | B21: Ratio | C21: CRR Independent | D21: Per CAM (Asserted) | E21: Variance | F21: Alignment | G21: Threshold (In Force) | H21: Vs Threshold | J21: Note
A22: LL-R1 | B22: Adjusted EBITDA ($000) | C22: =$C$12+$C$13 -> 26700 | E22: =IF(OR(ISTEXT(C22),C22="",D22=""),"",C22-D22) | F22: =IF(E22="","",IF(ABS(E22)<=0.05*MAX(ABS(D22),0.0001),"Aligned","Variance")) | H22: n/a
A23: LL-R2 | B23: Add-Backs % of Adj. EBITDA | C23: =IF(($C$12+$C$13)=0,"n/m",$C$13/($C$12+$C$13)) -> 0.16104869 | E23: =IF(OR(ISTEXT(C23),C23="",D23=""),"",C23-D23) | F23: =IF(E23="","",IF(ABS(E23)<=0.05*MAX(ABS(D23),0.0001),"Aligned","Variance")) | H23: n/a
A24: LL-R3 | B24: Total Debt / Adj. EBITDA | C24: =IF(($C$12+$C$13)<=0,"n/m",$C$14/($C$12+$C$13)) -> 5.6928839 | D24: 5.7 | E24: =IF(OR(ISTEXT(C24),C24="",D24=""),"",C24-D24) -> -0.0071161049 | F24: =IF(E24="","",IF(ABS(E24)<=0.05*MAX(ABS(D24),0.0001),"Aligned","Variance")) -> Aligned | G24: =IF(SUMPRODUCT(MAX((Crosswalk!$O$2:$O$300="Total Debt / EBITDA|"&PrimaryAgency)*(Crosswalk!$H$2:$H$300<>"")*(Crosswalk!$H$2:$H$300<=$F$5)*((Crosswalk!$I$2:$I$300="")+(Crosswalk!$I$2:$I$300>$F$5))*Crosswalk!$C$2:$C$300))=0,"",SUMPRODUCT(MAX((Crosswalk!$O$2:$O$300="Total Debt / EBITDA|"&PrimaryAgency)*(Crosswalk!$H$2:$H$300<>"")*(Crosswalk!$H$2:$H$300<=$F$5)*((Crosswalk!$I$2:$I$300="")+(Crosswalk!$I$2:$I$300>$F$5))*Crosswalk!$C$2:$C$300))) -> 6 | H24: =IF(OR(G24="",ISTEXT(C24),C24=""),"n/a",IF(C24>G24,"Exception","Pass")) -> Pass
A25: LL-R4 | B25: Senior Debt / Adj. EBITDA | C25: =IF(($C$12+$C$13)<=0,"n/m",$C$15/($C$12+$C$13)) -> 3.670412 | D25: 3.7 | E25: =IF(OR(ISTEXT(C25),C25="",D25=""),"",C25-D25) -> -0.029588015 | F25: =IF(E25="","",IF(ABS(E25)<=0.05*MAX(ABS(D25),0.0001),"Aligned","Variance")) -> Aligned | G25: =IF(SUMPRODUCT(MAX((Crosswalk!$O$2:$O$300="Senior Debt / EBITDA|"&PrimaryAgency)*(Crosswalk!$H$2:$H$300<>"")*(Crosswalk!$H$2:$H$300<=$F$5)*((Crosswalk!$I$2:$I$300="")+(Crosswalk!$I$2:$I$300>$F$5))*Crosswalk!$C$2:$C$300))=0,"",SUMPRODUCT(MAX((Crosswalk!$O$2:$O$300="Senior Debt / EBITDA|"&PrimaryAgency)*(Crosswalk!$H$2:$H$300<>"")*(Crosswalk!$H$2:$H$300<=$F$5)*((Crosswalk!$I$2:$I$300="")+(Crosswalk!$I$2:$I$300>$F$5))*Crosswalk!$C$2:$C$300))) -> 3 | H25: =IF(OR(G25="",ISTEXT(C25),C25=""),"n/a",IF(C25>G25,"Exception","Pass")) -> Exception
A26: LL-R5 | B26: Interest Coverage | C26: =IF($C$18=0,"n/m",($C$12+$C$13)/$C$18) -> 1.9208633 | E26: =IF(OR(ISTEXT(C26),C26="",D26=""),"",C26-D26) | F26: =IF(E26="","",IF(ABS(E26)<=0.05*MAX(ABS(D26),0.0001),"Aligned","Variance")) | H26: n/a
A27: LL-R6 | B27: Years to Repay 50% of Total Debt | C27: =IF($C$16<=0,"n/m",0.5*$C$14/$C$16) -> 6.6086957 | D27: 6.6 | E27: =IF(OR(ISTEXT(C27),C27="",D27=""),"",C27-D27) -> 0.0086956522 | F27: =IF(E27="","",IF(ABS(E27)<=0.05*MAX(ABS(D27),0.0001),"Aligned","Variance")) -> Aligned | H27: n/a
A28: LL-R7 | B28: EV Cushion | C28: =IF($C$17=0,"n/m",($C$17-$C$14)/$C$17) -> 0.36666667 | E28: =IF(OR(ISTEXT(C28),C28="",D28=""),"",C28-D28) | F28: =IF(E28="","",IF(ABS(E28)<=0.05*MAX(ABS(D28),0.0001),"Aligned","Variance")) | H28: n/a
B30: D. Credit Quality & Risk-Grade Accuracy
A31: ID | B31: Review Question | C31: Severity | D31: Answer | E31: Reviewer Note / Finding Rationale | J31: Check
A32: LL-Q01 | B32: LOB-assigned risk grade is supported by current financial analysis. | C32: High | D32: Yes | J32: =IF(AND(D32="Obs",E32=""),"Note required",IF(AND(D32="No",E32=""),"Rationale required",""))
A33: LL-Q02 | B33: Grade reflects all material credit weaknesses identified in the file. | C33: High | D33: Yes | J33: =IF(AND(D33="Obs",E33=""),"Note required",IF(AND(D33="No",E33=""),"Rationale required",""))
A34: LL-Q03 | B34: Grade was reviewed/affirmed within policy frequency requirements. | C34: Medium | D34: Yes | J34: =IF(AND(D34="Obs",E34=""),"Note required",IF(AND(D34="No",E34=""),"Rationale required",""))
B35: E. Underwriting Soundness
A36: ID | B36: Review Question | C36: Severity | D36: Answer | E36: Reviewer Note / Finding Rationale | J36: Check
A37: LL-Q04 | B37: Underwriting at origination conformed to policy standards in effect. | C37: High | D37: Yes | J37: =IF(AND(D37="Obs",E37=""),"Note required",IF(AND(D37="No",E37=""),"Rationale required",""))
A38: LL-Q05 | B38: Financial statements meet policy quality/recency requirements (audit level, age). | C38: Medium | D38: Yes | J38: =IF(AND(D38="Obs",E38=""),"Note required",IF(AND(D38="No",E38=""),"Rationale required",""))
A39: LL-Q06 | B39: Analysis critically evaluates borrower-provided information rather than restating it. | C39: High | D39: Yes | J39: =IF(AND(D39="Obs",E39=""),"Note required",IF(AND(D39="No",E39=""),"Rationale required",""))
B40: F. Repayment Sources & Projections
A41: ID | B41: Review Question | C41: Severity | D41: Answer | E41: Reviewer Note / Finding Rationale | J41: Check
A42: LL-Q07 | B42: Primary repayment source is clearly identified and quantitatively supported. | C42: High | D42: Yes | J42: =IF(AND(D42="Obs",E42=""),"Note required",IF(AND(D42="No",E42=""),"Rationale required",""))
A43: LL-Q08 | B43: Secondary repayment source is identified and realizable. | C43: Medium | D43: Yes | J43: =IF(AND(D43="Obs",E43=""),"Note required",IF(AND(D43="No",E43=""),"Rationale required",""))
A44: LL-Q09 | B44: Projection assumptions are reasonable versus historical performance and market data. | C44: High | D44: Yes | J44: =IF(AND(D44="Obs",E44=""),"Note required",IF(AND(D44="No",E44=""),"Rationale required",""))
B45: G. Guarantor / Sponsor Creditworthiness
A46: ID | B46: Review Question | C46: Severity | D46: Answer | E46: Reviewer Note / Finding Rationale | J46: Check
A47: LL-Q10 | B47: Guarantor/sponsor financial condition is current, analyzed, and supports reliance. | C47: Medium | D47: N/A | J47: =IF(AND(D47="Obs",E47=""),"Note required",IF(AND(D47="No",E47=""),"Rationale required",""))
A48: LL-Q11 | B48: Guaranty enforceability documented (signed, unconditional unless approved otherwise). | C48: Medium | D48: Yes | J48: =IF(AND(D48="Obs",E48=""),"Note required",IF(AND(D48="No",E48=""),"Rationale required",""))
B49: H. Credit & Collateral Documentation / Lien Perfection
A50: ID | B50: Review Question | C50: Severity | D50: Answer | E50: Reviewer Note / Finding Rationale | J50: Check
A51: LL-Q12 | B51: All required credit documents are present, current, and properly executed. | C51: High | D51: Obs | E51: Site-visit memo informative but not filed in imaging system. | J51: =IF(AND(D51="Obs",E51=""),"Note required",IF(AND(D51="No",E51=""),"Rationale required",""))
A52: LL-Q13 | B52: Lien positions are perfected and verified (searches, filings, titles). | C52: High | D52: No | E52: Guarantor PFS older than 12 months; reliance not currently supported. | J52: =IF(AND(D52="Obs",E52=""),"Note required",IF(AND(D52="No",E52=""),"Rationale required",""))
A53: LL-Q14 | B53: Insurance requirements are met and the bank is loss payee where required. | C53: Low | D53: Yes | J53: =IF(AND(D53="Obs",E53=""),"Note required",IF(AND(D53="No",E53=""),"Rationale required",""))
B54: I. Approval Authority
A55: ID | B55: Review Question | C55: Severity | D55: Answer | E55: Reviewer Note / Finding Rationale | J55: Check
A56: LL-Q15 | B56: Credit was approved within delegated authority of the approving officer(s). | C56: High | D56: Yes | J56: =IF(AND(D56="Obs",E56=""),"Note required",IF(AND(D56="No",E56=""),"Rationale required",""))
A57: LL-Q16 | B57: Policy exceptions at approval were identified, justified, and approved at proper level. | C57: Medium | D57: Yes | J57: =IF(AND(D57="Obs",E57=""),"Note required",IF(AND(D57="No",E57=""),"Rationale required",""))
B58: J. Covenant Adherence
A59: ID | B59: Review Question | C59: Severity | D59: Answer | E59: Reviewer Note / Finding Rationale | J59: Check
A60: LL-Q17 | B60: Covenant compliance is tested at required frequency with evidence retained. | C60: Medium | D60: Yes | J60: =IF(AND(D60="Obs",E60=""),"Note required",IF(AND(D60="No",E60=""),"Rationale required",""))
A61: LL-Q18 | B61: Covenant breaches (if any) were identified, reported, and waived/cured per policy. | C61: High | D61: Yes | J61: =IF(AND(D61="Obs",E61=""),"Note required",IF(AND(D61="No",E61=""),"Rationale required",""))
B62: K. Policy Compliance
A63: ID | B63: Review Question | C63: Severity | D63: Answer | E63: Reviewer Note / Finding Rationale | J63: Check
A64: LL-Q19 | B64: Credit complies with internal lending policy limits (hold limits, tenor, pricing floors). | C64: Medium | D64: Yes | J64: =IF(AND(D64="Obs",E64=""),"Note required",IF(AND(D64="No",E64=""),"Rationale required",""))
A65: LL-Q20 | B65: Required periodic monitoring (annual review, site visits) is current. | C65: Medium | D65: Yes | J65: =IF(AND(D65="Obs",E65=""),"Note required",IF(AND(D65="No",E65=""),"Rationale required",""))
B66: L. Leveraged Lending Specifics
A67: ID | B67: Review Question | C67: Severity | D67: Answer | E67: Reviewer Note / Finding Rationale | J67: Check
A68: LL-Q21 | B68: Transaction meets the bank's leveraged-lending definition and is flagged in systems. | C68: Medium | D68: Yes | J68: =IF(AND(D68="Obs",E68=""),"Note required",IF(AND(D68="No",E68=""),"Rationale required",""))
A69: LL-Q22 | B69: Sponsor track record, support history, and equity contribution are analyzed. | C69: Medium | D69: Yes | J69: =IF(AND(D69="Obs",E69=""),"Note required",IF(AND(D69="No",E69=""),"Rationale required",""))
A70: LL-Q23 | B70: Covenant package adequacy assessed; cov-lite structure identified and justified. | C70: High | D70: N/A | J70: =IF(AND(D70="Obs",E70=""),"Note required",IF(AND(D70="No",E70=""),"Rationale required",""))
A71: LL-Q24 | B71: EBITDA adjustments/add-backs are scrutinized and supportable. | C71: High | D71: No | E71: Guarantor PFS older than 12 months; reliance not currently supported. | J71: =IF(AND(D71="Obs",E71=""),"Note required",IF(AND(D71="No",E71=""),"Rationale required",""))
A72: LL-Q25 | B72: Enterprise-value cushion is estimated on a supportable basis. | C72: Medium | D72: Yes | J72: =IF(AND(D72="Obs",E72=""),"Note required",IF(AND(D72="No",E72=""),"Rationale required",""))
A73: LL-Q26 | B73: Repayment-capacity test (de-lever >=50% of total debt over 5-7 years, base case) is evidenced. | C73: High | D73: Yes | J73: =IF(AND(D73="Obs",E73=""),"Note required",IF(AND(D73="No",E73=""),"Rationale required",""))
B75: Review Summary
B76: Questions (total) | C76: =26 -> 26
B77: Answered (Yes / No / N/A / Obs) | C77: =COUNTIF(D32:D73,"Yes")+COUNTIF(D32:D73,"No")+COUNTIF(D32:D73,"N/A")+COUNTIF(D32:D73,"Obs") -> 26
B78: Completion % | C78: =IF(C76=0,"",C77/C76) -> 1
B79: Applicable (excl. N/A) | C79: =C77-COUNTIF(D32:D73,"N/A") -> 24
B80: Exceptions (No) | C80: =COUNTIF(D32:D73,"No") -> 2
B81: Observations (Obs) | C81: =COUNTIF(D32:D73,"Obs") -> 1
B82: Exception Rate (No / Applicable) | C82: =IF(C79=0,"",C80/C79) -> 0.083333333
B83: Note Checks Outstanding | C83: =COUNTIF(J32:J73,"*required*") -> 0
B85: CRR Conclusion / Grade Rationale:

Sheet LS_ABL
B1: Asset-Based Lending — Credit Risk Review Line Sheet
B2: Independent challenge function: re-derive, confirm, or dispute each asserted value. Answers: Yes / No / N/A / Obs (Obs requires a note; N/A is excluded from all rates).
B4: A. Credit Identification
B5: Credit ID | C5: ABL-2026001 | E5: Review Date | F5: 45883 | H5: LOB Assigned Grade | I5: 4
B6: Borrower | C6: Royal Textile Mills, Inc. | E6: Financials As-Of | F6: 45808 | H6: CRR Concluded Grade | I6: 4
B7: Commitment ($000) | C7: 10000 | E7: Reviewer | F7: A. Chen | H7: Regulatory Category | I7: =IF($I$6="","",VLOOKUP($I$6,Lists!$D$2:$E$9,2,0)) -> Pass
B8: Review Type | C8: Periodic | E8: Subtype / Property Type | H8: Grade Concurrence | I8: =IF(OR($I$5="",$I$6=""),"",IF($I$5=$I$6,"Concur","Grade Change")) -> Concur
B10: B. Financial Inputs — CRR Independent Spread
B11: Input | C11: Value | D11: Source / Note
B12: Gross Accounts Receivable ($000) | C12: 38500
B13: Ineligible AR ($000) | C13: 6200
B14: AR Advance Rate (%) | C14: 0.85 | D14: Per credit agreement
B15: Gross Inventory ($000) | C15: 27400
B16: Ineligible Inventory ($000) | C16: 8100
B17: Inventory Advance Rate (%) | C17: 0.6 | D17: Per credit agreement
B18: Reserves ($000) | C18: 2500 | D18: Availability reserves
B19: Outstanding Balance ($000) | C19: 31750
B20: Dilution (%) | C20: 0.043 | D20: Trailing 12-month
B22: C. Ratio Engine — Independent vs. Asserted
A23: ID | B23: Ratio | C23: CRR Independent | D23: Per CAM (Asserted) | E23: Variance | F23: Alignment | G23: Threshold (In Force) | H23: Vs Threshold | J23: Note
A24: ABL-R1 | B24: Eligible AR ($000) | C24: =$C$12-$C$13 -> 32300 | E24: =IF(OR(ISTEXT(C24),C24="",D24=""),"",C24-D24) | F24: =IF(E24="","",IF(ABS(E24)<=0.05*MAX(ABS(D24),0.0001),"Aligned","Variance")) | H24: n/a
A25: ABL-R2 | B25: Eligible Inventory ($000) | C25: =$C$15-$C$16 -> 19300 | E25: =IF(OR(ISTEXT(C25),C25="",D25=""),"",C25-D25) | F25: =IF(E25="","",IF(ABS(E25)<=0.05*MAX(ABS(D25),0.0001),"Aligned","Variance")) | H25: n/a
A26: ABL-R3 | B26: Borrowing Base ($000) | C26: =($C$12-$C$13)*$C$14+($C$15-$C$16)*$C$17-$C$18 -> 36535 | D26: 36000 | E26: =IF(OR(ISTEXT(C26),C26="",D26=""),"",C26-D26) -> 535 | F26: =IF(E26="","",IF(ABS(E26)<=0.05*MAX(ABS(D26),0.0001),"Aligned","Variance")) -> Aligned | H26: n/a
A27: ABL-R4 | B27: Availability ($000) | C27: =($C$12-$C$13)*$C$14+($C$15-$C$16)*$C$17-$C$18-$C$19 -> 4785 | E27: =IF(OR(ISTEXT(C27),C27="",D27=""),"",C27-D27) | F27: =IF(E27="","",IF(ABS(E27)<=0.05*MAX(ABS(D27),0.0001),"Aligned","Variance")) | H27: n/a
A28: ABL-R5 | B28: Collateral Coverage (BB / Outstandings) | C28: =IF($C$19=0,"n/m",(($C$12-$C$13)*$C$14+($C$15-$C$16)*$C$17-$C$18)/$C$19) -> 1.1507087 | D28: 1.13 | E28: =IF(OR(ISTEXT(C28),C28="",D28=""),"",C28-D28) -> 0.020708661 | F28: =IF(E28="","",IF(ABS(E28)<=0.05*MAX(ABS(D28),0.0001),"Aligned","Variance")) -> Aligned | H28: n/a
A29: ABL-R6 | B29: Ineligible % of Gross AR | C29: =IF($C$12=0,"n/m",$C$13/$C$12) -> 0.16103896 | E29: =IF(OR(ISTEXT(C29),C29="",D29=""),"",C29-D29) | F29: =IF(E29="","",IF(ABS(E29)<=0.05*MAX(ABS(D29),0.0001),"Aligned","Variance")) | H29: n/a
B31: D. Credit Quality & Risk-Grade Accuracy
A32: ID | B32: Review Question | C32: Severity | D32: Answer | E32: Reviewer Note / Finding Rationale | J32: Check
A33: ABL-Q01 | B33: LOB-assigned risk grade is supported by current financial analysis. | C33: High | D33: Yes | J33: =IF(AND(D33="Obs",E33=""),"Note required",IF(AND(D33="No",E33=""),"Rationale required",""))
A34: ABL-Q02 | B34: Grade reflects all material credit weaknesses identified in the file. | C34: High | D34: Yes | J34: =IF(AND(D34="Obs",E34=""),"Note required",IF(AND(D34="No",E34=""),"Rationale required",""))
A35: ABL-Q03 | B35: Grade was reviewed/affirmed within policy frequency requirements. | C35: Medium | D35: Yes | J35: =IF(AND(D35="Obs",E35=""),"Note required",IF(AND(D35="No",E35=""),"Rationale required",""))
B36: E. Underwriting Soundness
A37: ID | B37: Review Question | C37: Severity | D37: Answer | E37: Reviewer Note / Finding Rationale | J37: Check
A38: ABL-Q04 | B38: Underwriting at origination conformed to policy standards in effect. | C38: High | D38: Yes | J38: =IF(AND(D38="Obs",E38=""),"Note required",IF(AND(D38="No",E38=""),"Rationale required",""))
A39: ABL-Q05 | B39: Financial statements meet policy quality/recency requirements (audit level, age). | C39: Medium | D39: Yes | J39: =IF(AND(D39="Obs",E39=""),"Note required",IF(AND(D39="No",E39=""),"Rationale required",""))
A40: ABL-Q06 | B40: Analysis critically evaluates borrower-provided information rather than restating it. | C40: High | D40: Obs | E40: Annual review completed 10 days before deadline two cycles running - timing risk. | J40: =IF(AND(D40="Obs",E40=""),"Note required",IF(AND(D40="No",E40=""),"Rationale required",""))
B41: F. Repayment Sources & Projections
A42: ID | B42: Review Question | C42: Severity | D42: Answer | E42: Reviewer Note / Finding Rationale | J42: Check
A43: ABL-Q07 | B43: Primary repayment source is clearly identified and quantitatively supported. | C43: High | D43: Yes | J43: =IF(AND(D43="Obs",E43=""),"Note required",IF(AND(D43="No",E43=""),"Rationale required",""))
A44: ABL-Q08 | B44: Secondary repayment source is identified and realizable. | C44: Medium | D44: Yes | J44: =IF(AND(D44="Obs",E44=""),"Note required",IF(AND(D44="No",E44=""),"Rationale required",""))
A45: ABL-Q09 | B45: Projection assumptions are reasonable versus historical performance and market data. | C45: High | D45: Yes | J45: =IF(AND(D45="Obs",E45=""),"Note required",IF(AND(D45="No",E45=""),"Rationale required",""))
B46: G. Guarantor / Sponsor Creditworthiness
A47: ID | B47: Review Question | C47: Severity | D47: Answer | E47: Reviewer Note / Finding Rationale | J47: Check
A48: ABL-Q10 | B48: Guarantor/sponsor financial condition is current, analyzed, and supports reliance. | C48: Medium | D48: Yes | J48: =IF(AND(D48="Obs",E48=""),"Note required",IF(AND(D48="No",E48=""),"Rationale required",""))
A49: ABL-Q11 | B49: Guaranty enforceability documented (signed, unconditional unless approved otherwise). | C49: Medium | D49: N/A | J49: =IF(AND(D49="Obs",E49=""),"Note required",IF(AND(D49="No",E49=""),"Rationale required",""))
B50: H. Credit & Collateral Documentation / Lien Perfection
A51: ID | B51: Review Question | C51: Severity | D51: Answer | E51: Reviewer Note / Finding Rationale | J51: Check
A52: ABL-Q12 | B52: All required credit documents are present, current, and properly executed. | C52: High | D52: Yes | J52: =IF(AND(D52="Obs",E52=""),"Note required",IF(AND(D52="No",E52=""),"Rationale required",""))
A53: ABL-Q13 | B53: Lien positions are perfected and verified (searches, filings, titles). | C53: High | D53: Yes | J53: =IF(AND(D53="Obs",E53=""),"Note required",IF(AND(D53="No",E53=""),"Rationale required",""))
A54: ABL-Q14 | B54: Insurance requirements are met and the bank is loss payee where required. | C54: Low | D54: Yes | J54: =IF(AND(D54="Obs",E54=""),"Note required",IF(AND(D54="No",E54=""),"Rationale required",""))
B55: I. Approval Authority
A56: ID | B56: Review Question | C56: Severity | D56: Answer | E56: Reviewer Note / Finding Rationale | J56: Check
A57: ABL-Q15 | B57: Credit was approved within delegated authority of the approving officer(s). | C57: High | D57: Yes | J57: =IF(AND(D57="Obs",E57=""),"Note required",IF(AND(D57="No",E57=""),"Rationale required",""))
A58: ABL-Q16 | B58: Policy exceptions at approval were identified, justified, and approved at proper level. | C58: Medium | D58: Yes | J58: =IF(AND(D58="Obs",E58=""),"Note required",IF(AND(D58="No",E58=""),"Rationale required",""))
B59: J. Covenant Adherence
A60: ID | B60: Review Question | C60: Severity | D60: Answer | E60: Reviewer Note / Finding Rationale | J60: Check
A61: ABL-Q17 | B61: Covenant compliance is tested at required frequency with evidence retained. | C61: Medium | D61: Obs | E61: Annual review completed 10 days before deadline two cycles running - timing risk. | J61: =IF(AND(D61="Obs",E61=""),"Note required",IF(AND(D61="No",E61=""),"Rationale required",""))
A62: ABL-Q18 | B62: Covenant breaches (if any) were identified, reported, and waived/cured per policy. | C62: High | D62: No | E62: Financial statements stale beyond policy window; no waiver in file. | J62: =IF(AND(D62="Obs",E62=""),"Note required",IF(AND(D62="No",E62=""),"Rationale required",""))
B63: K. Policy Compliance
A64: ID | B64: Review Question | C64: Severity | D64: Answer | E64: Reviewer Note / Finding Rationale | J64: Check
A65: ABL-Q19 | B65: Credit complies with internal lending policy limits (hold limits, tenor, pricing floors). | C65: Medium | D65: Yes | J65: =IF(AND(D65="Obs",E65=""),"Note required",IF(AND(D65="No",E65=""),"Rationale required",""))
A66: ABL-Q20 | B66: Required periodic monitoring (annual review, site visits) is current. | C66: Medium | D66: Yes | J66: =IF(AND(D66="Obs",E66=""),"Note required",IF(AND(D66="No",E66=""),"Rationale required",""))
B67: L. Borrowing Base Mechanics
A68: ID | B68: Review Question | C68: Severity | D68: Answer | E68: Reviewer Note / Finding Rationale | J68: Check
A69: ABL-Q21 | B69: Eligibility criteria (AR aging, concentration, cross-age; inventory categories) applied per agreement. | C69: High | D69: Yes | J69: =IF(AND(D69="Obs",E69=""),"Note required",IF(AND(D69="No",E69=""),"Rationale required",""))
A70: ABL-Q22 | B70: Ineligibles are identified, current, and correctly deducted. | C70: High | D70: Yes | J70: =IF(AND(D70="Obs",E70=""),"Note required",IF(AND(D70="No",E70=""),"Rationale required",""))
A71: ABL-Q23 | B71: Dilution is tracked and advance rates remain appropriate to dilution experience. | C71: Medium | D71: Yes | J71: =IF(AND(D71="Obs",E71=""),"Note required",IF(AND(D71="No",E71=""),"Rationale required",""))
A72: ABL-Q24 | B72: Field examination is current per policy frequency and findings were cleared. | C72: High | D72: Yes | J72: =IF(AND(D72="Obs",E72=""),"Note required",IF(AND(D72="No",E72=""),"Rationale required",""))
A73: ABL-Q25 | B73: Inventory appraisal (NOLV) is current and supports the advance rate. | C73: Medium | D73: Yes | J73: =IF(AND(D73="Obs",E73=""),"Note required",IF(AND(D73="No",E73=""),"Rationale required",""))
A74: ABL-Q26 | B74: Borrowing-base certificate frequency and verification meet monitoring requirements. | C74: Medium | D74: Yes | J74: =IF(AND(D74="Obs",E74=""),"Note required",IF(AND(D74="No",E74=""),"Rationale required",""))
B76: Review Summary
B77: Questions (total) | C77: =26 -> 26
B78: Answered (Yes / No / N/A / Obs) | C78: =COUNTIF(D33:D74,"Yes")+COUNTIF(D33:D74,"No")+COUNTIF(D33:D74,"N/A")+COUNTIF(D33:D74,"Obs") -> 26
B79: Completion % | C79: =IF(C77=0,"",C78/C77) -> 1
B80: Applicable (excl. N/A) | C80: =C78-COUNTIF(D33:D74,"N/A") -> 25
B81: Exceptions (No) | C81: =COUNTIF(D33:D74,"No") -> 1
B82: Observations (Obs) | C82: =COUNTIF(D33:D74,"Obs") -> 2
B83: Exception Rate (No / Applicable) | C83: =IF(C80=0,"",C81/C80) -> 0.04
B84: Note Checks Outstanding | C84: =COUNTIF(J33:J74,"*required*") -> 0
B86: CRR Conclusion / Grade Rationale:

Sheet LS_ARG
B1: ARG / Workout — Credit Risk Review Line Sheet
B2: Independent challenge function: re-derive, confirm, or dispute each asserted value. Answers: Yes / No / N/A / Obs (Obs requires a note; N/A is excluded from all rates).
B4: A. Credit Identification
B5: Credit ID | C5: ARG-2026001 | E5: Review Date | F5: 45883 | H5: LOB Assigned Grade | I5: 6
B6: Borrower | C6: Fairmont Hospitality LLC (Workout) | E6: Financials As-Of | F6: 45808 | H6: CRR Concluded Grade | I6: 6
B7: Commitment ($000) | C7: 42500 | E7: Reviewer | F7: A. Chen | H7: Regulatory Category | I7: =IF($I$6="","",VLOOKUP($I$6,Lists!$D$2:$E$9,2,0)) -> Substandard
B8: Review Type | C8: Periodic | E8: Subtype / Property Type | H8: Grade Concurrence | I8: =IF(OR($I$5="",$I$6=""),"",IF($I$5=$I$6,"Concur","Grade Change")) -> Concur
B10: B. Financial Inputs — CRR Independent Spread
B11: Input | C11: Value | D11: Source / Note
B12: Loan Balance ($000) | C12: 18600
B13: Specific Reserve ($000) | C13: 3100
B14: Prior Charge-Offs ($000) | C14: 2400
B15: Recoveries to Date ($000) | C15: 350
B16: Collateral Value - Gross ($000) | C16: 21000 | D16: Most recent valuation
B17: Liquidation Discount (%) | C17: 0.25 | D17: Key assumption
B18: Estimated Costs to Sell (%) | C18: 0.08
B20: C. Ratio Engine — Independent vs. Asserted
A21: ID | B21: Ratio | C21: CRR Independent | D21: Per CAM (Asserted) | E21: Variance | F21: Alignment | G21: Threshold (In Force) | H21: Vs Threshold | J21: Note
A22: ARG-R1 | B22: Net Liquidation Value ($000) | C22: =$C$16*(1-$C$17)*(1-$C$18) -> 14490 | E22: =IF(OR(ISTEXT(C22),C22="",D22=""),"",C22-D22) | F22: =IF(E22="","",IF(ABS(E22)<=0.05*MAX(ABS(D22),0.0001),"Aligned","Variance")) | H22: n/a
A23: ARG-R2 | B23: Collateral Coverage (NLV / Balance) | C23: =IF($C$12=0,"n/m",$C$16*(1-$C$17)*(1-$C$18)/$C$12) -> 0.77903226 | D23: 0.78 | E23: =IF(OR(ISTEXT(C23),C23="",D23=""),"",C23-D23) -> -0.00096774194 | F23: =IF(E23="","",IF(ABS(E23)<=0.05*MAX(ABS(D23),0.0001),"Aligned","Variance")) -> Aligned | H23: n/a
A24: ARG-R3 | B24: Collateral Shortfall ($000) | C24: =MAX(0,$C$12-$C$16*(1-$C$17)*(1-$C$18)) -> 4110 | E24: =IF(OR(ISTEXT(C24),C24="",D24=""),"",C24-D24) | F24: =IF(E24="","",IF(ABS(E24)<=0.05*MAX(ABS(D24),0.0001),"Aligned","Variance")) | H24: n/a
A25: ARG-R4 | B25: Reserve Coverage of Shortfall | C25: =IF(MAX(0,$C$12-$C$16*(1-$C$17)*(1-$C$18))=0,"n/a",$C$13/MAX(0.001,$C$12-$C$16*(1-$C$17)*(1-$C$18))) -> 0.75425791 | E25: =IF(OR(ISTEXT(C25),C25="",D25=""),"",C25-D25) | F25: =IF(E25="","",IF(ABS(E25)<=0.05*MAX(ABS(D25),0.0001),"Aligned","Variance")) | H25: n/a
A26: ARG-R5 | B26: Net Charge-Off ($000) | C26: =$C$14-$C$15 -> 2050 | E26: =IF(OR(ISTEXT(C26),C26="",D26=""),"",C26-D26) | F26: =IF(E26="","",IF(ABS(E26)<=0.05*MAX(ABS(D26),0.0001),"Aligned","Variance")) | H26: n/a
B28: D. Credit Quality & Risk-Grade Accuracy
A29: ID | B29: Review Question | C29: Severity | D29: Answer | E29: Reviewer Note / Finding Rationale | J29: Check
A30: ARG-Q01 | B30: LOB-assigned risk grade is supported by current financial analysis. | C30: High | D30: Yes | J30: =IF(AND(D30="Obs",E30=""),"Note required",IF(AND(D30="No",E30=""),"Rationale required",""))
A31: ARG-Q02 | B31: Grade reflects all material credit weaknesses identified in the file. | C31: High | D31: Yes | J31: =IF(AND(D31="Obs",E31=""),"Note required",IF(AND(D31="No",E31=""),"Rationale required",""))
A32: ARG-Q03 | B32: Grade was reviewed/affirmed within policy frequency requirements. | C32: Medium | D32: Yes | J32: =IF(AND(D32="Obs",E32=""),"Note required",IF(AND(D32="No",E32=""),"Rationale required",""))
B33: E. Underwriting Soundness
A34: ID | B34: Review Question | C34: Severity | D34: Answer | E34: Reviewer Note / Finding Rationale | J34: Check
A35: ARG-Q04 | B35: Underwriting at origination conformed to policy standards in effect. | C35: High | D35: Yes | J35: =IF(AND(D35="Obs",E35=""),"Note required",IF(AND(D35="No",E35=""),"Rationale required",""))
A36: ARG-Q05 | B36: Financial statements meet policy quality/recency requirements (audit level, age). | C36: Medium | D36: No | E36: UCC continuation lapsed; lien perfection not verified at review date. | J36: =IF(AND(D36="Obs",E36=""),"Note required",IF(AND(D36="No",E36=""),"Rationale required",""))
A37: ARG-Q06 | B37: Analysis critically evaluates borrower-provided information rather than restating it. | C37: High | D37: Yes | J37: =IF(AND(D37="Obs",E37=""),"Note required",IF(AND(D37="No",E37=""),"Rationale required",""))
B38: F. Repayment Sources & Projections
A39: ID | B39: Review Question | C39: Severity | D39: Answer | E39: Reviewer Note / Finding Rationale | J39: Check
A40: ARG-Q07 | B40: Primary repayment source is clearly identified and quantitatively supported. | C40: High | D40: N/A | J40: =IF(AND(D40="Obs",E40=""),"Note required",IF(AND(D40="No",E40=""),"Rationale required",""))
A41: ARG-Q08 | B41: Secondary repayment source is identified and realizable. | C41: Medium | D41: Yes | J41: =IF(AND(D41="Obs",E41=""),"Note required",IF(AND(D41="No",E41=""),"Rationale required",""))
A42: ARG-Q09 | B42: Projection assumptions are reasonable versus historical performance and market data. | C42: High | D42: Yes | J42: =IF(AND(D42="Obs",E42=""),"Note required",IF(AND(D42="No",E42=""),"Rationale required",""))
B43: G. Guarantor / Sponsor Creditworthiness
A44: ID | B44: Review Question | C44: Severity | D44: Answer | E44: Reviewer Note / Finding Rationale | J44: Check
A45: ARG-Q10 | B45: Guarantor/sponsor financial condition is current, analyzed, and supports reliance. | C45: Medium | D45: Yes | J45: =IF(AND(D45="Obs",E45=""),"Note required",IF(AND(D45="No",E45=""),"Rationale required",""))
A46: ARG-Q11 | B46: Guaranty enforceability documented (signed, unconditional unless approved otherwise). | C46: Medium | D46: Obs | E46: Spread mislabels FY2024 column as FY2025; values correct. | J46: =IF(AND(D46="Obs",E46=""),"Note required",IF(AND(D46="No",E46=""),"Rationale required",""))
B47: H. Credit & Collateral Documentation / Lien Perfection
A48: ID | B48: Review Question | C48: Severity | D48: Answer | E48: Reviewer Note / Finding Rationale | J48: Check
A49: ARG-Q12 | B49: All required credit documents are present, current, and properly executed. | C49: High | D49: Yes | J49: =IF(AND(D49="Obs",E49=""),"Note required",IF(AND(D49="No",E49=""),"Rationale required",""))
A50: ARG-Q13 | B50: Lien positions are perfected and verified (searches, filings, titles). | C50: High | D50: Obs | E50: Spread mislabels FY2024 column as FY2025; values correct. | J50: =IF(AND(D50="Obs",E50=""),"Note required",IF(AND(D50="No",E50=""),"Rationale required",""))
A51: ARG-Q14 | B51: Insurance requirements are met and the bank is loss payee where required. | C51: Low | D51: Yes | J51: =IF(AND(D51="Obs",E51=""),"Note required",IF(AND(D51="No",E51=""),"Rationale required",""))
B52: I. Approval Authority
A53: ID | B53: Review Question | C53: Severity | D53: Answer | E53: Reviewer Note / Finding Rationale | J53: Check
A54: ARG-Q15 | B54: Credit was approved within delegated authority of the approving officer(s). | C54: High | D54: Yes | J54: =IF(AND(D54="Obs",E54=""),"Note required",IF(AND(D54="No",E54=""),"Rationale required",""))
A55: ARG-Q16 | B55: Policy exceptions at approval were identified, justified, and approved at proper level. | C55: Medium | D55: Yes | J55: =IF(AND(D55="Obs",E55=""),"Note required",IF(AND(D55="No",E55=""),"Rationale required",""))
B56: J. Covenant Adherence
A57: ID | B57: Review Question | C57: Severity | D57: Answer | E57: Reviewer Note / Finding Rationale | J57: Check
A58: ARG-Q17 | B58: Covenant compliance is tested at required frequency with evidence retained. | C58: Medium | D58: Obs | E58: Site-visit memo informative but not filed in imaging system. | J58: =IF(AND(D58="Obs",E58=""),"Note required",IF(AND(D58="No",E58=""),"Rationale required",""))
A59: ARG-Q18 | B59: Covenant breaches (if any) were identified, reported, and waived/cured per policy. | C59: High | D59: Yes | J59: =IF(AND(D59="Obs",E59=""),"Note required",IF(AND(D59="No",E59=""),"Rationale required",""))
B60: K. Policy Compliance
A61: ID | B61: Review Question | C61: Severity | D61: Answer | E61: Reviewer Note / Finding Rationale | J61: Check
A62: ARG-Q19 | B62: Credit complies with internal lending policy limits (hold limits, tenor, pricing floors). | C62: Medium | D62: Yes | J62: =IF(AND(D62="Obs",E62=""),"Note required",IF(AND(D62="No",E62=""),"Rationale required",""))
A63: ARG-Q20 | B63: Required periodic monitoring (annual review, site visits) is current. | C63: Medium | D63: Yes | J63: =IF(AND(D63="Obs",E63=""),"Note required",IF(AND(D63="No",E63=""),"Rationale required",""))
B64: L. Impairment, Accrual & Workout (ASC 326)
A65: ID | B65: Review Question | C65: Severity | D65: Answer | E65: Reviewer Note / Finding Rationale | J65: Check
A66: ARG-Q21 | B66: Impairment measurement method is appropriate (collateral-dependent practical expedient applied correctly). | C66: High | D66: No | E66: Approval signature exceeds officer's delegated authority; no co-approval. | J66: =IF(AND(D66="Obs",E66=""),"Note required",IF(AND(D66="No",E66=""),"Rationale required",""))
A67: ARG-Q22 | B67: Nonaccrual status is correct and timely per regulatory definitions. | C67: High | D67: Yes | J67: =IF(AND(D67="Obs",E67=""),"Note required",IF(AND(D67="No",E67=""),"Rationale required",""))
A68: ARG-Q23 | B68: Modification / TDR-successor disclosures and tracking are accurate. | C68: Medium | D68: N/A | J68: =IF(AND(D68="Obs",E68=""),"Note required",IF(AND(D68="No",E68=""),"Rationale required",""))
A69: ARG-Q24 | B69: Charge-offs were taken timely when loss was confirmed; recoveries posted correctly. | C69: High | D69: Yes | J69: =IF(AND(D69="Obs",E69=""),"Note required",IF(AND(D69="No",E69=""),"Rationale required",""))
A70: ARG-Q25 | B70: Liquidation values reflect current, supportable collateral data and costs to sell. | C70: Medium | D70: Yes | J70: =IF(AND(D70="Obs",E70=""),"Note required",IF(AND(D70="No",E70=""),"Rationale required",""))
A71: ARG-Q26 | B71: Exit strategy is documented, realistic, and progressing against milestones. | C71: Medium | D71: Yes | J71: =IF(AND(D71="Obs",E71=""),"Note required",IF(AND(D71="No",E71=""),"Rationale required",""))
A72: ARG-Q27 | B72: Criticized/classified migration history is captured accurately in systems. | C72: Low | D72: Yes | J72: =IF(AND(D72="Obs",E72=""),"Note required",IF(AND(D72="No",E72=""),"Rationale required",""))
B74: Review Summary
B75: Questions (total) | C75: =27 -> 27
B76: Answered (Yes / No / N/A / Obs) | C76: =COUNTIF(D30:D72,"Yes")+COUNTIF(D30:D72,"No")+COUNTIF(D30:D72,"N/A")+COUNTIF(D30:D72,"Obs") -> 27
B77: Completion % | C77: =IF(C75=0,"",C76/C75) -> 1
B78: Applicable (excl. N/A) | C78: =C76-COUNTIF(D30:D72,"N/A") -> 25
B79: Exceptions (No) | C79: =COUNTIF(D30:D72,"No") -> 2
B80: Observations (Obs) | C80: =COUNTIF(D30:D72,"Obs") -> 3
B81: Exception Rate (No / Applicable) | C81: =IF(C78=0,"",C79/C78) -> 0.08
B82: Note Checks Outstanding | C82: =COUNTIF(J30:J72,"*required*") -> 0
B84: CRR Conclusion / Grade Rationale:

Sheet LS_COMP
B1: General Compliance Crosswalk — Credit Risk Review Line Sheet
B2: Independent challenge function: re-derive, confirm, or dispute each asserted value. Answers: Yes / No / N/A / Obs (Obs requires a note; N/A is excluded from all rates).
B4: A. Credit Identification
B5: Credit ID | C5: COMP-2026001 | E5: Review Date | F5: 45883 | H5: LOB Assigned Grade | I5: 4
B6: Borrower | C6: Compliance Sweep - Alder Mfg. | E6: Financials As-Of | F6: 45808 | H6: CRR Concluded Grade | I6: 5
B7: Commitment ($000) | C7: 30000 | E7: Reviewer | F7: A. Chen | H7: Regulatory Category | I7: =IF($I$6="","",VLOOKUP($I$6,Lists!$D$2:$E$9,2,0)) -> Special Mention
B8: Review Type | C8: Periodic | E8: Subtype / Property Type | H8: Grade Concurrence | I8: =IF(OR($I$5="",$I$6=""),"",IF($I$5=$I$6,"Concur","Grade Change")) -> Grade Change
B10: B. Credit Quality & Risk-Grade Accuracy
A11: ID | B11: Review Question | C11: Severity | D11: Answer | E11: Reviewer Note / Finding Rationale | J11: Check
A12: COMP-Q01 | B12: LOB-assigned risk grade is supported by current financial analysis. | C12: High | D12: Yes | J12: =IF(AND(D12="Obs",E12=""),"Note required",IF(AND(D12="No",E12=""),"Rationale required",""))
A13: COMP-Q02 | B13: Grade reflects all material credit weaknesses identified in the file. | C13: High | D13: Obs | E13: Borrowing-base certificate delivered by email rather than portal per agreement. | J13: =IF(AND(D13="Obs",E13=""),"Note required",IF(AND(D13="No",E13=""),"Rationale required",""))
A14: COMP-Q03 | B14: Grade was reviewed/affirmed within policy frequency requirements. | C14: Medium | D14: Yes | J14: =IF(AND(D14="Obs",E14=""),"Note required",IF(AND(D14="No",E14=""),"Rationale required",""))
B15: C. Underwriting Soundness
A16: ID | B16: Review Question | C16: Severity | D16: Answer | E16: Reviewer Note / Finding Rationale | J16: Check
A17: COMP-Q04 | B17: Underwriting at origination conformed to policy standards in effect. | C17: High | D17: Yes | J17: =IF(AND(D17="Obs",E17=""),"Note required",IF(AND(D17="No",E17=""),"Rationale required",""))
A18: COMP-Q05 | B18: Financial statements meet policy quality/recency requirements (audit level, age). | C18: Medium | D18: Yes | J18: =IF(AND(D18="Obs",E18=""),"Note required",IF(AND(D18="No",E18=""),"Rationale required",""))
A19: COMP-Q06 | B19: Analysis critically evaluates borrower-provided information rather than restating it. | C19: High | D19: Yes | J19: =IF(AND(D19="Obs",E19=""),"Note required",IF(AND(D19="No",E19=""),"Rationale required",""))
B20: D. Repayment Sources & Projections
A21: ID | B21: Review Question | C21: Severity | D21: Answer | E21: Reviewer Note / Finding Rationale | J21: Check
A22: COMP-Q07 | B22: Primary repayment source is clearly identified and quantitatively supported. | C22: High | D22: Yes | J22: =IF(AND(D22="Obs",E22=""),"Note required",IF(AND(D22="No",E22=""),"Rationale required",""))
A23: COMP-Q08 | B23: Secondary repayment source is identified and realizable. | C23: Medium | D23: Yes | J23: =IF(AND(D23="Obs",E23=""),"Note required",IF(AND(D23="No",E23=""),"Rationale required",""))
A24: COMP-Q09 | B24: Projection assumptions are reasonable versus historical performance and market data. | C24: High | D24: Yes | J24: =IF(AND(D24="Obs",E24=""),"Note required",IF(AND(D24="No",E24=""),"Rationale required",""))
B25: E. Guarantor / Sponsor Creditworthiness
A26: ID | B26: Review Question | C26: Severity | D26: Answer | E26: Reviewer Note / Finding Rationale | J26: Check
A27: COMP-Q10 | B27: Guarantor/sponsor financial condition is current, analyzed, and supports reliance. | C27: Medium | D27: Yes | J27: =IF(AND(D27="Obs",E27=""),"Note required",IF(AND(D27="No",E27=""),"Rationale required",""))
A28: COMP-Q11 | B28: Guaranty enforceability documented (signed, unconditional unless approved otherwise). | C28: Medium | D28: Yes | J28: =IF(AND(D28="Obs",E28=""),"Note required",IF(AND(D28="No",E28=""),"Rationale required",""))
B29: F. Credit & Collateral Documentation / Lien Perfection
A30: ID | B30: Review Question | C30: Severity | D30: Answer | E30: Reviewer Note / Finding Rationale | J30: Check
A31: COMP-Q12 | B31: All required credit documents are present, current, and properly executed. | C31: High | D31: Yes | J31: =IF(AND(D31="Obs",E31=""),"Note required",IF(AND(D31="No",E31=""),"Rationale required",""))
A32: COMP-Q13 | B32: Lien positions are perfected and verified (searches, filings, titles). | C32: High | D32: Yes | J32: =IF(AND(D32="Obs",E32=""),"Note required",IF(AND(D32="No",E32=""),"Rationale required",""))
A33: COMP-Q14 | B33: Insurance requirements are met and the bank is loss payee where required. | C33: Low | D33: Yes | J33: =IF(AND(D33="Obs",E33=""),"Note required",IF(AND(D33="No",E33=""),"Rationale required",""))
B34: G. Approval Authority
A35: ID | B35: Review Question | C35: Severity | D35: Answer | E35: Reviewer Note / Finding Rationale | J35: Check
A36: COMP-Q15 | B36: Credit was approved within delegated authority of the approving officer(s). | C36: High | D36: Yes | J36: =IF(AND(D36="Obs",E36=""),"Note required",IF(AND(D36="No",E36=""),"Rationale required",""))
A37: COMP-Q16 | B37: Policy exceptions at approval were identified, justified, and approved at proper level. | C37: Medium | D37: Yes | J37: =IF(AND(D37="Obs",E37=""),"Note required",IF(AND(D37="No",E37=""),"Rationale required",""))
B38: H. Covenant Adherence
A39: ID | B39: Review Question | C39: Severity | D39: Answer | E39: Reviewer Note / Finding Rationale | J39: Check
A40: COMP-Q17 | B40: Covenant compliance is tested at required frequency with evidence retained. | C40: Medium | D40: Yes | J40: =IF(AND(D40="Obs",E40=""),"Note required",IF(AND(D40="No",E40=""),"Rationale required",""))
A41: COMP-Q18 | B41: Covenant breaches (if any) were identified, reported, and waived/cured per policy. | C41: High | D41: Yes | J41: =IF(AND(D41="Obs",E41=""),"Note required",IF(AND(D41="No",E41=""),"Rationale required",""))
B42: I. Policy Compliance
A43: ID | B43: Review Question | C43: Severity | D43: Answer | E43: Reviewer Note / Finding Rationale | J43: Check
A44: COMP-Q19 | B44: Credit complies with internal lending policy limits (hold limits, tenor, pricing floors). | C44: Medium | D44: Yes | J44: =IF(AND(D44="Obs",E44=""),"Note required",IF(AND(D44="No",E44=""),"Rationale required",""))
A45: COMP-Q20 | B45: Required periodic monitoring (annual review, site visits) is current. | C45: Medium | D45: Yes | J45: =IF(AND(D45="Obs",E45=""),"Note required",IF(AND(D45="No",E45=""),"Rationale required",""))
B46: J. Risk-Rating Framework
A47: ID | B47: Review Question | C47: Severity | D47: Answer | E47: Reviewer Note / Finding Rationale | J47: Check
A48: COMP-Q21 | B48: Assigned rating maps correctly to the regulatory scale (Pass / Special Mention / Substandard / Doubtful / Loss). | C48: High | D48: Yes | J48: =IF(AND(D48="Obs",E48=""),"Note required",IF(AND(D48="No",E48=""),"Rationale required",""))
A49: COMP-Q22 | B49: Rating definitions applied match the bank's approved rating policy. | C49: Medium | D49: Yes | J49: =IF(AND(D49="Obs",E49=""),"Note required",IF(AND(D49="No",E49=""),"Rationale required",""))
B50: K. ALLL / CECL Linkage
A51: ID | B51: Review Question | C51: Severity | D51: Answer | E51: Reviewer Note / Finding Rationale | J51: Check
A52: COMP-Q23 | B52: Risk grade flows correctly into the CECL pool / individual evaluation status. | C52: High | D52: Yes | J52: =IF(AND(D52="Obs",E52=""),"Note required",IF(AND(D52="No",E52=""),"Rationale required",""))
A53: COMP-Q24 | B53: Individually evaluated credits have current, supportable measurement inputs. | C53: Medium | D53: Yes | J53: =IF(AND(D53="Obs",E53=""),"Note required",IF(AND(D53="No",E53=""),"Rationale required",""))
B54: L. Consumer-Adjacent Touchpoints
A55: ID | B55: Review Question | C55: Severity | D55: Answer | E55: Reviewer Note / Finding Rationale | J55: Check
A56: COMP-Q25 | B56: Flood determination obtained and insurance in place for improved collateral in SFHA. | C56: High | D56: Yes | J56: =IF(AND(D56="Obs",E56=""),"Note required",IF(AND(D56="No",E56=""),"Rationale required",""))
A57: COMP-Q26 | B57: Fair-lending / HMDA data points captured where the credit is reportable. | C57: Medium | D57: Yes | J57: =IF(AND(D57="Obs",E57=""),"Note required",IF(AND(D57="No",E57=""),"Rationale required",""))
B59: Review Summary
B60: Questions (total) | C60: =26 -> 26
B61: Answered (Yes / No / N/A / Obs) | C61: =COUNTIF(D12:D57,"Yes")+COUNTIF(D12:D57,"No")+COUNTIF(D12:D57,"N/A")+COUNTIF(D12:D57,"Obs") -> 26
B62: Completion % | C62: =IF(C60=0,"",C61/C60) -> 1
B63: Applicable (excl. N/A) | C63: =C61-COUNTIF(D12:D57,"N/A") -> 26
B64: Exceptions (No) | C64: =COUNTIF(D12:D57,"No") -> 0
B65: Observations (Obs) | C65: =COUNTIF(D12:D57,"Obs") -> 1
B66: Exception Rate (No / Applicable) | C66: =IF(C63=0,"",C64/C63) -> 0
B67: Note Checks Outstanding | C67: =COUNTIF(J12:J57,"*required*") -> 0
B69: CRR Conclusion / Grade Rationale:

Sheet LS_IA
B1: Internal Audit — Test Work Sheet
B2: Independent challenge function: re-derive, confirm, or dispute each asserted value. Answers: Yes / No / N/A / Obs (Obs requires a note; N/A is excluded from all rates).
B4: A. Engagement Identification
B5: Engagement ID | C5: IA-2026001 | E5: Fieldwork Date | F5: 45883 | H5: Mgmt Self-Assessed Rating (1-8) | I5: 2
B6: Auditable Entity | C6: Wire Transfer Operations Audit | E6: Period Under Audit (End) | F6: 45808 | H6: IA Concluded Rating (1-8) | I6: 2
B7: Population ($000 or units) | C7: 15000 | E7: Auditor | F7: A. Chen | H7: Rating Category (mapped) | I7: =IF($I$6="","",VLOOKUP($I$6,Lists!$D$2:$E$9,2,0)) -> Pass
B8: Engagement Type | C8: Periodic | E8: Process / Cycle | H8: IA vs Mgmt Concurrence | I8: =IF(OR($I$5="",$I$6=""),"",IF($I$5=$I$6,"Concur","Grade Change")) -> Concur
B10: B. Financial Inputs — CRR Independent Spread
B11: Input | C11: Value | D11: Source / Note
B12: Population Size (items) | C12: 1240 | D12: Per system extract; reconcile to source
B13: Sample Size (items) | C13: 60 | D13: Per sampling methodology
B14: Items Tested (items) | C14: 60
B15: Exceptions Found (items) | C15: 4
B16: Tolerable Exception Rate (%) | C16: 0.05 | D16: Key assumption - per audit methodology
B18: C. Ratio Engine — Independent vs. Asserted
A19: ID | B19: Ratio | C19: IA Re-Performed | D19: Per Mgmt (Asserted) | E19: Variance | F19: Alignment | G19: Threshold (In Force) | H19: Vs Threshold | J19: Note
A20: IA-R1 | B20: Sample Coverage (of population) | C20: =IF($C$12=0,"n/m",$C$13/$C$12) -> 0.048387097 | E20: =IF(OR(ISTEXT(C20),C20="",D20=""),"",C20-D20) | F20: =IF(E20="","",IF(ABS(E20)<=0.05*MAX(ABS(D20),0.0001),"Aligned","Variance")) | H20: n/a
A21: IA-R2 | B21: Test Completion (tested / sample) | C21: =IF($C$13=0,"n/m",$C$14/$C$13) -> 1 | E21: =IF(OR(ISTEXT(C21),C21="",D21=""),"",C21-D21) | F21: =IF(E21="","",IF(ABS(E21)<=0.05*MAX(ABS(D21),0.0001),"Aligned","Variance")) | H21: n/a
A22: IA-R3 | B22: Sample Exception Rate | C22: =IF($C$14=0,"n/m",$C$15/$C$14) -> 0.066666667 | D22: 0.033 | E22: =IF(OR(ISTEXT(C22),C22="",D22=""),"",C22-D22) -> 0.033666667 | F22: =IF(E22="","",IF(ABS(E22)<=0.05*MAX(ABS(D22),0.0001),"Aligned","Variance")) -> Variance | H22: n/a
A23: IA-R4 | B23: Exceptions vs Tolerable (pp) | C23: =IF($C$14=0,"n/m",$C$15/$C$14-$C$16) -> 0.016666667 | E23: =IF(OR(ISTEXT(C23),C23="",D23=""),"",C23-D23) | F23: =IF(E23="","",IF(ABS(E23)<=0.05*MAX(ABS(D23),0.0001),"Aligned","Variance")) | H23: n/a
B25: D. Engagement Planning & Scoping
A26: ID | B26: Review Question | C26: Severity | D26: Answer | E26: Reviewer Note / Finding Rationale | J26: Check
A27: IA-Q01 | B27: Engagement objectives and scope are documented and approved before fieldwork. | C27: High | D27: Yes | J27: =IF(AND(D27="Obs",E27=""),"Note required",IF(AND(D27="No",E27=""),"Rationale required",""))
A28: IA-Q02 | B28: Risk assessment supports the audit scope and the controls selected for testing. | C28: High | D28: Yes | J28: =IF(AND(D28="Obs",E28=""),"Note required",IF(AND(D28="No",E28=""),"Rationale required",""))
A29: IA-Q03 | B29: Prior audit issues and external findings in scope were considered in planning. | C29: Medium | D29: Obs | E29: Rate-reset sensitivity shown only at +100bp; broader stress would aid analysis. | J29: =IF(AND(D29="Obs",E29=""),"Note required",IF(AND(D29="No",E29=""),"Rationale required",""))
A30: IA-Q04 | B30: Auditor independence and objectivity are documented (no scope conflicts). | C30: Medium | D30: Yes | J30: =IF(AND(D30="Obs",E30=""),"Note required",IF(AND(D30="No",E30=""),"Rationale required",""))
B31: E. Control Design Effectiveness
A32: ID | B32: Review Question | C32: Severity | D32: Answer | E32: Reviewer Note / Finding Rationale | J32: Check
A33: IA-Q05 | B33: The control, as designed, addresses the stated risk and control objective. | C33: High | D33: Yes | J33: =IF(AND(D33="Obs",E33=""),"Note required",IF(AND(D33="No",E33=""),"Rationale required",""))
A34: IA-Q06 | B34: Control owner, frequency, and precision level are documented and current. | C34: Medium | D34: Yes | J34: =IF(AND(D34="Obs",E34=""),"Note required",IF(AND(D34="No",E34=""),"Rationale required",""))
A35: IA-Q07 | B35: Key reports / system configurations relied on by the control are validated (IPE). | C35: High | D35: Yes | J35: =IF(AND(D35="Obs",E35=""),"Note required",IF(AND(D35="No",E35=""),"Rationale required",""))
B36: F. Control Operating Effectiveness
A37: ID | B37: Review Question | C37: Severity | D37: Answer | E37: Reviewer Note / Finding Rationale | J37: Check
A38: IA-Q08 | B38: Sample size and selection method conform to the audit sampling methodology. | C38: High | D38: Yes | J38: =IF(AND(D38="Obs",E38=""),"Note required",IF(AND(D38="No",E38=""),"Rationale required",""))
A39: IA-Q09 | B39: Testing covers the full period under audit, including period-end activity. | C39: Medium | D39: N/A | J39: =IF(AND(D39="Obs",E39=""),"Note required",IF(AND(D39="No",E39=""),"Rationale required",""))
A40: IA-Q10 | B40: All sample exceptions are evaluated, dispositioned, and extrapolated where required. | C40: High | D40: Obs | E40: Site-visit memo informative but not filed in imaging system. | J40: =IF(AND(D40="Obs",E40=""),"Note required",IF(AND(D40="No",E40=""),"Rationale required",""))
A41: IA-Q11 | B41: Compensating controls are identified and tested where the primary control failed. | C41: Medium | D41: Yes | J41: =IF(AND(D41="Obs",E41=""),"Note required",IF(AND(D41="No",E41=""),"Rationale required",""))
B42: G. Evidence & Workpaper Documentation
A43: ID | B43: Review Question | C43: Severity | D43: Answer | E43: Reviewer Note / Finding Rationale | J43: Check
A44: IA-Q12 | B44: Workpapers allow re-performance: source, population, sample, and results are traceable. | C44: High | D44: Yes | J44: =IF(AND(D44="Obs",E44=""),"Note required",IF(AND(D44="No",E44=""),"Rationale required",""))
A45: IA-Q13 | B45: Evidence is retained per the records schedule and references tie to the audit program. | C45: Medium | D45: Yes | J45: =IF(AND(D45="Obs",E45=""),"Note required",IF(AND(D45="No",E45=""),"Rationale required",""))
A46: IA-Q14 | B46: Conclusions in the workpaper are consistent with the evidence documented. | C46: High | D46: N/A | J46: =IF(AND(D46="Obs",E46=""),"Note required",IF(AND(D46="No",E46=""),"Rationale required",""))
B47: H. Reporting & Issue Management
A48: ID | B48: Review Question | C48: Severity | D48: Answer | E48: Reviewer Note / Finding Rationale | J48: Check
A49: IA-Q15 | B49: Findings are risk-rated per methodology and agreed with the issue owner. | C49: High | D49: Yes | J49: =IF(AND(D49="Obs",E49=""),"Note required",IF(AND(D49="No",E49=""),"Rationale required",""))
A50: IA-Q16 | B50: Management action plans have owners and realistic target dates. | C50: Medium | D50: Yes | J50: =IF(AND(D50="Obs",E50=""),"Note required",IF(AND(D50="No",E50=""),"Rationale required",""))
A51: IA-Q17 | B51: Report conclusions are supported by the documented test results. | C51: High | D51: Yes | J51: =IF(AND(D51="Obs",E51=""),"Note required",IF(AND(D51="No",E51=""),"Rationale required",""))
B52: I. Follow-Up & Remediation
A53: ID | B53: Review Question | C53: Severity | D53: Answer | E53: Reviewer Note / Finding Rationale | J53: Check
A54: IA-Q18 | B54: Past-due issues are escalated per policy. | C54: Medium | D54: Yes | J54: =IF(AND(D54="Obs",E54=""),"Note required",IF(AND(D54="No",E54=""),"Rationale required",""))
A55: IA-Q19 | B55: Issue closure is supported by independent validation, not management attestation alone. | C55: High | D55: N/A | J55: =IF(AND(D55="Obs",E55=""),"Note required",IF(AND(D55="No",E55=""),"Rationale required",""))
B57: Review Summary
B58: Questions (total) | C58: =19 -> 19
B59: Answered (Yes / No / N/A / Obs) | C59: =COUNTIF(D27:D55,"Yes")+COUNTIF(D27:D55,"No")+COUNTIF(D27:D55,"N/A")+COUNTIF(D27:D55,"Obs") -> 19
B60: Completion % | C60: =IF(C58=0,"",C59/C58) -> 1
B61: Applicable (excl. N/A) | C61: =C59-COUNTIF(D27:D55,"N/A") -> 16
B62: Exceptions (No) | C62: =COUNTIF(D27:D55,"No") -> 0
B63: Observations (Obs) | C63: =COUNTIF(D27:D55,"Obs") -> 2
B64: Exception Rate (No / Applicable) | C64: =IF(C61=0,"",C62/C61) -> 0
B65: Note Checks Outstanding | C65: =COUNTIF(J27:J55,"*required*") -> 0
B67: CRR Conclusion / Grade Rationale:

Sheet Database
A1: Credit ID | B1: Seg | C1: Segment | D1: Borrower | E1: Commitment ($000) | F1: Review Date | G1: Quarter | H1: Reviewer | I1: LOB Grade | J1: CRR Grade | K1: Regulatory Category | L1: Grade Concurrence | M1: Leverage (x) | N1: DSCR (x) | O1: LTV (%) | P1: Exceptions (No) | Q1: Observations (Obs) | R1: Applicable (excl. N/A) | S1: Answered | T1: Total Qs | U1: Completion % | V1: Exception Rate | W1: Status | X1: Notes
A2: CI-2026001 | B2: CI | C2: C&I / Commercial | D2: Meridian Fabrication Holdings, LLC | E2: 25000 | F2: 45883 | G2: =IF(F2="","",YEAR(F2)&"-Q"&ROUNDUP(MONTH(F2)/3,0)) -> 2025-Q3 | H2: A. Chen | I2: 2 | J2: 2 | K2: =IF(J2="","",VLOOKUP(J2,Lists!$D$2:$E$9,2,0)) -> Pass | L2: =IF(OR(I2="",J2=""),"",IF(I2=J2,"Concur","Grade Change")) -> Concur | M2: 3.4 | N2: 2.02 | P2: =COUNTIFS(Responses!$A:$A,$A2,Responses!$G:$G,"No") -> 2 | Q2: =COUNTIFS(Responses!$A:$A,$A2,Responses!$G:$G,"Obs") -> 0 | R2: =COUNTIFS(Responses!$A:$A,$A2,Responses!$G:$G,"Yes")+P2+Q2 -> 23 | S2: =R2+COUNTIFS(Responses!$A:$A,$A2,Responses!$G:$G,"N/A") -> 27 | T2: =COUNTIFS(Responses!$A:$A,$A2) -> 27 | U2: =IF(T2=0,"",S2/T2) -> 1 | V2: =IF(R2=0,"",P2/R2) -> 0.086956522 | W2: Complete
A3: CI-2026002 | B3: CI | C3: C&I / Commercial | D3: Cascade Food Distributors, Inc. | E3: 12500 | F3: 45967 | G3: =IF(F3="","",YEAR(F3)&"-Q"&ROUNDUP(MONTH(F3)/3,0)) -> 2025-Q4 | H3: R. Ortiz | I3: 2 | J3: 2 | K3: =IF(J3="","",VLOOKUP(J3,Lists!$D$2:$E$9,2,0)) -> Pass | L3: =IF(OR(I3="",J3=""),"",IF(I3=J3,"Concur","Grade Change")) -> Concur | M3: 3.1 | N3: 1.19 | P3: =COUNTIFS(Responses!$A:$A,$A3,Responses!$G:$G,"No") -> 2 | Q3: =COUNTIFS(Responses!$A:$A,$A3,Responses!$G:$G,"Obs") -> 1 | R3: =COUNTIFS(Responses!$A:$A,$A3,Responses!$G:$G,"Yes")+P3+Q3 -> 25 | S3: =R3+COUNTIFS(Responses!$A:$A,$A3,Responses!$G:$G,"N/A") -> 27 | T3: =COUNTIFS(Responses!$A:$A,$A3) -> 27 | U3: =IF(T3=0,"",S3/T3) -> 1 | V3: =IF(R3=0,"",P3/R3) -> 0.08 | W3: Complete
A4: CI-2026003 | B4: CI | C4: C&I / Commercial | D4: Brightline Logistics Group | E4: 42500 | F4: 46072 | G4: =IF(F4="","",YEAR(F4)&"-Q"&ROUNDUP(MONTH(F4)/3,0)) -> 2026-Q1 | H4: M. Kowalski | I4: 5 | J4: 5 | K4: =IF(J4="","",VLOOKUP(J4,Lists!$D$2:$E$9,2,0)) -> Special Mention | L4: =IF(OR(I4="",J4=""),"",IF(I4=J4,"Concur","Grade Change")) -> Concur | M4: 2.6 | N4: 1.61 | P4: =COUNTIFS(Responses!$A:$A,$A4,Responses!$G:$G,"No") -> 2 | Q4: =COUNTIFS(Responses!$A:$A,$A4,Responses!$G:$G,"Obs") -> 0 | R4: =COUNTIFS(Responses!$A:$A,$A4,Responses!$G:$G,"Yes")+P4+Q4 -> 26 | S4: =R4+COUNTIFS(Responses!$A:$A,$A4,Responses!$G:$G,"N/A") -> 27 | T4: =COUNTIFS(Responses!$A:$A,$A4) -> 27 | U4: =IF(T4=0,"",S4/T4) -> 1 | V4: =IF(R4=0,"",P4/R4) -> 0.076923077 | W4: Complete
A5: CI-2026004 | B5: CI | C5: C&I / Commercial | D5: Harbor Tool & Die Co. | E5: 15000 | F5: 46149 | G5: =IF(F5="","",YEAR(F5)&"-Q"&ROUNDUP(MONTH(F5)/3,0)) -> 2026-Q2 | H5: D. Whitaker | I5: 3 | J5: 3 | K5: =IF(J5="","",VLOOKUP(J5,Lists!$D$2:$E$9,2,0)) -> Pass | L5: =IF(OR(I5="",J5=""),"",IF(I5=J5,"Concur","Grade Change")) -> Concur | M5: 4.4 | N5: 1.62 | P5: =COUNTIFS(Responses!$A:$A,$A5,Responses!$G:$G,"No") -> 2 | Q5: =COUNTIFS(Responses!$A:$A,$A5,Responses!$G:$G,"Obs") -> 1 | R5: =COUNTIFS(Responses!$A:$A,$A5,Responses!$G:$G,"Yes")+P5+Q5 -> 24 | S5: =R5+COUNTIFS(Responses!$A:$A,$A5,Responses!$G:$G,"N/A") -> 27 | T5: =COUNTIFS(Responses!$A:$A,$A5) -> 27 | U5: =IF(T5=0,"",S5/T5) -> 1 | V5: =IF(R5=0,"",P5/R5) -> 0.083333333 | W5: In Progress
A6: CRE-2026001 | B6: CRE | C6: Commercial Real Estate | D6: Lakeview Office Partners LP | E6: 32500 | F6: 45883 | G6: =IF(F6="","",YEAR(F6)&"-Q"&ROUNDUP(MONTH(F6)/3,0)) -> 2025-Q3 | H6: A. Chen | I6: 4 | J6: 4 | K6: =IF(J6="","",VLOOKUP(J6,Lists!$D$2:$E$9,2,0)) -> Pass | L6: =IF(OR(I6="",J6=""),"",IF(I6=J6,"Concur","Grade Change")) -> Concur | N6: 1.42 | O6: 0.563 | P6: =COUNTIFS(Responses!$A:$A,$A6,Responses!$G:$G,"No") -> 1 | Q6: =COUNTIFS(Responses!$A:$A,$A6,Responses!$G:$G,"Obs") -> 1 | R6: =COUNTIFS(Responses!$A:$A,$A6,Responses!$G:$G,"Yes")+P6+Q6 -> 24 | S6: =R6+COUNTIFS(Responses!$A:$A,$A6,Responses!$G:$G,"N/A") -> 27 | T6: =COUNTIFS(Responses!$A:$A,$A6) -> 27 | U6: =IF(T6=0,"",S6/T6) -> 1 | V6: =IF(R6=0,"",P6/R6) -> 0.041666667 | W6: Complete
A7: CRE-2026002 | B7: CRE | C7: Commercial Real Estate | D7: Stonebridge Multifamily I LLC | E7: 12500 | F7: 45967 | G7: =IF(F7="","",YEAR(F7)&"-Q"&ROUNDUP(MONTH(F7)/3,0)) -> 2025-Q4 | H7: R. Ortiz | I7: 4 | J7: 5 | K7: =IF(J7="","",VLOOKUP(J7,Lists!$D$2:$E$9,2,0)) -> Special Mention | L7: =IF(OR(I7="",J7=""),"",IF(I7=J7,"Concur","Grade Change")) -> Grade Change | N7: 1.53 | O7: 0.721 | P7: =COUNTIFS(Responses!$A:$A,$A7,Responses!$G:$G,"No") -> 2 | Q7: =COUNTIFS(Responses!$A:$A,$A7,Responses!$G:$G,"Obs") -> 2 | R7: =COUNTIFS(Responses!$A:$A,$A7,Responses!$G:$G,"Yes")+P7+Q7 -> 23 | S7: =R7+COUNTIFS(Responses!$A:$A,$A7,Responses!$G:$G,"N/A") -> 27 | T7: =COUNTIFS(Responses!$A:$A,$A7) -> 27 | U7: =IF(T7=0,"",S7/T7) -> 1 | V7: =IF(R7=0,"",P7/R7) -> 0.086956522 | W7: Complete
A8: CRE-2026003 | B8: CRE | C8: Commercial Real Estate | D8: Pinecrest Retail Center LLC | E8: 30000 | F8: 46072 | G8: =IF(F8="","",YEAR(F8)&"-Q"&ROUNDUP(MONTH(F8)/3,0)) -> 2026-Q1 | H8: M. Kowalski | I8: 3 | J8: 3 | K8: =IF(J8="","",VLOOKUP(J8,Lists!$D$2:$E$9,2,0)) -> Pass | L8: =IF(OR(I8="",J8=""),"",IF(I8=J8,"Concur","Grade Change")) -> Concur | N8: 1.47 | O8: 0.592 | P8: =COUNTIFS(Responses!$A:$A,$A8,Responses!$G:$G,"No") -> 3 | Q8: =COUNTIFS(Responses!$A:$A,$A8,Responses!$G:$G,"Obs") -> 4 | R8: =COUNTIFS(Responses!$A:$A,$A8,Responses!$G:$G,"Yes")+P8+Q8 -> 27 | S8: =R8+COUNTIFS(Responses!$A:$A,$A8,Responses!$G:$G,"N/A") -> 27 | T8: =COUNTIFS(Responses!$A:$A,$A8) -> 27 | U8: =IF(T8=0,"",S8/T8) -> 1 | V8: =IF(R8=0,"",P8/R8) -> 0.11111111 | W8: Complete
A9: CRE-2026004 | B9: CRE | C9: Commercial Real Estate | D9: Gateway Industrial Park LLC | E9: 12500 | F9: 46149 | G9: =IF(F9="","",YEAR(F9)&"-Q"&ROUNDUP(MONTH(F9)/3,0)) -> 2026-Q2 | H9: D. Whitaker | I9: 5 | J9: 5 | K9: =IF(J9="","",VLOOKUP(J9,Lists!$D$2:$E$9,2,0)) -> Special Mention | L9: =IF(OR(I9="",J9=""),"",IF(I9=J9,"Concur","Grade Change")) -> Concur | N9: 1.38 | O9: 0.634 | P9: =COUNTIFS(Responses!$A:$A,$A9,Responses!$G:$G,"No") -> 2 | Q9: =COUNTIFS(Responses!$A:$A,$A9,Responses!$G:$G,"Obs") -> 1 | R9: =COUNTIFS(Responses!$A:$A,$A9,Responses!$G:$G,"Yes")+P9+Q9 -> 23 | S9: =R9+COUNTIFS(Responses!$A:$A,$A9,Responses!$G:$G,"N/A") -> 27 | T9: =COUNTIFS(Responses!$A:$A,$A9) -> 27 | U9: =IF(T9=0,"",S9/T9) -> 1 | V9: =IF(R9=0,"",P9/R9) -> 0.086956522 | W9: In Progress
A10: LL-2026001 | B10: LL | C10: Leveraged Lending | D10: Apex Packaging Buyout Co. | E10: 27500 | F10: 45883 | G10: =IF(F10="","",YEAR(F10)&"-Q"&ROUNDUP(MONTH(F10)/3,0)) -> 2025-Q3 | H10: A. Chen | I10: 4 | J10: 4 | K10: =IF(J10="","",VLOOKUP(J10,Lists!$D$2:$E$9,2,0)) -> Pass | L10: =IF(OR(I10="",J10=""),"",IF(I10=J10,"Concur","Grade Change")) -> Concur | M10: 6.2 | N10: 1.39 | P10: =COUNTIFS(Responses!$A:$A,$A10,Responses!$G:$G,"No") -> 2 | Q10: =COUNTIFS(Responses!$A:$A,$A10,Responses!$G:$G,"Obs") -> 1 | R10: =COUNTIFS(Responses!$A:$A,$A10,Responses!$G:$G,"Yes")+P10+Q10 -> 24 | S10: =R10+COUNTIFS(Responses!$A:$A,$A10,Responses!$G:$G,"N/A") -> 26 | T10: =COUNTIFS(Responses!$A:$A,$A10) -> 26 | U10: =IF(T10=0,"",S10/T10) -> 1 | V10: =IF(R10=0,"",P10/R10) -> 0.083333333 | W10: Complete
A11: LL-2026002 | B11: LL | C11: Leveraged Lending | D11: Summit HealthTech Acquisition | E11: 37500 | F11: 45967 | G11: =IF(F11="","",YEAR(F11)&"-Q"&ROUNDUP(MONTH(F11)/3,0)) -> 2025-Q4 | H11: R. Ortiz | I11: 4 | J11: 5 | K11: =IF(J11="","",VLOOKUP(J11,Lists!$D$2:$E$9,2,0)) -> Special Mention | L11: =IF(OR(I11="",J11=""),"",IF(I11=J11,"Concur","Grade Change")) -> Grade Change | M11: 5.4 | N11: 1.46 | P11: =COUNTIFS(Responses!$A:$A,$A11,Responses!$G:$G,"No") -> 3 | Q11: =COUNTIFS(Responses!$A:$A,$A11,Responses!$G:$G,"Obs") -> 2 | R11: =COUNTIFS(Responses!$A:$A,$A11,Responses!$G:$G,"Yes")+P11+Q11 -> 25 | S11: =R11+COUNTIFS(Responses!$A:$A,$A11,Responses!$G:$G,"N/A") -> 26 | T11: =COUNTIFS(Responses!$A:$A,$A11) -> 26 | U11: =IF(T11=0,"",S11/T11) -> 1 | V11: =IF(R11=0,"",P11/R11) -> 0.12 | W11: Complete
A12: LL-2026003 | B12: LL | C12: Leveraged Lending | D12: Ironwood Components Holdings | E12: 55000 | F12: 46072 | G12: =IF(F12="","",YEAR(F12)&"-Q"&ROUNDUP(MONTH(F12)/3,0)) -> 2026-Q1 | H12: M. Kowalski | I12: 3 | J12: 3 | K12: =IF(J12="","",VLOOKUP(J12,Lists!$D$2:$E$9,2,0)) -> Pass | L12: =IF(OR(I12="",J12=""),"",IF(I12=J12,"Concur","Grade Change")) -> Concur | M12: 5.1 | N12: 1.23 | P12: =COUNTIFS(Responses!$A:$A,$A12,Responses!$G:$G,"No") -> 1 | Q12: =COUNTIFS(Responses!$A:$A,$A12,Responses!$G:$G,"Obs") -> 2 | R12: =COUNTIFS(Responses!$A:$A,$A12,Responses!$G:$G,"Yes")+P12+Q12 -> 24 | S12: =R12+COUNTIFS(Responses!$A:$A,$A12,Responses!$G:$G,"N/A") -> 26 | T12: =COUNTIFS(Responses!$A:$A,$A12) -> 26 | U12: =IF(T12=0,"",S12/T12) -> 1 | V12: =IF(R12=0,"",P12/R12) -> 0.041666667 | W12: Complete
A13: LL-2026004 | B13: LL | C13: Leveraged Lending | D13: Bluepeak Software Group | E13: 37500 | F13: 46149 | G13: =IF(F13="","",YEAR(F13)&"-Q"&ROUNDUP(MONTH(F13)/3,0)) -> 2026-Q2 | H13: D. Whitaker | I13: 4 | J13: 5 | K13: =IF(J13="","",VLOOKUP(J13,Lists!$D$2:$E$9,2,0)) -> Special Mention | L13: =IF(OR(I13="",J13=""),"",IF(I13=J13,"Concur","Grade Change")) -> Grade Change | M13: 4.3 | N13: 1.45 | P13: =COUNTIFS(Responses!$A:$A,$A13,Responses!$G:$G,"No") -> 4 | Q13: =COUNTIFS(Responses!$A:$A,$A13,Responses!$G:$G,"Obs") -> 1 | R13: =COUNTIFS(Responses!$A:$A,$A13,Responses!$G:$G,"Yes")+P13+Q13 -> 25 | S13: =R13+COUNTIFS(Responses!$A:$A,$A13,Responses!$G:$G,"N/A") -> 26 | T13: =COUNTIFS(Responses!$A:$A,$A13) -> 26 | U13: =IF(T13=0,"",S13/T13) -> 1 | V13: =IF(R13=0,"",P13/R13) -> 0.16 | W13: In Progress
A14: ABL-2026001 | B14: ABL | C14: Asset-Based Lending | D14: Royal Textile Mills, Inc. | E14: 10000 | F14: 45883 | G14: =IF(F14="","",YEAR(F14)&"-Q"&ROUNDUP(MONTH(F14)/3,0)) -> 2025-Q3 | H14: A. Chen | I14: 4 | J14: 4 | K14: =IF(J14="","",VLOOKUP(J14,Lists!$D$2:$E$9,2,0)) -> Pass | L14: =IF(OR(I14="",J14=""),"",IF(I14=J14,"Concur","Grade Change")) -> Concur | M14: 4.7 | N14: 1.22 | P14: =COUNTIFS(Responses!$A:$A,$A14,Responses!$G:$G,"No") -> 1 | Q14: =COUNTIFS(Responses!$A:$A,$A14,Responses!$G:$G,"Obs") -> 2 | R14: =COUNTIFS(Responses!$A:$A,$A14,Responses!$G:$G,"Yes")+P14+Q14 -> 25 | S14: =R14+COUNTIFS(Responses!$A:$A,$A14,Responses!$G:$G,"N/A") -> 26 | T14: =COUNTIFS(Responses!$A:$A,$A14) -> 26 | U14: =IF(T14=0,"",S14/T14) -> 1 | V14: =IF(R14=0,"",P14/R14) -> 0.04 | W14: Complete
A15: ABL-2026002 | B15: ABL | C15: Asset-Based Lending | D15: Northgate Auto Parts Supply | E15: 17500 | F15: 45967 | G15: =IF(F15="","",YEAR(F15)&"-Q"&ROUNDUP(MONTH(F15)/3,0)) -> 2025-Q4 | H15: R. Ortiz | I15: 3 | J15: 3 | K15: =IF(J15="","",VLOOKUP(J15,Lists!$D$2:$E$9,2,0)) -> Pass | L15: =IF(OR(I15="",J15=""),"",IF(I15=J15,"Concur","Grade Change")) -> Concur | M15: 4.2 | N15: 1.4 | P15: =COUNTIFS(Responses!$A:$A,$A15,Responses!$G:$G,"No") -> 0 | Q15: =COUNTIFS(Responses!$A:$A,$A15,Responses!$G:$G,"Obs") -> 3 | R15: =COUNTIFS(Responses!$A:$A,$A15,Responses!$G:$G,"Yes")+P15+Q15 -> 24 | S15: =R15+COUNTIFS(Responses!$A:$A,$A15,Responses!$G:$G,"N/A") -> 26 | T15: =COUNTIFS(Responses!$A:$A,$A15) -> 26 | U15: =IF(T15=0,"",S15/T15) -> 1 | V15: =IF(R15=0,"",P15/R15) -> 0 | W15: Complete
A16: ABL-2026003 | B16: ABL | C16: Asset-Based Lending | D16: Crestline Paper Converters | E16: 42500 | F16: 46072 | G16: =IF(F16="","",YEAR(F16)&"-Q"&ROUNDUP(MONTH(F16)/3,0)) -> 2026-Q1 | H16: M. Kowalski | I16: 3 | J16: 3 | K16: =IF(J16="","",VLOOKUP(J16,Lists!$D$2:$E$9,2,0)) -> Pass | L16: =IF(OR(I16="",J16=""),"",IF(I16=J16,"Concur","Grade Change")) -> Concur | M16: 4.3 | N16: 1.42 | P16: =COUNTIFS(Responses!$A:$A,$A16,Responses!$G:$G,"No") -> 3 | Q16: =COUNTIFS(Responses!$A:$A,$A16,Responses!$G:$G,"Obs") -> 2 | R16: =COUNTIFS(Responses!$A:$A,$A16,Responses!$G:$G,"Yes")+P16+Q16 -> 23 | S16: =R16+COUNTIFS(Responses!$A:$A,$A16,Responses!$G:$G,"N/A") -> 26 | T16: =COUNTIFS(Responses!$A:$A,$A16) -> 26 | U16: =IF(T16=0,"",S16/T16) -> 1 | V16: =IF(R16=0,"",P16/R16) -> 0.13043478 | W16: Complete
A17: ABL-2026004 | B17: ABL | C17: Asset-Based Lending | D17: Delta Steel Service Center | E17: 52500 | F17: 46149 | G17: =IF(F17="","",YEAR(F17)&"-Q"&ROUNDUP(MONTH(F17)/3,0)) -> 2026-Q2 | H17: D. Whitaker | I17: 3 | J17: 4 | K17: =IF(J17="","",VLOOKUP(J17,Lists!$D$2:$E$9,2,0)) -> Pass | L17: =IF(OR(I17="",J17=""),"",IF(I17=J17,"Concur","Grade Change")) -> Grade Change | M17: 4.4 | N17: 1.44 | P17: =COUNTIFS(Responses!$A:$A,$A17,Responses!$G:$G,"No") -> 2 | Q17: =COUNTIFS(Responses!$A:$A,$A17,Responses!$G:$G,"Obs") -> 3 | R17: =COUNTIFS(Responses!$A:$A,$A17,Responses!$G:$G,"Yes")+P17+Q17 -> 22 | S17: =R17+COUNTIFS(Responses!$A:$A,$A17,Responses!$G:$G,"N/A") -> 26 | T17: =COUNTIFS(Responses!$A:$A,$A17) -> 26 | U17: =IF(T17=0,"",S17/T17) -> 1 | V17: =IF(R17=0,"",P17/R17) -> 0.090909091 | W17: In Progress
A18: ARG-2026001 | B18: ARG | C18: ARG / Workout | D18: Fairmont Hospitality LLC (Workout) | E18: 42500 | F18: 45883 | G18: =IF(F18="","",YEAR(F18)&"-Q"&ROUNDUP(MONTH(F18)/3,0)) -> 2025-Q3 | H18: A. Chen | I18: 6 | J18: 6 | K18: =IF(J18="","",VLOOKUP(J18,Lists!$D$2:$E$9,2,0)) -> Substandard | L18: =IF(OR(I18="",J18=""),"",IF(I18=J18,"Concur","Grade Change")) -> Concur | M18: 5.7 | N18: 0.66 | P18: =COUNTIFS(Responses!$A:$A,$A18,Responses!$G:$G,"No") -> 2 | Q18: =COUNTIFS(Responses!$A:$A,$A18,Responses!$G:$G,"Obs") -> 3 | R18: =COUNTIFS(Responses!$A:$A,$A18,Responses!$G:$G,"Yes")+P18+Q18 -> 25 | S18: =R18+COUNTIFS(Responses!$A:$A,$A18,Responses!$G:$G,"N/A") -> 27 | T18: =COUNTIFS(Responses!$A:$A,$A18) -> 27 | U18: =IF(T18=0,"",S18/T18) -> 1 | V18: =IF(R18=0,"",P18/R18) -> 0.08 | W18: Complete
A19: ARG-2026002 | B19: ARG | C19: ARG / Workout | D19: Quarry Ridge Homes, Inc. (Workout) | E19: 15000 | F19: 45967 | G19: =IF(F19="","",YEAR(F19)&"-Q"&ROUNDUP(MONTH(F19)/3,0)) -> 2025-Q4 | H19: R. Ortiz | I19: 5 | J19: 5 | K19: =IF(J19="","",VLOOKUP(J19,Lists!$D$2:$E$9,2,0)) -> Special Mention | L19: =IF(OR(I19="",J19=""),"",IF(I19=J19,"Concur","Grade Change")) -> Concur | M19: 6.6 | N19: 0.96 | P19: =COUNTIFS(Responses!$A:$A,$A19,Responses!$G:$G,"No") -> 2 | Q19: =COUNTIFS(Responses!$A:$A,$A19,Responses!$G:$G,"Obs") -> 2 | R19: =COUNTIFS(Responses!$A:$A,$A19,Responses!$G:$G,"Yes")+P19+Q19 -> 27 | S19: =R19+COUNTIFS(Responses!$A:$A,$A19,Responses!$G:$G,"N/A") -> 27 | T19: =COUNTIFS(Responses!$A:$A,$A19) -> 27 | U19: =IF(T19=0,"",S19/T19) -> 1 | V19: =IF(R19=0,"",P19/R19) -> 0.074074074 | W19: Complete
A20: ARG-2026003 | B20: ARG | C20: ARG / Workout | D20: Westbrook Printing Co. (Workout) | E20: 50000 | F20: 46072 | G20: =IF(F20="","",YEAR(F20)&"-Q"&ROUNDUP(MONTH(F20)/3,0)) -> 2026-Q1 | H20: M. Kowalski | I20: 5 | J20: 6 | K20: =IF(J20="","",VLOOKUP(J20,Lists!$D$2:$E$9,2,0)) -> Substandard | L20: =IF(OR(I20="",J20=""),"",IF(I20=J20,"Concur","Grade Change")) -> Grade Change | M20: 5.6 | N20: 0.88 | P20: =COUNTIFS(Responses!$A:$A,$A20,Responses!$G:$G,"No") -> 3 | Q20: =COUNTIFS(Responses!$A:$A,$A20,Responses!$G:$G,"Obs") -> 1 | R20: =COUNTIFS(Responses!$A:$A,$A20,Responses!$G:$G,"Yes")+P20+Q20 -> 25 | S20: =R20+COUNTIFS(Responses!$A:$A,$A20,Responses!$G:$G,"N/A") -> 27 | T20: =COUNTIFS(Responses!$A:$A,$A20) -> 27 | U20: =IF(T20=0,"",S20/T20) -> 1 | V20: =IF(R20=0,"",P20/R20) -> 0.12 | W20: Complete
A21: ARG-2026004 | B21: ARG | C21: ARG / Workout | D21: Sablewood Furniture Mfg. (Workout) | E21: 57500 | F21: 46149 | G21: =IF(F21="","",YEAR(F21)&"-Q"&ROUNDUP(MONTH(F21)/3,0)) -> 2026-Q2 | H21: D. Whitaker | I21: 7 | J21: 7 | K21: =IF(J21="","",VLOOKUP(J21,Lists!$D$2:$E$9,2,0)) -> Doubtful | L21: =IF(OR(I21="",J21=""),"",IF(I21=J21,"Concur","Grade Change")) -> Concur | M21: 5.6 | N21: 0.64 | P21: =COUNTIFS(Responses!$A:$A,$A21,Responses!$G:$G,"No") -> 2 | Q21: =COUNTIFS(Responses!$A:$A,$A21,Responses!$G:$G,"Obs") -> 2 | R21: =COUNTIFS(Responses!$A:$A,$A21,Responses!$G:$G,"Yes")+P21+Q21 -> 27 | S21: =R21+COUNTIFS(Responses!$A:$A,$A21,Responses!$G:$G,"N/A") -> 27 | T21: =COUNTIFS(Responses!$A:$A,$A21) -> 27 | U21: =IF(T21=0,"",S21/T21) -> 1 | V21: =IF(R21=0,"",P21/R21) -> 0.074074074 | W21: In Progress
A22: IA-2026001 | B22: IA | C22: Internal Audit (Generic) | D22: Wire Transfer Operations Audit | E22: 15000 | F22: 45883 | G22: =IF(F22="","",YEAR(F22)&"-Q"&ROUNDUP(MONTH(F22)/3,0)) -> 2025-Q3 | H22: A. Chen | I22: 2 | J22: 2 | K22: =IF(J22="","",VLOOKUP(J22,Lists!$D$2:$E$9,2,0)) -> Pass | L22: =IF(OR(I22="",J22=""),"",IF(I22=J22,"Concur","Grade Change")) -> Concur | P22: =COUNTIFS(Responses!$A:$A,$A22,Responses!$G:$G,"No") -> 0 | Q22: =COUNTIFS(Responses!$A:$A,$A22,Responses!$G:$G,"Obs") -> 2 | R22: =COUNTIFS(Responses!$A:$A,$A22,Responses!$G:$G,"Yes")+P22+Q22 -> 16 | S22: =R22+COUNTIFS(Responses!$A:$A,$A22,Responses!$G:$G,"N/A") -> 19 | T22: =COUNTIFS(Responses!$A:$A,$A22) -> 19 | U22: =IF(T22=0,"",S22/T22) -> 1 | V22: =IF(R22=0,"",P22/R22) -> 0 | W22: Complete
A23: IA-2026002 | B23: IA | C23: Internal Audit (Generic) | D23: Vendor Management Program Audit | E23: 20000 | F23: 45967 | G23: =IF(F23="","",YEAR(F23)&"-Q"&ROUNDUP(MONTH(F23)/3,0)) -> 2025-Q4 | H23: R. Ortiz | I23: 4 | J23: 4 | K23: =IF(J23="","",VLOOKUP(J23,Lists!$D$2:$E$9,2,0)) -> Pass | L23: =IF(OR(I23="",J23=""),"",IF(I23=J23,"Concur","Grade Change")) -> Concur | P23: =COUNTIFS(Responses!$A:$A,$A23,Responses!$G:$G,"No") -> 1 | Q23: =COUNTIFS(Responses!$A:$A,$A23,Responses!$G:$G,"Obs") -> 1 | R23: =COUNTIFS(Responses!$A:$A,$A23,Responses!$G:$G,"Yes")+P23+Q23 -> 16 | S23: =R23+COUNTIFS(Responses!$A:$A,$A23,Responses!$G:$G,"N/A") -> 19 | T23: =COUNTIFS(Responses!$A:$A,$A23) -> 19 | U23: =IF(T23=0,"",S23/T23) -> 1 | V23: =IF(R23=0,"",P23/R23) -> 0.0625 | W23: Complete
A24: IA-2026003 | B24: IA | C24: Internal Audit (Generic) | D24: Loan Servicing Controls Audit | E24: 17500 | F24: 46072 | G24: =IF(F24="","",YEAR(F24)&"-Q"&ROUNDUP(MONTH(F24)/3,0)) -> 2026-Q1 | H24: M. Kowalski | I24: 4 | J24: 4 | K24: =IF(J24="","",VLOOKUP(J24,Lists!$D$2:$E$9,2,0)) -> Pass | L24: =IF(OR(I24="",J24=""),"",IF(I24=J24,"Concur","Grade Change")) -> Concur | P24: =COUNTIFS(Responses!$A:$A,$A24,Responses!$G:$G,"No") -> 1 | Q24: =COUNTIFS(Responses!$A:$A,$A24,Responses!$G:$G,"Obs") -> 3 | R24: =COUNTIFS(Responses!$A:$A,$A24,Responses!$G:$G,"Yes")+P24+Q24 -> 18 | S24: =R24+COUNTIFS(Responses!$A:$A,$A24,Responses!$G:$G,"N/A") -> 19 | T24: =COUNTIFS(Responses!$A:$A,$A24) -> 19 | U24: =IF(T24=0,"",S24/T24) -> 1 | V24: =IF(R24=0,"",P24/R24) -> 0.055555556 | W24: Complete
A25: IA-2026004 | B25: IA | C25: Internal Audit (Generic) | D25: Model Risk Governance Audit | E25: 70000 | F25: 46149 | G25: =IF(F25="","",YEAR(F25)&"-Q"&ROUNDUP(MONTH(F25)/3,0)) -> 2026-Q2 | H25: D. Whitaker | I25: 4 | J25: 5 | K25: =IF(J25="","",VLOOKUP(J25,Lists!$D$2:$E$9,2,0)) -> Special Mention | L25: =IF(OR(I25="",J25=""),"",IF(I25=J25,"Concur","Grade Change")) -> Grade Change | P25: =COUNTIFS(Responses!$A:$A,$A25,Responses!$G:$G,"No") -> 2 | Q25: =COUNTIFS(Responses!$A:$A,$A25,Responses!$G:$G,"Obs") -> 2 | R25: =COUNTIFS(Responses!$A:$A,$A25,Responses!$G:$G,"Yes")+P25+Q25 -> 19 | S25: =R25+COUNTIFS(Responses!$A:$A,$A25,Responses!$G:$G,"N/A") -> 19 | T25: =COUNTIFS(Responses!$A:$A,$A25) -> 19 | U25: =IF(T25=0,"",S25/T25) -> 1 | V25: =IF(R25=0,"",P25/R25) -> 0.10526316 | W25: In Progress
A26: COMP-2026001 | B26: COMP | C26: General Compliance Crosswalk | D26: Compliance Sweep - Alder Mfg. | E26: 30000 | F26: 45883 | G26: =IF(F26="","",YEAR(F26)&"-Q"&ROUNDUP(MONTH(F26)/3,0)) -> 2025-Q3 | H26: A. Chen | I26: 4 | J26: 5 | K26: =IF(J26="","",VLOOKUP(J26,Lists!$D$2:$E$9,2,0)) -> Special Mention | L26: =IF(OR(I26="",J26=""),"",IF(I26=J26,"Concur","Grade Change")) -> Grade Change | P26: =COUNTIFS(Responses!$A:$A,$A26,Responses!$G:$G,"No") -> 0 | Q26: =COUNTIFS(Responses!$A:$A,$A26,Responses!$G:$G,"Obs") -> 1 | R26: =COUNTIFS(Responses!$A:$A,$A26,Responses!$G:$G,"Yes")+P26+Q26 -> 26 | S26: =R26+COUNTIFS(Responses!$A:$A,$A26,Responses!$G:$G,"N/A") -> 26 | T26: =COUNTIFS(Responses!$A:$A,$A26) -> 26 | U26: =IF(T26=0,"",S26/T26) -> 1 | V26: =IF(R26=0,"",P26/R26) -> 0 | W26: Complete
A27: COMP-2026002 | B27: COMP | C27: General Compliance Crosswalk | D27: Compliance Sweep - Birchway Clinics | E27: 22500 | F27: 45967 | G27: =IF(F27="","",YEAR(F27)&"-Q"&ROUNDUP(MONTH(F27)/3,0)) -> 2025-Q4 | H27: R. Ortiz | I27: 2 | J27: 2 | K27: =IF(J27="","",VLOOKUP(J27,Lists!$D$2:$E$9,2,0)) -> Pass | L27: =IF(OR(I27="",J27=""),"",IF(I27=J27,"Concur","Grade Change")) -> Concur | P27: =COUNTIFS(Responses!$A:$A,$A27,Responses!$G:$G,"No") -> 0 | Q27: =COUNTIFS(Responses!$A:$A,$A27,Responses!$G:$G,"Obs") -> 2 | R27: =COUNTIFS(Responses!$A:$A,$A27,Responses!$G:$G,"Yes")+P27+Q27 -> 23 | S27: =R27+COUNTIFS(Responses!$A:$A,$A27,Responses!$G:$G,"N/A") -> 26 | T27: =COUNTIFS(Responses!$A:$A,$A27) -> 26 | U27: =IF(T27=0,"",S27/T27) -> 1 | V27: =IF(R27=0,"",P27/R27) -> 0 | W27: Complete
A28: COMP-2026003 | B28: COMP | C28: General Compliance Crosswalk | D28: Compliance Sweep - Cobalt Foods | E28: 35000 | F28: 46072 | G28: =IF(F28="","",YEAR(F28)&"-Q"&ROUNDUP(MONTH(F28)/3,0)) -> 2026-Q1 | H28: M. Kowalski | I28: 4 | J28: 4 | K28: =IF(J28="","",VLOOKUP(J28,Lists!$D$2:$E$9,2,0)) -> Pass | L28: =IF(OR(I28="",J28=""),"",IF(I28=J28,"Concur","Grade Change")) -> Concur | P28: =COUNTIFS(Responses!$A:$A,$A28,Responses!$G:$G,"No") -> 1 | Q28: =COUNTIFS(Responses!$A:$A,$A28,Responses!$G:$G,"Obs") -> 3 | R28: =COUNTIFS(Responses!$A:$A,$A28,Responses!$G:$G,"Yes")+P28+Q28 -> 25 | S28: =R28+COUNTIFS(Responses!$A:$A,$A28,Responses!$G:$G,"N/A") -> 26 | T28: =COUNTIFS(Responses!$A:$A,$A28) -> 26 | U28: =IF(T28=0,"",S28/T28) -> 1 | V28: =IF(R28=0,"",P28/R28) -> 0.04 | W28: Complete
A29: COMP-2026004 | B29: COMP | C29: General Compliance Crosswalk | D29: Compliance Sweep - Dunmore Plastics | E29: 10000 | F29: 46149 | G29: =IF(F29="","",YEAR(F29)&"-Q"&ROUNDUP(MONTH(F29)/3,0)) -> 2026-Q2 | H29: D. Whitaker | I29: 5 | J29: 5 | K29: =IF(J29="","",VLOOKUP(J29,Lists!$D$2:$E$9,2,0)) -> Special Mention | L29: =IF(OR(I29="",J29=""),"",IF(I29=J29,"Concur","Grade Change")) -> Concur | P29: =COUNTIFS(Responses!$A:$A,$A29,Responses!$G:$G,"No") -> 0 | Q29: =COUNTIFS(Responses!$A:$A,$A29,Responses!$G:$G,"Obs") -> 2 | R29: =COUNTIFS(Responses!$A:$A,$A29,Responses!$G:$G,"Yes")+P29+Q29 -> 24 | S29: =R29+COUNTIFS(Responses!$A:$A,$A29,Responses!$G:$G,"N/A") -> 26 | T29: =COUNTIFS(Responses!$A:$A,$A29) -> 26 | U29: =IF(T29=0,"",S29/T29) -> 1 | V29: =IF(R29=0,"",P29/R29) -> 0 | W29: In Progress

Sheet Responses
A1: Credit ID | B1: Seg | C1: QID | D1: Section | E1: Question | F1: Severity | G1: Answer | H1: Note | I1: Review Date | J1: Reviewer | K1: Days Open (No) | L1: Aging Bucket | M1: ObsIdx | N1: NoIdx
A2: CI-2026001 | B2: CI | C2: CI-Q01 | D2: Credit Quality & Risk-Grade Accuracy | E2: LOB-assigned risk grade is supported by current financial analysis. | F2: High | G2: Yes | I2: 45883 | J2: A. Chen | K2: =IF(G2="No",MAX(0,AsOfDate-I2),"") | L2: =IF(K2="","",IF(K2<=90,"0-90",IF(K2<=180,"91-180",IF(K2<=270,"181-270",">270")))) | M2: =IF(G2="Obs",COUNTIF(G$2:G2,"Obs"),"") | N2: =IF(G2="No",COUNTIF(G$2:G2,"No"),"")
A3: CI-2026001 | B3: CI | C3: CI-Q02 | D3: Credit Quality & Risk-Grade Accuracy | E3: Grade reflects all material credit weaknesses identified in the file. | F3: High | G3: Yes | I3: 45883 | J3: A. Chen | K3: =IF(G3="No",MAX(0,AsOfDate-I3),"") | L3: =IF(K3="","",IF(K3<=90,"0-90",IF(K3<=180,"91-180",IF(K3<=270,"181-270",">270")))) | M3: =IF(G3="Obs",COUNTIF(G$2:G3,"Obs"),"") | N3: =IF(G3="No",COUNTIF(G$2:G3,"No"),"")
A4: CI-2026001 | B4: CI | C4: CI-Q03 | D4: Credit Quality & Risk-Grade Accuracy | E4: Grade was reviewed/affirmed within policy frequency requirements. | F4: Medium | G4: N/A | I4: 45883 | J4: A. Chen | K4: =IF(G4="No",MAX(0,AsOfDate-I4),"") | L4: =IF(K4="","",IF(K4<=90,"0-90",IF(K4<=180,"91-180",IF(K4<=270,"181-270",">270")))) | M4: =IF(G4="Obs",COUNTIF(G$2:G4,"Obs"),"") | N4: =IF(G4="No",COUNTIF(G$2:G4,"No"),"")
A5: CI-2026001 | B5: CI | C5: CI-Q04 | D5: Underwriting Soundness | E5: Underwriting at origination conformed to policy standards in effect. | F5: High | G5: Yes | I5: 45883 | J5: A. Chen | K5: =IF(G5="No",MAX(0,AsOfDate-I5),"") | L5: =IF(K5="","",IF(K5<=90,"0-90",IF(K5<=180,"91-180",IF(K5<=270,"181-270",">270")))) | M5: =IF(G5="Obs",COUNTIF(G$2:G5,"Obs"),"") | N5: =IF(G5="No",COUNTIF(G$2:G5,"No"),"")
A6: CI-2026001 | B6: CI | C6: CI-Q05 | D6: Underwriting Soundness | E6: Financial statements meet policy quality/recency requirements (audit level, age). | F6: Medium | G6: Yes | I6: 45883 | J6: A. Chen | K6: =IF(G6="No",MAX(0,AsOfDate-I6),"") | L6: =IF(K6="","",IF(K6<=90,"0-90",IF(K6<=180,"91-180",IF(K6<=270,"181-270",">270")))) | M6: =IF(G6="Obs",COUNTIF(G$2:G6,"Obs"),"") | N6: =IF(G6="No",COUNTIF(G$2:G6,"No"),"")
A7: CI-2026001 | B7: CI | C7: CI-Q06 | D7: Underwriting Soundness | E7: Analysis critically evaluates borrower-provided information rather than restating it. | F7: High | G7: Yes | I7: 45883 | J7: A. Chen | K7: =IF(G7="No",MAX(0,AsOfDate-I7),"") | L7: =IF(K7="","",IF(K7<=90,"0-90",IF(K7<=180,"91-180",IF(K7<=270,"181-270",">270")))) | M7: =IF(G7="Obs",COUNTIF(G$2:G7,"Obs"),"") | N7: =IF(G7="No",COUNTIF(G$2:G7,"No"),"")
A8: CI-2026001 | B8: CI | C8: CI-Q07 | D8: Repayment Sources & Projections | E8: Primary repayment source is clearly identified and quantitatively supported. | F8: High | G8: Yes | I8: 45883 | J8: A. Chen | K8: =IF(G8="No",MAX(0,AsOfDate-I8),"") | L8: =IF(K8="","",IF(K8<=90,"0-90",IF(K8<=180,"91-180",IF(K8<=270,"181-270",">270")))) | M8: =IF(G8="Obs",COUNTIF(G$2:G8,"Obs"),"") | N8: =IF(G8="No",COUNTIF(G$2:G8,"No"),"")
A9: CI-2026001 | B9: CI | C9: CI-Q08 | D9: Repayment Sources & Projections | E9: Secondary repayment source is identified and realizable. | F9: Medium | G9: Yes | I9: 45883 | J9: A. Chen | K9: =IF(G9="No",MAX(0,AsOfDate-I9),"") | L9: =IF(K9="","",IF(K9<=90,"0-90",IF(K9<=180,"91-180",IF(K9<=270,"181-270",">270")))) | M9: =IF(G9="Obs",COUNTIF(G$2:G9,"Obs"),"") | N9: =IF(G9="No",COUNTIF(G$2:G9,"No"),"")
A10: CI-2026001 | B10: CI | C10: CI-Q09 | D10: Repayment Sources & Projections | E10: Projection assumptions are reasonable versus historical performance and market data. | F10: High | G10: No | H10: UCC continuation lapsed; lien perfection not verified at review date. | I10: 45883 | J10: A. Chen | K10: =IF(G10="No",MAX(0,AsOfDate-I10),"") -> 300 | L10: =IF(K10="","",IF(K10<=90,"0-90",IF(K10<=180,"91-180",IF(K10<=270,"181-270",">270")))) -> >270 | M10: =IF(G10="Obs",COUNTIF(G$2:G10,"Obs"),"") | N10: =IF(G10="No",COUNTIF(G$2:G10,"No"),"") -> 1
A11: CI-2026001 | B11: CI | C11: CI-Q10 | D11: Guarantor / Sponsor Creditworthiness | E11: Guarantor/sponsor financial condition is current, analyzed, and supports reliance. | F11: Medium | G11: N/A | I11: 45883 | J11: A. Chen | K11: =IF(G11="No",MAX(0,AsOfDate-I11),"") | L11: =IF(K11="","",IF(K11<=90,"0-90",IF(K11<=180,"91-180",IF(K11<=270,"181-270",">270")))) | M11: =IF(G11="Obs",COUNTIF(G$2:G11,"Obs"),"") | N11: =IF(G11="No",COUNTIF(G$2:G11,"No"),"")
A12: CI-2026001 | B12: CI | C12: CI-Q11 | D12: Guarantor / Sponsor Creditworthiness | E12: Guaranty enforceability documented (signed, unconditional unless approved otherwise). | F12: Medium | G12: Yes | I12: 45883 | J12: A. Chen | K12: =IF(G12="No",MAX(0,AsOfDate-I12),"") | L12: =IF(K12="","",IF(K12<=90,"0-90",IF(K12<=180,"91-180",IF(K12<=270,"181-270",">270")))) | M12: =IF(G12="Obs",COUNTIF(G$2:G12,"Obs"),"") | N12: =IF(G12="No",COUNTIF(G$2:G12,"No"),"")
A13: CI-2026001 | B13: CI | C13: CI-Q12 | D13: Credit & Collateral Documentation / Lien Perfection | E13: All required credit documents are present, current, and properly executed. | F13: High | G13: Yes | I13: 45883 | J13: A. Chen | K13: =IF(G13="No",MAX(0,AsOfDate-I13),"") | L13: =IF(K13="","",IF(K13<=90,"0-90",IF(K13<=180,"91-180",IF(K13<=270,"181-270",">270")))) | M13: =IF(G13="Obs",COUNTIF(G$2:G13,"Obs"),"") | N13: =IF(G13="No",COUNTIF(G$2:G13,"No"),"")
A14: CI-2026001 | B14: CI | C14: CI-Q13 | D14: Credit & Collateral Documentation / Lien Perfection | E14: Lien positions are perfected and verified (searches, filings, titles). | F14: High | G14: Yes | I14: 45883 | J14: A. Chen | K14: =IF(G14="No",MAX(0,AsOfDate-I14),"") | L14: =IF(K14="","",IF(K14<=90,"0-90",IF(K14<=180,"91-180",IF(K14<=270,"181-270",">270")))) | M14: =IF(G14="Obs",COUNTIF(G$2:G14,"Obs"),"") | N14: =IF(G14="No",COUNTIF(G$2:G14,"No"),"")
A15: CI-2026001 | B15: CI | C15: CI-Q14 | D15: Credit & Collateral Documentation / Lien Perfection | E15: Insurance requirements are met and the bank is loss payee where required. | F15: Low | G15: No | H15: UCC continuation lapsed; lien perfection not verified at review date. | I15: 45883 | J15: A. Chen | K15: =IF(G15="No",MAX(0,AsOfDate-I15),"") -> 300 | L15: =IF(K15="","",IF(K15<=90,"0-90",IF(K15<=180,"91-180",IF(K15<=270,"181-270",">270")))) -> >270 | M15: =IF(G15="Obs",COUNTIF(G$2:G15,"Obs"),"") | N15: =IF(G15="No",COUNTIF(G$2:G15,"No"),"") -> 2
A16: CI-2026001 | B16: CI | C16: CI-Q15 | D16: Approval Authority | E16: Credit was approved within delegated authority of the approving officer(s). | F16: High | G16: Yes | I16: 45883 | J16: A. Chen | K16: =IF(G16="No",MAX(0,AsOfDate-I16),"") | L16: =IF(K16="","",IF(K16<=90,"0-90",IF(K16<=180,"91-180",IF(K16<=270,"181-270",">270")))) | M16: =IF(G16="Obs",COUNTIF(G$2:G16,"Obs"),"") | N16: =IF(G16="No",COUNTIF(G$2:G16,"No"),"")
A17: CI-2026001 | B17: CI | C17: CI-Q16 | D17: Approval Authority | E17: Policy exceptions at approval were identified, justified, and approved at proper level. | F17: Medium | G17: Yes | I17: 45883 | J17: A. Chen | K17: =IF(G17="No",MAX(0,AsOfDate-I17),"") | L17: =IF(K17="","",IF(K17<=90,"0-90",IF(K17<=180,"91-180",IF(K17<=270,"181-270",">270")))) | M17: =IF(G17="Obs",COUNTIF(G$2:G17,"Obs"),"") | N17: =IF(G17="No",COUNTIF(G$2:G17,"No"),"")
A18: CI-2026001 | B18: CI | C18: CI-Q17 | D18: Covenant Adherence | E18: Covenant compliance is tested at required frequency with evidence retained. | F18: Medium | G18: Yes | I18: 45883 | J18: A. Chen | K18: =IF(G18="No",MAX(0,AsOfDate-I18),"") | L18: =IF(K18="","",IF(K18<=90,"0-90",IF(K18<=180,"91-180",IF(K18<=270,"181-270",">270")))) | M18: =IF(G18="Obs",COUNTIF(G$2:G18,"Obs"),"") | N18: =IF(G18="No",COUNTIF(G$2:G18,"No"),"")
A19: CI-2026001 | B19: CI | C19: CI-Q18 | D19: Covenant Adherence | E19: Covenant breaches (if any) were identified, reported, and waived/cured per policy. | F19: High | G19: Yes | I19: 45883 | J19: A. Chen | K19: =IF(G19="No",MAX(0,AsOfDate-I19),"") | L19: =IF(K19="","",IF(K19<=90,"0-90",IF(K19<=180,"91-180",IF(K19<=270,"181-270",">270")))) | M19: =IF(G19="Obs",COUNTIF(G$2:G19,"Obs"),"") | N19: =IF(G19="No",COUNTIF(G$2:G19,"No"),"")
A20: CI-2026001 | B20: CI | C20: CI-Q19 | D20: Policy Compliance | E20: Credit complies with internal lending policy limits (hold limits, tenor, pricing floors). | F20: Medium | G20: Yes | I20: 45883 | J20: A. Chen | K20: =IF(G20="No",MAX(0,AsOfDate-I20),"") | L20: =IF(K20="","",IF(K20<=90,"0-90",IF(K20<=180,"91-180",IF(K20<=270,"181-270",">270")))) | M20: =IF(G20="Obs",COUNTIF(G$2:G20,"Obs"),"") | N20: =IF(G20="No",COUNTIF(G$2:G20,"No"),"")
A21: CI-2026001 | B21: CI | C21: CI-Q20 | D21: Policy Compliance | E21: Required periodic monitoring (annual review, site visits) is current. | F21: Medium | G21: N/A | I21: 45883 | J21: A. Chen | K21: =IF(G21="No",MAX(0,AsOfDate-I21),"") | L21: =IF(K21="","",IF(K21<=90,"0-90",IF(K21<=180,"91-180",IF(K21<=270,"181-270",">270")))) | M21: =IF(G21="Obs",COUNTIF(G$2:G21,"Obs"),"") | N21: =IF(G21="No",COUNTIF(G$2:G21,"No"),"")
A22: CI-2026001 | B22: CI | C22: CI-Q21 | D22: Five Cs of Credit | E22: Character: management track record, credit history, and integrity assessed. | F22: Medium | G22: Yes | I22: 45883 | J22: A. Chen | K22: =IF(G22="No",MAX(0,AsOfDate-I22),"") | L22: =IF(K22="","",IF(K22<=90,"0-90",IF(K22<=180,"91-180",IF(K22<=270,"181-270",">270")))) | M22: =IF(G22="Obs",COUNTIF(G$2:G22,"Obs"),"") | N22: =IF(G22="No",COUNTIF(G$2:G22,"No"),"")
A23: CI-2026001 | B23: CI | C23: CI-Q22 | D23: Five Cs of Credit | E23: Capacity: cash-flow capacity analysis covers debt service under stress. | F23: High | G23: Yes | I23: 45883 | J23: A. Chen | K23: =IF(G23="No",MAX(0,AsOfDate-I23),"") | L23: =IF(K23="","",IF(K23<=90,"0-90",IF(K23<=180,"91-180",IF(K23<=270,"181-270",">270")))) | M23: =IF(G23="Obs",COUNTIF(G$2:G23,"Obs"),"") | N23: =IF(G23="No",COUNTIF(G$2:G23,"No"),"")
A24: CI-2026001 | B24: CI | C24: CI-Q23 | D24: Five Cs of Credit | E24: Capital: borrower equity/tangible net worth is adequate for the risk. | F24: Medium | G24: Yes | I24: 45883 | J24: A. Chen | K24: =IF(G24="No",MAX(0,AsOfDate-I24),"") | L24: =IF(K24="","",IF(K24<=90,"0-90",IF(K24<=180,"91-180",IF(K24<=270,"181-270",">270")))) | M24: =IF(G24="Obs",COUNTIF(G$2:G24,"Obs"),"") | N24: =IF(G24="No",COUNTIF(G$2:G24,"No"),"")
A25: CI-2026001 | B25: CI | C25: CI-Q24 | D25: Five Cs of Credit | E25: Collateral: valuation basis is current and discounts are appropriate. | F25: Medium | G25: Yes | I25: 45883 | J25: A. Chen | K25: =IF(G25="No",MAX(0,AsOfDate-I25),"") | L25: =IF(K25="","",IF(K25<=90,"0-90",IF(K25<=180,"91-180",IF(K25<=270,"181-270",">270")))) | M25: =IF(G25="Obs",COUNTIF(G$2:G25,"Obs"),"") | N25: =IF(G25="No",COUNTIF(G$2:G25,"No"),"")
A26: CI-2026001 | B26: CI | C26: CI-Q25 | D26: Five Cs of Credit | E26: Conditions: industry, market, and macro conditions are evaluated. | F26: Low | G26: N/A | I26: 45883 | J26: A. Chen | K26: =IF(G26="No",MAX(0,AsOfDate-I26),"") | L26: =IF(K26="","",IF(K26<=90,"0-90",IF(K26<=180,"91-180",IF(K26<=270,"181-270",">270")))) | M26: =IF(G26="Obs",COUNTIF(G$2:G26,"Obs"),"") | N26: =IF(G26="No",COUNTIF(G$2:G26,"No"),"")
A27: CI-2026001 | B27: CI | C27: CI-Q26 | D27: Global Cash Flow | E27: Global cash flow combines business and guarantor sources with consistent treatment of taxes/living expenses. | F27: High | G27: Yes | I27: 45883 | J27: A. Chen | K27: =IF(G27="No",MAX(0,AsOfDate-I27),"") | L27: =IF(K27="","",IF(K27<=90,"0-90",IF(K27<=180,"91-180",IF(K27<=270,"181-270",">270")))) | M27: =IF(G27="Obs",COUNTIF(G$2:G27,"Obs"),"") | N27: =IF(G27="No",COUNTIF(G$2:G27,"No"),"")
... A31: CI-2026002 | B31: CI | C31: CI-Q03 | D31: Credit Quality & Risk-Grade Accuracy | E31: Grade was reviewed/affirmed within policy frequency requirements. | F31: Medium | G31: Yes | I31: 45967 | J31: R. Ortiz | K31: =IF(G31="No",MAX(0,AsOfDate-I31),"") | L31: =IF(K31="","",IF(K31<=90,"0-90",IF(K31<=180,"91-180",IF(K31<=270,"181-270",">270")))) | M31: =IF(G31="Obs",COUNTIF(G$2:G31,"Obs"),"") | N31: =IF(G31="No",COUNTIF(G$2:G31,"No"),"")
A32: CI-2026002 | B32: CI | C32: CI-Q04 | D32: Underwriting Soundness | E32: Underwriting at origination conformed to policy standards in effect. | F32: High | G32: No | H32: Covenant test for Q4 not evidenced; compliance certificate missing. | I32: 45967 | J32: R. Ortiz | K32: =IF(G32="No",MAX(0,AsOfDate-I32),"") -> 216 | L32: =IF(K32="","",IF(K32<=90,"0-90",IF(K32<=180,"91-180",IF(K32<=270,"181-270",">270")))) -> 181-270 | M32: =IF(G32="Obs",COUNTIF(G$2:G32,"Obs"),"") | N32: =IF(G32="No",COUNTIF(G$2:G32,"No"),"") -> 3
A33: CI-2026002 | B33: CI | C33: CI-Q05 | D33: Underwriting Soundness | E33: Financial statements meet policy quality/recency requirements (audit level, age). | F33: Medium | G33: Yes | I33: 45967 | J33: R. Ortiz | K33: =IF(G33="No",MAX(0,AsOfDate-I33),"") | L33: =IF(K33="","",IF(K33<=90,"0-90",IF(K33<=180,"91-180",IF(K33<=270,"181-270",">270")))) | M33: =IF(G33="Obs",COUNTIF(G$2:G33,"Obs"),"") | N33: =IF(G33="No",COUNTIF(G$2:G33,"No"),"")
A34: CI-2026002 | B34: CI | C34: CI-Q06 | D34: Underwriting Soundness | E34: Analysis critically evaluates borrower-provided information rather than restating it. | F34: High | G34: N/A | I34: 45967 | J34: R. Ortiz | K34: =IF(G34="No",MAX(0,AsOfDate-I34),"") | L34: =IF(K34="","",IF(K34<=90,"0-90",IF(K34<=180,"91-180",IF(K34<=270,"181-270",">270")))) | M34: =IF(G34="Obs",COUNTIF(G$2:G34,"Obs"),"") | N34: =IF(G34="No",COUNTIF(G$2:G34,"No"),"")
A35: CI-2026002 | B35: CI | C35: CI-Q07 | D35: Repayment Sources & Projections | E35: Primary repayment source is clearly identified and quantitatively supported. | F35: High | G35: Yes | I35: 45967 | J35: R. Ortiz | K35: =IF(G35="No",MAX(0,AsOfDate-I35),"") | L35: =IF(K35="","",IF(K35<=90,"0-90",IF(K35<=180,"91-180",IF(K35<=270,"181-270",">270")))) | M35: =IF(G35="Obs",COUNTIF(G$2:G35,"Obs"),"") | N35: =IF(G35="No",COUNTIF(G$2:G35,"No"),"")
A36: CI-2026002 | B36: CI | C36: CI-Q08 | D36: Repayment Sources & Projections | E36: Secondary repayment source is identified and realizable. | F36: Medium | G36: Yes | I36: 45967 | J36: R. Ortiz | K36: =IF(G36="No",MAX(0,AsOfDate-I36),"") | L36: =IF(K36="","",IF(K36<=90,"0-90",IF(K36<=180,"91-180",IF(K36<=270,"181-270",">270")))) | M36: =IF(G36="Obs",COUNTIF(G$2:G36,"Obs"),"") | N36: =IF(G36="No",COUNTIF(G$2:G36,"No"),"")
A37: CI-2026002 | B37: CI | C37: CI-Q09 | D37: Repayment Sources & Projections | E37: Projection assumptions are reasonable versus historical performance and market data. | F37: High | G37: Yes | I37: 45967 | J37: R. Ortiz | K37: =IF(G37="No",MAX(0,AsOfDate-I37),"") | L37: =IF(K37="","",IF(K37<=90,"0-90",IF(K37<=180,"91-180",IF(K37<=270,"181-270",">270")))) | M37: =IF(G37="Obs",COUNTIF(G$2:G37,"Obs"),"") | N37: =IF(G37="No",COUNTIF(G$2:G37,"No"),"")
A38: CI-2026002 | B38: CI | C38: CI-Q10 | D38: Guarantor / Sponsor Creditworthiness | E38: Guarantor/sponsor financial condition is current, analyzed, and supports reliance. | F38: Medium | G38: Yes | I38: 45967 | J38: R. Ortiz | K38: =IF(G38="No",MAX(0,AsOfDate-I38),"") | L38: =IF(K38="","",IF(K38<=90,"0-90",IF(K38<=180,"91-180",IF(K38<=270,"181-270",">270")))) | M38: =IF(G38="Obs",COUNTIF(G$2:G38,"Obs"),"") | N38: =IF(G38="No",COUNTIF(G$2:G38,"No"),"")
A39: CI-2026002 | B39: CI | C39: CI-Q11 | D39: Guarantor / Sponsor Creditworthiness | E39: Guaranty enforceability documented (signed, unconditional unless approved otherwise). | F39: Medium | G39: Yes | I39: 45967 | J39: R. Ortiz | K39: =IF(G39="No",MAX(0,AsOfDate-I39),"") | L39: =IF(K39="","",IF(K39<=90,"0-90",IF(K39<=180,"91-180",IF(K39<=270,"181-270",">270")))) | M39: =IF(G39="Obs",COUNTIF(G$2:G39,"Obs"),"") | N39: =IF(G39="No",COUNTIF(G$2:G39,"No"),"")
A40: CI-2026002 | B40: CI | C40: CI-Q12 | D40: Credit & Collateral Documentation / Lien Perfection | E40: All required credit documents are present, current, and properly executed. | F40: High | G40: Yes | I40: 45967 | J40: R. Ortiz | K40: =IF(G40="No",MAX(0,AsOfDate-I40),"") | L40: =IF(K40="","",IF(K40<=90,"0-90",IF(K40<=180,"91-180",IF(K40<=270,"181-270",">270")))) | M40: =IF(G40="Obs",COUNTIF(G$2:G40,"Obs"),"") | N40: =IF(G40="No",COUNTIF(G$2:G40,"No"),"")
A41: CI-2026002 | B41: CI | C41: CI-Q13 | D41: Credit & Collateral Documentation / Lien Perfection | E41: Lien positions are perfected and verified (searches, filings, titles). | F41: High | G41: Yes | I41: 45967 | J41: R. Ortiz | K41: =IF(G41="No",MAX(0,AsOfDate-I41),"") | L41: =IF(K41="","",IF(K41<=90,"0-90",IF(K41<=180,"91-180",IF(K41<=270,"181-270",">270")))) | M41: =IF(G41="Obs",COUNTIF(G$2:G41,"Obs"),"") | N41: =IF(G41="No",COUNTIF(G$2:G41,"No"),"")
A42: CI-2026002 | B42: CI | C42: CI-Q14 | D42: Credit & Collateral Documentation / Lien Perfection | E42: Insurance requirements are met and the bank is loss payee where required. | F42: Low | G42: Yes | I42: 45967 | J42: R. Ortiz | K42: =IF(G42="No",MAX(0,AsOfDate-I42),"") | L42: =IF(K42="","",IF(K42<=90,"0-90",IF(K42<=180,"91-180",IF(K42<=270,"181-270",">270")))) | M42: =IF(G42="Obs",COUNTIF(G$2:G42,"Obs"),"") | N42: =IF(G42="No",COUNTIF(G$2:G42,"No"),"")
A43: CI-2026002 | B43: CI | C43: CI-Q15 | D43: Approval Authority | E43: Credit was approved within delegated authority of the approving officer(s). | F43: High | G43: Yes | I43: 45967 | J43: R. Ortiz | K43: =IF(G43="No",MAX(0,AsOfDate-I43),"") | L43: =IF(K43="","",IF(K43<=90,"0-90",IF(K43<=180,"91-180",IF(K43<=270,"181-270",">270")))) | M43: =IF(G43="Obs",COUNTIF(G$2:G43,"Obs"),"") | N43: =IF(G43="No",COUNTIF(G$2:G43,"No"),"")
A44: CI-2026002 | B44: CI | C44: CI-Q16 | D44: Approval Authority | E44: Policy exceptions at approval were identified, justified, and approved at proper level. | F44: Medium | G44: Yes | I44: 45967 | J44: R. Ortiz | K44: =IF(G44="No",MAX(0,AsOfDate-I44),"") | L44: =IF(K44="","",IF(K44<=90,"0-90",IF(K44<=180,"91-180",IF(K44<=270,"181-270",">270")))) | M44: =IF(G44="Obs",COUNTIF(G$2:G44,"Obs"),"") | N44: =IF(G44="No",COUNTIF(G$2:G44,"No"),"")
... A47: CI-2026002 | B47: CI | C47: CI-Q19 | D47: Policy Compliance | E47: Credit complies with internal lending policy limits (hold limits, tenor, pricing floors). | F47: Medium | G47: N/A | I47: 45967 | J47: R. Ortiz | K47: =IF(G47="No",MAX(0,AsOfDate-I47),"") | L47: =IF(K47="","",IF(K47<=90,"0-90",IF(K47<=180,"91-180",IF(K47<=270,"181-270",">270")))) | M47: =IF(G47="Obs",COUNTIF(G$2:G47,"Obs"),"") | N47: =IF(G47="No",COUNTIF(G$2:G47,"No"),"")
A48: CI-2026002 | B48: CI | C48: CI-Q20 | D48: Policy Compliance | E48: Required periodic monitoring (annual review, site visits) is current. | F48: Medium | G48: Obs | H48: Annual review completed 10 days before deadline two cycles running - timing risk. | I48: 45967 | J48: R. Ortiz | K48: =IF(G48="No",MAX(0,AsOfDate-I48),"") | L48: =IF(K48="","",IF(K48<=90,"0-90",IF(K48<=180,"91-180",IF(K48<=270,"181-270",">270")))) | M48: =IF(G48="Obs",COUNTIF(G$2:G48,"Obs"),"") -> 1 | N48: =IF(G48="No",COUNTIF(G$2:G48,"No"),"")
A49: CI-2026002 | B49: CI | C49: CI-Q21 | D49: Five Cs of Credit | E49: Character: management track record, credit history, and integrity assessed. | F49: Medium | G49: Yes | I49: 45967 | J49: R. Ortiz | K49: =IF(G49="No",MAX(0,AsOfDate-I49),"") | L49: =IF(K49="","",IF(K49<=90,"0-90",IF(K49<=180,"91-180",IF(K49<=270,"181-270",">270")))) | M49: =IF(G49="Obs",COUNTIF(G$2:G49,"Obs"),"") | N49: =IF(G49="No",COUNTIF(G$2:G49,"No"),"")
A50: CI-2026002 | B50: CI | C50: CI-Q22 | D50: Five Cs of Credit | E50: Capacity: cash-flow capacity analysis covers debt service under stress. | F50: High | G50: Yes | I50: 45967 | J50: R. Ortiz | K50: =IF(G50="No",MAX(0,AsOfDate-I50),"") | L50: =IF(K50="","",IF(K50<=90,"0-90",IF(K50<=180,"91-180",IF(K50<=270,"181-270",">270")))) | M50: =IF(G50="Obs",COUNTIF(G$2:G50,"Obs"),"") | N50: =IF(G50="No",COUNTIF(G$2:G50,"No"),"")
A51: CI-2026002 | B51: CI | C51: CI-Q23 | D51: Five Cs of Credit | E51: Capital: borrower equity/tangible net worth is adequate for the risk. | F51: Medium | G51: No | H51: Financial statements stale beyond policy window; no waiver in file. | I51: 45967 | J51: R. Ortiz | K51: =IF(G51="No",MAX(0,AsOfDate-I51),"") -> 216 | L51: =IF(K51="","",IF(K51<=90,"0-90",IF(K51<=180,"91-180",IF(K51<=270,"181-270",">270")))) -> 181-270 | M51: =IF(G51="Obs",COUNTIF(G$2:G51,"Obs"),"") | N51: =IF(G51="No",COUNTIF(G$2:G51,"No"),"") -> 4
A52: CI-2026002 | B52: CI | C52: CI-Q24 | D52: Five Cs of Credit | E52: Collateral: valuation basis is current and discounts are appropriate. | F52: Medium | G52: Yes | I52: 45967 | J52: R. Ortiz | K52: =IF(G52="No",MAX(0,AsOfDate-I52),"") | L52: =IF(K52="","",IF(K52<=90,"0-90",IF(K52<=180,"91-180",IF(K52<=270,"181-270",">270")))) | M52: =IF(G52="Obs",COUNTIF(G$2:G52,"Obs"),"") | N52: =IF(G52="No",COUNTIF(G$2:G52,"No"),"")
A53: CI-2026002 | B53: CI | C53: CI-Q25 | D53: Five Cs of Credit | E53: Conditions: industry, market, and macro conditions are evaluated. | F53: Low | G53: Yes | I53: 45967 | J53: R. Ortiz | K53: =IF(G53="No",MAX(0,AsOfDate-I53),"") | L53: =IF(K53="","",IF(K53<=90,"0-90",IF(K53<=180,"91-180",IF(K53<=270,"181-270",">270")))) | M53: =IF(G53="Obs",COUNTIF(G$2:G53,"Obs"),"") | N53: =IF(G53="No",COUNTIF(G$2:G53,"No"),"")
A54: CI-2026002 | B54: CI | C54: CI-Q26 | D54: Global Cash Flow | E54: Global cash flow combines business and guarantor sources with consistent treatment of taxes/living expenses. | F54: High | G54: Yes | I54: 45967 | J54: R. Ortiz | K54: =IF(G54="No",MAX(0,AsOfDate-I54),"") | L54: =IF(K54="","",IF(K54<=90,"0-90",IF(K54<=180,"91-180",IF(K54<=270,"181-270",">270")))) | M54: =IF(G54="Obs",COUNTIF(G$2:G54,"Obs"),"") | N54: =IF(G54="No",COUNTIF(G$2:G54,"No"),"")
A55: CI-2026002 | B55: CI | C55: CI-Q27 | D55: Global Cash Flow | E55: Inter-company / related-entity flows are identified and not double-counted. | F55: Medium | G55: Yes | I55: 45967 | J55: R. Ortiz | K55: =IF(G55="No",MAX(0,AsOfDate-I55),"") | L55: =IF(K55="","",IF(K55<=90,"0-90",IF(K55<=180,"91-180",IF(K55<=270,"181-270",">270")))) | M55: =IF(G55="Obs",COUNTIF(G$2:G55,"Obs"),"") | N55: =IF(G55="No",COUNTIF(G$2:G55,"No"),"")
A56: CI-2026003 | B56: CI | C56: CI-Q01 | D56: Credit Quality & Risk-Grade Accuracy | E56: LOB-assigned risk grade is supported by current financial analysis. | F56: High | G56: No | H56: Financial statements stale beyond policy window; no waiver in file. | I56: 46072 | J56: M. Kowalski | K56: =IF(G56="No",MAX(0,AsOfDate-I56),"") -> 111 | L56: =IF(K56="","",IF(K56<=90,"0-90",IF(K56<=180,"91-180",IF(K56<=270,"181-270",">270")))) -> 91-180 | M56: =IF(G56="Obs",COUNTIF(G$2:G56,"Obs"),"") | N56: =IF(G56="No",COUNTIF(G$2:G56,"No"),"") -> 5
A57: CI-2026003 | B57: CI | C57: CI-Q02 | D57: Credit Quality & Risk-Grade Accuracy | E57: Grade reflects all material credit weaknesses identified in the file. | F57: High | G57: Yes | I57: 46072 | J57: M. Kowalski | K57: =IF(G57="No",MAX(0,AsOfDate-I57),"") | L57: =IF(K57="","",IF(K57<=90,"0-90",IF(K57<=180,"91-180",IF(K57<=270,"181-270",">270")))) | M57: =IF(G57="Obs",COUNTIF(G$2:G57,"Obs"),"") | N57: =IF(G57="No",COUNTIF(G$2:G57,"No"),"")
A58: CI-2026003 | B58: CI | C58: CI-Q03 | D58: Credit Quality & Risk-Grade Accuracy | E58: Grade was reviewed/affirmed within policy frequency requirements. | F58: Medium | G58: Yes | I58: 46072 | J58: M. Kowalski | K58: =IF(G58="No",MAX(0,AsOfDate-I58),"") | L58: =IF(K58="","",IF(K58<=90,"0-90",IF(K58<=180,"91-180",IF(K58<=270,"181-270",">270")))) | M58: =IF(G58="Obs",COUNTIF(G$2:G58,"Obs"),"") | N58: =IF(G58="No",COUNTIF(G$2:G58,"No"),"")
A59: CI-2026003 | B59: CI | C59: CI-Q04 | D59: Underwriting Soundness | E59: Underwriting at origination conformed to policy standards in effect. | F59: High | G59: Yes | I59: 46072 | J59: M. Kowalski | K59: =IF(G59="No",MAX(0,AsOfDate-I59),"") | L59: =IF(K59="","",IF(K59<=90,"0-90",IF(K59<=180,"91-180",IF(K59<=270,"181-270",">270")))) | M59: =IF(G59="Obs",COUNTIF(G$2:G59,"Obs"),"") | N59: =IF(G59="No",COUNTIF(G$2:G59,"No"),"")
A60: CI-2026003 | B60: CI | C60: CI-Q05 | D60: Underwriting Soundness | E60: Financial statements meet policy quality/recency requirements (audit level, age). | F60: Medium | G60: Yes | I60: 46072 | J60: M. Kowalski | K60: =IF(G60="No",MAX(0,AsOfDate-I60),"") | L60: =IF(K60="","",IF(K60<=90,"0-90",IF(K60<=180,"91-180",IF(K60<=270,"181-270",">270")))) | M60: =IF(G60="Obs",COUNTIF(G$2:G60,"Obs"),"") | N60: =IF(G60="No",COUNTIF(G$2:G60,"No"),"")
A61: CI-2026003 | B61: CI | C61: CI-Q06 | D61: Underwriting Soundness | E61: Analysis critically evaluates borrower-provided information rather than restating it. | F61: High | G61: Yes | I61: 46072 | J61: M. Kowalski | K61: =IF(G61="No",MAX(0,AsOfDate-I61),"") | L61: =IF(K61="","",IF(K61<=90,"0-90",IF(K61<=180,"91-180",IF(K61<=270,"181-270",">270")))) | M61: =IF(G61="Obs",COUNTIF(G$2:G61,"Obs"),"") | N61: =IF(G61="No",COUNTIF(G$2:G61,"No"),"")
A62: CI-2026003 | B62: CI | C62: CI-Q07 | D62: Repayment Sources & Projections | E62: Primary repayment source is clearly identified and quantitatively supported. | F62: High | G62: Yes | I62: 46072 | J62: M. Kowalski | K62: =IF(G62="No",MAX(0,AsOfDate-I62),"") | L62: =IF(K62="","",IF(K62<=90,"0-90",IF(K62<=180,"91-180",IF(K62<=270,"181-270",">270")))) | M62: =IF(G62="Obs",COUNTIF(G$2:G62,"Obs"),"") | N62: =IF(G62="No",COUNTIF(G$2:G62,"No"),"")
A63: CI-2026003 | B63: CI | C63: CI-Q08 | D63: Repayment Sources & Projections | E63: Secondary repayment source is identified and realizable. | F63: Medium | G63: Yes | I63: 46072 | J63: M. Kowalski | K63: =IF(G63="No",MAX(0,AsOfDate-I63),"") | L63: =IF(K63="","",IF(K63<=90,"0-90",IF(K63<=180,"91-180",IF(K63<=270,"181-270",">270")))) | M63: =IF(G63="Obs",COUNTIF(G$2:G63,"Obs"),"") | N63: =IF(G63="No",COUNTIF(G$2:G63,"No"),"")
A64: CI-2026003 | B64: CI | C64: CI-Q09 | D64: Repayment Sources & Projections | E64: Projection assumptions are reasonable versus historical performance and market data. | F64: High | G64: Yes | I64: 46072 | J64: M. Kowalski | K64: =IF(G64="No",MAX(0,AsOfDate-I64),"") | L64: =IF(K64="","",IF(K64<=90,"0-90",IF(K64<=180,"91-180",IF(K64<=270,"181-270",">270")))) | M64: =IF(G64="Obs",COUNTIF(G$2:G64,"Obs"),"") | N64: =IF(G64="No",COUNTIF(G$2:G64,"No"),"")
A65: CI-2026003 | B65: CI | C65: CI-Q10 | D65: Guarantor / Sponsor Creditworthiness | E65: Guarantor/sponsor financial condition is current, analyzed, and supports reliance. | F65: Medium | G65: N/A | I65: 46072 | J65: M. Kowalski | K65: =IF(G65="No",MAX(0,AsOfDate-I65),"") | L65: =IF(K65="","",IF(K65<=90,"0-90",IF(K65<=180,"91-180",IF(K65<=270,"181-270",">270")))) | M65: =IF(G65="Obs",COUNTIF(G$2:G65,"Obs"),"") | N65: =IF(G65="No",COUNTIF(G$2:G65,"No"),"")
A66: CI-2026003 | B66: CI | C66: CI-Q11 | D66: Guarantor / Sponsor Creditworthiness | E66: Guaranty enforceability documented (signed, unconditional unless approved otherwise). | F66: Medium | G66: Yes | I66: 46072 | J66: M. Kowalski | K66: =IF(G66="No",MAX(0,AsOfDate-I66),"") | L66: =IF(K66="","",IF(K66<=90,"0-90",IF(K66<=180,"91-180",IF(K66<=270,"181-270",">270")))) | M66: =IF(G66="Obs",COUNTIF(G$2:G66,"Obs"),"") | N66: =IF(G66="No",COUNTIF(G$2:G66,"No"),"")
A67: CI-2026003 | B67: CI | C67: CI-Q12 | D67: Credit & Collateral Documentation / Lien Perfection | E67: All required credit documents are present, current, and properly executed. | F67: High | G67: Yes | I67: 46072 | J67: M. Kowalski | K67: =IF(G67="No",MAX(0,AsOfDate-I67),"") | L67: =IF(K67="","",IF(K67<=90,"0-90",IF(K67<=180,"91-180",IF(K67<=270,"181-270",">270")))) | M67: =IF(G67="Obs",COUNTIF(G$2:G67,"Obs"),"") | N67: =IF(G67="No",COUNTIF(G$2:G67,"No"),"")
A68: CI-2026003 | B68: CI | C68: CI-Q13 | D68: Credit & Collateral Documentation / Lien Perfection | E68: Lien positions are perfected and verified (searches, filings, titles). | F68: High | G68: Yes | I68: 46072 | J68: M. Kowalski | K68: =IF(G68="No",MAX(0,AsOfDate-I68),"") | L68: =IF(K68="","",IF(K68<=90,"0-90",IF(K68<=180,"91-180",IF(K68<=270,"181-270",">270")))) | M68: =IF(G68="Obs",COUNTIF(G$2:G68,"Obs"),"") | N68: =IF(G68="No",COUNTIF(G$2:G68,"No"),"")
... A79: CI-2026003 | B79: CI | C79: CI-Q24 | D79: Five Cs of Credit | E79: Collateral: valuation basis is current and discounts are appropriate. | F79: Medium | G79: Yes | I79: 46072 | J79: M. Kowalski | K79: =IF(G79="No",MAX(0,AsOfDate-I79),"") | L79: =IF(K79="","",IF(K79<=90,"0-90",IF(K79<=180,"91-180",IF(K79<=270,"181-270",">270")))) | M79: =IF(G79="Obs",COUNTIF(G$2:G79,"Obs"),"") | N79: =IF(G79="No",COUNTIF(G$2:G79,"No"),"")
A80: CI-2026003 | B80: CI | C80: CI-Q25 | D80: Five Cs of Credit | E80: Conditions: industry, market, and macro conditions are evaluated. | F80: Low | G80: No | H80: Covenant test for Q4 not evidenced; compliance certificate missing. | I80: 46072 | J80: M. Kowalski | K80: =IF(G80="No",MAX(0,AsOfDate-I80),"") -> 111 | L80: =IF(K80="","",IF(K80<=90,"0-90",IF(K80<=180,"91-180",IF(K80<=270,"181-270",">270")))) -> 91-180 | M80: =IF(G80="Obs",COUNTIF(G$2:G80,"Obs"),"") | N80: =IF(G80="No",COUNTIF(G$2:G80,"No"),"") -> 6
A81: CI-2026003 | B81: CI | C81: CI-Q26 | D81: Global Cash Flow | E81: Global cash flow combines business and guarantor sources with consistent treatment of taxes/living expenses. | F81: High | G81: Yes | I81: 46072 | J81: M. Kowalski | K81: =IF(G81="No",MAX(0,AsOfDate-I81),"") | L81: =IF(K81="","",IF(K81<=90,"0-90",IF(K81<=180,"91-180",IF(K81<=270,"181-270",">270")))) | M81: =IF(G81="Obs",COUNTIF(G$2:G81,"Obs"),"") | N81: =IF(G81="No",COUNTIF(G$2:G81,"No"),"")
A82: CI-2026003 | B82: CI | C82: CI-Q27 | D82: Global Cash Flow | E82: Inter-company / related-entity flows are identified and not double-counted. | F82: Medium | G82: Yes | I82: 46072 | J82: M. Kowalski | K82: =IF(G82="No",MAX(0,AsOfDate-I82),"") | L82: =IF(K82="","",IF(K82<=90,"0-90",IF(K82<=180,"91-180",IF(K82<=270,"181-270",">270")))) | M82: =IF(G82="Obs",COUNTIF(G$2:G82,"Obs"),"") | N82: =IF(G82="No",COUNTIF(G$2:G82,"No"),"")
A83: CI-2026004 | B83: CI | C83: CI-Q01 | D83: Credit Quality & Risk-Grade Accuracy | E83: LOB-assigned risk grade is supported by current financial analysis. | F83: High | G83: N/A | I83: 46149 | J83: D. Whitaker | K83: =IF(G83="No",MAX(0,AsOfDate-I83),"") | L83: =IF(K83="","",IF(K83<=90,"0-90",IF(K83<=180,"91-180",IF(K83<=270,"181-270",">270")))) | M83: =IF(G83="Obs",COUNTIF(G$2:G83,"Obs"),"") | N83: =IF(G83="No",COUNTIF(G$2:G83,"No"),"")
A84: CI-2026004 | B84: CI | C84: CI-Q02 | D84: Credit Quality & Risk-Grade Accuracy | E84: Grade reflects all material credit weaknesses identified in the file. | F84: High | G84: Yes | I84: 46149 | J84: D. Whitaker | K84: =IF(G84="No",MAX(0,AsOfDate-I84),"") | L84: =IF(K84="","",IF(K84<=90,"0-90",IF(K84<=180,"91-180",IF(K84<=270,"181-270",">270")))) | M84: =IF(G84="Obs",COUNTIF(G$2:G84,"Obs"),"") | N84: =IF(G84="No",COUNTIF(G$2:G84,"No"),"")
A85: CI-2026004 | B85: CI | C85: CI-Q03 | D85: Credit Quality & Risk-Grade Accuracy | E85: Grade was reviewed/affirmed within policy frequency requirements. | F85: Medium | G85: Yes | I85: 46149 | J85: D. Whitaker | K85: =IF(G85="No",MAX(0,AsOfDate-I85),"") | L85: =IF(K85="","",IF(K85<=90,"0-90",IF(K85<=180,"91-180",IF(K85<=270,"181-270",">270")))) | M85: =IF(G85="Obs",COUNTIF(G$2:G85,"Obs"),"") | N85: =IF(G85="No",COUNTIF(G$2:G85,"No"),"")
A86: CI-2026004 | B86: CI | C86: CI-Q04 | D86: Underwriting Soundness | E86: Underwriting at origination conformed to policy standards in effect. | F86: High | G86: Yes | I86: 46149 | J86: D. Whitaker | K86: =IF(G86="No",MAX(0,AsOfDate-I86),"") | L86: =IF(K86="","",IF(K86<=90,"0-90",IF(K86<=180,"91-180",IF(K86<=270,"181-270",">270")))) | M86: =IF(G86="Obs",COUNTIF(G$2:G86,"Obs"),"") | N86: =IF(G86="No",COUNTIF(G$2:G86,"No"),"")
A87: CI-2026004 | B87: CI | C87: CI-Q05 | D87: Underwriting Soundness | E87: Financial statements meet policy quality/recency requirements (audit level, age). | F87: Medium | G87: Yes | I87: 46149 | J87: D. Whitaker | K87: =IF(G87="No",MAX(0,AsOfDate-I87),"") | L87: =IF(K87="","",IF(K87<=90,"0-90",IF(K87<=180,"91-180",IF(K87<=270,"181-270",">270")))) | M87: =IF(G87="Obs",COUNTIF(G$2:G87,"Obs"),"") | N87: =IF(G87="No",COUNTIF(G$2:G87,"No"),"")
A88: CI-2026004 | B88: CI | C88: CI-Q06 | D88: Underwriting Soundness | E88: Analysis critically evaluates borrower-provided information rather than restating it. | F88: High | G88: Yes | I88: 46149 | J88: D. Whitaker | K88: =IF(G88="No",MAX(0,AsOfDate-I88),"") | L88: =IF(K88="","",IF(K88<=90,"0-90",IF(K88<=180,"91-180",IF(K88<=270,"181-270",">270")))) | M88: =IF(G88="Obs",COUNTIF(G$2:G88,"Obs"),"") | N88: =IF(G88="No",COUNTIF(G$2:G88,"No"),"")
A89: CI-2026004 | B89: CI | C89: CI-Q07 | D89: Repayment Sources & Projections | E89: Primary repayment source is clearly identified and quantitatively supported. | F89: High | G89: Yes | I89: 46149 | J89: D. Whitaker | K89: =IF(G89="No",MAX(0,AsOfDate-I89),"") | L89: =IF(K89="","",IF(K89<=90,"0-90",IF(K89<=180,"91-180",IF(K89<=270,"181-270",">270")))) | M89: =IF(G89="Obs",COUNTIF(G$2:G89,"Obs"),"") | N89: =IF(G89="No",COUNTIF(G$2:G89,"No"),"")
A90: CI-2026004 | B90: CI | C90: CI-Q08 | D90: Repayment Sources & Projections | E90: Secondary repayment source is identified and realizable. | F90: Medium | G90: Yes | I90: 46149 | J90: D. Whitaker | K90: =IF(G90="No",MAX(0,AsOfDate-I90),"") | L90: =IF(K90="","",IF(K90<=90,"0-90",IF(K90<=180,"91-180",IF(K90<=270,"181-270",">270")))) | M90: =IF(G90="Obs",COUNTIF(G$2:G90,"Obs"),"") | N90: =IF(G90="No",COUNTIF(G$2:G90,"No"),"")
A91: CI-2026004 | B91: CI | C91: CI-Q09 | D91: Repayment Sources & Projections | E91: Projection assumptions are reasonable versus historical performance and market data. | F91: High | G91: Yes | I91: 46149 | J91: D. Whitaker | K91: =IF(G91="No",MAX(0,AsOfDate-I91),"") | L91: =IF(K91="","",IF(K91<=90,"0-90",IF(K91<=180,"91-180",IF(K91<=270,"181-270",">270")))) | M91: =IF(G91="Obs",COUNTIF(G$2:G91,"Obs"),"") | N91: =IF(G91="No",COUNTIF(G$2:G91,"No"),"")
A92: CI-2026004 | B92: CI | C92: CI-Q10 | D92: Guarantor / Sponsor Creditworthiness | E92: Guarantor/sponsor financial condition is current, analyzed, and supports reliance. | F92: Medium | G92: N/A | I92: 46149 | J92: D. Whitaker | K92: =IF(G92="No",MAX(0,AsOfDate-I92),"") | L92: =IF(K92="","",IF(K92<=90,"0-90",IF(K92<=180,"91-180",IF(K92<=270,"181-270",">270")))) | M92: =IF(G92="Obs",COUNTIF(G$2:G92,"Obs"),"") | N92: =IF(G92="No",COUNTIF(G$2:G92,"No"),"")
A93: CI-2026004 | B93: CI | C93: CI-Q11 | D93: Guarantor / Sponsor Creditworthiness | E93: Guaranty enforceability documented (signed, unconditional unless approved otherwise). | F93: Medium | G93: No | H93: Financial statements stale beyond policy window; no waiver in file. | I93: 46149 | J93: D. Whitaker | K93: =IF(G93="No",MAX(0,AsOfDate-I93),"") -> 34 | L93: =IF(K93="","",IF(K93<=90,"0-90",IF(K93<=180,"91-180",IF(K93<=270,"181-270",">270")))) -> 0-90 | M93: =IF(G93="Obs",COUNTIF(G$2:G93,"Obs"),"") | N93: =IF(G93="No",COUNTIF(G$2:G93,"No"),"") -> 7
A94: CI-2026004 | B94: CI | C94: CI-Q12 | D94: Credit & Collateral Documentation / Lien Perfection | E94: All required credit documents are present, current, and properly executed. | F94: High | G94: Yes | I94: 46149 | J94: D. Whitaker | K94: =IF(G94="No",MAX(0,AsOfDate-I94),"") | L94: =IF(K94="","",IF(K94<=90,"0-90",IF(K94<=180,"91-180",IF(K94<=270,"181-270",">270")))) | M94: =IF(G94="Obs",COUNTIF(G$2:G94,"Obs"),"") | N94: =IF(G94="No",COUNTIF(G$2:G94,"No"),"")
A95: CI-2026004 | B95: CI | C95: CI-Q13 | D95: Credit & Collateral Documentation / Lien Perfection | E95: Lien positions are perfected and verified (searches, filings, titles). | F95: High | G95: No | H95: Projection growth assumption unsupported versus 3-year actuals. | I95: 46149 | J95: D. Whitaker | K95: =IF(G95="No",MAX(0,AsOfDate-I95),"") -> 34 | L95: =IF(K95="","",IF(K95<=90,"0-90",IF(K95<=180,"91-180",IF(K95<=270,"181-270",">270")))) -> 0-90 | M95: =IF(G95="Obs",COUNTIF(G$2:G95,"Obs"),"") | N95: =IF(G95="No",COUNTIF(G$2:G95,"No"),"") -> 8
A96: CI-2026004 | B96: CI | C96: CI-Q14 | D96: Credit & Collateral Documentation / Lien Perfection | E96: Insurance requirements are met and the bank is loss payee where required. | F96: Low | G96: Yes | I96: 46149 | J96: D. Whitaker | K96: =IF(G96="No",MAX(0,AsOfDate-I96),"") | L96: =IF(K96="","",IF(K96<=90,"0-90",IF(K96<=180,"91-180",IF(K96<=270,"181-270",">270")))) | M96: =IF(G96="Obs",COUNTIF(G$2:G96,"Obs"),"") | N96: =IF(G96="No",COUNTIF(G$2:G96,"No"),"")
A97: CI-2026004 | B97: CI | C97: CI-Q15 | D97: Approval Authority | E97: Credit was approved within delegated authority of the approving officer(s). | F97: High | G97: Yes | I97: 46149 | J97: D. Whitaker | K97: =IF(G97="No",MAX(0,AsOfDate-I97),"") | L97: =IF(K97="","",IF(K97<=90,"0-90",IF(K97<=180,"91-180",IF(K97<=270,"181-270",">270")))) | M97: =IF(G97="Obs",COUNTIF(G$2:G97,"Obs"),"") | N97: =IF(G97="No",COUNTIF(G$2:G97,"No"),"")
A98: CI-2026004 | B98: CI | C98: CI-Q16 | D98: Approval Authority | E98: Policy exceptions at approval were identified, justified, and approved at proper level. | F98: Medium | G98: N/A | I98: 46149 | J98: D. Whitaker | K98: =IF(G98="No",MAX(0,AsOfDate-I98),"") | L98: =IF(K98="","",IF(K98<=90,"0-90",IF(K98<=180,"91-180",IF(K98<=270,"181-270",">270")))) | M98: =IF(G98="Obs",COUNTIF(G$2:G98,"Obs"),"") | N98: =IF(G98="No",COUNTIF(G$2:G98,"No"),"")
A99: CI-2026004 | B99: CI | C99: CI-Q17 | D99: Covenant Adherence | E99: Covenant compliance is tested at required frequency with evidence retained. | F99: Medium | G99: Yes | I99: 46149 | J99: D. Whitaker | K99: =IF(G99="No",MAX(0,AsOfDate-I99),"") | L99: =IF(K99="","",IF(K99<=90,"0-90",IF(K99<=180,"91-180",IF(K99<=270,"181-270",">270")))) | M99: =IF(G99="Obs",COUNTIF(G$2:G99,"Obs"),"") | N99: =IF(G99="No",COUNTIF(G$2:G99,"No"),"")
A100: CI-2026004 | B100: CI | C100: CI-Q18 | D100: Covenant Adherence | E100: Covenant breaches (if any) were identified, reported, and waived/cured per policy. | F100: High | G100: Yes | I100: 46149 | J100: D. Whitaker | K100: =IF(G100="No",MAX(0,AsOfDate-I100),"") | L100: =IF(K100="","",IF(K100<=90,"0-90",IF(K100<=180,"91-180",IF(K100<=270,"181-270",">270")))) | M100: =IF(G100="Obs",COUNTIF(G$2:G100,"Obs"),"") | N100: =IF(G100="No",COUNTIF(G$2:G100,"No"),"")
A101: CI-2026004 | B101: CI | C101: CI-Q19 | D101: Policy Compliance | E101: Credit complies with internal lending policy limits (hold limits, tenor, pricing floors). | F101: Medium | G101: Obs | H101: Borrowing-base certificate delivered by email rather than portal per agreement. | I101: 46149 | J101: D. Whitaker | K101: =IF(G101="No",MAX(0,AsOfDate-I101),"") | L101: =IF(K101="","",IF(K101<=90,"0-90",IF(K101<=180,"91-180",IF(K101<=270,"181-270",">270")))) | M101: =IF(G101="Obs",COUNTIF(G$2:G101,"Obs"),"") -> 2 | N101: =IF(G101="No",COUNTIF(G$2:G101,"No"),"")
A102: CI-2026004 | B102: CI | C102: CI-Q20 | D102: Policy Compliance | E102: Required periodic monitoring (annual review, site visits) is current. | F102: Medium | G102: Yes | I102: 46149 | J102: D. Whitaker | K102: =IF(G102="No",MAX(0,AsOfDate-I102),"") | L102: =IF(K102="","",IF(K102<=90,"0-90",IF(K102<=180,"91-180",IF(K102<=270,"181-270",">270")))) | M102: =IF(G102="Obs",COUNTIF(G$2:G102,"Obs"),"") | N102: =IF(G102="No",COUNTIF(G$2:G102,"No"),"")
A103: CI-2026004 | B103: CI | C103: CI-Q21 | D103: Five Cs of Credit | E103: Character: management track record, credit history, and integrity assessed. | F103: Medium | G103: Yes | I103: 46149 | J103: D. Whitaker | K103: =IF(G103="No",MAX(0,AsOfDate-I103),"") | L103: =IF(K103="","",IF(K103<=90,"0-90",IF(K103<=180,"91-180",IF(K103<=270,"181-270",">270")))) | M103: =IF(G103="Obs",COUNTIF(G$2:G103,"Obs"),"") | N103: =IF(G103="No",COUNTIF(G$2:G103,"No"),"")
A104: CI-2026004 | B104: CI | C104: CI-Q22 | D104: Five Cs of Credit | E104: Capacity: cash-flow capacity analysis covers debt service under stress. | F104: High | G104: Yes | I104: 46149 | J104: D. Whitaker | K104: =IF(G104="No",MAX(0,AsOfDate-I104),"") | L104: =IF(K104="","",IF(K104<=90,"0-90",IF(K104<=180,"91-180",IF(K104<=270,"181-270",">270")))) | M104: =IF(G104="Obs",COUNTIF(G$2:G104,"Obs"),"") | N104: =IF(G104="No",COUNTIF(G$2:G104,"No"),"")
A105: CI-2026004 | B105: CI | C105: CI-Q23 | D105: Five Cs of Credit | E105: Capital: borrower equity/tangible net worth is adequate for the risk. | F105: Medium | G105: Yes | I105: 46149 | J105: D. Whitaker | K105: =IF(G105="No",MAX(0,AsOfDate-I105),"") | L105: =IF(K105="","",IF(K105<=90,"0-90",IF(K105<=180,"91-180",IF(K105<=270,"181-270",">270")))) | M105: =IF(G105="Obs",COUNTIF(G$2:G105,"Obs"),"") | N105: =IF(G105="No",COUNTIF(G$2:G105,"No"),"")
A106: CI-2026004 | B106: CI | C106: CI-Q24 | D106: Five Cs of Credit | E106: Collateral: valuation basis is current and discounts are appropriate. | F106: Medium | G106: Yes | I106: 46149 | J106: D. Whitaker | K106: =IF(G106="No",MAX(0,AsOfDate-I106),"") | L106: =IF(K106="","",IF(K106<=90,"0-90",IF(K106<=180,"91-180",IF(K106<=270,"181-270",">270")))) | M106: =IF(G106="Obs",COUNTIF(G$2:G106,"Obs"),"") | N106: =IF(G106="No",COUNTIF(G$2:G106,"No"),"")
A107: CI-2026004 | B107: CI | C107: CI-Q25 | D107: Five Cs of Credit | E107: Conditions: industry, market, and macro conditions are evaluated. | F107: Low | G107: Yes | I107: 46149 | J107: D. Whitaker | K107: =IF(G107="No",MAX(0,AsOfDate-I107),"") | L107: =IF(K107="","",IF(K107<=90,"0-90",IF(K107<=180,"91-180",IF(K107<=270,"181-270",">270")))) | M107: =IF(G107="Obs",COUNTIF(G$2:G107,"Obs"),"") | N107: =IF(G107="No",COUNTIF(G$2:G107,"No"),"")
A108: CI-2026004 | B108: CI | C108: CI-Q26 | D108: Global Cash Flow | E108: Global cash flow combines business and guarantor sources with consistent treatment of taxes/living expenses. | F108: High | G108: Yes | I108: 46149 | J108: D. Whitaker | K108: =IF(G108="No",MAX(0,AsOfDate-I108),"") | L108: =IF(K108="","",IF(K108<=90,"0-90",IF(K108<=180,"91-180",IF(K108<=270,"181-270",">270")))) | M108: =IF(G108="Obs",COUNTIF(G$2:G108,"Obs"),"") | N108: =IF(G108="No",COUNTIF(G$2:G108,"No"),"")
A109: CI-2026004 | B109: CI | C109: CI-Q27 | D109: Global Cash Flow | E109: Inter-company / related-entity flows are identified and not double-counted. | F109: Medium | G109: Yes | I109: 46149 | J109: D. Whitaker | K109: =IF(G109="No",MAX(0,AsOfDate-I109),"") | L109: =IF(K109="","",IF(K109<=90,"0-90",IF(K109<=180,"91-180",IF(K109<=270,"181-270",">270")))) | M109: =IF(G109="Obs",COUNTIF(G$2:G109,"Obs"),"") | N109: =IF(G109="No",COUNTIF(G$2:G109,"No"),"")
A110: CRE-2026001 | B110: CRE | C110: CRE-Q01 | D110: Credit Quality & Risk-Grade Accuracy | E110: LOB-assigned risk grade is supported by current financial analysis. | F110: High | G110: Yes | I110: 45883 | J110: A. Chen | K110: =IF(G110="No",MAX(0,AsOfDate-I110),"") | L110: =IF(K110="","",IF(K110<=90,"0-90",IF(K110<=180,"91-180",IF(K110<=270,"181-270",">270")))) | M110: =IF(G110="Obs",COUNTIF(G$2:G110,"Obs"),"") | N110: =IF(G110="No",COUNTIF(G$2:G110,"No"),"")
A111: CRE-2026001 | B111: CRE | C111: CRE-Q02 | D111: Credit Quality & Risk-Grade Accuracy | E111: Grade reflects all material credit weaknesses identified in the file. | F111: High | G111: Yes | I111: 45883 | J111: A. Chen | K111: =IF(G111="No",MAX(0,AsOfDate-I111),"") | L111: =IF(K111="","",IF(K111<=90,"0-90",IF(K111<=180,"91-180",IF(K111<=270,"181-270",">270")))) | M111: =IF(G111="Obs",COUNTIF(G$2:G111,"Obs"),"") | N111: =IF(G111="No",COUNTIF(G$2:G111,"No"),"")
A112: CRE-2026001 | B112: CRE | C112: CRE-Q03 | D112: Credit Quality & Risk-Grade Accuracy | E112: Grade was reviewed/affirmed within policy frequency requirements. | F112: Medium | G112: Yes | I112: 45883 | J112: A. Chen | K112: =IF(G112="No",MAX(0,AsOfDate-I112),"") | L112: =IF(K112="","",IF(K112<=90,"0-90",IF(K112<=180,"91-180",IF(K112<=270,"181-270",">270")))) | M112: =IF(G112="Obs",COUNTIF(G$2:G112,"Obs"),"") | N112: =IF(G112="No",COUNTIF(G$2:G112,"No"),"")
A113: CRE-2026001 | B113: CRE | C113: CRE-Q04 | D113: Underwriting Soundness | E113: Underwriting at origination conformed to policy standards in effect. | F113: High | G113: Yes | I113: 45883 | J113: A. Chen | K113: =IF(G113="No",MAX(0,AsOfDate-I113),"") | L113: =IF(K113="","",IF(K113<=90,"0-90",IF(K113<=180,"91-180",IF(K113<=270,"181-270",">270")))) | M113: =IF(G113="Obs",COUNTIF(G$2:G113,"Obs"),"") | N113: =IF(G113="No",COUNTIF(G$2:G113,"No"),"")
... A118: CRE-2026001 | B118: CRE | C118: CRE-Q09 | D118: Repayment Sources & Projections | E118: Projection assumptions are reasonable versus historical performance and market data. | F118: High | G118: N/A | I118: 45883 | J118: A. Chen | K118: =IF(G118="No",MAX(0,AsOfDate-I118),"") | L118: =IF(K118="","",IF(K118<=90,"0-90",IF(K118<=180,"91-180",IF(K118<=270,"181-270",">270")))) | M118: =IF(G118="Obs",COUNTIF(G$2:G118,"Obs"),"") | N118: =IF(G118="No",COUNTIF(G$2:G118,"No"),"")
A119: CRE-2026001 | B119: CRE | C119: CRE-Q10 | D119: Guarantor / Sponsor Creditworthiness | E119: Guarantor/sponsor financial condition is current, analyzed, and supports reliance. | F119: Medium | G119: Obs | H119: Spread mislabels FY2024 column as FY2025; values correct. | I119: 45883 | J119: A. Chen | K119: =IF(G119="No",MAX(0,AsOfDate-I119),"") | L119: =IF(K119="","",IF(K119<=90,"0-90",IF(K119<=180,"91-180",IF(K119<=270,"181-270",">270")))) | M119: =IF(G119="Obs",COUNTIF(G$2:G119,"Obs"),"") -> 3 | N119: =IF(G119="No",COUNTIF(G$2:G119,"No"),"")
...

Sheet Dash_Portfolio
B1: Portfolio Overview Dashboard
B2: Recalculates from the Database; grade scale 1-8 (5 = Special Mention, 6+ = Classified).
B4: CREDITS REVIEWED | C4: COMPLETE | D4: GRADE CHANGES | E4: CONCURRENCE RATE | F4: CRITICIZED (CRR ≥ 5)
B5: =COUNTA(Database!$A$2:$A$29) -> 28 | C5: =COUNTIF(Database!$W:$W,"Complete") -> 21 | D5: =COUNTIF(Database!$L:$L,"Grade Change") -> 7 | E5: =IF(COUNTA(Database!$A$2:$A$29)=0,"",1-COUNTIF(Database!$L:$L,"Grade Change")/COUNTA(Database!$A$2:$A$29)) -> 0.75 | F5: =COUNTIF(Database!$J:$J,">=5") -> 12
B7: Reviews by Segment
B8: Segment | C8: Reviews | D8: Exceptions | E8: Downgrades
B9: C&I / Commercial | C9: =COUNTIF(Database!$C:$C,B9) -> 4 | D9: =SUMIFS(Database!$P:$P,Database!$C:$C,B9) -> 8 | E9: =COUNTIFS(Database!$C:$C,B9,Database!$L:$L,"Grade Change") -> 0
B10: Commercial Real Estate | C10: =COUNTIF(Database!$C:$C,B10) -> 4 | D10: =SUMIFS(Database!$P:$P,Database!$C:$C,B10) -> 8 | E10: =COUNTIFS(Database!$C:$C,B10,Database!$L:$L,"Grade Change") -> 1
B11: Leveraged Lending | C11: =COUNTIF(Database!$C:$C,B11) -> 4 | D11: =SUMIFS(Database!$P:$P,Database!$C:$C,B11) -> 10 | E11: =COUNTIFS(Database!$C:$C,B11,Database!$L:$L,"Grade Change") -> 2
B12: Asset-Based Lending | C12: =COUNTIF(Database!$C:$C,B12) -> 4 | D12: =SUMIFS(Database!$P:$P,Database!$C:$C,B12) -> 6 | E12: =COUNTIFS(Database!$C:$C,B12,Database!$L:$L,"Grade Change") -> 1
B13: ARG / Workout | C13: =COUNTIF(Database!$C:$C,B13) -> 4 | D13: =SUMIFS(Database!$P:$P,Database!$C:$C,B13) -> 9 | E13: =COUNTIFS(Database!$C:$C,B13,Database!$L:$L,"Grade Change") -> 1
B14: Internal Audit (Generic) | C14: =COUNTIF(Database!$C:$C,B14) -> 4 | D14: =SUMIFS(Database!$P:$P,Database!$C:$C,B14) -> 4 | E14: =COUNTIFS(Database!$C:$C,B14,Database!$L:$L,"Grade Change") -> 1
B15: General Compliance Crosswalk | C15: =COUNTIF(Database!$C:$C,B15) -> 4 | D15: =SUMIFS(Database!$P:$P,Database!$C:$C,B15) -> 1 | E15: =COUNTIFS(Database!$C:$C,B15,Database!$L:$L,"Grade Change") -> 1
B18: Grade Distribution (LOB vs CRR)
B19: Grade | C19: LOB Assigned | D19: CRR Concluded
B20: 1 | C20: =COUNTIF(Database!$I:$I,B20) -> 0 | D20: =COUNTIF(Database!$J:$J,B20) -> 0
B21: 2 | C21: =COUNTIF(Database!$I:$I,B21) -> 4 | D21: =COUNTIF(Database!$J:$J,B21) -> 4
B22: 3 | C22: =COUNTIF(Database!$I:$I,B22) -> 6 | D22: =COUNTIF(Database!$J:$J,B22) -> 5
B23: 4 | C23: =COUNTIF(Database!$I:$I,B23) -> 11 | D23: =COUNTIF(Database!$J:$J,B23) -> 7
B24: 5 | C24: =COUNTIF(Database!$I:$I,B24) -> 5 | D24: =COUNTIF(Database!$J:$J,B24) -> 9
B25: 6 | C25: =COUNTIF(Database!$I:$I,B25) -> 1 | D25: =COUNTIF(Database!$J:$J,B25) -> 2
B26: 7 | C26: =COUNTIF(Database!$I:$I,B26) -> 1 | D26: =COUNTIF(Database!$J:$J,B26) -> 1
B27: 8 | C27: =COUNTIF(Database!$I:$I,B27) -> 0 | D27: =COUNTIF(Database!$J:$J,B27) -> 0
B30: Migration Matrix — LOB Assigned (rows) vs CRR Concluded (columns)
B31: LOB \ CRR | C31: 1 | D31: 2 | E31: 3 | F31: 4 | G31: 5 | H31: 6 | I31: 7 | J31: 8
B32: 1 | C32: =IF(COUNTIFS(Database!$I:$I,$B32,Database!$J:$J,1)=0,"",COUNTIFS(Database!$I:$I,$B32,Database!$J:$J,1)) | D32: =IF(COUNTIFS(Database!$I:$I,$B32,Database!$J:$J,2)=0,"",COUNTIFS(Database!$I:$I,$B32,Database!$J:$J,2)) | E32: =IF(COUNTIFS(Database!$I:$I,$B32,Database!$J:$J,3)=0,"",COUNTIFS(Database!$I:$I,$B32,Database!$J:$J,3)) | F32: =IF(COUNTIFS(Database!$I:$I,$B32,Database!$J:$J,4)=0,"",COUNTIFS(Database!$I:$I,$B32,Database!$J:$J,4)) | G32: =IF(COUNTIFS(Database!$I:$I,$B32,Database!$J:$J,5)=0,"",COUNTIFS(Database!$I:$I,$B32,Database!$J:$J,5)) | H32: =IF(COUNTIFS(Database!$I:$I,$B32,Database!$J:$J,6)=0,"",COUNTIFS(Database!$I:$I,$B32,Database!$J:$J,6)) | I32: =IF(COUNTIFS(Database!$I:$I,$B32,Database!$J:$J,7)=0,"",COUNTIFS(Database!$I:$I,$B32,Database!$J:$J,7)) | J32: =IF(COUNTIFS(Database!$I:$I,$B32,Database!$J:$J,8)=0,"",COUNTIFS(Database!$I:$I,$B32,Database!$J:$J,8))
B33: 2 | C33: =IF(COUNTIFS(Database!$I:$I,$B33,Database!$J:$J,1)=0,"",COUNTIFS(Database!$I:$I,$B33,Database!$J:$J,1)) | D33: =IF(COUNTIFS(Database!$I:$I,$B33,Database!$J:$J,2)=0,"",COUNTIFS(Database!$I:$I,$B33,Database!$J:$J,2)) -> 4 | E33: =IF(COUNTIFS(Database!$I:$I,$B33,Database!$J:$J,3)=0,"",COUNTIFS(Database!$I:$I,$B33,Database!$J:$J,3)) | F33: =IF(COUNTIFS(Database!$I:$I,$B33,Database!$J:$J,4)=0,"",COUNTIFS(Database!$I:$I,$B33,Database!$J:$J,4)) | G33: =IF(COUNTIFS(Database!$I:$I,$B33,Database!$J:$J,5)=0,"",COUNTIFS(Database!$I:$I,$B33,Database!$J:$J,5)) | H33: =IF(COUNTIFS(Database!$I:$I,$B33,Database!$J:$J,6)=0,"",COUNTIFS(Database!$I:$I,$B33,Database!$J:$J,6)) | I33: =IF(COUNTIFS(Database!$I:$I,$B33,Database!$J:$J,7)=0,"",COUNTIFS(Database!$I:$I,$B33,Database!$J:$J,7)) | J33: =IF(COUNTIFS(Database!$I:$I,$B33,Database!$J:$J,8)=0,"",COUNTIFS(Database!$I:$I,$B33,Database!$J:$J,8))
B34: 3 | C34: =IF(COUNTIFS(Database!$I:$I,$B34,Database!$J:$J,1)=0,"",COUNTIFS(Database!$I:$I,$B34,Database!$J:$J,1)) | D34: =IF(COUNTIFS(Database!$I:$I,$B34,Database!$J:$J,2)=0,"",COUNTIFS(Database!$I:$I,$B34,Database!$J:$J,2)) | E34: =IF(COUNTIFS(Database!$I:$I,$B34,Database!$J:$J,3)=0,"",COUNTIFS(Database!$I:$I,$B34,Database!$J:$J,3)) -> 5 | F34: =IF(COUNTIFS(Database!$I:$I,$B34,Database!$J:$J,4)=0,"",COUNTIFS(Database!$I:$I,$B34,Database!$J:$J,4)) -> 1 | G34: =IF(COUNTIFS(Database!$I:$I,$B34,Database!$J:$J,5)=0,"",COUNTIFS(Database!$I:$I,$B34,Database!$J:$J,5)) | H34: =IF(COUNTIFS(Database!$I:$I,$B34,Database!$J:$J,6)=0,"",COUNTIFS(Database!$I:$I,$B34,Database!$J:$J,6)) | I34: =IF(COUNTIFS(Database!$I:$I,$B34,Database!$J:$J,7)=0,"",COUNTIFS(Database!$I:$I,$B34,Database!$J:$J,7)) | J34: =IF(COUNTIFS(Database!$I:$I,$B34,Database!$J:$J,8)=0,"",COUNTIFS(Database!$I:$I,$B34,Database!$J:$J,8))
B35: 4 | C35: =IF(COUNTIFS(Database!$I:$I,$B35,Database!$J:$J,1)=0,"",COUNTIFS(Database!$I:$I,$B35,Database!$J:$J,1)) | D35: =IF(COUNTIFS(Database!$I:$I,$B35,Database!$J:$J,2)=0,"",COUNTIFS(Database!$I:$I,$B35,Database!$J:$J,2)) | E35: =IF(COUNTIFS(Database!$I:$I,$B35,Database!$J:$J,3)=0,"",COUNTIFS(Database!$I:$I,$B35,Database!$J:$J,3)) | F35: =IF(COUNTIFS(Database!$I:$I,$B35,Database!$J:$J,4)=0,"",COUNTIFS(Database!$I:$I,$B35,Database!$J:$J,4)) -> 6 | G35: =IF(COUNTIFS(Database!$I:$I,$B35,Database!$J:$J,5)=0,"",COUNTIFS(Database!$I:$I,$B35,Database!$J:$J,5)) -> 5 | H35: =IF(COUNTIFS(Database!$I:$I,$B35,Database!$J:$J,6)=0,"",COUNTIFS(Database!$I:$I,$B35,Database!$J:$J,6)) | I35: =IF(COUNTIFS(Database!$I:$I,$B35,Database!$J:$J,7)=0,"",COUNTIFS(Database!$I:$I,$B35,Database!$J:$J,7)) | J35: =IF(COUNTIFS(Database!$I:$I,$B35,Database!$J:$J,8)=0,"",COUNTIFS(Database!$I:$I,$B35,Database!$J:$J,8))
B36: 5 | C36: =IF(COUNTIFS(Database!$I:$I,$B36,Database!$J:$J,1)=0,"",COUNTIFS(Database!$I:$I,$B36,Database!$J:$J,1)) | D36: =IF(COUNTIFS(Database!$I:$I,$B36,Database!$J:$J,2)=0,"",COUNTIFS(Database!$I:$I,$B36,Database!$J:$J,2)) | E36: =IF(COUNTIFS(Database!$I:$I,$B36,Database!$J:$J,3)=0,"",COUNTIFS(Database!$I:$I,$B36,Database!$J:$J,3)) | F36: =IF(COUNTIFS(Database!$I:$I,$B36,Database!$J:$J,4)=0,"",COUNTIFS(Database!$I:$I,$B36,Database!$J:$J,4)) | G36: =IF(COUNTIFS(Database!$I:$I,$B36,Database!$J:$J,5)=0,"",COUNTIFS(Database!$I:$I,$B36,Database!$J:$J,5)) -> 4 | H36: =IF(COUNTIFS(Database!$I:$I,$B36,Database!$J:$J,6)=0,"",COUNTIFS(Database!$I:$I,$B36,Database!$J:$J,6)) -> 1 | I36: =IF(COUNTIFS(Database!$I:$I,$B36,Database!$J:$J,7)=0,"",COUNTIFS(Database!$I:$I,$B36,Database!$J:$J,7)) | J36: =IF(COUNTIFS(Database!$I:$I,$B36,Database!$J:$J,8)=0,"",COUNTIFS(Database!$I:$I,$B36,Database!$J:$J,8))
B37: 6 | C37: =IF(COUNTIFS(Database!$I:$I,$B37,Database!$J:$J,1)=0,"",COUNTIFS(Database!$I:$I,$B37,Database!$J:$J,1)) | D37: =IF(COUNTIFS(Database!$I:$I,$B37,Database!$J:$J,2)=0,"",COUNTIFS(Database!$I:$I,$B37,Database!$J:$J,2)) | E37: =IF(COUNTIFS(Database!$I:$I,$B37,Database!$J:$J,3)=0,"",COUNTIFS(Database!$I:$I,$B37,Database!$J:$J,3)) | F37: =IF(COUNTIFS(Database!$I:$I,$B37,Database!$J:$J,4)=0,"",COUNTIFS(Database!$I:$I,$B37,Database!$J:$J,4)) | G37: =IF(COUNTIFS(Database!$I:$I,$B37,Database!$J:$J,5)=0,"",COUNTIFS(Database!$I:$I,$B37,Database!$J:$J,5)) | H37: =IF(COUNTIFS(Database!$I:$I,$B37,Database!$J:$J,6)=0,"",COUNTIFS(Database!$I:$I,$B37,Database!$J:$J,6)) -> 1 | I37: =IF(COUNTIFS(Database!$I:$I,$B37,Database!$J:$J,7)=0,"",COUNTIFS(Database!$I:$I,$B37,Database!$J:$J,7)) | J37: =IF(COUNTIFS(Database!$I:$I,$B37,Database!$J:$J,8)=0,"",COUNTIFS(Database!$I:$I,$B37,Database!$J:$J,8))
B38: 7 | C38: =IF(COUNTIFS(Database!$I:$I,$B38,Database!$J:$J,1)=0,"",COUNTIFS(Database!$I:$I,$B38,Database!$J:$J,1)) | D38: =IF(COUNTIFS(Database!$I:$I,$B38,Database!$J:$J,2)=0,"",COUNTIFS(Database!$I:$I,$B38,Database!$J:$J,2)) | E38: =IF(COUNTIFS(Database!$I:$I,$B38,Database!$J:$J,3)=0,"",COUNTIFS(Database!$I:$I,$B38,Database!$J:$J,3)) | F38: =IF(COUNTIFS(Database!$I:$I,$B38,Database!$J:$J,4)=0,"",COUNTIFS(Database!$I:$I,$B38,Database!$J:$J,4)) | G38: =IF(COUNTIFS(Database!$I:$I,$B38,Database!$J:$J,5)=0,"",COUNTIFS(Database!$I:$I,$B38,Database!$J:$J,5)) | H38: =IF(COUNTIFS(Database!$I:$I,$B38,Database!$J:$J,6)=0,"",COUNTIFS(Database!$I:$I,$B38,Database!$J:$J,6)) | I38: =IF(COUNTIFS(Database!$I:$I,$B38,Database!$J:$J,7)=0,"",COUNTIFS(Database!$I:$I,$B38,Database!$J:$J,7)) -> 1 | J38: =IF(COUNTIFS(Database!$I:$I,$B38,Database!$J:$J,8)=0,"",COUNTIFS(Database!$I:$I,$B38,Database!$J:$J,8))
B39: 8 | C39: =IF(COUNTIFS(Database!$I:$I,$B39,Database!$J:$J,1)=0,"",COUNTIFS(Database!$I:$I,$B39,Database!$J:$J,1)) | D39: =IF(COUNTIFS(Database!$I:$I,$B39,Database!$J:$J,2)=0,"",COUNTIFS(Database!$I:$I,$B39,Database!$J:$J,2)) | E39: =IF(COUNTIFS(Database!$I:$I,$B39,Database!$J:$J,3)=0,"",COUNTIFS(Database!$I:$I,$B39,Database!$J:$J,3)) | F39: =IF(COUNTIFS(Database!$I:$I,$B39,Database!$J:$J,4)=0,"",COUNTIFS(Database!$I:$I,$B39,Database!$J:$J,4)) | G39: =IF(COUNTIFS(Database!$I:$I,$B39,Database!$J:$J,5)=0,"",COUNTIFS(Database!$I:$I,$B39,Database!$J:$J,5)) | H39: =IF(COUNTIFS(Database!$I:$I,$B39,Database!$J:$J,6)=0,"",COUNTIFS(Database!$I:$I,$B39,Database!$J:$J,6)) | I39: =IF(COUNTIFS(Database!$I:$I,$B39,Database!$J:$J,7)=0,"",COUNTIFS(Database!$I:$I,$B39,Database!$J:$J,7)) | J39: =IF(COUNTIFS(Database!$I:$I,$B39,Database!$J:$J,8)=0,"",COUNTIFS(Database!$I:$I,$B39,Database!$J:$J,8))
B41: Shaded cells right of the diagonal = CRR downgrades vs the LOB grade.

Sheet Dash_Exceptions
B1: Exceptions / Findings Dashboard
B2: Counts ONLY 'No' answers. Obs is never an exception; N/A is excluded from every rate.
B4: TOTAL EXCEPTIONS | C4: HIGH SEVERITY | D4: AGED > 180 DAYS | E4: NOTES MISSING
B5: =COUNTIF(Responses!$G:$G,"No") -> 46 | C5: =COUNTIFS(Responses!$G:$G,"No",Responses!$F:$F,"High") -> 25 | D5: =COUNTIFS(Responses!$G:$G,"No",Responses!$K:$K,">180") -> 18 | E5: =COUNTIFS(Responses!$G:$G,"No",Responses!$H:$H,"")+COUNTIFS(Responses!$G:$G,"Obs",Responses!$H:$H,"") -> 0
B7: Exceptions by Segment
B8: Segment | C8: Exceptions | D8: Rate (excl. N/A)
B9: CI | C9: =COUNTIFS(Responses!$B:$B,$B9,Responses!$G:$G,"No") -> 8 | D9: =IF(COUNTIFS(Responses!$B:$B,$B9,Responses!$G:$G,"Yes")+COUNTIFS(Responses!$B:$B,$B9,Responses!$G:$G,"No")+COUNTIFS(Responses!$B:$B,$B9,Responses!$G:$G,"Obs")=0,"",COUNTIFS(Responses!$B:$B,$B9,Responses!$G:$G,"No")/(COUNTIFS(Responses!$B:$B,$B9,Responses!$G:$G,"Yes")+COUNTIFS(Responses!$B:$B,$B9,Responses!$G:$G,"No")+COUNTIFS(Responses!$B:$B,$B9,Responses!$G:$G,"Obs"))) -> 0.081632653
B10: CRE | C10: =COUNTIFS(Responses!$B:$B,$B10,Responses!$G:$G,"No") -> 8 | D10: =IF(COUNTIFS(Responses!$B:$B,$B10,Responses!$G:$G,"Yes")+COUNTIFS(Responses!$B:$B,$B10,Responses!$G:$G,"No")+COUNTIFS(Responses!$B:$B,$B10,Responses!$G:$G,"Obs")=0,"",COUNTIFS(Responses!$B:$B,$B10,Responses!$G:$G,"No")/(COUNTIFS(Responses!$B:$B,$B10,Responses!$G:$G,"Yes")+COUNTIFS(Responses!$B:$B,$B10,Responses!$G:$G,"No")+COUNTIFS(Responses!$B:$B,$B10,Responses!$G:$G,"Obs"))) -> 0.082474227
B11: LL | C11: =COUNTIFS(Responses!$B:$B,$B11,Responses!$G:$G,"No") -> 10 | D11: =IF(COUNTIFS(Responses!$B:$B,$B11,Responses!$G:$G,"Yes")+COUNTIFS(Responses!$B:$B,$B11,Responses!$G:$G,"No")+COUNTIFS(Responses!$B:$B,$B11,Responses!$G:$G,"Obs")=0,"",COUNTIFS(Responses!$B:$B,$B11,Responses!$G:$G,"No")/(COUNTIFS(Responses!$B:$B,$B11,Responses!$G:$G,"Yes")+COUNTIFS(Responses!$B:$B,$B11,Responses!$G:$G,"No")+COUNTIFS(Responses!$B:$B,$B11,Responses!$G:$G,"Obs"))) -> 0.10204082
B12: ABL | C12: =COUNTIFS(Responses!$B:$B,$B12,Responses!$G:$G,"No") -> 6 | D12: =IF(COUNTIFS(Responses!$B:$B,$B12,Responses!$G:$G,"Yes")+COUNTIFS(Responses!$B:$B,$B12,Responses!$G:$G,"No")+COUNTIFS(Responses!$B:$B,$B12,Responses!$G:$G,"Obs")=0,"",COUNTIFS(Responses!$B:$B,$B12,Responses!$G:$G,"No")/(COUNTIFS(Responses!$B:$B,$B12,Responses!$G:$G,"Yes")+COUNTIFS(Responses!$B:$B,$B12,Responses!$G:$G,"No")+COUNTIFS(Responses!$B:$B,$B12,Responses!$G:$G,"Obs"))) -> 0.063829787
B13: ARG | C13: =COUNTIFS(Responses!$B:$B,$B13,Responses!$G:$G,"No") -> 9 | D13: =IF(COUNTIFS(Responses!$B:$B,$B13,Responses!$G:$G,"Yes")+COUNTIFS(Responses!$B:$B,$B13,Responses!$G:$G,"No")+COUNTIFS(Responses!$B:$B,$B13,Responses!$G:$G,"Obs")=0,"",COUNTIFS(Responses!$B:$B,$B13,Responses!$G:$G,"No")/(COUNTIFS(Responses!$B:$B,$B13,Responses!$G:$G,"Yes")+COUNTIFS(Responses!$B:$B,$B13,Responses!$G:$G,"No")+COUNTIFS(Responses!$B:$B,$B13,Responses!$G:$G,"Obs"))) -> 0.086538462
B14: IA | C14: =COUNTIFS(Responses!$B:$B,$B14,Responses!$G:$G,"No") -> 4 | D14: =IF(COUNTIFS(Responses!$B:$B,$B14,Responses!$G:$G,"Yes")+COUNTIFS(Responses!$B:$B,$B14,Responses!$G:$G,"No")+COUNTIFS(Responses!$B:$B,$B14,Responses!$G:$G,"Obs")=0,"",COUNTIFS(Responses!$B:$B,$B14,Responses!$G:$G,"No")/(COUNTIFS(Responses!$B:$B,$B14,Responses!$G:$G,"Yes")+COUNTIFS(Responses!$B:$B,$B14,Responses!$G:$G,"No")+COUNTIFS(Responses!$B:$B,$B14,Responses!$G:$G,"Obs"))) -> 0.057971014
B15: COMP | C15: =COUNTIFS(Responses!$B:$B,$B15,Responses!$G:$G,"No") -> 1 | D15: =IF(COUNTIFS(Responses!$B:$B,$B15,Responses!$G:$G,"Yes")+COUNTIFS(Responses!$B:$B,$B15,Responses!$G:$G,"No")+COUNTIFS(Responses!$B:$B,$B15,Responses!$G:$G,"Obs")=0,"",COUNTIFS(Responses!$B:$B,$B15,Responses!$G:$G,"No")/(COUNTIFS(Responses!$B:$B,$B15,Responses!$G:$G,"Yes")+COUNTIFS(Responses!$B:$B,$B15,Responses!$G:$G,"No")+COUNTIFS(Responses!$B:$B,$B15,Responses!$G:$G,"Obs"))) -> 0.010204082
B18: Exceptions by Severity
B19: Severity | C19: Count
B20: High | C20: =COUNTIFS(Responses!$G:$G,"No",Responses!$F:$F,B20) -> 25
B21: Medium | C21: =COUNTIFS(Responses!$G:$G,"No",Responses!$F:$F,B21) -> 16
B22: Low | C22: =COUNTIFS(Responses!$G:$G,"No",Responses!$F:$F,B22) -> 5
B25: Exception Aging (days since review)
B26: Bucket | C26: Count
B27: 0-90 | C27: =COUNTIFS(Responses!$G:$G,"No",Responses!$L:$L,B27) -> 14
B28: 91-180 | C28: =COUNTIFS(Responses!$G:$G,"No",Responses!$L:$L,B28) -> 14
B29: 181-270 | C29: =COUNTIFS(Responses!$G:$G,"No",Responses!$L:$L,B29) -> 10
B30: >270 | C30: =COUNTIFS(Responses!$G:$G,"No",Responses!$L:$L,B30) -> 0
B33: Exception Detail (first 30)
G34: # | H34: Credit | I34: Seg | J34: QID | K34: Severity | L34: Question | M34: Finding Rationale | N34: Days Open
G35: 1 | H35: =IFERROR(INDEX(Responses!$A:$A,MATCH($G35,Responses!$N:$N,0)),"") -> CI-2026001 | I35: =IFERROR(INDEX(Responses!$B:$B,MATCH($G35,Responses!$N:$N,0)),"") -> CI | J35: =IFERROR(INDEX(Responses!$C:$C,MATCH($G35,Responses!$N:$N,0)),"") -> CI-Q09 | K35: =IFERROR(INDEX(Responses!$F:$F,MATCH($G35,Responses!$N:$N,0)),"") -> High | L35: =IFERROR(INDEX(Responses!$E:$E,MATCH($G35,Responses!$N:$N,0)),"") -> Projection assumptions are reasonable versus historical performance and market data. | M35: =IFERROR(INDEX(Responses!$H:$H,MATCH($G35,Responses!$N:$N,0)),"") -> UCC continuation lapsed; lien perfection not verified at review date. | N35: =IFERROR(INDEX(Responses!$K:$K,MATCH($G35,Responses!$N:$N,0)),"") -> 300
G36: 2 | H36: =IFERROR(INDEX(Responses!$A:$A,MATCH($G36,Responses!$N:$N,0)),"") -> CI-2026001 | I36: =IFERROR(INDEX(Responses!$B:$B,MATCH($G36,Responses!$N:$N,0)),"") -> CI | J36: =IFERROR(INDEX(Responses!$C:$C,MATCH($G36,Responses!$N:$N,0)),"") -> CI-Q14 | K36: =IFERROR(INDEX(Responses!$F:$F,MATCH($G36,Responses!$N:$N,0)),"") -> Low | L36: =IFERROR(INDEX(Responses!$E:$E,MATCH($G36,Responses!$N:$N,0)),"") -> Insurance requirements are met and the bank is loss payee where required. | M36: =IFERROR(INDEX(Responses!$H:$H,MATCH($G36,Responses!$N:$N,0)),"") -> UCC continuation lapsed; lien perfection not verified at review date. | N36: =IFERROR(INDEX(Responses!$K:$K,MATCH($G36,Responses!$N:$N,0)),"") -> 300
G37: 3 | H37: =IFERROR(INDEX(Responses!$A:$A,MATCH($G37,Responses!$N:$N,0)),"") -> CI-2026002 | I37: =IFERROR(INDEX(Responses!$B:$B,MATCH($G37,Responses!$N:$N,0)),"") -> CI | J37: =IFERROR(INDEX(Responses!$C:$C,MATCH($G37,Responses!$N:$N,0)),"") -> CI-Q04 | K37: =IFERROR(INDEX(Responses!$F:$F,MATCH($G37,Responses!$N:$N,0)),"") -> High | L37: =IFERROR(INDEX(Responses!$E:$E,MATCH($G37,Responses!$N:$N,0)),"") -> Underwriting at origination conformed to policy standards in effect. | M37: =IFERROR(INDEX(Responses!$H:$H,MATCH($G37,Responses!$N:$N,0)),"") -> Covenant test for Q4 not evidenced; compliance certificate missing. | N37: =IFERROR(INDEX(Responses!$K:$K,MATCH($G37,Responses!$N:$N,0)),"") -> 216
G38: 4 | H38: =IFERROR(INDEX(Responses!$A:$A,MATCH($G38,Responses!$N:$N,0)),"") -> CI-2026002 | I38: =IFERROR(INDEX(Responses!$B:$B,MATCH($G38,Responses!$N:$N,0)),"") -> CI | J38: =IFERROR(INDEX(Responses!$C:$C,MATCH($G38,Responses!$N:$N,0)),"") -> CI-Q23 | K38: =IFERROR(INDEX(Responses!$F:$F,MATCH($G38,Responses!$N:$N,0)),"") -> Medium | L38: =IFERROR(INDEX(Responses!$E:$E,MATCH($G38,Responses!$N:$N,0)),"") -> Capital: borrower equity/tangible net worth is adequate for the risk. | M38: =IFERROR(INDEX(Responses!$H:$H,MATCH($G38,Responses!$N:$N,0)),"") -> Financial statements stale beyond policy window; no waiver in file. | N38: =IFERROR(INDEX(Responses!$K:$K,MATCH($G38,Responses!$N:$N,0)),"") -> 216
G39: 5 | H39: =IFERROR(INDEX(Responses!$A:$A,MATCH($G39,Responses!$N:$N,0)),"") -> CI-2026003 | I39: =IFERROR(INDEX(Responses!$B:$B,MATCH($G39,Responses!$N:$N,0)),"") -> CI | J39: =IFERROR(INDEX(Responses!$C:$C,MATCH($G39,Responses!$N:$N,0)),"") -> CI-Q01 | K39: =IFERROR(INDEX(Responses!$F:$F,MATCH($G39,Responses!$N:$N,0)),"") -> High | L39: =IFERROR(INDEX(Responses!$E:$E,MATCH($G39,Responses!$N:$N,0)),"") -> LOB-assigned risk grade is supported by current financial analysis. | M39: =IFERROR(INDEX(Responses!$H:$H,MATCH($G39,Responses!$N:$N,0)),"") -> Financial statements stale beyond policy window; no waiver in file. | N39: =IFERROR(INDEX(Responses!$K:$K,MATCH($G39,Responses!$N:$N,0)),"") -> 111
G40: 6 | H40: =IFERROR(INDEX(Responses!$A:$A,MATCH($G40,Responses!$N:$N,0)),"") -> CI-2026003 | I40: =IFERROR(INDEX(Responses!$B:$B,MATCH($G40,Responses!$N:$N,0)),"") -> CI | J40: =IFERROR(INDEX(Responses!$C:$C,MATCH($G40,Responses!$N:$N,0)),"") -> CI-Q25 | K40: =IFERROR(INDEX(Responses!$F:$F,MATCH($G40,Responses!$N:$N,0)),"") -> Low | L40: =IFERROR(INDEX(Responses!$E:$E,MATCH($G40,Responses!$N:$N,0)),"") -> Conditions: industry, market, and macro conditions are evaluated. | M40: =IFERROR(INDEX(Responses!$H:$H,MATCH($G40,Responses!$N:$N,0)),"") -> Covenant test for Q4 not evidenced; compliance certificate missing. | N40: =IFERROR(INDEX(Responses!$K:$K,MATCH($G40,Responses!$N:$N,0)),"") -> 111
G41: 7 | H41: =IFERROR(INDEX(Responses!$A:$A,MATCH($G41,Responses!$N:$N,0)),"") -> CI-2026004 | I41: =IFERROR(INDEX(Responses!$B:$B,MATCH($G41,Responses!$N:$N,0)),"") -> CI | J41: =IFERROR(INDEX(Responses!$C:$C,MATCH($G41,Responses!$N:$N,0)),"") -> CI-Q11 | K41: =IFERROR(INDEX(Responses!$F:$F,MATCH($G41,Responses!$N:$N,0)),"") -> Medium | L41: =IFERROR(INDEX(Responses!$E:$E,MATCH($G41,Responses!$N:$N,0)),"") -> Guaranty enforceability documented (signed, unconditional unless approved otherwise). | M41: =IFERROR(INDEX(Responses!$H:$H,MATCH($G41,Responses!$N:$N,0)),"") -> Financial statements stale beyond policy window; no waiver in file. | N41: =IFERROR(INDEX(Responses!$K:$K,MATCH($G41,Responses!$N:$N,0)),"") -> 34
G42: 8 | H42: =IFERROR(INDEX(Responses!$A:$A,MATCH($G42,Responses!$N:$N,0)),"") -> CI-2026004 | I42: =IFERROR(INDEX(Responses!$B:$B,MATCH($G42,Responses!$N:$N,0)),"") -> CI | J42: =IFERROR(INDEX(Responses!$C:$C,MATCH($G42,Responses!$N:$N,0)),"") -> CI-Q13 | K42: =IFERROR(INDEX(Responses!$F:$F,MATCH($G42,Responses!$N:$N,0)),"") -> High | L42: =IFERROR(INDEX(Responses!$E:$E,MATCH($G42,Responses!$N:$N,0)),"") -> Lien positions are perfected and verified (searches, filings, titles). | M42: =IFERROR(INDEX(Responses!$H:$H,MATCH($G42,Responses!$N:$N,0)),"") -> Projection growth assumption unsupported versus 3-year actuals. | N42: =IFERROR(INDEX(Responses!$K:$K,MATCH($G42,Responses!$N:$N,0)),"") -> 34
G43: 9 | H43: =IFERROR(INDEX(Responses!$A:$A,MATCH($G43,Responses!$N:$N,0)),"") -> CRE-2026001 | I43: =IFERROR(INDEX(Responses!$B:$B,MATCH($G43,Responses!$N:$N,0)),"") -> CRE | J43: =IFERROR(INDEX(Responses!$C:$C,MATCH($G43,Responses!$N:$N,0)),"") -> CRE-Q16 | K43: =IFERROR(INDEX(Responses!$F:$F,MATCH($G43,Responses!$N:$N,0)),"") -> Medium | L43: =IFERROR(INDEX(Responses!$E:$E,MATCH($G43,Responses!$N:$N,0)),"") -> Policy exceptions at approval were identified, justified, and approved at proper level. | M43: =IFERROR(INDEX(Responses!$H:$H,MATCH($G43,Responses!$N:$N,0)),"") -> Financial statements stale beyond policy window; no waiver in file. | N43: =IFERROR(INDEX(Responses!$K:$K,MATCH($G43,Responses!$N:$N,0)),"") -> 300
G44: 10 | H44: =IFERROR(INDEX(Responses!$A:$A,MATCH($G44,Responses!$N:$N,0)),"") -> CRE-2026002 | I44: =IFERROR(INDEX(Responses!$B:$B,MATCH($G44,Responses!$N:$N,0)),"") -> CRE | J44: =IFERROR(INDEX(Responses!$C:$C,MATCH($G44,Responses!$N:$N,0)),"") -> CRE-Q06 | K44: =IFERROR(INDEX(Responses!$F:$F,MATCH($G44,Responses!$N:$N,0)),"") -> High | L44: =IFERROR(INDEX(Responses!$E:$E,MATCH($G44,Responses!$N:$N,0)),"") -> Analysis critically evaluates borrower-provided information rather than restating it. | M44: =IFERROR(INDEX(Responses!$H:$H,MATCH($G44,Responses!$N:$N,0)),"") -> Guarantor PFS older than 12 months; reliance not currently supported. | N44: =IFERROR(INDEX(Responses!$K:$K,MATCH($G44,Responses!$N:$N,0)),"") -> 216
G45: 11 | H45: =IFERROR(INDEX(Responses!$A:$A,MATCH($G45,Responses!$N:$N,0)),"") -> CRE-2026002 | I45: =IFERROR(INDEX(Responses!$B:$B,MATCH($G45,Responses!$N:$N,0)),"") -> CRE | J45: =IFERROR(INDEX(Responses!$C:$C,MATCH($G45,Responses!$N:$N,0)),"") -> CRE-Q22 | K45: =IFERROR(INDEX(Responses!$F:$F,MATCH($G45,Responses!$N:$N,0)),"") -> High | L45: =IFERROR(INDEX(Responses!$E:$E,MATCH($G45,Responses!$N:$N,0)),"") -> Occupancy and lease rollover within 24 months are analyzed against market. | M45: =IFERROR(INDEX(Responses!$H:$H,MATCH($G45,Responses!$N:$N,0)),"") -> Approval signature exceeds officer's delegated authority; no co-approval. | N45: =IFERROR(INDEX(Responses!$K:$K,MATCH($G45,Responses!$N:$N,0)),"") -> 216
G46: 12 | H46: =IFERROR(INDEX(Responses!$A:$A,MATCH($G46,Responses!$N:$N,0)),"") -> CRE-2026003 | I46: =IFERROR(INDEX(Responses!$B:$B,MATCH($G46,Responses!$N:$N,0)),"") -> CRE | J46: =IFERROR(INDEX(Responses!$C:$C,MATCH($G46,Responses!$N:$N,0)),"") -> CRE-Q09 | K46: =IFERROR(INDEX(Responses!$F:$F,MATCH($G46,Responses!$N:$N,0)),"") -> High | L46: =IFERROR(INDEX(Responses!$E:$E,MATCH($G46,Responses!$N:$N,0)),"") -> Projection assumptions are reasonable versus historical performance and market data. | M46: =IFERROR(INDEX(Responses!$H:$H,MATCH($G46,Responses!$N:$N,0)),"") -> Guarantor PFS older than 12 months; reliance not currently supported. | N46: =IFERROR(INDEX(Responses!$K:$K,MATCH($G46,Responses!$N:$N,0)),"") -> 111
... G64: 30 | H64: =IFERROR(INDEX(Responses!$A:$A,MATCH($G64,Responses!$N:$N,0)),"") -> ABL-2026003 | I64: =IFERROR(INDEX(Responses!$B:$B,MATCH($G64,Responses!$N:$N,0)),"") -> ABL | J64: =IFERROR(INDEX(Responses!$C:$C,MATCH($G64,Responses!$N:$N,0)),"") -> ABL-Q26 | K64: =IFERROR(INDEX(Responses!$F:$F,MATCH($G64,Responses!$N:$N,0)),"") -> Medium | L64: =IFERROR(INDEX(Responses!$E:$E,MATCH($G64,Responses!$N:$N,0)),"") -> Borrowing-base certificate frequency and verification meet monitoring requirements. | M64: =IFERROR(INDEX(Responses!$H:$H,MATCH($G64,Responses!$N:$N,0)),"") -> Approval signature exceeds officer's delegated authority; no co-approval. | N64: =IFERROR(INDEX(Responses!$K:$K,MATCH($G64,Responses!$N:$N,0)),"") -> 111

Sheet Obs_View
B1: Observations View
B2: Obs = pass with a required note. Never counted as an exception; listed here so thematic patterns across files stay visible.
B4: TOTAL OBSERVATIONS
B5: =COUNTIF(Responses!$G:$G,"Obs") -> 50
E6: Observation Detail (first 30)
B7: Observations by Section (thematic patterns) | E7: # | F7: Credit | G7: Seg | H7: QID | I7: Question | J7: Observation Note | K7: Review Date
B8: Section | C8: Obs Count | E8: 1 | F8: =IFERROR(INDEX(Responses!$A:$A,MATCH($E8,Responses!$M:$M,0)),"") -> CI-2026002 | G8: =IFERROR(INDEX(Responses!$B:$B,MATCH($E8,Responses!$M:$M,0)),"") -> CI | H8: =IFERROR(INDEX(Responses!$C:$C,MATCH($E8,Responses!$M:$M,0)),"") -> CI-Q20 | I8: =IFERROR(INDEX(Responses!$E:$E,MATCH($E8,Responses!$M:$M,0)),"") -> Required periodic monitoring (annual review, site visits) is current. | J8: =IFERROR(INDEX(Responses!$H:$H,MATCH($E8,Responses!$M:$M,0)),"") -> Annual review completed 10 days before deadline two cycles running - timing risk. | K8: =IFERROR(INDEX(Responses!$I:$I,MATCH($E8,Responses!$M:$M,0)),"") -> 45967
B9: Credit Quality & Risk-Grade Accuracy | C9: =COUNTIFS(Responses!$D:$D,B9,Responses!$G:$G,"Obs") -> 4 | E9: 2 | F9: =IFERROR(INDEX(Responses!$A:$A,MATCH($E9,Responses!$M:$M,0)),"") -> CI-2026004 | G9: =IFERROR(INDEX(Responses!$B:$B,MATCH($E9,Responses!$M:$M,0)),"") -> CI | H9: =IFERROR(INDEX(Responses!$C:$C,MATCH($E9,Responses!$M:$M,0)),"") -> CI-Q19 | I9: =IFERROR(INDEX(Responses!$E:$E,MATCH($E9,Responses!$M:$M,0)),"") -> Credit complies with internal lending policy limits (hold limits, tenor, pricing floors). | J9: =IFERROR(INDEX(Responses!$H:$H,MATCH($E9,Responses!$M:$M,0)),"") -> Borrowing-base certificate delivered by email rather than portal per agreement. | K9: =IFERROR(INDEX(Responses!$I:$I,MATCH($E9,Responses!$M:$M,0)),"") -> 46149
B10: Underwriting Soundness | C10: =COUNTIFS(Responses!$D:$D,B10,Responses!$G:$G,"Obs") -> 2 | E10: 3 | F10: =IFERROR(INDEX(Responses!$A:$A,MATCH($E10,Responses!$M:$M,0)),"") -> CRE-2026001 | G10: =IFERROR(INDEX(Responses!$B:$B,MATCH($E10,Responses!$M:$M,0)),"") -> CRE | H10: =IFERROR(INDEX(Responses!$C:$C,MATCH($E10,Responses!$M:$M,0)),"") -> CRE-Q10 | I10: =IFERROR(INDEX(Responses!$E:$E,MATCH($E10,Responses!$M:$M,0)),"") -> Guarantor/sponsor financial condition is current, analyzed, and supports reliance. | J10: =IFERROR(INDEX(Responses!$H:$H,MATCH($E10,Responses!$M:$M,0)),"") -> Spread mislabels FY2024 column as FY2025; values correct. | K10: =IFERROR(INDEX(Responses!$I:$I,MATCH($E10,Responses!$M:$M,0)),"") -> 45883
B11: Repayment Sources & Projections | C11: =COUNTIFS(Responses!$D:$D,B11,Responses!$G:$G,"Obs") -> 4 | E11: 4 | F11: =IFERROR(INDEX(Responses!$A:$A,MATCH($E11,Responses!$M:$M,0)),"") -> CRE-2026002 | G11: =IFERROR(INDEX(Responses!$B:$B,MATCH($E11,Responses!$M:$M,0)),"") -> CRE | H11: =IFERROR(INDEX(Responses!$C:$C,MATCH($E11,Responses!$M:$M,0)),"") -> CRE-Q16 | I11: =IFERROR(INDEX(Responses!$E:$E,MATCH($E11,Responses!$M:$M,0)),"") -> Policy exceptions at approval were identified, justified, and approved at proper level. | J11: =IFERROR(INDEX(Responses!$H:$H,MATCH($E11,Responses!$M:$M,0)),"") -> Annual review completed 10 days before deadline two cycles running - timing risk. | K11: =IFERROR(INDEX(Responses!$I:$I,MATCH($E11,Responses!$M:$M,0)),"") -> 45967
B12: Guarantor / Sponsor Creditworthiness | C12: =COUNTIFS(Responses!$D:$D,B12,Responses!$G:$G,"Obs") -> 4 | E12: 5 | F12: =IFERROR(INDEX(Responses!$A:$A,MATCH($E12,Responses!$M:$M,0)),"") -> CRE-2026002 | G12: =IFERROR(INDEX(Responses!$B:$B,MATCH($E12,Responses!$M:$M,0)),"") -> CRE | H12: =IFERROR(INDEX(Responses!$C:$C,MATCH($E12,Responses!$M:$M,0)),"") -> CRE-Q17 | I12: =IFERROR(INDEX(Responses!$E:$E,MATCH($E12,Responses!$M:$M,0)),"") -> Covenant compliance is tested at required frequency with evidence retained. | J12: =IFERROR(INDEX(Responses!$H:$H,MATCH($E12,Responses!$M:$M,0)),"") -> Site-visit memo informative but not filed in imaging system. | K12: =IFERROR(INDEX(Responses!$I:$I,MATCH($E12,Responses!$M:$M,0)),"") -> 45967
B13: Credit & Collateral Documentation / Lien Perfection | C13: =COUNTIFS(Responses!$D:$D,B13,Responses!$G:$G,"Obs") -> 5 | E13: 6 | F13: =IFERROR(INDEX(Responses!$A:$A,MATCH($E13,Responses!$M:$M,0)),"") -> CRE-2026003 | G13: =IFERROR(INDEX(Responses!$B:$B,MATCH($E13,Responses!$M:$M,0)),"") -> CRE | H13: =IFERROR(INDEX(Responses!$C:$C,MATCH($E13,Responses!$M:$M,0)),"") -> CRE-Q03 | I13: =IFERROR(INDEX(Responses!$E:$E,MATCH($E13,Responses!$M:$M,0)),"") -> Grade was reviewed/affirmed within policy frequency requirements. | J13: =IFERROR(INDEX(Responses!$H:$H,MATCH($E13,Responses!$M:$M,0)),"") -> Spread mislabels FY2024 column as FY2025; values correct. | K13: =IFERROR(INDEX(Responses!$I:$I,MATCH($E13,Responses!$M:$M,0)),"") -> 46072
B14: Approval Authority | C14: =COUNTIFS(Responses!$D:$D,B14,Responses!$G:$G,"Obs") -> 6 | E14: 7 | F14: =IFERROR(INDEX(Responses!$A:$A,MATCH($E14,Responses!$M:$M,0)),"") -> CRE-2026003 | G14: =IFERROR(INDEX(Responses!$B:$B,MATCH($E14,Responses!$M:$M,0)),"") -> CRE | H14: =IFERROR(INDEX(Responses!$C:$C,MATCH($E14,Responses!$M:$M,0)),"") -> CRE-Q06 | I14: =IFERROR(INDEX(Responses!$E:$E,MATCH($E14,Responses!$M:$M,0)),"") -> Analysis critically evaluates borrower-provided information rather than restating it. | J14: =IFERROR(INDEX(Responses!$H:$H,MATCH($E14,Responses!$M:$M,0)),"") -> Rate-reset sensitivity shown only at +100bp; broader stress would aid analysis. | K14: =IFERROR(INDEX(Responses!$I:$I,MATCH($E14,Responses!$M:$M,0)),"") -> 46072
B15: Covenant Adherence | C15: =COUNTIFS(Responses!$D:$D,B15,Responses!$G:$G,"Obs") -> 6 | E15: 8 | F15: =IFERROR(INDEX(Responses!$A:$A,MATCH($E15,Responses!$M:$M,0)),"") -> CRE-2026003 | G15: =IFERROR(INDEX(Responses!$B:$B,MATCH($E15,Responses!$M:$M,0)),"") -> CRE | H15: =IFERROR(INDEX(Responses!$C:$C,MATCH($E15,Responses!$M:$M,0)),"") -> CRE-Q18 | I15: =IFERROR(INDEX(Responses!$E:$E,MATCH($E15,Responses!$M:$M,0)),"") -> Covenant breaches (if any) were identified, reported, and waived/cured per policy. | J15: =IFERROR(INDEX(Responses!$H:$H,MATCH($E15,Responses!$M:$M,0)),"") -> Spread mislabels FY2024 column as FY2025; values correct. | K15: =IFERROR(INDEX(Responses!$I:$I,MATCH($E15,Responses!$M:$M,0)),"") -> 46072
B16: Policy Compliance | C16: =COUNTIFS(Responses!$D:$D,B16,Responses!$G:$G,"Obs") -> 3 | E16: 9 | F16: =IFERROR(INDEX(Responses!$A:$A,MATCH($E16,Responses!$M:$M,0)),"") -> CRE-2026003 | G16: =IFERROR(INDEX(Responses!$B:$B,MATCH($E16,Responses!$M:$M,0)),"") -> CRE | H16: =IFERROR(INDEX(Responses!$C:$C,MATCH($E16,Responses!$M:$M,0)),"") -> CRE-Q21 | I16: =IFERROR(INDEX(Responses!$E:$E,MATCH($E16,Responses!$M:$M,0)),"") -> Property-type risk factors (office obsolescence, MF supply, retail anchor risk) addressed for the subject type. | J16: =IFERROR(INDEX(Responses!$H:$H,MATCH($E16,Responses!$M:$M,0)),"") -> Annual review completed 10 days before deadline two cycles running - timing risk. | K16: =IFERROR(INDEX(Responses!$I:$I,MATCH($E16,Responses!$M:$M,0)),"") -> 46072
B17: Five Cs of Credit | C17: =COUNTIFS(Responses!$D:$D,B17,Responses!$G:$G,"Obs") -> 0 | E17: 10 | F17: =IFERROR(INDEX(Responses!$A:$A,MATCH($E17,Responses!$M:$M,0)),"") -> CRE-2026004 | G17: =IFERROR(INDEX(Responses!$B:$B,MATCH($E17,Responses!$M:$M,0)),"") -> CRE | H17: =IFERROR(INDEX(Responses!$C:$C,MATCH($E17,Responses!$M:$M,0)),"") -> CRE-Q16 | I17: =IFERROR(INDEX(Responses!$E:$E,MATCH($E17,Responses!$M:$M,0)),"") -> Policy exceptions at approval were identified, justified, and approved at proper level. | J17: =IFERROR(INDEX(Responses!$H:$H,MATCH($E17,Responses!$M:$M,0)),"") -> Rate-reset sensitivity shown only at +100bp; broader stress would aid analysis. | K17: =IFERROR(INDEX(Responses!$I:$I,MATCH($E17,Responses!$M:$M,0)),"") -> 46149
B18: Global Cash Flow | C18: =COUNTIFS(Responses!$D:$D,B18,Responses!$G:$G,"Obs") -> 0 | E18: 11 | F18: =IFERROR(INDEX(Responses!$A:$A,MATCH($E18,Responses!$M:$M,0)),"") -> LL-2026001 | G18: =IFERROR(INDEX(Responses!$B:$B,MATCH($E18,Responses!$M:$M,0)),"") -> LL | H18: =IFERROR(INDEX(Responses!$C:$C,MATCH($E18,Responses!$M:$M,0)),"") -> LL-Q12 | I18: =IFERROR(INDEX(Responses!$E:$E,MATCH($E18,Responses!$M:$M,0)),"") -> All required credit documents are present, current, and properly executed. | J18: =IFERROR(INDEX(Responses!$H:$H,MATCH($E18,Responses!$M:$M,0)),"") -> Site-visit memo informative but not filed in imaging system. | K18: =IFERROR(INDEX(Responses!$I:$I,MATCH($E18,Responses!$M:$M,0)),"") -> 45883
B19: Property & Market (subform: Office / Multifamily / Retail) | C19: =COUNTIFS(Responses!$D:$D,B19,Responses!$G:$G,"Obs") -> 1 | E19: 12 | F19: =IFERROR(INDEX(Responses!$A:$A,MATCH($E19,Responses!$M:$M,0)),"") -> LL-2026002 | G19: =IFERROR(INDEX(Responses!$B:$B,MATCH($E19,Responses!$M:$M,0)),"") -> LL | H19: =IFERROR(INDEX(Responses!$C:$C,MATCH($E19,Responses!$M:$M,0)),"") -> LL-Q01 | I19: =IFERROR(INDEX(Responses!$E:$E,MATCH($E19,Responses!$M:$M,0)),"") -> LOB-assigned risk grade is supported by current financial analysis. | J19: =IFERROR(INDEX(Responses!$H:$H,MATCH($E19,Responses!$M:$M,0)),"") -> Annual review completed 10 days before deadline two cycles running - timing risk. | K19: =IFERROR(INDEX(Responses!$I:$I,MATCH($E19,Responses!$M:$M,0)),"") -> 45967
B20: Appraisal & Evaluation (FIRREA / USPAP) | C20: =COUNTIFS(Responses!$D:$D,B20,Responses!$G:$G,"Obs") -> 0 | E20: 13 | F20: =IFERROR(INDEX(Responses!$A:$A,MATCH($E20,Responses!$M:$M,0)),"") -> LL-2026002 | G20: =IFERROR(INDEX(Responses!$B:$B,MATCH($E20,Responses!$M:$M,0)),"") -> LL | H20: =IFERROR(INDEX(Responses!$C:$C,MATCH($E20,Responses!$M:$M,0)),"") -> LL-Q15 | I20: =IFERROR(INDEX(Responses!$E:$E,MATCH($E20,Responses!$M:$M,0)),"") -> Credit was approved within delegated authority of the approving officer(s). | J20: =IFERROR(INDEX(Responses!$H:$H,MATCH($E20,Responses!$M:$M,0)),"") -> Spread mislabels FY2024 column as FY2025; values correct. | K20: =IFERROR(INDEX(Responses!$I:$I,MATCH($E20,Responses!$M:$M,0)),"") -> 45967
... B32: Consumer-Adjacent Touchpoints | C32: =COUNTIFS(Responses!$D:$D,B32,Responses!$G:$G,"Obs") -> 1 | E32: 25 | F32: =IFERROR(INDEX(Responses!$A:$A,MATCH($E32,Responses!$M:$M,0)),"") -> ABL-2026004 | G32: =IFERROR(INDEX(Responses!$B:$B,MATCH($E32,Responses!$M:$M,0)),"") -> ABL | H32: =IFERROR(INDEX(Responses!$C:$C,MATCH($E32,Responses!$M:$M,0)),"") -> ABL-Q09 | I32: =IFERROR(INDEX(Responses!$E:$E,MATCH($E32,Responses!$M:$M,0)),"") -> Projection assumptions are reasonable versus historical performance and market data. | J32: =IFERROR(INDEX(Responses!$H:$H,MATCH($E32,Responses!$M:$M,0)),"") -> Site-visit memo informative but not filed in imaging system. | K32: =IFERROR(INDEX(Responses!$I:$I,MATCH($E32,Responses!$M:$M,0)),"") -> 46149
B33: Amber = section with 2+ observations across files (potential thematic finding). | E33: 26 | F33: =IFERROR(INDEX(Responses!$A:$A,MATCH($E33,Responses!$M:$M,0)),"") -> ABL-2026004 | G33: =IFERROR(INDEX(Responses!$B:$B,MATCH($E33,Responses!$M:$M,0)),"") -> ABL | H33: =IFERROR(INDEX(Responses!$C:$C,MATCH($E33,Responses!$M:$M,0)),"") -> ABL-Q22 | I33: =IFERROR(INDEX(Responses!$E:$E,MATCH($E33,Responses!$M:$M,0)),"") -> Ineligibles are identified, current, and correctly deducted. | J33: =IFERROR(INDEX(Responses!$H:$H,MATCH($E33,Responses!$M:$M,0)),"") -> Spread mislabels FY2024 column as FY2025; values correct. | K33: =IFERROR(INDEX(Responses!$I:$I,MATCH($E33,Responses!$M:$M,0)),"") -> 46149
E34: 27 | F34: =IFERROR(INDEX(Responses!$A:$A,MATCH($E34,Responses!$M:$M,0)),"") -> ARG-2026001 | G34: =IFERROR(INDEX(Responses!$B:$B,MATCH($E34,Responses!$M:$M,0)),"") -> ARG | H34: =IFERROR(INDEX(Responses!$C:$C,MATCH($E34,Responses!$M:$M,0)),"") -> ARG-Q11 | I34: =IFERROR(INDEX(Responses!$E:$E,MATCH($E34,Responses!$M:$M,0)),"") -> Guaranty enforceability documented (signed, unconditional unless approved otherwise). | J34: =IFERROR(INDEX(Responses!$H:$H,MATCH($E34,Responses!$M:$M,0)),"") -> Spread mislabels FY2024 column as FY2025; values correct. | K34: =IFERROR(INDEX(Responses!$I:$I,MATCH($E34,Responses!$M:$M,0)),"") -> 45883
E35: 28 | F35: =IFERROR(INDEX(Responses!$A:$A,MATCH($E35,Responses!$M:$M,0)),"") -> ARG-2026001 | G35: =IFERROR(INDEX(Responses!$B:$B,MATCH($E35,Responses!$M:$M,0)),"") -> ARG | H35: =IFERROR(INDEX(Responses!$C:$C,MATCH($E35,Responses!$M:$M,0)),"") -> ARG-Q13 | I35: =IFERROR(INDEX(Responses!$E:$E,MATCH($E35,Responses!$M:$M,0)),"") -> Lien positions are perfected and verified (searches, filings, titles). | J35: =IFERROR(INDEX(Responses!$H:$H,MATCH($E35,Responses!$M:$M,0)),"") -> Spread mislabels FY2024 column as FY2025; values correct. | K35: =IFERROR(INDEX(Responses!$I:$I,MATCH($E35,Responses!$M:$M,0)),"") -> 45883
E36: 29 | F36: =IFERROR(INDEX(Responses!$A:$A,MATCH($E36,Responses!$M:$M,0)),"") -> ARG-2026001 | G36: =IFERROR(INDEX(Responses!$B:$B,MATCH($E36,Responses!$M:$M,0)),"") -> ARG | H36: =IFERROR(INDEX(Responses!$C:$C,MATCH($E36,Responses!$M:$M,0)),"") -> ARG-Q17 | I36: =IFERROR(INDEX(Responses!$E:$E,MATCH($E36,Responses!$M:$M,0)),"") -> Covenant compliance is tested at required frequency with evidence retained. | J36: =IFERROR(INDEX(Responses!$H:$H,MATCH($E36,Responses!$M:$M,0)),"") -> Site-visit memo informative but not filed in imaging system. | K36: =IFERROR(INDEX(Responses!$I:$I,MATCH($E36,Responses!$M:$M,0)),"") -> 45883
E37: 30 | F37: =IFERROR(INDEX(Responses!$A:$A,MATCH($E37,Responses!$M:$M,0)),"") -> ARG-2026002 | G37: =IFERROR(INDEX(Responses!$B:$B,MATCH($E37,Responses!$M:$M,0)),"") -> ARG | H37: =IFERROR(INDEX(Responses!$C:$C,MATCH($E37,Responses!$M:$M,0)),"") -> ARG-Q08 | I37: =IFERROR(INDEX(Responses!$E:$E,MATCH($E37,Responses!$M:$M,0)),"") -> Secondary repayment source is identified and realizable. | J37: =IFERROR(INDEX(Responses!$H:$H,MATCH($E37,Responses!$M:$M,0)),"") -> Spread mislabels FY2024 column as FY2025; values correct. | K37: =IFERROR(INDEX(Responses!$I:$I,MATCH($E37,Responses!$M:$M,0)),"") -> 45967

Sheet Dash_Concentration
B1: Concentration vs. Capital — Live Crosswalk Status
B2: Criteria pull from the confirmed Crosswalk for the bank's primary agency, as of the Review As-Of Date. Supervisory criteria trigger heightened scrutiny - they are not hard caps.
B4: Bank inputs (edit on Settings sheet)
B5: Total Risk-Based Capital ($000) | C5: =TotalRBC -> 185000
B6: Construction, Land & Development Loans ($000) | C6: =CLDLoans -> 142000
B7: Total Non-Owner-Occupied CRE Loans ($000) | C7: =CRELoans -> 612000
B8: Non-OO CRE Balance 36 Months Ago ($000) | C8: =CRELoans36 -> 425000
B11: Supervisory criteria status (2006 Interagency CRE Guidance, as confirmed in Crosswalk)
B12: Measure | C12: Bank Level | D12: Criterion (In Force) | E12: Status
B13: CLD Loans / Total Risk-Based Capital | C13: =IF(TotalRBC=0,"",CLDLoans/TotalRBC) -> 0.76756757 | D13: =IF(SUMPRODUCT(MAX((Crosswalk!$O$2:$O$300="CLD Concentration / Total Risk-Based Capital|"&PrimaryAgency)*(Crosswalk!$P$2:$P$300=1)*Crosswalk!$C$2:$C$300))=0,"Coverage gap",SUMPRODUCT(MAX((Crosswalk!$O$2:$O$300="CLD Concentration / Total Risk-Based Capital|"&PrimaryAgency)*(Crosswalk!$P$2:$P$300=1)*Crosswalk!$C$2:$C$300))/100) -> 1 | E13: =IF(OR(C13="",ISTEXT(D13)),"n/a",IF(C13>=D13,"Criterion met — heightened scrutiny","Below criterion")) -> Below criterion
B14: Total Non-OO CRE / Total Risk-Based Capital | C14: =IF(TotalRBC=0,"",CRELoans/TotalRBC) -> 3.3081081 | D14: =IF(SUMPRODUCT(MAX((Crosswalk!$O$2:$O$300="Total CRE / Total Risk-Based Capital|"&PrimaryAgency)*(Crosswalk!$P$2:$P$300=1)*Crosswalk!$C$2:$C$300))=0,"Coverage gap",SUMPRODUCT(MAX((Crosswalk!$O$2:$O$300="Total CRE / Total Risk-Based Capital|"&PrimaryAgency)*(Crosswalk!$P$2:$P$300=1)*Crosswalk!$C$2:$C$300))/100) -> 3 | E14: =IF(OR(C14="",ISTEXT(D14)),"n/a",IF(C14>=D14,"Part 1 met — test growth","Below criterion")) -> Part 1 met — test growth
B15: 36-Month CRE Growth | C15: =IF(CRELoans36=0,"",(CRELoans-CRELoans36)/CRELoans36) -> 0.44 | D15: =IF(SUMPRODUCT(MAX((Crosswalk!$O$2:$O$300="CRE 36-Month Growth Trigger|"&PrimaryAgency)*(Crosswalk!$P$2:$P$300=1)*Crosswalk!$C$2:$C$300))=0,"Coverage gap",SUMPRODUCT(MAX((Crosswalk!$O$2:$O$300="CRE 36-Month Growth Trigger|"&PrimaryAgency)*(Crosswalk!$P$2:$P$300=1)*Crosswalk!$C$2:$C$300))/100) -> 0.5 | E15: =IF(OR(C15="",ISTEXT(D15)),"n/a",IF(AND(C15>=D15,C14>=D14),"Combined criterion met — heightened scrutiny","Below combined criterion")) -> Below combined criterion
B18: Leveraged-Lending Guidance status by agency (Total Debt / EBITDA criterion, as of Review As-Of Date)
B19: Agency | C19: Threshold | D19: Effective | E19: Rescinded | F19: Status As-Of
B20: OCC | C20: =IFERROR(IF(INDEX(Crosswalk!$C:$C,MATCH("Total Debt / EBITDA|OCC",Crosswalk!$O:$O,0))=0,"—",INDEX(Crosswalk!$C:$C,MATCH("Total Debt / EBITDA|OCC",Crosswalk!$O:$O,0))),"not in crosswalk") -> 6 | D20: =IFERROR(IF(INDEX(Crosswalk!$H:$H,MATCH("Total Debt / EBITDA|OCC",Crosswalk!$O:$O,0))=0,"—",INDEX(Crosswalk!$H:$H,MATCH("Total Debt / EBITDA|OCC",Crosswalk!$O:$O,0))),"not in crosswalk") -> 41354 | E20: =IFERROR(IF(INDEX(Crosswalk!$I:$I,MATCH("Total Debt / EBITDA|OCC",Crosswalk!$O:$O,0))=0,"—",INDEX(Crosswalk!$I:$I,MATCH("Total Debt / EBITDA|OCC",Crosswalk!$O:$O,0))),"not in crosswalk") -> 46007 | F20: =IFERROR(IF(INDEX(Crosswalk!$J:$J,MATCH("Total Debt / EBITDA|OCC",Crosswalk!$O:$O,0))=0,"—",INDEX(Crosswalk!$J:$J,MATCH("Total Debt / EBITDA|OCC",Crosswalk!$O:$O,0))),"not in crosswalk") -> Rescinded
B21: FDIC | C21: =IFERROR(IF(INDEX(Crosswalk!$C:$C,MATCH("Total Debt / EBITDA|FDIC",Crosswalk!$O:$O,0))=0,"—",INDEX(Crosswalk!$C:$C,MATCH("Total Debt / EBITDA|FDIC",Crosswalk!$O:$O,0))),"not in crosswalk") -> 6 | D21: =IFERROR(IF(INDEX(Crosswalk!$H:$H,MATCH("Total Debt / EBITDA|FDIC",Crosswalk!$O:$O,0))=0,"—",INDEX(Crosswalk!$H:$H,MATCH("Total Debt / EBITDA|FDIC",Crosswalk!$O:$O,0))),"not in crosswalk") -> 41354 | E21: =IFERROR(IF(INDEX(Crosswalk!$I:$I,MATCH("Total Debt / EBITDA|FDIC",Crosswalk!$O:$O,0))=0,"—",INDEX(Crosswalk!$I:$I,MATCH("Total Debt / EBITDA|FDIC",Crosswalk!$O:$O,0))),"not in crosswalk") -> 46007 | F21: =IFERROR(IF(INDEX(Crosswalk!$J:$J,MATCH("Total Debt / EBITDA|FDIC",Crosswalk!$O:$O,0))=0,"—",INDEX(Crosswalk!$J:$J,MATCH("Total Debt / EBITDA|FDIC",Crosswalk!$O:$O,0))),"not in crosswalk") -> Rescinded
B22: FRB | C22: =IFERROR(IF(INDEX(Crosswalk!$C:$C,MATCH("Total Debt / EBITDA|FRB",Crosswalk!$O:$O,0))=0,"—",INDEX(Crosswalk!$C:$C,MATCH("Total Debt / EBITDA|FRB",Crosswalk!$O:$O,0))),"not in crosswalk") -> 6 | D22: =IFERROR(IF(INDEX(Crosswalk!$H:$H,MATCH("Total Debt / EBITDA|FRB",Crosswalk!$O:$O,0))=0,"—",INDEX(Crosswalk!$H:$H,MATCH("Total Debt / EBITDA|FRB",Crosswalk!$O:$O,0))),"not in crosswalk") -> 41354 | E22: =IFERROR(IF(INDEX(Crosswalk!$I:$I,MATCH("Total Debt / EBITDA|FRB",Crosswalk!$O:$O,0))=0,"—",INDEX(Crosswalk!$I:$I,MATCH("Total Debt / EBITDA|FRB",Crosswalk!$O:$O,0))),"not in crosswalk") -> — | F22: =IFERROR(IF(INDEX(Crosswalk!$J:$J,MATCH("Total Debt / EBITDA|FRB",Crosswalk!$O:$O,0))=0,"—",INDEX(Crosswalk!$J:$J,MATCH("Total Debt / EBITDA|FRB",Crosswalk!$O:$O,0))),"not in crosswalk") -> Active
B24: A threshold can be Active for one agency and Rescinded for another on the same date; reviews cite the rule in force at the review as-of date.

Sheet Dash_Trends
B1: Risk-Grade & Watch-List Trend
B2: By review quarter, from the Database. Watch = Special Mention (5); Classified = Substandard or worse (6+).
B5: Quarterly trend
B6: Quarter | C6: Reviews | D6: Watch (SM) | E6: Classified (6+) | F6: Avg CRR Grade
B7: 2025-Q3 | C7: =COUNTIF(Database!$G:$G,B7) -> 7 | D7: =COUNTIFS(Database!$G:$G,B7,Database!$J:$J,5) -> 1 | E7: =COUNTIFS(Database!$G:$G,B7,Database!$J:$J,">=6") -> 1 | F7: =IF(COUNTIF(Database!$G:$G,B7)=0,"",AVERAGEIFS(Database!$J:$J,Database!$G:$G,B7)) -> 3.8571429
B8: 2025-Q4 | C8: =COUNTIF(Database!$G:$G,B8) -> 7 | D8: =COUNTIFS(Database!$G:$G,B8,Database!$J:$J,5) -> 3 | E8: =COUNTIFS(Database!$G:$G,B8,Database!$J:$J,">=6") -> 0 | F8: =IF(COUNTIF(Database!$G:$G,B8)=0,"",AVERAGEIFS(Database!$J:$J,Database!$G:$G,B8)) -> 3.7142857
B9: 2026-Q1 | C9: =COUNTIF(Database!$G:$G,B9) -> 7 | D9: =COUNTIFS(Database!$G:$G,B9,Database!$J:$J,5) -> 1 | E9: =COUNTIFS(Database!$G:$G,B9,Database!$J:$J,">=6") -> 1 | F9: =IF(COUNTIF(Database!$G:$G,B9)=0,"",AVERAGEIFS(Database!$J:$J,Database!$G:$G,B9)) -> 4
B10: 2026-Q2 | C10: =COUNTIF(Database!$G:$G,B10) -> 7 | D10: =COUNTIFS(Database!$G:$G,B10,Database!$J:$J,5) -> 4 | E10: =COUNTIFS(Database!$G:$G,B10,Database!$J:$J,">=6") -> 1 | F10: =IF(COUNTIF(Database!$G:$G,B10)=0,"",AVERAGEIFS(Database!$J:$J,Database!$G:$G,B10)) -> 4.8571429

Sheet Crosswalk
A1: Row ID | B1: Metric | C1: Value | D1: Unit | E1: Basis / Definition | F1: Agency | G1: Citation | H1: Effective Date | I1: Rescinded Date | J1: Status As-Of Review Date | K1: Source Document | L1: Page / Section | M1: Verbatim Source Span | N1: Reviewer Notes | O1: Key (Metric|Agency) | P1: Active (1/0)
A2: THR-869C3178BE | B2: Total Debt / EBITDA | C2: 6 | D2: x | E2: Supervisory expectation | F2: OCC | G2: 2013 Interagency Guidance on Leveraged Lending (OCC 2013-9 et al.) | H2: 41354 | I2: 46007 | J2: =IF(H2="","Unknown (Coverage Gap)",IF(AsOfDate<H2,"Not Yet Effective",IF(AND(I2<>"",AsOfDate>=I2),"Rescinded","Active"))) -> Rescinded | K2: fixture_2013_leveraged_lending.pdf | L2: p.1, UNDERWRITING STANDARDS | M2: A leverage level after planned asset sales in excess of 6.0x Total Debt to EBITDA raises concerns for most industries. | N2: Verified against source p./section cited. | O2: =B2&"|"&F2 -> Total Debt / EBITDA|OCC | P2: =IF(J2="Active",1,0) -> 0
A3: THR-F1539FA4CB | B3: Total Debt / EBITDA | C3: 6 | D3: x | E3: Supervisory expectation | F3: FRB | G3: 2013 Interagency Guidance on Leveraged Lending (OCC 2013-9 et al.) | H3: 41354 | J3: =IF(H3="","Unknown (Coverage Gap)",IF(AsOfDate<H3,"Not Yet Effective",IF(AND(I3<>"",AsOfDate>=I3),"Rescinded","Active"))) -> Active | K3: fixture_2013_leveraged_lending.pdf | L3: p.1, UNDERWRITING STANDARDS | M3: A leverage level after planned asset sales in excess of 6.0x Total Debt to EBITDA raises concerns for most industries. | N3: Verified against source p./section cited. | O3: =B3&"|"&F3 -> Total Debt / EBITDA|FRB | P3: =IF(J3="Active",1,0) -> 1
