Workbook
Name answers_needed: Control!$J$15:$J$30
Name Status: Control!$H$24:$H$44
Name waiting_words: Control!$K$24:$K$44
Name worse_at: '_live'!$C$5
Name better_at: '_live'!$C$6
Name confidence: '_live'!$C$7
Name significance_bar: '_live'!$C$8
Name judged_band: '_live'!$C$9
Name materiality_kind: '_live'!$C$10
Name materiality_share: '_live'!$C$11
Name materiality_gco: '_live'!$C$12
Name profit_kind: '_live'!$C$13
Name profit_line: '_live'!$C$14
Name in_use_words: '_live'!$C$17
Name line_keys: '_live'!$G$20:$G$30
Name line_values: '_live'!$C$20:$C$30
Name book_gco: '_live'!$C$15
Name pk_kind: '_pockets'!$A$4:$A$1048576
Name pk_measure: '_pockets'!$E$4:$E$1048576
Name pk_dollars: '_pockets'!$Z$4:$Z$1048576
Name pk_flag: '_pockets'!$Y$4:$Y$1048576
Name pk_material: '_pockets'!$AA$4:$AA$1048576
Name pk_worse: '_pockets'!$AI$4:$AI$1048576
Name pk_mat: '_pockets'!$AJ$4:$AJ$1048576
Name pk_border: '_pockets'!$AM$4:$AM$1048576
Name pk_wborder: '_pockets'!$AN$4:$AN$1048576
Name pk_sel_measure: 'Pockets'!$C$17
Name pk_sel_kind: 'Pockets'!$D$17
Name pk_sel_show: 'Pockets'!$E$17

Sheet Start here
B1: PocketBook | C1: Summary book.csv · 8,000 loans · 10 columns · last Run 2026-09-30 15:23
B3: How this tab works
B4: Where things stand | C4: What is left before Run, counted live from Control and Columns as you fill them in.
B5: What the last Run found | C5: Pockets worse and material at Control's lines, and the five largest.
B6: The tabs | C6: Red tabs you fill in; black tabs hold results; grey tabs are the record.
B8: WHERE THINGS STAND
B9: Answers needed before Run | D9: Odd values to answer | F9: Changes waiting for a Run
B10: =IFERROR(SUM(answers_needed),0)+IF(Control!$C$33="",1,0)+IF(Columns!$C$3="Yes",0,1) | D10: =COUNTIFS(Columns!$S$13:$S$22,"?*",Columns!$H$13:$H$22,"") | F10: =IFERROR(COUNTIF(Status,"↻ Waiting for a Run"),0)
B11: Control and Columns | D11: Columns · Treat as | F11: Control · Status
B13: =IFERROR(IF(COUNTIF(Status,"↻ Waiting for a Run")=0,"","↻ "&COUNTIF(Status,"↻ Waiting for a Run")&IF(COUNTIF(Status,"↻ Waiting for a Run")=1," change is"," changes are")&" waiting for a Run. "&LEFT(INDEX(waiting_words,1)&INDEX(waiting_words,2)&INDEX(waiting_words,3)&INDEX(waiting_words,4)&INDEX(waiting_words,5)&INDEX(waiting_words,6)&INDEX(waiting_words,7)&INDEX(waiting_words,8)&INDEX(waiting_words,9)&INDEX(waiting_words,10)&INDEX(waiting_words,11)&INDEX(waiting_words,12)&INDEX(waiting_words,13)&INDEX(waiting_words,14)&INDEX(waiting_words,15)&INDEX(waiting_words,16)&INDEX(waiting_words,17)&INDEX(waiting_words,18)&INDEX(waiting_words,19)&INDEX(waiting_words,20)&INDEX(waiting_words,21),LEN(INDEX(waiting_words,1)&INDEX(waiting_words,2)&INDEX(waiting_words,3)&INDEX(waiting_words,4)&INDEX(waiting_words,5)&INDEX(waiting_words,6)&INDEX(waiting_words,7)&INDEX(waiting_words,8)&INDEX(waiting_words,9)&INDEX(waiting_words,10)&INDEX(waiting_words,11)&INDEX(waiting_words,12)&INDEX(waiting_words,13)&INDEX(waiting_words,14)&INDEX(waiting_words,15)&INDEX(waiting_words,16)&INDEX(waiting_words,17)&INDEX(waiting_words,18)&INDEX(waiting_words,19)&INDEX(waiting_words,20)&INDEX(waiting_words,21))-2)&". The result tabs still show the last Run. Save, close, and press Run in the launcher."),"")
B15: WHAT THE LAST RUN FOUND
B16: Pockets worse and material, charge-offs | D16: Dollars above their share, in those | F16: Pockets keeping less, worse and material
B17: =IFERROR(COUNTIFS(pk_kind,"grids",pk_measure,"gco_rate",pk_flag,"worse",pk_material,"yes")&" of 79"&IF(COUNTIFS(pk_kind,"grids",pk_measure,"gco_rate",pk_flag,"worse",pk_material,"yes",pk_wborder,"?*")>0," · "&COUNTIFS(pk_kind,"grids",pk_measure,"gco_rate",pk_flag,"worse",pk_material,"yes",pk_wborder,"?*")&" borderline",""),"") | D17: =IFERROR(SUMIFS(pk_dollars,pk_kind,"grids",pk_measure,"gco_rate",pk_flag,"worse",pk_material,"yes"),"") | F17: =IFERROR(COUNTIFS(pk_kind,"grids",pk_measure,"ranr_rate",pk_flag,"worse",pk_material,"yes")&" short $"&TEXT(SUMIFS(pk_dollars,pk_kind,"grids",pk_measure,"ranr_rate",pk_flag,"worse",pk_material,"yes"),"#,##0"),"")
B19: Largest, worse and material | C19: Segment | D19: Loans | E19: × its comparison | F19: Dollars above share
B20: =IF($K20="","No pocket is worse and material.",INDEX('_found'!$B$6:$B$53,$K20)) | C20: =IF($K20="","",IF(OR(INDEX('_found'!$C$6:$C$53,$K20)="",INDEX('_pockets'!$AN:$AN,INDEX('_found'!$E$6:$E$53,$K20))=""),INDEX('_found'!$C$6:$C$53,$K20),INDEX('_found'!$C$6:$C$53,$K20)&" · borderline (p "&INDEX('_pockets'!$AN:$AN,INDEX('_found'!$E$6:$E$53,$K20))&")")) | D20: =IF($K20="","",INDEX('_found'!$D$6:$D$53,$K20)) | E20: =IF($K20="","",IF(INDEX('_pockets'!$AB:$AB,INDEX('_found'!$E$6:$E$53,$K20))="","",INDEX('_pockets'!$AB:$AB,INDEX('_found'!$E$6:$E$53,$K20)))) | F20: =IF($K20="","",IF(INDEX('_pockets'!$Z:$Z,INDEX('_found'!$E$6:$E$53,$K20))="","",INDEX('_pockets'!$Z:$Z,INDEX('_found'!$E$6:$E$53,$K20)))) | K20: =IFERROR(MATCH(1,'_found'!$G$6:$G$53,0),"")
B21: =IF($K21="","",INDEX('_found'!$B$6:$B$53,$K21)) | C21: =IF($K21="","",IF(OR(INDEX('_found'!$C$6:$C$53,$K21)="",INDEX('_pockets'!$AN:$AN,INDEX('_found'!$E$6:$E$53,$K21))=""),INDEX('_found'!$C$6:$C$53,$K21),INDEX('_found'!$C$6:$C$53,$K21)&" · borderline (p "&INDEX('_pockets'!$AN:$AN,INDEX('_found'!$E$6:$E$53,$K21))&")")) | D21: =IF($K21="","",INDEX('_found'!$D$6:$D$53,$K21)) | E21: =IF($K21="","",IF(INDEX('_pockets'!$AB:$AB,INDEX('_found'!$E$6:$E$53,$K21))="","",INDEX('_pockets'!$AB:$AB,INDEX('_found'!$E$6:$E$53,$K21)))) | F21: =IF($K21="","",IF(INDEX('_pockets'!$Z:$Z,INDEX('_found'!$E$6:$E$53,$K21))="","",INDEX('_pockets'!$Z:$Z,INDEX('_found'!$E$6:$E$53,$K21)))) | K21: =IFERROR(MATCH(2,'_found'!$G$6:$G$53,0),"")
B22: =IF($K22="","",INDEX('_found'!$B$6:$B$53,$K22)) | C22: =IF($K22="","",IF(OR(INDEX('_found'!$C$6:$C$53,$K22)="",INDEX('_pockets'!$AN:$AN,INDEX('_found'!$E$6:$E$53,$K22))=""),INDEX('_found'!$C$6:$C$53,$K22),INDEX('_found'!$C$6:$C$53,$K22)&" · borderline (p "&INDEX('_pockets'!$AN:$AN,INDEX('_found'!$E$6:$E$53,$K22))&")")) | D22: =IF($K22="","",INDEX('_found'!$D$6:$D$53,$K22)) | E22: =IF($K22="","",IF(INDEX('_pockets'!$AB:$AB,INDEX('_found'!$E$6:$E$53,$K22))="","",INDEX('_pockets'!$AB:$AB,INDEX('_found'!$E$6:$E$53,$K22)))) | F22: =IF($K22="","",IF(INDEX('_pockets'!$Z:$Z,INDEX('_found'!$E$6:$E$53,$K22))="","",INDEX('_pockets'!$Z:$Z,INDEX('_found'!$E$6:$E$53,$K22)))) | K22: =IFERROR(MATCH(3,'_found'!$G$6:$G$53,0),"")
B23: =IF($K23="","",INDEX('_found'!$B$6:$B$53,$K23)) | C23: =IF($K23="","",IF(OR(INDEX('_found'!$C$6:$C$53,$K23)="",INDEX('_pockets'!$AN:$AN,INDEX('_found'!$E$6:$E$53,$K23))=""),INDEX('_found'!$C$6:$C$53,$K23),INDEX('_found'!$C$6:$C$53,$K23)&" · borderline (p "&INDEX('_pockets'!$AN:$AN,INDEX('_found'!$E$6:$E$53,$K23))&")")) | D23: =IF($K23="","",INDEX('_found'!$D$6:$D$53,$K23)) | E23: =IF($K23="","",IF(INDEX('_pockets'!$AB:$AB,INDEX('_found'!$E$6:$E$53,$K23))="","",INDEX('_pockets'!$AB:$AB,INDEX('_found'!$E$6:$E$53,$K23)))) | F23: =IF($K23="","",IF(INDEX('_pockets'!$Z:$Z,INDEX('_found'!$E$6:$E$53,$K23))="","",INDEX('_pockets'!$Z:$Z,INDEX('_found'!$E$6:$E$53,$K23)))) | K23: =IFERROR(MATCH(4,'_found'!$G$6:$G$53,0),"")
B24: =IF($K24="","",INDEX('_found'!$B$6:$B$53,$K24)) | C24: =IF($K24="","",IF(OR(INDEX('_found'!$C$6:$C$53,$K24)="",INDEX('_pockets'!$AN:$AN,INDEX('_found'!$E$6:$E$53,$K24))=""),INDEX('_found'!$C$6:$C$53,$K24),INDEX('_found'!$C$6:$C$53,$K24)&" · borderline (p "&INDEX('_pockets'!$AN:$AN,INDEX('_found'!$E$6:$E$53,$K24))&")")) | D24: =IF($K24="","",INDEX('_found'!$D$6:$D$53,$K24)) | E24: =IF($K24="","",IF(INDEX('_pockets'!$AB:$AB,INDEX('_found'!$E$6:$E$53,$K24))="","",INDEX('_pockets'!$AB:$AB,INDEX('_found'!$E$6:$E$53,$K24)))) | F24: =IF($K24="","",IF(INDEX('_pockets'!$Z:$Z,INDEX('_found'!$E$6:$E$53,$K24))="","",INDEX('_pockets'!$Z:$Z,INDEX('_found'!$E$6:$E$53,$K24)))) | K24: =IFERROR(MATCH(5,'_found'!$G$6:$G$53,0),"")
B25: Every pocket, every measure: the Pockets tab.
B28: THE TABS
B29: You answer | D29: Results | G29: Record
B30: Control: the professional calls | D30: Pockets: every pocket, worse first | G30: Record: what ran, the tie-outs, every Run
B31: Columns: meanings, odd values, memory | D31: Paid, cost, kept: paid against cost
B32: Look: each number column's shape | D32: Grids: one grid at a time, and how common
D33: Summary: one band column's plain figures

Sheet Control
B1: Control | C1: The professional calls. The top block changes results now; the second waits for a Run.
B3: How this tab works
B4: Changes now | C4: The result tabs read these answers with formulas. Change one and every reading, dollar figure, colour and verdict follows at once. The order of rows stays as the last Run left it.
B5: Needs a Run | C5: These decide which pockets exist and which test each one gets, so they take effect when you press Run again. Status says when an answer differs from what the last Run used.
B6: Your answer | C6: Pick from the list, or type a number under Or your own: a number there wins. A shaded answer still needs one. Comes to shows what the answer amounts to now.
B7: Worked out | C7: Fewest loans, worse at and better at each have a value worked out from this extract, shown beside the setting. It is never picked for you.
B8: Chosen in the launcher | C8: What you're running and how the pockets are cut. Change them in the launcher's Choose tests, then press Next. They are shown here so a reviewer sees them.
B9: Materiality levels | C9: For each level: its dollar line, how many pockets have charge-offs above their share that reach it, and their part of all such dollars. It follows your answer live.
B11: Changes now | C11: Needs a Run | F11: Still needs an answer | G11: legend
B13: Changes now · the result tabs follow as you change these | G13: block|now | M13: What each materiality level keeps
B14: Setting | C14: Your answer | D14: Or your own | E14: Comes to | F14: Last Run used | I14: Worked out from the loans | M14: Level | N14: Dollars | O14: Pockets | P14: Of excess
B15: How much worse than its comparison a pocket must be | C15: 1.25 times | E15: =IF(NOT(TRUE),"",IF(AND($D$15<>"",$D$15<>"n/a"),$D$15,IF($C$15="","",IF(ISNA(IFERROR(MATCH($G$15&"|"&$C$15,_options!$A:$A,0),MATCH($G$15&"|"&IFERROR(VALUE($C$15),$C$15),_options!$H:$H,0))),"not an option",IFERROR(TEXT(worse_at,"0.00")&"×",IF(ISNUMBER(IFERROR(INDEX(_options!$D:$D,IFERROR(MATCH($G$15&"|"&$C$15,_options!$A:$A,0),MATCH($G$15&"|"&IFERROR(VALUE($C$15),$C$15),_options!$H:$H,0))),"")),TEXT(IFERROR(INDEX(_options!$D:$D,IFERROR(MATCH($G$15&"|"&$C$15,_options!$A:$A,0),MATCH($G$15&"|"&IFERROR(VALUE($C$15),$C$15),_options!$H:$H,0))),""),"0.00")&"×",IF(ISNUMBER($K$15),TEXT($K$15,"0.00")&"×",""))))))) | F15: 1.25 times | G15: worse_at | I15: suggested: 1.34x, from this extract at the last Run | J15: =IF(AND(TRUE,$C15="",OR($D15="",$D15="n/a")),1,0) | K15: 1.34 | M15: =IFERROR("0.5%"&IF(AND(materiality_kind="share",ABS(materiality_share-0.005)<1E-9)," ◂",""),"0.5%") | N15: =IFERROR((0.005*book_gco),"") | O15: =IFERROR(COUNTIFS(pk_kind,"grids",pk_measure,"gco_rate",pk_dollars,">="&(0.005*book_gco),pk_dollars,">0"),"") | P15: =IFERROR(IF(SUMIFS(pk_dollars,pk_kind,"grids",pk_measure,"gco_rate",pk_dollars,">0")=0,0,SUMIFS(pk_dollars,pk_kind,"grids",pk_measure,"gco_rate",pk_dollars,">="&(0.005*book_gco),pk_dollars,">0")/SUMIFS(pk_dollars,pk_kind,"grids",pk_measure,"gco_rate",pk_dollars,">0")),"")
B16: How much better than its comparison a pocket must be | C16: 0.8 times | E16: =IF(NOT($C$33="Where the book bleeds"),"",IF(AND($D$16<>"",$D$16<>"n/a"),$D$16,IF($C$16="","",IF(ISNA(IFERROR(MATCH($G$16&"|"&$C$16,_options!$A:$A,0),MATCH($G$16&"|"&IFERROR(VALUE($C$16),$C$16),_options!$H:$H,0))),"not an option",IFERROR(TEXT(better_at,"0.00")&"×",IF(ISNUMBER(IFERROR(INDEX(_options!$D:$D,IFERROR(MATCH($G$16&"|"&$C$16,_options!$A:$A,0),MATCH($G$16&"|"&IFERROR(VALUE($C$16),$C$16),_options!$H:$H,0))),"")),TEXT(IFERROR(INDEX(_options!$D:$D,IFERROR(MATCH($G$16&"|"&$C$16,_options!$A:$A,0),MATCH($G$16&"|"&IFERROR(VALUE($C$16),$C$16),_options!$H:$H,0))),""),"0.00")&"×",IF(ISNUMBER($K$16),TEXT($K$16,"0.00")&"×",""))))))) | F16: 0.8 times | G16: better_at | I16: suggested: 0.75x, from this extract at the last Run | J16: =IF(AND($C$33="Where the book bleeds",$C16="",OR($D16="",$D16="n/a")),1,0) | K16: 0.75 | M16: =IFERROR("1%"&IF(AND(materiality_kind="share",ABS(materiality_share-0.01)<1E-9)," ◂",""),"1%") | N16: =IFERROR((0.01*book_gco),"") | O16: =IFERROR(COUNTIFS(pk_kind,"grids",pk_measure,"gco_rate",pk_dollars,">="&(0.01*book_gco),pk_dollars,">0"),"") | P16: =IFERROR(IF(SUMIFS(pk_dollars,pk_kind,"grids",pk_measure,"gco_rate",pk_dollars,">0")=0,0,SUMIFS(pk_dollars,pk_kind,"grids",pk_measure,"gco_rate",pk_dollars,">="&(0.01*book_gco),pk_dollars,">0")/SUMIFS(pk_dollars,pk_kind,"grids",pk_measure,"gco_rate",pk_dollars,">0")),"")
B17: How far profit must move before it counts as more or less | C17: Each pocket's own test (suggested) | E17: =IF(NOT($C$33="Where the book bleeds"),"",IF(AND($D$17<>"",$D$17<>"n/a"),$D$17,IF($C$17="","",IF(ISNA(IFERROR(MATCH($G$17&"|"&$C$17,_options!$A:$A,0),MATCH($G$17&"|"&IFERROR(VALUE($C$17),$C$17),_options!$H:$H,0))),"not an option","")))) | F17: each pocket's own test | G17: revenue_line | J17: =IF(AND($C$33="Where the book bleeds",$C17="",OR($D17="",$D17="n/a")),1,0) | M17: =IFERROR("2%"&IF(AND(materiality_kind="share",ABS(materiality_share-0.02)<1E-9)," ◂",""),"2%") | N17: =IFERROR((0.02*book_gco),"") | O17: =IFERROR(COUNTIFS(pk_kind,"grids",pk_measure,"gco_rate",pk_dollars,">="&(0.02*book_gco),pk_dollars,">0"),"") | P17: =IFERROR(IF(SUMIFS(pk_dollars,pk_kind,"grids",pk_measure,"gco_rate",pk_dollars,">0")=0,0,SUMIFS(pk_dollars,pk_kind,"grids",pk_measure,"gco_rate",pk_dollars,">="&(0.02*book_gco),pk_dollars,">0")/SUMIFS(pk_dollars,pk_kind,"grids",pk_measure,"gco_rate",pk_dollars,">0")),"")
B18: How sure a difference must be before it counts | C18: 95% | E18: =IF(NOT(TRUE),"",IF(AND($D$18<>"",$D$18<>"n/a"),$D$18,IF($C$18="","",IF(ISNA(IFERROR(MATCH($G$18&"|"&$C$18,_options!$A:$A,0),MATCH($G$18&"|"&IFERROR(VALUE($C$18),$C$18),_options!$H:$H,0))),"not an option","")))) | F18: 95% sure | G18: confidence | J18: =IF(AND(TRUE,$C18="",OR($D18="",$D18="n/a")),1,0) | M18: =IFERROR("5%"&IF(AND(materiality_kind="share",ABS(materiality_share-0.05)<1E-9)," ◂",""),"5%") | N18: =IFERROR((0.05*book_gco),"") | O18: =IFERROR(COUNTIFS(pk_kind,"grids",pk_measure,"gco_rate",pk_dollars,">="&(0.05*book_gco),pk_dollars,">0"),"") | P18: =IFERROR(IF(SUMIFS(pk_dollars,pk_kind,"grids",pk_measure,"gco_rate",pk_dollars,">0")=0,0,SUMIFS(pk_dollars,pk_kind,"grids",pk_measure,"gco_rate",pk_dollars,">="&(0.05*book_gco),pk_dollars,">0")/SUMIFS(pk_dollars,pk_kind,"grids",pk_measure,"gco_rate",pk_dollars,">0")),"")
B19: Smallest excess loss worth reporting | C19: 1% of the book's total losses | E19: =IF(NOT(TRUE),"",IF(AND($D$19<>"",$D$19<>"n/a"),$D$19,IF($C$19="","",IF(ISNA(IFERROR(MATCH($G$19&"|"&$C$19,_options!$A:$A,0),MATCH($G$19&"|"&IFERROR(VALUE($C$19),$C$19),_options!$H:$H,0))),"not an option",IFERROR(IF(materiality_kind="none","No floor",IF(materiality_gco>0,"$"&TEXT(materiality_gco,"#,##0"),IFERROR(INDEX(_options!$G:$G,IFERROR(MATCH($G$19&"|"&$C$19,_options!$A:$A,0),MATCH($G$19&"|"&IFERROR(VALUE($C$19),$C$19),_options!$H:$H,0))),"not an option"))),""))))) | F19: 1% of the book's total losses | G19: materiality | J19: =IF(AND(TRUE,$C19="",OR($D19="",$D19="n/a")),1,0) | M19: =IFERROR("10%"&IF(AND(materiality_kind="share",ABS(materiality_share-0.1)<1E-9)," ◂",""),"10%") | N19: =IFERROR((0.1*book_gco),"") | O19: =IFERROR(COUNTIFS(pk_kind,"grids",pk_measure,"gco_rate",pk_dollars,">="&(0.1*book_gco),pk_dollars,">0"),"") | P19: =IFERROR(IF(SUMIFS(pk_dollars,pk_kind,"grids",pk_measure,"gco_rate",pk_dollars,">0")=0,0,SUMIFS(pk_dollars,pk_kind,"grids",pk_measure,"gco_rate",pk_dollars,">="&(0.1*book_gco),pk_dollars,">0")/SUMIFS(pk_dollars,pk_kind,"grids",pk_measure,"gco_rate",pk_dollars,">0")),"")
B20: What a pocket is judged against | C20: The rest of its band | D20: n/a | E20: =IF(NOT($C$33="Where the book bleeds"),"",IF(AND($D$20<>"",$D$20<>"n/a"),$D$20,IF($C$20="","",IF(ISNA(IFERROR(MATCH($G$20&"|"&$C$20,_options!$A:$A,0),MATCH($G$20&"|"&IFERROR(VALUE($C$20),$C$20),_options!$H:$H,0))),"not an option","")))) | F20: The rest of its band | G20: compare_to | J20: =IF(AND($C$33="Where the book bleeds",$C20="",OR($D20="",$D20="n/a")),1,0) | M20: Charge-offs, every grid, against what each pocket is judged against.
M21: A profit shortfall is held to the same dollar line.
B22: ↻ Needs a Run · takes effect when you press Run again | G22: block|run
B23: Setting | C23: Your answer ↻ | D23: Or your own | F23: Last Run used | H23: Status | I23: Worked out from the loans
B24: Fewest loans in a pocket for the usual test (smaller ones get the exact test) | C24: 30 | F24: 30 loans | G24: min_loans | H24: =IF(OR(NOT($C$33="Where the book bleeds"),AND($C$33="Where the book bleeds",$C24="",OR($D24="",$D24="n/a"))),"",IFERROR(IF(IF(AND($D$24<>"",$D$24<>"n/a"),$D$24,$C$24)&""=INDEX(_used!$B:$B,MATCH($G$24,_used!$A:$A,0))&"","Same as last Run","↻ Waiting for a Run"),"")) | I24: suggested: 65, from this extract at the last Run | J24: =IF(AND($C$33="Where the book bleeds",$C24="",OR($D24="",$D24="n/a")),1,0) | K24: =IF($H24="↻ Waiting for a Run",$B24&": "&INDEX(_used!$C:$C,MATCH($G$24,_used!$A:$A,0))&" → "&IF(AND($D$24<>"",$D$24<>"n/a"),$D$24,$C$24)&" (Control C24); ","")
B25: Fewest loans with a loss before a loss rate is tested | C25: 10 | F25: 10 losses | G25: min_events | H25: =IF(OR(NOT($C$33="Where the book bleeds"),AND($C$33="Where the book bleeds",$C25="",OR($D25="",$D25="n/a"))),"",IFERROR(IF(IF(AND($D$25<>"",$D$25<>"n/a"),$D$25,$C$25)&""=INDEX(_used!$B:$B,MATCH($G$25,_used!$A:$A,0))&"","Same as last Run","↻ Waiting for a Run"),"")) | J25: =IF(AND($C$33="Where the book bleeds",$C25="",OR($D25="",$D25="n/a")),1,0) | K25: =IF($H25="↻ Waiting for a Run",$B25&": "&INDEX(_used!$C:$C,MATCH($G$25,_used!$A:$A,0))&" → "&IF(AND($D$25<>"",$D$25<>"n/a"),$D$25,$C$25)&" (Control C25); ","")
B26: How many bands a number column is cut into | C26: 5 bands (recommended) | F26: 5 bands | G26: band_count | H26: =IF(OR(NOT(TRUE),AND(TRUE,$C26="",OR($D26="",$D26="n/a"))),"",IFERROR(IF(IF(AND($D$26<>"",$D$26<>"n/a"),$D$26,$C$26)&""=INDEX(_used!$B:$B,MATCH($G$26,_used!$A:$A,0))&"","Same as last Run","↻ Waiting for a Run"),"")) | J26: =IF(AND(TRUE,$C26="",OR($D26="",$D26="n/a")),1,0) | K26: =IF($H26="↻ Waiting for a Run",$B26&": "&INDEX(_used!$C:$C,MATCH($G$26,_used!$A:$A,0))&" → "&IF(AND($D$26<>"",$D$26<>"n/a"),$D$26,$C$26)&" (Control C26); ","")
B27: Where the band edges fall | C27: Each band holds about the same number of loans (recommended) | D27: n/a | F27: Each band holds about the same number of loans | G27: band_cut | H27: =IF(OR(NOT(TRUE),AND(TRUE,$C27="",OR($D27="",$D27="n/a"))),"",IFERROR(IF(IF(AND($D$27<>"",$D$27<>"n/a"),$D$27,$C$27)&""=INDEX(_used!$B:$B,MATCH($G$27,_used!$A:$A,0))&"","Same as last Run","↻ Waiting for a Run"),"")) | J27: =IF(AND(TRUE,$C27="",OR($D27="",$D27="n/a")),1,0) | K27: =IF($H27="↻ Waiting for a Run",$B27&": "&INDEX(_used!$C:$C,MATCH($G$27,_used!$A:$A,0))&" → "&IF(AND($D$27<>"",$D$27<>"n/a"),$D$27,$C$27)&" (Control C27); ","")
B28: How often a real gap should be caught | C28: 80% of the time (recommended) | F28: 80% of the time | G28: power | H28: =IF(OR(NOT($C$33="Where the book bleeds"),AND($C$33="Where the book bleeds",$C28="",OR($D28="",$D28="n/a"))),"",IFERROR(IF(IF(AND($D$28<>"",$D$28<>"n/a"),$D$28,$C$28)&""=INDEX(_used!$B:$B,MATCH($G$28,_used!$A:$A,0))&"","Same as last Run","↻ Waiting for a Run"),"")) | J28: =IF(AND($C$33="Where the book bleeds",$C28="",OR($D28="",$D28="n/a")),1,0) | K28: =IF($H28="↻ Waiting for a Run",$B28&": "&INDEX(_used!$C:$C,MATCH($G$28,_used!$A:$A,0))&" → "&IF(AND($D$28<>"",$D$28<>"n/a"),$D$28,$C$28)&" (Control C28); ","")
B29: Allowing for testing many pockets at once | C29: Hold down the share of false finds (Benjamini-Hochberg) (recommended) | D29: n/a | F29: Hold down the share of false finds (Benjamini-Hochberg) | G29: many_tests | H29: =IF(OR(NOT(TRUE),AND(TRUE,$C29="",OR($D29="",$D29="n/a"))),"",IFERROR(IF(IF(AND($D$29<>"",$D$29<>"n/a"),$D$29,$C$29)&""=INDEX(_used!$B:$B,MATCH($G$29,_used!$A:$A,0))&"","Same as last Run","↻ Waiting for a Run"),"")) | J29: =IF(AND(TRUE,$C29="",OR($D29="",$D29="n/a")),1,0) | K29: =IF($H29="↻ Waiting for a Run",$B29&": "&INDEX(_used!$C:$C,MATCH($G$29,_used!$A:$A,0))&" → "&IF(AND($D$29<>"",$D$29<>"n/a"),$D$29,$C$29)&" (Control C29); ","")
B30: Loans made before this date find the candidates; the rest are held back | G30: cutoff | H30: =IF(OR(NOT(AND($C$33="Finding and testing a new variable",$C$34="Scout first")),AND(AND($C$33="Finding and testing a new variable",$C$34="Scout first"),$C30="",OR($D30="",$D30="n/a"))),"",IFERROR(IF(IF(AND($D$30<>"",$D$30<>"n/a"),$D$30,$C$30)&""=INDEX(_used!$B:$B,MATCH($G$30,_used!$A:$A,0))&"","Same as last Run","↻ Waiting for a Run"),"")) | I30: suggested: 2024-11-01 (5,641 loans before, 2,359 after) | J30: =IF(AND(AND($C$33="Finding and testing a new variable",$C$34="Scout first"),$C30="",OR($D30="",$D30="n/a")),1,0) | K30: =IF($H30="↻ Waiting for a Run",$B30&": "&INDEX(_used!$C:$C,MATCH($G$30,_used!$A:$A,0))&" → "&IF(AND($D$30<>"",$D$30<>"n/a"),$D$30,$C$30)&" (Control C30); ","")
B32: Chosen in the launcher · read-only here | D32: To change these, go back to Choose tests in the launcher and press Next. | G32: launcher|head
B33: What are you running? | C33: Where the book bleeds | G33: run_kind | H33: =IFERROR(IF(IF(AND($D$33<>"",$D$33<>"n/a"),$D$33,$C$33)&""=INDEX(_used!$B:$B,MATCH($G$33,_used!$A:$A,0))&"","Same as last Run","↻ Waiting for a Run"),"") | K33: =IF($H33="↻ Waiting for a Run",$B33&": "&IF(INDEX(_used!$B:$B,MATCH($G$33,_used!$A:$A,0))&""="","none",INDEX(_used!$B:$B,MATCH($G$33,_used!$A:$A,0)))&" → "&IF(IF(AND($D$33<>"",$D$33<>"n/a"),$D$33,$C$33)&""="","none",IF(AND($D$33<>"",$D$33<>"n/a"),$D$33,$C$33))&" (launcher); ","")
B34: Scout first, or test from a pre-spec already written? | G34: new_variable_step | H34: =IF($H$33="↻ Waiting for a Run","",IFERROR(IF(IF(AND($D$34<>"",$D$34<>"n/a"),$D$34,$C$34)&""=INDEX(_used!$B:$B,MATCH($G$34,_used!$A:$A,0))&"","Same as last Run","↻ Waiting for a Run"),"")) | K34: =IF($H34="↻ Waiting for a Run",$B34&": "&IF(INDEX(_used!$B:$B,MATCH($G$34,_used!$A:$A,0))&""="","none",INDEX(_used!$B:$B,MATCH($G$34,_used!$A:$A,0)))&" → "&IF(IF(AND($D$34<>"",$D$34<>"n/a"),$D$34,$C$34)&""="","none",IF(AND($D$34<>"",$D$34<>"n/a"),$D$34,$C$34))&" (launcher); ","")
B35: Cut into bands | C35: FICO, REV_DEBT | G35: launcher|bands | H35: =IF($H$33="↻ Waiting for a Run","",IFERROR(IF(IF(AND($D$35<>"",$D$35<>"n/a"),$D$35,$C$35)&""=INDEX(_used!$B:$B,MATCH($G$35,_used!$A:$A,0))&"","Same as last Run","↻ Waiting for a Run"),"")) | K35: =IF($H35="↻ Waiting for a Run",$B35&": "&IF(INDEX(_used!$B:$B,MATCH($G$35,_used!$A:$A,0))&""="","none",INDEX(_used!$B:$B,MATCH($G$35,_used!$A:$A,0)))&" → "&IF(IF(AND($D$35<>"",$D$35<>"n/a"),$D$35,$C$35)&""="","none",IF(AND($D$35<>"",$D$35<>"n/a"),$D$35,$C$35))&" (launcher); ","")
B36: Segment by | C36: CHANNEL, ASSET_CLASS | G36: launcher|segments | H36: =IF($H$33="↻ Waiting for a Run","",IFERROR(IF(IF(AND($D$36<>"",$D$36<>"n/a"),$D$36,$C$36)&""=INDEX(_used!$B:$B,MATCH($G$36,_used!$A:$A,0))&"","Same as last Run","↻ Waiting for a Run"),"")) | K36: =IF($H36="↻ Waiting for a Run",$B36&": "&IF(INDEX(_used!$B:$B,MATCH($G$36,_used!$A:$A,0))&""="","none",INDEX(_used!$B:$B,MATCH($G$36,_used!$A:$A,0)))&" → "&IF(IF(AND($D$36<>"",$D$36<>"n/a"),$D$36,$C$36)&""="","none",IF(AND($D$36<>"",$D$36<>"n/a"),$D$36,$C$36))&" (launcher); ","")
B37: Split every pocket by | G37: launcher|split | H37: =IF($H$33="↻ Waiting for a Run","",IFERROR(IF(IF(AND($D$37<>"",$D$37<>"n/a"),$D$37,$C$37)&""=INDEX(_used!$B:$B,MATCH($G$37,_used!$A:$A,0))&"","Same as last Run","↻ Waiting for a Run"),"")) | K37: =IF($H37="↻ Waiting for a Run",$B37&": "&IF(INDEX(_used!$B:$B,MATCH($G$37,_used!$A:$A,0))&""="","none",INDEX(_used!$B:$B,MATCH($G$37,_used!$A:$A,0)))&" → "&IF(IF(AND($D$37<>"",$D$37<>"n/a"),$D$37,$C$37)&""="","none",IF(AND($D$37<>"",$D$37<>"n/a"),$D$37,$C$37))&" (launcher); ","")
B38: Filter the Grids by | C38: ORIG_YEAR | G38: launcher|filter | H38: =IF($H$33="↻ Waiting for a Run","",IFERROR(IF(IF(AND($D$38<>"",$D$38<>"n/a"),$D$38,$C$38)&""=INDEX(_used!$B:$B,MATCH($G$38,_used!$A:$A,0))&"","Same as last Run","↻ Waiting for a Run"),"")) | K38: =IF($H38="↻ Waiting for a Run",$B38&": "&IF(INDEX(_used!$B:$B,MATCH($G$38,_used!$A:$A,0))&""="","none",INDEX(_used!$B:$B,MATCH($G$38,_used!$A:$A,0)))&" → "&IF(IF(AND($D$38<>"",$D$38<>"n/a"),$D$38,$C$38)&""="","none",IF(AND($D$38<>"",$D$38<>"n/a"),$D$38,$C$38))&" (launcher); ","")
B39: Tested against | G39: launcher|outcome | H39: =IF($H$33="↻ Waiting for a Run","",IFERROR(IF(IF(AND($D$39<>"",$D$39<>"n/a"),$D$39,$C$39)&""=INDEX(_used!$B:$B,MATCH($G$39,_used!$A:$A,0))&"","Same as last Run","↻ Waiting for a Run"),"")) | K39: =IF($H39="↻ Waiting for a Run",$B39&": "&IF(INDEX(_used!$B:$B,MATCH($G$39,_used!$A:$A,0))&""="","none",INDEX(_used!$B:$B,MATCH($G$39,_used!$A:$A,0)))&" → "&IF(IF(AND($D$39<>"",$D$39<>"n/a"),$D$39,$C$39)&""="","none",IF(AND($D$39<>"",$D$39<>"n/a"),$D$39,$C$39))&" (launcher); ","")
B40: Inputs tested | G40: launcher|test | H40: =IF($H$33="↻ Waiting for a Run","",IFERROR(IF(IF(AND($D$40<>"",$D$40<>"n/a"),$D$40,$C$40)&""=INDEX(_used!$B:$B,MATCH($G$40,_used!$A:$A,0))&"","Same as last Run","↻ Waiting for a Run"),"")) | K40: =IF($H40="↻ Waiting for a Run",$B40&": "&IF(INDEX(_used!$B:$B,MATCH($G$40,_used!$A:$A,0))&""="","none",INDEX(_used!$B:$B,MATCH($G$40,_used!$A:$A,0)))&" → "&IF(IF(AND($D$40<>"",$D$40<>"n/a"),$D$40,$C$40)&""="","none",IF(AND($D$40<>"",$D$40<>"n/a"),$D$40,$C$40))&" (launcher); ","")
B41: Held fixed | G41: launcher|hold | H41: =IF($H$33="↻ Waiting for a Run","",IFERROR(IF(IF(AND($D$41<>"",$D$41<>"n/a"),$D$41,$C$41)&""=INDEX(_used!$B:$B,MATCH($G$41,_used!$A:$A,0))&"","Same as last Run","↻ Waiting for a Run"),"")) | K41: =IF($H41="↻ Waiting for a Run",$B41&": "&IF(INDEX(_used!$B:$B,MATCH($G$41,_used!$A:$A,0))&""="","none",INDEX(_used!$B:$B,MATCH($G$41,_used!$A:$A,0)))&" → "&IF(IF(AND($D$41<>"",$D$41<>"n/a"),$D$41,$C$41)&""="","none",IF(AND($D$41<>"",$D$41<>"n/a"),$D$41,$C$41))&" (launcher); ","")
B42: Saved shortlist (pre-spec file) | G42: prespec | H42: =IF($H$33="↻ Waiting for a Run","",IFERROR(IF(IF(AND($D$42<>"",$D$42<>"n/a"),$D$42,$C$42)&""=INDEX(_used!$B:$B,MATCH($G$42,_used!$A:$A,0))&"","Same as last Run","↻ Waiting for a Run"),"")) | K42: =IF($H42="↻ Waiting for a Run",$B42&": "&IF(INDEX(_used!$B:$B,MATCH($G$42,_used!$A:$A,0))&""="","none",INDEX(_used!$B:$B,MATCH($G$42,_used!$A:$A,0)))&" → "&IF(IF(AND($D$42<>"",$D$42<>"n/a"),$D$42,$C$42)&""="","none",IF(AND($D$42<>"",$D$42<>"n/a"),$D$42,$C$42))&" (launcher); ","")
B43: Number columns: this many values or fewer is a category; more is cut into bands | C43: 12 values | G43: few_values | H43: =IF($H$33="↻ Waiting for a Run","",IFERROR(IF(IF(AND($D$43<>"",$D$43<>"n/a"),$D$43,$C$43)&""=INDEX(_used!$B:$B,MATCH($G$43,_used!$A:$A,0))&"","Same as last Run","↻ Waiting for a Run"),"")) | K43: =IF($H43="↻ Waiting for a Run",$B43&": "&IF(INDEX(_used!$B:$B,MATCH($G$43,_used!$A:$A,0))&""="","none",INDEX(_used!$B:$B,MATCH($G$43,_used!$A:$A,0)))&" → "&IF(IF(AND($D$43<>"",$D$43<>"n/a"),$D$43,$C$43)&""="","none",IF(AND($D$43<>"",$D$43<>"n/a"),$D$43,$C$43))&" (launcher); ","")
B44: Text columns: more values than this is too many to cut by (text is never cut into bands) | C44: 50 values | G44: many_values | H44: =IF($H$33="↻ Waiting for a Run","",IFERROR(IF(IF(AND($D$44<>"",$D$44<>"n/a"),$D$44,$C$44)&""=INDEX(_used!$B:$B,MATCH($G$44,_used!$A:$A,0))&"","Same as last Run","↻ Waiting for a Run"),"")) | K44: =IF($H44="↻ Waiting for a Run",$B44&": "&IF(INDEX(_used!$B:$B,MATCH($G$44,_used!$A:$A,0))&""="","none",INDEX(_used!$B:$B,MATCH($G$44,_used!$A:$A,0)))&" → "&IF(IF(AND($D$44<>"",$D$44<>"n/a"),$D$44,$C$44)&""="","none",IF(AND($D$44<>"",$D$44<>"n/a"),$D$44,$C$44))&" (launcher); ","")

Sheet Columns
B1: Columns | C1: What each column means, what looks odd in it, and what PocketBook remembers about it.
B3: Checked every column? | C3: Yes | D3: Run won't start until this is Yes.
B5: How this tab works
B6: What it is | C6: Set up guesses each column's meaning from its name and values; the reason is beside it. Fix any that's wrong. Confirmed meanings are remembered for the next extract.
B7: Odd values | C7: Values that may be codes rather than real numbers: one value far more often than any other, or negatives in a column that's mostly positive. Missing is treated as blank and counted.
B8: Treat as | C8: Answer Real or Missing. One left blank is used as recorded.
B9: Band edges | C9: Blank means Control's setting. Type edges as 620; 680; 740, or every 20. Look shows what each would cut, live.
B10: Remembered | C10: Set Forget? to Yes to drop what was learned about a column at the next Run. It then waits here for you to confirm it again. Answers marked ↻ take effect at the next Run.
B12: Column | C12: Samples | D12: What it is ↻ | E12: Why we think so | F12: Blank | G12: Odd values | H12: Treat as ↻ | I12: Band edges ↻ | J12: Remembered | K12: Forget? ↻ | L12: Check first | M12: Yes means ↻ | N12: Show per pocket ↻ | O12: Period ↻ | P12: In your words
B13: LOAN_NBR | C13: L0000000, L0000001, L0000002 | D13: Loan number (key) | E13: name contains 'loan'; a different value on every row | F13: 0 | J13: Yes · 1 Run | K13: No | Q13: key
B14: FICO | C14: -9999, 713, 716 | D14: FICO score | E14: name contains 'fico'; 98% of values between 300 and 850 | F14: 0.000125 | G14: -9999 on 160 loans | H14: Missing | J14: Yes · 1 Run | K14: No | Q14: fico | S14: FICO|repeated_value|-9999.0
B15: CHANNEL | C15: Online, Broker, Branch | D15: Category | E15: 3 different values | F15: 0 | J15: Yes · 1 Run | K15: No | L15: suggested as Category from its shape alone (3 different values). If it's something more specific, say so and it will be remembered. | Q15: category
B16: ORIG_BAL | C16: 7655.75, 27999.47, 39684.43 | D16: Booked amount | E16: name contains 'bal'; positive on every loan | F16: 0.000125 | J16: Yes · 1 Run | K16: No | Q16: booked
B17: BAD_FLAG | C17: 0, 2, 1 | D17: Outcome (yes/no) | E17: picked and confirmed in the launcher as the outcome | F17: 0 | J17: Yes · 1 Run | K17: No | L17: 1 value is neither 0 nor 1. They're left out of the outcome rates and counted; if they mean something, fix the extract. | Q17: outcome
B18: GCO_AMT | C18: 0.0, #N/A, 27620.62 | D18: GCO dollars | E18: name contains 'gco'; zero on 92% of loans, never negative | F18: 0 | J18: Yes · 1 Run | K18: No | L18: 1 value isn't a number among 7,999 that are. They're left out of any rate using this column and counted. | Q18: gco
B19: RANR_AMT | C19: 3017.35, 3928.24, 5816.98 | D19: RANR dollars | E19: name contains 'ranr'; numbers | F19: 0 | G19: Negative on 595 loans | J19: Yes · 1 Run | K19: No | Q19: ranr | S19: RANR_AMT|negatives|
B20: ASSET_CLASS | C20: 1, 2, 4 | D20: Category | E20: 4 different values | F20: 0 | J20: Yes · 1 Run | K20: No | L20: suggested as Category from its shape alone (4 different values). If it's something more specific, say so and it will be remembered. | Q20: category
B21: REV_DEBT | C21: 15868.86, 12884.7, 8920.97 | D21: Amount or number | E21: numbers with 7,889 values | F21: 0 | J21: Yes · 1 Run | K21: No | L21: suggested as Amount or number from its shape alone (numbers with 7,889 values). If it's something more specific, say so and it will be remembered. | Q21: amount
B22: ORIG_DATE | C22: 2021-11-18, 2024-06-24, 2023-07-12 | D22: Origination date | E22: name contains 'orig'; dates | F22: 0 | J22: Yes · 1 Run | K22: No | Q22: origination_date
S23: table|end
B25: Add a column: one divided by another | S25: derived|head
B26: Shows here and on Look, and in Choose tests, once you press Set up again. Blank where the bottom is zero or blank. | S26: derived|note
B27: New column name ↻ | C27: Top (divided) | D27: Bottom (divided by) | E27: What it makes | S27: derived|cols
E28: =IF(COUNTA(B28:D28)=0,"",IF(COUNTA(B28:D28)<3,"Needs a name, a top and a bottom.",B28&" = "&C28&" ÷ "&D28&" on each loan.")) | S28: derived|1
E29: =IF(COUNTA(B29:D29)=0,"",IF(COUNTA(B29:D29)<3,"Needs a name, a top and a bottom.",B29&" = "&C29&" ÷ "&D29&" on each loan.")) | S29: derived|2
E30: =IF(COUNTA(B30:D30)=0,"",IF(COUNTA(B30:D30)<3,"Needs a name, a top and a bottom.",B30&" = "&C30&" ÷ "&D30&" on each loan.")) | S30: derived|3

Sheet Look
B1: Look | C1: Each number column before you choose its band edges.
B3: How this tab works
B4: The bars | C4: How many loans fall in each step between From and To. Pick 10, 20 or 50 bars and change the range; the chart follows. The grey bar at each end holds the loans outside the range.
B5: The red bar | C5: A value that looks like a code, such as a score of -9999, gets a red bar of its own left of the chart, so it doesn't flatten the rest. Columns asks whether it means missing.
B6: The lines | C6: Red dashed: the band edges typed on Columns. They follow that tab as you type, so you can try edges here before the next Run; blank edges are cut at the Run, so no lines show. Grey: the 10th, 25th, 50th, 75th and 90th percentile, P10 to P90. A tenth of the loans on the chart lie below P10, half below P50 (the median). Worked out as Excel's PERCENTILE.INC does.
B7: How it counts | C7: Set up counts each column once, in 200 equal slices around its 1st to 99th percentile. A range you type is counted to the nearest slice.
B8: The dots | C8: The split column against each band column: a random 2,000 loans, the same every time. If the dots slope, the two move together, and part of a gap on Split may belong to the band column.
B10: FICO | H10: =IF('_look'!$F$20="","FICO · no edges on Columns yet","FICO · edges now "&'_look'!$F$20)
B11: Loans | C11: 8000
B12: Blank | C12: 1 | D12: 0.000125
B13: Not a number | C13: 0 | D13: 0
B14: Likely a code | C14: none found
B15: Smallest | C15: 496
B16: Median | C16: 699
B17: Mean | C17: 699.75099
B18: Largest | C18: 921
B19: Answered missing, left out | C19: 160 | D19: 0.02
B20: Bars | C20: 20
B21: From | C21: 550
B22: To | C22: 850
B24: 10th percentile (P10) | C24: 629
B25: 25th percentile (P25) | C25: 663
B26: 50th percentile (P50), the median | C26: 699
B27: 75th percentile (P75) | C27: 736
B28: 90th percentile (P90) | C28: 772
B30: ORIG_BAL | H30: =IF('_look'!$S$20="","ORIG_BAL · no edges on Columns yet","ORIG_BAL · edges now "&'_look'!$S$20)
B31: Loans | C31: 8000
B32: Blank | C32: 1 | D32: 0.000125
B33: Not a number | C33: 0 | D33: 0
B34: Likely a code | C34: none found
B35: Smallest | C35: 5005.32
B36: Median | C36: 32112.83
B37: Mean | C37: 32262.589
B38: Largest | C38: 59983.86
B40: Bars | C40: 20
B41: From | C41: 0
B42: To | C42: 60000
B44: 10th percentile (P10) | C44: 10110.416
B45: 25th percentile (P25) | C45: 18191.43
B46: 50th percentile (P50), the median | C46: 32112.83
B47: 75th percentile (P75) | C47: 46264.885
B48: 90th percentile (P90) | C48: 54495.472
B50: REV_DEBT | H50: =IF('_look'!$AF$20="","REV_DEBT · no edges on Columns yet","REV_DEBT · edges now "&'_look'!$AF$20)
B51: Loans | C51: 8000
B52: Blank | C52: 0 | D52: 0
B53: Not a number | C53: 0 | D53: 0
B54: Likely a code | C54: none found
B55: Smallest | C55: 0
B56: Median | C56: 11392.84
B57: Mean | C57: 12064.483
B58: Largest | C58: 48521.79
B60: Bars | C60: 20
B61: From | C61: 0
B62: To | C62: 30000
B64: 10th percentile (P10) | C64: 4382.994
B65: 25th percentile (P25) | C65: 7384.4825
B66: 50th percentile (P50), the median | C66: 11392.84
B67: 75th percentile (P75) | C67: 15940.795
B68: 90th percentile (P90) | C68: 20607.534
B70: Scatters
B71: None: nothing splits the pockets. Pick a column to split by in the launcher's Choose tests; a scatter of it against each band column shows here.

Sheet Pockets
C1: Pockets | D1: Which pockets lose more than their share, how much, and whether it's real and big enough to matter.
C3: How this tab works
C4: A pocket | D4: One band of one column crossed with one segment of another, in every grid chosen in the launcher. Loans: how many are in it.
C5: Rest of band | D5: ="Every other loan in the same band. Judged against on Control picks it or the rest of the book (every other loan in the book); now "&IF(judged_band,"the rest of its band","the rest of the book")&". It decides the gap, the excess and both verdicts. A pocket alone in its band has nothing beside it to compare with, so it is judged against the rest of the book, whatever Control says."
C6: Excess | D6: What the pocket lost above what it would have lost at the rest's rate: bad loans for Bad loans, dollars for the dollar measures. For Kept after losses and Earned before losses, the dollars it fell short of the rest, and the gap is in points of booked dollars.
C7: Worse? | D7: ="Yes: at least "&TEXT(worse_at,"0.00")&"x the rest"&" (for profit, short of it by the profit line on Control)"&", with a p-value under "&TEXT(significance_bar,"0%")&". Not sure: the gap is there, but the p-value isn't under it. Too few losses: fewer than "&"10 (a setting for the next Run), so not tested. No: anything else."
C8: p-value | D8: ="The chance of a gap at least this big if the pocket were no different from the rest, after the allowance for testing many pockets at once (Benjamini-Hochberg, across one grid and one measure). Bad loans: the z test, or the exact test for a pocket und"&"er 30 loans. Dollar measures: the loans are shuffled 200 times, within the band for the rest of its band, and it is how often a gap as big turned up."&" Under "&TEXT(significance_bar,"0%")&" counts."&" Borderline: the test's p-value is within the shuffle's own margin of the "&TEXT(significance_bar,"0%")&" bar, so another run could read it the other way."
C9: Material? | D9: Yes when the excess reaches the materiality line on Control (the Material at tile, in the measure's own unit). It is judged apart from Worse?: a pocket can be one without the other.
C10: Could have caught | D10: The smallest gap a pocket this size would catch 80% of the time at the last Run's confidence. As of the last Run.
C11: Order | D11: Sorted as of the last Run: worse pockets first, largest excess first, then the rest by their excess. Last come pockets losing more only against the other comparison, so that changing Judged against on Control finds them here. A change on Control updates Worse?, Material?, the dollars and the colours at once, not the order. The caption counts what the dropdowns pick.
C13: LINES IN USE NOW | D13: Worse at | E13: Better at | F13: How sure | H13: Material at | J13: Judged against | K13: Order and "Could have caught" are from the last Run, 2026-09-30 15:23.
C14: live from Control | D14: =worse_at | E14: =better_at | F14: =confidence | H14: =IFERROR(IF(materiality_kind="none","No floor",IF(INDEX(line_values,MATCH($U$17,line_keys,0))="","No line",IF($U$19,TEXT(INDEX(line_values,MATCH($U$17,line_keys,0)),"#,##0.0")&" bad loans","$"&TEXT(INDEX(line_values,MATCH($U$17,line_keys,0)),"#,##0")))),"") | J14: =IF(judged_band,"Rest of its band","Rest of the book") | K14: =IFERROR(IF(COUNTIF(Status,"↻ Waiting for a Run")=0,"","↻ "&COUNTIF(Status,"↻ Waiting for a Run")&IF(COUNTIF(Status,"↻ Waiting for a Run")=1," Control change waits for a Run."," Control changes wait for a Run.")),"")
C16: MEASURE | D16: POCKETS | E16: SHOW
C17: Bad loans | D17: Two-way | E17: All | F17: =IFERROR(COUNTIFS('_list'!$A$2:$A$246,'Pockets'!$D$17,'_list'!$B$2:$B$246,'Pockets'!$C$17,'_list'!$K$2:$K$246,"Yes",'_list'!$L$2:$L$246,"Yes")&" worse and material · "&COUNTIFS('_list'!$A$2:$A$246,'Pockets'!$D$17,'_list'!$B$2:$B$246,'Pockets'!$C$17,'_list'!$K$2:$K$246,"Yes")&" worse · "&SUM('_list'!$M$2:$M$246)&" shown","") | U17: =IFERROR(INDEX('_choices'!$B$2:$B$6,MATCH('Pockets'!$C$17,'_choices'!$A$2:$A$6,0)),"")
U18: =IFERROR(INDEX('_choices'!$C$2:$C$6,MATCH('Pockets'!$C$17,'_choices'!$A$2:$A$6,0))=1,FALSE)
B19: # | C19: Band | D19: Segment | F19: Loans | G19: This pocket | H19: =IF(judged_band,"Rest of band","Rest of book") | I19: =IF($U$18,"Gap in pts",IF(judged_band,"× rest of band","× rest of book")) | J19: =IF($U$19,"Bad loans above share",IF($U$18,IF(judged_band,"Dollars short of band","Dollars short of book"),"Dollars above share")) | K19: Worse? | L19: p-value | M19: Material? | N19: Could have caught | U19: =IFERROR(INDEX('_choices'!$D$2:$D$6,MATCH('Pockets'!$C$17,'_choices'!$A$2:$A$6,0))=1,FALSE)
B20: =IF($R20="","",1) | C20: =IF($R20="","",IF(INDEX('_list'!$D$2:$D$246,$R20)="","",INDEX('_list'!$D$2:$D$246,$R20))) | D20: =IF($R20="","",IF(INDEX('_list'!$E$2:$E$246,$R20)="","",INDEX('_list'!$E$2:$E$246,$R20))) | E20: =IF($R20="","",IF(INDEX('_list'!$F$2:$F$246,$R20)="","",INDEX('_list'!$F$2:$F$246,$R20))) | F20: =IF($R20="","",IF(INDEX('_list'!$G$2:$G$246,$R20)="","",INDEX('_list'!$G$2:$G$246,$R20))) | G20: =IF($S20="","",IF(INDEX('_pockets'!$AH:$AH,$S20)="","",INDEX('_pockets'!$AH:$AH,$S20))) | H20: =IF($S20="","",IF(INDEX('_pockets'!$AF:$AF,$S20)="","",INDEX('_pockets'!$AF:$AF,$S20))) | I20: =IF(IF($S20="","",IF(INDEX('_pockets'!$AB:$AB,$S20)="","",INDEX('_pockets'!$AB:$AB,$S20)))="","",IF($S20="","",IF(INDEX('_pockets'!$AB:$AB,$S20)="","",INDEX('_pockets'!$AB:$AB,$S20)))*IF($U$18,100,1)) | J20: =IF($S20="","",IF(INDEX('_pockets'!$Z:$Z,$S20)="","",INDEX('_pockets'!$Z:$Z,$S20))) | K20: =IF($S20="","",IF(INDEX('_pockets'!$AO:$AO,$S20)="","",INDEX('_pockets'!$AO:$AO,$S20))) | L20: =IF($S20="","",IF(INDEX('_pockets'!$AC:$AC,$S20)="","",INDEX('_pockets'!$AC:$AC,$S20))) | M20: =IF($R20="","",IF(INDEX('_list'!$L$2:$L$246,$R20)="","",INDEX('_list'!$L$2:$L$246,$R20))) | N20: =IF($R20="","",IF(INDEX('_list'!$H$2:$H$246,$R20)="","",INDEX('_list'!$H$2:$H$246,$R20))) | O20: =IF($R20="","",IF(INDEX('_list'!$I$2:$I$246,$R20)="","",INDEX('_list'!$I$2:$I$246,$R20))) | R20: =IFERROR(MATCH(1,'_list'!$N$2:$N$246,0),"") | S20: =IF($R20="","",INDEX('_list'!$C$2:$C$246,$R20))
B21: =IF($R21="","",2) | C21: =IF($R21="","",IF(INDEX('_list'!$D$2:$D$246,$R21)="","",INDEX('_list'!$D$2:$D$246,$R21))) | D21: =IF($R21="","",IF(INDEX('_list'!$E$2:$E$246,$R21)="","",INDEX('_list'!$E$2:$E$246,$R21))) | E21: =IF($R21="","",IF(INDEX('_list'!$F$2:$F$246,$R21)="","",INDEX('_list'!$F$2:$F$246,$R21))) | F21: =IF($R21="","",IF(INDEX('_list'!$G$2:$G$246,$R21)="","",INDEX('_list'!$G$2:$G$246,$R21))) | G21: =IF($S21="","",IF(INDEX('_pockets'!$AH:$AH,$S21)="","",INDEX('_pockets'!$AH:$AH,$S21))) | H21: =IF($S21="","",IF(INDEX('_pockets'!$AF:$AF,$S21)="","",INDEX('_pockets'!$AF:$AF,$S21))) | I21: =IF(IF($S21="","",IF(INDEX('_pockets'!$AB:$AB,$S21)="","",INDEX('_pockets'!$AB:$AB,$S21)))="","",IF($S21="","",IF(INDEX('_pockets'!$AB:$AB,$S21)="","",INDEX('_pockets'!$AB:$AB,$S21)))*IF($U$18,100,1)) | J21: =IF($S21="","",IF(INDEX('_pockets'!$Z:$Z,$S21)="","",INDEX('_pockets'!$Z:$Z,$S21))) | K21: =IF($S21="","",IF(INDEX('_pockets'!$AO:$AO,$S21)="","",INDEX('_pockets'!$AO:$AO,$S21))) | L21: =IF($S21="","",IF(INDEX('_pockets'!$AC:$AC,$S21)="","",INDEX('_pockets'!$AC:$AC,$S21))) | M21: =IF($R21="","",IF(INDEX('_list'!$L$2:$L$246,$R21)="","",INDEX('_list'!$L$2:$L$246,$R21))) | N21: =IF($R21="","",IF(INDEX('_list'!$H$2:$H$246,$R21)="","",INDEX('_list'!$H$2:$H$246,$R21))) | O21: =IF($R21="","",IF(INDEX('_list'!$I$2:$I$246,$R21)="","",INDEX('_list'!$I$2:$I$246,$R21))) | R21: =IFERROR(MATCH(2,'_list'!$N$2:$N$246,0),"") | S21: =IF($R21="","",INDEX('_list'!$C$2:$C$246,$R21))
B22: =IF($R22="","",3) | C22: =IF($R22="","",IF(INDEX('_list'!$D$2:$D$246,$R22)="","",INDEX('_list'!$D$2:$D$246,$R22))) | D22: =IF($R22="","",IF(INDEX('_list'!$E$2:$E$246,$R22)="","",INDEX('_list'!$E$2:$E$246,$R22))) | E22: =IF($R22="","",IF(INDEX('_list'!$F$2:$F$246,$R22)="","",INDEX('_list'!$F$2:$F$246,$R22))) | F22: =IF($R22="","",IF(INDEX('_list'!$G$2:$G$246,$R22)="","",INDEX('_list'!$G$2:$G$246,$R22))) | G22: =IF($S22="","",IF(INDEX('_pockets'!$AH:$AH,$S22)="","",INDEX('_pockets'!$AH:$AH,$S22))) | H22: =IF($S22="","",IF(INDEX('_pockets'!$AF:$AF,$S22)="","",INDEX('_pockets'!$AF:$AF,$S22))) | I22: =IF(IF($S22="","",IF(INDEX('_pockets'!$AB:$AB,$S22)="","",INDEX('_pockets'!$AB:$AB,$S22)))="","",IF($S22="","",IF(INDEX('_pockets'!$AB:$AB,$S22)="","",INDEX('_pockets'!$AB:$AB,$S22)))*IF($U$18,100,1)) | J22: =IF($S22="","",IF(INDEX('_pockets'!$Z:$Z,$S22)="","",INDEX('_pockets'!$Z:$Z,$S22))) | K22: =IF($S22="","",IF(INDEX('_pockets'!$AO:$AO,$S22)="","",INDEX('_pockets'!$AO:$AO,$S22))) | L22: =IF($S22="","",IF(INDEX('_pockets'!$AC:$AC,$S22)="","",INDEX('_pockets'!$AC:$AC,$S22))) | M22: =IF($R22="","",IF(INDEX('_list'!$L$2:$L$246,$R22)="","",INDEX('_list'!$L$2:$L$246,$R22))) | N22: =IF($R22="","",IF(INDEX('_list'!$H$2:$H$246,$R22)="","",INDEX('_list'!$H$2:$H$246,$R22))) | O22: =IF($R22="","",IF(INDEX('_list'!$I$2:$I$246,$R22)="","",INDEX('_list'!$I$2:$I$246,$R22))) | R22: =IFERROR(MATCH(3,'_list'!$N$2:$N$246,0),"") | S22: =IF($R22="","",INDEX('_list'!$C$2:$C$246,$R22))
B23: =IF($R23="","",4) | C23: =IF($R23="","",IF(INDEX('_list'!$D$2:$D$246,$R23)="","",INDEX('_list'!$D$2:$D$246,$R23))) | D23: =IF($R23="","",IF(INDEX('_list'!$E$2:$E$246,$R23)="","",INDEX('_list'!$E$2:$E$246,$R23))) | E23: =IF($R23="","",IF(INDEX('_list'!$F$2:$F$246,$R23)="","",INDEX('_list'!$F$2:$F$246,$R23))) | F23: =IF($R23="","",IF(INDEX('_list'!$G$2:$G$246,$R23)="","",INDEX('_list'!$G$2:$G$246,$R23))) | G23: =IF($S23="","",IF(INDEX('_pockets'!$AH:$AH,$S23)="","",INDEX('_pockets'!$AH:$AH,$S23))) | H23: =IF($S23="","",IF(INDEX('_pockets'!$AF:$AF,$S23)="","",INDEX('_pockets'!$AF:$AF,$S23))) | I23: =IF(IF($S23="","",IF(INDEX('_pockets'!$AB:$AB,$S23)="","",INDEX('_pockets'!$AB:$AB,$S23)))="","",IF($S23="","",IF(INDEX('_pockets'!$AB:$AB,$S23)="","",INDEX('_pockets'!$AB:$AB,$S23)))*IF($U$18,100,1)) | J23: =IF($S23="","",IF(INDEX('_pockets'!$Z:$Z,$S23)="","",INDEX('_pockets'!$Z:$Z,$S23))) | K23: =IF($S23="","",IF(INDEX('_pockets'!$AO:$AO,$S23)="","",INDEX('_pockets'!$AO:$AO,$S23))) | L23: =IF($S23="","",IF(INDEX('_pockets'!$AC:$AC,$S23)="","",INDEX('_pockets'!$AC:$AC,$S23))) | M23: =IF($R23="","",IF(INDEX('_list'!$L$2:$L$246,$R23)="","",INDEX('_list'!$L$2:$L$246,$R23))) | N23: =IF($R23="","",IF(INDEX('_list'!$H$2:$H$246,$R23)="","",INDEX('_list'!$H$2:$H$246,$R23))) | O23: =IF($R23="","",IF(INDEX('_list'!$I$2:$I$246,$R23)="","",INDEX('_list'!$I$2:$I$246,$R23))) | R23: =IFERROR(MATCH(4,'_list'!$N$2:$N$246,0),"") | S23: =IF($R23="","",INDEX('_list'!$C$2:$C$246,$R23))
B24: =IF($R24="","",5) | C24: =IF($R24="","",IF(INDEX('_list'!$D$2:$D$246,$R24)="","",INDEX('_list'!$D$2:$D$246,$R24))) | D24: =IF($R24="","",IF(INDEX('_list'!$E$2:$E$246,$R24)="","",INDEX('_list'!$E$2:$E$246,$R24))) | E24: =IF($R24="","",IF(INDEX('_list'!$F$2:$F$246,$R24)="","",INDEX('_list'!$F$2:$F$246,$R24))) | F24: =IF($R24="","",IF(INDEX('_list'!$G$2:$G$246,$R24)="","",INDEX('_list'!$G$2:$G$246,$R24))) | G24: =IF($S24="","",IF(INDEX('_pockets'!$AH:$AH,$S24)="","",INDEX('_pockets'!$AH:$AH,$S24))) | H24: =IF($S24="","",IF(INDEX('_pockets'!$AF:$AF,$S24)="","",INDEX('_pockets'!$AF:$AF,$S24))) | I24: =IF(IF($S24="","",IF(INDEX('_pockets'!$AB:$AB,$S24)="","",INDEX('_pockets'!$AB:$AB,$S24)))="","",IF($S24="","",IF(INDEX('_pockets'!$AB:$AB,$S24)="","",INDEX('_pockets'!$AB:$AB,$S24)))*IF($U$18,100,1)) | J24: =IF($S24="","",IF(INDEX('_pockets'!$Z:$Z,$S24)="","",INDEX('_pockets'!$Z:$Z,$S24))) | K24: =IF($S24="","",IF(INDEX('_pockets'!$AO:$AO,$S24)="","",INDEX('_pockets'!$AO:$AO,$S24))) | L24: =IF($S24="","",IF(INDEX('_pockets'!$AC:$AC,$S24)="","",INDEX('_pockets'!$AC:$AC,$S24))) | M24: =IF($R24="","",IF(INDEX('_list'!$L$2:$L$246,$R24)="","",INDEX('_list'!$L$2:$L$246,$R24))) | N24: =IF($R24="","",IF(INDEX('_list'!$H$2:$H$246,$R24)="","",INDEX('_list'!$H$2:$H$246,$R24))) | O24: =IF($R24="","",IF(INDEX('_list'!$I$2:$I$246,$R24)="","",INDEX('_list'!$I$2:$I$246,$R24))) | R24: =IFERROR(MATCH(5,'_list'!$N$2:$N$246,0),"") | S24: =IF($R24="","",INDEX('_list'!$C$2:$C$246,$R24))
B25: =IF($R25="","",6) | C25: =IF($R25="","",IF(INDEX('_list'!$D$2:$D$246,$R25)="","",INDEX('_list'!$D$2:$D$246,$R25))) | D25: =IF($R25="","",IF(INDEX('_list'!$E$2:$E$246,$R25)="","",INDEX('_list'!$E$2:$E$246,$R25))) | E25: =IF($R25="","",IF(INDEX('_list'!$F$2:$F$246,$R25)="","",INDEX('_list'!$F$2:$F$246,$R25))) | F25: =IF($R25="","",IF(INDEX('_list'!$G$2:$G$246,$R25)="","",INDEX('_list'!$G$2:$G$246,$R25))) | G25: =IF($S25="","",IF(INDEX('_pockets'!$AH:$AH,$S25)="","",INDEX('_pockets'!$AH:$AH,$S25))) | H25: =IF($S25="","",IF(INDEX('_pockets'!$AF:$AF,$S25)="","",INDEX('_pockets'!$AF:$AF,$S25))) | I25: =IF(IF($S25="","",IF(INDEX('_pockets'!$AB:$AB,$S25)="","",INDEX('_pockets'!$AB:$AB,$S25)))="","",IF($S25="","",IF(INDEX('_pockets'!$AB:$AB,$S25)="","",INDEX('_pockets'!$AB:$AB,$S25)))*IF($U$18,100,1)) | J25: =IF($S25="","",IF(INDEX('_pockets'!$Z:$Z,$S25)="","",INDEX('_pockets'!$Z:$Z,$S25))) | K25: =IF($S25="","",IF(INDEX('_pockets'!$AO:$AO,$S25)="","",INDEX('_pockets'!$AO:$AO,$S25))) | L25: =IF($S25="","",IF(INDEX('_pockets'!$AC:$AC,$S25)="","",INDEX('_pockets'!$AC:$AC,$S25))) | M25: =IF($R25="","",IF(INDEX('_list'!$L$2:$L$246,$R25)="","",INDEX('_list'!$L$2:$L$246,$R25))) | N25: =IF($R25="","",IF(INDEX('_list'!$H$2:$H$246,$R25)="","",INDEX('_list'!$H$2:$H$246,$R25))) | O25: =IF($R25="","",IF(INDEX('_list'!$I$2:$I$246,$R25)="","",INDEX('_list'!$I$2:$I$246,$R25))) | R25: =IFERROR(MATCH(6,'_list'!$N$2:$N$246,0),"") | S25: =IF($R25="","",INDEX('_list'!$C$2:$C$246,$R25))
B26: =IF($R26="","",7) | C26: =IF($R26="","",IF(INDEX('_list'!$D$2:$D$246,$R26)="","",INDEX('_list'!$D$2:$D$246,$R26))) | D26: =IF($R26="","",IF(INDEX('_list'!$E$2:$E$246,$R26)="","",INDEX('_list'!$E$2:$E$246,$R26))) | E26: =IF($R26="","",IF(INDEX('_list'!$F$2:$F$246,$R26)="","",INDEX('_list'!$F$2:$F$246,$R26))) | F26: =IF($R26="","",IF(INDEX('_list'!$G$2:$G$246,$R26)="","",INDEX('_list'!$G$2:$G$246,$R26))) | G26: =IF($S26="","",IF(INDEX('_pockets'!$AH:$AH,$S26)="","",INDEX('_pockets'!$AH:$AH,$S26))) | H26: =IF($S26="","",IF(INDEX('_pockets'!$AF:$AF,$S26)="","",INDEX('_pockets'!$AF:$AF,$S26))) | I26: =IF(IF($S26="","",IF(INDEX('_pockets'!$AB:$AB,$S26)="","",INDEX('_pockets'!$AB:$AB,$S26)))="","",IF($S26="","",IF(INDEX('_pockets'!$AB:$AB,$S26)="","",INDEX('_pockets'!$AB:$AB,$S26)))*IF($U$18,100,1)) | J26: =IF($S26="","",IF(INDEX('_pockets'!$Z:$Z,$S26)="","",INDEX('_pockets'!$Z:$Z,$S26))) | K26: =IF($S26="","",IF(INDEX('_pockets'!$AO:$AO,$S26)="","",INDEX('_pockets'!$AO:$AO,$S26))) | L26: =IF($S26="","",IF(INDEX('_pockets'!$AC:$AC,$S26)="","",INDEX('_pockets'!$AC:$AC,$S26))) | M26: =IF($R26="","",IF(INDEX('_list'!$L$2:$L$246,$R26)="","",INDEX('_list'!$L$2:$L$246,$R26))) | N26: =IF($R26="","",IF(INDEX('_list'!$H$2:$H$246,$R26)="","",INDEX('_list'!$H$2:$H$246,$R26))) | O26: =IF($R26="","",IF(INDEX('_list'!$I$2:$I$246,$R26)="","",INDEX('_list'!$I$2:$I$246,$R26))) | R26: =IFERROR(MATCH(7,'_list'!$N$2:$N$246,0),"") | S26: =IF($R26="","",INDEX('_list'!$C$2:$C$246,$R26))
B27: =IF($R27="","",8) | C27: =IF($R27="","",IF(INDEX('_list'!$D$2:$D$246,$R27)="","",INDEX('_list'!$D$2:$D$246,$R27))) | D27: =IF($R27="","",IF(INDEX('_list'!$E$2:$E$246,$R27)="","",INDEX('_list'!$E$2:$E$246,$R27))) | E27: =IF($R27="","",IF(INDEX('_list'!$F$2:$F$246,$R27)="","",INDEX('_list'!$F$2:$F$246,$R27))) | F27: =IF($R27="","",IF(INDEX('_list'!$G$2:$G$246,$R27)="","",INDEX('_list'!$G$2:$G$246,$R27))) | G27: =IF($S27="","",IF(INDEX('_pockets'!$AH:$AH,$S27)="","",INDEX('_pockets'!$AH:$AH,$S27))) | H27: =IF($S27="","",IF(INDEX('_pockets'!$AF:$AF,$S27)="","",INDEX('_pockets'!$AF:$AF,$S27))) | I27: =IF(IF($S27="","",IF(INDEX('_pockets'!$AB:$AB,$S27)="","",INDEX('_pockets'!$AB:$AB,$S27)))="","",IF($S27="","",IF(INDEX('_pockets'!$AB:$AB,$S27)="","",INDEX('_pockets'!$AB:$AB,$S27)))*IF($U$18,100,1)) | J27: =IF($S27="","",IF(INDEX('_pockets'!$Z:$Z,$S27)="","",INDEX('_pockets'!$Z:$Z,$S27))) | K27: =IF($S27="","",IF(INDEX('_pockets'!$AO:$AO,$S27)="","",INDEX('_pockets'!$AO:$AO,$S27))) | L27: =IF($S27="","",IF(INDEX('_pockets'!$AC:$AC,$S27)="","",INDEX('_pockets'!$AC:$AC,$S27))) | M27: =IF($R27="","",IF(INDEX('_list'!$L$2:$L$246,$R27)="","",INDEX('_list'!$L$2:$L$246,$R27))) | N27: =IF($R27="","",IF(INDEX('_list'!$H$2:$H$246,$R27)="","",INDEX('_list'!$H$2:$H$246,$R27))) | O27: =IF($R27="","",IF(INDEX('_list'!$I$2:$I$246,$R27)="","",INDEX('_list'!$I$2:$I$246,$R27))) | R27: =IFERROR(MATCH(8,'_list'!$N$2:$N$246,0),"") | S27: =IF($R27="","",INDEX('_list'!$C$2:$C$246,$R27))
B28: =IF($R28="","",9) | C28: =IF($R28="","",IF(INDEX('_list'!$D$2:$D$246,$R28)="","",INDEX('_list'!$D$2:$D$246,$R28))) | D28: =IF($R28="","",IF(INDEX('_list'!$E$2:$E$246,$R28)="","",INDEX('_list'!$E$2:$E$246,$R28))) | E28: =IF($R28="","",IF(INDEX('_list'!$F$2:$F$246,$R28)="","",INDEX('_list'!$F$2:$F$246,$R28))) | F28: =IF($R28="","",IF(INDEX('_list'!$G$2:$G$246,$R28)="","",INDEX('_list'!$G$2:$G$246,$R28))) | G28: =IF($S28="","",IF(INDEX('_pockets'!$AH:$AH,$S28)="","",INDEX('_pockets'!$AH:$AH,$S28))) | H28: =IF($S28="","",IF(INDEX('_pockets'!$AF:$AF,$S28)="","",INDEX('_pockets'!$AF:$AF,$S28))) | I28: =IF(IF($S28="","",IF(INDEX('_pockets'!$AB:$AB,$S28)="","",INDEX('_pockets'!$AB:$AB,$S28)))="","",IF($S28="","",IF(INDEX('_pockets'!$AB:$AB,$S28)="","",INDEX('_pockets'!$AB:$AB,$S28)))*IF($U$18,100,1)) | J28: =IF($S28="","",IF(INDEX('_pockets'!$Z:$Z,$S28)="","",INDEX('_pockets'!$Z:$Z,$S28))) | K28: =IF($S28="","",IF(INDEX('_pockets'!$AO:$AO,$S28)="","",INDEX('_pockets'!$AO:$AO,$S28))) | L28: =IF($S28="","",IF(INDEX('_pockets'!$AC:$AC,$S28)="","",INDEX('_pockets'!$AC:$AC,$S28))) | M28: =IF($R28="","",IF(INDEX('_list'!$L$2:$L$246,$R28)="","",INDEX('_list'!$L$2:$L$246,$R28))) | N28: =IF($R28="","",IF(INDEX('_list'!$H$2:$H$246,$R28)="","",INDEX('_list'!$H$2:$H$246,$R28))) | O28: =IF($R28="","",IF(INDEX('_list'!$I$2:$I$246,$R28)="","",INDEX('_list'!$I$2:$I$246,$R28))) | R28: =IFERROR(MATCH(9,'_list'!$N$2:$N$246,0),"") | S28: =IF($R28="","",INDEX('_list'!$C$2:$C$246,$R28))
B29: =IF($R29="","",10) | C29: =IF($R29="","",IF(INDEX('_list'!$D$2:$D$246,$R29)="","",INDEX('_list'!$D$2:$D$246,$R29))) | D29: =IF($R29="","",IF(INDEX('_list'!$E$2:$E$246,$R29)="","",INDEX('_list'!$E$2:$E$246,$R29))) | E29: =IF($R29="","",IF(INDEX('_list'!$F$2:$F$246,$R29)="","",INDEX('_list'!$F$2:$F$246,$R29))) | F29: =IF($R29="","",IF(INDEX('_list'!$G$2:$G$246,$R29)="","",INDEX('_list'!$G$2:$G$246,$R29))) | G29: =IF($S29="","",IF(INDEX('_pockets'!$AH:$AH,$S29)="","",INDEX('_pockets'!$AH:$AH,$S29))) | H29: =IF($S29="","",IF(INDEX('_pockets'!$AF:$AF,$S29)="","",INDEX('_pockets'!$AF:$AF,$S29))) | I29: =IF(IF($S29="","",IF(INDEX('_pockets'!$AB:$AB,$S29)="","",INDEX('_pockets'!$AB:$AB,$S29)))="","",IF($S29="","",IF(INDEX('_pockets'!$AB:$AB,$S29)="","",INDEX('_pockets'!$AB:$AB,$S29)))*IF($U$18,100,1)) | J29: =IF($S29="","",IF(INDEX('_pockets'!$Z:$Z,$S29)="","",INDEX('_pockets'!$Z:$Z,$S29))) | K29: =IF($S29="","",IF(INDEX('_pockets'!$AO:$AO,$S29)="","",INDEX('_pockets'!$AO:$AO,$S29))) | L29: =IF($S29="","",IF(INDEX('_pockets'!$AC:$AC,$S29)="","",INDEX('_pockets'!$AC:$AC,$S29))) | M29: =IF($R29="","",IF(INDEX('_list'!$L$2:$L$246,$R29)="","",INDEX('_list'!$L$2:$L$246,$R29))) | N29: =IF($R29="","",IF(INDEX('_list'!$H$2:$H$246,$R29)="","",INDEX('_list'!$H$2:$H$246,$R29))) | O29: =IF($R29="","",IF(INDEX('_list'!$I$2:$I$246,$R29)="","",INDEX('_list'!$I$2:$I$246,$R29))) | R29: =IFERROR(MATCH(10,'_list'!$N$2:$N$246,0),"") | S29: =IF($R29="","",INDEX('_list'!$C$2:$C$246,$R29))
B30: =IF($R30="","",11) | C30: =IF($R30="","",IF(INDEX('_list'!$D$2:$D$246,$R30)="","",INDEX('_list'!$D$2:$D$246,$R30))) | D30: =IF($R30="","",IF(INDEX('_list'!$E$2:$E$246,$R30)="","",INDEX('_list'!$E$2:$E$246,$R30))) | E30: =IF($R30="","",IF(INDEX('_list'!$F$2:$F$246,$R30)="","",INDEX('_list'!$F$2:$F$246,$R30))) | F30: =IF($R30="","",IF(INDEX('_list'!$G$2:$G$246,$R30)="","",INDEX('_list'!$G$2:$G$246,$R30))) | G30: =IF($S30="","",IF(INDEX('_pockets'!$AH:$AH,$S30)="","",INDEX('_pockets'!$AH:$AH,$S30))) | H30: =IF($S30="","",IF(INDEX('_pockets'!$AF:$AF,$S30)="","",INDEX('_pockets'!$AF:$AF,$S30))) | I30: =IF(IF($S30="","",IF(INDEX('_pockets'!$AB:$AB,$S30)="","",INDEX('_pockets'!$AB:$AB,$S30)))="","",IF($S30="","",IF(INDEX('_pockets'!$AB:$AB,$S30)="","",INDEX('_pockets'!$AB:$AB,$S30)))*IF($U$18,100,1)) | J30: =IF($S30="","",IF(INDEX('_pockets'!$Z:$Z,$S30)="","",INDEX('_pockets'!$Z:$Z,$S30))) | K30: =IF($S30="","",IF(INDEX('_pockets'!$AO:$AO,$S30)="","",INDEX('_pockets'!$AO:$AO,$S30))) | L30: =IF($S30="","",IF(INDEX('_pockets'!$AC:$AC,$S30)="","",INDEX('_pockets'!$AC:$AC,$S30))) | M30: =IF($R30="","",IF(INDEX('_list'!$L$2:$L$246,$R30)="","",INDEX('_list'!$L$2:$L$246,$R30))) | N30: =IF($R30="","",IF(INDEX('_list'!$H$2:$H$246,$R30)="","",INDEX('_list'!$H$2:$H$246,$R30))) | O30: =IF($R30="","",IF(INDEX('_list'!$I$2:$I$246,$R30)="","",INDEX('_list'!$I$2:$I$246,$R30))) | R30: =IFERROR(MATCH(11,'_list'!$N$2:$N$246,0),"") | S30: =IF($R30="","",INDEX('_list'!$C$2:$C$246,$R30))
B31: =IF($R31="","",12) | C31: =IF($R31="","",IF(INDEX('_list'!$D$2:$D$246,$R31)="","",INDEX('_list'!$D$2:$D$246,$R31))) | D31: =IF($R31="","",IF(INDEX('_list'!$E$2:$E$246,$R31)="","",INDEX('_list'!$E$2:$E$246,$R31))) | E31: =IF($R31="","",IF(INDEX('_list'!$F$2:$F$246,$R31)="","",INDEX('_list'!$F$2:$F$246,$R31))) | F31: =IF($R31="","",IF(INDEX('_list'!$G$2:$G$246,$R31)="","",INDEX('_list'!$G$2:$G$246,$R31))) | G31: =IF($S31="","",IF(INDEX('_pockets'!$AH:$AH,$S31)="","",INDEX('_pockets'!$AH:$AH,$S31))) | H31: =IF($S31="","",IF(INDEX('_pockets'!$AF:$AF,$S31)="","",INDEX('_pockets'!$AF:$AF,$S31))) | I31: =IF(IF($S31="","",IF(INDEX('_pockets'!$AB:$AB,$S31)="","",INDEX('_pockets'!$AB:$AB,$S31)))="","",IF($S31="","",IF(INDEX('_pockets'!$AB:$AB,$S31)="","",INDEX('_pockets'!$AB:$AB,$S31)))*IF($U$18,100,1)) | J31: =IF($S31="","",IF(INDEX('_pockets'!$Z:$Z,$S31)="","",INDEX('_pockets'!$Z:$Z,$S31))) | K31: =IF($S31="","",IF(INDEX('_pockets'!$AO:$AO,$S31)="","",INDEX('_pockets'!$AO:$AO,$S31))) | L31: =IF($S31="","",IF(INDEX('_pockets'!$AC:$AC,$S31)="","",INDEX('_pockets'!$AC:$AC,$S31))) | M31: =IF($R31="","",IF(INDEX('_list'!$L$2:$L$246,$R31)="","",INDEX('_list'!$L$2:$L$246,$R31))) | N31: =IF($R31="","",IF(INDEX('_list'!$H$2:$H$246,$R31)="","",INDEX('_list'!$H$2:$H$246,$R31))) | O31: =IF($R31="","",IF(INDEX('_list'!$I$2:$I$246,$R31)="","",INDEX('_list'!$I$2:$I$246,$R31))) | R31: =IFERROR(MATCH(12,'_list'!$N$2:$N$246,0),"") | S31: =IF($R31="","",INDEX('_list'!$C$2:$C$246,$R31))
B32: =IF($R32="","",13) | C32: =IF($R32="","",IF(INDEX('_list'!$D$2:$D$246,$R32)="","",INDEX('_list'!$D$2:$D$246,$R32))) | D32: =IF($R32="","",IF(INDEX('_list'!$E$2:$E$246,$R32)="","",INDEX('_list'!$E$2:$E$246,$R32))) | E32: =IF($R32="","",IF(INDEX('_list'!$F$2:$F$246,$R32)="","",INDEX('_list'!$F$2:$F$246,$R32))) | F32: =IF($R32="","",IF(INDEX('_list'!$G$2:$G$246,$R32)="","",INDEX('_list'!$G$2:$G$246,$R32))) | G32: =IF($S32="","",IF(INDEX('_pockets'!$AH:$AH,$S32)="","",INDEX('_pockets'!$AH:$AH,$S32))) | H32: =IF($S32="","",IF(INDEX('_pockets'!$AF:$AF,$S32)="","",INDEX('_pockets'!$AF:$AF,$S32))) | I32: =IF(IF($S32="","",IF(INDEX('_pockets'!$AB:$AB,$S32)="","",INDEX('_pockets'!$AB:$AB,$S32)))="","",IF($S32="","",IF(INDEX('_pockets'!$AB:$AB,$S32)="","",INDEX('_pockets'!$AB:$AB,$S32)))*IF($U$18,100,1)) | J32: =IF($S32="","",IF(INDEX('_pockets'!$Z:$Z,$S32)="","",INDEX('_pockets'!$Z:$Z,$S32))) | K32: =IF($S32="","",IF(INDEX('_pockets'!$AO:$AO,$S32)="","",INDEX('_pockets'!$AO:$AO,$S32))) | L32: =IF($S32="","",IF(INDEX('_pockets'!$AC:$AC,$S32)="","",INDEX('_pockets'!$AC:$AC,$S32))) | M32: =IF($R32="","",IF(INDEX('_list'!$L$2:$L$246,$R32)="","",INDEX('_list'!$L$2:$L$246,$R32))) | N32: =IF($R32="","",IF(INDEX('_list'!$H$2:$H$246,$R32)="","",INDEX('_list'!$H$2:$H$246,$R32))) | O32: =IF($R32="","",IF(INDEX('_list'!$I$2:$I$246,$R32)="","",INDEX('_list'!$I$2:$I$246,$R32))) | R32: =IFERROR(MATCH(13,'_list'!$N$2:$N$246,0),"") | S32: =IF($R32="","",INDEX('_list'!$C$2:$C$246,$R32))
B33: =IF($R33="","",14) | C33: =IF($R33="","",IF(INDEX('_list'!$D$2:$D$246,$R33)="","",INDEX('_list'!$D$2:$D$246,$R33))) | D33: =IF($R33="","",IF(INDEX('_list'!$E$2:$E$246,$R33)="","",INDEX('_list'!$E$2:$E$246,$R33))) | E33: =IF($R33="","",IF(INDEX('_list'!$F$2:$F$246,$R33)="","",INDEX('_list'!$F$2:$F$246,$R33))) | F33: =IF($R33="","",IF(INDEX('_list'!$G$2:$G$246,$R33)="","",INDEX('_list'!$G$2:$G$246,$R33))) | G33: =IF($S33="","",IF(INDEX('_pockets'!$AH:$AH,$S33)="","",INDEX('_pockets'!$AH:$AH,$S33))) | H33: =IF($S33="","",IF(INDEX('_pockets'!$AF:$AF,$S33)="","",INDEX('_pockets'!$AF:$AF,$S33))) | I33: =IF(IF($S33="","",IF(INDEX('_pockets'!$AB:$AB,$S33)="","",INDEX('_pockets'!$AB:$AB,$S33)))="","",IF($S33="","",IF(INDEX('_pockets'!$AB:$AB,$S33)="","",INDEX('_pockets'!$AB:$AB,$S33)))*IF($U$18,100,1)) | J33: =IF($S33="","",IF(INDEX('_pockets'!$Z:$Z,$S33)="","",INDEX('_pockets'!$Z:$Z,$S33))) | K33: =IF($S33="","",IF(INDEX('_pockets'!$AO:$AO,$S33)="","",INDEX('_pockets'!$AO:$AO,$S33))) | L33: =IF($S33="","",IF(INDEX('_pockets'!$AC:$AC,$S33)="","",INDEX('_pockets'!$AC:$AC,$S33))) | M33: =IF($R33="","",IF(INDEX('_list'!$L$2:$L$246,$R33)="","",INDEX('_list'!$L$2:$L$246,$R33))) | N33: =IF($R33="","",IF(INDEX('_list'!$H$2:$H$246,$R33)="","",INDEX('_list'!$H$2:$H$246,$R33))) | O33: =IF($R33="","",IF(INDEX('_list'!$I$2:$I$246,$R33)="","",INDEX('_list'!$I$2:$I$246,$R33))) | R33: =IFERROR(MATCH(14,'_list'!$N$2:$N$246,0),"") | S33: =IF($R33="","",INDEX('_list'!$C$2:$C$246,$R33))
B34: =IF($R34="","",15) | C34: =IF($R34="","",IF(INDEX('_list'!$D$2:$D$246,$R34)="","",INDEX('_list'!$D$2:$D$246,$R34))) | D34: =IF($R34="","",IF(INDEX('_list'!$E$2:$E$246,$R34)="","",INDEX('_list'!$E$2:$E$246,$R34))) | E34: =IF($R34="","",IF(INDEX('_list'!$F$2:$F$246,$R34)="","",INDEX('_list'!$F$2:$F$246,$R34))) | F34: =IF($R34="","",IF(INDEX('_list'!$G$2:$G$246,$R34)="","",INDEX('_list'!$G$2:$G$246,$R34))) | G34: =IF($S34="","",IF(INDEX('_pockets'!$AH:$AH,$S34)="","",INDEX('_pockets'!$AH:$AH,$S34))) | H34: =IF($S34="","",IF(INDEX('_pockets'!$AF:$AF,$S34)="","",INDEX('_pockets'!$AF:$AF,$S34))) | I34: =IF(IF($S34="","",IF(INDEX('_pockets'!$AB:$AB,$S34)="","",INDEX('_pockets'!$AB:$AB,$S34)))="","",IF($S34="","",IF(INDEX('_pockets'!$AB:$AB,$S34)="","",INDEX('_pockets'!$AB:$AB,$S34)))*IF($U$18,100,1)) | J34: =IF($S34="","",IF(INDEX('_pockets'!$Z:$Z,$S34)="","",INDEX('_pockets'!$Z:$Z,$S34))) | K34: =IF($S34="","",IF(INDEX('_pockets'!$AO:$AO,$S34)="","",INDEX('_pockets'!$AO:$AO,$S34))) | L34: =IF($S34="","",IF(INDEX('_pockets'!$AC:$AC,$S34)="","",INDEX('_pockets'!$AC:$AC,$S34))) | M34: =IF($R34="","",IF(INDEX('_list'!$L$2:$L$246,$R34)="","",INDEX('_list'!$L$2:$L$246,$R34))) | N34: =IF($R34="","",IF(INDEX('_list'!$H$2:$H$246,$R34)="","",INDEX('_list'!$H$2:$H$246,$R34))) | O34: =IF($R34="","",IF(INDEX('_list'!$I$2:$I$246,$R34)="","",INDEX('_list'!$I$2:$I$246,$R34))) | R34: =IFERROR(MATCH(15,'_list'!$N$2:$N$246,0),"") | S34: =IF($R34="","",INDEX('_list'!$C$2:$C$246,$R34))
B35: =IF($R35="","",16) | C35: =IF($R35="","",IF(INDEX('_list'!$D$2:$D$246,$R35)="","",INDEX('_list'!$D$2:$D$246,$R35))) | D35: =IF($R35="","",IF(INDEX('_list'!$E$2:$E$246,$R35)="","",INDEX('_list'!$E$2:$E$246,$R35))) | E35: =IF($R35="","",IF(INDEX('_list'!$F$2:$F$246,$R35)="","",INDEX('_list'!$F$2:$F$246,$R35))) | F35: =IF($R35="","",IF(INDEX('_list'!$G$2:$G$246,$R35)="","",INDEX('_list'!$G$2:$G$246,$R35))) | G35: =IF($S35="","",IF(INDEX('_pockets'!$AH:$AH,$S35)="","",INDEX('_pockets'!$AH:$AH,$S35))) | H35: =IF($S35="","",IF(INDEX('_pockets'!$AF:$AF,$S35)="","",INDEX('_pockets'!$AF:$AF,$S35))) | I35: =IF(IF($S35="","",IF(INDEX('_pockets'!$AB:$AB,$S35)="","",INDEX('_pockets'!$AB:$AB,$S35)))="","",IF($S35="","",IF(INDEX('_pockets'!$AB:$AB,$S35)="","",INDEX('_pockets'!$AB:$AB,$S35)))*IF($U$18,100,1)) | J35: =IF($S35="","",IF(INDEX('_pockets'!$Z:$Z,$S35)="","",INDEX('_pockets'!$Z:$Z,$S35))) | K35: =IF($S35="","",IF(INDEX('_pockets'!$AO:$AO,$S35)="","",INDEX('_pockets'!$AO:$AO,$S35))) | L35: =IF($S35="","",IF(INDEX('_pockets'!$AC:$AC,$S35)="","",INDEX('_pockets'!$AC:$AC,$S35))) | M35: =IF($R35="","",IF(INDEX('_list'!$L$2:$L$246,$R35)="","",INDEX('_list'!$L$2:$L$246,$R35))) | N35: =IF($R35="","",IF(INDEX('_list'!$H$2:$H$246,$R35)="","",INDEX('_list'!$H$2:$H$246,$R35))) | O35: =IF($R35="","",IF(INDEX('_list'!$I$2:$I$246,$R35)="","",INDEX('_list'!$I$2:$I$246,$R35))) | R35: =IFERROR(MATCH(16,'_list'!$N$2:$N$246,0),"") | S35: =IF($R35="","",INDEX('_list'!$C$2:$C$246,$R35))
B36: =IF($R36="","",17) | C36: =IF($R36="","",IF(INDEX('_list'!$D$2:$D$246,$R36)="","",INDEX('_list'!$D$2:$D$246,$R36))) | D36: =IF($R36="","",IF(INDEX('_list'!$E$2:$E$246,$R36)="","",INDEX('_list'!$E$2:$E$246,$R36))) | E36: =IF($R36="","",IF(INDEX('_list'!$F$2:$F$246,$R36)="","",INDEX('_list'!$F$2:$F$246,$R36))) | F36: =IF($R36="","",IF(INDEX('_list'!$G$2:$G$246,$R36)="","",INDEX('_list'!$G$2:$G$246,$R36))) | G36: =IF($S36="","",IF(INDEX('_pockets'!$AH:$AH,$S36)="","",INDEX('_pockets'!$AH:$AH,$S36))) | H36: =IF($S36="","",IF(INDEX('_pockets'!$AF:$AF,$S36)="","",INDEX('_pockets'!$AF:$AF,$S36))) | I36: =IF(IF($S36="","",IF(INDEX('_pockets'!$AB:$AB,$S36)="","",INDEX('_pockets'!$AB:$AB,$S36)))="","",IF($S36="","",IF(INDEX('_pockets'!$AB:$AB,$S36)="","",INDEX('_pockets'!$AB:$AB,$S36)))*IF($U$18,100,1)) | J36: =IF($S36="","",IF(INDEX('_pockets'!$Z:$Z,$S36)="","",INDEX('_pockets'!$Z:$Z,$S36))) | K36: =IF($S36="","",IF(INDEX('_pockets'!$AO:$AO,$S36)="","",INDEX('_pockets'!$AO:$AO,$S36))) | L36: =IF($S36="","",IF(INDEX('_pockets'!$AC:$AC,$S36)="","",INDEX('_pockets'!$AC:$AC,$S36))) | M36: =IF($R36="","",IF(INDEX('_list'!$L$2:$L$246,$R36)="","",INDEX('_list'!$L$2:$L$246,$R36))) | N36: =IF($R36="","",IF(INDEX('_list'!$H$2:$H$246,$R36)="","",INDEX('_list'!$H$2:$H$246,$R36))) | O36: =IF($R36="","",IF(INDEX('_list'!$I$2:$I$246,$R36)="","",INDEX('_list'!$I$2:$I$246,$R36))) | R36: =IFERROR(MATCH(17,'_list'!$N$2:$N$246,0),"") | S36: =IF($R36="","",INDEX('_list'!$C$2:$C$246,$R36))
B37: =IF($R37="","",18) | C37: =IF($R37="","",IF(INDEX('_list'!$D$2:$D$246,$R37)="","",INDEX('_list'!$D$2:$D$246,$R37))) | D37: =IF($R37="","",IF(INDEX('_list'!$E$2:$E$246,$R37)="","",INDEX('_list'!$E$2:$E$246,$R37))) | E37: =IF($R37="","",IF(INDEX('_list'!$F$2:$F$246,$R37)="","",INDEX('_list'!$F$2:$F$246,$R37))) | F37: =IF($R37="","",IF(INDEX('_list'!$G$2:$G$246,$R37)="","",INDEX('_list'!$G$2:$G$246,$R37))) | G37: =IF($S37="","",IF(INDEX('_pockets'!$AH:$AH,$S37)="","",INDEX('_pockets'!$AH:$AH,$S37))) | H37: =IF($S37="","",IF(INDEX('_pockets'!$AF:$AF,$S37)="","",INDEX('_pockets'!$AF:$AF,$S37))) | I37: =IF(IF($S37="","",IF(INDEX('_pockets'!$AB:$AB,$S37)="","",INDEX('_pockets'!$AB:$AB,$S37)))="","",IF($S37="","",IF(INDEX('_pockets'!$AB:$AB,$S37)="","",INDEX('_pockets'!$AB:$AB,$S37)))*IF($U$18,100,1)) | J37: =IF($S37="","",IF(INDEX('_pockets'!$Z:$Z,$S37)="","",INDEX('_pockets'!$Z:$Z,$S37))) | K37: =IF($S37="","",IF(INDEX('_pockets'!$AO:$AO,$S37)="","",INDEX('_pockets'!$AO:$AO,$S37))) | L37: =IF($S37="","",IF(INDEX('_pockets'!$AC:$AC,$S37)="","",INDEX('_pockets'!$AC:$AC,$S37))) | M37: =IF($R37="","",IF(INDEX('_list'!$L$2:$L$246,$R37)="","",INDEX('_list'!$L$2:$L$246,$R37))) | N37: =IF($R37="","",IF(INDEX('_list'!$H$2:$H$246,$R37)="","",INDEX('_list'!$H$2:$H$246,$R37))) | O37: =IF($R37="","",IF(INDEX('_list'!$I$2:$I$246,$R37)="","",INDEX('_list'!$I$2:$I$246,$R37))) | R37: =IFERROR(MATCH(18,'_list'!$N$2:$N$246,0),"") | S37: =IF($R37="","",INDEX('_list'!$C$2:$C$246,$R37))
B38: =IF($R38="","",19) | C38: =IF($R38="","",IF(INDEX('_list'!$D$2:$D$246,$R38)="","",INDEX('_list'!$D$2:$D$246,$R38))) | D38: =IF($R38="","",IF(INDEX('_list'!$E$2:$E$246,$R38)="","",INDEX('_list'!$E$2:$E$246,$R38))) | E38: =IF($R38="","",IF(INDEX('_list'!$F$2:$F$246,$R38)="","",INDEX('_list'!$F$2:$F$246,$R38))) | F38: =IF($R38="","",IF(INDEX('_list'!$G$2:$G$246,$R38)="","",INDEX('_list'!$G$2:$G$246,$R38))) | G38: =IF($S38="","",IF(INDEX('_pockets'!$AH:$AH,$S38)="","",INDEX('_pockets'!$AH:$AH,$S38))) | H38: =IF($S38="","",IF(INDEX('_pockets'!$AF:$AF,$S38)="","",INDEX('_pockets'!$AF:$AF,$S38))) | I38: =IF(IF($S38="","",IF(INDEX('_pockets'!$AB:$AB,$S38)="","",INDEX('_pockets'!$AB:$AB,$S38)))="","",IF($S38="","",IF(INDEX('_pockets'!$AB:$AB,$S38)="","",INDEX('_pockets'!$AB:$AB,$S38)))*IF($U$18,100,1)) | J38: =IF($S38="","",IF(INDEX('_pockets'!$Z:$Z,$S38)="","",INDEX('_pockets'!$Z:$Z,$S38))) | K38: =IF($S38="","",IF(INDEX('_pockets'!$AO:$AO,$S38)="","",INDEX('_pockets'!$AO:$AO,$S38))) | L38: =IF($S38="","",IF(INDEX('_pockets'!$AC:$AC,$S38)="","",INDEX('_pockets'!$AC:$AC,$S38))) | M38: =IF($R38="","",IF(INDEX('_list'!$L$2:$L$246,$R38)="","",INDEX('_list'!$L$2:$L$246,$R38))) | N38: =IF($R38="","",IF(INDEX('_list'!$H$2:$H$246,$R38)="","",INDEX('_list'!$H$2:$H$246,$R38))) | O38: =IF($R38="","",IF(INDEX('_list'!$I$2:$I$246,$R38)="","",INDEX('_list'!$I$2:$I$246,$R38))) | R38: =IFERROR(MATCH(19,'_list'!$N$2:$N$246,0),"") | S38: =IF($R38="","",INDEX('_list'!$C$2:$C$246,$R38))
B39: =IF($R39="","",20) | C39: =IF($R39="","",IF(INDEX('_list'!$D$2:$D$246,$R39)="","",INDEX('_list'!$D$2:$D$246,$R39))) | D39: =IF($R39="","",IF(INDEX('_list'!$E$2:$E$246,$R39)="","",INDEX('_list'!$E$2:$E$246,$R39))) | E39: =IF($R39="","",IF(INDEX('_list'!$F$2:$F$246,$R39)="","",INDEX('_list'!$F$2:$F$246,$R39))) | F39: =IF($R39="","",IF(INDEX('_list'!$G$2:$G$246,$R39)="","",INDEX('_list'!$G$2:$G$246,$R39))) | G39: =IF($S39="","",IF(INDEX('_pockets'!$AH:$AH,$S39)="","",INDEX('_pockets'!$AH:$AH,$S39))) | H39: =IF($S39="","",IF(INDEX('_pockets'!$AF:$AF,$S39)="","",INDEX('_pockets'!$AF:$AF,$S39))) | I39: =IF(IF($S39="","",IF(INDEX('_pockets'!$AB:$AB,$S39)="","",INDEX('_pockets'!$AB:$AB,$S39)))="","",IF($S39="","",IF(INDEX('_pockets'!$AB:$AB,$S39)="","",INDEX('_pockets'!$AB:$AB,$S39)))*IF($U$18,100,1)) | J39: =IF($S39="","",IF(INDEX('_pockets'!$Z:$Z,$S39)="","",INDEX('_pockets'!$Z:$Z,$S39))) | K39: =IF($S39="","",IF(INDEX('_pockets'!$AO:$AO,$S39)="","",INDEX('_pockets'!$AO:$AO,$S39))) | L39: =IF($S39="","",IF(INDEX('_pockets'!$AC:$AC,$S39)="","",INDEX('_pockets'!$AC:$AC,$S39))) | M39: =IF($R39="","",IF(INDEX('_list'!$L$2:$L$246,$R39)="","",INDEX('_list'!$L$2:$L$246,$R39))) | N39: =IF($R39="","",IF(INDEX('_list'!$H$2:$H$246,$R39)="","",INDEX('_list'!$H$2:$H$246,$R39))) | O39: =IF($R39="","",IF(INDEX('_list'!$I$2:$I$246,$R39)="","",INDEX('_list'!$I$2:$I$246,$R39))) | R39: =IFERROR(MATCH(20,'_list'!$N$2:$N$246,0),"") | S39: =IF($R39="","",INDEX('_list'!$C$2:$C$246,$R39))
B40: =IF($R40="","",21) | C40: =IF($R40="","",IF(INDEX('_list'!$D$2:$D$246,$R40)="","",INDEX('_list'!$D$2:$D$246,$R40))) | D40: =IF($R40="","",IF(INDEX('_list'!$E$2:$E$246,$R40)="","",INDEX('_list'!$E$2:$E$246,$R40))) | E40: =IF($R40="","",IF(INDEX('_list'!$F$2:$F$246,$R40)="","",INDEX('_list'!$F$2:$F$246,$R40))) | F40: =IF($R40="","",IF(INDEX('_list'!$G$2:$G$246,$R40)="","",INDEX('_list'!$G$2:$G$246,$R40))) | G40: =IF($S40="","",IF(INDEX('_pockets'!$AH:$AH,$S40)="","",INDEX('_pockets'!$AH:$AH,$S40))) | H40: =IF($S40="","",IF(INDEX('_pockets'!$AF:$AF,$S40)="","",INDEX('_pockets'!$AF:$AF,$S40))) | I40: =IF(IF($S40="","",IF(INDEX('_pockets'!$AB:$AB,$S40)="","",INDEX('_pockets'!$AB:$AB,$S40)))="","",IF($S40="","",IF(INDEX('_pockets'!$AB:$AB,$S40)="","",INDEX('_pockets'!$AB:$AB,$S40)))*IF($U$18,100,1)) | J40: =IF($S40="","",IF(INDEX('_pockets'!$Z:$Z,$S40)="","",INDEX('_pockets'!$Z:$Z,$S40))) | K40: =IF($S40="","",IF(INDEX('_pockets'!$AO:$AO,$S40)="","",INDEX('_pockets'!$AO:$AO,$S40))) | L40: =IF($S40="","",IF(INDEX('_pockets'!$AC:$AC,$S40)="","",INDEX('_pockets'!$AC:$AC,$S40))) | M40: =IF($R40="","",IF(INDEX('_list'!$L$2:$L$246,$R40)="","",INDEX('_list'!$L$2:$L$246,$R40))) | N40: =IF($R40="","",IF(INDEX('_list'!$H$2:$H$246,$R40)="","",INDEX('_list'!$H$2:$H$246,$R40))) | O40: =IF($R40="","",IF(INDEX('_list'!$I$2:$I$246,$R40)="","",INDEX('_list'!$I$2:$I$246,$R40))) | R40: =IFERROR(MATCH(21,'_list'!$N$2:$N$246,0),"") | S40: =IF($R40="","",INDEX('_list'!$C$2:$C$246,$R40))
B41: =IF($R41="","",22) | C41: =IF($R41="","",IF(INDEX('_list'!$D$2:$D$246,$R41)="","",INDEX('_list'!$D$2:$D$246,$R41))) | D41: =IF($R41="","",IF(INDEX('_list'!$E$2:$E$246,$R41)="","",INDEX('_list'!$E$2:$E$246,$R41))) | E41: =IF($R41="","",IF(INDEX('_list'!$F$2:$F$246,$R41)="","",INDEX('_list'!$F$2:$F$246,$R41))) | F41: =IF($R41="","",IF(INDEX('_list'!$G$2:$G$246,$R41)="","",INDEX('_list'!$G$2:$G$246,$R41))) | G41: =IF($S41="","",IF(INDEX('_pockets'!$AH:$AH,$S41)="","",INDEX('_pockets'!$AH:$AH,$S41))) | H41: =IF($S41="","",IF(INDEX('_pockets'!$AF:$AF,$S41)="","",INDEX('_pockets'!$AF:$AF,$S41))) | I41: =IF(IF($S41="","",IF(INDEX('_pockets'!$AB:$AB,$S41)="","",INDEX('_pockets'!$AB:$AB,$S41)))="","",IF($S41="","",IF(INDEX('_pockets'!$AB:$AB,$S41)="","",INDEX('_pockets'!$AB:$AB,$S41)))*IF($U$18,100,1)) | J41: =IF($S41="","",IF(INDEX('_pockets'!$Z:$Z,$S41)="","",INDEX('_pockets'!$Z:$Z,$S41))) | K41: =IF($S41="","",IF(INDEX('_pockets'!$AO:$AO,$S41)="","",INDEX('_pockets'!$AO:$AO,$S41))) | L41: =IF($S41="","",IF(INDEX('_pockets'!$AC:$AC,$S41)="","",INDEX('_pockets'!$AC:$AC,$S41))) | M41: =IF($R41="","",IF(INDEX('_list'!$L$2:$L$246,$R41)="","",INDEX('_list'!$L$2:$L$246,$R41))) | N41: =IF($R41="","",IF(INDEX('_list'!$H$2:$H$246,$R41)="","",INDEX('_list'!$H$2:$H$246,$R41))) | O41: =IF($R41="","",IF(INDEX('_list'!$I$2:$I$246,$R41)="","",INDEX('_list'!$I$2:$I$246,$R41))) | R41: =IFERROR(MATCH(22,'_list'!$N$2:$N$246,0),"") | S41: =IF($R41="","",INDEX('_list'!$C$2:$C$246,$R41))
B42: =IF($R42="","",23) | C42: =IF($R42="","",IF(INDEX('_list'!$D$2:$D$246,$R42)="","",INDEX('_list'!$D$2:$D$246,$R42))) | D42: =IF($R42="","",IF(INDEX('_list'!$E$2:$E$246,$R42)="","",INDEX('_list'!$E$2:$E$246,$R42))) | E42: =IF($R42="","",IF(INDEX('_list'!$F$2:$F$246,$R42)="","",INDEX('_list'!$F$2:$F$246,$R42))) | F42: =IF($R42="","",IF(INDEX('_list'!$G$2:$G$246,$R42)="","",INDEX('_list'!$G$2:$G$246,$R42))) | G42: =IF($S42="","",IF(INDEX('_pockets'!$AH:$AH,$S42)="","",INDEX('_pockets'!$AH:$AH,$S42))) | H42: =IF($S42="","",IF(INDEX('_pockets'!$AF:$AF,$S42)="","",INDEX('_pockets'!$AF:$AF,$S42))) | I42: =IF(IF($S42="","",IF(INDEX('_pockets'!$AB:$AB,$S42)="","",INDEX('_pockets'!$AB:$AB,$S42)))="","",IF($S42="","",IF(INDEX('_pockets'!$AB:$AB,$S42)="","",INDEX('_pockets'!$AB:$AB,$S42)))*IF($U$18,100,1)) | J42: =IF($S42="","",IF(INDEX('_pockets'!$Z:$Z,$S42)="","",INDEX('_pockets'!$Z:$Z,$S42))) | K42: =IF($S42="","",IF(INDEX('_pockets'!$AO:$AO,$S42)="","",INDEX('_pockets'!$AO:$AO,$S42))) | L42: =IF($S42="","",IF(INDEX('_pockets'!$AC:$AC,$S42)="","",INDEX('_pockets'!$AC:$AC,$S42))) | M42: =IF($R42="","",IF(INDEX('_list'!$L$2:$L$246,$R42)="","",INDEX('_list'!$L$2:$L$246,$R42))) | N42: =IF($R42="","",IF(INDEX('_list'!$H$2:$H$246,$R42)="","",INDEX('_list'!$H$2:$H$246,$R42))) | O42: =IF($R42="","",IF(INDEX('_list'!$I$2:$I$246,$R42)="","",INDEX('_list'!$I$2:$I$246,$R42))) | R42: =IFERROR(MATCH(23,'_list'!$N$2:$N$246,0),"") | S42: =IF($R42="","",INDEX('_list'!$C$2:$C$246,$R42))
B43: =IF($R43="","",24) | C43: =IF($R43="","",IF(INDEX('_list'!$D$2:$D$246,$R43)="","",INDEX('_list'!$D$2:$D$246,$R43))) | D43: =IF($R43="","",IF(INDEX('_list'!$E$2:$E$246,$R43)="","",INDEX('_list'!$E$2:$E$246,$R43))) | E43: =IF($R43="","",IF(INDEX('_list'!$F$2:$F$246,$R43)="","",INDEX('_list'!$F$2:$F$246,$R43))) | F43: =IF($R43="","",IF(INDEX('_list'!$G$2:$G$246,$R43)="","",INDEX('_list'!$G$2:$G$246,$R43))) | G43: =IF($S43="","",IF(INDEX('_pockets'!$AH:$AH,$S43)="","",INDEX('_pockets'!$AH:$AH,$S43))) | H43: =IF($S43="","",IF(INDEX('_pockets'!$AF:$AF,$S43)="","",INDEX('_pockets'!$AF:$AF,$S43))) | I43: =IF(IF($S43="","",IF(INDEX('_pockets'!$AB:$AB,$S43)="","",INDEX('_pockets'!$AB:$AB,$S43)))="","",IF($S43="","",IF(INDEX('_pockets'!$AB:$AB,$S43)="","",INDEX('_pockets'!$AB:$AB,$S43)))*IF($U$18,100,1)) | J43: =IF($S43="","",IF(INDEX('_pockets'!$Z:$Z,$S43)="","",INDEX('_pockets'!$Z:$Z,$S43))) | K43: =IF($S43="","",IF(INDEX('_pockets'!$AO:$AO,$S43)="","",INDEX('_pockets'!$AO:$AO,$S43))) | L43: =IF($S43="","",IF(INDEX('_pockets'!$AC:$AC,$S43)="","",INDEX('_pockets'!$AC:$AC,$S43))) | M43: =IF($R43="","",IF(INDEX('_list'!$L$2:$L$246,$R43)="","",INDEX('_list'!$L$2:$L$246,$R43))) | N43: =IF($R43="","",IF(INDEX('_list'!$H$2:$H$246,$R43)="","",INDEX('_list'!$H$2:$H$246,$R43))) | O43: =IF($R43="","",IF(INDEX('_list'!$I$2:$I$246,$R43)="","",INDEX('_list'!$I$2:$I$246,$R43))) | R43: =IFERROR(MATCH(24,'_list'!$N$2:$N$246,0),"") | S43: =IF($R43="","",INDEX('_list'!$C$2:$C$246,$R43))
B44: =IF($R44="","",25) | C44: =IF($R44="","",IF(INDEX('_list'!$D$2:$D$246,$R44)="","",INDEX('_list'!$D$2:$D$246,$R44))) | D44: =IF($R44="","",IF(INDEX('_list'!$E$2:$E$246,$R44)="","",INDEX('_list'!$E$2:$E$246,$R44))) | E44: =IF($R44="","",IF(INDEX('_list'!$F$2:$F$246,$R44)="","",INDEX('_list'!$F$2:$F$246,$R44))) | F44: =IF($R44="","",IF(INDEX('_list'!$G$2:$G$246,$R44)="","",INDEX('_list'!$G$2:$G$246,$R44))) | G44: =IF($S44="","",IF(INDEX('_pockets'!$AH:$AH,$S44)="","",INDEX('_pockets'!$AH:$AH,$S44))) | H44: =IF($S44="","",IF(INDEX('_pockets'!$AF:$AF,$S44)="","",INDEX('_pockets'!$AF:$AF,$S44))) | I44: =IF(IF($S44="","",IF(INDEX('_pockets'!$AB:$AB,$S44)="","",INDEX('_pockets'!$AB:$AB,$S44)))="","",IF($S44="","",IF(INDEX('_pockets'!$AB:$AB,$S44)="","",INDEX('_pockets'!$AB:$AB,$S44)))*IF($U$18,100,1)) | J44: =IF($S44="","",IF(INDEX('_pockets'!$Z:$Z,$S44)="","",INDEX('_pockets'!$Z:$Z,$S44))) | K44: =IF($S44="","",IF(INDEX('_pockets'!$AO:$AO,$S44)="","",INDEX('_pockets'!$AO:$AO,$S44))) | L44: =IF($S44="","",IF(INDEX('_pockets'!$AC:$AC,$S44)="","",INDEX('_pockets'!$AC:$AC,$S44))) | M44: =IF($R44="","",IF(INDEX('_list'!$L$2:$L$246,$R44)="","",INDEX('_list'!$L$2:$L$246,$R44))) | N44: =IF($R44="","",IF(INDEX('_list'!$H$2:$H$246,$R44)="","",INDEX('_list'!$H$2:$H$246,$R44))) | O44: =IF($R44="","",IF(INDEX('_list'!$I$2:$I$246,$R44)="","",INDEX('_list'!$I$2:$I$246,$R44))) | R44: =IFERROR(MATCH(25,'_list'!$N$2:$N$246,0),"") | S44: =IF($R44="","",INDEX('_list'!$C$2:$C$246,$R44))
B45: =IF($R45="","",26) | C45: =IF($R45="","",IF(INDEX('_list'!$D$2:$D$246,$R45)="","",INDEX('_list'!$D$2:$D$246,$R45))) | D45: =IF($R45="","",IF(INDEX('_list'!$E$2:$E$246,$R45)="","",INDEX('_list'!$E$2:$E$246,$R45))) | E45: =IF($R45="","",IF(INDEX('_list'!$F$2:$F$246,$R45)="","",INDEX('_list'!$F$2:$F$246,$R45))) | F45: =IF($R45="","",IF(INDEX('_list'!$G$2:$G$246,$R45)="","",INDEX('_list'!$G$2:$G$246,$R45))) | G45: =IF($S45="","",IF(INDEX('_pockets'!$AH:$AH,$S45)="","",INDEX('_pockets'!$AH:$AH,$S45))) | H45: =IF($S45="","",IF(INDEX('_pockets'!$AF:$AF,$S45)="","",INDEX('_pockets'!$AF:$AF,$S45))) | I45: =IF(IF($S45="","",IF(INDEX('_pockets'!$AB:$AB,$S45)="","",INDEX('_pockets'!$AB:$AB,$S45)))="","",IF($S45="","",IF(INDEX('_pockets'!$AB:$AB,$S45)="","",INDEX('_pockets'!$AB:$AB,$S45)))*IF($U$18,100,1)) | J45: =IF($S45="","",IF(INDEX('_pockets'!$Z:$Z,$S45)="","",INDEX('_pockets'!$Z:$Z,$S45))) | K45: =IF($S45="","",IF(INDEX('_pockets'!$AO:$AO,$S45)="","",INDEX('_pockets'!$AO:$AO,$S45))) | L45: =IF($S45="","",IF(INDEX('_pockets'!$AC:$AC,$S45)="","",INDEX('_pockets'!$AC:$AC,$S45))) | M45: =IF($R45="","",IF(INDEX('_list'!$L$2:$L$246,$R45)="","",INDEX('_list'!$L$2:$L$246,$R45))) | N45: =IF($R45="","",IF(INDEX('_list'!$H$2:$H$246,$R45)="","",INDEX('_list'!$H$2:$H$246,$R45))) | O45: =IF($R45="","",IF(INDEX('_list'!$I$2:$I$246,$R45)="","",INDEX('_list'!$I$2:$I$246,$R45))) | R45: =IFERROR(MATCH(26,'_list'!$N$2:$N$246,0),"") | S45: =IF($R45="","",INDEX('_list'!$C$2:$C$246,$R45))
B46: =IF($R46="","",27) | C46: =IF($R46="","",IF(INDEX('_list'!$D$2:$D$246,$R46)="","",INDEX('_list'!$D$2:$D$246,$R46))) | D46: =IF($R46="","",IF(INDEX('_list'!$E$2:$E$246,$R46)="","",INDEX('_list'!$E$2:$E$246,$R46))) | E46: =IF($R46="","",IF(INDEX('_list'!$F$2:$F$246,$R46)="","",INDEX('_list'!$F$2:$F$246,$R46))) | F46: =IF($R46="","",IF(INDEX('_list'!$G$2:$G$246,$R46)="","",INDEX('_list'!$G$2:$G$246,$R46))) | G46: =IF($S46="","",IF(INDEX('_pockets'!$AH:$AH,$S46)="","",INDEX('_pockets'!$AH:$AH,$S46))) | H46: =IF($S46="","",IF(INDEX('_pockets'!$AF:$AF,$S46)="","",INDEX('_pockets'!$AF:$AF,$S46))) | I46: =IF(IF($S46="","",IF(INDEX('_pockets'!$AB:$AB,$S46)="","",INDEX('_pockets'!$AB:$AB,$S46)))="","",IF($S46="","",IF(INDEX('_pockets'!$AB:$AB,$S46)="","",INDEX('_pockets'!$AB:$AB,$S46)))*IF($U$18,100,1)) | J46: =IF($S46="","",IF(INDEX('_pockets'!$Z:$Z,$S46)="","",INDEX('_pockets'!$Z:$Z,$S46))) | K46: =IF($S46="","",IF(INDEX('_pockets'!$AO:$AO,$S46)="","",INDEX('_pockets'!$AO:$AO,$S46))) | L46: =IF($S46="","",IF(INDEX('_pockets'!$AC:$AC,$S46)="","",INDEX('_pockets'!$AC:$AC,$S46))) | M46: =IF($R46="","",IF(INDEX('_list'!$L$2:$L$246,$R46)="","",INDEX('_list'!$L$2:$L$246,$R46))) | N46: =IF($R46="","",IF(INDEX('_list'!$H$2:$H$246,$R46)="","",INDEX('_list'!$H$2:$H$246,$R46))) | O46: =IF($R46="","",IF(INDEX('_list'!$I$2:$I$246,$R46)="","",INDEX('_list'!$I$2:$I$246,$R46))) | R46: =IFERROR(MATCH(27,'_list'!$N$2:$N$246,0),"") | S46: =IF($R46="","",INDEX('_list'!$C$2:$C$246,$R46))
B47: =IF($R47="","",28) | C47: =IF($R47="","",IF(INDEX('_list'!$D$2:$D$246,$R47)="","",INDEX('_list'!$D$2:$D$246,$R47))) | D47: =IF($R47="","",IF(INDEX('_list'!$E$2:$E$246,$R47)="","",INDEX('_list'!$E$2:$E$246,$R47))) | E47: =IF($R47="","",IF(INDEX('_list'!$F$2:$F$246,$R47)="","",INDEX('_list'!$F$2:$F$246,$R47))) | F47: =IF($R47="","",IF(INDEX('_list'!$G$2:$G$246,$R47)="","",INDEX('_list'!$G$2:$G$246,$R47))) | G47: =IF($S47="","",IF(INDEX('_pockets'!$AH:$AH,$S47)="","",INDEX('_pockets'!$AH:$AH,$S47))) | H47: =IF($S47="","",IF(INDEX('_pockets'!$AF:$AF,$S47)="","",INDEX('_pockets'!$AF:$AF,$S47))) | I47: =IF(IF($S47="","",IF(INDEX('_pockets'!$AB:$AB,$S47)="","",INDEX('_pockets'!$AB:$AB,$S47)))="","",IF($S47="","",IF(INDEX('_pockets'!$AB:$AB,$S47)="","",INDEX('_pockets'!$AB:$AB,$S47)))*IF($U$18,100,1)) | J47: =IF($S47="","",IF(INDEX('_pockets'!$Z:$Z,$S47)="","",INDEX('_pockets'!$Z:$Z,$S47))) | K47: =IF($S47="","",IF(INDEX('_pockets'!$AO:$AO,$S47)="","",INDEX('_pockets'!$AO:$AO,$S47))) | L47: =IF($S47="","",IF(INDEX('_pockets'!$AC:$AC,$S47)="","",INDEX('_pockets'!$AC:$AC,$S47))) | M47: =IF($R47="","",IF(INDEX('_list'!$L$2:$L$246,$R47)="","",INDEX('_list'!$L$2:$L$246,$R47))) | N47: =IF($R47="","",IF(INDEX('_list'!$H$2:$H$246,$R47)="","",INDEX('_list'!$H$2:$H$246,$R47))) | O47: =IF($R47="","",IF(INDEX('_list'!$I$2:$I$246,$R47)="","",INDEX('_list'!$I$2:$I$246,$R47))) | R47: =IFERROR(MATCH(28,'_list'!$N$2:$N$246,0),"") | S47: =IF($R47="","",INDEX('_list'!$C$2:$C$246,$R47))
B48: =IF($R48="","",29) | C48: =IF($R48="","",IF(INDEX('_list'!$D$2:$D$246,$R48)="","",INDEX('_list'!$D$2:$D$246,$R48))) | D48: =IF($R48="","",IF(INDEX('_list'!$E$2:$E$246,$R48)="","",INDEX('_list'!$E$2:$E$246,$R48))) | E48: =IF($R48="","",IF(INDEX('_list'!$F$2:$F$246,$R48)="","",INDEX('_list'!$F$2:$F$246,$R48))) | F48: =IF($R48="","",IF(INDEX('_list'!$G$2:$G$246,$R48)="","",INDEX('_list'!$G$2:$G$246,$R48))) | G48: =IF($S48="","",IF(INDEX('_pockets'!$AH:$AH,$S48)="","",INDEX('_pockets'!$AH:$AH,$S48))) | H48: =IF($S48="","",IF(INDEX('_pockets'!$AF:$AF,$S48)="","",INDEX('_pockets'!$AF:$AF,$S48))) | I48: =IF(IF($S48="","",IF(INDEX('_pockets'!$AB:$AB,$S48)="","",INDEX('_pockets'!$AB:$AB,$S48)))="","",IF($S48="","",IF(INDEX('_pockets'!$AB:$AB,$S48)="","",INDEX('_pockets'!$AB:$AB,$S48)))*IF($U$18,100,1)) | J48: =IF($S48="","",IF(INDEX('_pockets'!$Z:$Z,$S48)="","",INDEX('_pockets'!$Z:$Z,$S48))) | K48: =IF($S48="","",IF(INDEX('_pockets'!$AO:$AO,$S48)="","",INDEX('_pockets'!$AO:$AO,$S48))) | L48: =IF($S48="","",IF(INDEX('_pockets'!$AC:$AC,$S48)="","",INDEX('_pockets'!$AC:$AC,$S48))) | M48: =IF($R48="","",IF(INDEX('_list'!$L$2:$L$246,$R48)="","",INDEX('_list'!$L$2:$L$246,$R48))) | N48: =IF($R48="","",IF(INDEX('_list'!$H$2:$H$246,$R48)="","",INDEX('_list'!$H$2:$H$246,$R48))) | O48: =IF($R48="","",IF(INDEX('_list'!$I$2:$I$246,$R48)="","",INDEX('_list'!$I$2:$I$246,$R48))) | R48: =IFERROR(MATCH(29,'_list'!$N$2:$N$246,0),"") | S48: =IF($R48="","",INDEX('_list'!$C$2:$C$246,$R48))
B49: =IF($R49="","",30) | C49: =IF($R49="","",IF(INDEX('_list'!$D$2:$D$246,$R49)="","",INDEX('_list'!$D$2:$D$246,$R49))) | D49: =IF($R49="","",IF(INDEX('_list'!$E$2:$E$246,$R49)="","",INDEX('_list'!$E$2:$E$246,$R49))) | E49: =IF($R49="","",IF(INDEX('_list'!$F$2:$F$246,$R49)="","",INDEX('_list'!$F$2:$F$246,$R49))) | F49: =IF($R49="","",IF(INDEX('_list'!$G$2:$G$246,$R49)="","",INDEX('_list'!$G$2:$G$246,$R49))) | G49: =IF($S49="","",IF(INDEX('_pockets'!$AH:$AH,$S49)="","",INDEX('_pockets'!$AH:$AH,$S49))) | H49: =IF($S49="","",IF(INDEX('_pockets'!$AF:$AF,$S49)="","",INDEX('_pockets'!$AF:$AF,$S49))) | I49: =IF(IF($S49="","",IF(INDEX('_pockets'!$AB:$AB,$S49)="","",INDEX('_pockets'!$AB:$AB,$S49)))="","",IF($S49="","",IF(INDEX('_pockets'!$AB:$AB,$S49)="","",INDEX('_pockets'!$AB:$AB,$S49)))*IF($U$18,100,1)) | J49: =IF($S49="","",IF(INDEX('_pockets'!$Z:$Z,$S49)="","",INDEX('_pockets'!$Z:$Z,$S49))) | K49: =IF($S49="","",IF(INDEX('_pockets'!$AO:$AO,$S49)="","",INDEX('_pockets'!$AO:$AO,$S49))) | L49: =IF($S49="","",IF(INDEX('_pockets'!$AC:$AC,$S49)="","",INDEX('_pockets'!$AC:$AC,$S49))) | M49: =IF($R49="","",IF(INDEX('_list'!$L$2:$L$246,$R49)="","",INDEX('_list'!$L$2:$L$246,$R49))) | N49: =IF($R49="","",IF(INDEX('_list'!$H$2:$H$246,$R49)="","",INDEX('_list'!$H$2:$H$246,$R49))) | O49: =IF($R49="","",IF(INDEX('_list'!$I$2:$I$246,$R49)="","",INDEX('_list'!$I$2:$I$246,$R49))) | R49: =IFERROR(MATCH(30,'_list'!$N$2:$N$246,0),"") | S49: =IF($R49="","",INDEX('_list'!$C$2:$C$246,$R49))
B50: =IF($R50="","",31) | C50: =IF($R50="","",IF(INDEX('_list'!$D$2:$D$246,$R50)="","",INDEX('_list'!$D$2:$D$246,$R50))) | D50: =IF($R50="","",IF(INDEX('_list'!$E$2:$E$246,$R50)="","",INDEX('_list'!$E$2:$E$246,$R50))) | E50: =IF($R50="","",IF(INDEX('_list'!$F$2:$F$246,$R50)="","",INDEX('_list'!$F$2:$F$246,$R50))) | F50: =IF($R50="","",IF(INDEX('_list'!$G$2:$G$246,$R50)="","",INDEX('_list'!$G$2:$G$246,$R50))) | G50: =IF($S50="","",IF(INDEX('_pockets'!$AH:$AH,$S50)="","",INDEX('_pockets'!$AH:$AH,$S50))) | H50: =IF($S50="","",IF(INDEX('_pockets'!$AF:$AF,$S50)="","",INDEX('_pockets'!$AF:$AF,$S50))) | I50: =IF(IF($S50="","",IF(INDEX('_pockets'!$AB:$AB,$S50)="","",INDEX('_pockets'!$AB:$AB,$S50)))="","",IF($S50="","",IF(INDEX('_pockets'!$AB:$AB,$S50)="","",INDEX('_pockets'!$AB:$AB,$S50)))*IF($U$18,100,1)) | J50: =IF($S50="","",IF(INDEX('_pockets'!$Z:$Z,$S50)="","",INDEX('_pockets'!$Z:$Z,$S50))) | K50: =IF($S50="","",IF(INDEX('_pockets'!$AO:$AO,$S50)="","",INDEX('_pockets'!$AO:$AO,$S50))) | L50: =IF($S50="","",IF(INDEX('_pockets'!$AC:$AC,$S50)="","",INDEX('_pockets'!$AC:$AC,$S50))) | M50: =IF($R50="","",IF(INDEX('_list'!$L$2:$L$246,$R50)="","",INDEX('_list'!$L$2:$L$246,$R50))) | N50: =IF($R50="","",IF(INDEX('_list'!$H$2:$H$246,$R50)="","",INDEX('_list'!$H$2:$H$246,$R50))) | O50: =IF($R50="","",IF(INDEX('_list'!$I$2:$I$246,$R50)="","",INDEX('_list'!$I$2:$I$246,$R50))) | R50: =IFERROR(MATCH(31,'_list'!$N$2:$N$246,0),"") | S50: =IF($R50="","",INDEX('_list'!$C$2:$C$246,$R50))
B51: =IF($R51="","",32) | C51: =IF($R51="","",IF(INDEX('_list'!$D$2:$D$246,$R51)="","",INDEX('_list'!$D$2:$D$246,$R51))) | D51: =IF($R51="","",IF(INDEX('_list'!$E$2:$E$246,$R51)="","",INDEX('_list'!$E$2:$E$246,$R51))) | E51: =IF($R51="","",IF(INDEX('_list'!$F$2:$F$246,$R51)="","",INDEX('_list'!$F$2:$F$246,$R51))) | F51: =IF($R51="","",IF(INDEX('_list'!$G$2:$G$246,$R51)="","",INDEX('_list'!$G$2:$G$246,$R51))) | G51: =IF($S51="","",IF(INDEX('_pockets'!$AH:$AH,$S51)="","",INDEX('_pockets'!$AH:$AH,$S51))) | H51: =IF($S51="","",IF(INDEX('_pockets'!$AF:$AF,$S51)="","",INDEX('_pockets'!$AF:$AF,$S51))) | I51: =IF(IF($S51="","",IF(INDEX('_pockets'!$AB:$AB,$S51)="","",INDEX('_pockets'!$AB:$AB,$S51)))="","",IF($S51="","",IF(INDEX('_pockets'!$AB:$AB,$S51)="","",INDEX('_pockets'!$AB:$AB,$S51)))*IF($U$18,100,1)) | J51: =IF($S51="","",IF(INDEX('_pockets'!$Z:$Z,$S51)="","",INDEX('_pockets'!$Z:$Z,$S51))) | K51: =IF($S51="","",IF(INDEX('_pockets'!$AO:$AO,$S51)="","",INDEX('_pockets'!$AO:$AO,$S51))) | L51: =IF($S51="","",IF(INDEX('_pockets'!$AC:$AC,$S51)="","",INDEX('_pockets'!$AC:$AC,$S51))) | M51: =IF($R51="","",IF(INDEX('_list'!$L$2:$L$246,$R51)="","",INDEX('_list'!$L$2:$L$246,$R51))) | N51: =IF($R51="","",IF(INDEX('_list'!$H$2:$H$246,$R51)="","",INDEX('_list'!$H$2:$H$246,$R51))) | O51: =IF($R51="","",IF(INDEX('_list'!$I$2:$I$246,$R51)="","",INDEX('_list'!$I$2:$I$246,$R51))) | R51: =IFERROR(MATCH(32,'_list'!$N$2:$N$246,0),"") | S51: =IF($R51="","",INDEX('_list'!$C$2:$C$246,$R51))
B52: =IF($R52="","",33) | C52: =IF($R52="","",IF(INDEX('_list'!$D$2:$D$246,$R52)="","",INDEX('_list'!$D$2:$D$246,$R52))) | D52: =IF($R52="","",IF(INDEX('_list'!$E$2:$E$246,$R52)="","",INDEX('_list'!$E$2:$E$246,$R52))) | E52: =IF($R52="","",IF(INDEX('_list'!$F$2:$F$246,$R52)="","",INDEX('_list'!$F$2:$F$246,$R52))) | F52: =IF($R52="","",IF(INDEX('_list'!$G$2:$G$246,$R52)="","",INDEX('_list'!$G$2:$G$246,$R52))) | G52: =IF($S52="","",IF(INDEX('_pockets'!$AH:$AH,$S52)="","",INDEX('_pockets'!$AH:$AH,$S52))) | H52: =IF($S52="","",IF(INDEX('_pockets'!$AF:$AF,$S52)="","",INDEX('_pockets'!$AF:$AF,$S52))) | I52: =IF(IF($S52="","",IF(INDEX('_pockets'!$AB:$AB,$S52)="","",INDEX('_pockets'!$AB:$AB,$S52)))="","",IF($S52="","",IF(INDEX('_pockets'!$AB:$AB,$S52)="","",INDEX('_pockets'!$AB:$AB,$S52)))*IF($U$18,100,1)) | J52: =IF($S52="","",IF(INDEX('_pockets'!$Z:$Z,$S52)="","",INDEX('_pockets'!$Z:$Z,$S52))) | K52: =IF($S52="","",IF(INDEX('_pockets'!$AO:$AO,$S52)="","",INDEX('_pockets'!$AO:$AO,$S52))) | L52: =IF($S52="","",IF(INDEX('_pockets'!$AC:$AC,$S52)="","",INDEX('_pockets'!$AC:$AC,$S52))) | M52: =IF($R52="","",IF(INDEX('_list'!$L$2:$L$246,$R52)="","",INDEX('_list'!$L$2:$L$246,$R52))) | N52: =IF($R52="","",IF(INDEX('_list'!$H$2:$H$246,$R52)="","",INDEX('_list'!$H$2:$H$246,$R52))) | O52: =IF($R52="","",IF(INDEX('_list'!$I$2:$I$246,$R52)="","",INDEX('_list'!$I$2:$I$246,$R52))) | R52: =IFERROR(MATCH(33,'_list'!$N$2:$N$246,0),"") | S52: =IF($R52="","",INDEX('_list'!$C$2:$C$246,$R52))
B53: =IF($R53="","",34) | C53: =IF($R53="","",IF(INDEX('_list'!$D$2:$D$246,$R53)="","",INDEX('_list'!$D$2:$D$246,$R53))) | D53: =IF($R53="","",IF(INDEX('_list'!$E$2:$E$246,$R53)="","",INDEX('_list'!$E$2:$E$246,$R53))) | E53: =IF($R53="","",IF(INDEX('_list'!$F$2:$F$246,$R53)="","",INDEX('_list'!$F$2:$F$246,$R53))) | F53: =IF($R53="","",IF(INDEX('_list'!$G$2:$G$246,$R53)="","",INDEX('_list'!$G$2:$G$246,$R53))) | G53: =IF($S53="","",IF(INDEX('_pockets'!$AH:$AH,$S53)="","",INDEX('_pockets'!$AH:$AH,$S53))) | H53: =IF($S53="","",IF(INDEX('_pockets'!$AF:$AF,$S53)="","",INDEX('_pockets'!$AF:$AF,$S53))) | I53: =IF(IF($S53="","",IF(INDEX('_pockets'!$AB:$AB,$S53)="","",INDEX('_pockets'!$AB:$AB,$S53)))="","",IF($S53="","",IF(INDEX('_pockets'!$AB:$AB,$S53)="","",INDEX('_pockets'!$AB:$AB,$S53)))*IF($U$18,100,1)) | J53: =IF($S53="","",IF(INDEX('_pockets'!$Z:$Z,$S53)="","",INDEX('_pockets'!$Z:$Z,$S53))) | K53: =IF($S53="","",IF(INDEX('_pockets'!$AO:$AO,$S53)="","",INDEX('_pockets'!$AO:$AO,$S53))) | L53: =IF($S53="","",IF(INDEX('_pockets'!$AC:$AC,$S53)="","",INDEX('_pockets'!$AC:$AC,$S53))) | M53: =IF($R53="","",IF(INDEX('_list'!$L$2:$L$246,$R53)="","",INDEX('_list'!$L$2:$L$246,$R53))) | N53: =IF($R53="","",IF(INDEX('_list'!$H$2:$H$246,$R53)="","",INDEX('_list'!$H$2:$H$246,$R53))) | O53: =IF($R53="","",IF(INDEX('_list'!$I$2:$I$246,$R53)="","",INDEX('_list'!$I$2:$I$246,$R53))) | R53: =IFERROR(MATCH(34,'_list'!$N$2:$N$246,0),"") | S53: =IF($R53="","",INDEX('_list'!$C$2:$C$246,$R53))
B54: =IF($R54="","",35) | C54: =IF($R54="","",IF(INDEX('_list'!$D$2:$D$246,$R54)="","",INDEX('_list'!$D$2:$D$246,$R54))) | D54: =IF($R54="","",IF(INDEX('_list'!$E$2:$E$246,$R54)="","",INDEX('_list'!$E$2:$E$246,$R54))) | E54: =IF($R54="","",IF(INDEX('_list'!$F$2:$F$246,$R54)="","",INDEX('_list'!$F$2:$F$246,$R54))) | F54: =IF($R54="","",IF(INDEX('_list'!$G$2:$G$246,$R54)="","",INDEX('_list'!$G$2:$G$246,$R54))) | G54: =IF($S54="","",IF(INDEX('_pockets'!$AH:$AH,$S54)="","",INDEX('_pockets'!$AH:$AH,$S54))) | H54: =IF($S54="","",IF(INDEX('_pockets'!$AF:$AF,$S54)="","",INDEX('_pockets'!$AF:$AF,$S54))) | I54: =IF(IF($S54="","",IF(INDEX('_pockets'!$AB:$AB,$S54)="","",INDEX('_pockets'!$AB:$AB,$S54)))="","",IF($S54="","",IF(INDEX('_pockets'!$AB:$AB,$S54)="","",INDEX('_pockets'!$AB:$AB,$S54)))*IF($U$18,100,1)) | J54: =IF($S54="","",IF(INDEX('_pockets'!$Z:$Z,$S54)="","",INDEX('_pockets'!$Z:$Z,$S54))) | K54: =IF($S54="","",IF(INDEX('_pockets'!$AO:$AO,$S54)="","",INDEX('_pockets'!$AO:$AO,$S54))) | L54: =IF($S54="","",IF(INDEX('_pockets'!$AC:$AC,$S54)="","",INDEX('_pockets'!$AC:$AC,$S54))) | M54: =IF($R54="","",IF(INDEX('_list'!$L$2:$L$246,$R54)="","",INDEX('_list'!$L$2:$L$246,$R54))) | N54: =IF($R54="","",IF(INDEX('_list'!$H$2:$H$246,$R54)="","",INDEX('_list'!$H$2:$H$246,$R54))) | O54: =IF($R54="","",IF(INDEX('_list'!$I$2:$I$246,$R54)="","",INDEX('_list'!$I$2:$I$246,$R54))) | R54: =IFERROR(MATCH(35,'_list'!$N$2:$N$246,0),"") | S54: =IF($R54="","",INDEX('_list'!$C$2:$C$246,$R54))
B55: =IF($R55="","",36) | C55: =IF($R55="","",IF(INDEX('_list'!$D$2:$D$246,$R55)="","",INDEX('_list'!$D$2:$D$246,$R55))) | D55: =IF($R55="","",IF(INDEX('_list'!$E$2:$E$246,$R55)="","",INDEX('_list'!$E$2:$E$246,$R55))) | E55: =IF($R55="","",IF(INDEX('_list'!$F$2:$F$246,$R55)="","",INDEX('_list'!$F$2:$F$246,$R55))) | F55: =IF($R55="","",IF(INDEX('_list'!$G$2:$G$246,$R55)="","",INDEX('_list'!$G$2:$G$246,$R55))) | G55: =IF($S55="","",IF(INDEX('_pockets'!$AH:$AH,$S55)="","",INDEX('_pockets'!$AH:$AH,$S55))) | H55: =IF($S55="","",IF(INDEX('_pockets'!$AF:$AF,$S55)="","",INDEX('_pockets'!$AF:$AF,$S55))) | I55: =IF(IF($S55="","",IF(INDEX('_pockets'!$AB:$AB,$S55)="","",INDEX('_pockets'!$AB:$AB,$S55)))="","",IF($S55="","",IF(INDEX('_pockets'!$AB:$AB,$S55)="","",INDEX('_pockets'!$AB:$AB,$S55)))*IF($U$18,100,1)) | J55: =IF($S55="","",IF(INDEX('_pockets'!$Z:$Z,$S55)="","",INDEX('_pockets'!$Z:$Z,$S55))) | K55: =IF($S55="","",IF(INDEX('_pockets'!$AO:$AO,$S55)="","",INDEX('_pockets'!$AO:$AO,$S55))) | L55: =IF($S55="","",IF(INDEX('_pockets'!$AC:$AC,$S55)="","",INDEX('_pockets'!$AC:$AC,$S55))) | M55: =IF($R55="","",IF(INDEX('_list'!$L$2:$L$246,$R55)="","",INDEX('_list'!$L$2:$L$246,$R55))) | N55: =IF($R55="","",IF(INDEX('_list'!$H$2:$H$246,$R55)="","",INDEX('_list'!$H$2:$H$246,$R55))) | O55: =IF($R55="","",IF(INDEX('_list'!$I$2:$I$246,$R55)="","",INDEX('_list'!$I$2:$I$246,$R55))) | R55: =IFERROR(MATCH(36,'_list'!$N$2:$N$246,0),"") | S55: =IF($R55="","",INDEX('_list'!$C$2:$C$246,$R55))
B56: =IF($R56="","",37) | C56: =IF($R56="","",IF(INDEX('_list'!$D$2:$D$246,$R56)="","",INDEX('_list'!$D$2:$D$246,$R56))) | D56: =IF($R56="","",IF(INDEX('_list'!$E$2:$E$246,$R56)="","",INDEX('_list'!$E$2:$E$246,$R56))) | E56: =IF($R56="","",IF(INDEX('_list'!$F$2:$F$246,$R56)="","",INDEX('_list'!$F$2:$F$246,$R56))) | F56: =IF($R56="","",IF(INDEX('_list'!$G$2:$G$246,$R56)="","",INDEX('_list'!$G$2:$G$246,$R56))) | G56: =IF($S56="","",IF(INDEX('_pockets'!$AH:$AH,$S56)="","",INDEX('_pockets'!$AH:$AH,$S56))) | H56: =IF($S56="","",IF(INDEX('_pockets'!$AF:$AF,$S56)="","",INDEX('_pockets'!$AF:$AF,$S56))) | I56: =IF(IF($S56="","",IF(INDEX('_pockets'!$AB:$AB,$S56)="","",INDEX('_pockets'!$AB:$AB,$S56)))="","",IF($S56="","",IF(INDEX('_pockets'!$AB:$AB,$S56)="","",INDEX('_pockets'!$AB:$AB,$S56)))*IF($U$18,100,1)) | J56: =IF($S56="","",IF(INDEX('_pockets'!$Z:$Z,$S56)="","",INDEX('_pockets'!$Z:$Z,$S56))) | K56: =IF($S56="","",IF(INDEX('_pockets'!$AO:$AO,$S56)="","",INDEX('_pockets'!$AO:$AO,$S56))) | L56: =IF($S56="","",IF(INDEX('_pockets'!$AC:$AC,$S56)="","",INDEX('_pockets'!$AC:$AC,$S56))) | M56: =IF($R56="","",IF(INDEX('_list'!$L$2:$L$246,$R56)="","",INDEX('_list'!$L$2:$L$246,$R56))) | N56: =IF($R56="","",IF(INDEX('_list'!$H$2:$H$246,$R56)="","",INDEX('_list'!$H$2:$H$246,$R56))) | O56: =IF($R56="","",IF(INDEX('_list'!$I$2:$I$246,$R56)="","",INDEX('_list'!$I$2:$I$246,$R56))) | R56: =IFERROR(MATCH(37,'_list'!$N$2:$N$246,0),"") | S56: =IF($R56="","",INDEX('_list'!$C$2:$C$246,$R56))
B57: =IF($R57="","",38) | C57: =IF($R57="","",IF(INDEX('_list'!$D$2:$D$246,$R57)="","",INDEX('_list'!$D$2:$D$246,$R57))) | D57: =IF($R57="","",IF(INDEX('_list'!$E$2:$E$246,$R57)="","",INDEX('_list'!$E$2:$E$246,$R57))) | E57: =IF($R57="","",IF(INDEX('_list'!$F$2:$F$246,$R57)="","",INDEX('_list'!$F$2:$F$246,$R57))) | F57: =IF($R57="","",IF(INDEX('_list'!$G$2:$G$246,$R57)="","",INDEX('_list'!$G$2:$G$246,$R57))) | G57: =IF($S57="","",IF(INDEX('_pockets'!$AH:$AH,$S57)="","",INDEX('_pockets'!$AH:$AH,$S57))) | H57: =IF($S57="","",IF(INDEX('_pockets'!$AF:$AF,$S57)="","",INDEX('_pockets'!$AF:$AF,$S57))) | I57: =IF(IF($S57="","",IF(INDEX('_pockets'!$AB:$AB,$S57)="","",INDEX('_pockets'!$AB:$AB,$S57)))="","",IF($S57="","",IF(INDEX('_pockets'!$AB:$AB,$S57)="","",INDEX('_pockets'!$AB:$AB,$S57)))*IF($U$18,100,1)) | J57: =IF($S57="","",IF(INDEX('_pockets'!$Z:$Z,$S57)="","",INDEX('_pockets'!$Z:$Z,$S57))) | K57: =IF($S57="","",IF(INDEX('_pockets'!$AO:$AO,$S57)="","",INDEX('_pockets'!$AO:$AO,$S57))) | L57: =IF($S57="","",IF(INDEX('_pockets'!$AC:$AC,$S57)="","",INDEX('_pockets'!$AC:$AC,$S57))) | M57: =IF($R57="","",IF(INDEX('_list'!$L$2:$L$246,$R57)="","",INDEX('_list'!$L$2:$L$246,$R57))) | N57: =IF($R57="","",IF(INDEX('_list'!$H$2:$H$246,$R57)="","",INDEX('_list'!$H$2:$H$246,$R57))) | O57: =IF($R57="","",IF(INDEX('_list'!$I$2:$I$246,$R57)="","",INDEX('_list'!$I$2:$I$246,$R57))) | R57: =IFERROR(MATCH(38,'_list'!$N$2:$N$246,0),"") | S57: =IF($R57="","",INDEX('_list'!$C$2:$C$246,$R57))
B58: =IF($R58="","",39) | C58: =IF($R58="","",IF(INDEX('_list'!$D$2:$D$246,$R58)="","",INDEX('_list'!$D$2:$D$246,$R58))) | D58: =IF($R58="","",IF(INDEX('_list'!$E$2:$E$246,$R58)="","",INDEX('_list'!$E$2:$E$246,$R58))) | E58: =IF($R58="","",IF(INDEX('_list'!$F$2:$F$246,$R58)="","",INDEX('_list'!$F$2:$F$246,$R58))) | F58: =IF($R58="","",IF(INDEX('_list'!$G$2:$G$246,$R58)="","",INDEX('_list'!$G$2:$G$246,$R58))) | G58: =IF($S58="","",IF(INDEX('_pockets'!$AH:$AH,$S58)="","",INDEX('_pockets'!$AH:$AH,$S58))) | H58: =IF($S58="","",IF(INDEX('_pockets'!$AF:$AF,$S58)="","",INDEX('_pockets'!$AF:$AF,$S58))) | I58: =IF(IF($S58="","",IF(INDEX('_pockets'!$AB:$AB,$S58)="","",INDEX('_pockets'!$AB:$AB,$S58)))="","",IF($S58="","",IF(INDEX('_pockets'!$AB:$AB,$S58)="","",INDEX('_pockets'!$AB:$AB,$S58)))*IF($U$18,100,1)) | J58: =IF($S58="","",IF(INDEX('_pockets'!$Z:$Z,$S58)="","",INDEX('_pockets'!$Z:$Z,$S58))) | K58: =IF($S58="","",IF(INDEX('_pockets'!$AO:$AO,$S58)="","",INDEX('_pockets'!$AO:$AO,$S58))) | L58: =IF($S58="","",IF(INDEX('_pockets'!$AC:$AC,$S58)="","",INDEX('_pockets'!$AC:$AC,$S58))) | M58: =IF($R58="","",IF(INDEX('_list'!$L$2:$L$246,$R58)="","",INDEX('_list'!$L$2:$L$246,$R58))) | N58: =IF($R58="","",IF(INDEX('_list'!$H$2:$H$246,$R58)="","",INDEX('_list'!$H$2:$H$246,$R58))) | O58: =IF($R58="","",IF(INDEX('_list'!$I$2:$I$246,$R58)="","",INDEX('_list'!$I$2:$I$246,$R58))) | R58: =IFERROR(MATCH(39,'_list'!$N$2:$N$246,0),"") | S58: =IF($R58="","",INDEX('_list'!$C$2:$C$246,$R58))
B59: =IF($R59="","",40) | C59: =IF($R59="","",IF(INDEX('_list'!$D$2:$D$246,$R59)="","",INDEX('_list'!$D$2:$D$246,$R59))) | D59: =IF($R59="","",IF(INDEX('_list'!$E$2:$E$246,$R59)="","",INDEX('_list'!$E$2:$E$246,$R59))) | E59: =IF($R59="","",IF(INDEX('_list'!$F$2:$F$246,$R59)="","",INDEX('_list'!$F$2:$F$246,$R59))) | F59: =IF($R59="","",IF(INDEX('_list'!$G$2:$G$246,$R59)="","",INDEX('_list'!$G$2:$G$246,$R59))) | G59: =IF($S59="","",IF(INDEX('_pockets'!$AH:$AH,$S59)="","",INDEX('_pockets'!$AH:$AH,$S59))) | H59: =IF($S59="","",IF(INDEX('_pockets'!$AF:$AF,$S59)="","",INDEX('_pockets'!$AF:$AF,$S59))) | I59: =IF(IF($S59="","",IF(INDEX('_pockets'!$AB:$AB,$S59)="","",INDEX('_pockets'!$AB:$AB,$S59)))="","",IF($S59="","",IF(INDEX('_pockets'!$AB:$AB,$S59)="","",INDEX('_pockets'!$AB:$AB,$S59)))*IF($U$18,100,1)) | J59: =IF($S59="","",IF(INDEX('_pockets'!$Z:$Z,$S59)="","",INDEX('_pockets'!$Z:$Z,$S59))) | K59: =IF($S59="","",IF(INDEX('_pockets'!$AO:$AO,$S59)="","",INDEX('_pockets'!$AO:$AO,$S59))) | L59: =IF($S59="","",IF(INDEX('_pockets'!$AC:$AC,$S59)="","",INDEX('_pockets'!$AC:$AC,$S59))) | M59: =IF($R59="","",IF(INDEX('_list'!$L$2:$L$246,$R59)="","",INDEX('_list'!$L$2:$L$246,$R59))) | N59: =IF($R59="","",IF(INDEX('_list'!$H$2:$H$246,$R59)="","",INDEX('_list'!$H$2:$H$246,$R59))) | O59: =IF($R59="","",IF(INDEX('_list'!$I$2:$I$246,$R59)="","",INDEX('_list'!$I$2:$I$246,$R59))) | R59: =IFERROR(MATCH(40,'_list'!$N$2:$N$246,0),"") | S59: =IF($R59="","",INDEX('_list'!$C$2:$C$246,$R59))
B60: =IF($R60="","",41) | C60: =IF($R60="","",IF(INDEX('_list'!$D$2:$D$246,$R60)="","",INDEX('_list'!$D$2:$D$246,$R60))) | D60: =IF($R60="","",IF(INDEX('_list'!$E$2:$E$246,$R60)="","",INDEX('_list'!$E$2:$E$246,$R60))) | E60: =IF($R60="","",IF(INDEX('_list'!$F$2:$F$246,$R60)="","",INDEX('_list'!$F$2:$F$246,$R60))) | F60: =IF($R60="","",IF(INDEX('_list'!$G$2:$G$246,$R60)="","",INDEX('_list'!$G$2:$G$246,$R60))) | G60: =IF($S60="","",IF(INDEX('_pockets'!$AH:$AH,$S60)="","",INDEX('_pockets'!$AH:$AH,$S60))) | H60: =IF($S60="","",IF(INDEX('_pockets'!$AF:$AF,$S60)="","",INDEX('_pockets'!$AF:$AF,$S60))) | I60: =IF(IF($S60="","",IF(INDEX('_pockets'!$AB:$AB,$S60)="","",INDEX('_pockets'!$AB:$AB,$S60)))="","",IF($S60="","",IF(INDEX('_pockets'!$AB:$AB,$S60)="","",INDEX('_pockets'!$AB:$AB,$S60)))*IF($U$18,100,1)) | J60: =IF($S60="","",IF(INDEX('_pockets'!$Z:$Z,$S60)="","",INDEX('_pockets'!$Z:$Z,$S60))) | K60: =IF($S60="","",IF(INDEX('_pockets'!$AO:$AO,$S60)="","",INDEX('_pockets'!$AO:$AO,$S60))) | L60: =IF($S60="","",IF(INDEX('_pockets'!$AC:$AC,$S60)="","",INDEX('_pockets'!$AC:$AC,$S60))) | M60: =IF($R60="","",IF(INDEX('_list'!$L$2:$L$246,$R60)="","",INDEX('_list'!$L$2:$L$246,$R60))) | N60: =IF($R60="","",IF(INDEX('_list'!$H$2:$H$246,$R60)="","",INDEX('_list'!$H$2:$H$246,$R60))) | O60: =IF($R60="","",IF(INDEX('_list'!$I$2:$I$246,$R60)="","",INDEX('_list'!$I$2:$I$246,$R60))) | R60: =IFERROR(MATCH(41,'_list'!$N$2:$N$246,0),"") | S60: =IF($R60="","",INDEX('_list'!$C$2:$C$246,$R60))
B61: =IF($R61="","",42) | C61: =IF($R61="","",IF(INDEX('_list'!$D$2:$D$246,$R61)="","",INDEX('_list'!$D$2:$D$246,$R61))) | D61: =IF($R61="","",IF(INDEX('_list'!$E$2:$E$246,$R61)="","",INDEX('_list'!$E$2:$E$246,$R61))) | E61: =IF($R61="","",IF(INDEX('_list'!$F$2:$F$246,$R61)="","",INDEX('_list'!$F$2:$F$246,$R61))) | F61: =IF($R61="","",IF(INDEX('_list'!$G$2:$G$246,$R61)="","",INDEX('_list'!$G$2:$G$246,$R61))) | G61: =IF($S61="","",IF(INDEX('_pockets'!$AH:$AH,$S61)="","",INDEX('_pockets'!$AH:$AH,$S61))) | H61: =IF($S61="","",IF(INDEX('_pockets'!$AF:$AF,$S61)="","",INDEX('_pockets'!$AF:$AF,$S61))) | I61: =IF(IF($S61="","",IF(INDEX('_pockets'!$AB:$AB,$S61)="","",INDEX('_pockets'!$AB:$AB,$S61)))="","",IF($S61="","",IF(INDEX('_pockets'!$AB:$AB,$S61)="","",INDEX('_pockets'!$AB:$AB,$S61)))*IF($U$18,100,1)) | J61: =IF($S61="","",IF(INDEX('_pockets'!$Z:$Z,$S61)="","",INDEX('_pockets'!$Z:$Z,$S61))) | K61: =IF($S61="","",IF(INDEX('_pockets'!$AO:$AO,$S61)="","",INDEX('_pockets'!$AO:$AO,$S61))) | L61: =IF($S61="","",IF(INDEX('_pockets'!$AC:$AC,$S61)="","",INDEX('_pockets'!$AC:$AC,$S61))) | M61: =IF($R61="","",IF(INDEX('_list'!$L$2:$L$246,$R61)="","",INDEX('_list'!$L$2:$L$246,$R61))) | N61: =IF($R61="","",IF(INDEX('_list'!$H$2:$H$246,$R61)="","",INDEX('_list'!$H$2:$H$246,$R61))) | O61: =IF($R61="","",IF(INDEX('_list'!$I$2:$I$246,$R61)="","",INDEX('_list'!$I$2:$I$246,$R61))) | R61: =IFERROR(MATCH(42,'_list'!$N$2:$N$246,0),"") | S61: =IF($R61="","",INDEX('_list'!$C$2:$C$246,$R61))
B62: =IF($R62="","",43) | C62: =IF($R62="","",IF(INDEX('_list'!$D$2:$D$246,$R62)="","",INDEX('_list'!$D$2:$D$246,$R62))) | D62: =IF($R62="","",IF(INDEX('_list'!$E$2:$E$246,$R62)="","",INDEX('_list'!$E$2:$E$246,$R62))) | E62: =IF($R62="","",IF(INDEX('_list'!$F$2:$F$246,$R62)="","",INDEX('_list'!$F$2:$F$246,$R62))) | F62: =IF($R62="","",IF(INDEX('_list'!$G$2:$G$246,$R62)="","",INDEX('_list'!$G$2:$G$246,$R62))) | G62: =IF($S62="","",IF(INDEX('_pockets'!$AH:$AH,$S62)="","",INDEX('_pockets'!$AH:$AH,$S62))) | H62: =IF($S62="","",IF(INDEX('_pockets'!$AF:$AF,$S62)="","",INDEX('_pockets'!$AF:$AF,$S62))) | I62: =IF(IF($S62="","",IF(INDEX('_pockets'!$AB:$AB,$S62)="","",INDEX('_pockets'!$AB:$AB,$S62)))="","",IF($S62="","",IF(INDEX('_pockets'!$AB:$AB,$S62)="","",INDEX('_pockets'!$AB:$AB,$S62)))*IF($U$18,100,1)) | J62: =IF($S62="","",IF(INDEX('_pockets'!$Z:$Z,$S62)="","",INDEX('_pockets'!$Z:$Z,$S62))) | K62: =IF($S62="","",IF(INDEX('_pockets'!$AO:$AO,$S62)="","",INDEX('_pockets'!$AO:$AO,$S62))) | L62: =IF($S62="","",IF(INDEX('_pockets'!$AC:$AC,$S62)="","",INDEX('_pockets'!$AC:$AC,$S62))) | M62: =IF($R62="","",IF(INDEX('_list'!$L$2:$L$246,$R62)="","",INDEX('_list'!$L$2:$L$246,$R62))) | N62: =IF($R62="","",IF(INDEX('_list'!$H$2:$H$246,$R62)="","",INDEX('_list'!$H$2:$H$246,$R62))) | O62: =IF($R62="","",IF(INDEX('_list'!$I$2:$I$246,$R62)="","",INDEX('_list'!$I$2:$I$246,$R62))) | R62: =IFERROR(MATCH(43,'_list'!$N$2:$N$246,0),"") | S62: =IF($R62="","",INDEX('_list'!$C$2:$C$246,$R62))
B63: =IF($R63="","",44) | C63: =IF($R63="","",IF(INDEX('_list'!$D$2:$D$246,$R63)="","",INDEX('_list'!$D$2:$D$246,$R63))) | D63: =IF($R63="","",IF(INDEX('_list'!$E$2:$E$246,$R63)="","",INDEX('_list'!$E$2:$E$246,$R63))) | E63: =IF($R63="","",IF(INDEX('_list'!$F$2:$F$246,$R63)="","",INDEX('_list'!$F$2:$F$246,$R63))) | F63: =IF($R63="","",IF(INDEX('_list'!$G$2:$G$246,$R63)="","",INDEX('_list'!$G$2:$G$246,$R63))) | G63: =IF($S63="","",IF(INDEX('_pockets'!$AH:$AH,$S63)="","",INDEX('_pockets'!$AH:$AH,$S63))) | H63: =IF($S63="","",IF(INDEX('_pockets'!$AF:$AF,$S63)="","",INDEX('_pockets'!$AF:$AF,$S63))) | I63: =IF(IF($S63="","",IF(INDEX('_pockets'!$AB:$AB,$S63)="","",INDEX('_pockets'!$AB:$AB,$S63)))="","",IF($S63="","",IF(INDEX('_pockets'!$AB:$AB,$S63)="","",INDEX('_pockets'!$AB:$AB,$S63)))*IF($U$18,100,1)) | J63: =IF($S63="","",IF(INDEX('_pockets'!$Z:$Z,$S63)="","",INDEX('_pockets'!$Z:$Z,$S63))) | K63: =IF($S63="","",IF(INDEX('_pockets'!$AO:$AO,$S63)="","",INDEX('_pockets'!$AO:$AO,$S63))) | L63: =IF($S63="","",IF(INDEX('_pockets'!$AC:$AC,$S63)="","",INDEX('_pockets'!$AC:$AC,$S63))) | M63: =IF($R63="","",IF(INDEX('_list'!$L$2:$L$246,$R63)="","",INDEX('_list'!$L$2:$L$246,$R63))) | N63: =IF($R63="","",IF(INDEX('_list'!$H$2:$H$246,$R63)="","",INDEX('_list'!$H$2:$H$246,$R63))) | O63: =IF($R63="","",IF(INDEX('_list'!$I$2:$I$246,$R63)="","",INDEX('_list'!$I$2:$I$246,$R63))) | R63: =IFERROR(MATCH(44,'_list'!$N$2:$N$246,0),"") | S63: =IF($R63="","",INDEX('_list'!$C$2:$C$246,$R63))
B64: =IF($R64="","",45) | C64: =IF($R64="","",IF(INDEX('_list'!$D$2:$D$246,$R64)="","",INDEX('_list'!$D$2:$D$246,$R64))) | D64: =IF($R64="","",IF(INDEX('_list'!$E$2:$E$246,$R64)="","",INDEX('_list'!$E$2:$E$246,$R64))) | E64: =IF($R64="","",IF(INDEX('_list'!$F$2:$F$246,$R64)="","",INDEX('_list'!$F$2:$F$246,$R64))) | F64: =IF($R64="","",IF(INDEX('_list'!$G$2:$G$246,$R64)="","",INDEX('_list'!$G$2:$G$246,$R64))) | G64: =IF($S64="","",IF(INDEX('_pockets'!$AH:$AH,$S64)="","",INDEX('_pockets'!$AH:$AH,$S64))) | H64: =IF($S64="","",IF(INDEX('_pockets'!$AF:$AF,$S64)="","",INDEX('_pockets'!$AF:$AF,$S64))) | I64: =IF(IF($S64="","",IF(INDEX('_pockets'!$AB:$AB,$S64)="","",INDEX('_pockets'!$AB:$AB,$S64)))="","",IF($S64="","",IF(INDEX('_pockets'!$AB:$AB,$S64)="","",INDEX('_pockets'!$AB:$AB,$S64)))*IF($U$18,100,1)) | J64: =IF($S64="","",IF(INDEX('_pockets'!$Z:$Z,$S64)="","",INDEX('_pockets'!$Z:$Z,$S64))) | K64: =IF($S64="","",IF(INDEX('_pockets'!$AO:$AO,$S64)="","",INDEX('_pockets'!$AO:$AO,$S64))) | L64: =IF($S64="","",IF(INDEX('_pockets'!$AC:$AC,$S64)="","",INDEX('_pockets'!$AC:$AC,$S64))) | M64: =IF($R64="","",IF(INDEX('_list'!$L$2:$L$246,$R64)="","",INDEX('_list'!$L$2:$L$246,$R64))) | N64: =IF($R64="","",IF(INDEX('_list'!$H$2:$H$246,$R64)="","",INDEX('_list'!$H$2:$H$246,$R64))) | O64: =IF($R64="","",IF(INDEX('_list'!$I$2:$I$246,$R64)="","",INDEX('_list'!$I$2:$I$246,$R64))) | R64: =IFERROR(MATCH(45,'_list'!$N$2:$N$246,0),"") | S64: =IF($R64="","",INDEX('_list'!$C$2:$C$246,$R64))
B65: =IF($R65="","",46) | C65: =IF($R65="","",IF(INDEX('_list'!$D$2:$D$246,$R65)="","",INDEX('_list'!$D$2:$D$246,$R65))) | D65: =IF($R65="","",IF(INDEX('_list'!$E$2:$E$246,$R65)="","",INDEX('_list'!$E$2:$E$246,$R65))) | E65: =IF($R65="","",IF(INDEX('_list'!$F$2:$F$246,$R65)="","",INDEX('_list'!$F$2:$F$246,$R65))) | F65: =IF($R65="","",IF(INDEX('_list'!$G$2:$G$246,$R65)="","",INDEX('_list'!$G$2:$G$246,$R65))) | G65: =IF($S65="","",IF(INDEX('_pockets'!$AH:$AH,$S65)="","",INDEX('_pockets'!$AH:$AH,$S65))) | H65: =IF($S65="","",IF(INDEX('_pockets'!$AF:$AF,$S65)="","",INDEX('_pockets'!$AF:$AF,$S65))) | I65: =IF(IF($S65="","",IF(INDEX('_pockets'!$AB:$AB,$S65)="","",INDEX('_pockets'!$AB:$AB,$S65)))="","",IF($S65="","",IF(INDEX('_pockets'!$AB:$AB,$S65)="","",INDEX('_pockets'!$AB:$AB,$S65)))*IF($U$18,100,1)) | J65: =IF($S65="","",IF(INDEX('_pockets'!$Z:$Z,$S65)="","",INDEX('_pockets'!$Z:$Z,$S65))) | K65: =IF($S65="","",IF(INDEX('_pockets'!$AO:$AO,$S65)="","",INDEX('_pockets'!$AO:$AO,$S65))) | L65: =IF($S65="","",IF(INDEX('_pockets'!$AC:$AC,$S65)="","",INDEX('_pockets'!$AC:$AC,$S65))) | M65: =IF($R65="","",IF(INDEX('_list'!$L$2:$L$246,$R65)="","",INDEX('_list'!$L$2:$L$246,$R65))) | N65: =IF($R65="","",IF(INDEX('_list'!$H$2:$H$246,$R65)="","",INDEX('_list'!$H$2:$H$246,$R65))) | O65: =IF($R65="","",IF(INDEX('_list'!$I$2:$I$246,$R65)="","",INDEX('_list'!$I$2:$I$246,$R65))) | R65: =IFERROR(MATCH(46,'_list'!$N$2:$N$246,0),"") | S65: =IF($R65="","",INDEX('_list'!$C$2:$C$246,$R65))
B66: =IF($R66="","",47) | C66: =IF($R66="","",IF(INDEX('_list'!$D$2:$D$246,$R66)="","",INDEX('_list'!$D$2:$D$246,$R66))) | D66: =IF($R66="","",IF(INDEX('_list'!$E$2:$E$246,$R66)="","",INDEX('_list'!$E$2:$E$246,$R66))) | E66: =IF($R66="","",IF(INDEX('_list'!$F$2:$F$246,$R66)="","",INDEX('_list'!$F$2:$F$246,$R66))) | F66: =IF($R66="","",IF(INDEX('_list'!$G$2:$G$246,$R66)="","",INDEX('_list'!$G$2:$G$246,$R66))) | G66: =IF($S66="","",IF(INDEX('_pockets'!$AH:$AH,$S66)="","",INDEX('_pockets'!$AH:$AH,$S66))) | H66: =IF($S66="","",IF(INDEX('_pockets'!$AF:$AF,$S66)="","",INDEX('_pockets'!$AF:$AF,$S66))) | I66: =IF(IF($S66="","",IF(INDEX('_pockets'!$AB:$AB,$S66)="","",INDEX('_pockets'!$AB:$AB,$S66)))="","",IF($S66="","",IF(INDEX('_pockets'!$AB:$AB,$S66)="","",INDEX('_pockets'!$AB:$AB,$S66)))*IF($U$18,100,1)) | J66: =IF($S66="","",IF(INDEX('_pockets'!$Z:$Z,$S66)="","",INDEX('_pockets'!$Z:$Z,$S66))) | K66: =IF($S66="","",IF(INDEX('_pockets'!$AO:$AO,$S66)="","",INDEX('_pockets'!$AO:$AO,$S66))) | L66: =IF($S66="","",IF(INDEX('_pockets'!$AC:$AC,$S66)="","",INDEX('_pockets'!$AC:$AC,$S66))) | M66: =IF($R66="","",IF(INDEX('_list'!$L$2:$L$246,$R66)="","",INDEX('_list'!$L$2:$L$246,$R66))) | N66: =IF($R66="","",IF(INDEX('_list'!$H$2:$H$246,$R66)="","",INDEX('_list'!$H$2:$H$246,$R66))) | O66: =IF($R66="","",IF(INDEX('_list'!$I$2:$I$246,$R66)="","",INDEX('_list'!$I$2:$I$246,$R66))) | R66: =IFERROR(MATCH(47,'_list'!$N$2:$N$246,0),"") | S66: =IF($R66="","",INDEX('_list'!$C$2:$C$246,$R66))
B67: =IF($R67="","",48) | C67: =IF($R67="","",IF(INDEX('_list'!$D$2:$D$246,$R67)="","",INDEX('_list'!$D$2:$D$246,$R67))) | D67: =IF($R67="","",IF(INDEX('_list'!$E$2:$E$246,$R67)="","",INDEX('_list'!$E$2:$E$246,$R67))) | E67: =IF($R67="","",IF(INDEX('_list'!$F$2:$F$246,$R67)="","",INDEX('_list'!$F$2:$F$246,$R67))) | F67: =IF($R67="","",IF(INDEX('_list'!$G$2:$G$246,$R67)="","",INDEX('_list'!$G$2:$G$246,$R67))) | G67: =IF($S67="","",IF(INDEX('_pockets'!$AH:$AH,$S67)="","",INDEX('_pockets'!$AH:$AH,$S67))) | H67: =IF($S67="","",IF(INDEX('_pockets'!$AF:$AF,$S67)="","",INDEX('_pockets'!$AF:$AF,$S67))) | I67: =IF(IF($S67="","",IF(INDEX('_pockets'!$AB:$AB,$S67)="","",INDEX('_pockets'!$AB:$AB,$S67)))="","",IF($S67="","",IF(INDEX('_pockets'!$AB:$AB,$S67)="","",INDEX('_pockets'!$AB:$AB,$S67)))*IF($U$18,100,1)) | J67: =IF($S67="","",IF(INDEX('_pockets'!$Z:$Z,$S67)="","",INDEX('_pockets'!$Z:$Z,$S67))) | K67: =IF($S67="","",IF(INDEX('_pockets'!$AO:$AO,$S67)="","",INDEX('_pockets'!$AO:$AO,$S67))) | L67: =IF($S67="","",IF(INDEX('_pockets'!$AC:$AC,$S67)="","",INDEX('_pockets'!$AC:$AC,$S67))) | M67: =IF($R67="","",IF(INDEX('_list'!$L$2:$L$246,$R67)="","",INDEX('_list'!$L$2:$L$246,$R67))) | N67: =IF($R67="","",IF(INDEX('_list'!$H$2:$H$246,$R67)="","",INDEX('_list'!$H$2:$H$246,$R67))) | O67: =IF($R67="","",IF(INDEX('_list'!$I$2:$I$246,$R67)="","",INDEX('_list'!$I$2:$I$246,$R67))) | R67: =IFERROR(MATCH(48,'_list'!$N$2:$N$246,0),"") | S67: =IF($R67="","",INDEX('_list'!$C$2:$C$246,$R67))
B68: =IF($R68="","",49) | C68: =IF($R68="","",IF(INDEX('_list'!$D$2:$D$246,$R68)="","",INDEX('_list'!$D$2:$D$246,$R68))) | D68: =IF($R68="","",IF(INDEX('_list'!$E$2:$E$246,$R68)="","",INDEX('_list'!$E$2:$E$246,$R68))) | E68: =IF($R68="","",IF(INDEX('_list'!$F$2:$F$246,$R68)="","",INDEX('_list'!$F$2:$F$246,$R68))) | F68: =IF($R68="","",IF(INDEX('_list'!$G$2:$G$246,$R68)="","",INDEX('_list'!$G$2:$G$246,$R68))) | G68: =IF($S68="","",IF(INDEX('_pockets'!$AH:$AH,$S68)="","",INDEX('_pockets'!$AH:$AH,$S68))) | H68: =IF($S68="","",IF(INDEX('_pockets'!$AF:$AF,$S68)="","",INDEX('_pockets'!$AF:$AF,$S68))) | I68: =IF(IF($S68="","",IF(INDEX('_pockets'!$AB:$AB,$S68)="","",INDEX('_pockets'!$AB:$AB,$S68)))="","",IF($S68="","",IF(INDEX('_pockets'!$AB:$AB,$S68)="","",INDEX('_pockets'!$AB:$AB,$S68)))*IF($U$18,100,1)) | J68: =IF($S68="","",IF(INDEX('_pockets'!$Z:$Z,$S68)="","",INDEX('_pockets'!$Z:$Z,$S68))) | K68: =IF($S68="","",IF(INDEX('_pockets'!$AO:$AO,$S68)="","",INDEX('_pockets'!$AO:$AO,$S68))) | L68: =IF($S68="","",IF(INDEX('_pockets'!$AC:$AC,$S68)="","",INDEX('_pockets'!$AC:$AC,$S68))) | M68: =IF($R68="","",IF(INDEX('_list'!$L$2:$L$246,$R68)="","",INDEX('_list'!$L$2:$L$246,$R68))) | N68: =IF($R68="","",IF(INDEX('_list'!$H$2:$H$246,$R68)="","",INDEX('_list'!$H$2:$H$246,$R68))) | O68: =IF($R68="","",IF(INDEX('_list'!$I$2:$I$246,$R68)="","",INDEX('_list'!$I$2:$I$246,$R68))) | R68: =IFERROR(MATCH(49,'_list'!$N$2:$N$246,0),"") | S68: =IF($R68="","",INDEX('_list'!$C$2:$C$246,$R68))
B69: =IF($R69="","",50) | C69: =IF($R69="","",IF(INDEX('_list'!$D$2:$D$246,$R69)="","",INDEX('_list'!$D$2:$D$246,$R69))) | D69: =IF($R69="","",IF(INDEX('_list'!$E$2:$E$246,$R69)="","",INDEX('_list'!$E$2:$E$246,$R69))) | E69: =IF($R69="","",IF(INDEX('_list'!$F$2:$F$246,$R69)="","",INDEX('_list'!$F$2:$F$246,$R69))) | F69: =IF($R69="","",IF(INDEX('_list'!$G$2:$G$246,$R69)="","",INDEX('_list'!$G$2:$G$246,$R69))) | G69: =IF($S69="","",IF(INDEX('_pockets'!$AH:$AH,$S69)="","",INDEX('_pockets'!$AH:$AH,$S69))) | H69: =IF($S69="","",IF(INDEX('_pockets'!$AF:$AF,$S69)="","",INDEX('_pockets'!$AF:$AF,$S69))) | I69: =IF(IF($S69="","",IF(INDEX('_pockets'!$AB:$AB,$S69)="","",INDEX('_pockets'!$AB:$AB,$S69)))="","",IF($S69="","",IF(INDEX('_pockets'!$AB:$AB,$S69)="","",INDEX('_pockets'!$AB:$AB,$S69)))*IF($U$18,100,1)) | J69: =IF($S69="","",IF(INDEX('_pockets'!$Z:$Z,$S69)="","",INDEX('_pockets'!$Z:$Z,$S69))) | K69: =IF($S69="","",IF(INDEX('_pockets'!$AO:$AO,$S69)="","",INDEX('_pockets'!$AO:$AO,$S69))) | L69: =IF($S69="","",IF(INDEX('_pockets'!$AC:$AC,$S69)="","",INDEX('_pockets'!$AC:$AC,$S69))) | M69: =IF($R69="","",IF(INDEX('_list'!$L$2:$L$246,$R69)="","",INDEX('_list'!$L$2:$L$246,$R69))) | N69: =IF($R69="","",IF(INDEX('_list'!$H$2:$H$246,$R69)="","",INDEX('_list'!$H$2:$H$246,$R69))) | O69: =IF($R69="","",IF(INDEX('_list'!$I$2:$I$246,$R69)="","",INDEX('_list'!$I$2:$I$246,$R69))) | R69: =IFERROR(MATCH(50,'_list'!$N$2:$N$246,0),"") | S69: =IF($R69="","",INDEX('_list'!$C$2:$C$246,$R69))
B70: =IF($R70="","",51) | C70: =IF($R70="","",IF(INDEX('_list'!$D$2:$D$246,$R70)="","",INDEX('_list'!$D$2:$D$246,$R70))) | D70: =IF($R70="","",IF(INDEX('_list'!$E$2:$E$246,$R70)="","",INDEX('_list'!$E$2:$E$246,$R70))) | E70: =IF($R70="","",IF(INDEX('_list'!$F$2:$F$246,$R70)="","",INDEX('_list'!$F$2:$F$246,$R70))) | F70: =IF($R70="","",IF(INDEX('_list'!$G$2:$G$246,$R70)="","",INDEX('_list'!$G$2:$G$246,$R70))) | G70: =IF($S70="","",IF(INDEX('_pockets'!$AH:$AH,$S70)="","",INDEX('_pockets'!$AH:$AH,$S70))) | H70: =IF($S70="","",IF(INDEX('_pockets'!$AF:$AF,$S70)="","",INDEX('_pockets'!$AF:$AF,$S70))) | I70: =IF(IF($S70="","",IF(INDEX('_pockets'!$AB:$AB,$S70)="","",INDEX('_pockets'!$AB:$AB,$S70)))="","",IF($S70="","",IF(INDEX('_pockets'!$AB:$AB,$S70)="","",INDEX('_pockets'!$AB:$AB,$S70)))*IF($U$18,100,1)) | J70: =IF($S70="","",IF(INDEX('_pockets'!$Z:$Z,$S70)="","",INDEX('_pockets'!$Z:$Z,$S70))) | K70: =IF($S70="","",IF(INDEX('_pockets'!$AO:$AO,$S70)="","",INDEX('_pockets'!$AO:$AO,$S70))) | L70: =IF($S70="","",IF(INDEX('_pockets'!$AC:$AC,$S70)="","",INDEX('_pockets'!$AC:$AC,$S70))) | M70: =IF($R70="","",IF(INDEX('_list'!$L$2:$L$246,$R70)="","",INDEX('_list'!$L$2:$L$246,$R70))) | N70: =IF($R70="","",IF(INDEX('_list'!$H$2:$H$246,$R70)="","",INDEX('_list'!$H$2:$H$246,$R70))) | O70: =IF($R70="","",IF(INDEX('_list'!$I$2:$I$246,$R70)="","",INDEX('_list'!$I$2:$I$246,$R70))) | R70: =IFERROR(MATCH(51,'_list'!$N$2:$N$246,0),"") | S70: =IF($R70="","",INDEX('_list'!$C$2:$C$246,$R70))
B71: =IF($R71="","",52) | C71: =IF($R71="","",IF(INDEX('_list'!$D$2:$D$246,$R71)="","",INDEX('_list'!$D$2:$D$246,$R71))) | D71: =IF($R71="","",IF(INDEX('_list'!$E$2:$E$246,$R71)="","",INDEX('_list'!$E$2:$E$246,$R71))) | E71: =IF($R71="","",IF(INDEX('_list'!$F$2:$F$246,$R71)="","",INDEX('_list'!$F$2:$F$246,$R71))) | F71: =IF($R71="","",IF(INDEX('_list'!$G$2:$G$246,$R71)="","",INDEX('_list'!$G$2:$G$246,$R71))) | G71: =IF($S71="","",IF(INDEX('_pockets'!$AH:$AH,$S71)="","",INDEX('_pockets'!$AH:$AH,$S71))) | H71: =IF($S71="","",IF(INDEX('_pockets'!$AF:$AF,$S71)="","",INDEX('_pockets'!$AF:$AF,$S71))) | I71: =IF(IF($S71="","",IF(INDEX('_pockets'!$AB:$AB,$S71)="","",INDEX('_pockets'!$AB:$AB,$S71)))="","",IF($S71="","",IF(INDEX('_pockets'!$AB:$AB,$S71)="","",INDEX('_pockets'!$AB:$AB,$S71)))*IF($U$18,100,1)) | J71: =IF($S71="","",IF(INDEX('_pockets'!$Z:$Z,$S71)="","",INDEX('_pockets'!$Z:$Z,$S71))) | K71: =IF($S71="","",IF(INDEX('_pockets'!$AO:$AO,$S71)="","",INDEX('_pockets'!$AO:$AO,$S71))) | L71: =IF($S71="","",IF(INDEX('_pockets'!$AC:$AC,$S71)="","",INDEX('_pockets'!$AC:$AC,$S71))) | M71: =IF($R71="","",IF(INDEX('_list'!$L$2:$L$246,$R71)="","",INDEX('_list'!$L$2:$L$246,$R71))) | N71: =IF($R71="","",IF(INDEX('_list'!$H$2:$H$246,$R71)="","",INDEX('_list'!$H$2:$H$246,$R71))) | O71: =IF($R71="","",IF(INDEX('_list'!$I$2:$I$246,$R71)="","",INDEX('_list'!$I$2:$I$246,$R71))) | R71: =IFERROR(MATCH(52,'_list'!$N$2:$N$246,0),"") | S71: =IF($R71="","",INDEX('_list'!$C$2:$C$246,$R71))
B72: =IF($R72="","",53) | C72: =IF($R72="","",IF(INDEX('_list'!$D$2:$D$246,$R72)="","",INDEX('_list'!$D$2:$D$246,$R72))) | D72: =IF($R72="","",IF(INDEX('_list'!$E$2:$E$246,$R72)="","",INDEX('_list'!$E$2:$E$246,$R72))) | E72: =IF($R72="","",IF(INDEX('_list'!$F$2:$F$246,$R72)="","",INDEX('_list'!$F$2:$F$246,$R72))) | F72: =IF($R72="","",IF(INDEX('_list'!$G$2:$G$246,$R72)="","",INDEX('_list'!$G$2:$G$246,$R72))) | G72: =IF($S72="","",IF(INDEX('_pockets'!$AH:$AH,$S72)="","",INDEX('_pockets'!$AH:$AH,$S72))) | H72: =IF($S72="","",IF(INDEX('_pockets'!$AF:$AF,$S72)="","",INDEX('_pockets'!$AF:$AF,$S72))) | I72: =IF(IF($S72="","",IF(INDEX('_pockets'!$AB:$AB,$S72)="","",INDEX('_pockets'!$AB:$AB,$S72)))="","",IF($S72="","",IF(INDEX('_pockets'!$AB:$AB,$S72)="","",INDEX('_pockets'!$AB:$AB,$S72)))*IF($U$18,100,1)) | J72: =IF($S72="","",IF(INDEX('_pockets'!$Z:$Z,$S72)="","",INDEX('_pockets'!$Z:$Z,$S72))) | K72: =IF($S72="","",IF(INDEX('_pockets'!$AO:$AO,$S72)="","",INDEX('_pockets'!$AO:$AO,$S72))) | L72: =IF($S72="","",IF(INDEX('_pockets'!$AC:$AC,$S72)="","",INDEX('_pockets'!$AC:$AC,$S72))) | M72: =IF($R72="","",IF(INDEX('_list'!$L$2:$L$246,$R72)="","",INDEX('_list'!$L$2:$L$246,$R72))) | N72: =IF($R72="","",IF(INDEX('_list'!$H$2:$H$246,$R72)="","",INDEX('_list'!$H$2:$H$246,$R72))) | O72: =IF($R72="","",IF(INDEX('_list'!$I$2:$I$246,$R72)="","",INDEX('_list'!$I$2:$I$246,$R72))) | R72: =IFERROR(MATCH(53,'_list'!$N$2:$N$246,0),"") | S72: =IF($R72="","",INDEX('_list'!$C$2:$C$246,$R72))
B73: =IF($R73="","",54) | C73: =IF($R73="","",IF(INDEX('_list'!$D$2:$D$246,$R73)="","",INDEX('_list'!$D$2:$D$246,$R73))) | D73: =IF($R73="","",IF(INDEX('_list'!$E$2:$E$246,$R73)="","",INDEX('_list'!$E$2:$E$246,$R73))) | E73: =IF($R73="","",IF(INDEX('_list'!$F$2:$F$246,$R73)="","",INDEX('_list'!$F$2:$F$246,$R73))) | F73: =IF($R73="","",IF(INDEX('_list'!$G$2:$G$246,$R73)="","",INDEX('_list'!$G$2:$G$246,$R73))) | G73: =IF($S73="","",IF(INDEX('_pockets'!$AH:$AH,$S73)="","",INDEX('_pockets'!$AH:$AH,$S73))) | H73: =IF($S73="","",IF(INDEX('_pockets'!$AF:$AF,$S73)="","",INDEX('_pockets'!$AF:$AF,$S73))) | I73: =IF(IF($S73="","",IF(INDEX('_pockets'!$AB:$AB,$S73)="","",INDEX('_pockets'!$AB:$AB,$S73)))="","",IF($S73="","",IF(INDEX('_pockets'!$AB:$AB,$S73)="","",INDEX('_pockets'!$AB:$AB,$S73)))*IF($U$18,100,1)) | J73: =IF($S73="","",IF(INDEX('_pockets'!$Z:$Z,$S73)="","",INDEX('_pockets'!$Z:$Z,$S73))) | K73: =IF($S73="","",IF(INDEX('_pockets'!$AO:$AO,$S73)="","",INDEX('_pockets'!$AO:$AO,$S73))) | L73: =IF($S73="","",IF(INDEX('_pockets'!$AC:$AC,$S73)="","",INDEX('_pockets'!$AC:$AC,$S73))) | M73: =IF($R73="","",IF(INDEX('_list'!$L$2:$L$246,$R73)="","",INDEX('_list'!$L$2:$L$246,$R73))) | N73: =IF($R73="","",IF(INDEX('_list'!$H$2:$H$246,$R73)="","",INDEX('_list'!$H$2:$H$246,$R73))) | O73: =IF($R73="","",IF(INDEX('_list'!$I$2:$I$246,$R73)="","",INDEX('_list'!$I$2:$I$246,$R73))) | R73: =IFERROR(MATCH(54,'_list'!$N$2:$N$246,0),"") | S73: =IF($R73="","",INDEX('_list'!$C$2:$C$246,$R73))
B74: =IF($R74="","",55) | C74: =IF($R74="","",IF(INDEX('_list'!$D$2:$D$246,$R74)="","",INDEX('_list'!$D$2:$D$246,$R74))) | D74: =IF($R74="","",IF(INDEX('_list'!$E$2:$E$246,$R74)="","",INDEX('_list'!$E$2:$E$246,$R74))) | E74: =IF($R74="","",IF(INDEX('_list'!$F$2:$F$246,$R74)="","",INDEX('_list'!$F$2:$F$246,$R74))) | F74: =IF($R74="","",IF(INDEX('_list'!$G$2:$G$246,$R74)="","",INDEX('_list'!$G$2:$G$246,$R74))) | G74: =IF($S74="","",IF(INDEX('_pockets'!$AH:$AH,$S74)="","",INDEX('_pockets'!$AH:$AH,$S74))) | H74: =IF($S74="","",IF(INDEX('_pockets'!$AF:$AF,$S74)="","",INDEX('_pockets'!$AF:$AF,$S74))) | I74: =IF(IF($S74="","",IF(INDEX('_pockets'!$AB:$AB,$S74)="","",INDEX('_pockets'!$AB:$AB,$S74)))="","",IF($S74="","",IF(INDEX('_pockets'!$AB:$AB,$S74)="","",INDEX('_pockets'!$AB:$AB,$S74)))*IF($U$18,100,1)) | J74: =IF($S74="","",IF(INDEX('_pockets'!$Z:$Z,$S74)="","",INDEX('_pockets'!$Z:$Z,$S74))) | K74: =IF($S74="","",IF(INDEX('_pockets'!$AO:$AO,$S74)="","",INDEX('_pockets'!$AO:$AO,$S74))) | L74: =IF($S74="","",IF(INDEX('_pockets'!$AC:$AC,$S74)="","",INDEX('_pockets'!$AC:$AC,$S74))) | M74: =IF($R74="","",IF(INDEX('_list'!$L$2:$L$246,$R74)="","",INDEX('_list'!$L$2:$L$246,$R74))) | N74: =IF($R74="","",IF(INDEX('_list'!$H$2:$H$246,$R74)="","",INDEX('_list'!$H$2:$H$246,$R74))) | O74: =IF($R74="","",IF(INDEX('_list'!$I$2:$I$246,$R74)="","",INDEX('_list'!$I$2:$I$246,$R74))) | R74: =IFERROR(MATCH(55,'_list'!$N$2:$N$246,0),"") | S74: =IF($R74="","",INDEX('_list'!$C$2:$C$246,$R74))
B75: =IF($R75="","",56) | C75: =IF($R75="","",IF(INDEX('_list'!$D$2:$D$246,$R75)="","",INDEX('_list'!$D$2:$D$246,$R75))) | D75: =IF($R75="","",IF(INDEX('_list'!$E$2:$E$246,$R75)="","",INDEX('_list'!$E$2:$E$246,$R75))) | E75: =IF($R75="","",IF(INDEX('_list'!$F$2:$F$246,$R75)="","",INDEX('_list'!$F$2:$F$246,$R75))) | F75: =IF($R75="","",IF(INDEX('_list'!$G$2:$G$246,$R75)="","",INDEX('_list'!$G$2:$G$246,$R75))) | G75: =IF($S75="","",IF(INDEX('_pockets'!$AH:$AH,$S75)="","",INDEX('_pockets'!$AH:$AH,$S75))) | H75: =IF($S75="","",IF(INDEX('_pockets'!$AF:$AF,$S75)="","",INDEX('_pockets'!$AF:$AF,$S75))) | I75: =IF(IF($S75="","",IF(INDEX('_pockets'!$AB:$AB,$S75)="","",INDEX('_pockets'!$AB:$AB,$S75)))="","",IF($S75="","",IF(INDEX('_pockets'!$AB:$AB,$S75)="","",INDEX('_pockets'!$AB:$AB,$S75)))*IF($U$18,100,1)) | J75: =IF($S75="","",IF(INDEX('_pockets'!$Z:$Z,$S75)="","",INDEX('_pockets'!$Z:$Z,$S75))) | K75: =IF($S75="","",IF(INDEX('_pockets'!$AO:$AO,$S75)="","",INDEX('_pockets'!$AO:$AO,$S75))) | L75: =IF($S75="","",IF(INDEX('_pockets'!$AC:$AC,$S75)="","",INDEX('_pockets'!$AC:$AC,$S75))) | M75: =IF($R75="","",IF(INDEX('_list'!$L$2:$L$246,$R75)="","",INDEX('_list'!$L$2:$L$246,$R75))) | N75: =IF($R75="","",IF(INDEX('_list'!$H$2:$H$246,$R75)="","",INDEX('_list'!$H$2:$H$246,$R75))) | O75: =IF($R75="","",IF(INDEX('_list'!$I$2:$I$246,$R75)="","",INDEX('_list'!$I$2:$I$246,$R75))) | R75: =IFERROR(MATCH(56,'_list'!$N$2:$N$246,0),"") | S75: =IF($R75="","",INDEX('_list'!$C$2:$C$246,$R75))
B76: =IF($R76="","",57) | C76: =IF($R76="","",IF(INDEX('_list'!$D$2:$D$246,$R76)="","",INDEX('_list'!$D$2:$D$246,$R76))) | D76: =IF($R76="","",IF(INDEX('_list'!$E$2:$E$246,$R76)="","",INDEX('_list'!$E$2:$E$246,$R76))) | E76: =IF($R76="","",IF(INDEX('_list'!$F$2:$F$246,$R76)="","",INDEX('_list'!$F$2:$F$246,$R76))) | F76: =IF($R76="","",IF(INDEX('_list'!$G$2:$G$246,$R76)="","",INDEX('_list'!$G$2:$G$246,$R76))) | G76: =IF($S76="","",IF(INDEX('_pockets'!$AH:$AH,$S76)="","",INDEX('_pockets'!$AH:$AH,$S76))) | H76: =IF($S76="","",IF(INDEX('_pockets'!$AF:$AF,$S76)="","",INDEX('_pockets'!$AF:$AF,$S76))) | I76: =IF(IF($S76="","",IF(INDEX('_pockets'!$AB:$AB,$S76)="","",INDEX('_pockets'!$AB:$AB,$S76)))="","",IF($S76="","",IF(INDEX('_pockets'!$AB:$AB,$S76)="","",INDEX('_pockets'!$AB:$AB,$S76)))*IF($U$18,100,1)) | J76: =IF($S76="","",IF(INDEX('_pockets'!$Z:$Z,$S76)="","",INDEX('_pockets'!$Z:$Z,$S76))) | K76: =IF($S76="","",IF(INDEX('_pockets'!$AO:$AO,$S76)="","",INDEX('_pockets'!$AO:$AO,$S76))) | L76: =IF($S76="","",IF(INDEX('_pockets'!$AC:$AC,$S76)="","",INDEX('_pockets'!$AC:$AC,$S76))) | M76: =IF($R76="","",IF(INDEX('_list'!$L$2:$L$246,$R76)="","",INDEX('_list'!$L$2:$L$246,$R76))) | N76: =IF($R76="","",IF(INDEX('_list'!$H$2:$H$246,$R76)="","",INDEX('_list'!$H$2:$H$246,$R76))) | O76: =IF($R76="","",IF(INDEX('_list'!$I$2:$I$246,$R76)="","",INDEX('_list'!$I$2:$I$246,$R76))) | R76: =IFERROR(MATCH(57,'_list'!$N$2:$N$246,0),"") | S76: =IF($R76="","",INDEX('_list'!$C$2:$C$246,$R76))
B77: =IF($R77="","",58) | C77: =IF($R77="","",IF(INDEX('_list'!$D$2:$D$246,$R77)="","",INDEX('_list'!$D$2:$D$246,$R77))) | D77: =IF($R77="","",IF(INDEX('_list'!$E$2:$E$246,$R77)="","",INDEX('_list'!$E$2:$E$246,$R77))) | E77: =IF($R77="","",IF(INDEX('_list'!$F$2:$F$246,$R77)="","",INDEX('_list'!$F$2:$F$246,$R77))) | F77: =IF($R77="","",IF(INDEX('_list'!$G$2:$G$246,$R77)="","",INDEX('_list'!$G$2:$G$246,$R77))) | G77: =IF($S77="","",IF(INDEX('_pockets'!$AH:$AH,$S77)="","",INDEX('_pockets'!$AH:$AH,$S77))) | H77: =IF($S77="","",IF(INDEX('_pockets'!$AF:$AF,$S77)="","",INDEX('_pockets'!$AF:$AF,$S77))) | I77: =IF(IF($S77="","",IF(INDEX('_pockets'!$AB:$AB,$S77)="","",INDEX('_pockets'!$AB:$AB,$S77)))="","",IF($S77="","",IF(INDEX('_pockets'!$AB:$AB,$S77)="","",INDEX('_pockets'!$AB:$AB,$S77)))*IF($U$18,100,1)) | J77: =IF($S77="","",IF(INDEX('_pockets'!$Z:$Z,$S77)="","",INDEX('_pockets'!$Z:$Z,$S77))) | K77: =IF($S77="","",IF(INDEX('_pockets'!$AO:$AO,$S77)="","",INDEX('_pockets'!$AO:$AO,$S77))) | L77: =IF($S77="","",IF(INDEX('_pockets'!$AC:$AC,$S77)="","",INDEX('_pockets'!$AC:$AC,$S77))) | M77: =IF($R77="","",IF(INDEX('_list'!$L$2:$L$246,$R77)="","",INDEX('_list'!$L$2:$L$246,$R77))) | N77: =IF($R77="","",IF(INDEX('_list'!$H$2:$H$246,$R77)="","",INDEX('_list'!$H$2:$H$246,$R77))) | O77: =IF($R77="","",IF(INDEX('_list'!$I$2:$I$246,$R77)="","",INDEX('_list'!$I$2:$I$246,$R77))) | R77: =IFERROR(MATCH(58,'_list'!$N$2:$N$246,0),"") | S77: =IF($R77="","",INDEX('_list'!$C$2:$C$246,$R77))

Sheet Paid, cost, kept
B1: Paid, cost, kept | C1: What each pocket paid us, what it cost us, and what we kept.
B3: How this tab works
B4: Paid us | C4: Earned before losses: RANR + GCO per booked dollar. RANR already has the charge-offs taken out, so this adds them back. Gap: points of booked dollars ahead of (+) or short of (-) the rest; Dollars: what that comes to.
B5: Cost us | C5: Charge-offs (GCO) per booked dollar, as a multiple of the rest; Dollars: charge-offs above the rest's rate.
B6: Kept | C6: Kept after losses: RANR per booked dollar, as a gap in points and dollars, like Paid us.
B7: The rest | C7: ="Judged against on Control picks it: now "&IF(judged_band,"the rest of its band","the rest of the book")&". A pocket alone in its band is compared with the rest of the book."
B8: Shading | C8: ="Pink: worse, and real. Green: better, and real. None: it could be chance (the p-value isn't under "&TEXT(significance_bar,"0%")&"), or the pocket has too few losses to test. Charge-offs count at "&TEXT(worse_at,"0.00")&"x or "&TEXT(better_at,"0.00")&"x; profit "&IF(profit_kind="test","when its own test says so",IF(profit_kind="points","at "&TEXT(profit_line*100,"0.00")&" points either way","at a gap of $"&TEXT(profit_line,"#,##0")))&"."
B9: Together | C9: ="The two sides read at once. Priced for it: more charge-offs and more kept. Net drain: more charge-offs and less kept. Strong: fewer charge-offs and more kept. Safe but idle: fewer charge-offs and less kept. Earns less, not from losses: less kept whil"&"e charge-offs are about the same. Losing more, profit holding: more charge-offs while what we kept is about the same. Blank: nothing to read together."&" Borderline: the test's p-value is within the shuffle's own margin of the "&TEXT(significance_bar,"0%")&" bar, so another run could read it the other way."&" Together gives the p-value of each side that is, charge-offs first."
B10: Order and chart | C10: Rows are as of the last Run: the pockets read together first, then by charge-off dollars; a pocket with too few losses last. The chart shows the grid picked above, live; the pockets read together are named on it.
B12: LINES IN USE NOW | C12: Worse at | D12: Better at | F12: How sure | H12: Material at | J12: Judged against | M12: The order is from the last Run, 2026-09-30 15:23.
B13: live from Control | C13: =worse_at | D13: =better_at | F13: =confidence | H13: =IFERROR(IF(materiality_kind="none","No floor",IF(INDEX(line_values,MATCH("gco_rate",line_keys,0))="","No line",IF(FALSE,TEXT(INDEX(line_values,MATCH("gco_rate",line_keys,0)),"#,##0.0")&" bad loans","$"&TEXT(INDEX(line_values,MATCH("gco_rate",line_keys,0)),"#,##0")))),"") | J13: =IF(judged_band,"Rest of its band","Rest of the book") | M13: =IFERROR(IF(COUNTIF(Status,"↻ Waiting for a Run")=0,"","↻ "&COUNTIF(Status,"↻ Waiting for a Run")&IF(COUNTIF(Status,"↻ Waiting for a Run")=1," Control change waits for a Run."," Control changes wait for a Run.")),"")
B15: GRID
B16: FICO x CHANNEL
M17: Across: charge-offs × the rest, on a log scale. Up: kept, as a gap in points. Red: Net drain. Green: Strong or Priced for it.
E18: ="Paid us · gap vs "&IF(judged_band,"band","book") | G18: Cost us · charge-offs | I18: ="Kept · gap vs "&IF(judged_band,"band","book")
B19: Band | C19: Segment | D19: Loans | E19: Gap pts | F19: Dollars | G19: =IF(judged_band,"× band","× book") | H19: Dollars | I19: Gap pts | J19: Dollars | K19: Together
B20: =IF($AN20="","",IF(INDEX('_views'!$B:$ZZ,$AN20,1)="","",INDEX('_views'!$B:$ZZ,$AN20,1))) | C20: =IF($AN20="","",IF(INDEX('_views'!$B:$ZZ,$AN20,2)="","",INDEX('_views'!$B:$ZZ,$AN20,2))) | D20: =IF($AN20="","",IF(INDEX('_views'!$B:$ZZ,$AN20,3)="","",INDEX('_views'!$B:$ZZ,$AN20,3))) | E20: =IF(IF($AP20="","",IF(INDEX('_pockets'!$AB:$AB,$AP20)="","",INDEX('_pockets'!$AB:$AB,$AP20)))="","",IF($AP20="","",IF(INDEX('_pockets'!$AB:$AB,$AP20)="","",INDEX('_pockets'!$AB:$AB,$AP20)))*100) | F20: =IF(IF($AP20="","",IF(INDEX('_pockets'!$Z:$Z,$AP20)="","",INDEX('_pockets'!$Z:$Z,$AP20)))="","",-IF($AP20="","",IF(INDEX('_pockets'!$Z:$Z,$AP20)="","",INDEX('_pockets'!$Z:$Z,$AP20)))) | G20: =IF($AQ20="","",IF(INDEX('_pockets'!$AB:$AB,$AQ20)="","",INDEX('_pockets'!$AB:$AB,$AQ20))) | H20: =IF($AQ20="","",IF(INDEX('_pockets'!$Z:$Z,$AQ20)="","",INDEX('_pockets'!$Z:$Z,$AQ20))) | I20: =IF(IF($AR20="","",IF(INDEX('_pockets'!$AB:$AB,$AR20)="","",INDEX('_pockets'!$AB:$AB,$AR20)))="","",IF($AR20="","",IF(INDEX('_pockets'!$AB:$AB,$AR20)="","",INDEX('_pockets'!$AB:$AB,$AR20)))*100) | J20: =IF(IF($AR20="","",IF(INDEX('_pockets'!$Z:$Z,$AR20)="","",INDEX('_pockets'!$Z:$Z,$AR20)))="","",-IF($AR20="","",IF(INDEX('_pockets'!$Z:$Z,$AR20)="","",INDEX('_pockets'!$Z:$Z,$AR20)))) | K20: =IF(OR($AV20="",AND($AW20="",$AX20="")),$AV20,$AV20&" · borderline (p "&IF(AND($AW20<>"",$AX20<>""),$AW20&" and "&$AX20,$AW20&$AX20)&")") | AN20: =IFERROR(MATCH("C|"&$B$16&"|1",'_views'!$A:$A,0),"") | AO20: =IF($AN20="","",IF(INDEX('_views'!$B:$ZZ,$AN20,4)="","",INDEX('_views'!$B:$ZZ,$AN20,4))) | AP20: =IF($AN20="","",IF(INDEX('_views'!$B:$ZZ,$AN20,5)="","",INDEX('_views'!$B:$ZZ,$AN20,5))) | AQ20: =IF($AN20="","",IF(INDEX('_views'!$B:$ZZ,$AN20,6)="","",INDEX('_views'!$B:$ZZ,$AN20,6))) | AR20: =IF($AN20="","",IF(INDEX('_views'!$B:$ZZ,$AN20,7)="","",INDEX('_views'!$B:$ZZ,$AN20,7))) | AS20: =IF($AP20="","",IF(INDEX('_pockets'!$Y:$Y,$AP20)="","",INDEX('_pockets'!$Y:$Y,$AP20))) | AT20: =IF($AQ20="","",IF(INDEX('_pockets'!$Y:$Y,$AQ20)="","",INDEX('_pockets'!$Y:$Y,$AQ20))) | AU20: =IF($AR20="","",IF(INDEX('_pockets'!$Y:$Y,$AR20)="","",INDEX('_pockets'!$Y:$Y,$AR20))) | AV20: =IF(OR($AO20=1,$AO20=""),"",IF(AND($AT20="worse",$AU20="better"),"Priced for it",IF(AND($AT20="worse",$AU20="worse"),"Net drain",IF(AND($AT20="better",$AU20="better"),"Strong",IF(AND($AT20="better",$AU20="worse"),"Safe but idle",IF(AND(OR($AT20="in line",$AT20="worse, not significant",$AT20="better, not significant"),$AU20="worse"),"Earns less, not from losses",IF(AND($AT20="worse",OR($AU20="in line",$AU20="worse, not significant",$AU20="better, not significant")),"Losing more, profit holding",""))))))) | AW20: =IF($AQ20="","",IF(INDEX('_pockets'!$AM:$AM,$AQ20)="","",INDEX('_pockets'!$AM:$AM,$AQ20))) | AX20: =IF($AR20="","",IF(INDEX('_pockets'!$AM:$AM,$AR20)="","",INDEX('_pockets'!$AM:$AM,$AR20)))
B21: =IF($AN21="","",IF(INDEX('_views'!$B:$ZZ,$AN21,1)="","",INDEX('_views'!$B:$ZZ,$AN21,1))) | C21: =IF($AN21="","",IF(INDEX('_views'!$B:$ZZ,$AN21,2)="","",INDEX('_views'!$B:$ZZ,$AN21,2))) | D21: =IF($AN21="","",IF(INDEX('_views'!$B:$ZZ,$AN21,3)="","",INDEX('_views'!$B:$ZZ,$AN21,3))) | E21: =IF(IF($AP21="","",IF(INDEX('_pockets'!$AB:$AB,$AP21)="","",INDEX('_pockets'!$AB:$AB,$AP21)))="","",IF($AP21="","",IF(INDEX('_pockets'!$AB:$AB,$AP21)="","",INDEX('_pockets'!$AB:$AB,$AP21)))*100) | F21: =IF(IF($AP21="","",IF(INDEX('_pockets'!$Z:$Z,$AP21)="","",INDEX('_pockets'!$Z:$Z,$AP21)))="","",-IF($AP21="","",IF(INDEX('_pockets'!$Z:$Z,$AP21)="","",INDEX('_pockets'!$Z:$Z,$AP21)))) | G21: =IF($AQ21="","",IF(INDEX('_pockets'!$AB:$AB,$AQ21)="","",INDEX('_pockets'!$AB:$AB,$AQ21))) | H21: =IF($AQ21="","",IF(INDEX('_pockets'!$Z:$Z,$AQ21)="","",INDEX('_pockets'!$Z:$Z,$AQ21))) | I21: =IF(IF($AR21="","",IF(INDEX('_pockets'!$AB:$AB,$AR21)="","",INDEX('_pockets'!$AB:$AB,$AR21)))="","",IF($AR21="","",IF(INDEX('_pockets'!$AB:$AB,$AR21)="","",INDEX('_pockets'!$AB:$AB,$AR21)))*100) | J21: =IF(IF($AR21="","",IF(INDEX('_pockets'!$Z:$Z,$AR21)="","",INDEX('_pockets'!$Z:$Z,$AR21)))="","",-IF($AR21="","",IF(INDEX('_pockets'!$Z:$Z,$AR21)="","",INDEX('_pockets'!$Z:$Z,$AR21)))) | K21: =IF(OR($AV21="",AND($AW21="",$AX21="")),$AV21,$AV21&" · borderline (p "&IF(AND($AW21<>"",$AX21<>""),$AW21&" and "&$AX21,$AW21&$AX21)&")") | AN21: =IFERROR(MATCH("C|"&$B$16&"|2",'_views'!$A:$A,0),"") | AO21: =IF($AN21="","",IF(INDEX('_views'!$B:$ZZ,$AN21,4)="","",INDEX('_views'!$B:$ZZ,$AN21,4))) | AP21: =IF($AN21="","",IF(INDEX('_views'!$B:$ZZ,$AN21,5)="","",INDEX('_views'!$B:$ZZ,$AN21,5))) | AQ21: =IF($AN21="","",IF(INDEX('_views'!$B:$ZZ,$AN21,6)="","",INDEX('_views'!$B:$ZZ,$AN21,6))) | AR21: =IF($AN21="","",IF(INDEX('_views'!$B:$ZZ,$AN21,7)="","",INDEX('_views'!$B:$ZZ,$AN21,7))) | AS21: =IF($AP21="","",IF(INDEX('_pockets'!$Y:$Y,$AP21)="","",INDEX('_pockets'!$Y:$Y,$AP21))) | AT21: =IF($AQ21="","",IF(INDEX('_pockets'!$Y:$Y,$AQ21)="","",INDEX('_pockets'!$Y:$Y,$AQ21))) | AU21: =IF($AR21="","",IF(INDEX('_pockets'!$Y:$Y,$AR21)="","",INDEX('_pockets'!$Y:$Y,$AR21))) | AV21: =IF(OR($AO21=1,$AO21=""),"",IF(AND($AT21="worse",$AU21="better"),"Priced for it",IF(AND($AT21="worse",$AU21="worse"),"Net drain",IF(AND($AT21="better",$AU21="better"),"Strong",IF(AND($AT21="better",$AU21="worse"),"Safe but idle",IF(AND(OR($AT21="in line",$AT21="worse, not significant",$AT21="better, not significant"),$AU21="worse"),"Earns less, not from losses",IF(AND($AT21="worse",OR($AU21="in line",$AU21="worse, not significant",$AU21="better, not significant")),"Losing more, profit holding",""))))))) | AW21: =IF($AQ21="","",IF(INDEX('_pockets'!$AM:$AM,$AQ21)="","",INDEX('_pockets'!$AM:$AM,$AQ21))) | AX21: =IF($AR21="","",IF(INDEX('_pockets'!$AM:$AM,$AR21)="","",INDEX('_pockets'!$AM:$AM,$AR21)))
B22: =IF($AN22="","",IF(INDEX('_views'!$B:$ZZ,$AN22,1)="","",INDEX('_views'!$B:$ZZ,$AN22,1))) | C22: =IF($AN22="","",IF(INDEX('_views'!$B:$ZZ,$AN22,2)="","",INDEX('_views'!$B:$ZZ,$AN22,2))) | D22: =IF($AN22="","",IF(INDEX('_views'!$B:$ZZ,$AN22,3)="","",INDEX('_views'!$B:$ZZ,$AN22,3))) | E22: =IF(IF($AP22="","",IF(INDEX('_pockets'!$AB:$AB,$AP22)="","",INDEX('_pockets'!$AB:$AB,$AP22)))="","",IF($AP22="","",IF(INDEX('_pockets'!$AB:$AB,$AP22)="","",INDEX('_pockets'!$AB:$AB,$AP22)))*100) | F22: =IF(IF($AP22="","",IF(INDEX('_pockets'!$Z:$Z,$AP22)="","",INDEX('_pockets'!$Z:$Z,$AP22)))="","",-IF($AP22="","",IF(INDEX('_pockets'!$Z:$Z,$AP22)="","",INDEX('_pockets'!$Z:$Z,$AP22)))) | G22: =IF($AQ22="","",IF(INDEX('_pockets'!$AB:$AB,$AQ22)="","",INDEX('_pockets'!$AB:$AB,$AQ22))) | H22: =IF($AQ22="","",IF(INDEX('_pockets'!$Z:$Z,$AQ22)="","",INDEX('_pockets'!$Z:$Z,$AQ22))) | I22: =IF(IF($AR22="","",IF(INDEX('_pockets'!$AB:$AB,$AR22)="","",INDEX('_pockets'!$AB:$AB,$AR22)))="","",IF($AR22="","",IF(INDEX('_pockets'!$AB:$AB,$AR22)="","",INDEX('_pockets'!$AB:$AB,$AR22)))*100) | J22: =IF(IF($AR22="","",IF(INDEX('_pockets'!$Z:$Z,$AR22)="","",INDEX('_pockets'!$Z:$Z,$AR22)))="","",-IF($AR22="","",IF(INDEX('_pockets'!$Z:$Z,$AR22)="","",INDEX('_pockets'!$Z:$Z,$AR22)))) | K22: =IF(OR($AV22="",AND($AW22="",$AX22="")),$AV22,$AV22&" · borderline (p "&IF(AND($AW22<>"",$AX22<>""),$AW22&" and "&$AX22,$AW22&$AX22)&")") | AN22: =IFERROR(MATCH("C|"&$B$16&"|3",'_views'!$A:$A,0),"") | AO22: =IF($AN22="","",IF(INDEX('_views'!$B:$ZZ,$AN22,4)="","",INDEX('_views'!$B:$ZZ,$AN22,4))) | AP22: =IF($AN22="","",IF(INDEX('_views'!$B:$ZZ,$AN22,5)="","",INDEX('_views'!$B:$ZZ,$AN22,5))) | AQ22: =IF($AN22="","",IF(INDEX('_views'!$B:$ZZ,$AN22,6)="","",INDEX('_views'!$B:$ZZ,$AN22,6))) | AR22: =IF($AN22="","",IF(INDEX('_views'!$B:$ZZ,$AN22,7)="","",INDEX('_views'!$B:$ZZ,$AN22,7))) | AS22: =IF($AP22="","",IF(INDEX('_pockets'!$Y:$Y,$AP22)="","",INDEX('_pockets'!$Y:$Y,$AP22))) | AT22: =IF($AQ22="","",IF(INDEX('_pockets'!$Y:$Y,$AQ22)="","",INDEX('_pockets'!$Y:$Y,$AQ22))) | AU22: =IF($AR22="","",IF(INDEX('_pockets'!$Y:$Y,$AR22)="","",INDEX('_pockets'!$Y:$Y,$AR22))) | AV22: =IF(OR($AO22=1,$AO22=""),"",IF(AND($AT22="worse",$AU22="better"),"Priced for it",IF(AND($AT22="worse",$AU22="worse"),"Net drain",IF(AND($AT22="better",$AU22="better"),"Strong",IF(AND($AT22="better",$AU22="worse"),"Safe but idle",IF(AND(OR($AT22="in line",$AT22="worse, not significant",$AT22="better, not significant"),$AU22="worse"),"Earns less, not from losses",IF(AND($AT22="worse",OR($AU22="in line",$AU22="worse, not significant",$AU22="better, not significant")),"Losing more, profit holding",""))))))) | AW22: =IF($AQ22="","",IF(INDEX('_pockets'!$AM:$AM,$AQ22)="","",INDEX('_pockets'!$AM:$AM,$AQ22))) | AX22: =IF($AR22="","",IF(INDEX('_pockets'!$AM:$AM,$AR22)="","",INDEX('_pockets'!$AM:$AM,$AR22)))
B23: =IF($AN23="","",IF(INDEX('_views'!$B:$ZZ,$AN23,1)="","",INDEX('_views'!$B:$ZZ,$AN23,1))) | C23: =IF($AN23="","",IF(INDEX('_views'!$B:$ZZ,$AN23,2)="","",INDEX('_views'!$B:$ZZ,$AN23,2))) | D23: =IF($AN23="","",IF(INDEX('_views'!$B:$ZZ,$AN23,3)="","",INDEX('_views'!$B:$ZZ,$AN23,3))) | E23: =IF(IF($AP23="","",IF(INDEX('_pockets'!$AB:$AB,$AP23)="","",INDEX('_pockets'!$AB:$AB,$AP23)))="","",IF($AP23="","",IF(INDEX('_pockets'!$AB:$AB,$AP23)="","",INDEX('_pockets'!$AB:$AB,$AP23)))*100) | F23: =IF(IF($AP23="","",IF(INDEX('_pockets'!$Z:$Z,$AP23)="","",INDEX('_pockets'!$Z:$Z,$AP23)))="","",-IF($AP23="","",IF(INDEX('_pockets'!$Z:$Z,$AP23)="","",INDEX('_pockets'!$Z:$Z,$AP23)))) | G23: =IF($AQ23="","",IF(INDEX('_pockets'!$AB:$AB,$AQ23)="","",INDEX('_pockets'!$AB:$AB,$AQ23))) | H23: =IF($AQ23="","",IF(INDEX('_pockets'!$Z:$Z,$AQ23)="","",INDEX('_pockets'!$Z:$Z,$AQ23))) | I23: =IF(IF($AR23="","",IF(INDEX('_pockets'!$AB:$AB,$AR23)="","",INDEX('_pockets'!$AB:$AB,$AR23)))="","",IF($AR23="","",IF(INDEX('_pockets'!$AB:$AB,$AR23)="","",INDEX('_pockets'!$AB:$AB,$AR23)))*100) | J23: =IF(IF($AR23="","",IF(INDEX('_pockets'!$Z:$Z,$AR23)="","",INDEX('_pockets'!$Z:$Z,$AR23)))="","",-IF($AR23="","",IF(INDEX('_pockets'!$Z:$Z,$AR23)="","",INDEX('_pockets'!$Z:$Z,$AR23)))) | K23: =IF(OR($AV23="",AND($AW23="",$AX23="")),$AV23,$AV23&" · borderline (p "&IF(AND($AW23<>"",$AX23<>""),$AW23&" and "&$AX23,$AW23&$AX23)&")") | AN23: =IFERROR(MATCH("C|"&$B$16&"|4",'_views'!$A:$A,0),"") | AO23: =IF($AN23="","",IF(INDEX('_views'!$B:$ZZ,$AN23,4)="","",INDEX('_views'!$B:$ZZ,$AN23,4))) | AP23: =IF($AN23="","",IF(INDEX('_views'!$B:$ZZ,$AN23,5)="","",INDEX('_views'!$B:$ZZ,$AN23,5))) | AQ23: =IF($AN23="","",IF(INDEX('_views'!$B:$ZZ,$AN23,6)="","",INDEX('_views'!$B:$ZZ,$AN23,6))) | AR23: =IF($AN23="","",IF(INDEX('_views'!$B:$ZZ,$AN23,7)="","",INDEX('_views'!$B:$ZZ,$AN23,7))) | AS23: =IF($AP23="","",IF(INDEX('_pockets'!$Y:$Y,$AP23)="","",INDEX('_pockets'!$Y:$Y,$AP23))) | AT23: =IF($AQ23="","",IF(INDEX('_pockets'!$Y:$Y,$AQ23)="","",INDEX('_pockets'!$Y:$Y,$AQ23))) | AU23: =IF($AR23="","",IF(INDEX('_pockets'!$Y:$Y,$AR23)="","",INDEX('_pockets'!$Y:$Y,$AR23))) | AV23: =IF(OR($AO23=1,$AO23=""),"",IF(AND($AT23="worse",$AU23="better"),"Priced for it",IF(AND($AT23="worse",$AU23="worse"),"Net drain",IF(AND($AT23="better",$AU23="better"),"Strong",IF(AND($AT23="better",$AU23="worse"),"Safe but idle",IF(AND(OR($AT23="in line",$AT23="worse, not significant",$AT23="better, not significant"),$AU23="worse"),"Earns less, not from losses",IF(AND($AT23="worse",OR($AU23="in line",$AU23="worse, not significant",$AU23="better, not significant")),"Losing more, profit holding",""))))))) | AW23: =IF($AQ23="","",IF(INDEX('_pockets'!$AM:$AM,$AQ23)="","",INDEX('_pockets'!$AM:$AM,$AQ23))) | AX23: =IF($AR23="","",IF(INDEX('_pockets'!$AM:$AM,$AR23)="","",INDEX('_pockets'!$AM:$AM,$AR23)))
B24: =IF($AN24="","",IF(INDEX('_views'!$B:$ZZ,$AN24,1)="","",INDEX('_views'!$B:$ZZ,$AN24,1))) | C24: =IF($AN24="","",IF(INDEX('_views'!$B:$ZZ,$AN24,2)="","",INDEX('_views'!$B:$ZZ,$AN24,2))) | D24: =IF($AN24="","",IF(INDEX('_views'!$B:$ZZ,$AN24,3)="","",INDEX('_views'!$B:$ZZ,$AN24,3))) | E24: =IF(IF($AP24="","",IF(INDEX('_pockets'!$AB:$AB,$AP24)="","",INDEX('_pockets'!$AB:$AB,$AP24)))="","",IF($AP24="","",IF(INDEX('_pockets'!$AB:$AB,$AP24)="","",INDEX('_pockets'!$AB:$AB,$AP24)))*100) | F24: =IF(IF($AP24="","",IF(INDEX('_pockets'!$Z:$Z,$AP24)="","",INDEX('_pockets'!$Z:$Z,$AP24)))="","",-IF($AP24="","",IF(INDEX('_pockets'!$Z:$Z,$AP24)="","",INDEX('_pockets'!$Z:$Z,$AP24)))) | G24: =IF($AQ24="","",IF(INDEX('_pockets'!$AB:$AB,$AQ24)="","",INDEX('_pockets'!$AB:$AB,$AQ24))) | H24: =IF($AQ24="","",IF(INDEX('_pockets'!$Z:$Z,$AQ24)="","",INDEX('_pockets'!$Z:$Z,$AQ24))) | I24: =IF(IF($AR24="","",IF(INDEX('_pockets'!$AB:$AB,$AR24)="","",INDEX('_pockets'!$AB:$AB,$AR24)))="","",IF($AR24="","",IF(INDEX('_pockets'!$AB:$AB,$AR24)="","",INDEX('_pockets'!$AB:$AB,$AR24)))*100) | J24: =IF(IF($AR24="","",IF(INDEX('_pockets'!$Z:$Z,$AR24)="","",INDEX('_pockets'!$Z:$Z,$AR24)))="","",-IF($AR24="","",IF(INDEX('_pockets'!$Z:$Z,$AR24)="","",INDEX('_pockets'!$Z:$Z,$AR24)))) | K24: =IF(OR($AV24="",AND($AW24="",$AX24="")),$AV24,$AV24&" · borderline (p "&IF(AND($AW24<>"",$AX24<>""),$AW24&" and "&$AX24,$AW24&$AX24)&")") | AN24: =IFERROR(MATCH("C|"&$B$16&"|5",'_views'!$A:$A,0),"") | AO24: =IF($AN24="","",IF(INDEX('_views'!$B:$ZZ,$AN24,4)="","",INDEX('_views'!$B:$ZZ,$AN24,4))) | AP24: =IF($AN24="","",IF(INDEX('_views'!$B:$ZZ,$AN24,5)="","",INDEX('_views'!$B:$ZZ,$AN24,5))) | AQ24: =IF($AN24="","",IF(INDEX('_views'!$B:$ZZ,$AN24,6)="","",INDEX('_views'!$B:$ZZ,$AN24,6))) | AR24: =IF($AN24="","",IF(INDEX('_views'!$B:$ZZ,$AN24,7)="","",INDEX('_views'!$B:$ZZ,$AN24,7))) | AS24: =IF($AP24="","",IF(INDEX('_pockets'!$Y:$Y,$AP24)="","",INDEX('_pockets'!$Y:$Y,$AP24))) | AT24: =IF($AQ24="","",IF(INDEX('_pockets'!$Y:$Y,$AQ24)="","",INDEX('_pockets'!$Y:$Y,$AQ24))) | AU24: =IF($AR24="","",IF(INDEX('_pockets'!$Y:$Y,$AR24)="","",INDEX('_pockets'!$Y:$Y,$AR24))) | AV24: =IF(OR($AO24=1,$AO24=""),"",IF(AND($AT24="worse",$AU24="better"),"Priced for it",IF(AND($AT24="worse",$AU24="worse"),"Net drain",IF(AND($AT24="better",$AU24="better"),"Strong",IF(AND($AT24="better",$AU24="worse"),"Safe but idle",IF(AND(OR($AT24="in line",$AT24="worse, not significant",$AT24="better, not significant"),$AU24="worse"),"Earns less, not from losses",IF(AND($AT24="worse",OR($AU24="in line",$AU24="worse, not significant",$AU24="better, not significant")),"Losing more, profit holding",""))))))) | AW24: =IF($AQ24="","",IF(INDEX('_pockets'!$AM:$AM,$AQ24)="","",INDEX('_pockets'!$AM:$AM,$AQ24))) | AX24: =IF($AR24="","",IF(INDEX('_pockets'!$AM:$AM,$AR24)="","",INDEX('_pockets'!$AM:$AM,$AR24)))
B25: =IF($AN25="","",IF(INDEX('_views'!$B:$ZZ,$AN25,1)="","",INDEX('_views'!$B:$ZZ,$AN25,1))) | C25: =IF($AN25="","",IF(INDEX('_views'!$B:$ZZ,$AN25,2)="","",INDEX('_views'!$B:$ZZ,$AN25,2))) | D25: =IF($AN25="","",IF(INDEX('_views'!$B:$ZZ,$AN25,3)="","",INDEX('_views'!$B:$ZZ,$AN25,3))) | E25: =IF(IF($AP25="","",IF(INDEX('_pockets'!$AB:$AB,$AP25)="","",INDEX('_pockets'!$AB:$AB,$AP25)))="","",IF($AP25="","",IF(INDEX('_pockets'!$AB:$AB,$AP25)="","",INDEX('_pockets'!$AB:$AB,$AP25)))*100) | F25: =IF(IF($AP25="","",IF(INDEX('_pockets'!$Z:$Z,$AP25)="","",INDEX('_pockets'!$Z:$Z,$AP25)))="","",-IF($AP25="","",IF(INDEX('_pockets'!$Z:$Z,$AP25)="","",INDEX('_pockets'!$Z:$Z,$AP25)))) | G25: =IF($AQ25="","",IF(INDEX('_pockets'!$AB:$AB,$AQ25)="","",INDEX('_pockets'!$AB:$AB,$AQ25))) | H25: =IF($AQ25="","",IF(INDEX('_pockets'!$Z:$Z,$AQ25)="","",INDEX('_pockets'!$Z:$Z,$AQ25))) | I25: =IF(IF($AR25="","",IF(INDEX('_pockets'!$AB:$AB,$AR25)="","",INDEX('_pockets'!$AB:$AB,$AR25)))="","",IF($AR25="","",IF(INDEX('_pockets'!$AB:$AB,$AR25)="","",INDEX('_pockets'!$AB:$AB,$AR25)))*100) | J25: =IF(IF($AR25="","",IF(INDEX('_pockets'!$Z:$Z,$AR25)="","",INDEX('_pockets'!$Z:$Z,$AR25)))="","",-IF($AR25="","",IF(INDEX('_pockets'!$Z:$Z,$AR25)="","",INDEX('_pockets'!$Z:$Z,$AR25)))) | K25: =IF(OR($AV25="",AND($AW25="",$AX25="")),$AV25,$AV25&" · borderline (p "&IF(AND($AW25<>"",$AX25<>""),$AW25&" and "&$AX25,$AW25&$AX25)&")") | AN25: =IFERROR(MATCH("C|"&$B$16&"|6",'_views'!$A:$A,0),"") | AO25: =IF($AN25="","",IF(INDEX('_views'!$B:$ZZ,$AN25,4)="","",INDEX('_views'!$B:$ZZ,$AN25,4))) | AP25: =IF($AN25="","",IF(INDEX('_views'!$B:$ZZ,$AN25,5)="","",INDEX('_views'!$B:$ZZ,$AN25,5))) | AQ25: =IF($AN25="","",IF(INDEX('_views'!$B:$ZZ,$AN25,6)="","",INDEX('_views'!$B:$ZZ,$AN25,6))) | AR25: =IF($AN25="","",IF(INDEX('_views'!$B:$ZZ,$AN25,7)="","",INDEX('_views'!$B:$ZZ,$AN25,7))) | AS25: =IF($AP25="","",IF(INDEX('_pockets'!$Y:$Y,$AP25)="","",INDEX('_pockets'!$Y:$Y,$AP25))) | AT25: =IF($AQ25="","",IF(INDEX('_pockets'!$Y:$Y,$AQ25)="","",INDEX('_pockets'!$Y:$Y,$AQ25))) | AU25: =IF($AR25="","",IF(INDEX('_pockets'!$Y:$Y,$AR25)="","",INDEX('_pockets'!$Y:$Y,$AR25))) | AV25: =IF(OR($AO25=1,$AO25=""),"",IF(AND($AT25="worse",$AU25="better"),"Priced for it",IF(AND($AT25="worse",$AU25="worse"),"Net drain",IF(AND($AT25="better",$AU25="better"),"Strong",IF(AND($AT25="better",$AU25="worse"),"Safe but idle",IF(AND(OR($AT25="in line",$AT25="worse, not significant",$AT25="better, not significant"),$AU25="worse"),"Earns less, not from losses",IF(AND($AT25="worse",OR($AU25="in line",$AU25="worse, not significant",$AU25="better, not significant")),"Losing more, profit holding",""))))))) | AW25: =IF($AQ25="","",IF(INDEX('_pockets'!$AM:$AM,$AQ25)="","",INDEX('_pockets'!$AM:$AM,$AQ25))) | AX25: =IF($AR25="","",IF(INDEX('_pockets'!$AM:$AM,$AR25)="","",INDEX('_pockets'!$AM:$AM,$AR25)))
B26: =IF($AN26="","",IF(INDEX('_views'!$B:$ZZ,$AN26,1)="","",INDEX('_views'!$B:$ZZ,$AN26,1))) | C26: =IF($AN26="","",IF(INDEX('_views'!$B:$ZZ,$AN26,2)="","",INDEX('_views'!$B:$ZZ,$AN26,2))) | D26: =IF($AN26="","",IF(INDEX('_views'!$B:$ZZ,$AN26,3)="","",INDEX('_views'!$B:$ZZ,$AN26,3))) | E26: =IF(IF($AP26="","",IF(INDEX('_pockets'!$AB:$AB,$AP26)="","",INDEX('_pockets'!$AB:$AB,$AP26)))="","",IF($AP26="","",IF(INDEX('_pockets'!$AB:$AB,$AP26)="","",INDEX('_pockets'!$AB:$AB,$AP26)))*100) | F26: =IF(IF($AP26="","",IF(INDEX('_pockets'!$Z:$Z,$AP26)="","",INDEX('_pockets'!$Z:$Z,$AP26)))="","",-IF($AP26="","",IF(INDEX('_pockets'!$Z:$Z,$AP26)="","",INDEX('_pockets'!$Z:$Z,$AP26)))) | G26: =IF($AQ26="","",IF(INDEX('_pockets'!$AB:$AB,$AQ26)="","",INDEX('_pockets'!$AB:$AB,$AQ26))) | H26: =IF($AQ26="","",IF(INDEX('_pockets'!$Z:$Z,$AQ26)="","",INDEX('_pockets'!$Z:$Z,$AQ26))) | I26: =IF(IF($AR26="","",IF(INDEX('_pockets'!$AB:$AB,$AR26)="","",INDEX('_pockets'!$AB:$AB,$AR26)))="","",IF($AR26="","",IF(INDEX('_pockets'!$AB:$AB,$AR26)="","",INDEX('_pockets'!$AB:$AB,$AR26)))*100) | J26: =IF(IF($AR26="","",IF(INDEX('_pockets'!$Z:$Z,$AR26)="","",INDEX('_pockets'!$Z:$Z,$AR26)))="","",-IF($AR26="","",IF(INDEX('_pockets'!$Z:$Z,$AR26)="","",INDEX('_pockets'!$Z:$Z,$AR26)))) | K26: =IF(OR($AV26="",AND($AW26="",$AX26="")),$AV26,$AV26&" · borderline (p "&IF(AND($AW26<>"",$AX26<>""),$AW26&" and "&$AX26,$AW26&$AX26)&")") | AN26: =IFERROR(MATCH("C|"&$B$16&"|7",'_views'!$A:$A,0),"") | AO26: =IF($AN26="","",IF(INDEX('_views'!$B:$ZZ,$AN26,4)="","",INDEX('_views'!$B:$ZZ,$AN26,4))) | AP26: =IF($AN26="","",IF(INDEX('_views'!$B:$ZZ,$AN26,5)="","",INDEX('_views'!$B:$ZZ,$AN26,5))) | AQ26: =IF($AN26="","",IF(INDEX('_views'!$B:$ZZ,$AN26,6)="","",INDEX('_views'!$B:$ZZ,$AN26,6))) | AR26: =IF($AN26="","",IF(INDEX('_views'!$B:$ZZ,$AN26,7)="","",INDEX('_views'!$B:$ZZ,$AN26,7))) | AS26: =IF($AP26="","",IF(INDEX('_pockets'!$Y:$Y,$AP26)="","",INDEX('_pockets'!$Y:$Y,$AP26))) | AT26: =IF($AQ26="","",IF(INDEX('_pockets'!$Y:$Y,$AQ26)="","",INDEX('_pockets'!$Y:$Y,$AQ26))) | AU26: =IF($AR26="","",IF(INDEX('_pockets'!$Y:$Y,$AR26)="","",INDEX('_pockets'!$Y:$Y,$AR26))) | AV26: =IF(OR($AO26=1,$AO26=""),"",IF(AND($AT26="worse",$AU26="better"),"Priced for it",IF(AND($AT26="worse",$AU26="worse"),"Net drain",IF(AND($AT26="better",$AU26="better"),"Strong",IF(AND($AT26="better",$AU26="worse"),"Safe but idle",IF(AND(OR($AT26="in line",$AT26="worse, not significant",$AT26="better, not significant"),$AU26="worse"),"Earns less, not from losses",IF(AND($AT26="worse",OR($AU26="in line",$AU26="worse, not significant",$AU26="better, not significant")),"Losing more, profit holding",""))))))) | AW26: =IF($AQ26="","",IF(INDEX('_pockets'!$AM:$AM,$AQ26)="","",INDEX('_pockets'!$AM:$AM,$AQ26))) | AX26: =IF($AR26="","",IF(INDEX('_pockets'!$AM:$AM,$AR26)="","",INDEX('_pockets'!$AM:$AM,$AR26)))
B27: =IF($AN27="","",IF(INDEX('_views'!$B:$ZZ,$AN27,1)="","",INDEX('_views'!$B:$ZZ,$AN27,1))) | C27: =IF($AN27="","",IF(INDEX('_views'!$B:$ZZ,$AN27,2)="","",INDEX('_views'!$B:$ZZ,$AN27,2))) | D27: =IF($AN27="","",IF(INDEX('_views'!$B:$ZZ,$AN27,3)="","",INDEX('_views'!$B:$ZZ,$AN27,3))) | E27: =IF(IF($AP27="","",IF(INDEX('_pockets'!$AB:$AB,$AP27)="","",INDEX('_pockets'!$AB:$AB,$AP27)))="","",IF($AP27="","",IF(INDEX('_pockets'!$AB:$AB,$AP27)="","",INDEX('_pockets'!$AB:$AB,$AP27)))*100) | F27: =IF(IF($AP27="","",IF(INDEX('_pockets'!$Z:$Z,$AP27)="","",INDEX('_pockets'!$Z:$Z,$AP27)))="","",-IF($AP27="","",IF(INDEX('_pockets'!$Z:$Z,$AP27)="","",INDEX('_pockets'!$Z:$Z,$AP27)))) | G27: =IF($AQ27="","",IF(INDEX('_pockets'!$AB:$AB,$AQ27)="","",INDEX('_pockets'!$AB:$AB,$AQ27))) | H27: =IF($AQ27="","",IF(INDEX('_pockets'!$Z:$Z,$AQ27)="","",INDEX('_pockets'!$Z:$Z,$AQ27))) | I27: =IF(IF($AR27="","",IF(INDEX('_pockets'!$AB:$AB,$AR27)="","",INDEX('_pockets'!$AB:$AB,$AR27)))="","",IF($AR27="","",IF(INDEX('_pockets'!$AB:$AB,$AR27)="","",INDEX('_pockets'!$AB:$AB,$AR27)))*100) | J27: =IF(IF($AR27="","",IF(INDEX('_pockets'!$Z:$Z,$AR27)="","",INDEX('_pockets'!$Z:$Z,$AR27)))="","",-IF($AR27="","",IF(INDEX('_pockets'!$Z:$Z,$AR27)="","",INDEX('_pockets'!$Z:$Z,$AR27)))) | K27: =IF(OR($AV27="",AND($AW27="",$AX27="")),$AV27,$AV27&" · borderline (p "&IF(AND($AW27<>"",$AX27<>""),$AW27&" and "&$AX27,$AW27&$AX27)&")") | AN27: =IFERROR(MATCH("C|"&$B$16&"|8",'_views'!$A:$A,0),"") | AO27: =IF($AN27="","",IF(INDEX('_views'!$B:$ZZ,$AN27,4)="","",INDEX('_views'!$B:$ZZ,$AN27,4))) | AP27: =IF($AN27="","",IF(INDEX('_views'!$B:$ZZ,$AN27,5)="","",INDEX('_views'!$B:$ZZ,$AN27,5))) | AQ27: =IF($AN27="","",IF(INDEX('_views'!$B:$ZZ,$AN27,6)="","",INDEX('_views'!$B:$ZZ,$AN27,6))) | AR27: =IF($AN27="","",IF(INDEX('_views'!$B:$ZZ,$AN27,7)="","",INDEX('_views'!$B:$ZZ,$AN27,7))) | AS27: =IF($AP27="","",IF(INDEX('_pockets'!$Y:$Y,$AP27)="","",INDEX('_pockets'!$Y:$Y,$AP27))) | AT27: =IF($AQ27="","",IF(INDEX('_pockets'!$Y:$Y,$AQ27)="","",INDEX('_pockets'!$Y:$Y,$AQ27))) | AU27: =IF($AR27="","",IF(INDEX('_pockets'!$Y:$Y,$AR27)="","",INDEX('_pockets'!$Y:$Y,$AR27))) | AV27: =IF(OR($AO27=1,$AO27=""),"",IF(AND($AT27="worse",$AU27="better"),"Priced for it",IF(AND($AT27="worse",$AU27="worse"),"Net drain",IF(AND($AT27="better",$AU27="better"),"Strong",IF(AND($AT27="better",$AU27="worse"),"Safe but idle",IF(AND(OR($AT27="in line",$AT27="worse, not significant",$AT27="better, not significant"),$AU27="worse"),"Earns less, not from losses",IF(AND($AT27="worse",OR($AU27="in line",$AU27="worse, not significant",$AU27="better, not significant")),"Losing more, profit holding",""))))))) | AW27: =IF($AQ27="","",IF(INDEX('_pockets'!$AM:$AM,$AQ27)="","",INDEX('_pockets'!$AM:$AM,$AQ27))) | AX27: =IF($AR27="","",IF(INDEX('_pockets'!$AM:$AM,$AR27)="","",INDEX('_pockets'!$AM:$AM,$AR27)))
B28: =IF($AN28="","",IF(INDEX('_views'!$B:$ZZ,$AN28,1)="","",INDEX('_views'!$B:$ZZ,$AN28,1))) | C28: =IF($AN28="","",IF(INDEX('_views'!$B:$ZZ,$AN28,2)="","",INDEX('_views'!$B:$ZZ,$AN28,2))) | D28: =IF($AN28="","",IF(INDEX('_views'!$B:$ZZ,$AN28,3)="","",INDEX('_views'!$B:$ZZ,$AN28,3))) | E28: =IF(IF($AP28="","",IF(INDEX('_pockets'!$AB:$AB,$AP28)="","",INDEX('_pockets'!$AB:$AB,$AP28)))="","",IF($AP28="","",IF(INDEX('_pockets'!$AB:$AB,$AP28)="","",INDEX('_pockets'!$AB:$AB,$AP28)))*100) | F28: =IF(IF($AP28="","",IF(INDEX('_pockets'!$Z:$Z,$AP28)="","",INDEX('_pockets'!$Z:$Z,$AP28)))="","",-IF($AP28="","",IF(INDEX('_pockets'!$Z:$Z,$AP28)="","",INDEX('_pockets'!$Z:$Z,$AP28)))) | G28: =IF($AQ28="","",IF(INDEX('_pockets'!$AB:$AB,$AQ28)="","",INDEX('_pockets'!$AB:$AB,$AQ28))) | H28: =IF($AQ28="","",IF(INDEX('_pockets'!$Z:$Z,$AQ28)="","",INDEX('_pockets'!$Z:$Z,$AQ28))) | I28: =IF(IF($AR28="","",IF(INDEX('_pockets'!$AB:$AB,$AR28)="","",INDEX('_pockets'!$AB:$AB,$AR28)))="","",IF($AR28="","",IF(INDEX('_pockets'!$AB:$AB,$AR28)="","",INDEX('_pockets'!$AB:$AB,$AR28)))*100) | J28: =IF(IF($AR28="","",IF(INDEX('_pockets'!$Z:$Z,$AR28)="","",INDEX('_pockets'!$Z:$Z,$AR28)))="","",-IF($AR28="","",IF(INDEX('_pockets'!$Z:$Z,$AR28)="","",INDEX('_pockets'!$Z:$Z,$AR28)))) | K28: =IF(OR($AV28="",AND($AW28="",$AX28="")),$AV28,$AV28&" · borderline (p "&IF(AND($AW28<>"",$AX28<>""),$AW28&" and "&$AX28,$AW28&$AX28)&")") | AN28: =IFERROR(MATCH("C|"&$B$16&"|9",'_views'!$A:$A,0),"") | AO28: =IF($AN28="","",IF(INDEX('_views'!$B:$ZZ,$AN28,4)="","",INDEX('_views'!$B:$ZZ,$AN28,4))) | AP28: =IF($AN28="","",IF(INDEX('_views'!$B:$ZZ,$AN28,5)="","",INDEX('_views'!$B:$ZZ,$AN28,5))) | AQ28: =IF($AN28="","",IF(INDEX('_views'!$B:$ZZ,$AN28,6)="","",INDEX('_views'!$B:$ZZ,$AN28,6))) | AR28: =IF($AN28="","",IF(INDEX('_views'!$B:$ZZ,$AN28,7)="","",INDEX('_views'!$B:$ZZ,$AN28,7))) | AS28: =IF($AP28="","",IF(INDEX('_pockets'!$Y:$Y,$AP28)="","",INDEX('_pockets'!$Y:$Y,$AP28))) | AT28: =IF($AQ28="","",IF(INDEX('_pockets'!$Y:$Y,$AQ28)="","",INDEX('_pockets'!$Y:$Y,$AQ28))) | AU28: =IF($AR28="","",IF(INDEX('_pockets'!$Y:$Y,$AR28)="","",INDEX('_pockets'!$Y:$Y,$AR28))) | AV28: =IF(OR($AO28=1,$AO28=""),"",IF(AND($AT28="worse",$AU28="better"),"Priced for it",IF(AND($AT28="worse",$AU28="worse"),"Net drain",IF(AND($AT28="better",$AU28="better"),"Strong",IF(AND($AT28="better",$AU28="worse"),"Safe but idle",IF(AND(OR($AT28="in line",$AT28="worse, not significant",$AT28="better, not significant"),$AU28="worse"),"Earns less, not from losses",IF(AND($AT28="worse",OR($AU28="in line",$AU28="worse, not significant",$AU28="better, not significant")),"Losing more, profit holding",""))))))) | AW28: =IF($AQ28="","",IF(INDEX('_pockets'!$AM:$AM,$AQ28)="","",INDEX('_pockets'!$AM:$AM,$AQ28))) | AX28: =IF($AR28="","",IF(INDEX('_pockets'!$AM:$AM,$AR28)="","",INDEX('_pockets'!$AM:$AM,$AR28)))
B29: =IF($AN29="","",IF(INDEX('_views'!$B:$ZZ,$AN29,1)="","",INDEX('_views'!$B:$ZZ,$AN29,1))) | C29: =IF($AN29="","",IF(INDEX('_views'!$B:$ZZ,$AN29,2)="","",INDEX('_views'!$B:$ZZ,$AN29,2))) | D29: =IF($AN29="","",IF(INDEX('_views'!$B:$ZZ,$AN29,3)="","",INDEX('_views'!$B:$ZZ,$AN29,3))) | E29: =IF(IF($AP29="","",IF(INDEX('_pockets'!$AB:$AB,$AP29)="","",INDEX('_pockets'!$AB:$AB,$AP29)))="","",IF($AP29="","",IF(INDEX('_pockets'!$AB:$AB,$AP29)="","",INDEX('_pockets'!$AB:$AB,$AP29)))*100) | F29: =IF(IF($AP29="","",IF(INDEX('_pockets'!$Z:$Z,$AP29)="","",INDEX('_pockets'!$Z:$Z,$AP29)))="","",-IF($AP29="","",IF(INDEX('_pockets'!$Z:$Z,$AP29)="","",INDEX('_pockets'!$Z:$Z,$AP29)))) | G29: =IF($AQ29="","",IF(INDEX('_pockets'!$AB:$AB,$AQ29)="","",INDEX('_pockets'!$AB:$AB,$AQ29))) | H29: =IF($AQ29="","",IF(INDEX('_pockets'!$Z:$Z,$AQ29)="","",INDEX('_pockets'!$Z:$Z,$AQ29))) | I29: =IF(IF($AR29="","",IF(INDEX('_pockets'!$AB:$AB,$AR29)="","",INDEX('_pockets'!$AB:$AB,$AR29)))="","",IF($AR29="","",IF(INDEX('_pockets'!$AB:$AB,$AR29)="","",INDEX('_pockets'!$AB:$AB,$AR29)))*100) | J29: =IF(IF($AR29="","",IF(INDEX('_pockets'!$Z:$Z,$AR29)="","",INDEX('_pockets'!$Z:$Z,$AR29)))="","",-IF($AR29="","",IF(INDEX('_pockets'!$Z:$Z,$AR29)="","",INDEX('_pockets'!$Z:$Z,$AR29)))) | K29: =IF(OR($AV29="",AND($AW29="",$AX29="")),$AV29,$AV29&" · borderline (p "&IF(AND($AW29<>"",$AX29<>""),$AW29&" and "&$AX29,$AW29&$AX29)&")") | AN29: =IFERROR(MATCH("C|"&$B$16&"|10",'_views'!$A:$A,0),"") | AO29: =IF($AN29="","",IF(INDEX('_views'!$B:$ZZ,$AN29,4)="","",INDEX('_views'!$B:$ZZ,$AN29,4))) | AP29: =IF($AN29="","",IF(INDEX('_views'!$B:$ZZ,$AN29,5)="","",INDEX('_views'!$B:$ZZ,$AN29,5))) | AQ29: =IF($AN29="","",IF(INDEX('_views'!$B:$ZZ,$AN29,6)="","",INDEX('_views'!$B:$ZZ,$AN29,6))) | AR29: =IF($AN29="","",IF(INDEX('_views'!$B:$ZZ,$AN29,7)="","",INDEX('_views'!$B:$ZZ,$AN29,7))) | AS29: =IF($AP29="","",IF(INDEX('_pockets'!$Y:$Y,$AP29)="","",INDEX('_pockets'!$Y:$Y,$AP29))) | AT29: =IF($AQ29="","",IF(INDEX('_pockets'!$Y:$Y,$AQ29)="","",INDEX('_pockets'!$Y:$Y,$AQ29))) | AU29: =IF($AR29="","",IF(INDEX('_pockets'!$Y:$Y,$AR29)="","",INDEX('_pockets'!$Y:$Y,$AR29))) | AV29: =IF(OR($AO29=1,$AO29=""),"",IF(AND($AT29="worse",$AU29="better"),"Priced for it",IF(AND($AT29="worse",$AU29="worse"),"Net drain",IF(AND($AT29="better",$AU29="better"),"Strong",IF(AND($AT29="better",$AU29="worse"),"Safe but idle",IF(AND(OR($AT29="in line",$AT29="worse, not significant",$AT29="better, not significant"),$AU29="worse"),"Earns less, not from losses",IF(AND($AT29="worse",OR($AU29="in line",$AU29="worse, not significant",$AU29="better, not significant")),"Losing more, profit holding",""))))))) | AW29: =IF($AQ29="","",IF(INDEX('_pockets'!$AM:$AM,$AQ29)="","",INDEX('_pockets'!$AM:$AM,$AQ29))) | AX29: =IF($AR29="","",IF(INDEX('_pockets'!$AM:$AM,$AR29)="","",INDEX('_pockets'!$AM:$AM,$AR29)))
B30: =IF($AN30="","",IF(INDEX('_views'!$B:$ZZ,$AN30,1)="","",INDEX('_views'!$B:$ZZ,$AN30,1))) | C30: =IF($AN30="","",IF(INDEX('_views'!$B:$ZZ,$AN30,2)="","",INDEX('_views'!$B:$ZZ,$AN30,2))) | D30: =IF($AN30="","",IF(INDEX('_views'!$B:$ZZ,$AN30,3)="","",INDEX('_views'!$B:$ZZ,$AN30,3))) | E30: =IF(IF($AP30="","",IF(INDEX('_pockets'!$AB:$AB,$AP30)="","",INDEX('_pockets'!$AB:$AB,$AP30)))="","",IF($AP30="","",IF(INDEX('_pockets'!$AB:$AB,$AP30)="","",INDEX('_pockets'!$AB:$AB,$AP30)))*100) | F30: =IF(IF($AP30="","",IF(INDEX('_pockets'!$Z:$Z,$AP30)="","",INDEX('_pockets'!$Z:$Z,$AP30)))="","",-IF($AP30="","",IF(INDEX('_pockets'!$Z:$Z,$AP30)="","",INDEX('_pockets'!$Z:$Z,$AP30)))) | G30: =IF($AQ30="","",IF(INDEX('_pockets'!$AB:$AB,$AQ30)="","",INDEX('_pockets'!$AB:$AB,$AQ30))) | H30: =IF($AQ30="","",IF(INDEX('_pockets'!$Z:$Z,$AQ30)="","",INDEX('_pockets'!$Z:$Z,$AQ30))) | I30: =IF(IF($AR30="","",IF(INDEX('_pockets'!$AB:$AB,$AR30)="","",INDEX('_pockets'!$AB:$AB,$AR30)))="","",IF($AR30="","",IF(INDEX('_pockets'!$AB:$AB,$AR30)="","",INDEX('_pockets'!$AB:$AB,$AR30)))*100) | J30: =IF(IF($AR30="","",IF(INDEX('_pockets'!$Z:$Z,$AR30)="","",INDEX('_pockets'!$Z:$Z,$AR30)))="","",-IF($AR30="","",IF(INDEX('_pockets'!$Z:$Z,$AR30)="","",INDEX('_pockets'!$Z:$Z,$AR30)))) | K30: =IF(OR($AV30="",AND($AW30="",$AX30="")),$AV30,$AV30&" · borderline (p "&IF(AND($AW30<>"",$AX30<>""),$AW30&" and "&$AX30,$AW30&$AX30)&")") | AN30: =IFERROR(MATCH("C|"&$B$16&"|11",'_views'!$A:$A,0),"") | AO30: =IF($AN30="","",IF(INDEX('_views'!$B:$ZZ,$AN30,4)="","",INDEX('_views'!$B:$ZZ,$AN30,4))) | AP30: =IF($AN30="","",IF(INDEX('_views'!$B:$ZZ,$AN30,5)="","",INDEX('_views'!$B:$ZZ,$AN30,5))) | AQ30: =IF($AN30="","",IF(INDEX('_views'!$B:$ZZ,$AN30,6)="","",INDEX('_views'!$B:$ZZ,$AN30,6))) | AR30: =IF($AN30="","",IF(INDEX('_views'!$B:$ZZ,$AN30,7)="","",INDEX('_views'!$B:$ZZ,$AN30,7))) | AS30: =IF($AP30="","",IF(INDEX('_pockets'!$Y:$Y,$AP30)="","",INDEX('_pockets'!$Y:$Y,$AP30))) | AT30: =IF($AQ30="","",IF(INDEX('_pockets'!$Y:$Y,$AQ30)="","",INDEX('_pockets'!$Y:$Y,$AQ30))) | AU30: =IF($AR30="","",IF(INDEX('_pockets'!$Y:$Y,$AR30)="","",INDEX('_pockets'!$Y:$Y,$AR30))) | AV30: =IF(OR($AO30=1,$AO30=""),"",IF(AND($AT30="worse",$AU30="better"),"Priced for it",IF(AND($AT30="worse",$AU30="worse"),"Net drain",IF(AND($AT30="better",$AU30="better"),"Strong",IF(AND($AT30="better",$AU30="worse"),"Safe but idle",IF(AND(OR($AT30="in line",$AT30="worse, not significant",$AT30="better, not significant"),$AU30="worse"),"Earns less, not from losses",IF(AND($AT30="worse",OR($AU30="in line",$AU30="worse, not significant",$AU30="better, not significant")),"Losing more, profit holding",""))))))) | AW30: =IF($AQ30="","",IF(INDEX('_pockets'!$AM:$AM,$AQ30)="","",INDEX('_pockets'!$AM:$AM,$AQ30))) | AX30: =IF($AR30="","",IF(INDEX('_pockets'!$AM:$AM,$AR30)="","",INDEX('_pockets'!$AM:$AM,$AR30)))
B31: =IF($AN31="","",IF(INDEX('_views'!$B:$ZZ,$AN31,1)="","",INDEX('_views'!$B:$ZZ,$AN31,1))) | C31: =IF($AN31="","",IF(INDEX('_views'!$B:$ZZ,$AN31,2)="","",INDEX('_views'!$B:$ZZ,$AN31,2))) | D31: =IF($AN31="","",IF(INDEX('_views'!$B:$ZZ,$AN31,3)="","",INDEX('_views'!$B:$ZZ,$AN31,3))) | E31: =IF(IF($AP31="","",IF(INDEX('_pockets'!$AB:$AB,$AP31)="","",INDEX('_pockets'!$AB:$AB,$AP31)))="","",IF($AP31="","",IF(INDEX('_pockets'!$AB:$AB,$AP31)="","",INDEX('_pockets'!$AB:$AB,$AP31)))*100) | F31: =IF(IF($AP31="","",IF(INDEX('_pockets'!$Z:$Z,$AP31)="","",INDEX('_pockets'!$Z:$Z,$AP31)))="","",-IF($AP31="","",IF(INDEX('_pockets'!$Z:$Z,$AP31)="","",INDEX('_pockets'!$Z:$Z,$AP31)))) | G31: =IF($AQ31="","",IF(INDEX('_pockets'!$AB:$AB,$AQ31)="","",INDEX('_pockets'!$AB:$AB,$AQ31))) | H31: =IF($AQ31="","",IF(INDEX('_pockets'!$Z:$Z,$AQ31)="","",INDEX('_pockets'!$Z:$Z,$AQ31))) | I31: =IF(IF($AR31="","",IF(INDEX('_pockets'!$AB:$AB,$AR31)="","",INDEX('_pockets'!$AB:$AB,$AR31)))="","",IF($AR31="","",IF(INDEX('_pockets'!$AB:$AB,$AR31)="","",INDEX('_pockets'!$AB:$AB,$AR31)))*100) | J31: =IF(IF($AR31="","",IF(INDEX('_pockets'!$Z:$Z,$AR31)="","",INDEX('_pockets'!$Z:$Z,$AR31)))="","",-IF($AR31="","",IF(INDEX('_pockets'!$Z:$Z,$AR31)="","",INDEX('_pockets'!$Z:$Z,$AR31)))) | K31: =IF(OR($AV31="",AND($AW31="",$AX31="")),$AV31,$AV31&" · borderline (p "&IF(AND($AW31<>"",$AX31<>""),$AW31&" and "&$AX31,$AW31&$AX31)&")") | AN31: =IFERROR(MATCH("C|"&$B$16&"|12",'_views'!$A:$A,0),"") | AO31: =IF($AN31="","",IF(INDEX('_views'!$B:$ZZ,$AN31,4)="","",INDEX('_views'!$B:$ZZ,$AN31,4))) | AP31: =IF($AN31="","",IF(INDEX('_views'!$B:$ZZ,$AN31,5)="","",INDEX('_views'!$B:$ZZ,$AN31,5))) | AQ31: =IF($AN31="","",IF(INDEX('_views'!$B:$ZZ,$AN31,6)="","",INDEX('_views'!$B:$ZZ,$AN31,6))) | AR31: =IF($AN31="","",IF(INDEX('_views'!$B:$ZZ,$AN31,7)="","",INDEX('_views'!$B:$ZZ,$AN31,7))) | AS31: =IF($AP31="","",IF(INDEX('_pockets'!$Y:$Y,$AP31)="","",INDEX('_pockets'!$Y:$Y,$AP31))) | AT31: =IF($AQ31="","",IF(INDEX('_pockets'!$Y:$Y,$AQ31)="","",INDEX('_pockets'!$Y:$Y,$AQ31))) | AU31: =IF($AR31="","",IF(INDEX('_pockets'!$Y:$Y,$AR31)="","",INDEX('_pockets'!$Y:$Y,$AR31))) | AV31: =IF(OR($AO31=1,$AO31=""),"",IF(AND($AT31="worse",$AU31="better"),"Priced for it",IF(AND($AT31="worse",$AU31="worse"),"Net drain",IF(AND($AT31="better",$AU31="better"),"Strong",IF(AND($AT31="better",$AU31="worse"),"Safe but idle",IF(AND(OR($AT31="in line",$AT31="worse, not significant",$AT31="better, not significant"),$AU31="worse"),"Earns less, not from losses",IF(AND($AT31="worse",OR($AU31="in line",$AU31="worse, not significant",$AU31="better, not significant")),"Losing more, profit holding",""))))))) | AW31: =IF($AQ31="","",IF(INDEX('_pockets'!$AM:$AM,$AQ31)="","",INDEX('_pockets'!$AM:$AM,$AQ31))) | AX31: =IF($AR31="","",IF(INDEX('_pockets'!$AM:$AM,$AR31)="","",INDEX('_pockets'!$AM:$AM,$AR31)))
B32: =IF($AN32="","",IF(INDEX('_views'!$B:$ZZ,$AN32,1)="","",INDEX('_views'!$B:$ZZ,$AN32,1))) | C32: =IF($AN32="","",IF(INDEX('_views'!$B:$ZZ,$AN32,2)="","",INDEX('_views'!$B:$ZZ,$AN32,2))) | D32: =IF($AN32="","",IF(INDEX('_views'!$B:$ZZ,$AN32,3)="","",INDEX('_views'!$B:$ZZ,$AN32,3))) | E32: =IF(IF($AP32="","",IF(INDEX('_pockets'!$AB:$AB,$AP32)="","",INDEX('_pockets'!$AB:$AB,$AP32)))="","",IF($AP32="","",IF(INDEX('_pockets'!$AB:$AB,$AP32)="","",INDEX('_pockets'!$AB:$AB,$AP32)))*100) | F32: =IF(IF($AP32="","",IF(INDEX('_pockets'!$Z:$Z,$AP32)="","",INDEX('_pockets'!$Z:$Z,$AP32)))="","",-IF($AP32="","",IF(INDEX('_pockets'!$Z:$Z,$AP32)="","",INDEX('_pockets'!$Z:$Z,$AP32)))) | G32: =IF($AQ32="","",IF(INDEX('_pockets'!$AB:$AB,$AQ32)="","",INDEX('_pockets'!$AB:$AB,$AQ32))) | H32: =IF($AQ32="","",IF(INDEX('_pockets'!$Z:$Z,$AQ32)="","",INDEX('_pockets'!$Z:$Z,$AQ32))) | I32: =IF(IF($AR32="","",IF(INDEX('_pockets'!$AB:$AB,$AR32)="","",INDEX('_pockets'!$AB:$AB,$AR32)))="","",IF($AR32="","",IF(INDEX('_pockets'!$AB:$AB,$AR32)="","",INDEX('_pockets'!$AB:$AB,$AR32)))*100) | J32: =IF(IF($AR32="","",IF(INDEX('_pockets'!$Z:$Z,$AR32)="","",INDEX('_pockets'!$Z:$Z,$AR32)))="","",-IF($AR32="","",IF(INDEX('_pockets'!$Z:$Z,$AR32)="","",INDEX('_pockets'!$Z:$Z,$AR32)))) | K32: =IF(OR($AV32="",AND($AW32="",$AX32="")),$AV32,$AV32&" · borderline (p "&IF(AND($AW32<>"",$AX32<>""),$AW32&" and "&$AX32,$AW32&$AX32)&")") | AN32: =IFERROR(MATCH("C|"&$B$16&"|13",'_views'!$A:$A,0),"") | AO32: =IF($AN32="","",IF(INDEX('_views'!$B:$ZZ,$AN32,4)="","",INDEX('_views'!$B:$ZZ,$AN32,4))) | AP32: =IF($AN32="","",IF(INDEX('_views'!$B:$ZZ,$AN32,5)="","",INDEX('_views'!$B:$ZZ,$AN32,5))) | AQ32: =IF($AN32="","",IF(INDEX('_views'!$B:$ZZ,$AN32,6)="","",INDEX('_views'!$B:$ZZ,$AN32,6))) | AR32: =IF($AN32="","",IF(INDEX('_views'!$B:$ZZ,$AN32,7)="","",INDEX('_views'!$B:$ZZ,$AN32,7))) | AS32: =IF($AP32="","",IF(INDEX('_pockets'!$Y:$Y,$AP32)="","",INDEX('_pockets'!$Y:$Y,$AP32))) | AT32: =IF($AQ32="","",IF(INDEX('_pockets'!$Y:$Y,$AQ32)="","",INDEX('_pockets'!$Y:$Y,$AQ32))) | AU32: =IF($AR32="","",IF(INDEX('_pockets'!$Y:$Y,$AR32)="","",INDEX('_pockets'!$Y:$Y,$AR32))) | AV32: =IF(OR($AO32=1,$AO32=""),"",IF(AND($AT32="worse",$AU32="better"),"Priced for it",IF(AND($AT32="worse",$AU32="worse"),"Net drain",IF(AND($AT32="better",$AU32="better"),"Strong",IF(AND($AT32="better",$AU32="worse"),"Safe but idle",IF(AND(OR($AT32="in line",$AT32="worse, not significant",$AT32="better, not significant"),$AU32="worse"),"Earns less, not from losses",IF(AND($AT32="worse",OR($AU32="in line",$AU32="worse, not significant",$AU32="better, not significant")),"Losing more, profit holding",""))))))) | AW32: =IF($AQ32="","",IF(INDEX('_pockets'!$AM:$AM,$AQ32)="","",INDEX('_pockets'!$AM:$AM,$AQ32))) | AX32: =IF($AR32="","",IF(INDEX('_pockets'!$AM:$AM,$AR32)="","",INDEX('_pockets'!$AM:$AM,$AR32)))
B33: =IF($AN33="","",IF(INDEX('_views'!$B:$ZZ,$AN33,1)="","",INDEX('_views'!$B:$ZZ,$AN33,1))) | C33: =IF($AN33="","",IF(INDEX('_views'!$B:$ZZ,$AN33,2)="","",INDEX('_views'!$B:$ZZ,$AN33,2))) | D33: =IF($AN33="","",IF(INDEX('_views'!$B:$ZZ,$AN33,3)="","",INDEX('_views'!$B:$ZZ,$AN33,3))) | E33: =IF(IF($AP33="","",IF(INDEX('_pockets'!$AB:$AB,$AP33)="","",INDEX('_pockets'!$AB:$AB,$AP33)))="","",IF($AP33="","",IF(INDEX('_pockets'!$AB:$AB,$AP33)="","",INDEX('_pockets'!$AB:$AB,$AP33)))*100) | F33: =IF(IF($AP33="","",IF(INDEX('_pockets'!$Z:$Z,$AP33)="","",INDEX('_pockets'!$Z:$Z,$AP33)))="","",-IF($AP33="","",IF(INDEX('_pockets'!$Z:$Z,$AP33)="","",INDEX('_pockets'!$Z:$Z,$AP33)))) | G33: =IF($AQ33="","",IF(INDEX('_pockets'!$AB:$AB,$AQ33)="","",INDEX('_pockets'!$AB:$AB,$AQ33))) | H33: =IF($AQ33="","",IF(INDEX('_pockets'!$Z:$Z,$AQ33)="","",INDEX('_pockets'!$Z:$Z,$AQ33))) | I33: =IF(IF($AR33="","",IF(INDEX('_pockets'!$AB:$AB,$AR33)="","",INDEX('_pockets'!$AB:$AB,$AR33)))="","",IF($AR33="","",IF(INDEX('_pockets'!$AB:$AB,$AR33)="","",INDEX('_pockets'!$AB:$AB,$AR33)))*100) | J33: =IF(IF($AR33="","",IF(INDEX('_pockets'!$Z:$Z,$AR33)="","",INDEX('_pockets'!$Z:$Z,$AR33)))="","",-IF($AR33="","",IF(INDEX('_pockets'!$Z:$Z,$AR33)="","",INDEX('_pockets'!$Z:$Z,$AR33)))) | K33: =IF(OR($AV33="",AND($AW33="",$AX33="")),$AV33,$AV33&" · borderline (p "&IF(AND($AW33<>"",$AX33<>""),$AW33&" and "&$AX33,$AW33&$AX33)&")") | AN33: =IFERROR(MATCH("C|"&$B$16&"|14",'_views'!$A:$A,0),"") | AO33: =IF($AN33="","",IF(INDEX('_views'!$B:$ZZ,$AN33,4)="","",INDEX('_views'!$B:$ZZ,$AN33,4))) | AP33: =IF($AN33="","",IF(INDEX('_views'!$B:$ZZ,$AN33,5)="","",INDEX('_views'!$B:$ZZ,$AN33,5))) | AQ33: =IF($AN33="","",IF(INDEX('_views'!$B:$ZZ,$AN33,6)="","",INDEX('_views'!$B:$ZZ,$AN33,6))) | AR33: =IF($AN33="","",IF(INDEX('_views'!$B:$ZZ,$AN33,7)="","",INDEX('_views'!$B:$ZZ,$AN33,7))) | AS33: =IF($AP33="","",IF(INDEX('_pockets'!$Y:$Y,$AP33)="","",INDEX('_pockets'!$Y:$Y,$AP33))) | AT33: =IF($AQ33="","",IF(INDEX('_pockets'!$Y:$Y,$AQ33)="","",INDEX('_pockets'!$Y:$Y,$AQ33))) | AU33: =IF($AR33="","",IF(INDEX('_pockets'!$Y:$Y,$AR33)="","",INDEX('_pockets'!$Y:$Y,$AR33))) | AV33: =IF(OR($AO33=1,$AO33=""),"",IF(AND($AT33="worse",$AU33="better"),"Priced for it",IF(AND($AT33="worse",$AU33="worse"),"Net drain",IF(AND($AT33="better",$AU33="better"),"Strong",IF(AND($AT33="better",$AU33="worse"),"Safe but idle",IF(AND(OR($AT33="in line",$AT33="worse, not significant",$AT33="better, not significant"),$AU33="worse"),"Earns less, not from losses",IF(AND($AT33="worse",OR($AU33="in line",$AU33="worse, not significant",$AU33="better, not significant")),"Losing more, profit holding",""))))))) | AW33: =IF($AQ33="","",IF(INDEX('_pockets'!$AM:$AM,$AQ33)="","",INDEX('_pockets'!$AM:$AM,$AQ33))) | AX33: =IF($AR33="","",IF(INDEX('_pockets'!$AM:$AM,$AR33)="","",INDEX('_pockets'!$AM:$AM,$AR33)))
B34: =IF($AN34="","",IF(INDEX('_views'!$B:$ZZ,$AN34,1)="","",INDEX('_views'!$B:$ZZ,$AN34,1))) | C34: =IF($AN34="","",IF(INDEX('_views'!$B:$ZZ,$AN34,2)="","",INDEX('_views'!$B:$ZZ,$AN34,2))) | D34: =IF($AN34="","",IF(INDEX('_views'!$B:$ZZ,$AN34,3)="","",INDEX('_views'!$B:$ZZ,$AN34,3))) | E34: =IF(IF($AP34="","",IF(INDEX('_pockets'!$AB:$AB,$AP34)="","",INDEX('_pockets'!$AB:$AB,$AP34)))="","",IF($AP34="","",IF(INDEX('_pockets'!$AB:$AB,$AP34)="","",INDEX('_pockets'!$AB:$AB,$AP34)))*100) | F34: =IF(IF($AP34="","",IF(INDEX('_pockets'!$Z:$Z,$AP34)="","",INDEX('_pockets'!$Z:$Z,$AP34)))="","",-IF($AP34="","",IF(INDEX('_pockets'!$Z:$Z,$AP34)="","",INDEX('_pockets'!$Z:$Z,$AP34)))) | G34: =IF($AQ34="","",IF(INDEX('_pockets'!$AB:$AB,$AQ34)="","",INDEX('_pockets'!$AB:$AB,$AQ34))) | H34: =IF($AQ34="","",IF(INDEX('_pockets'!$Z:$Z,$AQ34)="","",INDEX('_pockets'!$Z:$Z,$AQ34))) | I34: =IF(IF($AR34="","",IF(INDEX('_pockets'!$AB:$AB,$AR34)="","",INDEX('_pockets'!$AB:$AB,$AR34)))="","",IF($AR34="","",IF(INDEX('_pockets'!$AB:$AB,$AR34)="","",INDEX('_pockets'!$AB:$AB,$AR34)))*100) | J34: =IF(IF($AR34="","",IF(INDEX('_pockets'!$Z:$Z,$AR34)="","",INDEX('_pockets'!$Z:$Z,$AR34)))="","",-IF($AR34="","",IF(INDEX('_pockets'!$Z:$Z,$AR34)="","",INDEX('_pockets'!$Z:$Z,$AR34)))) | K34: =IF(OR($AV34="",AND($AW34="",$AX34="")),$AV34,$AV34&" · borderline (p "&IF(AND($AW34<>"",$AX34<>""),$AW34&" and "&$AX34,$AW34&$AX34)&")") | AN34: =IFERROR(MATCH("C|"&$B$16&"|15",'_views'!$A:$A,0),"") | AO34: =IF($AN34="","",IF(INDEX('_views'!$B:$ZZ,$AN34,4)="","",INDEX('_views'!$B:$ZZ,$AN34,4))) | AP34: =IF($AN34="","",IF(INDEX('_views'!$B:$ZZ,$AN34,5)="","",INDEX('_views'!$B:$ZZ,$AN34,5))) | AQ34: =IF($AN34="","",IF(INDEX('_views'!$B:$ZZ,$AN34,6)="","",INDEX('_views'!$B:$ZZ,$AN34,6))) | AR34: =IF($AN34="","",IF(INDEX('_views'!$B:$ZZ,$AN34,7)="","",INDEX('_views'!$B:$ZZ,$AN34,7))) | AS34: =IF($AP34="","",IF(INDEX('_pockets'!$Y:$Y,$AP34)="","",INDEX('_pockets'!$Y:$Y,$AP34))) | AT34: =IF($AQ34="","",IF(INDEX('_pockets'!$Y:$Y,$AQ34)="","",INDEX('_pockets'!$Y:$Y,$AQ34))) | AU34: =IF($AR34="","",IF(INDEX('_pockets'!$Y:$Y,$AR34)="","",INDEX('_pockets'!$Y:$Y,$AR34))) | AV34: =IF(OR($AO34=1,$AO34=""),"",IF(AND($AT34="worse",$AU34="better"),"Priced for it",IF(AND($AT34="worse",$AU34="worse"),"Net drain",IF(AND($AT34="better",$AU34="better"),"Strong",IF(AND($AT34="better",$AU34="worse"),"Safe but idle",IF(AND(OR($AT34="in line",$AT34="worse, not significant",$AT34="better, not significant"),$AU34="worse"),"Earns less, not from losses",IF(AND($AT34="worse",OR($AU34="in line",$AU34="worse, not significant",$AU34="better, not significant")),"Losing more, profit holding",""))))))) | AW34: =IF($AQ34="","",IF(INDEX('_pockets'!$AM:$AM,$AQ34)="","",INDEX('_pockets'!$AM:$AM,$AQ34))) | AX34: =IF($AR34="","",IF(INDEX('_pockets'!$AM:$AM,$AR34)="","",INDEX('_pockets'!$AM:$AM,$AR34)))
B35: =IF($AN35="","",IF(INDEX('_views'!$B:$ZZ,$AN35,1)="","",INDEX('_views'!$B:$ZZ,$AN35,1))) | C35: =IF($AN35="","",IF(INDEX('_views'!$B:$ZZ,$AN35,2)="","",INDEX('_views'!$B:$ZZ,$AN35,2))) | D35: =IF($AN35="","",IF(INDEX('_views'!$B:$ZZ,$AN35,3)="","",INDEX('_views'!$B:$ZZ,$AN35,3))) | E35: =IF(IF($AP35="","",IF(INDEX('_pockets'!$AB:$AB,$AP35)="","",INDEX('_pockets'!$AB:$AB,$AP35)))="","",IF($AP35="","",IF(INDEX('_pockets'!$AB:$AB,$AP35)="","",INDEX('_pockets'!$AB:$AB,$AP35)))*100) | F35: =IF(IF($AP35="","",IF(INDEX('_pockets'!$Z:$Z,$AP35)="","",INDEX('_pockets'!$Z:$Z,$AP35)))="","",-IF($AP35="","",IF(INDEX('_pockets'!$Z:$Z,$AP35)="","",INDEX('_pockets'!$Z:$Z,$AP35)))) | G35: =IF($AQ35="","",IF(INDEX('_pockets'!$AB:$AB,$AQ35)="","",INDEX('_pockets'!$AB:$AB,$AQ35))) | H35: =IF($AQ35="","",IF(INDEX('_pockets'!$Z:$Z,$AQ35)="","",INDEX('_pockets'!$Z:$Z,$AQ35))) | I35: =IF(IF($AR35="","",IF(INDEX('_pockets'!$AB:$AB,$AR35)="","",INDEX('_pockets'!$AB:$AB,$AR35)))="","",IF($AR35="","",IF(INDEX('_pockets'!$AB:$AB,$AR35)="","",INDEX('_pockets'!$AB:$AB,$AR35)))*100) | J35: =IF(IF($AR35="","",IF(INDEX('_pockets'!$Z:$Z,$AR35)="","",INDEX('_pockets'!$Z:$Z,$AR35)))="","",-IF($AR35="","",IF(INDEX('_pockets'!$Z:$Z,$AR35)="","",INDEX('_pockets'!$Z:$Z,$AR35)))) | K35: =IF(OR($AV35="",AND($AW35="",$AX35="")),$AV35,$AV35&" · borderline (p "&IF(AND($AW35<>"",$AX35<>""),$AW35&" and "&$AX35,$AW35&$AX35)&")") | AN35: =IFERROR(MATCH("C|"&$B$16&"|16",'_views'!$A:$A,0),"") | AO35: =IF($AN35="","",IF(INDEX('_views'!$B:$ZZ,$AN35,4)="","",INDEX('_views'!$B:$ZZ,$AN35,4))) | AP35: =IF($AN35="","",IF(INDEX('_views'!$B:$ZZ,$AN35,5)="","",INDEX('_views'!$B:$ZZ,$AN35,5))) | AQ35: =IF($AN35="","",IF(INDEX('_views'!$B:$ZZ,$AN35,6)="","",INDEX('_views'!$B:$ZZ,$AN35,6))) | AR35: =IF($AN35="","",IF(INDEX('_views'!$B:$ZZ,$AN35,7)="","",INDEX('_views'!$B:$ZZ,$AN35,7))) | AS35: =IF($AP35="","",IF(INDEX('_pockets'!$Y:$Y,$AP35)="","",INDEX('_pockets'!$Y:$Y,$AP35))) | AT35: =IF($AQ35="","",IF(INDEX('_pockets'!$Y:$Y,$AQ35)="","",INDEX('_pockets'!$Y:$Y,$AQ35))) | AU35: =IF($AR35="","",IF(INDEX('_pockets'!$Y:$Y,$AR35)="","",INDEX('_pockets'!$Y:$Y,$AR35))) | AV35: =IF(OR($AO35=1,$AO35=""),"",IF(AND($AT35="worse",$AU35="better"),"Priced for it",IF(AND($AT35="worse",$AU35="worse"),"Net drain",IF(AND($AT35="better",$AU35="better"),"Strong",IF(AND($AT35="better",$AU35="worse"),"Safe but idle",IF(AND(OR($AT35="in line",$AT35="worse, not significant",$AT35="better, not significant"),$AU35="worse"),"Earns less, not from losses",IF(AND($AT35="worse",OR($AU35="in line",$AU35="worse, not significant",$AU35="better, not significant")),"Losing more, profit holding",""))))))) | AW35: =IF($AQ35="","",IF(INDEX('_pockets'!$AM:$AM,$AQ35)="","",INDEX('_pockets'!$AM:$AM,$AQ35))) | AX35: =IF($AR35="","",IF(INDEX('_pockets'!$AM:$AM,$AR35)="","",INDEX('_pockets'!$AM:$AM,$AR35)))
B36: =IF($AN36="","",IF(INDEX('_views'!$B:$ZZ,$AN36,1)="","",INDEX('_views'!$B:$ZZ,$AN36,1))) | C36: =IF($AN36="","",IF(INDEX('_views'!$B:$ZZ,$AN36,2)="","",INDEX('_views'!$B:$ZZ,$AN36,2))) | D36: =IF($AN36="","",IF(INDEX('_views'!$B:$ZZ,$AN36,3)="","",INDEX('_views'!$B:$ZZ,$AN36,3))) | E36: =IF(IF($AP36="","",IF(INDEX('_pockets'!$AB:$AB,$AP36)="","",INDEX('_pockets'!$AB:$AB,$AP36)))="","",IF($AP36="","",IF(INDEX('_pockets'!$AB:$AB,$AP36)="","",INDEX('_pockets'!$AB:$AB,$AP36)))*100) | F36: =IF(IF($AP36="","",IF(INDEX('_pockets'!$Z:$Z,$AP36)="","",INDEX('_pockets'!$Z:$Z,$AP36)))="","",-IF($AP36="","",IF(INDEX('_pockets'!$Z:$Z,$AP36)="","",INDEX('_pockets'!$Z:$Z,$AP36)))) | G36: =IF($AQ36="","",IF(INDEX('_pockets'!$AB:$AB,$AQ36)="","",INDEX('_pockets'!$AB:$AB,$AQ36))) | H36: =IF($AQ36="","",IF(INDEX('_pockets'!$Z:$Z,$AQ36)="","",INDEX('_pockets'!$Z:$Z,$AQ36))) | I36: =IF(IF($AR36="","",IF(INDEX('_pockets'!$AB:$AB,$AR36)="","",INDEX('_pockets'!$AB:$AB,$AR36)))="","",IF($AR36="","",IF(INDEX('_pockets'!$AB:$AB,$AR36)="","",INDEX('_pockets'!$AB:$AB,$AR36)))*100) | J36: =IF(IF($AR36="","",IF(INDEX('_pockets'!$Z:$Z,$AR36)="","",INDEX('_pockets'!$Z:$Z,$AR36)))="","",-IF($AR36="","",IF(INDEX('_pockets'!$Z:$Z,$AR36)="","",INDEX('_pockets'!$Z:$Z,$AR36)))) | K36: =IF(OR($AV36="",AND($AW36="",$AX36="")),$AV36,$AV36&" · borderline (p "&IF(AND($AW36<>"",$AX36<>""),$AW36&" and "&$AX36,$AW36&$AX36)&")") | AN36: =IFERROR(MATCH("C|"&$B$16&"|17",'_views'!$A:$A,0),"") | AO36: =IF($AN36="","",IF(INDEX('_views'!$B:$ZZ,$AN36,4)="","",INDEX('_views'!$B:$ZZ,$AN36,4))) | AP36: =IF($AN36="","",IF(INDEX('_views'!$B:$ZZ,$AN36,5)="","",INDEX('_views'!$B:$ZZ,$AN36,5))) | AQ36: =IF($AN36="","",IF(INDEX('_views'!$B:$ZZ,$AN36,6)="","",INDEX('_views'!$B:$ZZ,$AN36,6))) | AR36: =IF($AN36="","",IF(INDEX('_views'!$B:$ZZ,$AN36,7)="","",INDEX('_views'!$B:$ZZ,$AN36,7))) | AS36: =IF($AP36="","",IF(INDEX('_pockets'!$Y:$Y,$AP36)="","",INDEX('_pockets'!$Y:$Y,$AP36))) | AT36: =IF($AQ36="","",IF(INDEX('_pockets'!$Y:$Y,$AQ36)="","",INDEX('_pockets'!$Y:$Y,$AQ36))) | AU36: =IF($AR36="","",IF(INDEX('_pockets'!$Y:$Y,$AR36)="","",INDEX('_pockets'!$Y:$Y,$AR36))) | AV36: =IF(OR($AO36=1,$AO36=""),"",IF(AND($AT36="worse",$AU36="better"),"Priced for it",IF(AND($AT36="worse",$AU36="worse"),"Net drain",IF(AND($AT36="better",$AU36="better"),"Strong",IF(AND($AT36="better",$AU36="worse"),"Safe but idle",IF(AND(OR($AT36="in line",$AT36="worse, not significant",$AT36="better, not significant"),$AU36="worse"),"Earns less, not from losses",IF(AND($AT36="worse",OR($AU36="in line",$AU36="worse, not significant",$AU36="better, not significant")),"Losing more, profit holding",""))))))) | AW36: =IF($AQ36="","",IF(INDEX('_pockets'!$AM:$AM,$AQ36)="","",INDEX('_pockets'!$AM:$AM,$AQ36))) | AX36: =IF($AR36="","",IF(INDEX('_pockets'!$AM:$AM,$AR36)="","",INDEX('_pockets'!$AM:$AM,$AR36)))
B37: =IF($AN37="","",IF(INDEX('_views'!$B:$ZZ,$AN37,1)="","",INDEX('_views'!$B:$ZZ,$AN37,1))) | C37: =IF($AN37="","",IF(INDEX('_views'!$B:$ZZ,$AN37,2)="","",INDEX('_views'!$B:$ZZ,$AN37,2))) | D37: =IF($AN37="","",IF(INDEX('_views'!$B:$ZZ,$AN37,3)="","",INDEX('_views'!$B:$ZZ,$AN37,3))) | E37: =IF(IF($AP37="","",IF(INDEX('_pockets'!$AB:$AB,$AP37)="","",INDEX('_pockets'!$AB:$AB,$AP37)))="","",IF($AP37="","",IF(INDEX('_pockets'!$AB:$AB,$AP37)="","",INDEX('_pockets'!$AB:$AB,$AP37)))*100) | F37: =IF(IF($AP37="","",IF(INDEX('_pockets'!$Z:$Z,$AP37)="","",INDEX('_pockets'!$Z:$Z,$AP37)))="","",-IF($AP37="","",IF(INDEX('_pockets'!$Z:$Z,$AP37)="","",INDEX('_pockets'!$Z:$Z,$AP37)))) | G37: =IF($AQ37="","",IF(INDEX('_pockets'!$AB:$AB,$AQ37)="","",INDEX('_pockets'!$AB:$AB,$AQ37))) | H37: =IF($AQ37="","",IF(INDEX('_pockets'!$Z:$Z,$AQ37)="","",INDEX('_pockets'!$Z:$Z,$AQ37))) | I37: =IF(IF($AR37="","",IF(INDEX('_pockets'!$AB:$AB,$AR37)="","",INDEX('_pockets'!$AB:$AB,$AR37)))="","",IF($AR37="","",IF(INDEX('_pockets'!$AB:$AB,$AR37)="","",INDEX('_pockets'!$AB:$AB,$AR37)))*100) | J37: =IF(IF($AR37="","",IF(INDEX('_pockets'!$Z:$Z,$AR37)="","",INDEX('_pockets'!$Z:$Z,$AR37)))="","",-IF($AR37="","",IF(INDEX('_pockets'!$Z:$Z,$AR37)="","",INDEX('_pockets'!$Z:$Z,$AR37)))) | K37: =IF(OR($AV37="",AND($AW37="",$AX37="")),$AV37,$AV37&" · borderline (p "&IF(AND($AW37<>"",$AX37<>""),$AW37&" and "&$AX37,$AW37&$AX37)&")") | AN37: =IFERROR(MATCH("C|"&$B$16&"|18",'_views'!$A:$A,0),"") | AO37: =IF($AN37="","",IF(INDEX('_views'!$B:$ZZ,$AN37,4)="","",INDEX('_views'!$B:$ZZ,$AN37,4))) | AP37: =IF($AN37="","",IF(INDEX('_views'!$B:$ZZ,$AN37,5)="","",INDEX('_views'!$B:$ZZ,$AN37,5))) | AQ37: =IF($AN37="","",IF(INDEX('_views'!$B:$ZZ,$AN37,6)="","",INDEX('_views'!$B:$ZZ,$AN37,6))) | AR37: =IF($AN37="","",IF(INDEX('_views'!$B:$ZZ,$AN37,7)="","",INDEX('_views'!$B:$ZZ,$AN37,7))) | AS37: =IF($AP37="","",IF(INDEX('_pockets'!$Y:$Y,$AP37)="","",INDEX('_pockets'!$Y:$Y,$AP37))) | AT37: =IF($AQ37="","",IF(INDEX('_pockets'!$Y:$Y,$AQ37)="","",INDEX('_pockets'!$Y:$Y,$AQ37))) | AU37: =IF($AR37="","",IF(INDEX('_pockets'!$Y:$Y,$AR37)="","",INDEX('_pockets'!$Y:$Y,$AR37))) | AV37: =IF(OR($AO37=1,$AO37=""),"",IF(AND($AT37="worse",$AU37="better"),"Priced for it",IF(AND($AT37="worse",$AU37="worse"),"Net drain",IF(AND($AT37="better",$AU37="better"),"Strong",IF(AND($AT37="better",$AU37="worse"),"Safe but idle",IF(AND(OR($AT37="in line",$AT37="worse, not significant",$AT37="better, not significant"),$AU37="worse"),"Earns less, not from losses",IF(AND($AT37="worse",OR($AU37="in line",$AU37="worse, not significant",$AU37="better, not significant")),"Losing more, profit holding",""))))))) | AW37: =IF($AQ37="","",IF(INDEX('_pockets'!$AM:$AM,$AQ37)="","",INDEX('_pockets'!$AM:$AM,$AQ37))) | AX37: =IF($AR37="","",IF(INDEX('_pockets'!$AM:$AM,$AR37)="","",INDEX('_pockets'!$AM:$AM,$AR37)))
B38: =IF($AN38="","",IF(INDEX('_views'!$B:$ZZ,$AN38,1)="","",INDEX('_views'!$B:$ZZ,$AN38,1))) | C38: =IF($AN38="","",IF(INDEX('_views'!$B:$ZZ,$AN38,2)="","",INDEX('_views'!$B:$ZZ,$AN38,2))) | D38: =IF($AN38="","",IF(INDEX('_views'!$B:$ZZ,$AN38,3)="","",INDEX('_views'!$B:$ZZ,$AN38,3))) | E38: =IF(IF($AP38="","",IF(INDEX('_pockets'!$AB:$AB,$AP38)="","",INDEX('_pockets'!$AB:$AB,$AP38)))="","",IF($AP38="","",IF(INDEX('_pockets'!$AB:$AB,$AP38)="","",INDEX('_pockets'!$AB:$AB,$AP38)))*100) | F38: =IF(IF($AP38="","",IF(INDEX('_pockets'!$Z:$Z,$AP38)="","",INDEX('_pockets'!$Z:$Z,$AP38)))="","",-IF($AP38="","",IF(INDEX('_pockets'!$Z:$Z,$AP38)="","",INDEX('_pockets'!$Z:$Z,$AP38)))) | G38: =IF($AQ38="","",IF(INDEX('_pockets'!$AB:$AB,$AQ38)="","",INDEX('_pockets'!$AB:$AB,$AQ38))) | H38: =IF($AQ38="","",IF(INDEX('_pockets'!$Z:$Z,$AQ38)="","",INDEX('_pockets'!$Z:$Z,$AQ38))) | I38: =IF(IF($AR38="","",IF(INDEX('_pockets'!$AB:$AB,$AR38)="","",INDEX('_pockets'!$AB:$AB,$AR38)))="","",IF($AR38="","",IF(INDEX('_pockets'!$AB:$AB,$AR38)="","",INDEX('_pockets'!$AB:$AB,$AR38)))*100) | J38: =IF(IF($AR38="","",IF(INDEX('_pockets'!$Z:$Z,$AR38)="","",INDEX('_pockets'!$Z:$Z,$AR38)))="","",-IF($AR38="","",IF(INDEX('_pockets'!$Z:$Z,$AR38)="","",INDEX('_pockets'!$Z:$Z,$AR38)))) | K38: =IF(OR($AV38="",AND($AW38="",$AX38="")),$AV38,$AV38&" · borderline (p "&IF(AND($AW38<>"",$AX38<>""),$AW38&" and "&$AX38,$AW38&$AX38)&")") | AN38: =IFERROR(MATCH("C|"&$B$16&"|19",'_views'!$A:$A,0),"") | AO38: =IF($AN38="","",IF(INDEX('_views'!$B:$ZZ,$AN38,4)="","",INDEX('_views'!$B:$ZZ,$AN38,4))) | AP38: =IF($AN38="","",IF(INDEX('_views'!$B:$ZZ,$AN38,5)="","",INDEX('_views'!$B:$ZZ,$AN38,5))) | AQ38: =IF($AN38="","",IF(INDEX('_views'!$B:$ZZ,$AN38,6)="","",INDEX('_views'!$B:$ZZ,$AN38,6))) | AR38: =IF($AN38="","",IF(INDEX('_views'!$B:$ZZ,$AN38,7)="","",INDEX('_views'!$B:$ZZ,$AN38,7))) | AS38: =IF($AP38="","",IF(INDEX('_pockets'!$Y:$Y,$AP38)="","",INDEX('_pockets'!$Y:$Y,$AP38))) | AT38: =IF($AQ38="","",IF(INDEX('_pockets'!$Y:$Y,$AQ38)="","",INDEX('_pockets'!$Y:$Y,$AQ38))) | AU38: =IF($AR38="","",IF(INDEX('_pockets'!$Y:$Y,$AR38)="","",INDEX('_pockets'!$Y:$Y,$AR38))) | AV38: =IF(OR($AO38=1,$AO38=""),"",IF(AND($AT38="worse",$AU38="better"),"Priced for it",IF(AND($AT38="worse",$AU38="worse"),"Net drain",IF(AND($AT38="better",$AU38="better"),"Strong",IF(AND($AT38="better",$AU38="worse"),"Safe but idle",IF(AND(OR($AT38="in line",$AT38="worse, not significant",$AT38="better, not significant"),$AU38="worse"),"Earns less, not from losses",IF(AND($AT38="worse",OR($AU38="in line",$AU38="worse, not significant",$AU38="better, not significant")),"Losing more, profit holding",""))))))) | AW38: =IF($AQ38="","",IF(INDEX('_pockets'!$AM:$AM,$AQ38)="","",INDEX('_pockets'!$AM:$AM,$AQ38))) | AX38: =IF($AR38="","",IF(INDEX('_pockets'!$AM:$AM,$AR38)="","",INDEX('_pockets'!$AM:$AM,$AR38)))
B39: =IF($AN39="","",IF(INDEX('_views'!$B:$ZZ,$AN39,1)="","",INDEX('_views'!$B:$ZZ,$AN39,1))) | C39: =IF($AN39="","",IF(INDEX('_views'!$B:$ZZ,$AN39,2)="","",INDEX('_views'!$B:$ZZ,$AN39,2))) | D39: =IF($AN39="","",IF(INDEX('_views'!$B:$ZZ,$AN39,3)="","",INDEX('_views'!$B:$ZZ,$AN39,3))) | E39: =IF(IF($AP39="","",IF(INDEX('_pockets'!$AB:$AB,$AP39)="","",INDEX('_pockets'!$AB:$AB,$AP39)))="","",IF($AP39="","",IF(INDEX('_pockets'!$AB:$AB,$AP39)="","",INDEX('_pockets'!$AB:$AB,$AP39)))*100) | F39: =IF(IF($AP39="","",IF(INDEX('_pockets'!$Z:$Z,$AP39)="","",INDEX('_pockets'!$Z:$Z,$AP39)))="","",-IF($AP39="","",IF(INDEX('_pockets'!$Z:$Z,$AP39)="","",INDEX('_pockets'!$Z:$Z,$AP39)))) | G39: =IF($AQ39="","",IF(INDEX('_pockets'!$AB:$AB,$AQ39)="","",INDEX('_pockets'!$AB:$AB,$AQ39))) | H39: =IF($AQ39="","",IF(INDEX('_pockets'!$Z:$Z,$AQ39)="","",INDEX('_pockets'!$Z:$Z,$AQ39))) | I39: =IF(IF($AR39="","",IF(INDEX('_pockets'!$AB:$AB,$AR39)="","",INDEX('_pockets'!$AB:$AB,$AR39)))="","",IF($AR39="","",IF(INDEX('_pockets'!$AB:$AB,$AR39)="","",INDEX('_pockets'!$AB:$AB,$AR39)))*100) | J39: =IF(IF($AR39="","",IF(INDEX('_pockets'!$Z:$Z,$AR39)="","",INDEX('_pockets'!$Z:$Z,$AR39)))="","",-IF($AR39="","",IF(INDEX('_pockets'!$Z:$Z,$AR39)="","",INDEX('_pockets'!$Z:$Z,$AR39)))) | K39: =IF(OR($AV39="",AND($AW39="",$AX39="")),$AV39,$AV39&" · borderline (p "&IF(AND($AW39<>"",$AX39<>""),$AW39&" and "&$AX39,$AW39&$AX39)&")") | AN39: =IFERROR(MATCH("C|"&$B$16&"|20",'_views'!$A:$A,0),"") | AO39: =IF($AN39="","",IF(INDEX('_views'!$B:$ZZ,$AN39,4)="","",INDEX('_views'!$B:$ZZ,$AN39,4))) | AP39: =IF($AN39="","",IF(INDEX('_views'!$B:$ZZ,$AN39,5)="","",INDEX('_views'!$B:$ZZ,$AN39,5))) | AQ39: =IF($AN39="","",IF(INDEX('_views'!$B:$ZZ,$AN39,6)="","",INDEX('_views'!$B:$ZZ,$AN39,6))) | AR39: =IF($AN39="","",IF(INDEX('_views'!$B:$ZZ,$AN39,7)="","",INDEX('_views'!$B:$ZZ,$AN39,7))) | AS39: =IF($AP39="","",IF(INDEX('_pockets'!$Y:$Y,$AP39)="","",INDEX('_pockets'!$Y:$Y,$AP39))) | AT39: =IF($AQ39="","",IF(INDEX('_pockets'!$Y:$Y,$AQ39)="","",INDEX('_pockets'!$Y:$Y,$AQ39))) | AU39: =IF($AR39="","",IF(INDEX('_pockets'!$Y:$Y,$AR39)="","",INDEX('_pockets'!$Y:$Y,$AR39))) | AV39: =IF(OR($AO39=1,$AO39=""),"",IF(AND($AT39="worse",$AU39="better"),"Priced for it",IF(AND($AT39="worse",$AU39="worse"),"Net drain",IF(AND($AT39="better",$AU39="better"),"Strong",IF(AND($AT39="better",$AU39="worse"),"Safe but idle",IF(AND(OR($AT39="in line",$AT39="worse, not significant",$AT39="better, not significant"),$AU39="worse"),"Earns less, not from losses",IF(AND($AT39="worse",OR($AU39="in line",$AU39="worse, not significant",$AU39="better, not significant")),"Losing more, profit holding",""))))))) | AW39: =IF($AQ39="","",IF(INDEX('_pockets'!$AM:$AM,$AQ39)="","",INDEX('_pockets'!$AM:$AM,$AQ39))) | AX39: =IF($AR39="","",IF(INDEX('_pockets'!$AM:$AM,$AR39)="","",INDEX('_pockets'!$AM:$AM,$AR39)))
B40: =IF($AN40="","",IF(INDEX('_views'!$B:$ZZ,$AN40,1)="","",INDEX('_views'!$B:$ZZ,$AN40,1))) | C40: =IF($AN40="","",IF(INDEX('_views'!$B:$ZZ,$AN40,2)="","",INDEX('_views'!$B:$ZZ,$AN40,2))) | D40: =IF($AN40="","",IF(INDEX('_views'!$B:$ZZ,$AN40,3)="","",INDEX('_views'!$B:$ZZ,$AN40,3))) | E40: =IF(IF($AP40="","",IF(INDEX('_pockets'!$AB:$AB,$AP40)="","",INDEX('_pockets'!$AB:$AB,$AP40)))="","",IF($AP40="","",IF(INDEX('_pockets'!$AB:$AB,$AP40)="","",INDEX('_pockets'!$AB:$AB,$AP40)))*100) | F40: =IF(IF($AP40="","",IF(INDEX('_pockets'!$Z:$Z,$AP40)="","",INDEX('_pockets'!$Z:$Z,$AP40)))="","",-IF($AP40="","",IF(INDEX('_pockets'!$Z:$Z,$AP40)="","",INDEX('_pockets'!$Z:$Z,$AP40)))) | G40: =IF($AQ40="","",IF(INDEX('_pockets'!$AB:$AB,$AQ40)="","",INDEX('_pockets'!$AB:$AB,$AQ40))) | H40: =IF($AQ40="","",IF(INDEX('_pockets'!$Z:$Z,$AQ40)="","",INDEX('_pockets'!$Z:$Z,$AQ40))) | I40: =IF(IF($AR40="","",IF(INDEX('_pockets'!$AB:$AB,$AR40)="","",INDEX('_pockets'!$AB:$AB,$AR40)))="","",IF($AR40="","",IF(INDEX('_pockets'!$AB:$AB,$AR40)="","",INDEX('_pockets'!$AB:$AB,$AR40)))*100) | J40: =IF(IF($AR40="","",IF(INDEX('_pockets'!$Z:$Z,$AR40)="","",INDEX('_pockets'!$Z:$Z,$AR40)))="","",-IF($AR40="","",IF(INDEX('_pockets'!$Z:$Z,$AR40)="","",INDEX('_pockets'!$Z:$Z,$AR40)))) | K40: =IF(OR($AV40="",AND($AW40="",$AX40="")),$AV40,$AV40&" · borderline (p "&IF(AND($AW40<>"",$AX40<>""),$AW40&" and "&$AX40,$AW40&$AX40)&")") | AN40: =IFERROR(MATCH("C|"&$B$16&"|21",'_views'!$A:$A,0),"") | AO40: =IF($AN40="","",IF(INDEX('_views'!$B:$ZZ,$AN40,4)="","",INDEX('_views'!$B:$ZZ,$AN40,4))) | AP40: =IF($AN40="","",IF(INDEX('_views'!$B:$ZZ,$AN40,5)="","",INDEX('_views'!$B:$ZZ,$AN40,5))) | AQ40: =IF($AN40="","",IF(INDEX('_views'!$B:$ZZ,$AN40,6)="","",INDEX('_views'!$B:$ZZ,$AN40,6))) | AR40: =IF($AN40="","",IF(INDEX('_views'!$B:$ZZ,$AN40,7)="","",INDEX('_views'!$B:$ZZ,$AN40,7))) | AS40: =IF($AP40="","",IF(INDEX('_pockets'!$Y:$Y,$AP40)="","",INDEX('_pockets'!$Y:$Y,$AP40))) | AT40: =IF($AQ40="","",IF(INDEX('_pockets'!$Y:$Y,$AQ40)="","",INDEX('_pockets'!$Y:$Y,$AQ40))) | AU40: =IF($AR40="","",IF(INDEX('_pockets'!$Y:$Y,$AR40)="","",INDEX('_pockets'!$Y:$Y,$AR40))) | AV40: =IF(OR($AO40=1,$AO40=""),"",IF(AND($AT40="worse",$AU40="better"),"Priced for it",IF(AND($AT40="worse",$AU40="worse"),"Net drain",IF(AND($AT40="better",$AU40="better"),"Strong",IF(AND($AT40="better",$AU40="worse"),"Safe but idle",IF(AND(OR($AT40="in line",$AT40="worse, not significant",$AT40="better, not significant"),$AU40="worse"),"Earns less, not from losses",IF(AND($AT40="worse",OR($AU40="in line",$AU40="worse, not significant",$AU40="better, not significant")),"Losing more, profit holding",""))))))) | AW40: =IF($AQ40="","",IF(INDEX('_pockets'!$AM:$AM,$AQ40)="","",INDEX('_pockets'!$AM:$AM,$AQ40))) | AX40: =IF($AR40="","",IF(INDEX('_pockets'!$AM:$AM,$AR40)="","",INDEX('_pockets'!$AM:$AM,$AR40)))
B41: =IF($AN41="","",IF(INDEX('_views'!$B:$ZZ,$AN41,1)="","",INDEX('_views'!$B:$ZZ,$AN41,1))) | C41: =IF($AN41="","",IF(INDEX('_views'!$B:$ZZ,$AN41,2)="","",INDEX('_views'!$B:$ZZ,$AN41,2))) | D41: =IF($AN41="","",IF(INDEX('_views'!$B:$ZZ,$AN41,3)="","",INDEX('_views'!$B:$ZZ,$AN41,3))) | E41: =IF(IF($AP41="","",IF(INDEX('_pockets'!$AB:$AB,$AP41)="","",INDEX('_pockets'!$AB:$AB,$AP41)))="","",IF($AP41="","",IF(INDEX('_pockets'!$AB:$AB,$AP41)="","",INDEX('_pockets'!$AB:$AB,$AP41)))*100) | F41: =IF(IF($AP41="","",IF(INDEX('_pockets'!$Z:$Z,$AP41)="","",INDEX('_pockets'!$Z:$Z,$AP41)))="","",-IF($AP41="","",IF(INDEX('_pockets'!$Z:$Z,$AP41)="","",INDEX('_pockets'!$Z:$Z,$AP41)))) | G41: =IF($AQ41="","",IF(INDEX('_pockets'!$AB:$AB,$AQ41)="","",INDEX('_pockets'!$AB:$AB,$AQ41))) | H41: =IF($AQ41="","",IF(INDEX('_pockets'!$Z:$Z,$AQ41)="","",INDEX('_pockets'!$Z:$Z,$AQ41))) | I41: =IF(IF($AR41="","",IF(INDEX('_pockets'!$AB:$AB,$AR41)="","",INDEX('_pockets'!$AB:$AB,$AR41)))="","",IF($AR41="","",IF(INDEX('_pockets'!$AB:$AB,$AR41)="","",INDEX('_pockets'!$AB:$AB,$AR41)))*100) | J41: =IF(IF($AR41="","",IF(INDEX('_pockets'!$Z:$Z,$AR41)="","",INDEX('_pockets'!$Z:$Z,$AR41)))="","",-IF($AR41="","",IF(INDEX('_pockets'!$Z:$Z,$AR41)="","",INDEX('_pockets'!$Z:$Z,$AR41)))) | K41: =IF(OR($AV41="",AND($AW41="",$AX41="")),$AV41,$AV41&" · borderline (p "&IF(AND($AW41<>"",$AX41<>""),$AW41&" and "&$AX41,$AW41&$AX41)&")") | M41: Numbered on the chart | AN41: =IFERROR(MATCH("C|"&$B$16&"|22",'_views'!$A:$A,0),"") | AO41: =IF($AN41="","",IF(INDEX('_views'!$B:$ZZ,$AN41,4)="","",INDEX('_views'!$B:$ZZ,$AN41,4))) | AP41: =IF($AN41="","",IF(INDEX('_views'!$B:$ZZ,$AN41,5)="","",INDEX('_views'!$B:$ZZ,$AN41,5))) | AQ41: =IF($AN41="","",IF(INDEX('_views'!$B:$ZZ,$AN41,6)="","",INDEX('_views'!$B:$ZZ,$AN41,6))) | AR41: =IF($AN41="","",IF(INDEX('_views'!$B:$ZZ,$AN41,7)="","",INDEX('_views'!$B:$ZZ,$AN41,7))) | AS41: =IF($AP41="","",IF(INDEX('_pockets'!$Y:$Y,$AP41)="","",INDEX('_pockets'!$Y:$Y,$AP41))) | AT41: =IF($AQ41="","",IF(INDEX('_pockets'!$Y:$Y,$AQ41)="","",INDEX('_pockets'!$Y:$Y,$AQ41))) | AU41: =IF($AR41="","",IF(INDEX('_pockets'!$Y:$Y,$AR41)="","",INDEX('_pockets'!$Y:$Y,$AR41))) | AV41: =IF(OR($AO41=1,$AO41=""),"",IF(AND($AT41="worse",$AU41="better"),"Priced for it",IF(AND($AT41="worse",$AU41="worse"),"Net drain",IF(AND($AT41="better",$AU41="better"),"Strong",IF(AND($AT41="better",$AU41="worse"),"Safe but idle",IF(AND(OR($AT41="in line",$AT41="worse, not significant",$AT41="better, not significant"),$AU41="worse"),"Earns less, not from losses",IF(AND($AT41="worse",OR($AU41="in line",$AU41="worse, not significant",$AU41="better, not significant")),"Losing more, profit holding",""))))))) | AW41: =IF($AQ41="","",IF(INDEX('_pockets'!$AM:$AM,$AQ41)="","",INDEX('_pockets'!$AM:$AM,$AQ41))) | AX41: =IF($AR41="","",IF(INDEX('_pockets'!$AM:$AM,$AR41)="","",INDEX('_pockets'!$AM:$AM,$AR41)))
B42: =IF($AN42="","",IF(INDEX('_views'!$B:$ZZ,$AN42,1)="","",INDEX('_views'!$B:$ZZ,$AN42,1))) | C42: =IF($AN42="","",IF(INDEX('_views'!$B:$ZZ,$AN42,2)="","",INDEX('_views'!$B:$ZZ,$AN42,2))) | D42: =IF($AN42="","",IF(INDEX('_views'!$B:$ZZ,$AN42,3)="","",INDEX('_views'!$B:$ZZ,$AN42,3))) | E42: =IF(IF($AP42="","",IF(INDEX('_pockets'!$AB:$AB,$AP42)="","",INDEX('_pockets'!$AB:$AB,$AP42)))="","",IF($AP42="","",IF(INDEX('_pockets'!$AB:$AB,$AP42)="","",INDEX('_pockets'!$AB:$AB,$AP42)))*100) | F42: =IF(IF($AP42="","",IF(INDEX('_pockets'!$Z:$Z,$AP42)="","",INDEX('_pockets'!$Z:$Z,$AP42)))="","",-IF($AP42="","",IF(INDEX('_pockets'!$Z:$Z,$AP42)="","",INDEX('_pockets'!$Z:$Z,$AP42)))) | G42: =IF($AQ42="","",IF(INDEX('_pockets'!$AB:$AB,$AQ42)="","",INDEX('_pockets'!$AB:$AB,$AQ42))) | H42: =IF($AQ42="","",IF(INDEX('_pockets'!$Z:$Z,$AQ42)="","",INDEX('_pockets'!$Z:$Z,$AQ42))) | I42: =IF(IF($AR42="","",IF(INDEX('_pockets'!$AB:$AB,$AR42)="","",INDEX('_pockets'!$AB:$AB,$AR42)))="","",IF($AR42="","",IF(INDEX('_pockets'!$AB:$AB,$AR42)="","",INDEX('_pockets'!$AB:$AB,$AR42)))*100) | J42: =IF(IF($AR42="","",IF(INDEX('_pockets'!$Z:$Z,$AR42)="","",INDEX('_pockets'!$Z:$Z,$AR42)))="","",-IF($AR42="","",IF(INDEX('_pockets'!$Z:$Z,$AR42)="","",INDEX('_pockets'!$Z:$Z,$AR42)))) | K42: =IF(OR($AV42="",AND($AW42="",$AX42="")),$AV42,$AV42&" · borderline (p "&IF(AND($AW42<>"",$AX42<>""),$AW42&" and "&$AX42,$AW42&$AX42)&")") | M42: =IF('_chart'!$C$1="","","1 "&'_chart'!$C$1) | AN42: =IFERROR(MATCH("C|"&$B$16&"|23",'_views'!$A:$A,0),"") | AO42: =IF($AN42="","",IF(INDEX('_views'!$B:$ZZ,$AN42,4)="","",INDEX('_views'!$B:$ZZ,$AN42,4))) | AP42: =IF($AN42="","",IF(INDEX('_views'!$B:$ZZ,$AN42,5)="","",INDEX('_views'!$B:$ZZ,$AN42,5))) | AQ42: =IF($AN42="","",IF(INDEX('_views'!$B:$ZZ,$AN42,6)="","",INDEX('_views'!$B:$ZZ,$AN42,6))) | AR42: =IF($AN42="","",IF(INDEX('_views'!$B:$ZZ,$AN42,7)="","",INDEX('_views'!$B:$ZZ,$AN42,7))) | AS42: =IF($AP42="","",IF(INDEX('_pockets'!$Y:$Y,$AP42)="","",INDEX('_pockets'!$Y:$Y,$AP42))) | AT42: =IF($AQ42="","",IF(INDEX('_pockets'!$Y:$Y,$AQ42)="","",INDEX('_pockets'!$Y:$Y,$AQ42))) | AU42: =IF($AR42="","",IF(INDEX('_pockets'!$Y:$Y,$AR42)="","",INDEX('_pockets'!$Y:$Y,$AR42))) | AV42: =IF(OR($AO42=1,$AO42=""),"",IF(AND($AT42="worse",$AU42="better"),"Priced for it",IF(AND($AT42="worse",$AU42="worse"),"Net drain",IF(AND($AT42="better",$AU42="better"),"Strong",IF(AND($AT42="better",$AU42="worse"),"Safe but idle",IF(AND(OR($AT42="in line",$AT42="worse, not significant",$AT42="better, not significant"),$AU42="worse"),"Earns less, not from losses",IF(AND($AT42="worse",OR($AU42="in line",$AU42="worse, not significant",$AU42="better, not significant")),"Losing more, profit holding",""))))))) | AW42: =IF($AQ42="","",IF(INDEX('_pockets'!$AM:$AM,$AQ42)="","",INDEX('_pockets'!$AM:$AM,$AQ42))) | AX42: =IF($AR42="","",IF(INDEX('_pockets'!$AM:$AM,$AR42)="","",INDEX('_pockets'!$AM:$AM,$AR42)))
B43: =IF($AN43="","",IF(INDEX('_views'!$B:$ZZ,$AN43,1)="","",INDEX('_views'!$B:$ZZ,$AN43,1))) | C43: =IF($AN43="","",IF(INDEX('_views'!$B:$ZZ,$AN43,2)="","",INDEX('_views'!$B:$ZZ,$AN43,2))) | D43: =IF($AN43="","",IF(INDEX('_views'!$B:$ZZ,$AN43,3)="","",INDEX('_views'!$B:$ZZ,$AN43,3))) | E43: =IF(IF($AP43="","",IF(INDEX('_pockets'!$AB:$AB,$AP43)="","",INDEX('_pockets'!$AB:$AB,$AP43)))="","",IF($AP43="","",IF(INDEX('_pockets'!$AB:$AB,$AP43)="","",INDEX('_pockets'!$AB:$AB,$AP43)))*100) | F43: =IF(IF($AP43="","",IF(INDEX('_pockets'!$Z:$Z,$AP43)="","",INDEX('_pockets'!$Z:$Z,$AP43)))="","",-IF($AP43="","",IF(INDEX('_pockets'!$Z:$Z,$AP43)="","",INDEX('_pockets'!$Z:$Z,$AP43)))) | G43: =IF($AQ43="","",IF(INDEX('_pockets'!$AB:$AB,$AQ43)="","",INDEX('_pockets'!$AB:$AB,$AQ43))) | H43: =IF($AQ43="","",IF(INDEX('_pockets'!$Z:$Z,$AQ43)="","",INDEX('_pockets'!$Z:$Z,$AQ43))) | I43: =IF(IF($AR43="","",IF(INDEX('_pockets'!$AB:$AB,$AR43)="","",INDEX('_pockets'!$AB:$AB,$AR43)))="","",IF($AR43="","",IF(INDEX('_pockets'!$AB:$AB,$AR43)="","",INDEX('_pockets'!$AB:$AB,$AR43)))*100) | J43: =IF(IF($AR43="","",IF(INDEX('_pockets'!$Z:$Z,$AR43)="","",INDEX('_pockets'!$Z:$Z,$AR43)))="","",-IF($AR43="","",IF(INDEX('_pockets'!$Z:$Z,$AR43)="","",INDEX('_pockets'!$Z:$Z,$AR43)))) | K43: =IF(OR($AV43="",AND($AW43="",$AX43="")),$AV43,$AV43&" · borderline (p "&IF(AND($AW43<>"",$AX43<>""),$AW43&" and "&$AX43,$AW43&$AX43)&")") | M43: =IF('_chart'!$C$2="","","2 "&'_chart'!$C$2) | AN43: =IFERROR(MATCH("C|"&$B$16&"|24",'_views'!$A:$A,0),"") | AO43: =IF($AN43="","",IF(INDEX('_views'!$B:$ZZ,$AN43,4)="","",INDEX('_views'!$B:$ZZ,$AN43,4))) | AP43: =IF($AN43="","",IF(INDEX('_views'!$B:$ZZ,$AN43,5)="","",INDEX('_views'!$B:$ZZ,$AN43,5))) | AQ43: =IF($AN43="","",IF(INDEX('_views'!$B:$ZZ,$AN43,6)="","",INDEX('_views'!$B:$ZZ,$AN43,6))) | AR43: =IF($AN43="","",IF(INDEX('_views'!$B:$ZZ,$AN43,7)="","",INDEX('_views'!$B:$ZZ,$AN43,7))) | AS43: =IF($AP43="","",IF(INDEX('_pockets'!$Y:$Y,$AP43)="","",INDEX('_pockets'!$Y:$Y,$AP43))) | AT43: =IF($AQ43="","",IF(INDEX('_pockets'!$Y:$Y,$AQ43)="","",INDEX('_pockets'!$Y:$Y,$AQ43))) | AU43: =IF($AR43="","",IF(INDEX('_pockets'!$Y:$Y,$AR43)="","",INDEX('_pockets'!$Y:$Y,$AR43))) | AV43: =IF(OR($AO43=1,$AO43=""),"",IF(AND($AT43="worse",$AU43="better"),"Priced for it",IF(AND($AT43="worse",$AU43="worse"),"Net drain",IF(AND($AT43="better",$AU43="better"),"Strong",IF(AND($AT43="better",$AU43="worse"),"Safe but idle",IF(AND(OR($AT43="in line",$AT43="worse, not significant",$AT43="better, not significant"),$AU43="worse"),"Earns less, not from losses",IF(AND($AT43="worse",OR($AU43="in line",$AU43="worse, not significant",$AU43="better, not significant")),"Losing more, profit holding",""))))))) | AW43: =IF($AQ43="","",IF(INDEX('_pockets'!$AM:$AM,$AQ43)="","",INDEX('_pockets'!$AM:$AM,$AQ43))) | AX43: =IF($AR43="","",IF(INDEX('_pockets'!$AM:$AM,$AR43)="","",INDEX('_pockets'!$AM:$AM,$AR43)))
