Workbook
Name answers_needed: Control!$J$15:$J$30
Name Status: Control!$H$24:$H$43
Name waiting_words: Control!$K$24:$K$43
Name worse_at: '_live'!$C$5
Name better_at: '_live'!$C$6
Name confidence: '_live'!$C$7
Name significance_bar: '_live'!$C$8
Name judged_band: '_live'!$C$9
Name materiality_kind: '_live'!$C$10
Name materiality_share: '_live'!$C$11
Name materiality_gco: '_live'!$C$12
Name profit_kind: '_live'!$C$13
Name profit_line: '_live'!$C$14
Name in_use_words: '_live'!$C$17
Name line_keys: '_live'!$G$20:$G$30
Name line_values: '_live'!$C$20:$C$30
Name book_gco: '_live'!$C$15
Name pk_kind: '_pockets'!$A$4:$A$1048576
Name pk_measure: '_pockets'!$E$4:$E$1048576
Name pk_dollars: '_pockets'!$Z$4:$Z$1048576
Name pk_flag: '_pockets'!$Y$4:$Y$1048576
Name pk_material: '_pockets'!$AA$4:$AA$1048576
Name pk_worse: '_pockets'!$AI$4:$AI$1048576
Name pk_mat: '_pockets'!$AJ$4:$AJ$1048576
Name pk_sel_measure: 'Pockets'!$C$18
Name pk_sel_kind: 'Pockets'!$D$18
Name pk_sel_show: 'Pockets'!$E$18

Sheet Start here
B1: PocketBook | C1: Consumer book Q3.csv · 8,000 loans · 10 columns · last Run 2026-09-29 21:04
B3: How this tab works
B4: Where things stand | C4: What is left before Run, counted live from Control and Columns as you fill them in.
B5: What the last Run found | C5: Pockets worse and material at Control's lines, and the five largest.
B6: The tabs | C6: Red tabs you fill in; black tabs hold results; grey tabs are the record.
B8: WHERE THINGS STAND
B9: Answers needed before Run | D9: Odd values to answer | F9: Changes waiting for a Run
B10: =IFERROR(SUM(answers_needed),0)+IF(Control!$C$33="",1,0)+IF(Columns!$C$3="Yes",0,1) | D10: =COUNTIFS(Columns!$S$13:$S$22,"?*",Columns!$H$13:$H$22,"") | F10: =IFERROR(COUNTIF(Status,"↻ Waiting for a Run"),0)
B11: Control and Columns | D11: Columns · Treat as | F11: Control · Status
B13: =IFERROR(IF(COUNTIF(Status,"↻ Waiting for a Run")=0,"","↻ "&COUNTIF(Status,"↻ Waiting for a Run")&IF(COUNTIF(Status,"↻ Waiting for a Run")=1," change is"," changes are")&" waiting for a Run. "&LEFT(INDEX(waiting_words,1)&INDEX(waiting_words,2)&INDEX(waiting_words,3)&INDEX(waiting_words,4)&INDEX(waiting_words,5)&INDEX(waiting_words,6)&INDEX(waiting_words,7)&INDEX(waiting_words,8)&INDEX(waiting_words,9)&INDEX(waiting_words,10)&INDEX(waiting_words,11)&INDEX(waiting_words,12)&INDEX(waiting_words,13)&INDEX(waiting_words,14)&INDEX(waiting_words,15)&INDEX(waiting_words,16)&INDEX(waiting_words,17)&INDEX(waiting_words,18)&INDEX(waiting_words,19)&INDEX(waiting_words,20),LEN(INDEX(waiting_words,1)&INDEX(waiting_words,2)&INDEX(waiting_words,3)&INDEX(waiting_words,4)&INDEX(waiting_words,5)&INDEX(waiting_words,6)&INDEX(waiting_words,7)&INDEX(waiting_words,8)&INDEX(waiting_words,9)&INDEX(waiting_words,10)&INDEX(waiting_words,11)&INDEX(waiting_words,12)&INDEX(waiting_words,13)&INDEX(waiting_words,14)&INDEX(waiting_words,15)&INDEX(waiting_words,16)&INDEX(waiting_words,17)&INDEX(waiting_words,18)&INDEX(waiting_words,19)&INDEX(waiting_words,20))-2)&". The result tabs still show the last Run. Save, close, and press Run in the launcher."),"")
B15: WHAT THE LAST RUN FOUND
B16: Pockets worse and material, charge-offs | D16: Dollars above their share, in those | F16: Pockets keeping less, worse and material
B17: =IFERROR(COUNTIFS(pk_kind,"grids",pk_measure,"gco_rate",pk_flag,"worse",pk_material,"yes")&" of 81","") | D17: =IFERROR(SUMIFS(pk_dollars,pk_kind,"grids",pk_measure,"gco_rate",pk_flag,"worse",pk_material,"yes"),"") | F17: =IFERROR(COUNTIFS(pk_kind,"grids",pk_measure,"ranr_rate",pk_flag,"worse",pk_material,"yes")&" short $"&TEXT(SUMIFS(pk_dollars,pk_kind,"grids",pk_measure,"ranr_rate",pk_flag,"worse",pk_material,"yes"),"#,##0"),"")
B19: Largest, worse and material | C19: Segment | D19: Loans | E19: × its comparison | F19: Dollars above share
B20: =IF($K20="","No pocket is worse and material.",INDEX('_found'!$B$6:$B$46,$K20)) | C20: =IF($K20="","",INDEX('_found'!$C$6:$C$46,$K20)) | D20: =IF($K20="","",INDEX('_found'!$D$6:$D$46,$K20)) | E20: =IF($K20="","",IF(INDEX('_pockets'!$AB:$AB,INDEX('_found'!$E$6:$E$46,$K20))="","",INDEX('_pockets'!$AB:$AB,INDEX('_found'!$E$6:$E$46,$K20)))) | F20: =IF($K20="","",IF(INDEX('_pockets'!$Z:$Z,INDEX('_found'!$E$6:$E$46,$K20))="","",INDEX('_pockets'!$Z:$Z,INDEX('_found'!$E$6:$E$46,$K20)))) | K20: =IFERROR(MATCH(1,'_found'!$G$6:$G$46,0),"")
B21: =IF($K21="","",INDEX('_found'!$B$6:$B$46,$K21)) | C21: =IF($K21="","",INDEX('_found'!$C$6:$C$46,$K21)) | D21: =IF($K21="","",INDEX('_found'!$D$6:$D$46,$K21)) | E21: =IF($K21="","",IF(INDEX('_pockets'!$AB:$AB,INDEX('_found'!$E$6:$E$46,$K21))="","",INDEX('_pockets'!$AB:$AB,INDEX('_found'!$E$6:$E$46,$K21)))) | F21: =IF($K21="","",IF(INDEX('_pockets'!$Z:$Z,INDEX('_found'!$E$6:$E$46,$K21))="","",INDEX('_pockets'!$Z:$Z,INDEX('_found'!$E$6:$E$46,$K21)))) | K21: =IFERROR(MATCH(2,'_found'!$G$6:$G$46,0),"")
B22: =IF($K22="","",INDEX('_found'!$B$6:$B$46,$K22)) | C22: =IF($K22="","",INDEX('_found'!$C$6:$C$46,$K22)) | D22: =IF($K22="","",INDEX('_found'!$D$6:$D$46,$K22)) | E22: =IF($K22="","",IF(INDEX('_pockets'!$AB:$AB,INDEX('_found'!$E$6:$E$46,$K22))="","",INDEX('_pockets'!$AB:$AB,INDEX('_found'!$E$6:$E$46,$K22)))) | F22: =IF($K22="","",IF(INDEX('_pockets'!$Z:$Z,INDEX('_found'!$E$6:$E$46,$K22))="","",INDEX('_pockets'!$Z:$Z,INDEX('_found'!$E$6:$E$46,$K22)))) | K22: =IFERROR(MATCH(3,'_found'!$G$6:$G$46,0),"")
B23: =IF($K23="","",INDEX('_found'!$B$6:$B$46,$K23)) | C23: =IF($K23="","",INDEX('_found'!$C$6:$C$46,$K23)) | D23: =IF($K23="","",INDEX('_found'!$D$6:$D$46,$K23)) | E23: =IF($K23="","",IF(INDEX('_pockets'!$AB:$AB,INDEX('_found'!$E$6:$E$46,$K23))="","",INDEX('_pockets'!$AB:$AB,INDEX('_found'!$E$6:$E$46,$K23)))) | F23: =IF($K23="","",IF(INDEX('_pockets'!$Z:$Z,INDEX('_found'!$E$6:$E$46,$K23))="","",INDEX('_pockets'!$Z:$Z,INDEX('_found'!$E$6:$E$46,$K23)))) | K23: =IFERROR(MATCH(4,'_found'!$G$6:$G$46,0),"")
B24: =IF($K24="","",INDEX('_found'!$B$6:$B$46,$K24)) | C24: =IF($K24="","",INDEX('_found'!$C$6:$C$46,$K24)) | D24: =IF($K24="","",INDEX('_found'!$D$6:$D$46,$K24)) | E24: =IF($K24="","",IF(INDEX('_pockets'!$AB:$AB,INDEX('_found'!$E$6:$E$46,$K24))="","",INDEX('_pockets'!$AB:$AB,INDEX('_found'!$E$6:$E$46,$K24)))) | F24: =IF($K24="","",IF(INDEX('_pockets'!$Z:$Z,INDEX('_found'!$E$6:$E$46,$K24))="","",INDEX('_pockets'!$Z:$Z,INDEX('_found'!$E$6:$E$46,$K24)))) | K24: =IFERROR(MATCH(5,'_found'!$G$6:$G$46,0),"")
B25: Every pocket, every measure: the Pockets tab.
B28: THE TABS
B29: You answer | D29: Results | G29: Record
B30: Control: the professional calls | D30: Pockets: every pocket, worse first | G30: Record: what ran, the tie-outs, every Run
B31: Columns: meanings, odd values, memory | D31: Paid, cost, kept: paid against cost
B32: Look: each number column's shape | D32: Grids: one grid at a time, and how common
D33: Split: each pocket split

Sheet Control
B1: Control | C1: The professional calls. The top block changes results now; the second waits for a Run.
B3: How this tab works
B4: Changes now | C4: The result tabs read these answers with formulas. Change one and every reading, dollar figure, colour and verdict follows at once. The order of rows stays as the last Run left it.
B5: Needs a Run | C5: These decide which pockets exist and which test each one gets, so they take effect when you press Run again. Status says when an answer differs from what the last Run used.
B6: Your answer | C6: Pick from the list, or type a number under Or your own: a number there wins. A shaded answer still needs one. Comes to shows what the answer amounts to now.
B7: Worked out | C7: Fewest loans, worse at and better at each have a value worked out from this extract, shown beside the setting. It is never picked for you.
B8: Chosen in the launcher | C8: What you're running and how the pockets are cut. Change them in the launcher's Choose tests, then press Next. They are shown here so a reviewer sees them.
B9: Materiality levels | C9: For each level: its dollar line, how many pockets have charge-offs above their share that reach it, and their part of all such dollars. It follows your answer live.
B11: Changes now | C11: Needs a Run | F11: Still needs an answer | G11: legend
B13: Changes now · the result tabs follow as you change these | G13: block|now | M13: What each materiality level keeps
B14: Setting | C14: Your answer | D14: Or your own | E14: Comes to | F14: Last Run used | I14: Worked out from the loans | M14: Level | N14: Dollars | O14: Pockets | P14: Of excess
B15: How much worse than its comparison a pocket must be | C15: The smallest significant gap in a typical pocket (suggested) | E15: =IF(NOT(TRUE),"",IF(AND($D$15<>"",$D$15<>"n/a"),$D$15,IF($C$15="","",IF(ISNA(IFERROR(MATCH($G$15&"|"&$C$15,_options!$A:$A,0),MATCH($G$15&"|"&IFERROR(VALUE($C$15),$C$15),_options!$H:$H,0))),"not an option",IFERROR(TEXT(worse_at,"0.00")&"×",IF(ISNUMBER(IFERROR(INDEX(_options!$D:$D,IFERROR(MATCH($G$15&"|"&$C$15,_options!$A:$A,0),MATCH($G$15&"|"&IFERROR(VALUE($C$15),$C$15),_options!$H:$H,0))),"")),TEXT(IFERROR(INDEX(_options!$D:$D,IFERROR(MATCH($G$15&"|"&$C$15,_options!$A:$A,0),MATCH($G$15&"|"&IFERROR(VALUE($C$15),$C$15),_options!$H:$H,0))),""),"0.00")&"×",IF(ISNUMBER($K$15),TEXT($K$15,"0.00")&"×",""))))))) | F15: 1.34 (worked out from this book) | G15: worse_at | I15: suggested: 1.34x, from this extract at the last Run | J15: =IF(AND(TRUE,$C15="",OR($D15="",$D15="n/a")),1,0) | K15: 1.34 | M15: =IFERROR("0.5%"&IF(AND(materiality_kind="share",ABS(materiality_share-0.005)<1E-9)," ◂",""),"0.5%") | N15: =IFERROR((0.005*book_gco),"") | O15: =IFERROR(COUNTIFS(pk_kind,"grids",pk_measure,"gco_rate",pk_dollars,">="&(0.005*book_gco),pk_dollars,">0"),"") | P15: =IFERROR(IF(SUMIFS(pk_dollars,pk_kind,"grids",pk_measure,"gco_rate",pk_dollars,">0")=0,0,SUMIFS(pk_dollars,pk_kind,"grids",pk_measure,"gco_rate",pk_dollars,">="&(0.005*book_gco),pk_dollars,">0")/SUMIFS(pk_dollars,pk_kind,"grids",pk_measure,"gco_rate",pk_dollars,">0")),"")
B16: How much better than its comparison a pocket must be | C16: The smallest significant gap in a typical pocket (suggested) | E16: =IF(NOT($C$33="Where the book bleeds"),"",IF(AND($D$16<>"",$D$16<>"n/a"),$D$16,IF($C$16="","",IF(ISNA(IFERROR(MATCH($G$16&"|"&$C$16,_options!$A:$A,0),MATCH($G$16&"|"&IFERROR(VALUE($C$16),$C$16),_options!$H:$H,0))),"not an option",IFERROR(TEXT(better_at,"0.00")&"×",IF(ISNUMBER(IFERROR(INDEX(_options!$D:$D,IFERROR(MATCH($G$16&"|"&$C$16,_options!$A:$A,0),MATCH($G$16&"|"&IFERROR(VALUE($C$16),$C$16),_options!$H:$H,0))),"")),TEXT(IFERROR(INDEX(_options!$D:$D,IFERROR(MATCH($G$16&"|"&$C$16,_options!$A:$A,0),MATCH($G$16&"|"&IFERROR(VALUE($C$16),$C$16),_options!$H:$H,0))),""),"0.00")&"×",IF(ISNUMBER($K$16),TEXT($K$16,"0.00")&"×",""))))))) | F16: 0.75 (worked out from this book) | G16: better_at | I16: suggested: 0.75x, from this extract at the last Run | J16: =IF(AND($C$33="Where the book bleeds",$C16="",OR($D16="",$D16="n/a")),1,0) | K16: 0.75 | M16: =IFERROR("1%"&IF(AND(materiality_kind="share",ABS(materiality_share-0.01)<1E-9)," ◂",""),"1%") | N16: =IFERROR((0.01*book_gco),"") | O16: =IFERROR(COUNTIFS(pk_kind,"grids",pk_measure,"gco_rate",pk_dollars,">="&(0.01*book_gco),pk_dollars,">0"),"") | P16: =IFERROR(IF(SUMIFS(pk_dollars,pk_kind,"grids",pk_measure,"gco_rate",pk_dollars,">0")=0,0,SUMIFS(pk_dollars,pk_kind,"grids",pk_measure,"gco_rate",pk_dollars,">="&(0.01*book_gco),pk_dollars,">0")/SUMIFS(pk_dollars,pk_kind,"grids",pk_measure,"gco_rate",pk_dollars,">0")),"")
B17: How far profit must move before it counts as more or less | C17: Each pocket's own test (suggested) | E17: =IF(NOT($C$33="Where the book bleeds"),"",IF(AND($D$17<>"",$D$17<>"n/a"),$D$17,IF($C$17="","",IF(ISNA(IFERROR(MATCH($G$17&"|"&$C$17,_options!$A:$A,0),MATCH($G$17&"|"&IFERROR(VALUE($C$17),$C$17),_options!$H:$H,0))),"not an option","")))) | F17: each pocket's own test | G17: revenue_line | J17: =IF(AND($C$33="Where the book bleeds",$C17="",OR($D17="",$D17="n/a")),1,0) | M17: =IFERROR("2%"&IF(AND(materiality_kind="share",ABS(materiality_share-0.02)<1E-9)," ◂",""),"2%") | N17: =IFERROR((0.02*book_gco),"") | O17: =IFERROR(COUNTIFS(pk_kind,"grids",pk_measure,"gco_rate",pk_dollars,">="&(0.02*book_gco),pk_dollars,">0"),"") | P17: =IFERROR(IF(SUMIFS(pk_dollars,pk_kind,"grids",pk_measure,"gco_rate",pk_dollars,">0")=0,0,SUMIFS(pk_dollars,pk_kind,"grids",pk_measure,"gco_rate",pk_dollars,">="&(0.02*book_gco),pk_dollars,">0")/SUMIFS(pk_dollars,pk_kind,"grids",pk_measure,"gco_rate",pk_dollars,">0")),"")
B18: How sure a difference must be before it counts | C18: 95% sure | E18: =IF(NOT(TRUE),"",IF(AND($D$18<>"",$D$18<>"n/a"),$D$18,IF($C$18="","",IF(ISNA(IFERROR(MATCH($G$18&"|"&$C$18,_options!$A:$A,0),MATCH($G$18&"|"&IFERROR(VALUE($C$18),$C$18),_options!$H:$H,0))),"not an option","")))) | F18: 95% sure | G18: confidence | J18: =IF(AND(TRUE,$C18="",OR($D18="",$D18="n/a")),1,0) | M18: =IFERROR("5%"&IF(AND(materiality_kind="share",ABS(materiality_share-0.05)<1E-9)," ◂",""),"5%") | N18: =IFERROR((0.05*book_gco),"") | O18: =IFERROR(COUNTIFS(pk_kind,"grids",pk_measure,"gco_rate",pk_dollars,">="&(0.05*book_gco),pk_dollars,">0"),"") | P18: =IFERROR(IF(SUMIFS(pk_dollars,pk_kind,"grids",pk_measure,"gco_rate",pk_dollars,">0")=0,0,SUMIFS(pk_dollars,pk_kind,"grids",pk_measure,"gco_rate",pk_dollars,">="&(0.05*book_gco),pk_dollars,">0")/SUMIFS(pk_dollars,pk_kind,"grids",pk_measure,"gco_rate",pk_dollars,">0")),"")
B19: Smallest excess loss worth reporting | C19: 1% of the book's total losses | E19: =IF(NOT(TRUE),"",IF(AND($D$19<>"",$D$19<>"n/a"),$D$19,IF($C$19="","",IF(ISNA(IFERROR(MATCH($G$19&"|"&$C$19,_options!$A:$A,0),MATCH($G$19&"|"&IFERROR(VALUE($C$19),$C$19),_options!$H:$H,0))),"not an option",IFERROR(IF(materiality_kind="none","No floor",IF(materiality_gco>0,"$"&TEXT(materiality_gco,"#,##0"),IFERROR(INDEX(_options!$G:$G,IFERROR(MATCH($G$19&"|"&$C$19,_options!$A:$A,0),MATCH($G$19&"|"&IFERROR(VALUE($C$19),$C$19),_options!$H:$H,0))),"not an option"))),""))))) | F19: 1% of the book's total losses | G19: materiality | J19: =IF(AND(TRUE,$C19="",OR($D19="",$D19="n/a")),1,0) | M19: =IFERROR("10%"&IF(AND(materiality_kind="share",ABS(materiality_share-0.1)<1E-9)," ◂",""),"10%") | N19: =IFERROR((0.1*book_gco),"") | O19: =IFERROR(COUNTIFS(pk_kind,"grids",pk_measure,"gco_rate",pk_dollars,">="&(0.1*book_gco),pk_dollars,">0"),"") | P19: =IFERROR(IF(SUMIFS(pk_dollars,pk_kind,"grids",pk_measure,"gco_rate",pk_dollars,">0")=0,0,SUMIFS(pk_dollars,pk_kind,"grids",pk_measure,"gco_rate",pk_dollars,">="&(0.1*book_gco),pk_dollars,">0")/SUMIFS(pk_dollars,pk_kind,"grids",pk_measure,"gco_rate",pk_dollars,">0")),"")
B20: What a pocket is judged against | C20: The rest of its band | D20: n/a | E20: =IF(NOT($C$33="Where the book bleeds"),"",IF(AND($D$20<>"",$D$20<>"n/a"),$D$20,IF($C$20="","",IF(ISNA(IFERROR(MATCH($G$20&"|"&$C$20,_options!$A:$A,0),MATCH($G$20&"|"&IFERROR(VALUE($C$20),$C$20),_options!$H:$H,0))),"not an option","")))) | F20: The rest of its band | G20: compare_to | J20: =IF(AND($C$33="Where the book bleeds",$C20="",OR($D20="",$D20="n/a")),1,0) | M20: Charge-offs, every grid, against what each pocket is judged against.
M21: A profit shortfall is held to the same dollar line.
B22: ↻ Needs a Run · takes effect when you press Run again | G22: block|run
B23: Setting | C23: Your answer ↻ | D23: Or your own | F23: Last Run used | H23: Status | I23: Worked out from the loans
B24: Fewest loans in a pocket for the usual test (smaller ones get the exact test) | C24: Enough for 5 expected losses (suggested) | F24: 65 (worked out from this book) | G24: min_loans | H24: =IF(OR(NOT($C$33="Where the book bleeds"),AND($C$33="Where the book bleeds",$C24="",OR($D24="",$D24="n/a"))),"",IFERROR(IF(IF(AND($D$24<>"",$D$24<>"n/a"),$D$24,$C$24)&""=INDEX(_used!$B:$B,MATCH($G$24,_used!$A:$A,0))&"","Same as last Run","↻ Waiting for a Run"),"")) | I24: suggested: 65, from this extract at the last Run | J24: =IF(AND($C$33="Where the book bleeds",$C24="",OR($D24="",$D24="n/a")),1,0) | K24: =IF($H24="↻ Waiting for a Run",$B24&": "&INDEX(_used!$C:$C,MATCH($G$24,_used!$A:$A,0))&" → "&IF(AND($D$24<>"",$D$24<>"n/a"),$D$24,$C$24)&" (Control C24); ","")
B25: Fewest loans with a loss before a loss rate is tested | C25: 10 losses | F25: 10 losses | G25: min_events | H25: =IF(OR(NOT($C$33="Where the book bleeds"),AND($C$33="Where the book bleeds",$C25="",OR($D25="",$D25="n/a"))),"",IFERROR(IF(IF(AND($D$25<>"",$D$25<>"n/a"),$D$25,$C$25)&""=INDEX(_used!$B:$B,MATCH($G$25,_used!$A:$A,0))&"","Same as last Run","↻ Waiting for a Run"),"")) | J25: =IF(AND($C$33="Where the book bleeds",$C25="",OR($D25="",$D25="n/a")),1,0) | K25: =IF($H25="↻ Waiting for a Run",$B25&": "&INDEX(_used!$C:$C,MATCH($G$25,_used!$A:$A,0))&" → "&IF(AND($D$25<>"",$D$25<>"n/a"),$D$25,$C$25)&" (Control C25); ","")
B26: How many bands a number column is cut into | C26: 5 bands (recommended) | F26: 5 bands | G26: band_count | H26: =IF(OR(NOT(TRUE),AND(TRUE,$C26="",OR($D26="",$D26="n/a"))),"",IFERROR(IF(IF(AND($D$26<>"",$D$26<>"n/a"),$D$26,$C$26)&""=INDEX(_used!$B:$B,MATCH($G$26,_used!$A:$A,0))&"","Same as last Run","↻ Waiting for a Run"),"")) | J26: =IF(AND(TRUE,$C26="",OR($D26="",$D26="n/a")),1,0) | K26: =IF($H26="↻ Waiting for a Run",$B26&": "&INDEX(_used!$C:$C,MATCH($G$26,_used!$A:$A,0))&" → "&IF(AND($D$26<>"",$D$26<>"n/a"),$D$26,$C$26)&" (Control C26); ","")
B27: Where the band edges fall | C27: Each band holds about the same number of loans (recommended) | D27: n/a | F27: Each band holds about the same number of loans | G27: band_cut | H27: =IF(OR(NOT(TRUE),AND(TRUE,$C27="",OR($D27="",$D27="n/a"))),"",IFERROR(IF(IF(AND($D$27<>"",$D$27<>"n/a"),$D$27,$C$27)&""=INDEX(_used!$B:$B,MATCH($G$27,_used!$A:$A,0))&"","Same as last Run","↻ Waiting for a Run"),"")) | J27: =IF(AND(TRUE,$C27="",OR($D27="",$D27="n/a")),1,0) | K27: =IF($H27="↻ Waiting for a Run",$B27&": "&INDEX(_used!$C:$C,MATCH($G$27,_used!$A:$A,0))&" → "&IF(AND($D$27<>"",$D$27<>"n/a"),$D$27,$C$27)&" (Control C27); ","")
B28: How often a real gap should be caught | C28: 80% of the time (recommended) | F28: 80% of the time | G28: power | H28: =IF(OR(NOT($C$33="Where the book bleeds"),AND($C$33="Where the book bleeds",$C28="",OR($D28="",$D28="n/a"))),"",IFERROR(IF(IF(AND($D$28<>"",$D$28<>"n/a"),$D$28,$C$28)&""=INDEX(_used!$B:$B,MATCH($G$28,_used!$A:$A,0))&"","Same as last Run","↻ Waiting for a Run"),"")) | J28: =IF(AND($C$33="Where the book bleeds",$C28="",OR($D28="",$D28="n/a")),1,0) | K28: =IF($H28="↻ Waiting for a Run",$B28&": "&INDEX(_used!$C:$C,MATCH($G$28,_used!$A:$A,0))&" → "&IF(AND($D$28<>"",$D$28<>"n/a"),$D$28,$C$28)&" (Control C28); ","")
B29: Allowing for testing many pockets at once | C29: Hold down the share of false finds (Benjamini-Hochberg) (recommended) | D29: n/a | F29: Hold down the share of false finds (Benjamini-Hochberg) | G29: many_tests | H29: =IF(OR(NOT(TRUE),AND(TRUE,$C29="",OR($D29="",$D29="n/a"))),"",IFERROR(IF(IF(AND($D$29<>"",$D$29<>"n/a"),$D$29,$C$29)&""=INDEX(_used!$B:$B,MATCH($G$29,_used!$A:$A,0))&"","Same as last Run","↻ Waiting for a Run"),"")) | J29: =IF(AND(TRUE,$C29="",OR($D29="",$D29="n/a")),1,0) | K29: =IF($H29="↻ Waiting for a Run",$B29&": "&INDEX(_used!$C:$C,MATCH($G$29,_used!$A:$A,0))&" → "&IF(AND($D$29<>"",$D$29<>"n/a"),$D$29,$C$29)&" (Control C29); ","")
B30: Loans made before this date find the candidates; the rest are held back | G30: cutoff | H30: =IF(OR(NOT(AND($C$33="Finding and testing a new variable",$C$34="Scout first")),AND(AND($C$33="Finding and testing a new variable",$C$34="Scout first"),$C30="",OR($D30="",$D30="n/a"))),"",IFERROR(IF(IF(AND($D$30<>"",$D$30<>"n/a"),$D$30,$C$30)&""=INDEX(_used!$B:$B,MATCH($G$30,_used!$A:$A,0))&"","Same as last Run","↻ Waiting for a Run"),"")) | I30: suggested: 2024-11-01 (5,641 loans before, 2,359 after) | J30: =IF(AND(AND($C$33="Finding and testing a new variable",$C$34="Scout first"),$C30="",OR($D30="",$D30="n/a")),1,0) | K30: =IF($H30="↻ Waiting for a Run",$B30&": "&INDEX(_used!$C:$C,MATCH($G$30,_used!$A:$A,0))&" → "&IF(AND($D$30<>"",$D$30<>"n/a"),$D$30,$C$30)&" (Control C30); ","")
B32: Chosen in the launcher · read-only here | D32: To change these, go back to Choose tests in the launcher and press Next. | G32: launcher|head
B33: What are you running? | C33: Where the book bleeds | G33: run_kind | H33: =IFERROR(IF(IF(AND($D$33<>"",$D$33<>"n/a"),$D$33,$C$33)&""=INDEX(_used!$B:$B,MATCH($G$33,_used!$A:$A,0))&"","Same as last Run","↻ Waiting for a Run"),"") | K33: =IF($H33="↻ Waiting for a Run",$B33&": "&IF(INDEX(_used!$B:$B,MATCH($G$33,_used!$A:$A,0))&""="","none",INDEX(_used!$B:$B,MATCH($G$33,_used!$A:$A,0)))&" → "&IF(IF(AND($D$33<>"",$D$33<>"n/a"),$D$33,$C$33)&""="","none",IF(AND($D$33<>"",$D$33<>"n/a"),$D$33,$C$33))&" (launcher); ","")
B34: Scout first, or test from a pre-spec already written? | G34: new_variable_step | H34: =IF($H$33="↻ Waiting for a Run","",IFERROR(IF(IF(AND($D$34<>"",$D$34<>"n/a"),$D$34,$C$34)&""=INDEX(_used!$B:$B,MATCH($G$34,_used!$A:$A,0))&"","Same as last Run","↻ Waiting for a Run"),"")) | K34: =IF($H34="↻ Waiting for a Run",$B34&": "&IF(INDEX(_used!$B:$B,MATCH($G$34,_used!$A:$A,0))&""="","none",INDEX(_used!$B:$B,MATCH($G$34,_used!$A:$A,0)))&" → "&IF(IF(AND($D$34<>"",$D$34<>"n/a"),$D$34,$C$34)&""="","none",IF(AND($D$34<>"",$D$34<>"n/a"),$D$34,$C$34))&" (launcher); ","")
B35: Cut into bands | C35: FICO, ORIG_BAL | G35: launcher|bands | H35: =IF($H$33="↻ Waiting for a Run","",IFERROR(IF(IF(AND($D$35<>"",$D$35<>"n/a"),$D$35,$C$35)&""=INDEX(_used!$B:$B,MATCH($G$35,_used!$A:$A,0))&"","Same as last Run","↻ Waiting for a Run"),"")) | K35: =IF($H35="↻ Waiting for a Run",$B35&": "&IF(INDEX(_used!$B:$B,MATCH($G$35,_used!$A:$A,0))&""="","none",INDEX(_used!$B:$B,MATCH($G$35,_used!$A:$A,0)))&" → "&IF(IF(AND($D$35<>"",$D$35<>"n/a"),$D$35,$C$35)&""="","none",IF(AND($D$35<>"",$D$35<>"n/a"),$D$35,$C$35))&" (launcher); ","")
B36: Segment by | C36: CHANNEL, ASSET_CLASS | G36: launcher|segments | H36: =IF($H$33="↻ Waiting for a Run","",IFERROR(IF(IF(AND($D$36<>"",$D$36<>"n/a"),$D$36,$C$36)&""=INDEX(_used!$B:$B,MATCH($G$36,_used!$A:$A,0))&"","Same as last Run","↻ Waiting for a Run"),"")) | K36: =IF($H36="↻ Waiting for a Run",$B36&": "&IF(INDEX(_used!$B:$B,MATCH($G$36,_used!$A:$A,0))&""="","none",INDEX(_used!$B:$B,MATCH($G$36,_used!$A:$A,0)))&" → "&IF(IF(AND($D$36<>"",$D$36<>"n/a"),$D$36,$C$36)&""="","none",IF(AND($D$36<>"",$D$36<>"n/a"),$D$36,$C$36))&" (launcher); ","")
B37: Split every pocket by | C37: REV_DEBT | G37: launcher|split | H37: =IF($H$33="↻ Waiting for a Run","",IFERROR(IF(IF(AND($D$37<>"",$D$37<>"n/a"),$D$37,$C$37)&""=INDEX(_used!$B:$B,MATCH($G$37,_used!$A:$A,0))&"","Same as last Run","↻ Waiting for a Run"),"")) | K37: =IF($H37="↻ Waiting for a Run",$B37&": "&IF(INDEX(_used!$B:$B,MATCH($G$37,_used!$A:$A,0))&""="","none",INDEX(_used!$B:$B,MATCH($G$37,_used!$A:$A,0)))&" → "&IF(IF(AND($D$37<>"",$D$37<>"n/a"),$D$37,$C$37)&""="","none",IF(AND($D$37<>"",$D$37<>"n/a"),$D$37,$C$37))&" (launcher); ","")
B38: Tested against | G38: launcher|outcome | H38: =IF($H$33="↻ Waiting for a Run","",IFERROR(IF(IF(AND($D$38<>"",$D$38<>"n/a"),$D$38,$C$38)&""=INDEX(_used!$B:$B,MATCH($G$38,_used!$A:$A,0))&"","Same as last Run","↻ Waiting for a Run"),"")) | K38: =IF($H38="↻ Waiting for a Run",$B38&": "&IF(INDEX(_used!$B:$B,MATCH($G$38,_used!$A:$A,0))&""="","none",INDEX(_used!$B:$B,MATCH($G$38,_used!$A:$A,0)))&" → "&IF(IF(AND($D$38<>"",$D$38<>"n/a"),$D$38,$C$38)&""="","none",IF(AND($D$38<>"",$D$38<>"n/a"),$D$38,$C$38))&" (launcher); ","")
B39: Inputs tested | G39: launcher|test | H39: =IF($H$33="↻ Waiting for a Run","",IFERROR(IF(IF(AND($D$39<>"",$D$39<>"n/a"),$D$39,$C$39)&""=INDEX(_used!$B:$B,MATCH($G$39,_used!$A:$A,0))&"","Same as last Run","↻ Waiting for a Run"),"")) | K39: =IF($H39="↻ Waiting for a Run",$B39&": "&IF(INDEX(_used!$B:$B,MATCH($G$39,_used!$A:$A,0))&""="","none",INDEX(_used!$B:$B,MATCH($G$39,_used!$A:$A,0)))&" → "&IF(IF(AND($D$39<>"",$D$39<>"n/a"),$D$39,$C$39)&""="","none",IF(AND($D$39<>"",$D$39<>"n/a"),$D$39,$C$39))&" (launcher); ","")
B40: Held fixed | G40: launcher|hold | H40: =IF($H$33="↻ Waiting for a Run","",IFERROR(IF(IF(AND($D$40<>"",$D$40<>"n/a"),$D$40,$C$40)&""=INDEX(_used!$B:$B,MATCH($G$40,_used!$A:$A,0))&"","Same as last Run","↻ Waiting for a Run"),"")) | K40: =IF($H40="↻ Waiting for a Run",$B40&": "&IF(INDEX(_used!$B:$B,MATCH($G$40,_used!$A:$A,0))&""="","none",INDEX(_used!$B:$B,MATCH($G$40,_used!$A:$A,0)))&" → "&IF(IF(AND($D$40<>"",$D$40<>"n/a"),$D$40,$C$40)&""="","none",IF(AND($D$40<>"",$D$40<>"n/a"),$D$40,$C$40))&" (launcher); ","")
B41: Saved shortlist (pre-spec file) | G41: prespec | H41: =IF($H$33="↻ Waiting for a Run","",IFERROR(IF(IF(AND($D$41<>"",$D$41<>"n/a"),$D$41,$C$41)&""=INDEX(_used!$B:$B,MATCH($G$41,_used!$A:$A,0))&"","Same as last Run","↻ Waiting for a Run"),"")) | K41: =IF($H41="↻ Waiting for a Run",$B41&": "&IF(INDEX(_used!$B:$B,MATCH($G$41,_used!$A:$A,0))&""="","none",INDEX(_used!$B:$B,MATCH($G$41,_used!$A:$A,0)))&" → "&IF(IF(AND($D$41<>"",$D$41<>"n/a"),$D$41,$C$41)&""="","none",IF(AND($D$41<>"",$D$41<>"n/a"),$D$41,$C$41))&" (launcher); ","")
B42: Number columns: this many values or fewer is a category; more is cut into bands | C42: 12 values | G42: few_values | H42: =IF($H$33="↻ Waiting for a Run","",IFERROR(IF(IF(AND($D$42<>"",$D$42<>"n/a"),$D$42,$C$42)&""=INDEX(_used!$B:$B,MATCH($G$42,_used!$A:$A,0))&"","Same as last Run","↻ Waiting for a Run"),"")) | K42: =IF($H42="↻ Waiting for a Run",$B42&": "&IF(INDEX(_used!$B:$B,MATCH($G$42,_used!$A:$A,0))&""="","none",INDEX(_used!$B:$B,MATCH($G$42,_used!$A:$A,0)))&" → "&IF(IF(AND($D$42<>"",$D$42<>"n/a"),$D$42,$C$42)&""="","none",IF(AND($D$42<>"",$D$42<>"n/a"),$D$42,$C$42))&" (launcher); ","")
B43: Text columns: more values than this is too many to cut by (text is never cut into bands) | C43: 50 values | G43: many_values | H43: =IF($H$33="↻ Waiting for a Run","",IFERROR(IF(IF(AND($D$43<>"",$D$43<>"n/a"),$D$43,$C$43)&""=INDEX(_used!$B:$B,MATCH($G$43,_used!$A:$A,0))&"","Same as last Run","↻ Waiting for a Run"),"")) | K43: =IF($H43="↻ Waiting for a Run",$B43&": "&IF(INDEX(_used!$B:$B,MATCH($G$43,_used!$A:$A,0))&""="","none",INDEX(_used!$B:$B,MATCH($G$43,_used!$A:$A,0)))&" → "&IF(IF(AND($D$43<>"",$D$43<>"n/a"),$D$43,$C$43)&""="","none",IF(AND($D$43<>"",$D$43<>"n/a"),$D$43,$C$43))&" (launcher); ","")

Sheet Columns
B1: Columns | C1: What each column means, what looks odd in it, and what PocketBook remembers about it.
B3: Checked every column? | C3: Yes | D3: Run won't start until this is Yes.
B5: How this tab works
B6: What it is | C6: Set up guesses each column's meaning from its name and values; the reason is beside it. Fix any that's wrong. Confirmed meanings are remembered for the next extract.
B7: Odd values | C7: Values that may be codes rather than real numbers: one value far more often than any other, or negatives in a column that's mostly positive. Missing is treated as blank and counted.
B8: Treat as | C8: Answer Real or Missing. One left blank is used as recorded.
B9: Band edges | C9: Blank means Control's setting. Type edges as 620; 680; 740, or every 20. Look shows what each would cut, live.
B10: Remembered | C10: Set Forget? to Yes to drop what was learned about a column at the next Run. It then waits here for you to confirm it again. Answers marked ↻ take effect at the next Run.
B12: Column | C12: Samples | D12: What it is ↻ | E12: Why we think so | F12: Blank | G12: Odd values | H12: Treat as ↻ | I12: Band edges ↻ | J12: Remembered | K12: Forget? ↻ | L12: Check first | M12: Yes means ↻ | N12: Show per pocket ↻ | O12: Period ↻ | P12: In your words
B13: LOAN_NBR | C13: L0000000, L0000001, L0000002 | D13: Loan number (key) | E13: name contains 'loan'; a different value on every row | F13: 0 | J13: Yes · 1 Run | K13: No | Q13: key
B14: FICO | C14: -9999, 713, 716 | D14: FICO score | E14: name contains 'fico'; 98% of values between 300 and 850 | F14: 0.000125 | G14: -9999 on 160 loans | H14: Missing | J14: Yes · 1 Run | K14: No | Q14: fico | S14: FICO|repeated_value|-9999.0
B15: CHANNEL | C15: Online, Broker, Branch | D15: Category | E15: 3 different values | F15: 0 | J15: Yes · 1 Run | K15: No | L15: suggested as Category from its shape alone (3 different values). If it's something more specific, say so and it will be remembered. | Q15: category
B16: ORIG_BAL | C16: 7655.75, 27999.47, 39684.43 | D16: Booked amount | E16: name contains 'bal'; positive on every loan | F16: 0.000125 | J16: Yes · 1 Run | K16: No | Q16: booked
B17: BAD_FLAG | C17: 0, 2, 1 | D17: Outcome (yes/no) | E17: picked and confirmed in the launcher as the outcome | F17: 0 | J17: Yes · 1 Run | K17: No | L17: 1 value is neither 0 nor 1. They're left out of the outcome rates and counted; if they mean something, fix the extract. | Q17: outcome
B18: GCO_AMT | C18: 0.0, #N/A, 27620.62 | D18: GCO dollars | E18: name contains 'gco'; zero on 92% of loans, never negative | F18: 0 | J18: Yes · 1 Run | K18: No | L18: 1 value isn't a number among 7,999 that are. They're left out of any rate using this column and counted. | Q18: gco
B19: RANR_AMT | C19: 3017.35, 3928.24, 5816.98 | D19: RANR dollars | E19: name contains 'ranr'; numbers | F19: 0 | G19: Negative on 595 loans | H19: Real | J19: Yes · 1 Run | K19: No | Q19: ranr | S19: RANR_AMT|negatives|
B20: ASSET_CLASS | C20: 1, 2, 4 | D20: Category | E20: 4 different values | F20: 0 | J20: Yes · 1 Run | K20: No | L20: suggested as Category from its shape alone (4 different values). If it's something more specific, say so and it will be remembered. | Q20: category
B21: REV_DEBT | C21: 15868.86, 12884.7, 8920.97 | D21: Amount or number | E21: numbers with 7,889 values | F21: 0 | J21: Yes · 1 Run | K21: No | L21: suggested as Amount or number from its shape alone (numbers with 7,889 values). If it's something more specific, say so and it will be remembered. | Q21: amount
B22: ORIG_DATE | C22: 2021-11-18, 2024-06-24, 2023-07-12 | D22: Origination date | E22: name contains 'orig'; dates | F22: 0 | J22: Yes · 1 Run | K22: No | Q22: origination_date
S23: table|end
B25: Add a column: one divided by another | S25: derived|head
B26: Shows here and on Look, and in Choose tests, once you press Set up again. Blank where the bottom is zero or blank. | S26: derived|note
B27: New column name ↻ | C27: Top (divided) | D27: Bottom (divided by) | E27: What it makes | S27: derived|cols
E28: =IF(COUNTA(B28:D28)=0,"",IF(COUNTA(B28:D28)<3,"Needs a name, a top and a bottom.",B28&" = "&C28&" ÷ "&D28&" on each loan.")) | S28: derived|1
E29: =IF(COUNTA(B29:D29)=0,"",IF(COUNTA(B29:D29)<3,"Needs a name, a top and a bottom.",B29&" = "&C29&" ÷ "&D29&" on each loan.")) | S29: derived|2
E30: =IF(COUNTA(B30:D30)=0,"",IF(COUNTA(B30:D30)<3,"Needs a name, a top and a bottom.",B30&" = "&C30&" ÷ "&D30&" on each loan.")) | S30: derived|3

Sheet Look
B1: Look | C1: Each number column before you choose its band edges.
B3: How this tab works
B4: The bars | C4: How many loans fall in each step between From and To. Pick 10, 20 or 50 bars and change the range; the chart follows. The grey bar at each end holds the loans outside the range.
B5: The red bar | C5: A value that looks like a code, such as a score of -9999, gets a red bar of its own left of the chart, so it doesn't flatten the rest. Columns asks whether it means missing.
B6: Red dashed lines | C6: The band edges typed on Columns. They follow that tab as you type, so you can try edges here before the next Run. Blank edges are cut at the Run, so no lines show.
B7: How it counts | C7: Set up counts each column once, in 200 equal slices around its 1st to 99th percentile. A range you type is counted to the nearest slice.
B8: The dots | C8: The split column against each band column: a random 2,000 loans, the same every time. If the dots slope, the two move together, and part of a gap on Split may belong to the band column.
B10: FICO | H10: =IF('_look'!$F$20="","FICO · no edges on Columns yet","FICO · edges now "&'_look'!$F$20)
B11: Loans | C11: 8000
B12: Blank | C12: 1 | D12: 0.000125
B13: Not a number | C13: 0 | D13: 0
B14: Likely a code | C14: none found
B15: Smallest | C15: 496
B16: Median | C16: 699
B17: Mean | C17: 699.75099
B18: Largest | C18: 921
B19: Answered missing, left out | C19: 160 | D19: 0.02
B20: Bars | C20: 20
B21: From | C21: 550
B22: To | C22: 850
B29: ORIG_BAL | H29: =IF('_look'!$S$20="","ORIG_BAL · no edges on Columns yet","ORIG_BAL · edges now "&'_look'!$S$20)
B30: Loans | C30: 8000
B31: Blank | C31: 1 | D31: 0.000125
B32: Not a number | C32: 0 | D32: 0
B33: Likely a code | C33: none found
B34: Smallest | C34: 5005.32
B35: Median | C35: 32112.83
B36: Mean | C36: 32262.589
B37: Largest | C37: 59983.86
B39: Bars | C39: 20
B40: From | C40: 0
B41: To | C41: 60000
B48: REV_DEBT | H48: =IF('_look'!$AF$20="","REV_DEBT · no edges on Columns yet","REV_DEBT · edges now "&'_look'!$AF$20)
B49: Loans | C49: 8000
B50: Blank | C50: 0 | D50: 0
B51: Not a number | C51: 0 | D51: 0
B52: Likely a code | C52: none found
B53: Smallest | C53: 0
B54: Median | C54: 11392.84
B55: Mean | C55: 12064.483
B56: Largest | C56: 48521.79
B58: Bars | C58: 20
B59: From | C59: 0
B60: To | C60: 30000
B67: REV_DEBT against FICO
B68: Loans with both values | C68: 7839
B69: Dots shown | C69: 2000
B70: Moves together (correlation) | C70: -0.53
B71: A random sample of 2,000: the same loans every time.
B86: REV_DEBT against ORIG_BAL
B87: Loans with both values | C87: 7999
B88: Dots shown | C88: 2000
B89: Moves together (correlation) | C89: -0.02
B90: A random sample of 2,000: the same loans every time.

Sheet Pockets
C1: Pockets | D1: Which pockets lose more than their share, how much, and whether it's real and big enough to matter.
C3: How this tab works
C4: A pocket | D4: One band of one column crossed with one segment of another, in every grid chosen in the launcher. Loans: how many are in it. Split by REV_DEBT: each pocket halved at its own median REV_DEBT, each half tested like any other pocket.
C5: Rest of band | D5: ="Every other loan in the same band. Judged against on Control picks it or the rest of the book (every other loan in the book); now "&IF(judged_band,"the rest of its band","the rest of the book")&". It decides the gap, the excess and both verdicts. A pocket alone in its band has nothing beside it to compare with, so it is judged against the rest of the book, whatever Control says."
C6: Excess | D6: What the pocket lost above what it would have lost at the rest's rate: bad loans for Bad loans, dollars for the dollar measures. For Kept after losses and Earned before losses, the dollars it fell short of the rest, and the gap is in points of booked dollars.
C7: Worse? | D7: ="Yes: at least "&TEXT(worse_at,"0.00")&"x the rest"&" (for profit, short of it by the profit line on Control)"&", with a p-value under "&TEXT(significance_bar,"0%")&". Not sure: the gap is there, but the p-value isn't under it. Too few losses: fewer than "&"10 (a setting for the next Run), so not tested. No: anything else."
C8: p-value | D8: ="The chance of a gap at least this big if the pocket were no different from the rest, after the allowance for testing many pockets at once (Benjamini-Hochberg, across one grid and one measure). Bad loans: the z test, or the exact test for a pocket und"&"er 65 loans. Dollar measures: the loans are shuffled 10,000 times, within the band for the rest of its band, and it is how often a gap as big turned up."&" Under "&TEXT(significance_bar,"0%")&" counts."
C9: Material? | D9: Yes when the excess reaches the materiality line on Control (the Material at tile, in the measure's own unit). It is judged apart from Worse?: a pocket can be one without the other.
C10: Could have caught | D10: The smallest gap a pocket this size would catch 80% of the time at the last Run's confidence. As of the last Run.
C11: Order | D11: Sorted as of the last Run: worse pockets first, largest excess first, then the rest by their excess. Last come pockets losing more only against the other comparison, so that changing Judged against on Control finds them here. A change on Control updates Worse?, Material?, the dollars and the colours at once, not the order. The caption counts what the dropdowns pick.
C12: Holds FICO fixed? | D12: Split only. REV_DEBT moves with FICO (correlation -0.53), so a split pocket in a grid that doesn't hold FICO fixed may be showing FICO, not REV_DEBT. Those rows come last, in grey, with no verdict colour.
C14: LINES IN USE NOW | D14: Worse at | E14: Better at | F14: How sure | H14: Material at | J14: Judged against | K14: Order and "Could have caught" are from the last Run, 2026-09-29 21:04.
C15: live from Control | D15: =worse_at | E15: =better_at | F15: =confidence | H15: =IFERROR(IF(materiality_kind="none","No floor",IF(INDEX(line_values,MATCH($U$18,line_keys,0))="","No line",IF($U$20,TEXT(INDEX(line_values,MATCH($U$18,line_keys,0)),"#,##0.0")&" bad loans","$"&TEXT(INDEX(line_values,MATCH($U$18,line_keys,0)),"#,##0")))),"") | J15: =IF(judged_band,"Rest of its band","Rest of the book") | K15: =IFERROR(IF(COUNTIF(Status,"↻ Waiting for a Run")=0,"","↻ "&COUNTIF(Status,"↻ Waiting for a Run")&IF(COUNTIF(Status,"↻ Waiting for a Run")=1," Control change waits for a Run."," Control changes wait for a Run.")),"")
C17: MEASURE | D17: POCKETS | E17: SHOW
C18: Bad loans | D18: Two-way | E18: All | F18: =IFERROR(COUNTIFS('_list'!$A$2:$A$652,'Pockets'!$D$18,'_list'!$B$2:$B$652,'Pockets'!$C$18,'_list'!$K$2:$K$652,"Yes",'_list'!$L$2:$L$652,"Yes")&" worse and material · "&COUNTIFS('_list'!$A$2:$A$652,'Pockets'!$D$18,'_list'!$B$2:$B$652,'Pockets'!$C$18,'_list'!$K$2:$K$652,"Yes")&" worse · "&SUM('_list'!$M$2:$M$652)&" shown","") | U18: =IFERROR(INDEX('_choices'!$B$2:$B$6,MATCH('Pockets'!$C$18,'_choices'!$A$2:$A$6,0)),"")
U19: =IFERROR(INDEX('_choices'!$C$2:$C$6,MATCH('Pockets'!$C$18,'_choices'!$A$2:$A$6,0))=1,FALSE)
B20: # | C20: Band | D20: Segment | E20: =IF('Pockets'!$D$18="Two-way","","REV_DEBT half") | F20: Loans | G20: This pocket | H20: =IF(judged_band,"Rest of band","Rest of book") | I20: =IF($U$19,"Gap in pts",IF(judged_band,"× rest of band","× rest of book")) | J20: =IF($U$20,"Bad loans above share",IF($U$19,IF(judged_band,"Dollars short of band","Dollars short of book"),"Dollars above share")) | K20: Worse? | L20: p-value | M20: Material? | N20: Could have caught | O20: =IF('Pockets'!$D$18="Two-way","","Holds FICO fixed?") | U20: =IFERROR(INDEX('_choices'!$D$2:$D$6,MATCH('Pockets'!$C$18,'_choices'!$A$2:$A$6,0))=1,FALSE)
B21: =IF($R21="","",1) | C21: =IF($R21="","",IF(INDEX('_list'!$D$2:$D$652,$R21)="","",INDEX('_list'!$D$2:$D$652,$R21))) | D21: =IF($R21="","",IF(INDEX('_list'!$E$2:$E$652,$R21)="","",INDEX('_list'!$E$2:$E$652,$R21))) | E21: =IF($R21="","",IF(INDEX('_list'!$F$2:$F$652,$R21)="","",INDEX('_list'!$F$2:$F$652,$R21))) | F21: =IF($R21="","",IF(INDEX('_list'!$G$2:$G$652,$R21)="","",INDEX('_list'!$G$2:$G$652,$R21))) | G21: =IF($S21="","",IF(INDEX('_pockets'!$AH:$AH,$S21)="","",INDEX('_pockets'!$AH:$AH,$S21))) | H21: =IF($S21="","",IF(INDEX('_pockets'!$AF:$AF,$S21)="","",INDEX('_pockets'!$AF:$AF,$S21))) | I21: =IF(IF($S21="","",IF(INDEX('_pockets'!$AB:$AB,$S21)="","",INDEX('_pockets'!$AB:$AB,$S21)))="","",IF($S21="","",IF(INDEX('_pockets'!$AB:$AB,$S21)="","",INDEX('_pockets'!$AB:$AB,$S21)))*IF($U$19,100,1)) | J21: =IF($S21="","",IF(INDEX('_pockets'!$Z:$Z,$S21)="","",INDEX('_pockets'!$Z:$Z,$S21))) | K21: =IF($R21="","",IF(INDEX('_list'!$K$2:$K$652,$R21)="","",INDEX('_list'!$K$2:$K$652,$R21))) | L21: =IF($S21="","",IF(INDEX('_pockets'!$AC:$AC,$S21)="","",INDEX('_pockets'!$AC:$AC,$S21))) | M21: =IF($R21="","",IF(INDEX('_list'!$L$2:$L$652,$R21)="","",INDEX('_list'!$L$2:$L$652,$R21))) | N21: =IF($R21="","",IF(INDEX('_list'!$H$2:$H$652,$R21)="","",INDEX('_list'!$H$2:$H$652,$R21))) | O21: =IF($R21="","",IF(INDEX('_list'!$I$2:$I$652,$R21)="","",INDEX('_list'!$I$2:$I$652,$R21))) | R21: =IFERROR(MATCH(1,'_list'!$N$2:$N$652,0),"") | S21: =IF($R21="","",INDEX('_list'!$C$2:$C$652,$R21))
B22: =IF($R22="","",2) | C22: =IF($R22="","",IF(INDEX('_list'!$D$2:$D$652,$R22)="","",INDEX('_list'!$D$2:$D$652,$R22))) | D22: =IF($R22="","",IF(INDEX('_list'!$E$2:$E$652,$R22)="","",INDEX('_list'!$E$2:$E$652,$R22))) | E22: =IF($R22="","",IF(INDEX('_list'!$F$2:$F$652,$R22)="","",INDEX('_list'!$F$2:$F$652,$R22))) | F22: =IF($R22="","",IF(INDEX('_list'!$G$2:$G$652,$R22)="","",INDEX('_list'!$G$2:$G$652,$R22))) | G22: =IF($S22="","",IF(INDEX('_pockets'!$AH:$AH,$S22)="","",INDEX('_pockets'!$AH:$AH,$S22))) | H22: =IF($S22="","",IF(INDEX('_pockets'!$AF:$AF,$S22)="","",INDEX('_pockets'!$AF:$AF,$S22))) | I22: =IF(IF($S22="","",IF(INDEX('_pockets'!$AB:$AB,$S22)="","",INDEX('_pockets'!$AB:$AB,$S22)))="","",IF($S22="","",IF(INDEX('_pockets'!$AB:$AB,$S22)="","",INDEX('_pockets'!$AB:$AB,$S22)))*IF($U$19,100,1)) | J22: =IF($S22="","",IF(INDEX('_pockets'!$Z:$Z,$S22)="","",INDEX('_pockets'!$Z:$Z,$S22))) | K22: =IF($R22="","",IF(INDEX('_list'!$K$2:$K$652,$R22)="","",INDEX('_list'!$K$2:$K$652,$R22))) | L22: =IF($S22="","",IF(INDEX('_pockets'!$AC:$AC,$S22)="","",INDEX('_pockets'!$AC:$AC,$S22))) | M22: =IF($R22="","",IF(INDEX('_list'!$L$2:$L$652,$R22)="","",INDEX('_list'!$L$2:$L$652,$R22))) | N22: =IF($R22="","",IF(INDEX('_list'!$H$2:$H$652,$R22)="","",INDEX('_list'!$H$2:$H$652,$R22))) | O22: =IF($R22="","",IF(INDEX('_list'!$I$2:$I$652,$R22)="","",INDEX('_list'!$I$2:$I$652,$R22))) | R22: =IFERROR(MATCH(2,'_list'!$N$2:$N$652,0),"") | S22: =IF($R22="","",INDEX('_list'!$C$2:$C$652,$R22))
B23: =IF($R23="","",3) | C23: =IF($R23="","",IF(INDEX('_list'!$D$2:$D$652,$R23)="","",INDEX('_list'!$D$2:$D$652,$R23))) | D23: =IF($R23="","",IF(INDEX('_list'!$E$2:$E$652,$R23)="","",INDEX('_list'!$E$2:$E$652,$R23))) | E23: =IF($R23="","",IF(INDEX('_list'!$F$2:$F$652,$R23)="","",INDEX('_list'!$F$2:$F$652,$R23))) | F23: =IF($R23="","",IF(INDEX('_list'!$G$2:$G$652,$R23)="","",INDEX('_list'!$G$2:$G$652,$R23))) | G23: =IF($S23="","",IF(INDEX('_pockets'!$AH:$AH,$S23)="","",INDEX('_pockets'!$AH:$AH,$S23))) | H23: =IF($S23="","",IF(INDEX('_pockets'!$AF:$AF,$S23)="","",INDEX('_pockets'!$AF:$AF,$S23))) | I23: =IF(IF($S23="","",IF(INDEX('_pockets'!$AB:$AB,$S23)="","",INDEX('_pockets'!$AB:$AB,$S23)))="","",IF($S23="","",IF(INDEX('_pockets'!$AB:$AB,$S23)="","",INDEX('_pockets'!$AB:$AB,$S23)))*IF($U$19,100,1)) | J23: =IF($S23="","",IF(INDEX('_pockets'!$Z:$Z,$S23)="","",INDEX('_pockets'!$Z:$Z,$S23))) | K23: =IF($R23="","",IF(INDEX('_list'!$K$2:$K$652,$R23)="","",INDEX('_list'!$K$2:$K$652,$R23))) | L23: =IF($S23="","",IF(INDEX('_pockets'!$AC:$AC,$S23)="","",INDEX('_pockets'!$AC:$AC,$S23))) | M23: =IF($R23="","",IF(INDEX('_list'!$L$2:$L$652,$R23)="","",INDEX('_list'!$L$2:$L$652,$R23))) | N23: =IF($R23="","",IF(INDEX('_list'!$H$2:$H$652,$R23)="","",INDEX('_list'!$H$2:$H$652,$R23))) | O23: =IF($R23="","",IF(INDEX('_list'!$I$2:$I$652,$R23)="","",INDEX('_list'!$I$2:$I$652,$R23))) | R23: =IFERROR(MATCH(3,'_list'!$N$2:$N$652,0),"") | S23: =IF($R23="","",INDEX('_list'!$C$2:$C$652,$R23))
B24: =IF($R24="","",4) | C24: =IF($R24="","",IF(INDEX('_list'!$D$2:$D$652,$R24)="","",INDEX('_list'!$D$2:$D$652,$R24))) | D24: =IF($R24="","",IF(INDEX('_list'!$E$2:$E$652,$R24)="","",INDEX('_list'!$E$2:$E$652,$R24))) | E24: =IF($R24="","",IF(INDEX('_list'!$F$2:$F$652,$R24)="","",INDEX('_list'!$F$2:$F$652,$R24))) | F24: =IF($R24="","",IF(INDEX('_list'!$G$2:$G$652,$R24)="","",INDEX('_list'!$G$2:$G$652,$R24))) | G24: =IF($S24="","",IF(INDEX('_pockets'!$AH:$AH,$S24)="","",INDEX('_pockets'!$AH:$AH,$S24))) | H24: =IF($S24="","",IF(INDEX('_pockets'!$AF:$AF,$S24)="","",INDEX('_pockets'!$AF:$AF,$S24))) | I24: =IF(IF($S24="","",IF(INDEX('_pockets'!$AB:$AB,$S24)="","",INDEX('_pockets'!$AB:$AB,$S24)))="","",IF($S24="","",IF(INDEX('_pockets'!$AB:$AB,$S24)="","",INDEX('_pockets'!$AB:$AB,$S24)))*IF($U$19,100,1)) | J24: =IF($S24="","",IF(INDEX('_pockets'!$Z:$Z,$S24)="","",INDEX('_pockets'!$Z:$Z,$S24))) | K24: =IF($R24="","",IF(INDEX('_list'!$K$2:$K$652,$R24)="","",INDEX('_list'!$K$2:$K$652,$R24))) | L24: =IF($S24="","",IF(INDEX('_pockets'!$AC:$AC,$S24)="","",INDEX('_pockets'!$AC:$AC,$S24))) | M24: =IF($R24="","",IF(INDEX('_list'!$L$2:$L$652,$R24)="","",INDEX('_list'!$L$2:$L$652,$R24))) | N24: =IF($R24="","",IF(INDEX('_list'!$H$2:$H$652,$R24)="","",INDEX('_list'!$H$2:$H$652,$R24))) | O24: =IF($R24="","",IF(INDEX('_list'!$I$2:$I$652,$R24)="","",INDEX('_list'!$I$2:$I$652,$R24))) | R24: =IFERROR(MATCH(4,'_list'!$N$2:$N$652,0),"") | S24: =IF($R24="","",INDEX('_list'!$C$2:$C$652,$R24))
B25: =IF($R25="","",5) | C25: =IF($R25="","",IF(INDEX('_list'!$D$2:$D$652,$R25)="","",INDEX('_list'!$D$2:$D$652,$R25))) | D25: =IF($R25="","",IF(INDEX('_list'!$E$2:$E$652,$R25)="","",INDEX('_list'!$E$2:$E$652,$R25))) | E25: =IF($R25="","",IF(INDEX('_list'!$F$2:$F$652,$R25)="","",INDEX('_list'!$F$2:$F$652,$R25))) | F25: =IF($R25="","",IF(INDEX('_list'!$G$2:$G$652,$R25)="","",INDEX('_list'!$G$2:$G$652,$R25))) | G25: =IF($S25="","",IF(INDEX('_pockets'!$AH:$AH,$S25)="","",INDEX('_pockets'!$AH:$AH,$S25))) | H25: =IF($S25="","",IF(INDEX('_pockets'!$AF:$AF,$S25)="","",INDEX('_pockets'!$AF:$AF,$S25))) | I25: =IF(IF($S25="","",IF(INDEX('_pockets'!$AB:$AB,$S25)="","",INDEX('_pockets'!$AB:$AB,$S25)))="","",IF($S25="","",IF(INDEX('_pockets'!$AB:$AB,$S25)="","",INDEX('_pockets'!$AB:$AB,$S25)))*IF($U$19,100,1)) | J25: =IF($S25="","",IF(INDEX('_pockets'!$Z:$Z,$S25)="","",INDEX('_pockets'!$Z:$Z,$S25))) | K25: =IF($R25="","",IF(INDEX('_list'!$K$2:$K$652,$R25)="","",INDEX('_list'!$K$2:$K$652,$R25))) | L25: =IF($S25="","",IF(INDEX('_pockets'!$AC:$AC,$S25)="","",INDEX('_pockets'!$AC:$AC,$S25))) | M25: =IF($R25="","",IF(INDEX('_list'!$L$2:$L$652,$R25)="","",INDEX('_list'!$L$2:$L$652,$R25))) | N25: =IF($R25="","",IF(INDEX('_list'!$H$2:$H$652,$R25)="","",INDEX('_list'!$H$2:$H$652,$R25))) | O25: =IF($R25="","",IF(INDEX('_list'!$I$2:$I$652,$R25)="","",INDEX('_list'!$I$2:$I$652,$R25))) | R25: =IFERROR(MATCH(5,'_list'!$N$2:$N$652,0),"") | S25: =IF($R25="","",INDEX('_list'!$C$2:$C$652,$R25))
B26: =IF($R26="","",6) | C26: =IF($R26="","",IF(INDEX('_list'!$D$2:$D$652,$R26)="","",INDEX('_list'!$D$2:$D$652,$R26))) | D26: =IF($R26="","",IF(INDEX('_list'!$E$2:$E$652,$R26)="","",INDEX('_list'!$E$2:$E$652,$R26))) | E26: =IF($R26="","",IF(INDEX('_list'!$F$2:$F$652,$R26)="","",INDEX('_list'!$F$2:$F$652,$R26))) | F26: =IF($R26="","",IF(INDEX('_list'!$G$2:$G$652,$R26)="","",INDEX('_list'!$G$2:$G$652,$R26))) | G26: =IF($S26="","",IF(INDEX('_pockets'!$AH:$AH,$S26)="","",INDEX('_pockets'!$AH:$AH,$S26))) | H26: =IF($S26="","",IF(INDEX('_pockets'!$AF:$AF,$S26)="","",INDEX('_pockets'!$AF:$AF,$S26))) | I26: =IF(IF($S26="","",IF(INDEX('_pockets'!$AB:$AB,$S26)="","",INDEX('_pockets'!$AB:$AB,$S26)))="","",IF($S26="","",IF(INDEX('_pockets'!$AB:$AB,$S26)="","",INDEX('_pockets'!$AB:$AB,$S26)))*IF($U$19,100,1)) | J26: =IF($S26="","",IF(INDEX('_pockets'!$Z:$Z,$S26)="","",INDEX('_pockets'!$Z:$Z,$S26))) | K26: =IF($R26="","",IF(INDEX('_list'!$K$2:$K$652,$R26)="","",INDEX('_list'!$K$2:$K$652,$R26))) | L26: =IF($S26="","",IF(INDEX('_pockets'!$AC:$AC,$S26)="","",INDEX('_pockets'!$AC:$AC,$S26))) | M26: =IF($R26="","",IF(INDEX('_list'!$L$2:$L$652,$R26)="","",INDEX('_list'!$L$2:$L$652,$R26))) | N26: =IF($R26="","",IF(INDEX('_list'!$H$2:$H$652,$R26)="","",INDEX('_list'!$H$2:$H$652,$R26))) | O26: =IF($R26="","",IF(INDEX('_list'!$I$2:$I$652,$R26)="","",INDEX('_list'!$I$2:$I$652,$R26))) | R26: =IFERROR(MATCH(6,'_list'!$N$2:$N$652,0),"") | S26: =IF($R26="","",INDEX('_list'!$C$2:$C$652,$R26))
B27: =IF($R27="","",7) | C27: =IF($R27="","",IF(INDEX('_list'!$D$2:$D$652,$R27)="","",INDEX('_list'!$D$2:$D$652,$R27))) | D27: =IF($R27="","",IF(INDEX('_list'!$E$2:$E$652,$R27)="","",INDEX('_list'!$E$2:$E$652,$R27))) | E27: =IF($R27="","",IF(INDEX('_list'!$F$2:$F$652,$R27)="","",INDEX('_list'!$F$2:$F$652,$R27))) | F27: =IF($R27="","",IF(INDEX('_list'!$G$2:$G$652,$R27)="","",INDEX('_list'!$G$2:$G$652,$R27))) | G27: =IF($S27="","",IF(INDEX('_pockets'!$AH:$AH,$S27)="","",INDEX('_pockets'!$AH:$AH,$S27))) | H27: =IF($S27="","",IF(INDEX('_pockets'!$AF:$AF,$S27)="","",INDEX('_pockets'!$AF:$AF,$S27))) | I27: =IF(IF($S27="","",IF(INDEX('_pockets'!$AB:$AB,$S27)="","",INDEX('_pockets'!$AB:$AB,$S27)))="","",IF($S27="","",IF(INDEX('_pockets'!$AB:$AB,$S27)="","",INDEX('_pockets'!$AB:$AB,$S27)))*IF($U$19,100,1)) | J27: =IF($S27="","",IF(INDEX('_pockets'!$Z:$Z,$S27)="","",INDEX('_pockets'!$Z:$Z,$S27))) | K27: =IF($R27="","",IF(INDEX('_list'!$K$2:$K$652,$R27)="","",INDEX('_list'!$K$2:$K$652,$R27))) | L27: =IF($S27="","",IF(INDEX('_pockets'!$AC:$AC,$S27)="","",INDEX('_pockets'!$AC:$AC,$S27))) | M27: =IF($R27="","",IF(INDEX('_list'!$L$2:$L$652,$R27)="","",INDEX('_list'!$L$2:$L$652,$R27))) | N27: =IF($R27="","",IF(INDEX('_list'!$H$2:$H$652,$R27)="","",INDEX('_list'!$H$2:$H$652,$R27))) | O27: =IF($R27="","",IF(INDEX('_list'!$I$2:$I$652,$R27)="","",INDEX('_list'!$I$2:$I$652,$R27))) | R27: =IFERROR(MATCH(7,'_list'!$N$2:$N$652,0),"") | S27: =IF($R27="","",INDEX('_list'!$C$2:$C$652,$R27))
B28: =IF($R28="","",8) | C28: =IF($R28="","",IF(INDEX('_list'!$D$2:$D$652,$R28)="","",INDEX('_list'!$D$2:$D$652,$R28))) | D28: =IF($R28="","",IF(INDEX('_list'!$E$2:$E$652,$R28)="","",INDEX('_list'!$E$2:$E$652,$R28))) | E28: =IF($R28="","",IF(INDEX('_list'!$F$2:$F$652,$R28)="","",INDEX('_list'!$F$2:$F$652,$R28))) | F28: =IF($R28="","",IF(INDEX('_list'!$G$2:$G$652,$R28)="","",INDEX('_list'!$G$2:$G$652,$R28))) | G28: =IF($S28="","",IF(INDEX('_pockets'!$AH:$AH,$S28)="","",INDEX('_pockets'!$AH:$AH,$S28))) | H28: =IF($S28="","",IF(INDEX('_pockets'!$AF:$AF,$S28)="","",INDEX('_pockets'!$AF:$AF,$S28))) | I28: =IF(IF($S28="","",IF(INDEX('_pockets'!$AB:$AB,$S28)="","",INDEX('_pockets'!$AB:$AB,$S28)))="","",IF($S28="","",IF(INDEX('_pockets'!$AB:$AB,$S28)="","",INDEX('_pockets'!$AB:$AB,$S28)))*IF($U$19,100,1)) | J28: =IF($S28="","",IF(INDEX('_pockets'!$Z:$Z,$S28)="","",INDEX('_pockets'!$Z:$Z,$S28))) | K28: =IF($R28="","",IF(INDEX('_list'!$K$2:$K$652,$R28)="","",INDEX('_list'!$K$2:$K$652,$R28))) | L28: =IF($S28="","",IF(INDEX('_pockets'!$AC:$AC,$S28)="","",INDEX('_pockets'!$AC:$AC,$S28))) | M28: =IF($R28="","",IF(INDEX('_list'!$L$2:$L$652,$R28)="","",INDEX('_list'!$L$2:$L$652,$R28))) | N28: =IF($R28="","",IF(INDEX('_list'!$H$2:$H$652,$R28)="","",INDEX('_list'!$H$2:$H$652,$R28))) | O28: =IF($R28="","",IF(INDEX('_list'!$I$2:$I$652,$R28)="","",INDEX('_list'!$I$2:$I$652,$R28))) | R28: =IFERROR(MATCH(8,'_list'!$N$2:$N$652,0),"") | S28: =IF($R28="","",INDEX('_list'!$C$2:$C$652,$R28))
B29: =IF($R29="","",9) | C29: =IF($R29="","",IF(INDEX('_list'!$D$2:$D$652,$R29)="","",INDEX('_list'!$D$2:$D$652,$R29))) | D29: =IF($R29="","",IF(INDEX('_list'!$E$2:$E$652,$R29)="","",INDEX('_list'!$E$2:$E$652,$R29))) | E29: =IF($R29="","",IF(INDEX('_list'!$F$2:$F$652,$R29)="","",INDEX('_list'!$F$2:$F$652,$R29))) | F29: =IF($R29="","",IF(INDEX('_list'!$G$2:$G$652,$R29)="","",INDEX('_list'!$G$2:$G$652,$R29))) | G29: =IF($S29="","",IF(INDEX('_pockets'!$AH:$AH,$S29)="","",INDEX('_pockets'!$AH:$AH,$S29))) | H29: =IF($S29="","",IF(INDEX('_pockets'!$AF:$AF,$S29)="","",INDEX('_pockets'!$AF:$AF,$S29))) | I29: =IF(IF($S29="","",IF(INDEX('_pockets'!$AB:$AB,$S29)="","",INDEX('_pockets'!$AB:$AB,$S29)))="","",IF($S29="","",IF(INDEX('_pockets'!$AB:$AB,$S29)="","",INDEX('_pockets'!$AB:$AB,$S29)))*IF($U$19,100,1)) | J29: =IF($S29="","",IF(INDEX('_pockets'!$Z:$Z,$S29)="","",INDEX('_pockets'!$Z:$Z,$S29))) | K29: =IF($R29="","",IF(INDEX('_list'!$K$2:$K$652,$R29)="","",INDEX('_list'!$K$2:$K$652,$R29))) | L29: =IF($S29="","",IF(INDEX('_pockets'!$AC:$AC,$S29)="","",INDEX('_pockets'!$AC:$AC,$S29))) | M29: =IF($R29="","",IF(INDEX('_list'!$L$2:$L$652,$R29)="","",INDEX('_list'!$L$2:$L$652,$R29))) | N29: =IF($R29="","",IF(INDEX('_list'!$H$2:$H$652,$R29)="","",INDEX('_list'!$H$2:$H$652,$R29))) | O29: =IF($R29="","",IF(INDEX('_list'!$I$2:$I$652,$R29)="","",INDEX('_list'!$I$2:$I$652,$R29))) | R29: =IFERROR(MATCH(9,'_list'!$N$2:$N$652,0),"") | S29: =IF($R29="","",INDEX('_list'!$C$2:$C$652,$R29))
B30: =IF($R30="","",10) | C30: =IF($R30="","",IF(INDEX('_list'!$D$2:$D$652,$R30)="","",INDEX('_list'!$D$2:$D$652,$R30))) | D30: =IF($R30="","",IF(INDEX('_list'!$E$2:$E$652,$R30)="","",INDEX('_list'!$E$2:$E$652,$R30))) | E30: =IF($R30="","",IF(INDEX('_list'!$F$2:$F$652,$R30)="","",INDEX('_list'!$F$2:$F$652,$R30))) | F30: =IF($R30="","",IF(INDEX('_list'!$G$2:$G$652,$R30)="","",INDEX('_list'!$G$2:$G$652,$R30))) | G30: =IF($S30="","",IF(INDEX('_pockets'!$AH:$AH,$S30)="","",INDEX('_pockets'!$AH:$AH,$S30))) | H30: =IF($S30="","",IF(INDEX('_pockets'!$AF:$AF,$S30)="","",INDEX('_pockets'!$AF:$AF,$S30))) | I30: =IF(IF($S30="","",IF(INDEX('_pockets'!$AB:$AB,$S30)="","",INDEX('_pockets'!$AB:$AB,$S30)))="","",IF($S30="","",IF(INDEX('_pockets'!$AB:$AB,$S30)="","",INDEX('_pockets'!$AB:$AB,$S30)))*IF($U$19,100,1)) | J30: =IF($S30="","",IF(INDEX('_pockets'!$Z:$Z,$S30)="","",INDEX('_pockets'!$Z:$Z,$S30))) | K30: =IF($R30="","",IF(INDEX('_list'!$K$2:$K$652,$R30)="","",INDEX('_list'!$K$2:$K$652,$R30))) | L30: =IF($S30="","",IF(INDEX('_pockets'!$AC:$AC,$S30)="","",INDEX('_pockets'!$AC:$AC,$S30))) | M30: =IF($R30="","",IF(INDEX('_list'!$L$2:$L$652,$R30)="","",INDEX('_list'!$L$2:$L$652,$R30))) | N30: =IF($R30="","",IF(INDEX('_list'!$H$2:$H$652,$R30)="","",INDEX('_list'!$H$2:$H$652,$R30))) | O30: =IF($R30="","",IF(INDEX('_list'!$I$2:$I$652,$R30)="","",INDEX('_list'!$I$2:$I$652,$R30))) | R30: =IFERROR(MATCH(10,'_list'!$N$2:$N$652,0),"") | S30: =IF($R30="","",INDEX('_list'!$C$2:$C$652,$R30))
B31: =IF($R31="","",11) | C31: =IF($R31="","",IF(INDEX('_list'!$D$2:$D$652,$R31)="","",INDEX('_list'!$D$2:$D$652,$R31))) | D31: =IF($R31="","",IF(INDEX('_list'!$E$2:$E$652,$R31)="","",INDEX('_list'!$E$2:$E$652,$R31))) | E31: =IF($R31="","",IF(INDEX('_list'!$F$2:$F$652,$R31)="","",INDEX('_list'!$F$2:$F$652,$R31))) | F31: =IF($R31="","",IF(INDEX('_list'!$G$2:$G$652,$R31)="","",INDEX('_list'!$G$2:$G$652,$R31))) | G31: =IF($S31="","",IF(INDEX('_pockets'!$AH:$AH,$S31)="","",INDEX('_pockets'!$AH:$AH,$S31))) | H31: =IF($S31="","",IF(INDEX('_pockets'!$AF:$AF,$S31)="","",INDEX('_pockets'!$AF:$AF,$S31))) | I31: =IF(IF($S31="","",IF(INDEX('_pockets'!$AB:$AB,$S31)="","",INDEX('_pockets'!$AB:$AB,$S31)))="","",IF($S31="","",IF(INDEX('_pockets'!$AB:$AB,$S31)="","",INDEX('_pockets'!$AB:$AB,$S31)))*IF($U$19,100,1)) | J31: =IF($S31="","",IF(INDEX('_pockets'!$Z:$Z,$S31)="","",INDEX('_pockets'!$Z:$Z,$S31))) | K31: =IF($R31="","",IF(INDEX('_list'!$K$2:$K$652,$R31)="","",INDEX('_list'!$K$2:$K$652,$R31))) | L31: =IF($S31="","",IF(INDEX('_pockets'!$AC:$AC,$S31)="","",INDEX('_pockets'!$AC:$AC,$S31))) | M31: =IF($R31="","",IF(INDEX('_list'!$L$2:$L$652,$R31)="","",INDEX('_list'!$L$2:$L$652,$R31))) | N31: =IF($R31="","",IF(INDEX('_list'!$H$2:$H$652,$R31)="","",INDEX('_list'!$H$2:$H$652,$R31))) | O31: =IF($R31="","",IF(INDEX('_list'!$I$2:$I$652,$R31)="","",INDEX('_list'!$I$2:$I$652,$R31))) | R31: =IFERROR(MATCH(11,'_list'!$N$2:$N$652,0),"") | S31: =IF($R31="","",INDEX('_list'!$C$2:$C$652,$R31))
B32: =IF($R32="","",12) | C32: =IF($R32="","",IF(INDEX('_list'!$D$2:$D$652,$R32)="","",INDEX('_list'!$D$2:$D$652,$R32))) | D32: =IF($R32="","",IF(INDEX('_list'!$E$2:$E$652,$R32)="","",INDEX('_list'!$E$2:$E$652,$R32))) | E32: =IF($R32="","",IF(INDEX('_list'!$F$2:$F$652,$R32)="","",INDEX('_list'!$F$2:$F$652,$R32))) | F32: =IF($R32="","",IF(INDEX('_list'!$G$2:$G$652,$R32)="","",INDEX('_list'!$G$2:$G$652,$R32))) | G32: =IF($S32="","",IF(INDEX('_pockets'!$AH:$AH,$S32)="","",INDEX('_pockets'!$AH:$AH,$S32))) | H32: =IF($S32="","",IF(INDEX('_pockets'!$AF:$AF,$S32)="","",INDEX('_pockets'!$AF:$AF,$S32))) | I32: =IF(IF($S32="","",IF(INDEX('_pockets'!$AB:$AB,$S32)="","",INDEX('_pockets'!$AB:$AB,$S32)))="","",IF($S32="","",IF(INDEX('_pockets'!$AB:$AB,$S32)="","",INDEX('_pockets'!$AB:$AB,$S32)))*IF($U$19,100,1)) | J32: =IF($S32="","",IF(INDEX('_pockets'!$Z:$Z,$S32)="","",INDEX('_pockets'!$Z:$Z,$S32))) | K32: =IF($R32="","",IF(INDEX('_list'!$K$2:$K$652,$R32)="","",INDEX('_list'!$K$2:$K$652,$R32))) | L32: =IF($S32="","",IF(INDEX('_pockets'!$AC:$AC,$S32)="","",INDEX('_pockets'!$AC:$AC,$S32))) | M32: =IF($R32="","",IF(INDEX('_list'!$L$2:$L$652,$R32)="","",INDEX('_list'!$L$2:$L$652,$R32))) | N32: =IF($R32="","",IF(INDEX('_list'!$H$2:$H$652,$R32)="","",INDEX('_list'!$H$2:$H$652,$R32))) | O32: =IF($R32="","",IF(INDEX('_list'!$I$2:$I$652,$R32)="","",INDEX('_list'!$I$2:$I$652,$R32))) | R32: =IFERROR(MATCH(12,'_list'!$N$2:$N$652,0),"") | S32: =IF($R32="","",INDEX('_list'!$C$2:$C$652,$R32))
B33: =IF($R33="","",13) | C33: =IF($R33="","",IF(INDEX('_list'!$D$2:$D$652,$R33)="","",INDEX('_list'!$D$2:$D$652,$R33))) | D33: =IF($R33="","",IF(INDEX('_list'!$E$2:$E$652,$R33)="","",INDEX('_list'!$E$2:$E$652,$R33))) | E33: =IF($R33="","",IF(INDEX('_list'!$F$2:$F$652,$R33)="","",INDEX('_list'!$F$2:$F$652,$R33))) | F33: =IF($R33="","",IF(INDEX('_list'!$G$2:$G$652,$R33)="","",INDEX('_list'!$G$2:$G$652,$R33))) | G33: =IF($S33="","",IF(INDEX('_pockets'!$AH:$AH,$S33)="","",INDEX('_pockets'!$AH:$AH,$S33))) | H33: =IF($S33="","",IF(INDEX('_pockets'!$AF:$AF,$S33)="","",INDEX('_pockets'!$AF:$AF,$S33))) | I33: =IF(IF($S33="","",IF(INDEX('_pockets'!$AB:$AB,$S33)="","",INDEX('_pockets'!$AB:$AB,$S33)))="","",IF($S33="","",IF(INDEX('_pockets'!$AB:$AB,$S33)="","",INDEX('_pockets'!$AB:$AB,$S33)))*IF($U$19,100,1)) | J33: =IF($S33="","",IF(INDEX('_pockets'!$Z:$Z,$S33)="","",INDEX('_pockets'!$Z:$Z,$S33))) | K33: =IF($R33="","",IF(INDEX('_list'!$K$2:$K$652,$R33)="","",INDEX('_list'!$K$2:$K$652,$R33))) | L33: =IF($S33="","",IF(INDEX('_pockets'!$AC:$AC,$S33)="","",INDEX('_pockets'!$AC:$AC,$S33))) | M33: =IF($R33="","",IF(INDEX('_list'!$L$2:$L$652,$R33)="","",INDEX('_list'!$L$2:$L$652,$R33))) | N33: =IF($R33="","",IF(INDEX('_list'!$H$2:$H$652,$R33)="","",INDEX('_list'!$H$2:$H$652,$R33))) | O33: =IF($R33="","",IF(INDEX('_list'!$I$2:$I$652,$R33)="","",INDEX('_list'!$I$2:$I$652,$R33))) | R33: =IFERROR(MATCH(13,'_list'!$N$2:$N$652,0),"") | S33: =IF($R33="","",INDEX('_list'!$C$2:$C$652,$R33))
B34: =IF($R34="","",14) | C34: =IF($R34="","",IF(INDEX('_list'!$D$2:$D$652,$R34)="","",INDEX('_list'!$D$2:$D$652,$R34))) | D34: =IF($R34="","",IF(INDEX('_list'!$E$2:$E$652,$R34)="","",INDEX('_list'!$E$2:$E$652,$R34))) | E34: =IF($R34="","",IF(INDEX('_list'!$F$2:$F$652,$R34)="","",INDEX('_list'!$F$2:$F$652,$R34))) | F34: =IF($R34="","",IF(INDEX('_list'!$G$2:$G$652,$R34)="","",INDEX('_list'!$G$2:$G$652,$R34))) | G34: =IF($S34="","",IF(INDEX('_pockets'!$AH:$AH,$S34)="","",INDEX('_pockets'!$AH:$AH,$S34))) | H34: =IF($S34="","",IF(INDEX('_pockets'!$AF:$AF,$S34)="","",INDEX('_pockets'!$AF:$AF,$S34))) | I34: =IF(IF($S34="","",IF(INDEX('_pockets'!$AB:$AB,$S34)="","",INDEX('_pockets'!$AB:$AB,$S34)))="","",IF($S34="","",IF(INDEX('_pockets'!$AB:$AB,$S34)="","",INDEX('_pockets'!$AB:$AB,$S34)))*IF($U$19,100,1)) | J34: =IF($S34="","",IF(INDEX('_pockets'!$Z:$Z,$S34)="","",INDEX('_pockets'!$Z:$Z,$S34))) | K34: =IF($R34="","",IF(INDEX('_list'!$K$2:$K$652,$R34)="","",INDEX('_list'!$K$2:$K$652,$R34))) | L34: =IF($S34="","",IF(INDEX('_pockets'!$AC:$AC,$S34)="","",INDEX('_pockets'!$AC:$AC,$S34))) | M34: =IF($R34="","",IF(INDEX('_list'!$L$2:$L$652,$R34)="","",INDEX('_list'!$L$2:$L$652,$R34))) | N34: =IF($R34="","",IF(INDEX('_list'!$H$2:$H$652,$R34)="","",INDEX('_list'!$H$2:$H$652,$R34))) | O34: =IF($R34="","",IF(INDEX('_list'!$I$2:$I$652,$R34)="","",INDEX('_list'!$I$2:$I$652,$R34))) | R34: =IFERROR(MATCH(14,'_list'!$N$2:$N$652,0),"") | S34: =IF($R34="","",INDEX('_list'!$C$2:$C$652,$R34))
B35: =IF($R35="","",15) | C35: =IF($R35="","",IF(INDEX('_list'!$D$2:$D$652,$R35)="","",INDEX('_list'!$D$2:$D$652,$R35))) | D35: =IF($R35="","",IF(INDEX('_list'!$E$2:$E$652,$R35)="","",INDEX('_list'!$E$2:$E$652,$R35))) | E35: =IF($R35="","",IF(INDEX('_list'!$F$2:$F$652,$R35)="","",INDEX('_list'!$F$2:$F$652,$R35))) | F35: =IF($R35="","",IF(INDEX('_list'!$G$2:$G$652,$R35)="","",INDEX('_list'!$G$2:$G$652,$R35))) | G35: =IF($S35="","",IF(INDEX('_pockets'!$AH:$AH,$S35)="","",INDEX('_pockets'!$AH:$AH,$S35))) | H35: =IF($S35="","",IF(INDEX('_pockets'!$AF:$AF,$S35)="","",INDEX('_pockets'!$AF:$AF,$S35))) | I35: =IF(IF($S35="","",IF(INDEX('_pockets'!$AB:$AB,$S35)="","",INDEX('_pockets'!$AB:$AB,$S35)))="","",IF($S35="","",IF(INDEX('_pockets'!$AB:$AB,$S35)="","",INDEX('_pockets'!$AB:$AB,$S35)))*IF($U$19,100,1)) | J35: =IF($S35="","",IF(INDEX('_pockets'!$Z:$Z,$S35)="","",INDEX('_pockets'!$Z:$Z,$S35))) | K35: =IF($R35="","",IF(INDEX('_list'!$K$2:$K$652,$R35)="","",INDEX('_list'!$K$2:$K$652,$R35))) | L35: =IF($S35="","",IF(INDEX('_pockets'!$AC:$AC,$S35)="","",INDEX('_pockets'!$AC:$AC,$S35))) | M35: =IF($R35="","",IF(INDEX('_list'!$L$2:$L$652,$R35)="","",INDEX('_list'!$L$2:$L$652,$R35))) | N35: =IF($R35="","",IF(INDEX('_list'!$H$2:$H$652,$R35)="","",INDEX('_list'!$H$2:$H$652,$R35))) | O35: =IF($R35="","",IF(INDEX('_list'!$I$2:$I$652,$R35)="","",INDEX('_list'!$I$2:$I$652,$R35))) | R35: =IFERROR(MATCH(15,'_list'!$N$2:$N$652,0),"") | S35: =IF($R35="","",INDEX('_list'!$C$2:$C$652,$R35))
B36: =IF($R36="","",16) | C36: =IF($R36="","",IF(INDEX('_list'!$D$2:$D$652,$R36)="","",INDEX('_list'!$D$2:$D$652,$R36))) | D36: =IF($R36="","",IF(INDEX('_list'!$E$2:$E$652,$R36)="","",INDEX('_list'!$E$2:$E$652,$R36))) | E36: =IF($R36="","",IF(INDEX('_list'!$F$2:$F$652,$R36)="","",INDEX('_list'!$F$2:$F$652,$R36))) | F36: =IF($R36="","",IF(INDEX('_list'!$G$2:$G$652,$R36)="","",INDEX('_list'!$G$2:$G$652,$R36))) | G36: =IF($S36="","",IF(INDEX('_pockets'!$AH:$AH,$S36)="","",INDEX('_pockets'!$AH:$AH,$S36))) | H36: =IF($S36="","",IF(INDEX('_pockets'!$AF:$AF,$S36)="","",INDEX('_pockets'!$AF:$AF,$S36))) | I36: =IF(IF($S36="","",IF(INDEX('_pockets'!$AB:$AB,$S36)="","",INDEX('_pockets'!$AB:$AB,$S36)))="","",IF($S36="","",IF(INDEX('_pockets'!$AB:$AB,$S36)="","",INDEX('_pockets'!$AB:$AB,$S36)))*IF($U$19,100,1)) | J36: =IF($S36="","",IF(INDEX('_pockets'!$Z:$Z,$S36)="","",INDEX('_pockets'!$Z:$Z,$S36))) | K36: =IF($R36="","",IF(INDEX('_list'!$K$2:$K$652,$R36)="","",INDEX('_list'!$K$2:$K$652,$R36))) | L36: =IF($S36="","",IF(INDEX('_pockets'!$AC:$AC,$S36)="","",INDEX('_pockets'!$AC:$AC,$S36))) | M36: =IF($R36="","",IF(INDEX('_list'!$L$2:$L$652,$R36)="","",INDEX('_list'!$L$2:$L$652,$R36))) | N36: =IF($R36="","",IF(INDEX('_list'!$H$2:$H$652,$R36)="","",INDEX('_list'!$H$2:$H$652,$R36))) | O36: =IF($R36="","",IF(INDEX('_list'!$I$2:$I$652,$R36)="","",INDEX('_list'!$I$2:$I$652,$R36))) | R36: =IFERROR(MATCH(16,'_list'!$N$2:$N$652,0),"") | S36: =IF($R36="","",INDEX('_list'!$C$2:$C$652,$R36))
B37: =IF($R37="","",17) | C37: =IF($R37="","",IF(INDEX('_list'!$D$2:$D$652,$R37)="","",INDEX('_list'!$D$2:$D$652,$R37))) | D37: =IF($R37="","",IF(INDEX('_list'!$E$2:$E$652,$R37)="","",INDEX('_list'!$E$2:$E$652,$R37))) | E37: =IF($R37="","",IF(INDEX('_list'!$F$2:$F$652,$R37)="","",INDEX('_list'!$F$2:$F$652,$R37))) | F37: =IF($R37="","",IF(INDEX('_list'!$G$2:$G$652,$R37)="","",INDEX('_list'!$G$2:$G$652,$R37))) | G37: =IF($S37="","",IF(INDEX('_pockets'!$AH:$AH,$S37)="","",INDEX('_pockets'!$AH:$AH,$S37))) | H37: =IF($S37="","",IF(INDEX('_pockets'!$AF:$AF,$S37)="","",INDEX('_pockets'!$AF:$AF,$S37))) | I37: =IF(IF($S37="","",IF(INDEX('_pockets'!$AB:$AB,$S37)="","",INDEX('_pockets'!$AB:$AB,$S37)))="","",IF($S37="","",IF(INDEX('_pockets'!$AB:$AB,$S37)="","",INDEX('_pockets'!$AB:$AB,$S37)))*IF($U$19,100,1)) | J37: =IF($S37="","",IF(INDEX('_pockets'!$Z:$Z,$S37)="","",INDEX('_pockets'!$Z:$Z,$S37))) | K37: =IF($R37="","",IF(INDEX('_list'!$K$2:$K$652,$R37)="","",INDEX('_list'!$K$2:$K$652,$R37))) | L37: =IF($S37="","",IF(INDEX('_pockets'!$AC:$AC,$S37)="","",INDEX('_pockets'!$AC:$AC,$S37))) | M37: =IF($R37="","",IF(INDEX('_list'!$L$2:$L$652,$R37)="","",INDEX('_list'!$L$2:$L$652,$R37))) | N37: =IF($R37="","",IF(INDEX('_list'!$H$2:$H$652,$R37)="","",INDEX('_list'!$H$2:$H$652,$R37))) | O37: =IF($R37="","",IF(INDEX('_list'!$I$2:$I$652,$R37)="","",INDEX('_list'!$I$2:$I$652,$R37))) | R37: =IFERROR(MATCH(17,'_list'!$N$2:$N$652,0),"") | S37: =IF($R37="","",INDEX('_list'!$C$2:$C$652,$R37))
B38: =IF($R38="","",18) | C38: =IF($R38="","",IF(INDEX('_list'!$D$2:$D$652,$R38)="","",INDEX('_list'!$D$2:$D$652,$R38))) | D38: =IF($R38="","",IF(INDEX('_list'!$E$2:$E$652,$R38)="","",INDEX('_list'!$E$2:$E$652,$R38))) | E38: =IF($R38="","",IF(INDEX('_list'!$F$2:$F$652,$R38)="","",INDEX('_list'!$F$2:$F$652,$R38))) | F38: =IF($R38="","",IF(INDEX('_list'!$G$2:$G$652,$R38)="","",INDEX('_list'!$G$2:$G$652,$R38))) | G38: =IF($S38="","",IF(INDEX('_pockets'!$AH:$AH,$S38)="","",INDEX('_pockets'!$AH:$AH,$S38))) | H38: =IF($S38="","",IF(INDEX('_pockets'!$AF:$AF,$S38)="","",INDEX('_pockets'!$AF:$AF,$S38))) | I38: =IF(IF($S38="","",IF(INDEX('_pockets'!$AB:$AB,$S38)="","",INDEX('_pockets'!$AB:$AB,$S38)))="","",IF($S38="","",IF(INDEX('_pockets'!$AB:$AB,$S38)="","",INDEX('_pockets'!$AB:$AB,$S38)))*IF($U$19,100,1)) | J38: =IF($S38="","",IF(INDEX('_pockets'!$Z:$Z,$S38)="","",INDEX('_pockets'!$Z:$Z,$S38))) | K38: =IF($R38="","",IF(INDEX('_list'!$K$2:$K$652,$R38)="","",INDEX('_list'!$K$2:$K$652,$R38))) | L38: =IF($S38="","",IF(INDEX('_pockets'!$AC:$AC,$S38)="","",INDEX('_pockets'!$AC:$AC,$S38))) | M38: =IF($R38="","",IF(INDEX('_list'!$L$2:$L$652,$R38)="","",INDEX('_list'!$L$2:$L$652,$R38))) | N38: =IF($R38="","",IF(INDEX('_list'!$H$2:$H$652,$R38)="","",INDEX('_list'!$H$2:$H$652,$R38))) | O38: =IF($R38="","",IF(INDEX('_list'!$I$2:$I$652,$R38)="","",INDEX('_list'!$I$2:$I$652,$R38))) | R38: =IFERROR(MATCH(18,'_list'!$N$2:$N$652,0),"") | S38: =IF($R38="","",INDEX('_list'!$C$2:$C$652,$R38))
B39: =IF($R39="","",19) | C39: =IF($R39="","",IF(INDEX('_list'!$D$2:$D$652,$R39)="","",INDEX('_list'!$D$2:$D$652,$R39))) | D39: =IF($R39="","",IF(INDEX('_list'!$E$2:$E$652,$R39)="","",INDEX('_list'!$E$2:$E$652,$R39))) | E39: =IF($R39="","",IF(INDEX('_list'!$F$2:$F$652,$R39)="","",INDEX('_list'!$F$2:$F$652,$R39))) | F39: =IF($R39="","",IF(INDEX('_list'!$G$2:$G$652,$R39)="","",INDEX('_list'!$G$2:$G$652,$R39))) | G39: =IF($S39="","",IF(INDEX('_pockets'!$AH:$AH,$S39)="","",INDEX('_pockets'!$AH:$AH,$S39))) | H39: =IF($S39="","",IF(INDEX('_pockets'!$AF:$AF,$S39)="","",INDEX('_pockets'!$AF:$AF,$S39))) | I39: =IF(IF($S39="","",IF(INDEX('_pockets'!$AB:$AB,$S39)="","",INDEX('_pockets'!$AB:$AB,$S39)))="","",IF($S39="","",IF(INDEX('_pockets'!$AB:$AB,$S39)="","",INDEX('_pockets'!$AB:$AB,$S39)))*IF($U$19,100,1)) | J39: =IF($S39="","",IF(INDEX('_pockets'!$Z:$Z,$S39)="","",INDEX('_pockets'!$Z:$Z,$S39))) | K39: =IF($R39="","",IF(INDEX('_list'!$K$2:$K$652,$R39)="","",INDEX('_list'!$K$2:$K$652,$R39))) | L39: =IF($S39="","",IF(INDEX('_pockets'!$AC:$AC,$S39)="","",INDEX('_pockets'!$AC:$AC,$S39))) | M39: =IF($R39="","",IF(INDEX('_list'!$L$2:$L$652,$R39)="","",INDEX('_list'!$L$2:$L$652,$R39))) | N39: =IF($R39="","",IF(INDEX('_list'!$H$2:$H$652,$R39)="","",INDEX('_list'!$H$2:$H$652,$R39))) | O39: =IF($R39="","",IF(INDEX('_list'!$I$2:$I$652,$R39)="","",INDEX('_list'!$I$2:$I$652,$R39))) | R39: =IFERROR(MATCH(19,'_list'!$N$2:$N$652,0),"") | S39: =IF($R39="","",INDEX('_list'!$C$2:$C$652,$R39))
B40: =IF($R40="","",20) | C40: =IF($R40="","",IF(INDEX('_list'!$D$2:$D$652,$R40)="","",INDEX('_list'!$D$2:$D$652,$R40))) | D40: =IF($R40="","",IF(INDEX('_list'!$E$2:$E$652,$R40)="","",INDEX('_list'!$E$2:$E$652,$R40))) | E40: =IF($R40="","",IF(INDEX('_list'!$F$2:$F$652,$R40)="","",INDEX('_list'!$F$2:$F$652,$R40))) | F40: =IF($R40="","",IF(INDEX('_list'!$G$2:$G$652,$R40)="","",INDEX('_list'!$G$2:$G$652,$R40))) | G40: =IF($S40="","",IF(INDEX('_pockets'!$AH:$AH,$S40)="","",INDEX('_pockets'!$AH:$AH,$S40))) | H40: =IF($S40="","",IF(INDEX('_pockets'!$AF:$AF,$S40)="","",INDEX('_pockets'!$AF:$AF,$S40))) | I40: =IF(IF($S40="","",IF(INDEX('_pockets'!$AB:$AB,$S40)="","",INDEX('_pockets'!$AB:$AB,$S40)))="","",IF($S40="","",IF(INDEX('_pockets'!$AB:$AB,$S40)="","",INDEX('_pockets'!$AB:$AB,$S40)))*IF($U$19,100,1)) | J40: =IF($S40="","",IF(INDEX('_pockets'!$Z:$Z,$S40)="","",INDEX('_pockets'!$Z:$Z,$S40))) | K40: =IF($R40="","",IF(INDEX('_list'!$K$2:$K$652,$R40)="","",INDEX('_list'!$K$2:$K$652,$R40))) | L40: =IF($S40="","",IF(INDEX('_pockets'!$AC:$AC,$S40)="","",INDEX('_pockets'!$AC:$AC,$S40))) | M40: =IF($R40="","",IF(INDEX('_list'!$L$2:$L$652,$R40)="","",INDEX('_list'!$L$2:$L$652,$R40))) | N40: =IF($R40="","",IF(INDEX('_list'!$H$2:$H$652,$R40)="","",INDEX('_list'!$H$2:$H$652,$R40))) | O40: =IF($R40="","",IF(INDEX('_list'!$I$2:$I$652,$R40)="","",INDEX('_list'!$I$2:$I$652,$R40))) | R40: =IFERROR(MATCH(20,'_list'!$N$2:$N$652,0),"") | S40: =IF($R40="","",INDEX('_list'!$C$2:$C$652,$R40))
B41: =IF($R41="","",21) | C41: =IF($R41="","",IF(INDEX('_list'!$D$2:$D$652,$R41)="","",INDEX('_list'!$D$2:$D$652,$R41))) | D41: =IF($R41="","",IF(INDEX('_list'!$E$2:$E$652,$R41)="","",INDEX('_list'!$E$2:$E$652,$R41))) | E41: =IF($R41="","",IF(INDEX('_list'!$F$2:$F$652,$R41)="","",INDEX('_list'!$F$2:$F$652,$R41))) | F41: =IF($R41="","",IF(INDEX('_list'!$G$2:$G$652,$R41)="","",INDEX('_list'!$G$2:$G$652,$R41))) | G41: =IF($S41="","",IF(INDEX('_pockets'!$AH:$AH,$S41)="","",INDEX('_pockets'!$AH:$AH,$S41))) | H41: =IF($S41="","",IF(INDEX('_pockets'!$AF:$AF,$S41)="","",INDEX('_pockets'!$AF:$AF,$S41))) | I41: =IF(IF($S41="","",IF(INDEX('_pockets'!$AB:$AB,$S41)="","",INDEX('_pockets'!$AB:$AB,$S41)))="","",IF($S41="","",IF(INDEX('_pockets'!$AB:$AB,$S41)="","",INDEX('_pockets'!$AB:$AB,$S41)))*IF($U$19,100,1)) | J41: =IF($S41="","",IF(INDEX('_pockets'!$Z:$Z,$S41)="","",INDEX('_pockets'!$Z:$Z,$S41))) | K41: =IF($R41="","",IF(INDEX('_list'!$K$2:$K$652,$R41)="","",INDEX('_list'!$K$2:$K$652,$R41))) | L41: =IF($S41="","",IF(INDEX('_pockets'!$AC:$AC,$S41)="","",INDEX('_pockets'!$AC:$AC,$S41))) | M41: =IF($R41="","",IF(INDEX('_list'!$L$2:$L$652,$R41)="","",INDEX('_list'!$L$2:$L$652,$R41))) | N41: =IF($R41="","",IF(INDEX('_list'!$H$2:$H$652,$R41)="","",INDEX('_list'!$H$2:$H$652,$R41))) | O41: =IF($R41="","",IF(INDEX('_list'!$I$2:$I$652,$R41)="","",INDEX('_list'!$I$2:$I$652,$R41))) | R41: =IFERROR(MATCH(21,'_list'!$N$2:$N$652,0),"") | S41: =IF($R41="","",INDEX('_list'!$C$2:$C$652,$R41))
B42: =IF($R42="","",22) | C42: =IF($R42="","",IF(INDEX('_list'!$D$2:$D$652,$R42)="","",INDEX('_list'!$D$2:$D$652,$R42))) | D42: =IF($R42="","",IF(INDEX('_list'!$E$2:$E$652,$R42)="","",INDEX('_list'!$E$2:$E$652,$R42))) | E42: =IF($R42="","",IF(INDEX('_list'!$F$2:$F$652,$R42)="","",INDEX('_list'!$F$2:$F$652,$R42))) | F42: =IF($R42="","",IF(INDEX('_list'!$G$2:$G$652,$R42)="","",INDEX('_list'!$G$2:$G$652,$R42))) | G42: =IF($S42="","",IF(INDEX('_pockets'!$AH:$AH,$S42)="","",INDEX('_pockets'!$AH:$AH,$S42))) | H42: =IF($S42="","",IF(INDEX('_pockets'!$AF:$AF,$S42)="","",INDEX('_pockets'!$AF:$AF,$S42))) | I42: =IF(IF($S42="","",IF(INDEX('_pockets'!$AB:$AB,$S42)="","",INDEX('_pockets'!$AB:$AB,$S42)))="","",IF($S42="","",IF(INDEX('_pockets'!$AB:$AB,$S42)="","",INDEX('_pockets'!$AB:$AB,$S42)))*IF($U$19,100,1)) | J42: =IF($S42="","",IF(INDEX('_pockets'!$Z:$Z,$S42)="","",INDEX('_pockets'!$Z:$Z,$S42))) | K42: =IF($R42="","",IF(INDEX('_list'!$K$2:$K$652,$R42)="","",INDEX('_list'!$K$2:$K$652,$R42))) | L42: =IF($S42="","",IF(INDEX('_pockets'!$AC:$AC,$S42)="","",INDEX('_pockets'!$AC:$AC,$S42))) | M42: =IF($R42="","",IF(INDEX('_list'!$L$2:$L$652,$R42)="","",INDEX('_list'!$L$2:$L$652,$R42))) | N42: =IF($R42="","",IF(INDEX('_list'!$H$2:$H$652,$R42)="","",INDEX('_list'!$H$2:$H$652,$R42))) | O42: =IF($R42="","",IF(INDEX('_list'!$I$2:$I$652,$R42)="","",INDEX('_list'!$I$2:$I$652,$R42))) | R42: =IFERROR(MATCH(22,'_list'!$N$2:$N$652,0),"") | S42: =IF($R42="","",INDEX('_list'!$C$2:$C$652,$R42))
B43: =IF($R43="","",23) | C43: =IF($R43="","",IF(INDEX('_list'!$D$2:$D$652,$R43)="","",INDEX('_list'!$D$2:$D$652,$R43))) | D43: =IF($R43="","",IF(INDEX('_list'!$E$2:$E$652,$R43)="","",INDEX('_list'!$E$2:$E$652,$R43))) | E43: =IF($R43="","",IF(INDEX('_list'!$F$2:$F$652,$R43)="","",INDEX('_list'!$F$2:$F$652,$R43))) | F43: =IF($R43="","",IF(INDEX('_list'!$G$2:$G$652,$R43)="","",INDEX('_list'!$G$2:$G$652,$R43))) | G43: =IF($S43="","",IF(INDEX('_pockets'!$AH:$AH,$S43)="","",INDEX('_pockets'!$AH:$AH,$S43))) | H43: =IF($S43="","",IF(INDEX('_pockets'!$AF:$AF,$S43)="","",INDEX('_pockets'!$AF:$AF,$S43))) | I43: =IF(IF($S43="","",IF(INDEX('_pockets'!$AB:$AB,$S43)="","",INDEX('_pockets'!$AB:$AB,$S43)))="","",IF($S43="","",IF(INDEX('_pockets'!$AB:$AB,$S43)="","",INDEX('_pockets'!$AB:$AB,$S43)))*IF($U$19,100,1)) | J43: =IF($S43="","",IF(INDEX('_pockets'!$Z:$Z,$S43)="","",INDEX('_pockets'!$Z:$Z,$S43))) | K43: =IF($R43="","",IF(INDEX('_list'!$K$2:$K$652,$R43)="","",INDEX('_list'!$K$2:$K$652,$R43))) | L43: =IF($S43="","",IF(INDEX('_pockets'!$AC:$AC,$S43)="","",INDEX('_pockets'!$AC:$AC,$S43))) | M43: =IF($R43="","",IF(INDEX('_list'!$L$2:$L$652,$R43)="","",INDEX('_list'!$L$2:$L$652,$R43))) | N43: =IF($R43="","",IF(INDEX('_list'!$H$2:$H$652,$R43)="","",INDEX('_list'!$H$2:$H$652,$R43))) | O43: =IF($R43="","",IF(INDEX('_list'!$I$2:$I$652,$R43)="","",INDEX('_list'!$I$2:$I$652,$R43))) | R43: =IFERROR(MATCH(23,'_list'!$N$2:$N$652,0),"") | S43: =IF($R43="","",INDEX('_list'!$C$2:$C$652,$R43))
B44: =IF($R44="","",24) | C44: =IF($R44="","",IF(INDEX('_list'!$D$2:$D$652,$R44)="","",INDEX('_list'!$D$2:$D$652,$R44))) | D44: =IF($R44="","",IF(INDEX('_list'!$E$2:$E$652,$R44)="","",INDEX('_list'!$E$2:$E$652,$R44))) | E44: =IF($R44="","",IF(INDEX('_list'!$F$2:$F$652,$R44)="","",INDEX('_list'!$F$2:$F$652,$R44))) | F44: =IF($R44="","",IF(INDEX('_list'!$G$2:$G$652,$R44)="","",INDEX('_list'!$G$2:$G$652,$R44))) | G44: =IF($S44="","",IF(INDEX('_pockets'!$AH:$AH,$S44)="","",INDEX('_pockets'!$AH:$AH,$S44))) | H44: =IF($S44="","",IF(INDEX('_pockets'!$AF:$AF,$S44)="","",INDEX('_pockets'!$AF:$AF,$S44))) | I44: =IF(IF($S44="","",IF(INDEX('_pockets'!$AB:$AB,$S44)="","",INDEX('_pockets'!$AB:$AB,$S44)))="","",IF($S44="","",IF(INDEX('_pockets'!$AB:$AB,$S44)="","",INDEX('_pockets'!$AB:$AB,$S44)))*IF($U$19,100,1)) | J44: =IF($S44="","",IF(INDEX('_pockets'!$Z:$Z,$S44)="","",INDEX('_pockets'!$Z:$Z,$S44))) | K44: =IF($R44="","",IF(INDEX('_list'!$K$2:$K$652,$R44)="","",INDEX('_list'!$K$2:$K$652,$R44))) | L44: =IF($S44="","",IF(INDEX('_pockets'!$AC:$AC,$S44)="","",INDEX('_pockets'!$AC:$AC,$S44))) | M44: =IF($R44="","",IF(INDEX('_list'!$L$2:$L$652,$R44)="","",INDEX('_list'!$L$2:$L$652,$R44))) | N44: =IF($R44="","",IF(INDEX('_list'!$H$2:$H$652,$R44)="","",INDEX('_list'!$H$2:$H$652,$R44))) | O44: =IF($R44="","",IF(INDEX('_list'!$I$2:$I$652,$R44)="","",INDEX('_list'!$I$2:$I$652,$R44))) | R44: =IFERROR(MATCH(24,'_list'!$N$2:$N$652,0),"") | S44: =IF($R44="","",INDEX('_list'!$C$2:$C$652,$R44))
B45: =IF($R45="","",25) | C45: =IF($R45="","",IF(INDEX('_list'!$D$2:$D$652,$R45)="","",INDEX('_list'!$D$2:$D$652,$R45))) | D45: =IF($R45="","",IF(INDEX('_list'!$E$2:$E$652,$R45)="","",INDEX('_list'!$E$2:$E$652,$R45))) | E45: =IF($R45="","",IF(INDEX('_list'!$F$2:$F$652,$R45)="","",INDEX('_list'!$F$2:$F$652,$R45))) | F45: =IF($R45="","",IF(INDEX('_list'!$G$2:$G$652,$R45)="","",INDEX('_list'!$G$2:$G$652,$R45))) | G45: =IF($S45="","",IF(INDEX('_pockets'!$AH:$AH,$S45)="","",INDEX('_pockets'!$AH:$AH,$S45))) | H45: =IF($S45="","",IF(INDEX('_pockets'!$AF:$AF,$S45)="","",INDEX('_pockets'!$AF:$AF,$S45))) | I45: =IF(IF($S45="","",IF(INDEX('_pockets'!$AB:$AB,$S45)="","",INDEX('_pockets'!$AB:$AB,$S45)))="","",IF($S45="","",IF(INDEX('_pockets'!$AB:$AB,$S45)="","",INDEX('_pockets'!$AB:$AB,$S45)))*IF($U$19,100,1)) | J45: =IF($S45="","",IF(INDEX('_pockets'!$Z:$Z,$S45)="","",INDEX('_pockets'!$Z:$Z,$S45))) | K45: =IF($R45="","",IF(INDEX('_list'!$K$2:$K$652,$R45)="","",INDEX('_list'!$K$2:$K$652,$R45))) | L45: =IF($S45="","",IF(INDEX('_pockets'!$AC:$AC,$S45)="","",INDEX('_pockets'!$AC:$AC,$S45))) | M45: =IF($R45="","",IF(INDEX('_list'!$L$2:$L$652,$R45)="","",INDEX('_list'!$L$2:$L$652,$R45))) | N45: =IF($R45="","",IF(INDEX('_list'!$H$2:$H$652,$R45)="","",INDEX('_list'!$H$2:$H$652,$R45))) | O45: =IF($R45="","",IF(INDEX('_list'!$I$2:$I$652,$R45)="","",INDEX('_list'!$I$2:$I$652,$R45))) | R45: =IFERROR(MATCH(25,'_list'!$N$2:$N$652,0),"") | S45: =IF($R45="","",INDEX('_list'!$C$2:$C$652,$R45))
B46: =IF($R46="","",26) | C46: =IF($R46="","",IF(INDEX('_list'!$D$2:$D$652,$R46)="","",INDEX('_list'!$D$2:$D$652,$R46))) | D46: =IF($R46="","",IF(INDEX('_list'!$E$2:$E$652,$R46)="","",INDEX('_list'!$E$2:$E$652,$R46))) | E46: =IF($R46="","",IF(INDEX('_list'!$F$2:$F$652,$R46)="","",INDEX('_list'!$F$2:$F$652,$R46))) | F46: =IF($R46="","",IF(INDEX('_list'!$G$2:$G$652,$R46)="","",INDEX('_list'!$G$2:$G$652,$R46))) | G46: =IF($S46="","",IF(INDEX('_pockets'!$AH:$AH,$S46)="","",INDEX('_pockets'!$AH:$AH,$S46))) | H46: =IF($S46="","",IF(INDEX('_pockets'!$AF:$AF,$S46)="","",INDEX('_pockets'!$AF:$AF,$S46))) | I46: =IF(IF($S46="","",IF(INDEX('_pockets'!$AB:$AB,$S46)="","",INDEX('_pockets'!$AB:$AB,$S46)))="","",IF($S46="","",IF(INDEX('_pockets'!$AB:$AB,$S46)="","",INDEX('_pockets'!$AB:$AB,$S46)))*IF($U$19,100,1)) | J46: =IF($S46="","",IF(INDEX('_pockets'!$Z:$Z,$S46)="","",INDEX('_pockets'!$Z:$Z,$S46))) | K46: =IF($R46="","",IF(INDEX('_list'!$K$2:$K$652,$R46)="","",INDEX('_list'!$K$2:$K$652,$R46))) | L46: =IF($S46="","",IF(INDEX('_pockets'!$AC:$AC,$S46)="","",INDEX('_pockets'!$AC:$AC,$S46))) | M46: =IF($R46="","",IF(INDEX('_list'!$L$2:$L$652,$R46)="","",INDEX('_list'!$L$2:$L$652,$R46))) | N46: =IF($R46="","",IF(INDEX('_list'!$H$2:$H$652,$R46)="","",INDEX('_list'!$H$2:$H$652,$R46))) | O46: =IF($R46="","",IF(INDEX('_list'!$I$2:$I$652,$R46)="","",INDEX('_list'!$I$2:$I$652,$R46))) | R46: =IFERROR(MATCH(26,'_list'!$N$2:$N$652,0),"") | S46: =IF($R46="","",INDEX('_list'!$C$2:$C$652,$R46))
B47: =IF($R47="","",27) | C47: =IF($R47="","",IF(INDEX('_list'!$D$2:$D$652,$R47)="","",INDEX('_list'!$D$2:$D$652,$R47))) | D47: =IF($R47="","",IF(INDEX('_list'!$E$2:$E$652,$R47)="","",INDEX('_list'!$E$2:$E$652,$R47))) | E47: =IF($R47="","",IF(INDEX('_list'!$F$2:$F$652,$R47)="","",INDEX('_list'!$F$2:$F$652,$R47))) | F47: =IF($R47="","",IF(INDEX('_list'!$G$2:$G$652,$R47)="","",INDEX('_list'!$G$2:$G$652,$R47))) | G47: =IF($S47="","",IF(INDEX('_pockets'!$AH:$AH,$S47)="","",INDEX('_pockets'!$AH:$AH,$S47))) | H47: =IF($S47="","",IF(INDEX('_pockets'!$AF:$AF,$S47)="","",INDEX('_pockets'!$AF:$AF,$S47))) | I47: =IF(IF($S47="","",IF(INDEX('_pockets'!$AB:$AB,$S47)="","",INDEX('_pockets'!$AB:$AB,$S47)))="","",IF($S47="","",IF(INDEX('_pockets'!$AB:$AB,$S47)="","",INDEX('_pockets'!$AB:$AB,$S47)))*IF($U$19,100,1)) | J47: =IF($S47="","",IF(INDEX('_pockets'!$Z:$Z,$S47)="","",INDEX('_pockets'!$Z:$Z,$S47))) | K47: =IF($R47="","",IF(INDEX('_list'!$K$2:$K$652,$R47)="","",INDEX('_list'!$K$2:$K$652,$R47))) | L47: =IF($S47="","",IF(INDEX('_pockets'!$AC:$AC,$S47)="","",INDEX('_pockets'!$AC:$AC,$S47))) | M47: =IF($R47="","",IF(INDEX('_list'!$L$2:$L$652,$R47)="","",INDEX('_list'!$L$2:$L$652,$R47))) | N47: =IF($R47="","",IF(INDEX('_list'!$H$2:$H$652,$R47)="","",INDEX('_list'!$H$2:$H$652,$R47))) | O47: =IF($R47="","",IF(INDEX('_list'!$I$2:$I$652,$R47)="","",INDEX('_list'!$I$2:$I$652,$R47))) | R47: =IFERROR(MATCH(27,'_list'!$N$2:$N$652,0),"") | S47: =IF($R47="","",INDEX('_list'!$C$2:$C$652,$R47))
B48: =IF($R48="","",28) | C48: =IF($R48="","",IF(INDEX('_list'!$D$2:$D$652,$R48)="","",INDEX('_list'!$D$2:$D$652,$R48))) | D48: =IF($R48="","",IF(INDEX('_list'!$E$2:$E$652,$R48)="","",INDEX('_list'!$E$2:$E$652,$R48))) | E48: =IF($R48="","",IF(INDEX('_list'!$F$2:$F$652,$R48)="","",INDEX('_list'!$F$2:$F$652,$R48))) | F48: =IF($R48="","",IF(INDEX('_list'!$G$2:$G$652,$R48)="","",INDEX('_list'!$G$2:$G$652,$R48))) | G48: =IF($S48="","",IF(INDEX('_pockets'!$AH:$AH,$S48)="","",INDEX('_pockets'!$AH:$AH,$S48))) | H48: =IF($S48="","",IF(INDEX('_pockets'!$AF:$AF,$S48)="","",INDEX('_pockets'!$AF:$AF,$S48))) | I48: =IF(IF($S48="","",IF(INDEX('_pockets'!$AB:$AB,$S48)="","",INDEX('_pockets'!$AB:$AB,$S48)))="","",IF($S48="","",IF(INDEX('_pockets'!$AB:$AB,$S48)="","",INDEX('_pockets'!$AB:$AB,$S48)))*IF($U$19,100,1)) | J48: =IF($S48="","",IF(INDEX('_pockets'!$Z:$Z,$S48)="","",INDEX('_pockets'!$Z:$Z,$S48))) | K48: =IF($R48="","",IF(INDEX('_list'!$K$2:$K$652,$R48)="","",INDEX('_list'!$K$2:$K$652,$R48))) | L48: =IF($S48="","",IF(INDEX('_pockets'!$AC:$AC,$S48)="","",INDEX('_pockets'!$AC:$AC,$S48))) | M48: =IF($R48="","",IF(INDEX('_list'!$L$2:$L$652,$R48)="","",INDEX('_list'!$L$2:$L$652,$R48))) | N48: =IF($R48="","",IF(INDEX('_list'!$H$2:$H$652,$R48)="","",INDEX('_list'!$H$2:$H$652,$R48))) | O48: =IF($R48="","",IF(INDEX('_list'!$I$2:$I$652,$R48)="","",INDEX('_list'!$I$2:$I$652,$R48))) | R48: =IFERROR(MATCH(28,'_list'!$N$2:$N$652,0),"") | S48: =IF($R48="","",INDEX('_list'!$C$2:$C$652,$R48))
B49: =IF($R49="","",29) | C49: =IF($R49="","",IF(INDEX('_list'!$D$2:$D$652,$R49)="","",INDEX('_list'!$D$2:$D$652,$R49))) | D49: =IF($R49="","",IF(INDEX('_list'!$E$2:$E$652,$R49)="","",INDEX('_list'!$E$2:$E$652,$R49))) | E49: =IF($R49="","",IF(INDEX('_list'!$F$2:$F$652,$R49)="","",INDEX('_list'!$F$2:$F$652,$R49))) | F49: =IF($R49="","",IF(INDEX('_list'!$G$2:$G$652,$R49)="","",INDEX('_list'!$G$2:$G$652,$R49))) | G49: =IF($S49="","",IF(INDEX('_pockets'!$AH:$AH,$S49)="","",INDEX('_pockets'!$AH:$AH,$S49))) | H49: =IF($S49="","",IF(INDEX('_pockets'!$AF:$AF,$S49)="","",INDEX('_pockets'!$AF:$AF,$S49))) | I49: =IF(IF($S49="","",IF(INDEX('_pockets'!$AB:$AB,$S49)="","",INDEX('_pockets'!$AB:$AB,$S49)))="","",IF($S49="","",IF(INDEX('_pockets'!$AB:$AB,$S49)="","",INDEX('_pockets'!$AB:$AB,$S49)))*IF($U$19,100,1)) | J49: =IF($S49="","",IF(INDEX('_pockets'!$Z:$Z,$S49)="","",INDEX('_pockets'!$Z:$Z,$S49))) | K49: =IF($R49="","",IF(INDEX('_list'!$K$2:$K$652,$R49)="","",INDEX('_list'!$K$2:$K$652,$R49))) | L49: =IF($S49="","",IF(INDEX('_pockets'!$AC:$AC,$S49)="","",INDEX('_pockets'!$AC:$AC,$S49))) | M49: =IF($R49="","",IF(INDEX('_list'!$L$2:$L$652,$R49)="","",INDEX('_list'!$L$2:$L$652,$R49))) | N49: =IF($R49="","",IF(INDEX('_list'!$H$2:$H$652,$R49)="","",INDEX('_list'!$H$2:$H$652,$R49))) | O49: =IF($R49="","",IF(INDEX('_list'!$I$2:$I$652,$R49)="","",INDEX('_list'!$I$2:$I$652,$R49))) | R49: =IFERROR(MATCH(29,'_list'!$N$2:$N$652,0),"") | S49: =IF($R49="","",INDEX('_list'!$C$2:$C$652,$R49))
B50: =IF($R50="","",30) | C50: =IF($R50="","",IF(INDEX('_list'!$D$2:$D$652,$R50)="","",INDEX('_list'!$D$2:$D$652,$R50))) | D50: =IF($R50="","",IF(INDEX('_list'!$E$2:$E$652,$R50)="","",INDEX('_list'!$E$2:$E$652,$R50))) | E50: =IF($R50="","",IF(INDEX('_list'!$F$2:$F$652,$R50)="","",INDEX('_list'!$F$2:$F$652,$R50))) | F50: =IF($R50="","",IF(INDEX('_list'!$G$2:$G$652,$R50)="","",INDEX('_list'!$G$2:$G$652,$R50))) | G50: =IF($S50="","",IF(INDEX('_pockets'!$AH:$AH,$S50)="","",INDEX('_pockets'!$AH:$AH,$S50))) | H50: =IF($S50="","",IF(INDEX('_pockets'!$AF:$AF,$S50)="","",INDEX('_pockets'!$AF:$AF,$S50))) | I50: =IF(IF($S50="","",IF(INDEX('_pockets'!$AB:$AB,$S50)="","",INDEX('_pockets'!$AB:$AB,$S50)))="","",IF($S50="","",IF(INDEX('_pockets'!$AB:$AB,$S50)="","",INDEX('_pockets'!$AB:$AB,$S50)))*IF($U$19,100,1)) | J50: =IF($S50="","",IF(INDEX('_pockets'!$Z:$Z,$S50)="","",INDEX('_pockets'!$Z:$Z,$S50))) | K50: =IF($R50="","",IF(INDEX('_list'!$K$2:$K$652,$R50)="","",INDEX('_list'!$K$2:$K$652,$R50))) | L50: =IF($S50="","",IF(INDEX('_pockets'!$AC:$AC,$S50)="","",INDEX('_pockets'!$AC:$AC,$S50))) | M50: =IF($R50="","",IF(INDEX('_list'!$L$2:$L$652,$R50)="","",INDEX('_list'!$L$2:$L$652,$R50))) | N50: =IF($R50="","",IF(INDEX('_list'!$H$2:$H$652,$R50)="","",INDEX('_list'!$H$2:$H$652,$R50))) | O50: =IF($R50="","",IF(INDEX('_list'!$I$2:$I$652,$R50)="","",INDEX('_list'!$I$2:$I$652,$R50))) | R50: =IFERROR(MATCH(30,'_list'!$N$2:$N$652,0),"") | S50: =IF($R50="","",INDEX('_list'!$C$2:$C$652,$R50))
B51: =IF($R51="","",31) | C51: =IF($R51="","",IF(INDEX('_list'!$D$2:$D$652,$R51)="","",INDEX('_list'!$D$2:$D$652,$R51))) | D51: =IF($R51="","",IF(INDEX('_list'!$E$2:$E$652,$R51)="","",INDEX('_list'!$E$2:$E$652,$R51))) | E51: =IF($R51="","",IF(INDEX('_list'!$F$2:$F$652,$R51)="","",INDEX('_list'!$F$2:$F$652,$R51))) | F51: =IF($R51="","",IF(INDEX('_list'!$G$2:$G$652,$R51)="","",INDEX('_list'!$G$2:$G$652,$R51))) | G51: =IF($S51="","",IF(INDEX('_pockets'!$AH:$AH,$S51)="","",INDEX('_pockets'!$AH:$AH,$S51))) | H51: =IF($S51="","",IF(INDEX('_pockets'!$AF:$AF,$S51)="","",INDEX('_pockets'!$AF:$AF,$S51))) | I51: =IF(IF($S51="","",IF(INDEX('_pockets'!$AB:$AB,$S51)="","",INDEX('_pockets'!$AB:$AB,$S51)))="","",IF($S51="","",IF(INDEX('_pockets'!$AB:$AB,$S51)="","",INDEX('_pockets'!$AB:$AB,$S51)))*IF($U$19,100,1)) | J51: =IF($S51="","",IF(INDEX('_pockets'!$Z:$Z,$S51)="","",INDEX('_pockets'!$Z:$Z,$S51))) | K51: =IF($R51="","",IF(INDEX('_list'!$K$2:$K$652,$R51)="","",INDEX('_list'!$K$2:$K$652,$R51))) | L51: =IF($S51="","",IF(INDEX('_pockets'!$AC:$AC,$S51)="","",INDEX('_pockets'!$AC:$AC,$S51))) | M51: =IF($R51="","",IF(INDEX('_list'!$L$2:$L$652,$R51)="","",INDEX('_list'!$L$2:$L$652,$R51))) | N51: =IF($R51="","",IF(INDEX('_list'!$H$2:$H$652,$R51)="","",INDEX('_list'!$H$2:$H$652,$R51))) | O51: =IF($R51="","",IF(INDEX('_list'!$I$2:$I$652,$R51)="","",INDEX('_list'!$I$2:$I$652,$R51))) | R51: =IFERROR(MATCH(31,'_list'!$N$2:$N$652,0),"") | S51: =IF($R51="","",INDEX('_list'!$C$2:$C$652,$R51))
B52: =IF($R52="","",32) | C52: =IF($R52="","",IF(INDEX('_list'!$D$2:$D$652,$R52)="","",INDEX('_list'!$D$2:$D$652,$R52))) | D52: =IF($R52="","",IF(INDEX('_list'!$E$2:$E$652,$R52)="","",INDEX('_list'!$E$2:$E$652,$R52))) | E52: =IF($R52="","",IF(INDEX('_list'!$F$2:$F$652,$R52)="","",INDEX('_list'!$F$2:$F$652,$R52))) | F52: =IF($R52="","",IF(INDEX('_list'!$G$2:$G$652,$R52)="","",INDEX('_list'!$G$2:$G$652,$R52))) | G52: =IF($S52="","",IF(INDEX('_pockets'!$AH:$AH,$S52)="","",INDEX('_pockets'!$AH:$AH,$S52))) | H52: =IF($S52="","",IF(INDEX('_pockets'!$AF:$AF,$S52)="","",INDEX('_pockets'!$AF:$AF,$S52))) | I52: =IF(IF($S52="","",IF(INDEX('_pockets'!$AB:$AB,$S52)="","",INDEX('_pockets'!$AB:$AB,$S52)))="","",IF($S52="","",IF(INDEX('_pockets'!$AB:$AB,$S52)="","",INDEX('_pockets'!$AB:$AB,$S52)))*IF($U$19,100,1)) | J52: =IF($S52="","",IF(INDEX('_pockets'!$Z:$Z,$S52)="","",INDEX('_pockets'!$Z:$Z,$S52))) | K52: =IF($R52="","",IF(INDEX('_list'!$K$2:$K$652,$R52)="","",INDEX('_list'!$K$2:$K$652,$R52))) | L52: =IF($S52="","",IF(INDEX('_pockets'!$AC:$AC,$S52)="","",INDEX('_pockets'!$AC:$AC,$S52))) | M52: =IF($R52="","",IF(INDEX('_list'!$L$2:$L$652,$R52)="","",INDEX('_list'!$L$2:$L$652,$R52))) | N52: =IF($R52="","",IF(INDEX('_list'!$H$2:$H$652,$R52)="","",INDEX('_list'!$H$2:$H$652,$R52))) | O52: =IF($R52="","",IF(INDEX('_list'!$I$2:$I$652,$R52)="","",INDEX('_list'!$I$2:$I$652,$R52))) | R52: =IFERROR(MATCH(32,'_list'!$N$2:$N$652,0),"") | S52: =IF($R52="","",INDEX('_list'!$C$2:$C$652,$R52))
B53: =IF($R53="","",33) | C53: =IF($R53="","",IF(INDEX('_list'!$D$2:$D$652,$R53)="","",INDEX('_list'!$D$2:$D$652,$R53))) | D53: =IF($R53="","",IF(INDEX('_list'!$E$2:$E$652,$R53)="","",INDEX('_list'!$E$2:$E$652,$R53))) | E53: =IF($R53="","",IF(INDEX('_list'!$F$2:$F$652,$R53)="","",INDEX('_list'!$F$2:$F$652,$R53))) | F53: =IF($R53="","",IF(INDEX('_list'!$G$2:$G$652,$R53)="","",INDEX('_list'!$G$2:$G$652,$R53))) | G53: =IF($S53="","",IF(INDEX('_pockets'!$AH:$AH,$S53)="","",INDEX('_pockets'!$AH:$AH,$S53))) | H53: =IF($S53="","",IF(INDEX('_pockets'!$AF:$AF,$S53)="","",INDEX('_pockets'!$AF:$AF,$S53))) | I53: =IF(IF($S53="","",IF(INDEX('_pockets'!$AB:$AB,$S53)="","",INDEX('_pockets'!$AB:$AB,$S53)))="","",IF($S53="","",IF(INDEX('_pockets'!$AB:$AB,$S53)="","",INDEX('_pockets'!$AB:$AB,$S53)))*IF($U$19,100,1)) | J53: =IF($S53="","",IF(INDEX('_pockets'!$Z:$Z,$S53)="","",INDEX('_pockets'!$Z:$Z,$S53))) | K53: =IF($R53="","",IF(INDEX('_list'!$K$2:$K$652,$R53)="","",INDEX('_list'!$K$2:$K$652,$R53))) | L53: =IF($S53="","",IF(INDEX('_pockets'!$AC:$AC,$S53)="","",INDEX('_pockets'!$AC:$AC,$S53))) | M53: =IF($R53="","",IF(INDEX('_list'!$L$2:$L$652,$R53)="","",INDEX('_list'!$L$2:$L$652,$R53))) | N53: =IF($R53="","",IF(INDEX('_list'!$H$2:$H$652,$R53)="","",INDEX('_list'!$H$2:$H$652,$R53))) | O53: =IF($R53="","",IF(INDEX('_list'!$I$2:$I$652,$R53)="","",INDEX('_list'!$I$2:$I$652,$R53))) | R53: =IFERROR(MATCH(33,'_list'!$N$2:$N$652,0),"") | S53: =IF($R53="","",INDEX('_list'!$C$2:$C$652,$R53))
B54: =IF($R54="","",34) | C54: =IF($R54="","",IF(INDEX('_list'!$D$2:$D$652,$R54)="","",INDEX('_list'!$D$2:$D$652,$R54))) | D54: =IF($R54="","",IF(INDEX('_list'!$E$2:$E$652,$R54)="","",INDEX('_list'!$E$2:$E$652,$R54))) | E54: =IF($R54="","",IF(INDEX('_list'!$F$2:$F$652,$R54)="","",INDEX('_list'!$F$2:$F$652,$R54))) | F54: =IF($R54="","",IF(INDEX('_list'!$G$2:$G$652,$R54)="","",INDEX('_list'!$G$2:$G$652,$R54))) | G54: =IF($S54="","",IF(INDEX('_pockets'!$AH:$AH,$S54)="","",INDEX('_pockets'!$AH:$AH,$S54))) | H54: =IF($S54="","",IF(INDEX('_pockets'!$AF:$AF,$S54)="","",INDEX('_pockets'!$AF:$AF,$S54))) | I54: =IF(IF($S54="","",IF(INDEX('_pockets'!$AB:$AB,$S54)="","",INDEX('_pockets'!$AB:$AB,$S54)))="","",IF($S54="","",IF(INDEX('_pockets'!$AB:$AB,$S54)="","",INDEX('_pockets'!$AB:$AB,$S54)))*IF($U$19,100,1)) | J54: =IF($S54="","",IF(INDEX('_pockets'!$Z:$Z,$S54)="","",INDEX('_pockets'!$Z:$Z,$S54))) | K54: =IF($R54="","",IF(INDEX('_list'!$K$2:$K$652,$R54)="","",INDEX('_list'!$K$2:$K$652,$R54))) | L54: =IF($S54="","",IF(INDEX('_pockets'!$AC:$AC,$S54)="","",INDEX('_pockets'!$AC:$AC,$S54))) | M54: =IF($R54="","",IF(INDEX('_list'!$L$2:$L$652,$R54)="","",INDEX('_list'!$L$2:$L$652,$R54))) | N54: =IF($R54="","",IF(INDEX('_list'!$H$2:$H$652,$R54)="","",INDEX('_list'!$H$2:$H$652,$R54))) | O54: =IF($R54="","",IF(INDEX('_list'!$I$2:$I$652,$R54)="","",INDEX('_list'!$I$2:$I$652,$R54))) | R54: =IFERROR(MATCH(34,'_list'!$N$2:$N$652,0),"") | S54: =IF($R54="","",INDEX('_list'!$C$2:$C$652,$R54))
B55: =IF($R55="","",35) | C55: =IF($R55="","",IF(INDEX('_list'!$D$2:$D$652,$R55)="","",INDEX('_list'!$D$2:$D$652,$R55))) | D55: =IF($R55="","",IF(INDEX('_list'!$E$2:$E$652,$R55)="","",INDEX('_list'!$E$2:$E$652,$R55))) | E55: =IF($R55="","",IF(INDEX('_list'!$F$2:$F$652,$R55)="","",INDEX('_list'!$F$2:$F$652,$R55))) | F55: =IF($R55="","",IF(INDEX('_list'!$G$2:$G$652,$R55)="","",INDEX('_list'!$G$2:$G$652,$R55))) | G55: =IF($S55="","",IF(INDEX('_pockets'!$AH:$AH,$S55)="","",INDEX('_pockets'!$AH:$AH,$S55))) | H55: =IF($S55="","",IF(INDEX('_pockets'!$AF:$AF,$S55)="","",INDEX('_pockets'!$AF:$AF,$S55))) | I55: =IF(IF($S55="","",IF(INDEX('_pockets'!$AB:$AB,$S55)="","",INDEX('_pockets'!$AB:$AB,$S55)))="","",IF($S55="","",IF(INDEX('_pockets'!$AB:$AB,$S55)="","",INDEX('_pockets'!$AB:$AB,$S55)))*IF($U$19,100,1)) | J55: =IF($S55="","",IF(INDEX('_pockets'!$Z:$Z,$S55)="","",INDEX('_pockets'!$Z:$Z,$S55))) | K55: =IF($R55="","",IF(INDEX('_list'!$K$2:$K$652,$R55)="","",INDEX('_list'!$K$2:$K$652,$R55))) | L55: =IF($S55="","",IF(INDEX('_pockets'!$AC:$AC,$S55)="","",INDEX('_pockets'!$AC:$AC,$S55))) | M55: =IF($R55="","",IF(INDEX('_list'!$L$2:$L$652,$R55)="","",INDEX('_list'!$L$2:$L$652,$R55))) | N55: =IF($R55="","",IF(INDEX('_list'!$H$2:$H$652,$R55)="","",INDEX('_list'!$H$2:$H$652,$R55))) | O55: =IF($R55="","",IF(INDEX('_list'!$I$2:$I$652,$R55)="","",INDEX('_list'!$I$2:$I$652,$R55))) | R55: =IFERROR(MATCH(35,'_list'!$N$2:$N$652,0),"") | S55: =IF($R55="","",INDEX('_list'!$C$2:$C$652,$R55))
B56: =IF($R56="","",36) | C56: =IF($R56="","",IF(INDEX('_list'!$D$2:$D$652,$R56)="","",INDEX('_list'!$D$2:$D$652,$R56))) | D56: =IF($R56="","",IF(INDEX('_list'!$E$2:$E$652,$R56)="","",INDEX('_list'!$E$2:$E$652,$R56))) | E56: =IF($R56="","",IF(INDEX('_list'!$F$2:$F$652,$R56)="","",INDEX('_list'!$F$2:$F$652,$R56))) | F56: =IF($R56="","",IF(INDEX('_list'!$G$2:$G$652,$R56)="","",INDEX('_list'!$G$2:$G$652,$R56))) | G56: =IF($S56="","",IF(INDEX('_pockets'!$AH:$AH,$S56)="","",INDEX('_pockets'!$AH:$AH,$S56))) | H56: =IF($S56="","",IF(INDEX('_pockets'!$AF:$AF,$S56)="","",INDEX('_pockets'!$AF:$AF,$S56))) | I56: =IF(IF($S56="","",IF(INDEX('_pockets'!$AB:$AB,$S56)="","",INDEX('_pockets'!$AB:$AB,$S56)))="","",IF($S56="","",IF(INDEX('_pockets'!$AB:$AB,$S56)="","",INDEX('_pockets'!$AB:$AB,$S56)))*IF($U$19,100,1)) | J56: =IF($S56="","",IF(INDEX('_pockets'!$Z:$Z,$S56)="","",INDEX('_pockets'!$Z:$Z,$S56))) | K56: =IF($R56="","",IF(INDEX('_list'!$K$2:$K$652,$R56)="","",INDEX('_list'!$K$2:$K$652,$R56))) | L56: =IF($S56="","",IF(INDEX('_pockets'!$AC:$AC,$S56)="","",INDEX('_pockets'!$AC:$AC,$S56))) | M56: =IF($R56="","",IF(INDEX('_list'!$L$2:$L$652,$R56)="","",INDEX('_list'!$L$2:$L$652,$R56))) | N56: =IF($R56="","",IF(INDEX('_list'!$H$2:$H$652,$R56)="","",INDEX('_list'!$H$2:$H$652,$R56))) | O56: =IF($R56="","",IF(INDEX('_list'!$I$2:$I$652,$R56)="","",INDEX('_list'!$I$2:$I$652,$R56))) | R56: =IFERROR(MATCH(36,'_list'!$N$2:$N$652,0),"") | S56: =IF($R56="","",INDEX('_list'!$C$2:$C$652,$R56))
B57: =IF($R57="","",37) | C57: =IF($R57="","",IF(INDEX('_list'!$D$2:$D$652,$R57)="","",INDEX('_list'!$D$2:$D$652,$R57))) | D57: =IF($R57="","",IF(INDEX('_list'!$E$2:$E$652,$R57)="","",INDEX('_list'!$E$2:$E$652,$R57))) | E57: =IF($R57="","",IF(INDEX('_list'!$F$2:$F$652,$R57)="","",INDEX('_list'!$F$2:$F$652,$R57))) | F57: =IF($R57="","",IF(INDEX('_list'!$G$2:$G$652,$R57)="","",INDEX('_list'!$G$2:$G$652,$R57))) | G57: =IF($S57="","",IF(INDEX('_pockets'!$AH:$AH,$S57)="","",INDEX('_pockets'!$AH:$AH,$S57))) | H57: =IF($S57="","",IF(INDEX('_pockets'!$AF:$AF,$S57)="","",INDEX('_pockets'!$AF:$AF,$S57))) | I57: =IF(IF($S57="","",IF(INDEX('_pockets'!$AB:$AB,$S57)="","",INDEX('_pockets'!$AB:$AB,$S57)))="","",IF($S57="","",IF(INDEX('_pockets'!$AB:$AB,$S57)="","",INDEX('_pockets'!$AB:$AB,$S57)))*IF($U$19,100,1)) | J57: =IF($S57="","",IF(INDEX('_pockets'!$Z:$Z,$S57)="","",INDEX('_pockets'!$Z:$Z,$S57))) | K57: =IF($R57="","",IF(INDEX('_list'!$K$2:$K$652,$R57)="","",INDEX('_list'!$K$2:$K$652,$R57))) | L57: =IF($S57="","",IF(INDEX('_pockets'!$AC:$AC,$S57)="","",INDEX('_pockets'!$AC:$AC,$S57))) | M57: =IF($R57="","",IF(INDEX('_list'!$L$2:$L$652,$R57)="","",INDEX('_list'!$L$2:$L$652,$R57))) | N57: =IF($R57="","",IF(INDEX('_list'!$H$2:$H$652,$R57)="","",INDEX('_list'!$H$2:$H$652,$R57))) | O57: =IF($R57="","",IF(INDEX('_list'!$I$2:$I$652,$R57)="","",INDEX('_list'!$I$2:$I$652,$R57))) | R57: =IFERROR(MATCH(37,'_list'!$N$2:$N$652,0),"") | S57: =IF($R57="","",INDEX('_list'!$C$2:$C$652,$R57))
B58: =IF($R58="","",38) | C58: =IF($R58="","",IF(INDEX('_list'!$D$2:$D$652,$R58)="","",INDEX('_list'!$D$2:$D$652,$R58))) | D58: =IF($R58="","",IF(INDEX('_list'!$E$2:$E$652,$R58)="","",INDEX('_list'!$E$2:$E$652,$R58))) | E58: =IF($R58="","",IF(INDEX('_list'!$F$2:$F$652,$R58)="","",INDEX('_list'!$F$2:$F$652,$R58))) | F58: =IF($R58="","",IF(INDEX('_list'!$G$2:$G$652,$R58)="","",INDEX('_list'!$G$2:$G$652,$R58))) | G58: =IF($S58="","",IF(INDEX('_pockets'!$AH:$AH,$S58)="","",INDEX('_pockets'!$AH:$AH,$S58))) | H58: =IF($S58="","",IF(INDEX('_pockets'!$AF:$AF,$S58)="","",INDEX('_pockets'!$AF:$AF,$S58))) | I58: =IF(IF($S58="","",IF(INDEX('_pockets'!$AB:$AB,$S58)="","",INDEX('_pockets'!$AB:$AB,$S58)))="","",IF($S58="","",IF(INDEX('_pockets'!$AB:$AB,$S58)="","",INDEX('_pockets'!$AB:$AB,$S58)))*IF($U$19,100,1)) | J58: =IF($S58="","",IF(INDEX('_pockets'!$Z:$Z,$S58)="","",INDEX('_pockets'!$Z:$Z,$S58))) | K58: =IF($R58="","",IF(INDEX('_list'!$K$2:$K$652,$R58)="","",INDEX('_list'!$K$2:$K$652,$R58))) | L58: =IF($S58="","",IF(INDEX('_pockets'!$AC:$AC,$S58)="","",INDEX('_pockets'!$AC:$AC,$S58))) | M58: =IF($R58="","",IF(INDEX('_list'!$L$2:$L$652,$R58)="","",INDEX('_list'!$L$2:$L$652,$R58))) | N58: =IF($R58="","",IF(INDEX('_list'!$H$2:$H$652,$R58)="","",INDEX('_list'!$H$2:$H$652,$R58))) | O58: =IF($R58="","",IF(INDEX('_list'!$I$2:$I$652,$R58)="","",INDEX('_list'!$I$2:$I$652,$R58))) | R58: =IFERROR(MATCH(38,'_list'!$N$2:$N$652,0),"") | S58: =IF($R58="","",INDEX('_list'!$C$2:$C$652,$R58))
B59: =IF($R59="","",39) | C59: =IF($R59="","",IF(INDEX('_list'!$D$2:$D$652,$R59)="","",INDEX('_list'!$D$2:$D$652,$R59))) | D59: =IF($R59="","",IF(INDEX('_list'!$E$2:$E$652,$R59)="","",INDEX('_list'!$E$2:$E$652,$R59))) | E59: =IF($R59="","",IF(INDEX('_list'!$F$2:$F$652,$R59)="","",INDEX('_list'!$F$2:$F$652,$R59))) | F59: =IF($R59="","",IF(INDEX('_list'!$G$2:$G$652,$R59)="","",INDEX('_list'!$G$2:$G$652,$R59))) | G59: =IF($S59="","",IF(INDEX('_pockets'!$AH:$AH,$S59)="","",INDEX('_pockets'!$AH:$AH,$S59))) | H59: =IF($S59="","",IF(INDEX('_pockets'!$AF:$AF,$S59)="","",INDEX('_pockets'!$AF:$AF,$S59))) | I59: =IF(IF($S59="","",IF(INDEX('_pockets'!$AB:$AB,$S59)="","",INDEX('_pockets'!$AB:$AB,$S59)))="","",IF($S59="","",IF(INDEX('_pockets'!$AB:$AB,$S59)="","",INDEX('_pockets'!$AB:$AB,$S59)))*IF($U$19,100,1)) | J59: =IF($S59="","",IF(INDEX('_pockets'!$Z:$Z,$S59)="","",INDEX('_pockets'!$Z:$Z,$S59))) | K59: =IF($R59="","",IF(INDEX('_list'!$K$2:$K$652,$R59)="","",INDEX('_list'!$K$2:$K$652,$R59))) | L59: =IF($S59="","",IF(INDEX('_pockets'!$AC:$AC,$S59)="","",INDEX('_pockets'!$AC:$AC,$S59))) | M59: =IF($R59="","",IF(INDEX('_list'!$L$2:$L$652,$R59)="","",INDEX('_list'!$L$2:$L$652,$R59))) | N59: =IF($R59="","",IF(INDEX('_list'!$H$2:$H$652,$R59)="","",INDEX('_list'!$H$2:$H$652,$R59))) | O59: =IF($R59="","",IF(INDEX('_list'!$I$2:$I$652,$R59)="","",INDEX('_list'!$I$2:$I$652,$R59))) | R59: =IFERROR(MATCH(39,'_list'!$N$2:$N$652,0),"") | S59: =IF($R59="","",INDEX('_list'!$C$2:$C$652,$R59))
B60: =IF($R60="","",40) | C60: =IF($R60="","",IF(INDEX('_list'!$D$2:$D$652,$R60)="","",INDEX('_list'!$D$2:$D$652,$R60))) | D60: =IF($R60="","",IF(INDEX('_list'!$E$2:$E$652,$R60)="","",INDEX('_list'!$E$2:$E$652,$R60))) | E60: =IF($R60="","",IF(INDEX('_list'!$F$2:$F$652,$R60)="","",INDEX('_list'!$F$2:$F$652,$R60))) | F60: =IF($R60="","",IF(INDEX('_list'!$G$2:$G$652,$R60)="","",INDEX('_list'!$G$2:$G$652,$R60))) | G60: =IF($S60="","",IF(INDEX('_pockets'!$AH:$AH,$S60)="","",INDEX('_pockets'!$AH:$AH,$S60))) | H60: =IF($S60="","",IF(INDEX('_pockets'!$AF:$AF,$S60)="","",INDEX('_pockets'!$AF:$AF,$S60))) | I60: =IF(IF($S60="","",IF(INDEX('_pockets'!$AB:$AB,$S60)="","",INDEX('_pockets'!$AB:$AB,$S60)))="","",IF($S60="","",IF(INDEX('_pockets'!$AB:$AB,$S60)="","",INDEX('_pockets'!$AB:$AB,$S60)))*IF($U$19,100,1)) | J60: =IF($S60="","",IF(INDEX('_pockets'!$Z:$Z,$S60)="","",INDEX('_pockets'!$Z:$Z,$S60))) | K60: =IF($R60="","",IF(INDEX('_list'!$K$2:$K$652,$R60)="","",INDEX('_list'!$K$2:$K$652,$R60))) | L60: =IF($S60="","",IF(INDEX('_pockets'!$AC:$AC,$S60)="","",INDEX('_pockets'!$AC:$AC,$S60))) | M60: =IF($R60="","",IF(INDEX('_list'!$L$2:$L$652,$R60)="","",INDEX('_list'!$L$2:$L$652,$R60))) | N60: =IF($R60="","",IF(INDEX('_list'!$H$2:$H$652,$R60)="","",INDEX('_list'!$H$2:$H$652,$R60))) | O60: =IF($R60="","",IF(INDEX('_list'!$I$2:$I$652,$R60)="","",INDEX('_list'!$I$2:$I$652,$R60))) | R60: =IFERROR(MATCH(40,'_list'!$N$2:$N$652,0),"") | S60: =IF($R60="","",INDEX('_list'!$C$2:$C$652,$R60))
B61: =IF($R61="","",41) | C61: =IF($R61="","",IF(INDEX('_list'!$D$2:$D$652,$R61)="","",INDEX('_list'!$D$2:$D$652,$R61))) | D61: =IF($R61="","",IF(INDEX('_list'!$E$2:$E$652,$R61)="","",INDEX('_list'!$E$2:$E$652,$R61))) | E61: =IF($R61="","",IF(INDEX('_list'!$F$2:$F$652,$R61)="","",INDEX('_list'!$F$2:$F$652,$R61))) | F61: =IF($R61="","",IF(INDEX('_list'!$G$2:$G$652,$R61)="","",INDEX('_list'!$G$2:$G$652,$R61))) | G61: =IF($S61="","",IF(INDEX('_pockets'!$AH:$AH,$S61)="","",INDEX('_pockets'!$AH:$AH,$S61))) | H61: =IF($S61="","",IF(INDEX('_pockets'!$AF:$AF,$S61)="","",INDEX('_pockets'!$AF:$AF,$S61))) | I61: =IF(IF($S61="","",IF(INDEX('_pockets'!$AB:$AB,$S61)="","",INDEX('_pockets'!$AB:$AB,$S61)))="","",IF($S61="","",IF(INDEX('_pockets'!$AB:$AB,$S61)="","",INDEX('_pockets'!$AB:$AB,$S61)))*IF($U$19,100,1)) | J61: =IF($S61="","",IF(INDEX('_pockets'!$Z:$Z,$S61)="","",INDEX('_pockets'!$Z:$Z,$S61))) | K61: =IF($R61="","",IF(INDEX('_list'!$K$2:$K$652,$R61)="","",INDEX('_list'!$K$2:$K$652,$R61))) | L61: =IF($S61="","",IF(INDEX('_pockets'!$AC:$AC,$S61)="","",INDEX('_pockets'!$AC:$AC,$S61))) | M61: =IF($R61="","",IF(INDEX('_list'!$L$2:$L$652,$R61)="","",INDEX('_list'!$L$2:$L$652,$R61))) | N61: =IF($R61="","",IF(INDEX('_list'!$H$2:$H$652,$R61)="","",INDEX('_list'!$H$2:$H$652,$R61))) | O61: =IF($R61="","",IF(INDEX('_list'!$I$2:$I$652,$R61)="","",INDEX('_list'!$I$2:$I$652,$R61))) | R61: =IFERROR(MATCH(41,'_list'!$N$2:$N$652,0),"") | S61: =IF($R61="","",INDEX('_list'!$C$2:$C$652,$R61))
B62: =IF($R62="","",42) | C62: =IF($R62="","",IF(INDEX('_list'!$D$2:$D$652,$R62)="","",INDEX('_list'!$D$2:$D$652,$R62))) | D62: =IF($R62="","",IF(INDEX('_list'!$E$2:$E$652,$R62)="","",INDEX('_list'!$E$2:$E$652,$R62))) | E62: =IF($R62="","",IF(INDEX('_list'!$F$2:$F$652,$R62)="","",INDEX('_list'!$F$2:$F$652,$R62))) | F62: =IF($R62="","",IF(INDEX('_list'!$G$2:$G$652,$R62)="","",INDEX('_list'!$G$2:$G$652,$R62))) | G62: =IF($S62="","",IF(INDEX('_pockets'!$AH:$AH,$S62)="","",INDEX('_pockets'!$AH:$AH,$S62))) | H62: =IF($S62="","",IF(INDEX('_pockets'!$AF:$AF,$S62)="","",INDEX('_pockets'!$AF:$AF,$S62))) | I62: =IF(IF($S62="","",IF(INDEX('_pockets'!$AB:$AB,$S62)="","",INDEX('_pockets'!$AB:$AB,$S62)))="","",IF($S62="","",IF(INDEX('_pockets'!$AB:$AB,$S62)="","",INDEX('_pockets'!$AB:$AB,$S62)))*IF($U$19,100,1)) | J62: =IF($S62="","",IF(INDEX('_pockets'!$Z:$Z,$S62)="","",INDEX('_pockets'!$Z:$Z,$S62))) | K62: =IF($R62="","",IF(INDEX('_list'!$K$2:$K$652,$R62)="","",INDEX('_list'!$K$2:$K$652,$R62))) | L62: =IF($S62="","",IF(INDEX('_pockets'!$AC:$AC,$S62)="","",INDEX('_pockets'!$AC:$AC,$S62))) | M62: =IF($R62="","",IF(INDEX('_list'!$L$2:$L$652,$R62)="","",INDEX('_list'!$L$2:$L$652,$R62))) | N62: =IF($R62="","",IF(INDEX('_list'!$H$2:$H$652,$R62)="","",INDEX('_list'!$H$2:$H$652,$R62))) | O62: =IF($R62="","",IF(INDEX('_list'!$I$2:$I$652,$R62)="","",INDEX('_list'!$I$2:$I$652,$R62))) | R62: =IFERROR(MATCH(42,'_list'!$N$2:$N$652,0),"") | S62: =IF($R62="","",INDEX('_list'!$C$2:$C$652,$R62))
B63: =IF($R63="","",43) | C63: =IF($R63="","",IF(INDEX('_list'!$D$2:$D$652,$R63)="","",INDEX('_list'!$D$2:$D$652,$R63))) | D63: =IF($R63="","",IF(INDEX('_list'!$E$2:$E$652,$R63)="","",INDEX('_list'!$E$2:$E$652,$R63))) | E63: =IF($R63="","",IF(INDEX('_list'!$F$2:$F$652,$R63)="","",INDEX('_list'!$F$2:$F$652,$R63))) | F63: =IF($R63="","",IF(INDEX('_list'!$G$2:$G$652,$R63)="","",INDEX('_list'!$G$2:$G$652,$R63))) | G63: =IF($S63="","",IF(INDEX('_pockets'!$AH:$AH,$S63)="","",INDEX('_pockets'!$AH:$AH,$S63))) | H63: =IF($S63="","",IF(INDEX('_pockets'!$AF:$AF,$S63)="","",INDEX('_pockets'!$AF:$AF,$S63))) | I63: =IF(IF($S63="","",IF(INDEX('_pockets'!$AB:$AB,$S63)="","",INDEX('_pockets'!$AB:$AB,$S63)))="","",IF($S63="","",IF(INDEX('_pockets'!$AB:$AB,$S63)="","",INDEX('_pockets'!$AB:$AB,$S63)))*IF($U$19,100,1)) | J63: =IF($S63="","",IF(INDEX('_pockets'!$Z:$Z,$S63)="","",INDEX('_pockets'!$Z:$Z,$S63))) | K63: =IF($R63="","",IF(INDEX('_list'!$K$2:$K$652,$R63)="","",INDEX('_list'!$K$2:$K$652,$R63))) | L63: =IF($S63="","",IF(INDEX('_pockets'!$AC:$AC,$S63)="","",INDEX('_pockets'!$AC:$AC,$S63))) | M63: =IF($R63="","",IF(INDEX('_list'!$L$2:$L$652,$R63)="","",INDEX('_list'!$L$2:$L$652,$R63))) | N63: =IF($R63="","",IF(INDEX('_list'!$H$2:$H$652,$R63)="","",INDEX('_list'!$H$2:$H$652,$R63))) | O63: =IF($R63="","",IF(INDEX('_list'!$I$2:$I$652,$R63)="","",INDEX('_list'!$I$2:$I$652,$R63))) | R63: =IFERROR(MATCH(43,'_list'!$N$2:$N$652,0),"") | S63: =IF($R63="","",INDEX('_list'!$C$2:$C$652,$R63))
B64: =IF($R64="","",44) | C64: =IF($R64="","",IF(INDEX('_list'!$D$2:$D$652,$R64)="","",INDEX('_list'!$D$2:$D$652,$R64))) | D64: =IF($R64="","",IF(INDEX('_list'!$E$2:$E$652,$R64)="","",INDEX('_list'!$E$2:$E$652,$R64))) | E64: =IF($R64="","",IF(INDEX('_list'!$F$2:$F$652,$R64)="","",INDEX('_list'!$F$2:$F$652,$R64))) | F64: =IF($R64="","",IF(INDEX('_list'!$G$2:$G$652,$R64)="","",INDEX('_list'!$G$2:$G$652,$R64))) | G64: =IF($S64="","",IF(INDEX('_pockets'!$AH:$AH,$S64)="","",INDEX('_pockets'!$AH:$AH,$S64))) | H64: =IF($S64="","",IF(INDEX('_pockets'!$AF:$AF,$S64)="","",INDEX('_pockets'!$AF:$AF,$S64))) | I64: =IF(IF($S64="","",IF(INDEX('_pockets'!$AB:$AB,$S64)="","",INDEX('_pockets'!$AB:$AB,$S64)))="","",IF($S64="","",IF(INDEX('_pockets'!$AB:$AB,$S64)="","",INDEX('_pockets'!$AB:$AB,$S64)))*IF($U$19,100,1)) | J64: =IF($S64="","",IF(INDEX('_pockets'!$Z:$Z,$S64)="","",INDEX('_pockets'!$Z:$Z,$S64))) | K64: =IF($R64="","",IF(INDEX('_list'!$K$2:$K$652,$R64)="","",INDEX('_list'!$K$2:$K$652,$R64))) | L64: =IF($S64="","",IF(INDEX('_pockets'!$AC:$AC,$S64)="","",INDEX('_pockets'!$AC:$AC,$S64))) | M64: =IF($R64="","",IF(INDEX('_list'!$L$2:$L$652,$R64)="","",INDEX('_list'!$L$2:$L$652,$R64))) | N64: =IF($R64="","",IF(INDEX('_list'!$H$2:$H$652,$R64)="","",INDEX('_list'!$H$2:$H$652,$R64))) | O64: =IF($R64="","",IF(INDEX('_list'!$I$2:$I$652,$R64)="","",INDEX('_list'!$I$2:$I$652,$R64))) | R64: =IFERROR(MATCH(44,'_list'!$N$2:$N$652,0),"") | S64: =IF($R64="","",INDEX('_list'!$C$2:$C$652,$R64))
B65: =IF($R65="","",45) | C65: =IF($R65="","",IF(INDEX('_list'!$D$2:$D$652,$R65)="","",INDEX('_list'!$D$2:$D$652,$R65))) | D65: =IF($R65="","",IF(INDEX('_list'!$E$2:$E$652,$R65)="","",INDEX('_list'!$E$2:$E$652,$R65))) | E65: =IF($R65="","",IF(INDEX('_list'!$F$2:$F$652,$R65)="","",INDEX('_list'!$F$2:$F$652,$R65))) | F65: =IF($R65="","",IF(INDEX('_list'!$G$2:$G$652,$R65)="","",INDEX('_list'!$G$2:$G$652,$R65))) | G65: =IF($S65="","",IF(INDEX('_pockets'!$AH:$AH,$S65)="","",INDEX('_pockets'!$AH:$AH,$S65))) | H65: =IF($S65="","",IF(INDEX('_pockets'!$AF:$AF,$S65)="","",INDEX('_pockets'!$AF:$AF,$S65))) | I65: =IF(IF($S65="","",IF(INDEX('_pockets'!$AB:$AB,$S65)="","",INDEX('_pockets'!$AB:$AB,$S65)))="","",IF($S65="","",IF(INDEX('_pockets'!$AB:$AB,$S65)="","",INDEX('_pockets'!$AB:$AB,$S65)))*IF($U$19,100,1)) | J65: =IF($S65="","",IF(INDEX('_pockets'!$Z:$Z,$S65)="","",INDEX('_pockets'!$Z:$Z,$S65))) | K65: =IF($R65="","",IF(INDEX('_list'!$K$2:$K$652,$R65)="","",INDEX('_list'!$K$2:$K$652,$R65))) | L65: =IF($S65="","",IF(INDEX('_pockets'!$AC:$AC,$S65)="","",INDEX('_pockets'!$AC:$AC,$S65))) | M65: =IF($R65="","",IF(INDEX('_list'!$L$2:$L$652,$R65)="","",INDEX('_list'!$L$2:$L$652,$R65))) | N65: =IF($R65="","",IF(INDEX('_list'!$H$2:$H$652,$R65)="","",INDEX('_list'!$H$2:$H$652,$R65))) | O65: =IF($R65="","",IF(INDEX('_list'!$I$2:$I$652,$R65)="","",INDEX('_list'!$I$2:$I$652,$R65))) | R65: =IFERROR(MATCH(45,'_list'!$N$2:$N$652,0),"") | S65: =IF($R65="","",INDEX('_list'!$C$2:$C$652,$R65))
B66: =IF($R66="","",46) | C66: =IF($R66="","",IF(INDEX('_list'!$D$2:$D$652,$R66)="","",INDEX('_list'!$D$2:$D$652,$R66))) | D66: =IF($R66="","",IF(INDEX('_list'!$E$2:$E$652,$R66)="","",INDEX('_list'!$E$2:$E$652,$R66))) | E66: =IF($R66="","",IF(INDEX('_list'!$F$2:$F$652,$R66)="","",INDEX('_list'!$F$2:$F$652,$R66))) | F66: =IF($R66="","",IF(INDEX('_list'!$G$2:$G$652,$R66)="","",INDEX('_list'!$G$2:$G$652,$R66))) | G66: =IF($S66="","",IF(INDEX('_pockets'!$AH:$AH,$S66)="","",INDEX('_pockets'!$AH:$AH,$S66))) | H66: =IF($S66="","",IF(INDEX('_pockets'!$AF:$AF,$S66)="","",INDEX('_pockets'!$AF:$AF,$S66))) | I66: =IF(IF($S66="","",IF(INDEX('_pockets'!$AB:$AB,$S66)="","",INDEX('_pockets'!$AB:$AB,$S66)))="","",IF($S66="","",IF(INDEX('_pockets'!$AB:$AB,$S66)="","",INDEX('_pockets'!$AB:$AB,$S66)))*IF($U$19,100,1)) | J66: =IF($S66="","",IF(INDEX('_pockets'!$Z:$Z,$S66)="","",INDEX('_pockets'!$Z:$Z,$S66))) | K66: =IF($R66="","",IF(INDEX('_list'!$K$2:$K$652,$R66)="","",INDEX('_list'!$K$2:$K$652,$R66))) | L66: =IF($S66="","",IF(INDEX('_pockets'!$AC:$AC,$S66)="","",INDEX('_pockets'!$AC:$AC,$S66))) | M66: =IF($R66="","",IF(INDEX('_list'!$L$2:$L$652,$R66)="","",INDEX('_list'!$L$2:$L$652,$R66))) | N66: =IF($R66="","",IF(INDEX('_list'!$H$2:$H$652,$R66)="","",INDEX('_list'!$H$2:$H$652,$R66))) | O66: =IF($R66="","",IF(INDEX('_list'!$I$2:$I$652,$R66)="","",INDEX('_list'!$I$2:$I$652,$R66))) | R66: =IFERROR(MATCH(46,'_list'!$N$2:$N$652,0),"") | S66: =IF($R66="","",INDEX('_list'!$C$2:$C$652,$R66))
B67: =IF($R67="","",47) | C67: =IF($R67="","",IF(INDEX('_list'!$D$2:$D$652,$R67)="","",INDEX('_list'!$D$2:$D$652,$R67))) | D67: =IF($R67="","",IF(INDEX('_list'!$E$2:$E$652,$R67)="","",INDEX('_list'!$E$2:$E$652,$R67))) | E67: =IF($R67="","",IF(INDEX('_list'!$F$2:$F$652,$R67)="","",INDEX('_list'!$F$2:$F$652,$R67))) | F67: =IF($R67="","",IF(INDEX('_list'!$G$2:$G$652,$R67)="","",INDEX('_list'!$G$2:$G$652,$R67))) | G67: =IF($S67="","",IF(INDEX('_pockets'!$AH:$AH,$S67)="","",INDEX('_pockets'!$AH:$AH,$S67))) | H67: =IF($S67="","",IF(INDEX('_pockets'!$AF:$AF,$S67)="","",INDEX('_pockets'!$AF:$AF,$S67))) | I67: =IF(IF($S67="","",IF(INDEX('_pockets'!$AB:$AB,$S67)="","",INDEX('_pockets'!$AB:$AB,$S67)))="","",IF($S67="","",IF(INDEX('_pockets'!$AB:$AB,$S67)="","",INDEX('_pockets'!$AB:$AB,$S67)))*IF($U$19,100,1)) | J67: =IF($S67="","",IF(INDEX('_pockets'!$Z:$Z,$S67)="","",INDEX('_pockets'!$Z:$Z,$S67))) | K67: =IF($R67="","",IF(INDEX('_list'!$K$2:$K$652,$R67)="","",INDEX('_list'!$K$2:$K$652,$R67))) | L67: =IF($S67="","",IF(INDEX('_pockets'!$AC:$AC,$S67)="","",INDEX('_pockets'!$AC:$AC,$S67))) | M67: =IF($R67="","",IF(INDEX('_list'!$L$2:$L$652,$R67)="","",INDEX('_list'!$L$2:$L$652,$R67))) | N67: =IF($R67="","",IF(INDEX('_list'!$H$2:$H$652,$R67)="","",INDEX('_list'!$H$2:$H$652,$R67))) | O67: =IF($R67="","",IF(INDEX('_list'!$I$2:$I$652,$R67)="","",INDEX('_list'!$I$2:$I$652,$R67))) | R67: =IFERROR(MATCH(47,'_list'!$N$2:$N$652,0),"") | S67: =IF($R67="","",INDEX('_list'!$C$2:$C$652,$R67))
B68: =IF($R68="","",48) | C68: =IF($R68="","",IF(INDEX('_list'!$D$2:$D$652,$R68)="","",INDEX('_list'!$D$2:$D$652,$R68))) | D68: =IF($R68="","",IF(INDEX('_list'!$E$2:$E$652,$R68)="","",INDEX('_list'!$E$2:$E$652,$R68))) | E68: =IF($R68="","",IF(INDEX('_list'!$F$2:$F$652,$R68)="","",INDEX('_list'!$F$2:$F$652,$R68))) | F68: =IF($R68="","",IF(INDEX('_list'!$G$2:$G$652,$R68)="","",INDEX('_list'!$G$2:$G$652,$R68))) | G68: =IF($S68="","",IF(INDEX('_pockets'!$AH:$AH,$S68)="","",INDEX('_pockets'!$AH:$AH,$S68))) | H68: =IF($S68="","",IF(INDEX('_pockets'!$AF:$AF,$S68)="","",INDEX('_pockets'!$AF:$AF,$S68))) | I68: =IF(IF($S68="","",IF(INDEX('_pockets'!$AB:$AB,$S68)="","",INDEX('_pockets'!$AB:$AB,$S68)))="","",IF($S68="","",IF(INDEX('_pockets'!$AB:$AB,$S68)="","",INDEX('_pockets'!$AB:$AB,$S68)))*IF($U$19,100,1)) | J68: =IF($S68="","",IF(INDEX('_pockets'!$Z:$Z,$S68)="","",INDEX('_pockets'!$Z:$Z,$S68))) | K68: =IF($R68="","",IF(INDEX('_list'!$K$2:$K$652,$R68)="","",INDEX('_list'!$K$2:$K$652,$R68))) | L68: =IF($S68="","",IF(INDEX('_pockets'!$AC:$AC,$S68)="","",INDEX('_pockets'!$AC:$AC,$S68))) | M68: =IF($R68="","",IF(INDEX('_list'!$L$2:$L$652,$R68)="","",INDEX('_list'!$L$2:$L$652,$R68))) | N68: =IF($R68="","",IF(INDEX('_list'!$H$2:$H$652,$R68)="","",INDEX('_list'!$H$2:$H$652,$R68))) | O68: =IF($R68="","",IF(INDEX('_list'!$I$2:$I$652,$R68)="","",INDEX('_list'!$I$2:$I$652,$R68))) | R68: =IFERROR(MATCH(48,'_list'!$N$2:$N$652,0),"") | S68: =IF($R68="","",INDEX('_list'!$C$2:$C$652,$R68))
B69: =IF($R69="","",49) | C69: =IF($R69="","",IF(INDEX('_list'!$D$2:$D$652,$R69)="","",INDEX('_list'!$D$2:$D$652,$R69))) | D69: =IF($R69="","",IF(INDEX('_list'!$E$2:$E$652,$R69)="","",INDEX('_list'!$E$2:$E$652,$R69))) | E69: =IF($R69="","",IF(INDEX('_list'!$F$2:$F$652,$R69)="","",INDEX('_list'!$F$2:$F$652,$R69))) | F69: =IF($R69="","",IF(INDEX('_list'!$G$2:$G$652,$R69)="","",INDEX('_list'!$G$2:$G$652,$R69))) | G69: =IF($S69="","",IF(INDEX('_pockets'!$AH:$AH,$S69)="","",INDEX('_pockets'!$AH:$AH,$S69))) | H69: =IF($S69="","",IF(INDEX('_pockets'!$AF:$AF,$S69)="","",INDEX('_pockets'!$AF:$AF,$S69))) | I69: =IF(IF($S69="","",IF(INDEX('_pockets'!$AB:$AB,$S69)="","",INDEX('_pockets'!$AB:$AB,$S69)))="","",IF($S69="","",IF(INDEX('_pockets'!$AB:$AB,$S69)="","",INDEX('_pockets'!$AB:$AB,$S69)))*IF($U$19,100,1)) | J69: =IF($S69="","",IF(INDEX('_pockets'!$Z:$Z,$S69)="","",INDEX('_pockets'!$Z:$Z,$S69))) | K69: =IF($R69="","",IF(INDEX('_list'!$K$2:$K$652,$R69)="","",INDEX('_list'!$K$2:$K$652,$R69))) | L69: =IF($S69="","",IF(INDEX('_pockets'!$AC:$AC,$S69)="","",INDEX('_pockets'!$AC:$AC,$S69))) | M69: =IF($R69="","",IF(INDEX('_list'!$L$2:$L$652,$R69)="","",INDEX('_list'!$L$2:$L$652,$R69))) | N69: =IF($R69="","",IF(INDEX('_list'!$H$2:$H$652,$R69)="","",INDEX('_list'!$H$2:$H$652,$R69))) | O69: =IF($R69="","",IF(INDEX('_list'!$I$2:$I$652,$R69)="","",INDEX('_list'!$I$2:$I$652,$R69))) | R69: =IFERROR(MATCH(49,'_list'!$N$2:$N$652,0),"") | S69: =IF($R69="","",INDEX('_list'!$C$2:$C$652,$R69))
B70: =IF($R70="","",50) | C70: =IF($R70="","",IF(INDEX('_list'!$D$2:$D$652,$R70)="","",INDEX('_list'!$D$2:$D$652,$R70))) | D70: =IF($R70="","",IF(INDEX('_list'!$E$2:$E$652,$R70)="","",INDEX('_list'!$E$2:$E$652,$R70))) | E70: =IF($R70="","",IF(INDEX('_list'!$F$2:$F$652,$R70)="","",INDEX('_list'!$F$2:$F$652,$R70))) | F70: =IF($R70="","",IF(INDEX('_list'!$G$2:$G$652,$R70)="","",INDEX('_list'!$G$2:$G$652,$R70))) | G70: =IF($S70="","",IF(INDEX('_pockets'!$AH:$AH,$S70)="","",INDEX('_pockets'!$AH:$AH,$S70))) | H70: =IF($S70="","",IF(INDEX('_pockets'!$AF:$AF,$S70)="","",INDEX('_pockets'!$AF:$AF,$S70))) | I70: =IF(IF($S70="","",IF(INDEX('_pockets'!$AB:$AB,$S70)="","",INDEX('_pockets'!$AB:$AB,$S70)))="","",IF($S70="","",IF(INDEX('_pockets'!$AB:$AB,$S70)="","",INDEX('_pockets'!$AB:$AB,$S70)))*IF($U$19,100,1)) | J70: =IF($S70="","",IF(INDEX('_pockets'!$Z:$Z,$S70)="","",INDEX('_pockets'!$Z:$Z,$S70))) | K70: =IF($R70="","",IF(INDEX('_list'!$K$2:$K$652,$R70)="","",INDEX('_list'!$K$2:$K$652,$R70))) | L70: =IF($S70="","",IF(INDEX('_pockets'!$AC:$AC,$S70)="","",INDEX('_pockets'!$AC:$AC,$S70))) | M70: =IF($R70="","",IF(INDEX('_list'!$L$2:$L$652,$R70)="","",INDEX('_list'!$L$2:$L$652,$R70))) | N70: =IF($R70="","",IF(INDEX('_list'!$H$2:$H$652,$R70)="","",INDEX('_list'!$H$2:$H$652,$R70))) | O70: =IF($R70="","",IF(INDEX('_list'!$I$2:$I$652,$R70)="","",INDEX('_list'!$I$2:$I$652,$R70))) | R70: =IFERROR(MATCH(50,'_list'!$N$2:$N$652,0),"") | S70: =IF($R70="","",INDEX('_list'!$C$2:$C$652,$R70))
B71: =IF($R71="","",51) | C71: =IF($R71="","",IF(INDEX('_list'!$D$2:$D$652,$R71)="","",INDEX('_list'!$D$2:$D$652,$R71))) | D71: =IF($R71="","",IF(INDEX('_list'!$E$2:$E$652,$R71)="","",INDEX('_list'!$E$2:$E$652,$R71))) | E71: =IF($R71="","",IF(INDEX('_list'!$F$2:$F$652,$R71)="","",INDEX('_list'!$F$2:$F$652,$R71))) | F71: =IF($R71="","",IF(INDEX('_list'!$G$2:$G$652,$R71)="","",INDEX('_list'!$G$2:$G$652,$R71))) | G71: =IF($S71="","",IF(INDEX('_pockets'!$AH:$AH,$S71)="","",INDEX('_pockets'!$AH:$AH,$S71))) | H71: =IF($S71="","",IF(INDEX('_pockets'!$AF:$AF,$S71)="","",INDEX('_pockets'!$AF:$AF,$S71))) | I71: =IF(IF($S71="","",IF(INDEX('_pockets'!$AB:$AB,$S71)="","",INDEX('_pockets'!$AB:$AB,$S71)))="","",IF($S71="","",IF(INDEX('_pockets'!$AB:$AB,$S71)="","",INDEX('_pockets'!$AB:$AB,$S71)))*IF($U$19,100,1)) | J71: =IF($S71="","",IF(INDEX('_pockets'!$Z:$Z,$S71)="","",INDEX('_pockets'!$Z:$Z,$S71))) | K71: =IF($R71="","",IF(INDEX('_list'!$K$2:$K$652,$R71)="","",INDEX('_list'!$K$2:$K$652,$R71))) | L71: =IF($S71="","",IF(INDEX('_pockets'!$AC:$AC,$S71)="","",INDEX('_pockets'!$AC:$AC,$S71))) | M71: =IF($R71="","",IF(INDEX('_list'!$L$2:$L$652,$R71)="","",INDEX('_list'!$L$2:$L$652,$R71))) | N71: =IF($R71="","",IF(INDEX('_list'!$H$2:$H$652,$R71)="","",INDEX('_list'!$H$2:$H$652,$R71))) | O71: =IF($R71="","",IF(INDEX('_list'!$I$2:$I$652,$R71)="","",INDEX('_list'!$I$2:$I$652,$R71))) | R71: =IFERROR(MATCH(51,'_list'!$N$2:$N$652,0),"") | S71: =IF($R71="","",INDEX('_list'!$C$2:$C$652,$R71))
B72: =IF($R72="","",52) | C72: =IF($R72="","",IF(INDEX('_list'!$D$2:$D$652,$R72)="","",INDEX('_list'!$D$2:$D$652,$R72))) | D72: =IF($R72="","",IF(INDEX('_list'!$E$2:$E$652,$R72)="","",INDEX('_list'!$E$2:$E$652,$R72))) | E72: =IF($R72="","",IF(INDEX('_list'!$F$2:$F$652,$R72)="","",INDEX('_list'!$F$2:$F$652,$R72))) | F72: =IF($R72="","",IF(INDEX('_list'!$G$2:$G$652,$R72)="","",INDEX('_list'!$G$2:$G$652,$R72))) | G72: =IF($S72="","",IF(INDEX('_pockets'!$AH:$AH,$S72)="","",INDEX('_pockets'!$AH:$AH,$S72))) | H72: =IF($S72="","",IF(INDEX('_pockets'!$AF:$AF,$S72)="","",INDEX('_pockets'!$AF:$AF,$S72))) | I72: =IF(IF($S72="","",IF(INDEX('_pockets'!$AB:$AB,$S72)="","",INDEX('_pockets'!$AB:$AB,$S72)))="","",IF($S72="","",IF(INDEX('_pockets'!$AB:$AB,$S72)="","",INDEX('_pockets'!$AB:$AB,$S72)))*IF($U$19,100,1)) | J72: =IF($S72="","",IF(INDEX('_pockets'!$Z:$Z,$S72)="","",INDEX('_pockets'!$Z:$Z,$S72))) | K72: =IF($R72="","",IF(INDEX('_list'!$K$2:$K$652,$R72)="","",INDEX('_list'!$K$2:$K$652,$R72))) | L72: =IF($S72="","",IF(INDEX('_pockets'!$AC:$AC,$S72)="","",INDEX('_pockets'!$AC:$AC,$S72))) | M72: =IF($R72="","",IF(INDEX('_list'!$L$2:$L$652,$R72)="","",INDEX('_list'!$L$2:$L$652,$R72))) | N72: =IF($R72="","",IF(INDEX('_list'!$H$2:$H$652,$R72)="","",INDEX('_list'!$H$2:$H$652,$R72))) | O72: =IF($R72="","",IF(INDEX('_list'!$I$2:$I$652,$R72)="","",INDEX('_list'!$I$2:$I$652,$R72))) | R72: =IFERROR(MATCH(52,'_list'!$N$2:$N$652,0),"") | S72: =IF($R72="","",INDEX('_list'!$C$2:$C$652,$R72))
B73: =IF($R73="","",53) | C73: =IF($R73="","",IF(INDEX('_list'!$D$2:$D$652,$R73)="","",INDEX('_list'!$D$2:$D$652,$R73))) | D73: =IF($R73="","",IF(INDEX('_list'!$E$2:$E$652,$R73)="","",INDEX('_list'!$E$2:$E$652,$R73))) | E73: =IF($R73="","",IF(INDEX('_list'!$F$2:$F$652,$R73)="","",INDEX('_list'!$F$2:$F$652,$R73))) | F73: =IF($R73="","",IF(INDEX('_list'!$G$2:$G$652,$R73)="","",INDEX('_list'!$G$2:$G$652,$R73))) | G73: =IF($S73="","",IF(INDEX('_pockets'!$AH:$AH,$S73)="","",INDEX('_pockets'!$AH:$AH,$S73))) | H73: =IF($S73="","",IF(INDEX('_pockets'!$AF:$AF,$S73)="","",INDEX('_pockets'!$AF:$AF,$S73))) | I73: =IF(IF($S73="","",IF(INDEX('_pockets'!$AB:$AB,$S73)="","",INDEX('_pockets'!$AB:$AB,$S73)))="","",IF($S73="","",IF(INDEX('_pockets'!$AB:$AB,$S73)="","",INDEX('_pockets'!$AB:$AB,$S73)))*IF($U$19,100,1)) | J73: =IF($S73="","",IF(INDEX('_pockets'!$Z:$Z,$S73)="","",INDEX('_pockets'!$Z:$Z,$S73))) | K73: =IF($R73="","",IF(INDEX('_list'!$K$2:$K$652,$R73)="","",INDEX('_list'!$K$2:$K$652,$R73))) | L73: =IF($S73="","",IF(INDEX('_pockets'!$AC:$AC,$S73)="","",INDEX('_pockets'!$AC:$AC,$S73))) | M73: =IF($R73="","",IF(INDEX('_list'!$L$2:$L$652,$R73)="","",INDEX('_list'!$L$2:$L$652,$R73))) | N73: =IF($R73="","",IF(INDEX('_list'!$H$2:$H$652,$R73)="","",INDEX('_list'!$H$2:$H$652,$R73))) | O73: =IF($R73="","",IF(INDEX('_list'!$I$2:$I$652,$R73)="","",INDEX('_list'!$I$2:$I$652,$R73))) | R73: =IFERROR(MATCH(53,'_list'!$N$2:$N$652,0),"") | S73: =IF($R73="","",INDEX('_list'!$C$2:$C$652,$R73))
B74: =IF($R74="","",54) | C74: =IF($R74="","",IF(INDEX('_list'!$D$2:$D$652,$R74)="","",INDEX('_list'!$D$2:$D$652,$R74))) | D74: =IF($R74="","",IF(INDEX('_list'!$E$2:$E$652,$R74)="","",INDEX('_list'!$E$2:$E$652,$R74))) | E74: =IF($R74="","",IF(INDEX('_list'!$F$2:$F$652,$R74)="","",INDEX('_list'!$F$2:$F$652,$R74))) | F74: =IF($R74="","",IF(INDEX('_list'!$G$2:$G$652,$R74)="","",INDEX('_list'!$G$2:$G$652,$R74))) | G74: =IF($S74="","",IF(INDEX('_pockets'!$AH:$AH,$S74)="","",INDEX('_pockets'!$AH:$AH,$S74))) | H74: =IF($S74="","",IF(INDEX('_pockets'!$AF:$AF,$S74)="","",INDEX('_pockets'!$AF:$AF,$S74))) | I74: =IF(IF($S74="","",IF(INDEX('_pockets'!$AB:$AB,$S74)="","",INDEX('_pockets'!$AB:$AB,$S74)))="","",IF($S74="","",IF(INDEX('_pockets'!$AB:$AB,$S74)="","",INDEX('_pockets'!$AB:$AB,$S74)))*IF($U$19,100,1)) | J74: =IF($S74="","",IF(INDEX('_pockets'!$Z:$Z,$S74)="","",INDEX('_pockets'!$Z:$Z,$S74))) | K74: =IF($R74="","",IF(INDEX('_list'!$K$2:$K$652,$R74)="","",INDEX('_list'!$K$2:$K$652,$R74))) | L74: =IF($S74="","",IF(INDEX('_pockets'!$AC:$AC,$S74)="","",INDEX('_pockets'!$AC:$AC,$S74))) | M74: =IF($R74="","",IF(INDEX('_list'!$L$2:$L$652,$R74)="","",INDEX('_list'!$L$2:$L$652,$R74))) | N74: =IF($R74="","",IF(INDEX('_list'!$H$2:$H$652,$R74)="","",INDEX('_list'!$H$2:$H$652,$R74))) | O74: =IF($R74="","",IF(INDEX('_list'!$I$2:$I$652,$R74)="","",INDEX('_list'!$I$2:$I$652,$R74))) | R74: =IFERROR(MATCH(54,'_list'!$N$2:$N$652,0),"") | S74: =IF($R74="","",INDEX('_list'!$C$2:$C$652,$R74))
B75: =IF($R75="","",55) | C75: =IF($R75="","",IF(INDEX('_list'!$D$2:$D$652,$R75)="","",INDEX('_list'!$D$2:$D$652,$R75))) | D75: =IF($R75="","",IF(INDEX('_list'!$E$2:$E$652,$R75)="","",INDEX('_list'!$E$2:$E$652,$R75))) | E75: =IF($R75="","",IF(INDEX('_list'!$F$2:$F$652,$R75)="","",INDEX('_list'!$F$2:$F$652,$R75))) | F75: =IF($R75="","",IF(INDEX('_list'!$G$2:$G$652,$R75)="","",INDEX('_list'!$G$2:$G$652,$R75))) | G75: =IF($S75="","",IF(INDEX('_pockets'!$AH:$AH,$S75)="","",INDEX('_pockets'!$AH:$AH,$S75))) | H75: =IF($S75="","",IF(INDEX('_pockets'!$AF:$AF,$S75)="","",INDEX('_pockets'!$AF:$AF,$S75))) | I75: =IF(IF($S75="","",IF(INDEX('_pockets'!$AB:$AB,$S75)="","",INDEX('_pockets'!$AB:$AB,$S75)))="","",IF($S75="","",IF(INDEX('_pockets'!$AB:$AB,$S75)="","",INDEX('_pockets'!$AB:$AB,$S75)))*IF($U$19,100,1)) | J75: =IF($S75="","",IF(INDEX('_pockets'!$Z:$Z,$S75)="","",INDEX('_pockets'!$Z:$Z,$S75))) | K75: =IF($R75="","",IF(INDEX('_list'!$K$2:$K$652,$R75)="","",INDEX('_list'!$K$2:$K$652,$R75))) | L75: =IF($S75="","",IF(INDEX('_pockets'!$AC:$AC,$S75)="","",INDEX('_pockets'!$AC:$AC,$S75))) | M75: =IF($R75="","",IF(INDEX('_list'!$L$2:$L$652,$R75)="","",INDEX('_list'!$L$2:$L$652,$R75))) | N75: =IF($R75="","",IF(INDEX('_list'!$H$2:$H$652,$R75)="","",INDEX('_list'!$H$2:$H$652,$R75))) | O75: =IF($R75="","",IF(INDEX('_list'!$I$2:$I$652,$R75)="","",INDEX('_list'!$I$2:$I$652,$R75))) | R75: =IFERROR(MATCH(55,'_list'!$N$2:$N$652,0),"") | S75: =IF($R75="","",INDEX('_list'!$C$2:$C$652,$R75))
B76: =IF($R76="","",56) | C76: =IF($R76="","",IF(INDEX('_list'!$D$2:$D$652,$R76)="","",INDEX('_list'!$D$2:$D$652,$R76))) | D76: =IF($R76="","",IF(INDEX('_list'!$E$2:$E$652,$R76)="","",INDEX('_list'!$E$2:$E$652,$R76))) | E76: =IF($R76="","",IF(INDEX('_list'!$F$2:$F$652,$R76)="","",INDEX('_list'!$F$2:$F$652,$R76))) | F76: =IF($R76="","",IF(INDEX('_list'!$G$2:$G$652,$R76)="","",INDEX('_list'!$G$2:$G$652,$R76))) | G76: =IF($S76="","",IF(INDEX('_pockets'!$AH:$AH,$S76)="","",INDEX('_pockets'!$AH:$AH,$S76))) | H76: =IF($S76="","",IF(INDEX('_pockets'!$AF:$AF,$S76)="","",INDEX('_pockets'!$AF:$AF,$S76))) | I76: =IF(IF($S76="","",IF(INDEX('_pockets'!$AB:$AB,$S76)="","",INDEX('_pockets'!$AB:$AB,$S76)))="","",IF($S76="","",IF(INDEX('_pockets'!$AB:$AB,$S76)="","",INDEX('_pockets'!$AB:$AB,$S76)))*IF($U$19,100,1)) | J76: =IF($S76="","",IF(INDEX('_pockets'!$Z:$Z,$S76)="","",INDEX('_pockets'!$Z:$Z,$S76))) | K76: =IF($R76="","",IF(INDEX('_list'!$K$2:$K$652,$R76)="","",INDEX('_list'!$K$2:$K$652,$R76))) | L76: =IF($S76="","",IF(INDEX('_pockets'!$AC:$AC,$S76)="","",INDEX('_pockets'!$AC:$AC,$S76))) | M76: =IF($R76="","",IF(INDEX('_list'!$L$2:$L$652,$R76)="","",INDEX('_list'!$L$2:$L$652,$R76))) | N76: =IF($R76="","",IF(INDEX('_list'!$H$2:$H$652,$R76)="","",INDEX('_list'!$H$2:$H$652,$R76))) | O76: =IF($R76="","",IF(INDEX('_list'!$I$2:$I$652,$R76)="","",INDEX('_list'!$I$2:$I$652,$R76))) | R76: =IFERROR(MATCH(56,'_list'!$N$2:$N$652,0),"") | S76: =IF($R76="","",INDEX('_list'!$C$2:$C$652,$R76))
B77: =IF($R77="","",57) | C77: =IF($R77="","",IF(INDEX('_list'!$D$2:$D$652,$R77)="","",INDEX('_list'!$D$2:$D$652,$R77))) | D77: =IF($R77="","",IF(INDEX('_list'!$E$2:$E$652,$R77)="","",INDEX('_list'!$E$2:$E$652,$R77))) | E77: =IF($R77="","",IF(INDEX('_list'!$F$2:$F$652,$R77)="","",INDEX('_list'!$F$2:$F$652,$R77))) | F77: =IF($R77="","",IF(INDEX('_list'!$G$2:$G$652,$R77)="","",INDEX('_list'!$G$2:$G$652,$R77))) | G77: =IF($S77="","",IF(INDEX('_pockets'!$AH:$AH,$S77)="","",INDEX('_pockets'!$AH:$AH,$S77))) | H77: =IF($S77="","",IF(INDEX('_pockets'!$AF:$AF,$S77)="","",INDEX('_pockets'!$AF:$AF,$S77))) | I77: =IF(IF($S77="","",IF(INDEX('_pockets'!$AB:$AB,$S77)="","",INDEX('_pockets'!$AB:$AB,$S77)))="","",IF($S77="","",IF(INDEX('_pockets'!$AB:$AB,$S77)="","",INDEX('_pockets'!$AB:$AB,$S77)))*IF($U$19,100,1)) | J77: =IF($S77="","",IF(INDEX('_pockets'!$Z:$Z,$S77)="","",INDEX('_pockets'!$Z:$Z,$S77))) | K77: =IF($R77="","",IF(INDEX('_list'!$K$2:$K$652,$R77)="","",INDEX('_list'!$K$2:$K$652,$R77))) | L77: =IF($S77="","",IF(INDEX('_pockets'!$AC:$AC,$S77)="","",INDEX('_pockets'!$AC:$AC,$S77))) | M77: =IF($R77="","",IF(INDEX('_list'!$L$2:$L$652,$R77)="","",INDEX('_list'!$L$2:$L$652,$R77))) | N77: =IF($R77="","",IF(INDEX('_list'!$H$2:$H$652,$R77)="","",INDEX('_list'!$H$2:$H$652,$R77))) | O77: =IF($R77="","",IF(INDEX('_list'!$I$2:$I$652,$R77)="","",INDEX('_list'!$I$2:$I$652,$R77))) | R77: =IFERROR(MATCH(57,'_list'!$N$2:$N$652,0),"") | S77: =IF($R77="","",INDEX('_list'!$C$2:$C$652,$R77))
B78: =IF($R78="","",58) | C78: =IF($R78="","",IF(INDEX('_list'!$D$2:$D$652,$R78)="","",INDEX('_list'!$D$2:$D$652,$R78))) | D78: =IF($R78="","",IF(INDEX('_list'!$E$2:$E$652,$R78)="","",INDEX('_list'!$E$2:$E$652,$R78))) | E78: =IF($R78="","",IF(INDEX('_list'!$F$2:$F$652,$R78)="","",INDEX('_list'!$F$2:$F$652,$R78))) | F78: =IF($R78="","",IF(INDEX('_list'!$G$2:$G$652,$R78)="","",INDEX('_list'!$G$2:$G$652,$R78))) | G78: =IF($S78="","",IF(INDEX('_pockets'!$AH:$AH,$S78)="","",INDEX('_pockets'!$AH:$AH,$S78))) | H78: =IF($S78="","",IF(INDEX('_pockets'!$AF:$AF,$S78)="","",INDEX('_pockets'!$AF:$AF,$S78))) | I78: =IF(IF($S78="","",IF(INDEX('_pockets'!$AB:$AB,$S78)="","",INDEX('_pockets'!$AB:$AB,$S78)))="","",IF($S78="","",IF(INDEX('_pockets'!$AB:$AB,$S78)="","",INDEX('_pockets'!$AB:$AB,$S78)))*IF($U$19,100,1)) | J78: =IF($S78="","",IF(INDEX('_pockets'!$Z:$Z,$S78)="","",INDEX('_pockets'!$Z:$Z,$S78))) | K78: =IF($R78="","",IF(INDEX('_list'!$K$2:$K$652,$R78)="","",INDEX('_list'!$K$2:$K$652,$R78))) | L78: =IF($S78="","",IF(INDEX('_pockets'!$AC:$AC,$S78)="","",INDEX('_pockets'!$AC:$AC,$S78))) | M78: =IF($R78="","",IF(INDEX('_list'!$L$2:$L$652,$R78)="","",INDEX('_list'!$L$2:$L$652,$R78))) | N78: =IF($R78="","",IF(INDEX('_list'!$H$2:$H$652,$R78)="","",INDEX('_list'!$H$2:$H$652,$R78))) | O78: =IF($R78="","",IF(INDEX('_list'!$I$2:$I$652,$R78)="","",INDEX('_list'!$I$2:$I$652,$R78))) | R78: =IFERROR(MATCH(58,'_list'!$N$2:$N$652,0),"") | S78: =IF($R78="","",INDEX('_list'!$C$2:$C$652,$R78))
B79: =IF($R79="","",59) | C79: =IF($R79="","",IF(INDEX('_list'!$D$2:$D$652,$R79)="","",INDEX('_list'!$D$2:$D$652,$R79))) | D79: =IF($R79="","",IF(INDEX('_list'!$E$2:$E$652,$R79)="","",INDEX('_list'!$E$2:$E$652,$R79))) | E79: =IF($R79="","",IF(INDEX('_list'!$F$2:$F$652,$R79)="","",INDEX('_list'!$F$2:$F$652,$R79))) | F79: =IF($R79="","",IF(INDEX('_list'!$G$2:$G$652,$R79)="","",INDEX('_list'!$G$2:$G$652,$R79))) | G79: =IF($S79="","",IF(INDEX('_pockets'!$AH:$AH,$S79)="","",INDEX('_pockets'!$AH:$AH,$S79))) | H79: =IF($S79="","",IF(INDEX('_pockets'!$AF:$AF,$S79)="","",INDEX('_pockets'!$AF:$AF,$S79))) | I79: =IF(IF($S79="","",IF(INDEX('_pockets'!$AB:$AB,$S79)="","",INDEX('_pockets'!$AB:$AB,$S79)))="","",IF($S79="","",IF(INDEX('_pockets'!$AB:$AB,$S79)="","",INDEX('_pockets'!$AB:$AB,$S79)))*IF($U$19,100,1)) | J79: =IF($S79="","",IF(INDEX('_pockets'!$Z:$Z,$S79)="","",INDEX('_pockets'!$Z:$Z,$S79))) | K79: =IF($R79="","",IF(INDEX('_list'!$K$2:$K$652,$R79)="","",INDEX('_list'!$K$2:$K$652,$R79))) | L79: =IF($S79="","",IF(INDEX('_pockets'!$AC:$AC,$S79)="","",INDEX('_pockets'!$AC:$AC,$S79))) | M79: =IF($R79="","",IF(INDEX('_list'!$L$2:$L$652,$R79)="","",INDEX('_list'!$L$2:$L$652,$R79))) | N79: =IF($R79="","",IF(INDEX('_list'!$H$2:$H$652,$R79)="","",INDEX('_list'!$H$2:$H$652,$R79))) | O79: =IF($R79="","",IF(INDEX('_list'!$I$2:$I$652,$R79)="","",INDEX('_list'!$I$2:$I$652,$R79))) | R79: =IFERROR(MATCH(59,'_list'!$N$2:$N$652,0),"") | S79: =IF($R79="","",INDEX('_list'!$C$2:$C$652,$R79))
B80: =IF($R80="","",60) | C80: =IF($R80="","",IF(INDEX('_list'!$D$2:$D$652,$R80)="","",INDEX('_list'!$D$2:$D$652,$R80))) | D80: =IF($R80="","",IF(INDEX('_list'!$E$2:$E$652,$R80)="","",INDEX('_list'!$E$2:$E$652,$R80))) | E80: =IF($R80="","",IF(INDEX('_list'!$F$2:$F$652,$R80)="","",INDEX('_list'!$F$2:$F$652,$R80))) | F80: =IF($R80="","",IF(INDEX('_list'!$G$2:$G$652,$R80)="","",INDEX('_list'!$G$2:$G$652,$R80))) | G80: =IF($S80="","",IF(INDEX('_pockets'!$AH:$AH,$S80)="","",INDEX('_pockets'!$AH:$AH,$S80))) | H80: =IF($S80="","",IF(INDEX('_pockets'!$AF:$AF,$S80)="","",INDEX('_pockets'!$AF:$AF,$S80))) | I80: =IF(IF($S80="","",IF(INDEX('_pockets'!$AB:$AB,$S80)="","",INDEX('_pockets'!$AB:$AB,$S80)))="","",IF($S80="","",IF(INDEX('_pockets'!$AB:$AB,$S80)="","",INDEX('_pockets'!$AB:$AB,$S80)))*IF($U$19,100,1)) | J80: =IF($S80="","",IF(INDEX('_pockets'!$Z:$Z,$S80)="","",INDEX('_pockets'!$Z:$Z,$S80))) | K80: =IF($R80="","",IF(INDEX('_list'!$K$2:$K$652,$R80)="","",INDEX('_list'!$K$2:$K$652,$R80))) | L80: =IF($S80="","",IF(INDEX('_pockets'!$AC:$AC,$S80)="","",INDEX('_pockets'!$AC:$AC,$S80))) | M80: =IF($R80="","",IF(INDEX('_list'!$L$2:$L$652,$R80)="","",INDEX('_list'!$L$2:$L$652,$R80))) | N80: =IF($R80="","",IF(INDEX('_list'!$H$2:$H$652,$R80)="","",INDEX('_list'!$H$2:$H$652,$R80))) | O80: =IF($R80="","",IF(INDEX('_list'!$I$2:$I$652,$R80)="","",INDEX('_list'!$I$2:$I$652,$R80))) | R80: =IFERROR(MATCH(60,'_list'!$N$2:$N$652,0),"") | S80: =IF($R80="","",INDEX('_list'!$C$2:$C$652,$R80))
B81: =IF($R81="","",61) | C81: =IF($R81="","",IF(INDEX('_list'!$D$2:$D$652,$R81)="","",INDEX('_list'!$D$2:$D$652,$R81))) | D81: =IF($R81="","",IF(INDEX('_list'!$E$2:$E$652,$R81)="","",INDEX('_list'!$E$2:$E$652,$R81))) | E81: =IF($R81="","",IF(INDEX('_list'!$F$2:$F$652,$R81)="","",INDEX('_list'!$F$2:$F$652,$R81))) | F81: =IF($R81="","",IF(INDEX('_list'!$G$2:$G$652,$R81)="","",INDEX('_list'!$G$2:$G$652,$R81))) | G81: =IF($S81="","",IF(INDEX('_pockets'!$AH:$AH,$S81)="","",INDEX('_pockets'!$AH:$AH,$S81))) | H81: =IF($S81="","",IF(INDEX('_pockets'!$AF:$AF,$S81)="","",INDEX('_pockets'!$AF:$AF,$S81))) | I81: =IF(IF($S81="","",IF(INDEX('_pockets'!$AB:$AB,$S81)="","",INDEX('_pockets'!$AB:$AB,$S81)))="","",IF($S81="","",IF(INDEX('_pockets'!$AB:$AB,$S81)="","",INDEX('_pockets'!$AB:$AB,$S81)))*IF($U$19,100,1)) | J81: =IF($S81="","",IF(INDEX('_pockets'!$Z:$Z,$S81)="","",INDEX('_pockets'!$Z:$Z,$S81))) | K81: =IF($R81="","",IF(INDEX('_list'!$K$2:$K$652,$R81)="","",INDEX('_list'!$K$2:$K$652,$R81))) | L81: =IF($S81="","",IF(INDEX('_pockets'!$AC:$AC,$S81)="","",INDEX('_pockets'!$AC:$AC,$S81))) | M81: =IF($R81="","",IF(INDEX('_list'!$L$2:$L$652,$R81)="","",INDEX('_list'!$L$2:$L$652,$R81))) | N81: =IF($R81="","",IF(INDEX('_list'!$H$2:$H$652,$R81)="","",INDEX('_list'!$H$2:$H$652,$R81))) | O81: =IF($R81="","",IF(INDEX('_list'!$I$2:$I$652,$R81)="","",INDEX('_list'!$I$2:$I$652,$R81))) | R81: =IFERROR(MATCH(61,'_list'!$N$2:$N$652,0),"") | S81: =IF($R81="","",INDEX('_list'!$C$2:$C$652,$R81))
B82: =IF($R82="","",62) | C82: =IF($R82="","",IF(INDEX('_list'!$D$2:$D$652,$R82)="","",INDEX('_list'!$D$2:$D$652,$R82))) | D82: =IF($R82="","",IF(INDEX('_list'!$E$2:$E$652,$R82)="","",INDEX('_list'!$E$2:$E$652,$R82))) | E82: =IF($R82="","",IF(INDEX('_list'!$F$2:$F$652,$R82)="","",INDEX('_list'!$F$2:$F$652,$R82))) | F82: =IF($R82="","",IF(INDEX('_list'!$G$2:$G$652,$R82)="","",INDEX('_list'!$G$2:$G$652,$R82))) | G82: =IF($S82="","",IF(INDEX('_pockets'!$AH:$AH,$S82)="","",INDEX('_pockets'!$AH:$AH,$S82))) | H82: =IF($S82="","",IF(INDEX('_pockets'!$AF:$AF,$S82)="","",INDEX('_pockets'!$AF:$AF,$S82))) | I82: =IF(IF($S82="","",IF(INDEX('_pockets'!$AB:$AB,$S82)="","",INDEX('_pockets'!$AB:$AB,$S82)))="","",IF($S82="","",IF(INDEX('_pockets'!$AB:$AB,$S82)="","",INDEX('_pockets'!$AB:$AB,$S82)))*IF($U$19,100,1)) | J82: =IF($S82="","",IF(INDEX('_pockets'!$Z:$Z,$S82)="","",INDEX('_pockets'!$Z:$Z,$S82))) | K82: =IF($R82="","",IF(INDEX('_list'!$K$2:$K$652,$R82)="","",INDEX('_list'!$K$2:$K$652,$R82))) | L82: =IF($S82="","",IF(INDEX('_pockets'!$AC:$AC,$S82)="","",INDEX('_pockets'!$AC:$AC,$S82))) | M82: =IF($R82="","",IF(INDEX('_list'!$L$2:$L$652,$R82)="","",INDEX('_list'!$L$2:$L$652,$R82))) | N82: =IF($R82="","",IF(INDEX('_list'!$H$2:$H$652,$R82)="","",INDEX('_list'!$H$2:$H$652,$R82))) | O82: =IF($R82="","",IF(INDEX('_list'!$I$2:$I$652,$R82)="","",INDEX('_list'!$I$2:$I$652,$R82))) | R82: =IFERROR(MATCH(62,'_list'!$N$2:$N$652,0),"") | S82: =IF($R82="","",INDEX('_list'!$C$2:$C$652,$R82))
B83: =IF($R83="","",63) | C83: =IF($R83="","",IF(INDEX('_list'!$D$2:$D$652,$R83)="","",INDEX('_list'!$D$2:$D$652,$R83))) | D83: =IF($R83="","",IF(INDEX('_list'!$E$2:$E$652,$R83)="","",INDEX('_list'!$E$2:$E$652,$R83))) | E83: =IF($R83="","",IF(INDEX('_list'!$F$2:$F$652,$R83)="","",INDEX('_list'!$F$2:$F$652,$R83))) | F83: =IF($R83="","",IF(INDEX('_list'!$G$2:$G$652,$R83)="","",INDEX('_list'!$G$2:$G$652,$R83))) | G83: =IF($S83="","",IF(INDEX('_pockets'!$AH:$AH,$S83)="","",INDEX('_pockets'!$AH:$AH,$S83))) | H83: =IF($S83="","",IF(INDEX('_pockets'!$AF:$AF,$S83)="","",INDEX('_pockets'!$AF:$AF,$S83))) | I83: =IF(IF($S83="","",IF(INDEX('_pockets'!$AB:$AB,$S83)="","",INDEX('_pockets'!$AB:$AB,$S83)))="","",IF($S83="","",IF(INDEX('_pockets'!$AB:$AB,$S83)="","",INDEX('_pockets'!$AB:$AB,$S83)))*IF($U$19,100,1)) | J83: =IF($S83="","",IF(INDEX('_pockets'!$Z:$Z,$S83)="","",INDEX('_pockets'!$Z:$Z,$S83))) | K83: =IF($R83="","",IF(INDEX('_list'!$K$2:$K$652,$R83)="","",INDEX('_list'!$K$2:$K$652,$R83))) | L83: =IF($S83="","",IF(INDEX('_pockets'!$AC:$AC,$S83)="","",INDEX('_pockets'!$AC:$AC,$S83))) | M83: =IF($R83="","",IF(INDEX('_list'!$L$2:$L$652,$R83)="","",INDEX('_list'!$L$2:$L$652,$R83))) | N83: =IF($R83="","",IF(INDEX('_list'!$H$2:$H$652,$R83)="","",INDEX('_list'!$H$2:$H$652,$R83))) | O83: =IF($R83="","",IF(INDEX('_list'!$I$2:$I$652,$R83)="","",INDEX('_list'!$I$2:$I$652,$R83))) | R83: =IFERROR(MATCH(63,'_list'!$N$2:$N$652,0),"") | S83: =IF($R83="","",INDEX('_list'!$C$2:$C$652,$R83))
B84: =IF($R84="","",64) | C84: =IF($R84="","",IF(INDEX('_list'!$D$2:$D$652,$R84)="","",INDEX('_list'!$D$2:$D$652,$R84))) | D84: =IF($R84="","",IF(INDEX('_list'!$E$2:$E$652,$R84)="","",INDEX('_list'!$E$2:$E$652,$R84))) | E84: =IF($R84="","",IF(INDEX('_list'!$F$2:$F$652,$R84)="","",INDEX('_list'!$F$2:$F$652,$R84))) | F84: =IF($R84="","",IF(INDEX('_list'!$G$2:$G$652,$R84)="","",INDEX('_list'!$G$2:$G$652,$R84))) | G84: =IF($S84="","",IF(INDEX('_pockets'!$AH:$AH,$S84)="","",INDEX('_pockets'!$AH:$AH,$S84))) | H84: =IF($S84="","",IF(INDEX('_pockets'!$AF:$AF,$S84)="","",INDEX('_pockets'!$AF:$AF,$S84))) | I84: =IF(IF($S84="","",IF(INDEX('_pockets'!$AB:$AB,$S84)="","",INDEX('_pockets'!$AB:$AB,$S84)))="","",IF($S84="","",IF(INDEX('_pockets'!$AB:$AB,$S84)="","",INDEX('_pockets'!$AB:$AB,$S84)))*IF($U$19,100,1)) | J84: =IF($S84="","",IF(INDEX('_pockets'!$Z:$Z,$S84)="","",INDEX('_pockets'!$Z:$Z,$S84))) | K84: =IF($R84="","",IF(INDEX('_list'!$K$2:$K$652,$R84)="","",INDEX('_list'!$K$2:$K$652,$R84))) | L84: =IF($S84="","",IF(INDEX('_pockets'!$AC:$AC,$S84)="","",INDEX('_pockets'!$AC:$AC,$S84))) | M84: =IF($R84="","",IF(INDEX('_list'!$L$2:$L$652,$R84)="","",INDEX('_list'!$L$2:$L$652,$R84))) | N84: =IF($R84="","",IF(INDEX('_list'!$H$2:$H$652,$R84)="","",INDEX('_list'!$H$2:$H$652,$R84))) | O84: =IF($R84="","",IF(INDEX('_list'!$I$2:$I$652,$R84)="","",INDEX('_list'!$I$2:$I$652,$R84))) | R84: =IFERROR(MATCH(64,'_list'!$N$2:$N$652,0),"") | S84: =IF($R84="","",INDEX('_list'!$C$2:$C$652,$R84))
B85: =IF($R85="","",65) | C85: =IF($R85="","",IF(INDEX('_list'!$D$2:$D$652,$R85)="","",INDEX('_list'!$D$2:$D$652,$R85))) | D85: =IF($R85="","",IF(INDEX('_list'!$E$2:$E$652,$R85)="","",INDEX('_list'!$E$2:$E$652,$R85))) | E85: =IF($R85="","",IF(INDEX('_list'!$F$2:$F$652,$R85)="","",INDEX('_list'!$F$2:$F$652,$R85))) | F85: =IF($R85="","",IF(INDEX('_list'!$G$2:$G$652,$R85)="","",INDEX('_list'!$G$2:$G$652,$R85))) | G85: =IF($S85="","",IF(INDEX('_pockets'!$AH:$AH,$S85)="","",INDEX('_pockets'!$AH:$AH,$S85))) | H85: =IF($S85="","",IF(INDEX('_pockets'!$AF:$AF,$S85)="","",INDEX('_pockets'!$AF:$AF,$S85))) | I85: =IF(IF($S85="","",IF(INDEX('_pockets'!$AB:$AB,$S85)="","",INDEX('_pockets'!$AB:$AB,$S85)))="","",IF($S85="","",IF(INDEX('_pockets'!$AB:$AB,$S85)="","",INDEX('_pockets'!$AB:$AB,$S85)))*IF($U$19,100,1)) | J85: =IF($S85="","",IF(INDEX('_pockets'!$Z:$Z,$S85)="","",INDEX('_pockets'!$Z:$Z,$S85))) | K85: =IF($R85="","",IF(INDEX('_list'!$K$2:$K$652,$R85)="","",INDEX('_list'!$K$2:$K$652,$R85))) | L85: =IF($S85="","",IF(INDEX('_pockets'!$AC:$AC,$S85)="","",INDEX('_pockets'!$AC:$AC,$S85))) | M85: =IF($R85="","",IF(INDEX('_list'!$L$2:$L$652,$R85)="","",INDEX('_list'!$L$2:$L$652,$R85))) | N85: =IF($R85="","",IF(INDEX('_list'!$H$2:$H$652,$R85)="","",INDEX('_list'!$H$2:$H$652,$R85))) | O85: =IF($R85="","",IF(INDEX('_list'!$I$2:$I$652,$R85)="","",INDEX('_list'!$I$2:$I$652,$R85))) | R85: =IFERROR(MATCH(65,'_list'!$N$2:$N$652,0),"") | S85: =IF($R85="","",INDEX('_list'!$C$2:$C$652,$R85))
B86: =IF($R86="","",66) | C86: =IF($R86="","",IF(INDEX('_list'!$D$2:$D$652,$R86)="","",INDEX('_list'!$D$2:$D$652,$R86))) | D86: =IF($R86="","",IF(INDEX('_list'!$E$2:$E$652,$R86)="","",INDEX('_list'!$E$2:$E$652,$R86))) | E86: =IF($R86="","",IF(INDEX('_list'!$F$2:$F$652,$R86)="","",INDEX('_list'!$F$2:$F$652,$R86))) | F86: =IF($R86="","",IF(INDEX('_list'!$G$2:$G$652,$R86)="","",INDEX('_list'!$G$2:$G$652,$R86))) | G86: =IF($S86="","",IF(INDEX('_pockets'!$AH:$AH,$S86)="","",INDEX('_pockets'!$AH:$AH,$S86))) | H86: =IF($S86="","",IF(INDEX('_pockets'!$AF:$AF,$S86)="","",INDEX('_pockets'!$AF:$AF,$S86))) | I86: =IF(IF($S86="","",IF(INDEX('_pockets'!$AB:$AB,$S86)="","",INDEX('_pockets'!$AB:$AB,$S86)))="","",IF($S86="","",IF(INDEX('_pockets'!$AB:$AB,$S86)="","",INDEX('_pockets'!$AB:$AB,$S86)))*IF($U$19,100,1)) | J86: =IF($S86="","",IF(INDEX('_pockets'!$Z:$Z,$S86)="","",INDEX('_pockets'!$Z:$Z,$S86))) | K86: =IF($R86="","",IF(INDEX('_list'!$K$2:$K$652,$R86)="","",INDEX('_list'!$K$2:$K$652,$R86))) | L86: =IF($S86="","",IF(INDEX('_pockets'!$AC:$AC,$S86)="","",INDEX('_pockets'!$AC:$AC,$S86))) | M86: =IF($R86="","",IF(INDEX('_list'!$L$2:$L$652,$R86)="","",INDEX('_list'!$L$2:$L$652,$R86))) | N86: =IF($R86="","",IF(INDEX('_list'!$H$2:$H$652,$R86)="","",INDEX('_list'!$H$2:$H$652,$R86))) | O86: =IF($R86="","",IF(INDEX('_list'!$I$2:$I$652,$R86)="","",INDEX('_list'!$I$2:$I$652,$R86))) | R86: =IFERROR(MATCH(66,'_list'!$N$2:$N$652,0),"") | S86: =IF($R86="","",INDEX('_list'!$C$2:$C$652,$R86))
B87: =IF($R87="","",67) | C87: =IF($R87="","",IF(INDEX('_list'!$D$2:$D$652,$R87)="","",INDEX('_list'!$D$2:$D$652,$R87))) | D87: =IF($R87="","",IF(INDEX('_list'!$E$2:$E$652,$R87)="","",INDEX('_list'!$E$2:$E$652,$R87))) | E87: =IF($R87="","",IF(INDEX('_list'!$F$2:$F$652,$R87)="","",INDEX('_list'!$F$2:$F$652,$R87))) | F87: =IF($R87="","",IF(INDEX('_list'!$G$2:$G$652,$R87)="","",INDEX('_list'!$G$2:$G$652,$R87))) | G87: =IF($S87="","",IF(INDEX('_pockets'!$AH:$AH,$S87)="","",INDEX('_pockets'!$AH:$AH,$S87))) | H87: =IF($S87="","",IF(INDEX('_pockets'!$AF:$AF,$S87)="","",INDEX('_pockets'!$AF:$AF,$S87))) | I87: =IF(IF($S87="","",IF(INDEX('_pockets'!$AB:$AB,$S87)="","",INDEX('_pockets'!$AB:$AB,$S87)))="","",IF($S87="","",IF(INDEX('_pockets'!$AB:$AB,$S87)="","",INDEX('_pockets'!$AB:$AB,$S87)))*IF($U$19,100,1)) | J87: =IF($S87="","",IF(INDEX('_pockets'!$Z:$Z,$S87)="","",INDEX('_pockets'!$Z:$Z,$S87))) | K87: =IF($R87="","",IF(INDEX('_list'!$K$2:$K$652,$R87)="","",INDEX('_list'!$K$2:$K$652,$R87))) | L87: =IF($S87="","",IF(INDEX('_pockets'!$AC:$AC,$S87)="","",INDEX('_pockets'!$AC:$AC,$S87))) | M87: =IF($R87="","",IF(INDEX('_list'!$L$2:$L$652,$R87)="","",INDEX('_list'!$L$2:$L$652,$R87))) | N87: =IF($R87="","",IF(INDEX('_list'!$H$2:$H$652,$R87)="","",INDEX('_list'!$H$2:$H$652,$R87))) | O87: =IF($R87="","",IF(INDEX('_list'!$I$2:$I$652,$R87)="","",INDEX('_list'!$I$2:$I$652,$R87))) | R87: =IFERROR(MATCH(67,'_list'!$N$2:$N$652,0),"") | S87: =IF($R87="","",INDEX('_list'!$C$2:$C$652,$R87))
B88: =IF($R88="","",68) | C88: =IF($R88="","",IF(INDEX('_list'!$D$2:$D$652,$R88)="","",INDEX('_list'!$D$2:$D$652,$R88))) | D88: =IF($R88="","",IF(INDEX('_list'!$E$2:$E$652,$R88)="","",INDEX('_list'!$E$2:$E$652,$R88))) | E88: =IF($R88="","",IF(INDEX('_list'!$F$2:$F$652,$R88)="","",INDEX('_list'!$F$2:$F$652,$R88))) | F88: =IF($R88="","",IF(INDEX('_list'!$G$2:$G$652,$R88)="","",INDEX('_list'!$G$2:$G$652,$R88))) | G88: =IF($S88="","",IF(INDEX('_pockets'!$AH:$AH,$S88)="","",INDEX('_pockets'!$AH:$AH,$S88))) | H88: =IF($S88="","",IF(INDEX('_pockets'!$AF:$AF,$S88)="","",INDEX('_pockets'!$AF:$AF,$S88))) | I88: =IF(IF($S88="","",IF(INDEX('_pockets'!$AB:$AB,$S88)="","",INDEX('_pockets'!$AB:$AB,$S88)))="","",IF($S88="","",IF(INDEX('_pockets'!$AB:$AB,$S88)="","",INDEX('_pockets'!$AB:$AB,$S88)))*IF($U$19,100,1)) | J88: =IF($S88="","",IF(INDEX('_pockets'!$Z:$Z,$S88)="","",INDEX('_pockets'!$Z:$Z,$S88))) | K88: =IF($R88="","",IF(INDEX('_list'!$K$2:$K$652,$R88)="","",INDEX('_list'!$K$2:$K$652,$R88))) | L88: =IF($S88="","",IF(INDEX('_pockets'!$AC:$AC,$S88)="","",INDEX('_pockets'!$AC:$AC,$S88))) | M88: =IF($R88="","",IF(INDEX('_list'!$L$2:$L$652,$R88)="","",INDEX('_list'!$L$2:$L$652,$R88))) | N88: =IF($R88="","",IF(INDEX('_list'!$H$2:$H$652,$R88)="","",INDEX('_list'!$H$2:$H$652,$R88))) | O88: =IF($R88="","",IF(INDEX('_list'!$I$2:$I$652,$R88)="","",INDEX('_list'!$I$2:$I$652,$R88))) | R88: =IFERROR(MATCH(68,'_list'!$N$2:$N$652,0),"") | S88: =IF($R88="","",INDEX('_list'!$C$2:$C$652,$R88))
B89: =IF($R89="","",69) | C89: =IF($R89="","",IF(INDEX('_list'!$D$2:$D$652,$R89)="","",INDEX('_list'!$D$2:$D$652,$R89))) | D89: =IF($R89="","",IF(INDEX('_list'!$E$2:$E$652,$R89)="","",INDEX('_list'!$E$2:$E$652,$R89))) | E89: =IF($R89="","",IF(INDEX('_list'!$F$2:$F$652,$R89)="","",INDEX('_list'!$F$2:$F$652,$R89))) | F89: =IF($R89="","",IF(INDEX('_list'!$G$2:$G$652,$R89)="","",INDEX('_list'!$G$2:$G$652,$R89))) | G89: =IF($S89="","",IF(INDEX('_pockets'!$AH:$AH,$S89)="","",INDEX('_pockets'!$AH:$AH,$S89))) | H89: =IF($S89="","",IF(INDEX('_pockets'!$AF:$AF,$S89)="","",INDEX('_pockets'!$AF:$AF,$S89))) | I89: =IF(IF($S89="","",IF(INDEX('_pockets'!$AB:$AB,$S89)="","",INDEX('_pockets'!$AB:$AB,$S89)))="","",IF($S89="","",IF(INDEX('_pockets'!$AB:$AB,$S89)="","",INDEX('_pockets'!$AB:$AB,$S89)))*IF($U$19,100,1)) | J89: =IF($S89="","",IF(INDEX('_pockets'!$Z:$Z,$S89)="","",INDEX('_pockets'!$Z:$Z,$S89))) | K89: =IF($R89="","",IF(INDEX('_list'!$K$2:$K$652,$R89)="","",INDEX('_list'!$K$2:$K$652,$R89))) | L89: =IF($S89="","",IF(INDEX('_pockets'!$AC:$AC,$S89)="","",INDEX('_pockets'!$AC:$AC,$S89))) | M89: =IF($R89="","",IF(INDEX('_list'!$L$2:$L$652,$R89)="","",INDEX('_list'!$L$2:$L$652,$R89))) | N89: =IF($R89="","",IF(INDEX('_list'!$H$2:$H$652,$R89)="","",INDEX('_list'!$H$2:$H$652,$R89))) | O89: =IF($R89="","",IF(INDEX('_list'!$I$2:$I$652,$R89)="","",INDEX('_list'!$I$2:$I$652,$R89))) | R89: =IFERROR(MATCH(69,'_list'!$N$2:$N$652,0),"") | S89: =IF($R89="","",INDEX('_list'!$C$2:$C$652,$R89))
B90: =IF($R90="","",70) | C90: =IF($R90="","",IF(INDEX('_list'!$D$2:$D$652,$R90)="","",INDEX('_list'!$D$2:$D$652,$R90))) | D90: =IF($R90="","",IF(INDEX('_list'!$E$2:$E$652,$R90)="","",INDEX('_list'!$E$2:$E$652,$R90))) | E90: =IF($R90="","",IF(INDEX('_list'!$F$2:$F$652,$R90)="","",INDEX('_list'!$F$2:$F$652,$R90))) | F90: =IF($R90="","",IF(INDEX('_list'!$G$2:$G$652,$R90)="","",INDEX('_list'!$G$2:$G$652,$R90))) | G90: =IF($S90="","",IF(INDEX('_pockets'!$AH:$AH,$S90)="","",INDEX('_pockets'!$AH:$AH,$S90))) | H90: =IF($S90="","",IF(INDEX('_pockets'!$AF:$AF,$S90)="","",INDEX('_pockets'!$AF:$AF,$S90))) | I90: =IF(IF($S90="","",IF(INDEX('_pockets'!$AB:$AB,$S90)="","",INDEX('_pockets'!$AB:$AB,$S90)))="","",IF($S90="","",IF(INDEX('_pockets'!$AB:$AB,$S90)="","",INDEX('_pockets'!$AB:$AB,$S90)))*IF($U$19,100,1)) | J90: =IF($S90="","",IF(INDEX('_pockets'!$Z:$Z,$S90)="","",INDEX('_pockets'!$Z:$Z,$S90))) | K90: =IF($R90="","",IF(INDEX('_list'!$K$2:$K$652,$R90)="","",INDEX('_list'!$K$2:$K$652,$R90))) | L90: =IF($S90="","",IF(INDEX('_pockets'!$AC:$AC,$S90)="","",INDEX('_pockets'!$AC:$AC,$S90))) | M90: =IF($R90="","",IF(INDEX('_list'!$L$2:$L$652,$R90)="","",INDEX('_list'!$L$2:$L$652,$R90))) | N90: =IF($R90="","",IF(INDEX('_list'!$H$2:$H$652,$R90)="","",INDEX('_list'!$H$2:$H$652,$R90))) | O90: =IF($R90="","",IF(INDEX('_list'!$I$2:$I$652,$R90)="","",INDEX('_list'!$I$2:$I$652,$R90))) | R90: =IFERROR(MATCH(70,'_list'!$N$2:$N$652,0),"") | S90: =IF($R90="","",INDEX('_list'!$C$2:$C$652,$R90))
B91: =IF($R91="","",71) | C91: =IF($R91="","",IF(INDEX('_list'!$D$2:$D$652,$R91)="","",INDEX('_list'!$D$2:$D$652,$R91))) | D91: =IF($R91="","",IF(INDEX('_list'!$E$2:$E$652,$R91)="","",INDEX('_list'!$E$2:$E$652,$R91))) | E91: =IF($R91="","",IF(INDEX('_list'!$F$2:$F$652,$R91)="","",INDEX('_list'!$F$2:$F$652,$R91))) | F91: =IF($R91="","",IF(INDEX('_list'!$G$2:$G$652,$R91)="","",INDEX('_list'!$G$2:$G$652,$R91))) | G91: =IF($S91="","",IF(INDEX('_pockets'!$AH:$AH,$S91)="","",INDEX('_pockets'!$AH:$AH,$S91))) | H91: =IF($S91="","",IF(INDEX('_pockets'!$AF:$AF,$S91)="","",INDEX('_pockets'!$AF:$AF,$S91))) | I91: =IF(IF($S91="","",IF(INDEX('_pockets'!$AB:$AB,$S91)="","",INDEX('_pockets'!$AB:$AB,$S91)))="","",IF($S91="","",IF(INDEX('_pockets'!$AB:$AB,$S91)="","",INDEX('_pockets'!$AB:$AB,$S91)))*IF($U$19,100,1)) | J91: =IF($S91="","",IF(INDEX('_pockets'!$Z:$Z,$S91)="","",INDEX('_pockets'!$Z:$Z,$S91))) | K91: =IF($R91="","",IF(INDEX('_list'!$K$2:$K$652,$R91)="","",INDEX('_list'!$K$2:$K$652,$R91))) | L91: =IF($S91="","",IF(INDEX('_pockets'!$AC:$AC,$S91)="","",INDEX('_pockets'!$AC:$AC,$S91))) | M91: =IF($R91="","",IF(INDEX('_list'!$L$2:$L$652,$R91)="","",INDEX('_list'!$L$2:$L$652,$R91))) | N91: =IF($R91="","",IF(INDEX('_list'!$H$2:$H$652,$R91)="","",INDEX('_list'!$H$2:$H$652,$R91))) | O91: =IF($R91="","",IF(INDEX('_list'!$I$2:$I$652,$R91)="","",INDEX('_list'!$I$2:$I$652,$R91))) | R91: =IFERROR(MATCH(71,'_list'!$N$2:$N$652,0),"") | S91: =IF($R91="","",INDEX('_list'!$C$2:$C$652,$R91))
B92: =IF($R92="","",72) | C92: =IF($R92="","",IF(INDEX('_list'!$D$2:$D$652,$R92)="","",INDEX('_list'!$D$2:$D$652,$R92))) | D92: =IF($R92="","",IF(INDEX('_list'!$E$2:$E$652,$R92)="","",INDEX('_list'!$E$2:$E$652,$R92))) | E92: =IF($R92="","",IF(INDEX('_list'!$F$2:$F$652,$R92)="","",INDEX('_list'!$F$2:$F$652,$R92))) | F92: =IF($R92="","",IF(INDEX('_list'!$G$2:$G$652,$R92)="","",INDEX('_list'!$G$2:$G$652,$R92))) | G92: =IF($S92="","",IF(INDEX('_pockets'!$AH:$AH,$S92)="","",INDEX('_pockets'!$AH:$AH,$S92))) | H92: =IF($S92="","",IF(INDEX('_pockets'!$AF:$AF,$S92)="","",INDEX('_pockets'!$AF:$AF,$S92))) | I92: =IF(IF($S92="","",IF(INDEX('_pockets'!$AB:$AB,$S92)="","",INDEX('_pockets'!$AB:$AB,$S92)))="","",IF($S92="","",IF(INDEX('_pockets'!$AB:$AB,$S92)="","",INDEX('_pockets'!$AB:$AB,$S92)))*IF($U$19,100,1)) | J92: =IF($S92="","",IF(INDEX('_pockets'!$Z:$Z,$S92)="","",INDEX('_pockets'!$Z:$Z,$S92))) | K92: =IF($R92="","",IF(INDEX('_list'!$K$2:$K$652,$R92)="","",INDEX('_list'!$K$2:$K$652,$R92))) | L92: =IF($S92="","",IF(INDEX('_pockets'!$AC:$AC,$S92)="","",INDEX('_pockets'!$AC:$AC,$S92))) | M92: =IF($R92="","",IF(INDEX('_list'!$L$2:$L$652,$R92)="","",INDEX('_list'!$L$2:$L$652,$R92))) | N92: =IF($R92="","",IF(INDEX('_list'!$H$2:$H$652,$R92)="","",INDEX('_list'!$H$2:$H$652,$R92))) | O92: =IF($R92="","",IF(INDEX('_list'!$I$2:$I$652,$R92)="","",INDEX('_list'!$I$2:$I$652,$R92))) | R92: =IFERROR(MATCH(72,'_list'!$N$2:$N$652,0),"") | S92: =IF($R92="","",INDEX('_list'!$C$2:$C$652,$R92))
B93: =IF($R93="","",73) | C93: =IF($R93="","",IF(INDEX('_list'!$D$2:$D$652,$R93)="","",INDEX('_list'!$D$2:$D$652,$R93))) | D93: =IF($R93="","",IF(INDEX('_list'!$E$2:$E$652,$R93)="","",INDEX('_list'!$E$2:$E$652,$R93))) | E93: =IF($R93="","",IF(INDEX('_list'!$F$2:$F$652,$R93)="","",INDEX('_list'!$F$2:$F$652,$R93))) | F93: =IF($R93="","",IF(INDEX('_list'!$G$2:$G$652,$R93)="","",INDEX('_list'!$G$2:$G$652,$R93))) | G93: =IF($S93="","",IF(INDEX('_pockets'!$AH:$AH,$S93)="","",INDEX('_pockets'!$AH:$AH,$S93))) | H93: =IF($S93="","",IF(INDEX('_pockets'!$AF:$AF,$S93)="","",INDEX('_pockets'!$AF:$AF,$S93))) | I93: =IF(IF($S93="","",IF(INDEX('_pockets'!$AB:$AB,$S93)="","",INDEX('_pockets'!$AB:$AB,$S93)))="","",IF($S93="","",IF(INDEX('_pockets'!$AB:$AB,$S93)="","",INDEX('_pockets'!$AB:$AB,$S93)))*IF($U$19,100,1)) | J93: =IF($S93="","",IF(INDEX('_pockets'!$Z:$Z,$S93)="","",INDEX('_pockets'!$Z:$Z,$S93))) | K93: =IF($R93="","",IF(INDEX('_list'!$K$2:$K$652,$R93)="","",INDEX('_list'!$K$2:$K$652,$R93))) | L93: =IF($S93="","",IF(INDEX('_pockets'!$AC:$AC,$S93)="","",INDEX('_pockets'!$AC:$AC,$S93))) | M93: =IF($R93="","",IF(INDEX('_list'!$L$2:$L$652,$R93)="","",INDEX('_list'!$L$2:$L$652,$R93))) | N93: =IF($R93="","",IF(INDEX('_list'!$H$2:$H$652,$R93)="","",INDEX('_list'!$H$2:$H$652,$R93))) | O93: =IF($R93="","",IF(INDEX('_list'!$I$2:$I$652,$R93)="","",INDEX('_list'!$I$2:$I$652,$R93))) | R93: =IFERROR(MATCH(73,'_list'!$N$2:$N$652,0),"") | S93: =IF($R93="","",INDEX('_list'!$C$2:$C$652,$R93))
B94: =IF($R94="","",74) | C94: =IF($R94="","",IF(INDEX('_list'!$D$2:$D$652,$R94)="","",INDEX('_list'!$D$2:$D$652,$R94))) | D94: =IF($R94="","",IF(INDEX('_list'!$E$2:$E$652,$R94)="","",INDEX('_list'!$E$2:$E$652,$R94))) | E94: =IF($R94="","",IF(INDEX('_list'!$F$2:$F$652,$R94)="","",INDEX('_list'!$F$2:$F$652,$R94))) | F94: =IF($R94="","",IF(INDEX('_list'!$G$2:$G$652,$R94)="","",INDEX('_list'!$G$2:$G$652,$R94))) | G94: =IF($S94="","",IF(INDEX('_pockets'!$AH:$AH,$S94)="","",INDEX('_pockets'!$AH:$AH,$S94))) | H94: =IF($S94="","",IF(INDEX('_pockets'!$AF:$AF,$S94)="","",INDEX('_pockets'!$AF:$AF,$S94))) | I94: =IF(IF($S94="","",IF(INDEX('_pockets'!$AB:$AB,$S94)="","",INDEX('_pockets'!$AB:$AB,$S94)))="","",IF($S94="","",IF(INDEX('_pockets'!$AB:$AB,$S94)="","",INDEX('_pockets'!$AB:$AB,$S94)))*IF($U$19,100,1)) | J94: =IF($S94="","",IF(INDEX('_pockets'!$Z:$Z,$S94)="","",INDEX('_pockets'!$Z:$Z,$S94))) | K94: =IF($R94="","",IF(INDEX('_list'!$K$2:$K$652,$R94)="","",INDEX('_list'!$K$2:$K$652,$R94))) | L94: =IF($S94="","",IF(INDEX('_pockets'!$AC:$AC,$S94)="","",INDEX('_pockets'!$AC:$AC,$S94))) | M94: =IF($R94="","",IF(INDEX('_list'!$L$2:$L$652,$R94)="","",INDEX('_list'!$L$2:$L$652,$R94))) | N94: =IF($R94="","",IF(INDEX('_list'!$H$2:$H$652,$R94)="","",INDEX('_list'!$H$2:$H$652,$R94))) | O94: =IF($R94="","",IF(INDEX('_list'!$I$2:$I$652,$R94)="","",INDEX('_list'!$I$2:$I$652,$R94))) | R94: =IFERROR(MATCH(74,'_list'!$N$2:$N$652,0),"") | S94: =IF($R94="","",INDEX('_list'!$C$2:$C$652,$R94))
B95: =IF($R95="","",75) | C95: =IF($R95="","",IF(INDEX('_list'!$D$2:$D$652,$R95)="","",INDEX('_list'!$D$2:$D$652,$R95))) | D95: =IF($R95="","",IF(INDEX('_list'!$E$2:$E$652,$R95)="","",INDEX('_list'!$E$2:$E$652,$R95))) | E95: =IF($R95="","",IF(INDEX('_list'!$F$2:$F$652,$R95)="","",INDEX('_list'!$F$2:$F$652,$R95))) | F95: =IF($R95="","",IF(INDEX('_list'!$G$2:$G$652,$R95)="","",INDEX('_list'!$G$2:$G$652,$R95))) | G95: =IF($S95="","",IF(INDEX('_pockets'!$AH:$AH,$S95)="","",INDEX('_pockets'!$AH:$AH,$S95))) | H95: =IF($S95="","",IF(INDEX('_pockets'!$AF:$AF,$S95)="","",INDEX('_pockets'!$AF:$AF,$S95))) | I95: =IF(IF($S95="","",IF(INDEX('_pockets'!$AB:$AB,$S95)="","",INDEX('_pockets'!$AB:$AB,$S95)))="","",IF($S95="","",IF(INDEX('_pockets'!$AB:$AB,$S95)="","",INDEX('_pockets'!$AB:$AB,$S95)))*IF($U$19,100,1)) | J95: =IF($S95="","",IF(INDEX('_pockets'!$Z:$Z,$S95)="","",INDEX('_pockets'!$Z:$Z,$S95))) | K95: =IF($R95="","",IF(INDEX('_list'!$K$2:$K$652,$R95)="","",INDEX('_list'!$K$2:$K$652,$R95))) | L95: =IF($S95="","",IF(INDEX('_pockets'!$AC:$AC,$S95)="","",INDEX('_pockets'!$AC:$AC,$S95))) | M95: =IF($R95="","",IF(INDEX('_list'!$L$2:$L$652,$R95)="","",INDEX('_list'!$L$2:$L$652,$R95))) | N95: =IF($R95="","",IF(INDEX('_list'!$H$2:$H$652,$R95)="","",INDEX('_list'!$H$2:$H$652,$R95))) | O95: =IF($R95="","",IF(INDEX('_list'!$I$2:$I$652,$R95)="","",INDEX('_list'!$I$2:$I$652,$R95))) | R95: =IFERROR(MATCH(75,'_list'!$N$2:$N$652,0),"") | S95: =IF($R95="","",INDEX('_list'!$C$2:$C$652,$R95))
B96: =IF($R96="","",76) | C96: =IF($R96="","",IF(INDEX('_list'!$D$2:$D$652,$R96)="","",INDEX('_list'!$D$2:$D$652,$R96))) | D96: =IF($R96="","",IF(INDEX('_list'!$E$2:$E$652,$R96)="","",INDEX('_list'!$E$2:$E$652,$R96))) | E96: =IF($R96="","",IF(INDEX('_list'!$F$2:$F$652,$R96)="","",INDEX('_list'!$F$2:$F$652,$R96))) | F96: =IF($R96="","",IF(INDEX('_list'!$G$2:$G$652,$R96)="","",INDEX('_list'!$G$2:$G$652,$R96))) | G96: =IF($S96="","",IF(INDEX('_pockets'!$AH:$AH,$S96)="","",INDEX('_pockets'!$AH:$AH,$S96))) | H96: =IF($S96="","",IF(INDEX('_pockets'!$AF:$AF,$S96)="","",INDEX('_pockets'!$AF:$AF,$S96))) | I96: =IF(IF($S96="","",IF(INDEX('_pockets'!$AB:$AB,$S96)="","",INDEX('_pockets'!$AB:$AB,$S96)))="","",IF($S96="","",IF(INDEX('_pockets'!$AB:$AB,$S96)="","",INDEX('_pockets'!$AB:$AB,$S96)))*IF($U$19,100,1)) | J96: =IF($S96="","",IF(INDEX('_pockets'!$Z:$Z,$S96)="","",INDEX('_pockets'!$Z:$Z,$S96))) | K96: =IF($R96="","",IF(INDEX('_list'!$K$2:$K$652,$R96)="","",INDEX('_list'!$K$2:$K$652,$R96))) | L96: =IF($S96="","",IF(INDEX('_pockets'!$AC:$AC,$S96)="","",INDEX('_pockets'!$AC:$AC,$S96))) | M96: =IF($R96="","",IF(INDEX('_list'!$L$2:$L$652,$R96)="","",INDEX('_list'!$L$2:$L$652,$R96))) | N96: =IF($R96="","",IF(INDEX('_list'!$H$2:$H$652,$R96)="","",INDEX('_list'!$H$2:$H$652,$R96))) | O96: =IF($R96="","",IF(INDEX('_list'!$I$2:$I$652,$R96)="","",INDEX('_list'!$I$2:$I$652,$R96))) | R96: =IFERROR(MATCH(76,'_list'!$N$2:$N$652,0),"") | S96: =IF($R96="","",INDEX('_list'!$C$2:$C$652,$R96))
B97: =IF($R97="","",77) | C97: =IF($R97="","",IF(INDEX('_list'!$D$2:$D$652,$R97)="","",INDEX('_list'!$D$2:$D$652,$R97))) | D97: =IF($R97="","",IF(INDEX('_list'!$E$2:$E$652,$R97)="","",INDEX('_list'!$E$2:$E$652,$R97))) | E97: =IF($R97="","",IF(INDEX('_list'!$F$2:$F$652,$R97)="","",INDEX('_list'!$F$2:$F$652,$R97))) | F97: =IF($R97="","",IF(INDEX('_list'!$G$2:$G$652,$R97)="","",INDEX('_list'!$G$2:$G$652,$R97))) | G97: =IF($S97="","",IF(INDEX('_pockets'!$AH:$AH,$S97)="","",INDEX('_pockets'!$AH:$AH,$S97))) | H97: =IF($S97="","",IF(INDEX('_pockets'!$AF:$AF,$S97)="","",INDEX('_pockets'!$AF:$AF,$S97))) | I97: =IF(IF($S97="","",IF(INDEX('_pockets'!$AB:$AB,$S97)="","",INDEX('_pockets'!$AB:$AB,$S97)))="","",IF($S97="","",IF(INDEX('_pockets'!$AB:$AB,$S97)="","",INDEX('_pockets'!$AB:$AB,$S97)))*IF($U$19,100,1)) | J97: =IF($S97="","",IF(INDEX('_pockets'!$Z:$Z,$S97)="","",INDEX('_pockets'!$Z:$Z,$S97))) | K97: =IF($R97="","",IF(INDEX('_list'!$K$2:$K$652,$R97)="","",INDEX('_list'!$K$2:$K$652,$R97))) | L97: =IF($S97="","",IF(INDEX('_pockets'!$AC:$AC,$S97)="","",INDEX('_pockets'!$AC:$AC,$S97))) | M97: =IF($R97="","",IF(INDEX('_list'!$L$2:$L$652,$R97)="","",INDEX('_list'!$L$2:$L$652,$R97))) | N97: =IF($R97="","",IF(INDEX('_list'!$H$2:$H$652,$R97)="","",INDEX('_list'!$H$2:$H$652,$R97))) | O97: =IF($R97="","",IF(INDEX('_list'!$I$2:$I$652,$R97)="","",INDEX('_list'!$I$2:$I$652,$R97))) | R97: =IFERROR(MATCH(77,'_list'!$N$2:$N$652,0),"") | S97: =IF($R97="","",INDEX('_list'!$C$2:$C$652,$R97))
B98: =IF($R98="","",78) | C98: =IF($R98="","",IF(INDEX('_list'!$D$2:$D$652,$R98)="","",INDEX('_list'!$D$2:$D$652,$R98))) | D98: =IF($R98="","",IF(INDEX('_list'!$E$2:$E$652,$R98)="","",INDEX('_list'!$E$2:$E$652,$R98))) | E98: =IF($R98="","",IF(INDEX('_list'!$F$2:$F$652,$R98)="","",INDEX('_list'!$F$2:$F$652,$R98))) | F98: =IF($R98="","",IF(INDEX('_list'!$G$2:$G$652,$R98)="","",INDEX('_list'!$G$2:$G$652,$R98))) | G98: =IF($S98="","",IF(INDEX('_pockets'!$AH:$AH,$S98)="","",INDEX('_pockets'!$AH:$AH,$S98))) | H98: =IF($S98="","",IF(INDEX('_pockets'!$AF:$AF,$S98)="","",INDEX('_pockets'!$AF:$AF,$S98))) | I98: =IF(IF($S98="","",IF(INDEX('_pockets'!$AB:$AB,$S98)="","",INDEX('_pockets'!$AB:$AB,$S98)))="","",IF($S98="","",IF(INDEX('_pockets'!$AB:$AB,$S98)="","",INDEX('_pockets'!$AB:$AB,$S98)))*IF($U$19,100,1)) | J98: =IF($S98="","",IF(INDEX('_pockets'!$Z:$Z,$S98)="","",INDEX('_pockets'!$Z:$Z,$S98))) | K98: =IF($R98="","",IF(INDEX('_list'!$K$2:$K$652,$R98)="","",INDEX('_list'!$K$2:$K$652,$R98))) | L98: =IF($S98="","",IF(INDEX('_pockets'!$AC:$AC,$S98)="","",INDEX('_pockets'!$AC:$AC,$S98))) | M98: =IF($R98="","",IF(INDEX('_list'!$L$2:$L$652,$R98)="","",INDEX('_list'!$L$2:$L$652,$R98))) | N98: =IF($R98="","",IF(INDEX('_list'!$H$2:$H$652,$R98)="","",INDEX('_list'!$H$2:$H$652,$R98))) | O98: =IF($R98="","",IF(INDEX('_list'!$I$2:$I$652,$R98)="","",INDEX('_list'!$I$2:$I$652,$R98))) | R98: =IFERROR(MATCH(78,'_list'!$N$2:$N$652,0),"") | S98: =IF($R98="","",INDEX('_list'!$C$2:$C$652,$R98))
B99: =IF($R99="","",79) | C99: =IF($R99="","",IF(INDEX('_list'!$D$2:$D$652,$R99)="","",INDEX('_list'!$D$2:$D$652,$R99))) | D99: =IF($R99="","",IF(INDEX('_list'!$E$2:$E$652,$R99)="","",INDEX('_list'!$E$2:$E$652,$R99))) | E99: =IF($R99="","",IF(INDEX('_list'!$F$2:$F$652,$R99)="","",INDEX('_list'!$F$2:$F$652,$R99))) | F99: =IF($R99="","",IF(INDEX('_list'!$G$2:$G$652,$R99)="","",INDEX('_list'!$G$2:$G$652,$R99))) | G99: =IF($S99="","",IF(INDEX('_pockets'!$AH:$AH,$S99)="","",INDEX('_pockets'!$AH:$AH,$S99))) | H99: =IF($S99="","",IF(INDEX('_pockets'!$AF:$AF,$S99)="","",INDEX('_pockets'!$AF:$AF,$S99))) | I99: =IF(IF($S99="","",IF(INDEX('_pockets'!$AB:$AB,$S99)="","",INDEX('_pockets'!$AB:$AB,$S99)))="","",IF($S99="","",IF(INDEX('_pockets'!$AB:$AB,$S99)="","",INDEX('_pockets'!$AB:$AB,$S99)))*IF($U$19,100,1)) | J99: =IF($S99="","",IF(INDEX('_pockets'!$Z:$Z,$S99)="","",INDEX('_pockets'!$Z:$Z,$S99))) | K99: =IF($R99="","",IF(INDEX('_list'!$K$2:$K$652,$R99)="","",INDEX('_list'!$K$2:$K$652,$R99))) | L99: =IF($S99="","",IF(INDEX('_pockets'!$AC:$AC,$S99)="","",INDEX('_pockets'!$AC:$AC,$S99))) | M99: =IF($R99="","",IF(INDEX('_list'!$L$2:$L$652,$R99)="","",INDEX('_list'!$L$2:$L$652,$R99))) | N99: =IF($R99="","",IF(INDEX('_list'!$H$2:$H$652,$R99)="","",INDEX('_list'!$H$2:$H$652,$R99))) | O99: =IF($R99="","",IF(INDEX('_list'!$I$2:$I$652,$R99)="","",INDEX('_list'!$I$2:$I$652,$R99))) | R99: =IFERROR(MATCH(79,'_list'!$N$2:$N$652,0),"") | S99: =IF($R99="","",INDEX('_list'!$C$2:$C$652,$R99))
B100: =IF($R100="","",80) | C100: =IF($R100="","",IF(INDEX('_list'!$D$2:$D$652,$R100)="","",INDEX('_list'!$D$2:$D$652,$R100))) | D100: =IF($R100="","",IF(INDEX('_list'!$E$2:$E$652,$R100)="","",INDEX('_list'!$E$2:$E$652,$R100))) | E100: =IF($R100="","",IF(INDEX('_list'!$F$2:$F$652,$R100)="","",INDEX('_list'!$F$2:$F$652,$R100))) | F100: =IF($R100="","",IF(INDEX('_list'!$G$2:$G$652,$R100)="","",INDEX('_list'!$G$2:$G$652,$R100))) | G100: =IF($S100="","",IF(INDEX('_pockets'!$AH:$AH,$S100)="","",INDEX('_pockets'!$AH:$AH,$S100))) | H100: =IF($S100="","",IF(INDEX('_pockets'!$AF:$AF,$S100)="","",INDEX('_pockets'!$AF:$AF,$S100))) | I100: =IF(IF($S100="","",IF(INDEX('_pockets'!$AB:$AB,$S100)="","",INDEX('_pockets'!$AB:$AB,$S100)))="","",IF($S100="","",IF(INDEX('_pockets'!$AB:$AB,$S100)="","",INDEX('_pockets'!$AB:$AB,$S100)))*IF($U$19,100,1)) | J100: =IF($S100="","",IF(INDEX('_pockets'!$Z:$Z,$S100)="","",INDEX('_pockets'!$Z:$Z,$S100))) | K100: =IF($R100="","",IF(INDEX('_list'!$K$2:$K$652,$R100)="","",INDEX('_list'!$K$2:$K$652,$R100))) | L100: =IF($S100="","",IF(INDEX('_pockets'!$AC:$AC,$S100)="","",INDEX('_pockets'!$AC:$AC,$S100))) | M100: =IF($R100="","",IF(INDEX('_list'!$L$2:$L$652,$R100)="","",INDEX('_list'!$L$2:$L$652,$R100))) | N100: =IF($R100="","",IF(INDEX('_list'!$H$2:$H$652,$R100)="","",INDEX('_list'!$H$2:$H$652,$R100))) | O100: =IF($R100="","",IF(INDEX('_list'!$I$2:$I$652,$R100)="","",INDEX('_list'!$I$2:$I$652,$R100))) | R100: =IFERROR(MATCH(80,'_list'!$N$2:$N$652,0),"") | S100: =IF($R100="","",INDEX('_list'!$C$2:$C$652,$R100))
B101: =IF($R101="","",81) | C101: =IF($R101="","",IF(INDEX('_list'!$D$2:$D$652,$R101)="","",INDEX('_list'!$D$2:$D$652,$R101))) | D101: =IF($R101="","",IF(INDEX('_list'!$E$2:$E$652,$R101)="","",INDEX('_list'!$E$2:$E$652,$R101))) | E101: =IF($R101="","",IF(INDEX('_list'!$F$2:$F$652,$R101)="","",INDEX('_list'!$F$2:$F$652,$R101))) | F101: =IF($R101="","",IF(INDEX('_list'!$G$2:$G$652,$R101)="","",INDEX('_list'!$G$2:$G$652,$R101))) | G101: =IF($S101="","",IF(INDEX('_pockets'!$AH:$AH,$S101)="","",INDEX('_pockets'!$AH:$AH,$S101))) | H101: =IF($S101="","",IF(INDEX('_pockets'!$AF:$AF,$S101)="","",INDEX('_pockets'!$AF:$AF,$S101))) | I101: =IF(IF($S101="","",IF(INDEX('_pockets'!$AB:$AB,$S101)="","",INDEX('_pockets'!$AB:$AB,$S101)))="","",IF($S101="","",IF(INDEX('_pockets'!$AB:$AB,$S101)="","",INDEX('_pockets'!$AB:$AB,$S101)))*IF($U$19,100,1)) | J101: =IF($S101="","",IF(INDEX('_pockets'!$Z:$Z,$S101)="","",INDEX('_pockets'!$Z:$Z,$S101))) | K101: =IF($R101="","",IF(INDEX('_list'!$K$2:$K$652,$R101)="","",INDEX('_list'!$K$2:$K$652,$R101))) | L101: =IF($S101="","",IF(INDEX('_pockets'!$AC:$AC,$S101)="","",INDEX('_pockets'!$AC:$AC,$S101))) | M101: =IF($R101="","",IF(INDEX('_list'!$L$2:$L$652,$R101)="","",INDEX('_list'!$L$2:$L$652,$R101))) | N101: =IF($R101="","",IF(INDEX('_list'!$H$2:$H$652,$R101)="","",INDEX('_list'!$H$2:$H$652,$R101))) | O101: =IF($R101="","",IF(INDEX('_list'!$I$2:$I$652,$R101)="","",INDEX('_list'!$I$2:$I$652,$R101))) | R101: =IFERROR(MATCH(81,'_list'!$N$2:$N$652,0),"") | S101: =IF($R101="","",INDEX('_list'!$C$2:$C$652,$R101))
B102: =IF($R102="","",82) | C102: =IF($R102="","",IF(INDEX('_list'!$D$2:$D$652,$R102)="","",INDEX('_list'!$D$2:$D$652,$R102))) | D102: =IF($R102="","",IF(INDEX('_list'!$E$2:$E$652,$R102)="","",INDEX('_list'!$E$2:$E$652,$R102))) | E102: =IF($R102="","",IF(INDEX('_list'!$F$2:$F$652,$R102)="","",INDEX('_list'!$F$2:$F$652,$R102))) | F102: =IF($R102="","",IF(INDEX('_list'!$G$2:$G$652,$R102)="","",INDEX('_list'!$G$2:$G$652,$R102))) | G102: =IF($S102="","",IF(INDEX('_pockets'!$AH:$AH,$S102)="","",INDEX('_pockets'!$AH:$AH,$S102))) | H102: =IF($S102="","",IF(INDEX('_pockets'!$AF:$AF,$S102)="","",INDEX('_pockets'!$AF:$AF,$S102))) | I102: =IF(IF($S102="","",IF(INDEX('_pockets'!$AB:$AB,$S102)="","",INDEX('_pockets'!$AB:$AB,$S102)))="","",IF($S102="","",IF(INDEX('_pockets'!$AB:$AB,$S102)="","",INDEX('_pockets'!$AB:$AB,$S102)))*IF($U$19,100,1)) | J102: =IF($S102="","",IF(INDEX('_pockets'!$Z:$Z,$S102)="","",INDEX('_pockets'!$Z:$Z,$S102))) | K102: =IF($R102="","",IF(INDEX('_list'!$K$2:$K$652,$R102)="","",INDEX('_list'!$K$2:$K$652,$R102))) | L102: =IF($S102="","",IF(INDEX('_pockets'!$AC:$AC,$S102)="","",INDEX('_pockets'!$AC:$AC,$S102))) | M102: =IF($R102="","",IF(INDEX('_list'!$L$2:$L$652,$R102)="","",INDEX('_list'!$L$2:$L$652,$R102))) | N102: =IF($R102="","",IF(INDEX('_list'!$H$2:$H$652,$R102)="","",INDEX('_list'!$H$2:$H$652,$R102))) | O102: =IF($R102="","",IF(INDEX('_list'!$I$2:$I$652,$R102)="","",INDEX('_list'!$I$2:$I$652,$R102))) | R102: =IFERROR(MATCH(82,'_list'!$N$2:$N$652,0),"") | S102: =IF($R102="","",INDEX('_list'!$C$2:$C$652,$R102))
B103: =IF($R103="","",83) | C103: =IF($R103="","",IF(INDEX('_list'!$D$2:$D$652,$R103)="","",INDEX('_list'!$D$2:$D$652,$R103))) | D103: =IF($R103="","",IF(INDEX('_list'!$E$2:$E$652,$R103)="","",INDEX('_list'!$E$2:$E$652,$R103))) | E103: =IF($R103="","",IF(INDEX('_list'!$F$2:$F$652,$R103)="","",INDEX('_list'!$F$2:$F$652,$R103))) | F103: =IF($R103="","",IF(INDEX('_list'!$G$2:$G$652,$R103)="","",INDEX('_list'!$G$2:$G$652,$R103))) | G103: =IF($S103="","",IF(INDEX('_pockets'!$AH:$AH,$S103)="","",INDEX('_pockets'!$AH:$AH,$S103))) | H103: =IF($S103="","",IF(INDEX('_pockets'!$AF:$AF,$S103)="","",INDEX('_pockets'!$AF:$AF,$S103))) | I103: =IF(IF($S103="","",IF(INDEX('_pockets'!$AB:$AB,$S103)="","",INDEX('_pockets'!$AB:$AB,$S103)))="","",IF($S103="","",IF(INDEX('_pockets'!$AB:$AB,$S103)="","",INDEX('_pockets'!$AB:$AB,$S103)))*IF($U$19,100,1)) | J103: =IF($S103="","",IF(INDEX('_pockets'!$Z:$Z,$S103)="","",INDEX('_pockets'!$Z:$Z,$S103))) | K103: =IF($R103="","",IF(INDEX('_list'!$K$2:$K$652,$R103)="","",INDEX('_list'!$K$2:$K$652,$R103))) | L103: =IF($S103="","",IF(INDEX('_pockets'!$AC:$AC,$S103)="","",INDEX('_pockets'!$AC:$AC,$S103))) | M103: =IF($R103="","",IF(INDEX('_list'!$L$2:$L$652,$R103)="","",INDEX('_list'!$L$2:$L$652,$R103))) | N103: =IF($R103="","",IF(INDEX('_list'!$H$2:$H$652,$R103)="","",INDEX('_list'!$H$2:$H$652,$R103))) | O103: =IF($R103="","",IF(INDEX('_list'!$I$2:$I$652,$R103)="","",INDEX('_list'!$I$2:$I$652,$R103))) | R103: =IFERROR(MATCH(83,'_list'!$N$2:$N$652,0),"") | S103: =IF($R103="","",INDEX('_list'!$C$2:$C$652,$R103))
...

Sheet Paid, cost, kept
B1: Paid, cost, kept | C1: What each pocket paid us, what it cost us, and what we kept.
B3: How this tab works
B4: Paid us | C4: Earned before losses: RANR + GCO per booked dollar. RANR already has the charge-offs taken out, so this adds them back. Gap: points of booked dollars ahead of (+) or short of (-) the rest; Dollars: what that comes to.
B5: Cost us | C5: Charge-offs (GCO) per booked dollar, as a multiple of the rest; Dollars: charge-offs above the rest's rate.
B6: Kept | C6: Kept after losses: RANR per booked dollar, as a gap in points and dollars, like Paid us.
B7: The rest | C7: ="Judged against on Control picks it: now "&IF(judged_band,"the rest of its band","the rest of the book")&". A pocket alone in its band is compared with the rest of the book."
B8: Shading | C8: ="Pink: worse, and real. Green: better, and real. None: it could be chance (the p-value isn't under "&TEXT(significance_bar,"0%")&"), or the pocket has too few losses to test. Charge-offs count at "&TEXT(worse_at,"0.00")&"x or "&TEXT(better_at,"0.00")&"x; profit "&IF(profit_kind="test","when its own test says so",IF(profit_kind="points","at "&TEXT(profit_line*100,"0.00")&" points either way","at a gap of $"&TEXT(profit_line,"#,##0")))&"."
B9: Together | C9: The two sides read at once. Priced for it: more charge-offs and more kept. Net drain: more charge-offs and less kept. Strong: fewer charge-offs and more kept. Safe but idle: fewer charge-offs and less kept. Earns less, not from losses: less kept while charge-offs are about the same. Losing more, profit holding: more charge-offs while what we kept is about the same. Blank: nothing to read together.
B10: Order and chart | C10: Rows are as of the last Run: the pockets read together first, then by charge-off dollars; a pocket with too few losses last. The chart shows the grid picked above, live; the pockets read together are named on it.
B12: LINES IN USE NOW | C12: Worse at | D12: Better at | F12: How sure | H12: Material at | J12: Judged against | M12: The order is from the last Run, 2026-09-29 21:04.
B13: live from Control | C13: =worse_at | D13: =better_at | F13: =confidence | H13: =IFERROR(IF(materiality_kind="none","No floor",IF(INDEX(line_values,MATCH("gco_rate",line_keys,0))="","No line",IF(FALSE,TEXT(INDEX(line_values,MATCH("gco_rate",line_keys,0)),"#,##0.0")&" bad loans","$"&TEXT(INDEX(line_values,MATCH("gco_rate",line_keys,0)),"#,##0")))),"") | J13: =IF(judged_band,"Rest of its band","Rest of the book") | M13: =IFERROR(IF(COUNTIF(Status,"↻ Waiting for a Run")=0,"","↻ "&COUNTIF(Status,"↻ Waiting for a Run")&IF(COUNTIF(Status,"↻ Waiting for a Run")=1," Control change waits for a Run."," Control changes wait for a Run.")),"")
B15: GRID
B16: FICO x CHANNEL
M17: Across: charge-offs × the rest, on a log scale. Up: kept, as a gap in points. Red: Net drain. Green: Strong or Priced for it.
E18: ="Paid us · gap vs "&IF(judged_band,"band","book") | G18: Cost us · charge-offs | I18: ="Kept · gap vs "&IF(judged_band,"band","book")
B19: Band | C19: Segment | D19: Loans | E19: Gap pts | F19: Dollars | G19: =IF(judged_band,"× band","× book") | H19: Dollars | I19: Gap pts | J19: Dollars | K19: Together
B20: =IF($AN20="","",IF(INDEX('_views'!$B:$ZZ,$AN20,1)="","",INDEX('_views'!$B:$ZZ,$AN20,1))) | C20: =IF($AN20="","",IF(INDEX('_views'!$B:$ZZ,$AN20,2)="","",INDEX('_views'!$B:$ZZ,$AN20,2))) | D20: =IF($AN20="","",IF(INDEX('_views'!$B:$ZZ,$AN20,3)="","",INDEX('_views'!$B:$ZZ,$AN20,3))) | E20: =IF(IF($AP20="","",IF(INDEX('_pockets'!$AB:$AB,$AP20)="","",INDEX('_pockets'!$AB:$AB,$AP20)))="","",IF($AP20="","",IF(INDEX('_pockets'!$AB:$AB,$AP20)="","",INDEX('_pockets'!$AB:$AB,$AP20)))*100) | F20: =IF(IF($AP20="","",IF(INDEX('_pockets'!$Z:$Z,$AP20)="","",INDEX('_pockets'!$Z:$Z,$AP20)))="","",-IF($AP20="","",IF(INDEX('_pockets'!$Z:$Z,$AP20)="","",INDEX('_pockets'!$Z:$Z,$AP20)))) | G20: =IF($AQ20="","",IF(INDEX('_pockets'!$AB:$AB,$AQ20)="","",INDEX('_pockets'!$AB:$AB,$AQ20))) | H20: =IF($AQ20="","",IF(INDEX('_pockets'!$Z:$Z,$AQ20)="","",INDEX('_pockets'!$Z:$Z,$AQ20))) | I20: =IF(IF($AR20="","",IF(INDEX('_pockets'!$AB:$AB,$AR20)="","",INDEX('_pockets'!$AB:$AB,$AR20)))="","",IF($AR20="","",IF(INDEX('_pockets'!$AB:$AB,$AR20)="","",INDEX('_pockets'!$AB:$AB,$AR20)))*100) | J20: =IF(IF($AR20="","",IF(INDEX('_pockets'!$Z:$Z,$AR20)="","",INDEX('_pockets'!$Z:$Z,$AR20)))="","",-IF($AR20="","",IF(INDEX('_pockets'!$Z:$Z,$AR20)="","",INDEX('_pockets'!$Z:$Z,$AR20)))) | K20: =IF(OR($AO20=1,$AO20=""),"",IF(AND($AT20="worse",$AU20="better"),"Priced for it",IF(AND($AT20="worse",$AU20="worse"),"Net drain",IF(AND($AT20="better",$AU20="better"),"Strong",IF(AND($AT20="better",$AU20="worse"),"Safe but idle",IF(AND(OR($AT20="in line",$AT20="worse, not significant",$AT20="better, not significant"),$AU20="worse"),"Earns less, not from losses",IF(AND($AT20="worse",OR($AU20="in line",$AU20="worse, not significant",$AU20="better, not significant")),"Losing more, profit holding",""))))))) | AN20: =IFERROR(MATCH("C|"&$B$16&"|1",'_views'!$A:$A,0),"") | AO20: =IF($AN20="","",IF(INDEX('_views'!$B:$ZZ,$AN20,4)="","",INDEX('_views'!$B:$ZZ,$AN20,4))) | AP20: =IF($AN20="","",IF(INDEX('_views'!$B:$ZZ,$AN20,5)="","",INDEX('_views'!$B:$ZZ,$AN20,5))) | AQ20: =IF($AN20="","",IF(INDEX('_views'!$B:$ZZ,$AN20,6)="","",INDEX('_views'!$B:$ZZ,$AN20,6))) | AR20: =IF($AN20="","",IF(INDEX('_views'!$B:$ZZ,$AN20,7)="","",INDEX('_views'!$B:$ZZ,$AN20,7))) | AS20: =IF($AP20="","",IF(INDEX('_pockets'!$Y:$Y,$AP20)="","",INDEX('_pockets'!$Y:$Y,$AP20))) | AT20: =IF($AQ20="","",IF(INDEX('_pockets'!$Y:$Y,$AQ20)="","",INDEX('_pockets'!$Y:$Y,$AQ20))) | AU20: =IF($AR20="","",IF(INDEX('_pockets'!$Y:$Y,$AR20)="","",INDEX('_pockets'!$Y:$Y,$AR20)))
B21: =IF($AN21="","",IF(INDEX('_views'!$B:$ZZ,$AN21,1)="","",INDEX('_views'!$B:$ZZ,$AN21,1))) | C21: =IF($AN21="","",IF(INDEX('_views'!$B:$ZZ,$AN21,2)="","",INDEX('_views'!$B:$ZZ,$AN21,2))) | D21: =IF($AN21="","",IF(INDEX('_views'!$B:$ZZ,$AN21,3)="","",INDEX('_views'!$B:$ZZ,$AN21,3))) | E21: =IF(IF($AP21="","",IF(INDEX('_pockets'!$AB:$AB,$AP21)="","",INDEX('_pockets'!$AB:$AB,$AP21)))="","",IF($AP21="","",IF(INDEX('_pockets'!$AB:$AB,$AP21)="","",INDEX('_pockets'!$AB:$AB,$AP21)))*100) | F21: =IF(IF($AP21="","",IF(INDEX('_pockets'!$Z:$Z,$AP21)="","",INDEX('_pockets'!$Z:$Z,$AP21)))="","",-IF($AP21="","",IF(INDEX('_pockets'!$Z:$Z,$AP21)="","",INDEX('_pockets'!$Z:$Z,$AP21)))) | G21: =IF($AQ21="","",IF(INDEX('_pockets'!$AB:$AB,$AQ21)="","",INDEX('_pockets'!$AB:$AB,$AQ21))) | H21: =IF($AQ21="","",IF(INDEX('_pockets'!$Z:$Z,$AQ21)="","",INDEX('_pockets'!$Z:$Z,$AQ21))) | I21: =IF(IF($AR21="","",IF(INDEX('_pockets'!$AB:$AB,$AR21)="","",INDEX('_pockets'!$AB:$AB,$AR21)))="","",IF($AR21="","",IF(INDEX('_pockets'!$AB:$AB,$AR21)="","",INDEX('_pockets'!$AB:$AB,$AR21)))*100) | J21: =IF(IF($AR21="","",IF(INDEX('_pockets'!$Z:$Z,$AR21)="","",INDEX('_pockets'!$Z:$Z,$AR21)))="","",-IF($AR21="","",IF(INDEX('_pockets'!$Z:$Z,$AR21)="","",INDEX('_pockets'!$Z:$Z,$AR21)))) | K21: =IF(OR($AO21=1,$AO21=""),"",IF(AND($AT21="worse",$AU21="better"),"Priced for it",IF(AND($AT21="worse",$AU21="worse"),"Net drain",IF(AND($AT21="better",$AU21="better"),"Strong",IF(AND($AT21="better",$AU21="worse"),"Safe but idle",IF(AND(OR($AT21="in line",$AT21="worse, not significant",$AT21="better, not significant"),$AU21="worse"),"Earns less, not from losses",IF(AND($AT21="worse",OR($AU21="in line",$AU21="worse, not significant",$AU21="better, not significant")),"Losing more, profit holding",""))))))) | AN21: =IFERROR(MATCH("C|"&$B$16&"|2",'_views'!$A:$A,0),"") | AO21: =IF($AN21="","",IF(INDEX('_views'!$B:$ZZ,$AN21,4)="","",INDEX('_views'!$B:$ZZ,$AN21,4))) | AP21: =IF($AN21="","",IF(INDEX('_views'!$B:$ZZ,$AN21,5)="","",INDEX('_views'!$B:$ZZ,$AN21,5))) | AQ21: =IF($AN21="","",IF(INDEX('_views'!$B:$ZZ,$AN21,6)="","",INDEX('_views'!$B:$ZZ,$AN21,6))) | AR21: =IF($AN21="","",IF(INDEX('_views'!$B:$ZZ,$AN21,7)="","",INDEX('_views'!$B:$ZZ,$AN21,7))) | AS21: =IF($AP21="","",IF(INDEX('_pockets'!$Y:$Y,$AP21)="","",INDEX('_pockets'!$Y:$Y,$AP21))) | AT21: =IF($AQ21="","",IF(INDEX('_pockets'!$Y:$Y,$AQ21)="","",INDEX('_pockets'!$Y:$Y,$AQ21))) | AU21: =IF($AR21="","",IF(INDEX('_pockets'!$Y:$Y,$AR21)="","",INDEX('_pockets'!$Y:$Y,$AR21)))
B22: =IF($AN22="","",IF(INDEX('_views'!$B:$ZZ,$AN22,1)="","",INDEX('_views'!$B:$ZZ,$AN22,1))) | C22: =IF($AN22="","",IF(INDEX('_views'!$B:$ZZ,$AN22,2)="","",INDEX('_views'!$B:$ZZ,$AN22,2))) | D22: =IF($AN22="","",IF(INDEX('_views'!$B:$ZZ,$AN22,3)="","",INDEX('_views'!$B:$ZZ,$AN22,3))) | E22: =IF(IF($AP22="","",IF(INDEX('_pockets'!$AB:$AB,$AP22)="","",INDEX('_pockets'!$AB:$AB,$AP22)))="","",IF($AP22="","",IF(INDEX('_pockets'!$AB:$AB,$AP22)="","",INDEX('_pockets'!$AB:$AB,$AP22)))*100) | F22: =IF(IF($AP22="","",IF(INDEX('_pockets'!$Z:$Z,$AP22)="","",INDEX('_pockets'!$Z:$Z,$AP22)))="","",-IF($AP22="","",IF(INDEX('_pockets'!$Z:$Z,$AP22)="","",INDEX('_pockets'!$Z:$Z,$AP22)))) | G22: =IF($AQ22="","",IF(INDEX('_pockets'!$AB:$AB,$AQ22)="","",INDEX('_pockets'!$AB:$AB,$AQ22))) | H22: =IF($AQ22="","",IF(INDEX('_pockets'!$Z:$Z,$AQ22)="","",INDEX('_pockets'!$Z:$Z,$AQ22))) | I22: =IF(IF($AR22="","",IF(INDEX('_pockets'!$AB:$AB,$AR22)="","",INDEX('_pockets'!$AB:$AB,$AR22)))="","",IF($AR22="","",IF(INDEX('_pockets'!$AB:$AB,$AR22)="","",INDEX('_pockets'!$AB:$AB,$AR22)))*100) | J22: =IF(IF($AR22="","",IF(INDEX('_pockets'!$Z:$Z,$AR22)="","",INDEX('_pockets'!$Z:$Z,$AR22)))="","",-IF($AR22="","",IF(INDEX('_pockets'!$Z:$Z,$AR22)="","",INDEX('_pockets'!$Z:$Z,$AR22)))) | K22: =IF(OR($AO22=1,$AO22=""),"",IF(AND($AT22="worse",$AU22="better"),"Priced for it",IF(AND($AT22="worse",$AU22="worse"),"Net drain",IF(AND($AT22="better",$AU22="better"),"Strong",IF(AND($AT22="better",$AU22="worse"),"Safe but idle",IF(AND(OR($AT22="in line",$AT22="worse, not significant",$AT22="better, not significant"),$AU22="worse"),"Earns less, not from losses",IF(AND($AT22="worse",OR($AU22="in line",$AU22="worse, not significant",$AU22="better, not significant")),"Losing more, profit holding",""))))))) | AN22: =IFERROR(MATCH("C|"&$B$16&"|3",'_views'!$A:$A,0),"") | AO22: =IF($AN22="","",IF(INDEX('_views'!$B:$ZZ,$AN22,4)="","",INDEX('_views'!$B:$ZZ,$AN22,4))) | AP22: =IF($AN22="","",IF(INDEX('_views'!$B:$ZZ,$AN22,5)="","",INDEX('_views'!$B:$ZZ,$AN22,5))) | AQ22: =IF($AN22="","",IF(INDEX('_views'!$B:$ZZ,$AN22,6)="","",INDEX('_views'!$B:$ZZ,$AN22,6))) | AR22: =IF($AN22="","",IF(INDEX('_views'!$B:$ZZ,$AN22,7)="","",INDEX('_views'!$B:$ZZ,$AN22,7))) | AS22: =IF($AP22="","",IF(INDEX('_pockets'!$Y:$Y,$AP22)="","",INDEX('_pockets'!$Y:$Y,$AP22))) | AT22: =IF($AQ22="","",IF(INDEX('_pockets'!$Y:$Y,$AQ22)="","",INDEX('_pockets'!$Y:$Y,$AQ22))) | AU22: =IF($AR22="","",IF(INDEX('_pockets'!$Y:$Y,$AR22)="","",INDEX('_pockets'!$Y:$Y,$AR22)))
B23: =IF($AN23="","",IF(INDEX('_views'!$B:$ZZ,$AN23,1)="","",INDEX('_views'!$B:$ZZ,$AN23,1))) | C23: =IF($AN23="","",IF(INDEX('_views'!$B:$ZZ,$AN23,2)="","",INDEX('_views'!$B:$ZZ,$AN23,2))) | D23: =IF($AN23="","",IF(INDEX('_views'!$B:$ZZ,$AN23,3)="","",INDEX('_views'!$B:$ZZ,$AN23,3))) | E23: =IF(IF($AP23="","",IF(INDEX('_pockets'!$AB:$AB,$AP23)="","",INDEX('_pockets'!$AB:$AB,$AP23)))="","",IF($AP23="","",IF(INDEX('_pockets'!$AB:$AB,$AP23)="","",INDEX('_pockets'!$AB:$AB,$AP23)))*100) | F23: =IF(IF($AP23="","",IF(INDEX('_pockets'!$Z:$Z,$AP23)="","",INDEX('_pockets'!$Z:$Z,$AP23)))="","",-IF($AP23="","",IF(INDEX('_pockets'!$Z:$Z,$AP23)="","",INDEX('_pockets'!$Z:$Z,$AP23)))) | G23: =IF($AQ23="","",IF(INDEX('_pockets'!$AB:$AB,$AQ23)="","",INDEX('_pockets'!$AB:$AB,$AQ23))) | H23: =IF($AQ23="","",IF(INDEX('_pockets'!$Z:$Z,$AQ23)="","",INDEX('_pockets'!$Z:$Z,$AQ23))) | I23: =IF(IF($AR23="","",IF(INDEX('_pockets'!$AB:$AB,$AR23)="","",INDEX('_pockets'!$AB:$AB,$AR23)))="","",IF($AR23="","",IF(INDEX('_pockets'!$AB:$AB,$AR23)="","",INDEX('_pockets'!$AB:$AB,$AR23)))*100) | J23: =IF(IF($AR23="","",IF(INDEX('_pockets'!$Z:$Z,$AR23)="","",INDEX('_pockets'!$Z:$Z,$AR23)))="","",-IF($AR23="","",IF(INDEX('_pockets'!$Z:$Z,$AR23)="","",INDEX('_pockets'!$Z:$Z,$AR23)))) | K23: =IF(OR($AO23=1,$AO23=""),"",IF(AND($AT23="worse",$AU23="better"),"Priced for it",IF(AND($AT23="worse",$AU23="worse"),"Net drain",IF(AND($AT23="better",$AU23="better"),"Strong",IF(AND($AT23="better",$AU23="worse"),"Safe but idle",IF(AND(OR($AT23="in line",$AT23="worse, not significant",$AT23="better, not significant"),$AU23="worse"),"Earns less, not from losses",IF(AND($AT23="worse",OR($AU23="in line",$AU23="worse, not significant",$AU23="better, not significant")),"Losing more, profit holding",""))))))) | AN23: =IFERROR(MATCH("C|"&$B$16&"|4",'_views'!$A:$A,0),"") | AO23: =IF($AN23="","",IF(INDEX('_views'!$B:$ZZ,$AN23,4)="","",INDEX('_views'!$B:$ZZ,$AN23,4))) | AP23: =IF($AN23="","",IF(INDEX('_views'!$B:$ZZ,$AN23,5)="","",INDEX('_views'!$B:$ZZ,$AN23,5))) | AQ23: =IF($AN23="","",IF(INDEX('_views'!$B:$ZZ,$AN23,6)="","",INDEX('_views'!$B:$ZZ,$AN23,6))) | AR23: =IF($AN23="","",IF(INDEX('_views'!$B:$ZZ,$AN23,7)="","",INDEX('_views'!$B:$ZZ,$AN23,7))) | AS23: =IF($AP23="","",IF(INDEX('_pockets'!$Y:$Y,$AP23)="","",INDEX('_pockets'!$Y:$Y,$AP23))) | AT23: =IF($AQ23="","",IF(INDEX('_pockets'!$Y:$Y,$AQ23)="","",INDEX('_pockets'!$Y:$Y,$AQ23))) | AU23: =IF($AR23="","",IF(INDEX('_pockets'!$Y:$Y,$AR23)="","",INDEX('_pockets'!$Y:$Y,$AR23)))
B24: =IF($AN24="","",IF(INDEX('_views'!$B:$ZZ,$AN24,1)="","",INDEX('_views'!$B:$ZZ,$AN24,1))) | C24: =IF($AN24="","",IF(INDEX('_views'!$B:$ZZ,$AN24,2)="","",INDEX('_views'!$B:$ZZ,$AN24,2))) | D24: =IF($AN24="","",IF(INDEX('_views'!$B:$ZZ,$AN24,3)="","",INDEX('_views'!$B:$ZZ,$AN24,3))) | E24: =IF(IF($AP24="","",IF(INDEX('_pockets'!$AB:$AB,$AP24)="","",INDEX('_pockets'!$AB:$AB,$AP24)))="","",IF($AP24="","",IF(INDEX('_pockets'!$AB:$AB,$AP24)="","",INDEX('_pockets'!$AB:$AB,$AP24)))*100) | F24: =IF(IF($AP24="","",IF(INDEX('_pockets'!$Z:$Z,$AP24)="","",INDEX('_pockets'!$Z:$Z,$AP24)))="","",-IF($AP24="","",IF(INDEX('_pockets'!$Z:$Z,$AP24)="","",INDEX('_pockets'!$Z:$Z,$AP24)))) | G24: =IF($AQ24="","",IF(INDEX('_pockets'!$AB:$AB,$AQ24)="","",INDEX('_pockets'!$AB:$AB,$AQ24))) | H24: =IF($AQ24="","",IF(INDEX('_pockets'!$Z:$Z,$AQ24)="","",INDEX('_pockets'!$Z:$Z,$AQ24))) | I24: =IF(IF($AR24="","",IF(INDEX('_pockets'!$AB:$AB,$AR24)="","",INDEX('_pockets'!$AB:$AB,$AR24)))="","",IF($AR24="","",IF(INDEX('_pockets'!$AB:$AB,$AR24)="","",INDEX('_pockets'!$AB:$AB,$AR24)))*100) | J24: =IF(IF($AR24="","",IF(INDEX('_pockets'!$Z:$Z,$AR24)="","",INDEX('_pockets'!$Z:$Z,$AR24)))="","",-IF($AR24="","",IF(INDEX('_pockets'!$Z:$Z,$AR24)="","",INDEX('_pockets'!$Z:$Z,$AR24)))) | K24: =IF(OR($AO24=1,$AO24=""),"",IF(AND($AT24="worse",$AU24="better"),"Priced for it",IF(AND($AT24="worse",$AU24="worse"),"Net drain",IF(AND($AT24="better",$AU24="better"),"Strong",IF(AND($AT24="better",$AU24="worse"),"Safe but idle",IF(AND(OR($AT24="in line",$AT24="worse, not significant",$AT24="better, not significant"),$AU24="worse"),"Earns less, not from losses",IF(AND($AT24="worse",OR($AU24="in line",$AU24="worse, not significant",$AU24="better, not significant")),"Losing more, profit holding",""))))))) | AN24: =IFERROR(MATCH("C|"&$B$16&"|5",'_views'!$A:$A,0),"") | AO24: =IF($AN24="","",IF(INDEX('_views'!$B:$ZZ,$AN24,4)="","",INDEX('_views'!$B:$ZZ,$AN24,4))) | AP24: =IF($AN24="","",IF(INDEX('_views'!$B:$ZZ,$AN24,5)="","",INDEX('_views'!$B:$ZZ,$AN24,5))) | AQ24: =IF($AN24="","",IF(INDEX('_views'!$B:$ZZ,$AN24,6)="","",INDEX('_views'!$B:$ZZ,$AN24,6))) | AR24: =IF($AN24="","",IF(INDEX('_views'!$B:$ZZ,$AN24,7)="","",INDEX('_views'!$B:$ZZ,$AN24,7))) | AS24: =IF($AP24="","",IF(INDEX('_pockets'!$Y:$Y,$AP24)="","",INDEX('_pockets'!$Y:$Y,$AP24))) | AT24: =IF($AQ24="","",IF(INDEX('_pockets'!$Y:$Y,$AQ24)="","",INDEX('_pockets'!$Y:$Y,$AQ24))) | AU24: =IF($AR24="","",IF(INDEX('_pockets'!$Y:$Y,$AR24)="","",INDEX('_pockets'!$Y:$Y,$AR24)))
B25: =IF($AN25="","",IF(INDEX('_views'!$B:$ZZ,$AN25,1)="","",INDEX('_views'!$B:$ZZ,$AN25,1))) | C25: =IF($AN25="","",IF(INDEX('_views'!$B:$ZZ,$AN25,2)="","",INDEX('_views'!$B:$ZZ,$AN25,2))) | D25: =IF($AN25="","",IF(INDEX('_views'!$B:$ZZ,$AN25,3)="","",INDEX('_views'!$B:$ZZ,$AN25,3))) | E25: =IF(IF($AP25="","",IF(INDEX('_pockets'!$AB:$AB,$AP25)="","",INDEX('_pockets'!$AB:$AB,$AP25)))="","",IF($AP25="","",IF(INDEX('_pockets'!$AB:$AB,$AP25)="","",INDEX('_pockets'!$AB:$AB,$AP25)))*100) | F25: =IF(IF($AP25="","",IF(INDEX('_pockets'!$Z:$Z,$AP25)="","",INDEX('_pockets'!$Z:$Z,$AP25)))="","",-IF($AP25="","",IF(INDEX('_pockets'!$Z:$Z,$AP25)="","",INDEX('_pockets'!$Z:$Z,$AP25)))) | G25: =IF($AQ25="","",IF(INDEX('_pockets'!$AB:$AB,$AQ25)="","",INDEX('_pockets'!$AB:$AB,$AQ25))) | H25: =IF($AQ25="","",IF(INDEX('_pockets'!$Z:$Z,$AQ25)="","",INDEX('_pockets'!$Z:$Z,$AQ25))) | I25: =IF(IF($AR25="","",IF(INDEX('_pockets'!$AB:$AB,$AR25)="","",INDEX('_pockets'!$AB:$AB,$AR25)))="","",IF($AR25="","",IF(INDEX('_pockets'!$AB:$AB,$AR25)="","",INDEX('_pockets'!$AB:$AB,$AR25)))*100) | J25: =IF(IF($AR25="","",IF(INDEX('_pockets'!$Z:$Z,$AR25)="","",INDEX('_pockets'!$Z:$Z,$AR25)))="","",-IF($AR25="","",IF(INDEX('_pockets'!$Z:$Z,$AR25)="","",INDEX('_pockets'!$Z:$Z,$AR25)))) | K25: =IF(OR($AO25=1,$AO25=""),"",IF(AND($AT25="worse",$AU25="better"),"Priced for it",IF(AND($AT25="worse",$AU25="worse"),"Net drain",IF(AND($AT25="better",$AU25="better"),"Strong",IF(AND($AT25="better",$AU25="worse"),"Safe but idle",IF(AND(OR($AT25="in line",$AT25="worse, not significant",$AT25="better, not significant"),$AU25="worse"),"Earns less, not from losses",IF(AND($AT25="worse",OR($AU25="in line",$AU25="worse, not significant",$AU25="better, not significant")),"Losing more, profit holding",""))))))) | AN25: =IFERROR(MATCH("C|"&$B$16&"|6",'_views'!$A:$A,0),"") | AO25: =IF($AN25="","",IF(INDEX('_views'!$B:$ZZ,$AN25,4)="","",INDEX('_views'!$B:$ZZ,$AN25,4))) | AP25: =IF($AN25="","",IF(INDEX('_views'!$B:$ZZ,$AN25,5)="","",INDEX('_views'!$B:$ZZ,$AN25,5))) | AQ25: =IF($AN25="","",IF(INDEX('_views'!$B:$ZZ,$AN25,6)="","",INDEX('_views'!$B:$ZZ,$AN25,6))) | AR25: =IF($AN25="","",IF(INDEX('_views'!$B:$ZZ,$AN25,7)="","",INDEX('_views'!$B:$ZZ,$AN25,7))) | AS25: =IF($AP25="","",IF(INDEX('_pockets'!$Y:$Y,$AP25)="","",INDEX('_pockets'!$Y:$Y,$AP25))) | AT25: =IF($AQ25="","",IF(INDEX('_pockets'!$Y:$Y,$AQ25)="","",INDEX('_pockets'!$Y:$Y,$AQ25))) | AU25: =IF($AR25="","",IF(INDEX('_pockets'!$Y:$Y,$AR25)="","",INDEX('_pockets'!$Y:$Y,$AR25)))
B26: =IF($AN26="","",IF(INDEX('_views'!$B:$ZZ,$AN26,1)="","",INDEX('_views'!$B:$ZZ,$AN26,1))) | C26: =IF($AN26="","",IF(INDEX('_views'!$B:$ZZ,$AN26,2)="","",INDEX('_views'!$B:$ZZ,$AN26,2))) | D26: =IF($AN26="","",IF(INDEX('_views'!$B:$ZZ,$AN26,3)="","",INDEX('_views'!$B:$ZZ,$AN26,3))) | E26: =IF(IF($AP26="","",IF(INDEX('_pockets'!$AB:$AB,$AP26)="","",INDEX('_pockets'!$AB:$AB,$AP26)))="","",IF($AP26="","",IF(INDEX('_pockets'!$AB:$AB,$AP26)="","",INDEX('_pockets'!$AB:$AB,$AP26)))*100) | F26: =IF(IF($AP26="","",IF(INDEX('_pockets'!$Z:$Z,$AP26)="","",INDEX('_pockets'!$Z:$Z,$AP26)))="","",-IF($AP26="","",IF(INDEX('_pockets'!$Z:$Z,$AP26)="","",INDEX('_pockets'!$Z:$Z,$AP26)))) | G26: =IF($AQ26="","",IF(INDEX('_pockets'!$AB:$AB,$AQ26)="","",INDEX('_pockets'!$AB:$AB,$AQ26))) | H26: =IF($AQ26="","",IF(INDEX('_pockets'!$Z:$Z,$AQ26)="","",INDEX('_pockets'!$Z:$Z,$AQ26))) | I26: =IF(IF($AR26="","",IF(INDEX('_pockets'!$AB:$AB,$AR26)="","",INDEX('_pockets'!$AB:$AB,$AR26)))="","",IF($AR26="","",IF(INDEX('_pockets'!$AB:$AB,$AR26)="","",INDEX('_pockets'!$AB:$AB,$AR26)))*100) | J26: =IF(IF($AR26="","",IF(INDEX('_pockets'!$Z:$Z,$AR26)="","",INDEX('_pockets'!$Z:$Z,$AR26)))="","",-IF($AR26="","",IF(INDEX('_pockets'!$Z:$Z,$AR26)="","",INDEX('_pockets'!$Z:$Z,$AR26)))) | K26: =IF(OR($AO26=1,$AO26=""),"",IF(AND($AT26="worse",$AU26="better"),"Priced for it",IF(AND($AT26="worse",$AU26="worse"),"Net drain",IF(AND($AT26="better",$AU26="better"),"Strong",IF(AND($AT26="better",$AU26="worse"),"Safe but idle",IF(AND(OR($AT26="in line",$AT26="worse, not significant",$AT26="better, not significant"),$AU26="worse"),"Earns less, not from losses",IF(AND($AT26="worse",OR($AU26="in line",$AU26="worse, not significant",$AU26="better, not significant")),"Losing more, profit holding",""))))))) | AN26: =IFERROR(MATCH("C|"&$B$16&"|7",'_views'!$A:$A,0),"") | AO26: =IF($AN26="","",IF(INDEX('_views'!$B:$ZZ,$AN26,4)="","",INDEX('_views'!$B:$ZZ,$AN26,4))) | AP26: =IF($AN26="","",IF(INDEX('_views'!$B:$ZZ,$AN26,5)="","",INDEX('_views'!$B:$ZZ,$AN26,5))) | AQ26: =IF($AN26="","",IF(INDEX('_views'!$B:$ZZ,$AN26,6)="","",INDEX('_views'!$B:$ZZ,$AN26,6))) | AR26: =IF($AN26="","",IF(INDEX('_views'!$B:$ZZ,$AN26,7)="","",INDEX('_views'!$B:$ZZ,$AN26,7))) | AS26: =IF($AP26="","",IF(INDEX('_pockets'!$Y:$Y,$AP26)="","",INDEX('_pockets'!$Y:$Y,$AP26))) | AT26: =IF($AQ26="","",IF(INDEX('_pockets'!$Y:$Y,$AQ26)="","",INDEX('_pockets'!$Y:$Y,$AQ26))) | AU26: =IF($AR26="","",IF(INDEX('_pockets'!$Y:$Y,$AR26)="","",INDEX('_pockets'!$Y:$Y,$AR26)))
B27: =IF($AN27="","",IF(INDEX('_views'!$B:$ZZ,$AN27,1)="","",INDEX('_views'!$B:$ZZ,$AN27,1))) | C27: =IF($AN27="","",IF(INDEX('_views'!$B:$ZZ,$AN27,2)="","",INDEX('_views'!$B:$ZZ,$AN27,2))) | D27: =IF($AN27="","",IF(INDEX('_views'!$B:$ZZ,$AN27,3)="","",INDEX('_views'!$B:$ZZ,$AN27,3))) | E27: =IF(IF($AP27="","",IF(INDEX('_pockets'!$AB:$AB,$AP27)="","",INDEX('_pockets'!$AB:$AB,$AP27)))="","",IF($AP27="","",IF(INDEX('_pockets'!$AB:$AB,$AP27)="","",INDEX('_pockets'!$AB:$AB,$AP27)))*100) | F27: =IF(IF($AP27="","",IF(INDEX('_pockets'!$Z:$Z,$AP27)="","",INDEX('_pockets'!$Z:$Z,$AP27)))="","",-IF($AP27="","",IF(INDEX('_pockets'!$Z:$Z,$AP27)="","",INDEX('_pockets'!$Z:$Z,$AP27)))) | G27: =IF($AQ27="","",IF(INDEX('_pockets'!$AB:$AB,$AQ27)="","",INDEX('_pockets'!$AB:$AB,$AQ27))) | H27: =IF($AQ27="","",IF(INDEX('_pockets'!$Z:$Z,$AQ27)="","",INDEX('_pockets'!$Z:$Z,$AQ27))) | I27: =IF(IF($AR27="","",IF(INDEX('_pockets'!$AB:$AB,$AR27)="","",INDEX('_pockets'!$AB:$AB,$AR27)))="","",IF($AR27="","",IF(INDEX('_pockets'!$AB:$AB,$AR27)="","",INDEX('_pockets'!$AB:$AB,$AR27)))*100) | J27: =IF(IF($AR27="","",IF(INDEX('_pockets'!$Z:$Z,$AR27)="","",INDEX('_pockets'!$Z:$Z,$AR27)))="","",-IF($AR27="","",IF(INDEX('_pockets'!$Z:$Z,$AR27)="","",INDEX('_pockets'!$Z:$Z,$AR27)))) | K27: =IF(OR($AO27=1,$AO27=""),"",IF(AND($AT27="worse",$AU27="better"),"Priced for it",IF(AND($AT27="worse",$AU27="worse"),"Net drain",IF(AND($AT27="better",$AU27="better"),"Strong",IF(AND($AT27="better",$AU27="worse"),"Safe but idle",IF(AND(OR($AT27="in line",$AT27="worse, not significant",$AT27="better, not significant"),$AU27="worse"),"Earns less, not from losses",IF(AND($AT27="worse",OR($AU27="in line",$AU27="worse, not significant",$AU27="better, not significant")),"Losing more, profit holding",""))))))) | AN27: =IFERROR(MATCH("C|"&$B$16&"|8",'_views'!$A:$A,0),"") | AO27: =IF($AN27="","",IF(INDEX('_views'!$B:$ZZ,$AN27,4)="","",INDEX('_views'!$B:$ZZ,$AN27,4))) | AP27: =IF($AN27="","",IF(INDEX('_views'!$B:$ZZ,$AN27,5)="","",INDEX('_views'!$B:$ZZ,$AN27,5))) | AQ27: =IF($AN27="","",IF(INDEX('_views'!$B:$ZZ,$AN27,6)="","",INDEX('_views'!$B:$ZZ,$AN27,6))) | AR27: =IF($AN27="","",IF(INDEX('_views'!$B:$ZZ,$AN27,7)="","",INDEX('_views'!$B:$ZZ,$AN27,7))) | AS27: =IF($AP27="","",IF(INDEX('_pockets'!$Y:$Y,$AP27)="","",INDEX('_pockets'!$Y:$Y,$AP27))) | AT27: =IF($AQ27="","",IF(INDEX('_pockets'!$Y:$Y,$AQ27)="","",INDEX('_pockets'!$Y:$Y,$AQ27))) | AU27: =IF($AR27="","",IF(INDEX('_pockets'!$Y:$Y,$AR27)="","",INDEX('_pockets'!$Y:$Y,$AR27)))
B28: =IF($AN28="","",IF(INDEX('_views'!$B:$ZZ,$AN28,1)="","",INDEX('_views'!$B:$ZZ,$AN28,1))) | C28: =IF($AN28="","",IF(INDEX('_views'!$B:$ZZ,$AN28,2)="","",INDEX('_views'!$B:$ZZ,$AN28,2))) | D28: =IF($AN28="","",IF(INDEX('_views'!$B:$ZZ,$AN28,3)="","",INDEX('_views'!$B:$ZZ,$AN28,3))) | E28: =IF(IF($AP28="","",IF(INDEX('_pockets'!$AB:$AB,$AP28)="","",INDEX('_pockets'!$AB:$AB,$AP28)))="","",IF($AP28="","",IF(INDEX('_pockets'!$AB:$AB,$AP28)="","",INDEX('_pockets'!$AB:$AB,$AP28)))*100) | F28: =IF(IF($AP28="","",IF(INDEX('_pockets'!$Z:$Z,$AP28)="","",INDEX('_pockets'!$Z:$Z,$AP28)))="","",-IF($AP28="","",IF(INDEX('_pockets'!$Z:$Z,$AP28)="","",INDEX('_pockets'!$Z:$Z,$AP28)))) | G28: =IF($AQ28="","",IF(INDEX('_pockets'!$AB:$AB,$AQ28)="","",INDEX('_pockets'!$AB:$AB,$AQ28))) | H28: =IF($AQ28="","",IF(INDEX('_pockets'!$Z:$Z,$AQ28)="","",INDEX('_pockets'!$Z:$Z,$AQ28))) | I28: =IF(IF($AR28="","",IF(INDEX('_pockets'!$AB:$AB,$AR28)="","",INDEX('_pockets'!$AB:$AB,$AR28)))="","",IF($AR28="","",IF(INDEX('_pockets'!$AB:$AB,$AR28)="","",INDEX('_pockets'!$AB:$AB,$AR28)))*100) | J28: =IF(IF($AR28="","",IF(INDEX('_pockets'!$Z:$Z,$AR28)="","",INDEX('_pockets'!$Z:$Z,$AR28)))="","",-IF($AR28="","",IF(INDEX('_pockets'!$Z:$Z,$AR28)="","",INDEX('_pockets'!$Z:$Z,$AR28)))) | K28: =IF(OR($AO28=1,$AO28=""),"",IF(AND($AT28="worse",$AU28="better"),"Priced for it",IF(AND($AT28="worse",$AU28="worse"),"Net drain",IF(AND($AT28="better",$AU28="better"),"Strong",IF(AND($AT28="better",$AU28="worse"),"Safe but idle",IF(AND(OR($AT28="in line",$AT28="worse, not significant",$AT28="better, not significant"),$AU28="worse"),"Earns less, not from losses",IF(AND($AT28="worse",OR($AU28="in line",$AU28="worse, not significant",$AU28="better, not significant")),"Losing more, profit holding",""))))))) | AN28: =IFERROR(MATCH("C|"&$B$16&"|9",'_views'!$A:$A,0),"") | AO28: =IF($AN28="","",IF(INDEX('_views'!$B:$ZZ,$AN28,4)="","",INDEX('_views'!$B:$ZZ,$AN28,4))) | AP28: =IF($AN28="","",IF(INDEX('_views'!$B:$ZZ,$AN28,5)="","",INDEX('_views'!$B:$ZZ,$AN28,5))) | AQ28: =IF($AN28="","",IF(INDEX('_views'!$B:$ZZ,$AN28,6)="","",INDEX('_views'!$B:$ZZ,$AN28,6))) | AR28: =IF($AN28="","",IF(INDEX('_views'!$B:$ZZ,$AN28,7)="","",INDEX('_views'!$B:$ZZ,$AN28,7))) | AS28: =IF($AP28="","",IF(INDEX('_pockets'!$Y:$Y,$AP28)="","",INDEX('_pockets'!$Y:$Y,$AP28))) | AT28: =IF($AQ28="","",IF(INDEX('_pockets'!$Y:$Y,$AQ28)="","",INDEX('_pockets'!$Y:$Y,$AQ28))) | AU28: =IF($AR28="","",IF(INDEX('_pockets'!$Y:$Y,$AR28)="","",INDEX('_pockets'!$Y:$Y,$AR28)))
B29: =IF($AN29="","",IF(INDEX('_views'!$B:$ZZ,$AN29,1)="","",INDEX('_views'!$B:$ZZ,$AN29,1))) | C29: =IF($AN29="","",IF(INDEX('_views'!$B:$ZZ,$AN29,2)="","",INDEX('_views'!$B:$ZZ,$AN29,2))) | D29: =IF($AN29="","",IF(INDEX('_views'!$B:$ZZ,$AN29,3)="","",INDEX('_views'!$B:$ZZ,$AN29,3))) | E29: =IF(IF($AP29="","",IF(INDEX('_pockets'!$AB:$AB,$AP29)="","",INDEX('_pockets'!$AB:$AB,$AP29)))="","",IF($AP29="","",IF(INDEX('_pockets'!$AB:$AB,$AP29)="","",INDEX('_pockets'!$AB:$AB,$AP29)))*100) | F29: =IF(IF($AP29="","",IF(INDEX('_pockets'!$Z:$Z,$AP29)="","",INDEX('_pockets'!$Z:$Z,$AP29)))="","",-IF($AP29="","",IF(INDEX('_pockets'!$Z:$Z,$AP29)="","",INDEX('_pockets'!$Z:$Z,$AP29)))) | G29: =IF($AQ29="","",IF(INDEX('_pockets'!$AB:$AB,$AQ29)="","",INDEX('_pockets'!$AB:$AB,$AQ29))) | H29: =IF($AQ29="","",IF(INDEX('_pockets'!$Z:$Z,$AQ29)="","",INDEX('_pockets'!$Z:$Z,$AQ29))) | I29: =IF(IF($AR29="","",IF(INDEX('_pockets'!$AB:$AB,$AR29)="","",INDEX('_pockets'!$AB:$AB,$AR29)))="","",IF($AR29="","",IF(INDEX('_pockets'!$AB:$AB,$AR29)="","",INDEX('_pockets'!$AB:$AB,$AR29)))*100) | J29: =IF(IF($AR29="","",IF(INDEX('_pockets'!$Z:$Z,$AR29)="","",INDEX('_pockets'!$Z:$Z,$AR29)))="","",-IF($AR29="","",IF(INDEX('_pockets'!$Z:$Z,$AR29)="","",INDEX('_pockets'!$Z:$Z,$AR29)))) | K29: =IF(OR($AO29=1,$AO29=""),"",IF(AND($AT29="worse",$AU29="better"),"Priced for it",IF(AND($AT29="worse",$AU29="worse"),"Net drain",IF(AND($AT29="better",$AU29="better"),"Strong",IF(AND($AT29="better",$AU29="worse"),"Safe but idle",IF(AND(OR($AT29="in line",$AT29="worse, not significant",$AT29="better, not significant"),$AU29="worse"),"Earns less, not from losses",IF(AND($AT29="worse",OR($AU29="in line",$AU29="worse, not significant",$AU29="better, not significant")),"Losing more, profit holding",""))))))) | AN29: =IFERROR(MATCH("C|"&$B$16&"|10",'_views'!$A:$A,0),"") | AO29: =IF($AN29="","",IF(INDEX('_views'!$B:$ZZ,$AN29,4)="","",INDEX('_views'!$B:$ZZ,$AN29,4))) | AP29: =IF($AN29="","",IF(INDEX('_views'!$B:$ZZ,$AN29,5)="","",INDEX('_views'!$B:$ZZ,$AN29,5))) | AQ29: =IF($AN29="","",IF(INDEX('_views'!$B:$ZZ,$AN29,6)="","",INDEX('_views'!$B:$ZZ,$AN29,6))) | AR29: =IF($AN29="","",IF(INDEX('_views'!$B:$ZZ,$AN29,7)="","",INDEX('_views'!$B:$ZZ,$AN29,7))) | AS29: =IF($AP29="","",IF(INDEX('_pockets'!$Y:$Y,$AP29)="","",INDEX('_pockets'!$Y:$Y,$AP29))) | AT29: =IF($AQ29="","",IF(INDEX('_pockets'!$Y:$Y,$AQ29)="","",INDEX('_pockets'!$Y:$Y,$AQ29))) | AU29: =IF($AR29="","",IF(INDEX('_pockets'!$Y:$Y,$AR29)="","",INDEX('_pockets'!$Y:$Y,$AR29)))
B30: =IF($AN30="","",IF(INDEX('_views'!$B:$ZZ,$AN30,1)="","",INDEX('_views'!$B:$ZZ,$AN30,1))) | C30: =IF($AN30="","",IF(INDEX('_views'!$B:$ZZ,$AN30,2)="","",INDEX('_views'!$B:$ZZ,$AN30,2))) | D30: =IF($AN30="","",IF(INDEX('_views'!$B:$ZZ,$AN30,3)="","",INDEX('_views'!$B:$ZZ,$AN30,3))) | E30: =IF(IF($AP30="","",IF(INDEX('_pockets'!$AB:$AB,$AP30)="","",INDEX('_pockets'!$AB:$AB,$AP30)))="","",IF($AP30="","",IF(INDEX('_pockets'!$AB:$AB,$AP30)="","",INDEX('_pockets'!$AB:$AB,$AP30)))*100) | F30: =IF(IF($AP30="","",IF(INDEX('_pockets'!$Z:$Z,$AP30)="","",INDEX('_pockets'!$Z:$Z,$AP30)))="","",-IF($AP30="","",IF(INDEX('_pockets'!$Z:$Z,$AP30)="","",INDEX('_pockets'!$Z:$Z,$AP30)))) | G30: =IF($AQ30="","",IF(INDEX('_pockets'!$AB:$AB,$AQ30)="","",INDEX('_pockets'!$AB:$AB,$AQ30))) | H30: =IF($AQ30="","",IF(INDEX('_pockets'!$Z:$Z,$AQ30)="","",INDEX('_pockets'!$Z:$Z,$AQ30))) | I30: =IF(IF($AR30="","",IF(INDEX('_pockets'!$AB:$AB,$AR30)="","",INDEX('_pockets'!$AB:$AB,$AR30)))="","",IF($AR30="","",IF(INDEX('_pockets'!$AB:$AB,$AR30)="","",INDEX('_pockets'!$AB:$AB,$AR30)))*100) | J30: =IF(IF($AR30="","",IF(INDEX('_pockets'!$Z:$Z,$AR30)="","",INDEX('_pockets'!$Z:$Z,$AR30)))="","",-IF($AR30="","",IF(INDEX('_pockets'!$Z:$Z,$AR30)="","",INDEX('_pockets'!$Z:$Z,$AR30)))) | K30: =IF(OR($AO30=1,$AO30=""),"",IF(AND($AT30="worse",$AU30="better"),"Priced for it",IF(AND($AT30="worse",$AU30="worse"),"Net drain",IF(AND($AT30="better",$AU30="better"),"Strong",IF(AND($AT30="better",$AU30="worse"),"Safe but idle",IF(AND(OR($AT30="in line",$AT30="worse, not significant",$AT30="better, not significant"),$AU30="worse"),"Earns less, not from losses",IF(AND($AT30="worse",OR($AU30="in line",$AU30="worse, not significant",$AU30="better, not significant")),"Losing more, profit holding",""))))))) | AN30: =IFERROR(MATCH("C|"&$B$16&"|11",'_views'!$A:$A,0),"") | AO30: =IF($AN30="","",IF(INDEX('_views'!$B:$ZZ,$AN30,4)="","",INDEX('_views'!$B:$ZZ,$AN30,4))) | AP30: =IF($AN30="","",IF(INDEX('_views'!$B:$ZZ,$AN30,5)="","",INDEX('_views'!$B:$ZZ,$AN30,5))) | AQ30: =IF($AN30="","",IF(INDEX('_views'!$B:$ZZ,$AN30,6)="","",INDEX('_views'!$B:$ZZ,$AN30,6))) | AR30: =IF($AN30="","",IF(INDEX('_views'!$B:$ZZ,$AN30,7)="","",INDEX('_views'!$B:$ZZ,$AN30,7))) | AS30: =IF($AP30="","",IF(INDEX('_pockets'!$Y:$Y,$AP30)="","",INDEX('_pockets'!$Y:$Y,$AP30))) | AT30: =IF($AQ30="","",IF(INDEX('_pockets'!$Y:$Y,$AQ30)="","",INDEX('_pockets'!$Y:$Y,$AQ30))) | AU30: =IF($AR30="","",IF(INDEX('_pockets'!$Y:$Y,$AR30)="","",INDEX('_pockets'!$Y:$Y,$AR30)))
B31: =IF($AN31="","",IF(INDEX('_views'!$B:$ZZ,$AN31,1)="","",INDEX('_views'!$B:$ZZ,$AN31,1))) | C31: =IF($AN31="","",IF(INDEX('_views'!$B:$ZZ,$AN31,2)="","",INDEX('_views'!$B:$ZZ,$AN31,2))) | D31: =IF($AN31="","",IF(INDEX('_views'!$B:$ZZ,$AN31,3)="","",INDEX('_views'!$B:$ZZ,$AN31,3))) | E31: =IF(IF($AP31="","",IF(INDEX('_pockets'!$AB:$AB,$AP31)="","",INDEX('_pockets'!$AB:$AB,$AP31)))="","",IF($AP31="","",IF(INDEX('_pockets'!$AB:$AB,$AP31)="","",INDEX('_pockets'!$AB:$AB,$AP31)))*100) | F31: =IF(IF($AP31="","",IF(INDEX('_pockets'!$Z:$Z,$AP31)="","",INDEX('_pockets'!$Z:$Z,$AP31)))="","",-IF($AP31="","",IF(INDEX('_pockets'!$Z:$Z,$AP31)="","",INDEX('_pockets'!$Z:$Z,$AP31)))) | G31: =IF($AQ31="","",IF(INDEX('_pockets'!$AB:$AB,$AQ31)="","",INDEX('_pockets'!$AB:$AB,$AQ31))) | H31: =IF($AQ31="","",IF(INDEX('_pockets'!$Z:$Z,$AQ31)="","",INDEX('_pockets'!$Z:$Z,$AQ31))) | I31: =IF(IF($AR31="","",IF(INDEX('_pockets'!$AB:$AB,$AR31)="","",INDEX('_pockets'!$AB:$AB,$AR31)))="","",IF($AR31="","",IF(INDEX('_pockets'!$AB:$AB,$AR31)="","",INDEX('_pockets'!$AB:$AB,$AR31)))*100) | J31: =IF(IF($AR31="","",IF(INDEX('_pockets'!$Z:$Z,$AR31)="","",INDEX('_pockets'!$Z:$Z,$AR31)))="","",-IF($AR31="","",IF(INDEX('_pockets'!$Z:$Z,$AR31)="","",INDEX('_pockets'!$Z:$Z,$AR31)))) | K31: =IF(OR($AO31=1,$AO31=""),"",IF(AND($AT31="worse",$AU31="better"),"Priced for it",IF(AND($AT31="worse",$AU31="worse"),"Net drain",IF(AND($AT31="better",$AU31="better"),"Strong",IF(AND($AT31="better",$AU31="worse"),"Safe but idle",IF(AND(OR($AT31="in line",$AT31="worse, not significant",$AT31="better, not significant"),$AU31="worse"),"Earns less, not from losses",IF(AND($AT31="worse",OR($AU31="in line",$AU31="worse, not significant",$AU31="better, not significant")),"Losing more, profit holding",""))))))) | AN31: =IFERROR(MATCH("C|"&$B$16&"|12",'_views'!$A:$A,0),"") | AO31: =IF($AN31="","",IF(INDEX('_views'!$B:$ZZ,$AN31,4)="","",INDEX('_views'!$B:$ZZ,$AN31,4))) | AP31: =IF($AN31="","",IF(INDEX('_views'!$B:$ZZ,$AN31,5)="","",INDEX('_views'!$B:$ZZ,$AN31,5))) | AQ31: =IF($AN31="","",IF(INDEX('_views'!$B:$ZZ,$AN31,6)="","",INDEX('_views'!$B:$ZZ,$AN31,6))) | AR31: =IF($AN31="","",IF(INDEX('_views'!$B:$ZZ,$AN31,7)="","",INDEX('_views'!$B:$ZZ,$AN31,7))) | AS31: =IF($AP31="","",IF(INDEX('_pockets'!$Y:$Y,$AP31)="","",INDEX('_pockets'!$Y:$Y,$AP31))) | AT31: =IF($AQ31="","",IF(INDEX('_pockets'!$Y:$Y,$AQ31)="","",INDEX('_pockets'!$Y:$Y,$AQ31))) | AU31: =IF($AR31="","",IF(INDEX('_pockets'!$Y:$Y,$AR31)="","",INDEX('_pockets'!$Y:$Y,$AR31)))
B32: =IF($AN32="","",IF(INDEX('_views'!$B:$ZZ,$AN32,1)="","",INDEX('_views'!$B:$ZZ,$AN32,1))) | C32: =IF($AN32="","",IF(INDEX('_views'!$B:$ZZ,$AN32,2)="","",INDEX('_views'!$B:$ZZ,$AN32,2))) | D32: =IF($AN32="","",IF(INDEX('_views'!$B:$ZZ,$AN32,3)="","",INDEX('_views'!$B:$ZZ,$AN32,3))) | E32: =IF(IF($AP32="","",IF(INDEX('_pockets'!$AB:$AB,$AP32)="","",INDEX('_pockets'!$AB:$AB,$AP32)))="","",IF($AP32="","",IF(INDEX('_pockets'!$AB:$AB,$AP32)="","",INDEX('_pockets'!$AB:$AB,$AP32)))*100) | F32: =IF(IF($AP32="","",IF(INDEX('_pockets'!$Z:$Z,$AP32)="","",INDEX('_pockets'!$Z:$Z,$AP32)))="","",-IF($AP32="","",IF(INDEX('_pockets'!$Z:$Z,$AP32)="","",INDEX('_pockets'!$Z:$Z,$AP32)))) | G32: =IF($AQ32="","",IF(INDEX('_pockets'!$AB:$AB,$AQ32)="","",INDEX('_pockets'!$AB:$AB,$AQ32))) | H32: =IF($AQ32="","",IF(INDEX('_pockets'!$Z:$Z,$AQ32)="","",INDEX('_pockets'!$Z:$Z,$AQ32))) | I32: =IF(IF($AR32="","",IF(INDEX('_pockets'!$AB:$AB,$AR32)="","",INDEX('_pockets'!$AB:$AB,$AR32)))="","",IF($AR32="","",IF(INDEX('_pockets'!$AB:$AB,$AR32)="","",INDEX('_pockets'!$AB:$AB,$AR32)))*100) | J32: =IF(IF($AR32="","",IF(INDEX('_pockets'!$Z:$Z,$AR32)="","",INDEX('_pockets'!$Z:$Z,$AR32)))="","",-IF($AR32="","",IF(INDEX('_pockets'!$Z:$Z,$AR32)="","",INDEX('_pockets'!$Z:$Z,$AR32)))) | K32: =IF(OR($AO32=1,$AO32=""),"",IF(AND($AT32="worse",$AU32="better"),"Priced for it",IF(AND($AT32="worse",$AU32="worse"),"Net drain",IF(AND($AT32="better",$AU32="better"),"Strong",IF(AND($AT32="better",$AU32="worse"),"Safe but idle",IF(AND(OR($AT32="in line",$AT32="worse, not significant",$AT32="better, not significant"),$AU32="worse"),"Earns less, not from losses",IF(AND($AT32="worse",OR($AU32="in line",$AU32="worse, not significant",$AU32="better, not significant")),"Losing more, profit holding",""))))))) | AN32: =IFERROR(MATCH("C|"&$B$16&"|13",'_views'!$A:$A,0),"") | AO32: =IF($AN32="","",IF(INDEX('_views'!$B:$ZZ,$AN32,4)="","",INDEX('_views'!$B:$ZZ,$AN32,4))) | AP32: =IF($AN32="","",IF(INDEX('_views'!$B:$ZZ,$AN32,5)="","",INDEX('_views'!$B:$ZZ,$AN32,5))) | AQ32: =IF($AN32="","",IF(INDEX('_views'!$B:$ZZ,$AN32,6)="","",INDEX('_views'!$B:$ZZ,$AN32,6))) | AR32: =IF($AN32="","",IF(INDEX('_views'!$B:$ZZ,$AN32,7)="","",INDEX('_views'!$B:$ZZ,$AN32,7))) | AS32: =IF($AP32="","",IF(INDEX('_pockets'!$Y:$Y,$AP32)="","",INDEX('_pockets'!$Y:$Y,$AP32))) | AT32: =IF($AQ32="","",IF(INDEX('_pockets'!$Y:$Y,$AQ32)="","",INDEX('_pockets'!$Y:$Y,$AQ32))) | AU32: =IF($AR32="","",IF(INDEX('_pockets'!$Y:$Y,$AR32)="","",INDEX('_pockets'!$Y:$Y,$AR32)))
